Workbook
Name _DLX1.USE: #REF!
Name _DLX2.USE: 'Monthly Haver'!$1:$4
Name _DLX3.USE: 'Quarterly Haver'!$A$1:$W$3

Sheet GDS_Monthly
A1: EcDatabase | B1: ID:GDS_LIVE | C1: ID:GDS_LIVE | D1: ID:GDS_LIVE | E1: ID:GDS_LIVE | F1: ID:GDS_LIVE | G1: ID:GDS_LIVE | H1: ID:GDS_LIVE | I1: ID:GDS_LIVE | J1: ID:GDS_LIVE | K1: ID:GDS_LIVE | L1: ID:GDS_LIVE | M1: ID:GDS_LIVE | N1: ID:GDS_LIVE | O1: ID:GDS_LIVE | P1: ID:GDS_LIVE | Q1: ID:GDS_LIVE | R1: ID:GDS_LIVE | S1: ID:GDS_LIVE | T1: ID:GDS_LIVE | U1: ID:GDS_LIVE | V1: ID:GDS_LIVE | W1: ID:GDS_LIVE | X1: ID:GDS_LIVE | Y1: ID:GDS_LIVE | Z1: ID:GDS_LIVE | AA1: ID:GDS_LIVE | AB1: ID:GDS_LIVE | AC1: ID:GDS_LIVE | AD1: ID:GDS_LIVE | AE1: ID:GDS_LIVE | AF1: ID:GDS_LIVE | AG1: ID:GDS_LIVE | AH1: ID:GDS_LIVE | AI1: ID:GDS_LIVE
A2: Series_code | B2: 001ACC_PPPWGT.M | C2: 001ACC.M | D2: 001AIP.M | E2: 001AIP_GDPWGT.M | F2: 001FIGB.M | G2: 001FIPR.M | H2: 001FISI.M | I2: 001FMB.M | J2: 001FMN.M | K2: 001FMSCID.M | L2: 001FMSCIL.M | M2: 001LE.M | N2: 001LUR.M | O2: 001NRS.M | P2: 001PALLFNFW.M | Q2: 001PBEVEW.M | R2: 001PCOALW.M | S2: 001PCPI.M | T2: 001PCPI_GDPWGT.M | U2: 001PCPIX.M | V2: 001.M | W2: 001PFOODW.M | X2: 001PMETAW.M | Y2: 001PMI.M | Z2: 001PMI_PPPWGT.M | AA2: 001PNFUELW.M | AB2: 001PNGASW.M | AC2: 001PNRGW.M | AD2: 001POILAPSP.M | AE2: 001POILAPSPW.M | AF2: 001PRAWMW.M | AG2: 001TG.M | AH2: 001TMG.M | AI2: 001TXG.M
A3: Country | B3: World | C3: World | D3: World | E3: World | F3: World | G3: World | H3: World | I3: World | J3: World | K3: World | L3: World | M3: World | N3: World | O3: World | P3: World | Q3: World | R3: World | S3: World | T3: World | U3: World | V3: World | W3: World | X3: World | Y3: World | Z3: World | AA3: World | AB3: World | AC3: World | AD3: World | AE3: World | AF3: World | AG3: World | AH3: World | AI3: World
A4: Country.Name | B4: World | C4: World | D4: World | E4: World | F4: World | G4: World | H4: World | I4: World | J4: World | K4: World | L4: World | M4: World | N4: World | O4: World | P4: World | Q4: World | R4: World | S4: World | T4: World | U4: World | V4: World | W4: World | X4: World | Y4: World | Z4: World | AA4: World | AB4: World | AC4: World | AD4: World | AE4: World | AF4: World | AG4: World | AH4: World | AI4: World
A5: Indicator | B5: ACC_PPPWGT | C5: ACC | D5: AIP | E5: AIP_GDPWGT | F5: FIGB | G5: FIPR | H5: FISI | I5: FMB | J5: FMN | K5: FMSCID | L5: FMSCIL | M5: LE | N5: LUR | O5: NRS | P5: PALLFNFW | Q5: PBEVEW | R5: PCOALW | S5: PCPI | T5: PCPI_GDPWGT | U5: PCPIX | V5: PCPIX_GDPWGT | W5: PFOODW | X5: PMETAW | Y5: PMI | Z5: PMI_PPPWGT | AA5: PNFUELW | AB5: PNGASW | AC5: PNRGW | AD5: POILAPSP | AE5: POILAPSPW | AF5: PRAWMW | AG5: TG | AH5: TMG | AI5: TXG
A6: Indicator.Code | B6: ACC_PPPWGT | C6: ACC | D6: AIP | E6: AIP_GDPWGT | F6: FIGB | G6: FIPR | H6: FISI | I6: FMB | J6: FMN | K6: FMSCID | L6: FMSCIL | M6: LE | N6: LUR | O6: NRS | P6: PALLFNFW | Q6: PBEVEW | R6: PCOALW | S6: PCPI | T6: PCPI_GDPWGT | U6: PCPIX | V6: PCPIX_GDPWGT | W6: PFOODW | X6: PMETAW | Y6: PMI | Z6: PMI_PPPWGT | AA6: PNFUELW | AB6: PNGASW | AC6: PNRGW | AD6: POILAPSP | AE6: POILAPSPW | AF6: PRAWMW | AG6: TG | AH6: TMG | AI6: TXG
A7: Indicator.Descriptor | B7: Consumer confidence, PPP weighted | C7: Consumer confidence | D7: Industrial production | E7: Industrial production, MER weighted | F7: Long-term interest rate | G7: Policy-related interest rate | H7: Benchmark stock market index | I7: Broad money | J7: Narrow money | K7: Morgan Stanley MSCI stock price index in US dollars | L7: Morgan Stanley MSCI stock price index in national currency | M7: Employment | N7: Unemployment rate | O7: Retail sales | P7: Commodity price: all primary commodities | Q7: Commodity price: beverage | R7: Commodity price: coal | S7: Consumer price index | T7: Consumer price index, MER weighted | U7: Core consumer price index | V7: Core consumer price index, GDP weighted | W7: Commodity price: food | X7: Commodity price: metals | Y7: Manufacturing PMI | Z7: Manufacturing PMI, PPP weighted | AA7: Commodity price: non-fuel primary commodities | AB7: Commodity price: natural gas | AC7: Commodity price: energy | AD7: Commodity price: petroleum, US dollar per barrel | AE7: Commodity price: petroleum | AF7: Commodity price: raw materials | AG7: Merchandise trade balance | AH7: Merchandise imports | AI7: Merchandise exports
A8: Frequency | B8: Monthly | C8: Monthly | D8: Monthly | E8: Monthly | F8: Monthly | G8: Monthly | H8: Monthly | I8: Monthly | J8: Monthly | K8: Monthly | L8: Monthly | M8: Monthly | N8: Monthly | O8: Monthly | P8: Monthly | Q8: Monthly | R8: Monthly | S8: Monthly | T8: Monthly | U8: Monthly | V8: Monthly | W8: Monthly | X8: Monthly | Y8: Monthly | Z8: Monthly | AA8: Monthly | AB8: Monthly | AC8: Monthly | AD8: Monthly | AE8: Monthly | AF8: Monthly | AG8: Monthly | AH8: Monthly | AI8: Monthly
A9: Scale | B9: Units | C9: Units | D9: Units | E9: Units | F9: Units | G9: Units | H9: Units | I9: Units | J9: Units | K9: Units | L9: Units | M9: Units | N9: Units | O9: Units | P9: Units | Q9: Units | R9: Units | S9: Units | T9: Units | U9: Units | V9: Units | W9: Units | X9: Units | Y9: Units | Z9: Units | AA9: Units | AB9: Units | AC9: Units | AD9: Units | AE9: Units | AF9: Units | AG9: Billions | AH9: Billions | AI9: Billions
A10: Display_scale | B10: Units | C10: Units | D10: Units | E10: Units | F10: Units | G10: Units | H10: Units | I10: Units | J10: Units | K10: Units | L10: Units | M10: Units | N10: Units | O10: Units | P10: Units | Q10: Units | R10: Units | S10: Units | T10: Units | U10: Units | V10: Units | W10: Units | X10: Units | Y10: Units | Z10: Units | AA10: Units | AB10: Units | AC10: Units | AD10: Units | AE10: Units | AF10: Units | AG10: Billions | AH10: Billions | AI10: Billions
A11: 1990M1 | B11: 114.51447 | C11: 123.71968 | D11: 49.314021 | E11: 63.283681 | F11: 8.3226593 | G11: 12.045953 | H11: 23.824297 | I11: 9.7869901 | J11: 10.812177 | K11: 27.286642 | L11: 17.279753 | N11: 3.3681693 | O11: 29.881555 | Q11: 49.20388 | R11: 51.172528 | S11: 11.330093 | T11: 29.868828 | U11: 46.254719 | V11: 57.548318 | AD11: 20.59 | AF11: 72.855085 | AG11: -5.0989287 | AH11: 196.4791 | AI11: 191.38017
A12: 1990M2 | B12: 114.56883 | C12: 123.76391 | D12: 49.545754 | E12: 63.624021 | F12: 8.5690154 | G12: 12.81087 | H12: 23.578783 | I12: 9.9383907 | J12: 10.892539 | K12: 26.768089 | L12: 17.860288 | N12: 3.3647859 | O12: 29.773219 | Q12: 49.947777 | R12: 51.172528 | S12: 11.459084 | T12: 30.157159 | U12: 46.445228 | V12: 57.787069 | AD12: 19.68 | AF12: 73.449658 | AG12: -2.6458987 | AH12: 193.39879 | AI12: 190.75289
A13: 1990M3 | B13: 115.36045 | C13: 125.23019 | D13: 49.770933 | E13: 64.172551 | F13: 8.8628869 | G13: 13.736319 | H13: 23.145268 | I13: 10.025448 | J13: 11.045264 | K13: 25.142776 | L13: 17.109457 | N13: 3.3460685 | O13: 30.118877 | Q13: 54.434712 | R13: 51.172528 | S13: 12.108967 | T13: 31.348698 | U13: 46.659986 | V13: 58.058774 | AD13: 18.12 | AF13: 74.172077 | AG13: -4.3970504 | AH13: 195.45892 | AI13: 191.06187
A14: 1990M4 | B14: 114.40041 | C14: 123.47383 | D14: 49.2027 | E14: 63.628984 | F14: 9.0530661 | G14: 10.215748 | H14: 22.576919 | I14: 10.161297 | J14: 11.194639 | K14: 25.180263 | L14: 17.192183 | N14: 3.39898 | O14: 29.971872 | Q14: 56.292064 | R14: 51.172528 | S14: 12.206263 | T14: 31.54256 | U14: 46.862083 | V14: 58.285526 | AD14: 16.32 | AF14: 76.022077 | AG14: -4.9160552 | AH14: 193.01728 | AI14: 188.10122
A15: 1990M5 | B15: 114.28377 | C15: 123.30754 | D15: 49.81236 | E15: 64.208728 | F15: 8.8850104 | G15: 9.8632439 | H15: 24.766186 | I15: 10.22205 | J15: 11.257825 | K15: 27.694036 | L15: 18.723435 | N15: 3.4184704 | O15: 30.197059 | Q15: 55.920823 | R15: 54.120417 | S15: 12.317709 | T15: 31.781257 | U15: 47.043499 | V15: 58.479016 | AD15: 16.21 | AF15: 75.418959 | AG15: -5.4187923 | AH15: 200.10086 | AI15: 194.68207
A16: 1990M6 | B16: 113.07135 | C16: 121.14802 | D16: 49.878132 | E16: 64.441221 | F16: 8.6778093 | G16: 10.141767 | H16: 24.52828 | I16: 10.313142 | J16: 11.35778 | K16: 27.336733 | L16: 18.433619 | N16: 3.406569 | O16: 30.460312 | Q16: 53.061015 | R16: 55.284677 | S16: 12.435436 | T16: 32.039774 | U16: 47.274781 | V16: 58.742454 | AD16: 14.93 | AF16: 75.563455 | AG16: -1.0477499 | AH16: 194.0062 | AI16: 192.95845
A17: 1990M7 | B17: 113.03171 | C17: 121.02093 | D17: 49.968687 | E17: 64.443695 | F17: 8.7393347 | G17: 9.9570955 | H17: 24.725588 | I17: 10.396776 | J17: 11.394999 | K17: 27.747213 | L17: 18.522206 | N17: 3.4265965 | O17: 30.542755 | Q17: 52.830834 | R17: 55.284677 | S17: 12.811723 | T17: 32.731921 | U17: 47.47904 | V17: 59.005804 | AD17: 16.81 | AF17: 76.236284 | AG17: -4.545488 | AH17: 199.83838 | AI17: 195.29289
A18: 1990M8 | B18: 108.35276 | C18: 112.91167 | D18: 50.208904 | E18: 64.729208 | F18: 9.1108035 | G18: 9.7702121 | H18: 22.248447 | I18: 10.492068 | J18: 11.497265 | K18: 25.111373 | L18: 16.691811 | N18: 3.4585306 | O18: 30.707238 | Q18: 54.507742 | R18: 55.284677 | S18: 13.09815 | T18: 33.404447 | U18: 47.729603 | V18: 59.320537 | AD18: 26.54 | AF18: 73.868209 | AG18: -7.586449 | AH18: 209.52499 | AI18: 202.41924
A19: 1990M9 | B19: 108.06044 | C19: 113.24927 | D19: 50.250207 | E19: 64.604251 | F19: 9.3294111 | G19: 10.46494 | H19: 20.322 | I19: 10.58601 | J19: 11.564105 | K19: 22.81548 | L19: 15.093753 | N19: 3.5072531 | O19: 30.819715 | Q19: 56.439606 | R19: 55.284677 | S19: 13.418738 | T19: 33.998772 | U19: 47.946922 | V19: 59.545981 | AD19: 33.62 | AF19: 73.204601 | AG19: -4.7038541 | AH19: 208.21249 | AI19: 203.97223
A20: 1990M10 | B20: 101.78818 | C20: 102.33262 | D20: 50.333904 | E20: 64.725252 | F20: 9.1281229 | G20: 9.8990985 | H20: 21.412596 | I20: 10.651504 | J20: 11.621382 | K20: 24.125008 | L20: 15.74034 | N20: 3.5349291 | O20: 31.008903 | Q20: 56.63649 | R20: 55.284677 | S20: 13.564987 | T20: 34.330378 | U20: 48.174506 | V20: 59.77075 | AD20: 34.85 | AF20: 73.155127 | AG20: -11.467118 | AH20: 224.83538 | AI20: 213.84766
A21: 1990M11 | B21: 101.68224 | C21: 101.92072 | D21: 49.957397 | E21: 64.289731 | F21: 8.7570808 | G21: 9.4100861 | H21: 21.392254 | I21: 10.699151 | J21: 11.715121 | K21: 24.145783 | L21: 16.023042 | N21: 3.5749406 | O21: 31.303291 | Q21: 55.621551 | R21: 55.284677 | S21: 13.810246 | T21: 34.781365 | U21: 48.374754 | V21: 59.974347 | AD21: 31.54 | AF21: 73.029421 | AG21: -12.769871 | AH21: 226.23958 | AI21: 213.89971
A22: 1990M12 | B22: 101.82957 | C22: 102.11802 | D22: 49.836694 | E22: 63.94567 | F22: 8.3653919 | G22: 9.1414919 | H22: 22.023779 | I22: 10.770466 | J22: 11.834423 | K22: 24.648403 | L22: 16.536699 | N22: 3.58973 | O22: 31.070077 | Q22: 55.882156 | R22: 55.284677 | S22: 14.026271 | T22: 35.171117 | U22: 48.597067 | V22: 60.224917 | AD22: 26.61 | AF22: 72.658165 | AG22: -6.735854 | AH22: 214.51252 | AI22: 208.21067
A23: 1991M1 | B23: 99.960835 | C23: 99.091477 | D23: 50.690885 | E23: 63.863824 | F23: 8.3127577 | G23: 9.4109205 | H23: 22.204286 | I23: 10.845284 | J23: 11.924376 | K23: 25.859673 | L23: 17.532073 | N23: 3.8666487 | O23: 31.097388 | Q23: 54.152241 | R23: 55.284677 | S23: 14.238246 | T23: 35.622741 | U23: 48.915663 | V23: 60.632197 | AD23: 22.81 | AE23: 51.895164 | AF23: 71.245906 | AG23: -10.098748 | AH23: 225.31323 | AI23: 215.61888
A24: 1991M2 | B24: 101.03893 | C24: 101.0196 | D24: 50.492965 | E24: 63.736862 | F24: 8.0389408 | G24: 9.5803252 | H24: 24.214526 | I24: 10.916885 | J24: 12.072768 | K24: 28.235656 | L24: 19.274861 | N24: 3.9289311 | O24: 31.377597 | Q24: 52.871024 | R24: 55.284677 | S24: 14.465398 | T24: 36.049568 | U24: 49.158243 | V24: 60.915172 | AD24: 18.53 | AE24: 41.623317 | AF24: 72.488907 | AG24: -8.1623706 | AH24: 218.7352 | AI24: 210.92063
A25: 1991M3 | B25: 107.20276 | C25: 111.48343 | D25: 50.251606 | E25: 63.402296 | F25: 8.2382637 | G25: 9.1798236 | H25: 24.496246 | I25: 10.984087 | J25: 12.154684 | K25: 28.011989 | L25: 19.681913 | N25: 4.016352 | O25: 31.549621 | Q25: 53.016481 | R25: 52.242706 | S25: 14.631409 | T25: 36.346553 | U25: 49.326401 | V25: 61.099826 | AD25: 18.21 | AE25: 42.713082 | AF25: 71.063991 | AG25: -4.8204298 | AH25: 210.00065 | AI25: 205.54752
A26: 1991M4 | B26: 106.66854 | C26: 110.68466 | D26: 50.221557 | E26: 63.513692 | F26: 8.1907168 | G26: 7.9350571 | H26: 24.51462 | I26: 11.055672 | J26: 12.235676 | K26: 28.234682 | L26: 19.83188 | N26: 4.033192 | O26: 31.913959 | Q26: 52.103358 | R26: 52.242706 | S26: 14.812783 | T26: 36.689325 | U26: 49.487843 | V26: 61.238237 | AD26: 18.49 | AE26: 44.273197 | AF26: 71.897367 | AG26: -5.2155274 | AH26: 206.23704 | AI26: 201.35451
A27: 1991M5 | B27: 105.86811 | C27: 109.12219 | D27: 50.431897 | E27: 64.015328 | F27: 8.1924619 | G27: 7.7615281 | H27: 25.179714 | I27: 11.138187 | J27: 12.38858 | K27: 29.220117 | L27: 20.666074 | N27: 4.076692 | O27: 32.011864 | Q27: 48.774236 | R27: 52.242706 | S27: 14.924991 | T27: 36.915591 | U27: 49.747303 | V27: 61.491385 | AD27: 18.72 | AE27: 45.108066 | AF27: 72.823651 | AG27: -5.3642246 | AH27: 210.08883 | AI27: 205.10011
A28: 1991M6 | B28: 106.18169 | C28: 109.95012 | D28: 50.63893 | E28: 63.818321 | F28: 8.381082 | G28: 7.7948896 | H28: 23.917544 | I28: 11.203662 | J28: 12.516554 | K28: 27.643224 | L28: 19.752751 | N28: 4.022414 | O28: 32.074732 | Q28: 47.46047 | R28: 52.242706 | S28: 15.102044 | T28: 37.22634 | U28: 49.974251 | V28: 61.729571 | AD28: 17.78 | AE28: 43.608103 | AF28: 74.039224 | AG28: -2.8746617 | AH28: 204.50807 | AI28: 201.93531
A29: 1991M7 | B29: 105.88541 | C29: 109.83381 | D29: 50.809317 | E29: 64.360601 | F29: 8.3325159 | G29: 7.6141335 | H29: 25.057386 | I29: 11.261497 | J29: 12.609906 | K29: 28.954028 | L29: 20.668506 | N29: 3.9265021 | O29: 32.333574 | Q29: 45.930383 | R29: 52.242706 | S29: 15.340976 | T29: 37.603533 | U29: 50.218062 | V29: 61.963891 | AD29: 19.02 | AE29: 46.598285 | AF29: 72.267005 | AG29: -6.6202743 | AH29: 211.16653 | AI29: 204.86976
A30: 1991M8 | B30: 105.43865 | C30: 109.20281 | D30: 50.642768 | E30: 64.104194 | F30: 8.040318 | G30: 7.4911521 | H30: 25.020917 | I30: 11.294781 | J30: 12.744968 | K30: 29.009034 | L30: 20.776685 | N30: 3.9748681 | O30: 32.368659 | Q30: 47.387427 | R30: 52.242706 | S30: 15.543876 | T30: 37.96973 | U30: 50.395713 | V30: 62.163604 | AD30: 19.3 | AE30: 46.77816 | AF30: 71.029708 | AG30: -4.4308916 | AH30: 210.98184 | AI30: 206.86245
A31: 1991M9 | B31: 104.8829 | C31: 107.9292 | D31: 50.759856 | E31: 64.363144 | F31: 7.7839714 | G31: 7.1515831 | H31: 25.319556 | I31: 11.350167 | J31: 12.851402 | K31: 29.226159 | L31: 20.828689 | N31: 4.0137633 | O31: 32.238535 | Q31: 50.699127 | R31: 52.242706 | S31: 15.704071 | T31: 38.241923 | U31: 50.594096 | V31: 62.411444 | AD31: 19.95 | AE31: 47.725344 | AF31: 71.490928 | AG31: -4.6822569 | AH31: 213.89908 | AI31: 209.49943
A32: 1991M10 | B32: 101.47869 | C32: 102.02613 | D32: 50.954508 | E32: 64.432804 | F32: 7.6423132 | G32: 7.0088647 | H32: 26.083115 | I32: 11.419729 | J32: 13.112368 | K32: 29.761164 | L32: 21.347691 | N32: 4.0191231 | O32: 32.422264 | Q32: 49.690825 | R32: 52.242706 | S32: 16.011123 | T32: 38.781758 | U32: 50.80609 | V32: 62.592083 | AD32: 21.56 | AE32: 51.2623 | AF32: 70.083241 | AG32: -3.9720873 | AH32: 217.37481 | AI32: 213.69783
A33: 1991M11 | B33: 99.476793 | C33: 98.517708 | D33: 50.948449 | E33: 64.369259 | F33: 7.5587706 | G33: 6.7459753 | H33: 24.611455 | I33: 11.487376 | J33: 13.288647 | K33: 28.427307 | L33: 20.461845 | N33: 4.0445707 | O33: 32.675094 | Q33: 51.331064 | R33: 52.242706 | S33: 16.270673 | T33: 39.286515 | U33: 51.024322 | V33: 62.82661 | AD33: 20.41 | AE33: 47.715173 | AF33: 68.819061 | AG33: -1.2702288 | AH33: 220.30186 | AI33: 219.36413
A34: 1991M12 | B34: 99.17882 | C34: 98.230013 | D34: 50.550454 | E34: 63.8663 | F34: 7.3015267 | G34: 6.4390198 | H34: 26.040758 | I34: 11.56187 | J34: 13.443819 | K34: 30.888271 | L34: 22.173155 | N34: 4.0659031 | O34: 32.366365 | Q34: 51.101844 | R34: 52.242706 | S34: 16.499304 | T34: 39.654581 | U34: 51.207614 | V34: 63.009806 | AD34: 17.63 | AE34: 40.52036 | AF34: 68.755252 | AG34: -2.0773755 | AH34: 220.15934 | AI34: 218.53137
A35: 1992M1 | B35: 98.43744 | C35: 96.893226 | D35: 50.816128 | E35: 63.778893 | F35: 7.1707613 | G35: 6.1287495 | H35: 26.528001 | I35: 11.614751 | J35: 13.649309 | K35: 30.935051 | L35: 22.628232 | N35: 4.1340025 | O35: 33.063355 | P35: 50.724146 | Q35: 48.467677 | R35: 52.242706 | S35: 18.915604 | T35: 39.996447 | U35: 51.373227 | V35: 63.176637 | W35: 67.512992 | X35: 46.948673 | AA35: 54.673375 | AB35: 54.51602 | AC35: 45.011688 | AD35: 17.52 | AE35: 40.225371 | AF35: 67.201791 | AG35: -3.5530929 | AH35: 223.10482 | AI35: 219.79732
A36: 1992M2 | B36: 97.922398 | C36: 95.813936 | D36: 51.013894 | E36: 63.993521 | F36: 7.3542937 | G36: 6.146693 | H36: 26.58258 | I36: 11.688174 | J36: 13.83816 | K36: 30.20739 | L36: 22.483462 | N36: 4.2763571 | O36: 33.548092 | P36: 50.722601 | Q36: 44.121634 | R36: 52.242706 | S36: 19.510749 | T36: 40.414001 | U36: 51.519711 | V36: 63.338763 | W36: 68.127248 | X36: 48.319412 | AA36: 55.120695 | AB36: 49.91186 | AC36: 44.36087 | AD36: 17.65 | AE36: 41.089686 | AF36: 68.202929 | AG36: -0.23245782 | AH36: 226.38648 | AI36: 226.50532
A37: 1992M3 | B37: 100.29176 | C37: 100.20242 | D37: 51.080618 | E37: 64.082475 | F37: 7.4881734 | G37: 6.131411 | H37: 25.969368 | I37: 11.738885 | J37: 14.005233 | K37: 29.051359 | L37: 21.988755 | N37: 4.2955163 | O37: 33.187242 | P37: 50.748701 | Q37: 44.006519 | R37: 52.242706 | S37: 20.135137 | T37: 40.80532 | U37: 51.756851 | V37: 63.590036 | W37: 69.04621 | X37: 48.220121 | AA37: 55.400467 | AB37: 50.533712 | AC37: 44.020041 | AD37: 17.35 | AE37: 41.165326 | AF37: 68.573076 | AG37: -2.960825 | AH37: 222.51376 | AI37: 219.88733
A38: 1992M4 | B38: 102.60534 | C38: 104.40873 | D38: 51.168299 | E38: 64.314997 | F38: 7.4644856 | G38: 5.7836822 | H38: 25.938185 | I38: 11.778921 | J38: 14.140455 | K38: 29.217931 | L38: 22.262401 | N38: 4.2812865 | O38: 33.384379 | P38: 51.1747 | Q38: 42.97254 | R38: 52.242706 | S38: 20.692425 | T38: 41.208527 | U38: 51.933629 | V38: 63.769895 | W38: 66.211724 | X38: 48.628629 | AA38: 54.364444 | AB38: 51.972758 | AC38: 46.560816 | AD38: 18.65 | AE38: 44.087573 | AF38: 72.508877 | AG38: -4.2078461 | AH38: 227.29775 | AI38: 223.4572
A39: 1992M5 | B39: 104.41226 | C39: 107.62821 | D39: 50.909706 | E39: 63.897892 | F39: 7.3533654 | G39: 5.7156343 | H39: 26.340449 | I39: 11.818255 | J39: 14.286668 | K39: 30.002591 | L39: 22.667576 | N39: 4.3508526 | O39: 33.433189 | P39: 52.635726 | Q39: 40.89879 | R39: 52.242706 | S39: 21.291126 | T39: 41.675494 | U39: 52.132857 | V39: 63.966218 | W39: 68.556314 | X39: 48.605568 | AA39: 55.424397 | AB39: 54.754973 | AC39: 48.601984 | AD39: 19.52 | AE39: 45.566176 | AF39: 72.273732 | AG39: -2.7445031 | AH39: 226.48888 | AI39: 224.05928
A40: 1992M6 | B40: 104.55227 | C40: 107.72247 | D40: 51.036245 | E40: 64.354112 | F40: 7.2689456 | G40: 5.702697 | H40: 24.879787 | I40: 11.858085 | J40: 14.372014 | K40: 28.651934 | L40: 21.559301 | N40: 4.2646222 | O40: 33.545854 | P40: 52.852571 | Q40: 39.672732 | R40: 50.690361 | S40: 21.928336 | T40: 42.082036 | U40: 52.299533 | V40: 64.14325 | W40: 65.571299 | X40: 48.725491 | AA40: 54.07814 | AB40: 55.870772 | AC40: 51.079817 | AD40: 20.88 | AE40: 47.918269 | AF40: 72.802168 | AG40: -6.8749301 | AH40: 236.27184 | AI40: 229.39691
A41: 1992M7 | B41: 101.52879 | C41: 102.14442 | D41: 51.107409 | E41: 64.667116 | F41: 6.9665819 | G41: 5.3836002 | H41: 24.919296 | I41: 11.90157 | J41: 14.512965 | K41: 28.903513 | L41: 21.898563 | N41: 4.232853 | O41: 33.737591 | P41: 52.518993 | Q41: 41.552698 | R41: 49.138015 | S41: 22.478997 | T41: 42.460496 | U41: 52.471373 | V41: 64.304207 | W41: 64.267139 | X41: 50.821035 | AA41: 54.074862 | AB41: 58.465806 | AC41: 50.268468 | AD41: 20.18 | AE41: 45.305162 | AF41: 73.511163 | AG41: -5.2141389 | AH41: 241.836 | AI41: 236.62186
A42: 1992M8 | B42: 100.90147 | C42: 101.07831 | D42: 50.809834 | E42: 64.043952 | F42: 6.7849116 | G42: 5.2919322 | H42: 25.11729 | I42: 11.953717 | J42: 14.665641 | K42: 29.447391 | L42: 22.170462 | N42: 4.2932723 | O42: 33.663128 | P42: 52.580209 | Q42: 41.845957 | R42: 49.138015 | S42: 22.996282 | T42: 42.881336 | U42: 52.658038 | V42: 64.47006 | W42: 65.663962 | X42: 50.472097 | AA42: 54.335454 | AB42: 61.642172 | AC42: 50.041292 | AD42: 19.62 | AE42: 43.653153 | AF42: 71.685422 | AG42: -3.2854362 | AH42: 238.55297 | AI42: 235.26754
A43: 1992M9 | B43: 100.36943 | C43: 100.23918 | D43: 51.263409 | E43: 64.913893 | F43: 6.6843316 | G43: 4.9272924 | H43: 25.090362 | I43: 12.012471 | J43: 14.851905 | K43: 29.106346 | L43: 22.245608 | N43: 4.2874745 | O43: 34.089111 | P43: 53.009 | Q43: 42.138255 | R43: 49.138015 | S43: 23.606505 | T43: 43.38624 | U43: 52.793552 | V43: 64.577833 | W43: 65.440411 | X43: 49.130352 | AA43: 53.989353 | AB43: 64.058887 | AC43: 51.590944 | AD43: 20.19 | AE43: 44.889477 | AF43: 71.487238 | AG43: -2.9716089 | AH43: 241.48587 | AI43: 238.51426
A44: 1992M10 | B44: 99.563428 | C44: 98.96988 | D44: 51.345297 | E44: 64.786064 | F44: 6.7006984 | G44: 4.9176559 | H44: 24.934681 | I44: 12.090316 | J44: 15.122183 | K44: 28.562581 | L44: 22.491845 | N44: 4.2835826 | O44: 34.836265 | P44: 52.500685 | Q44: 43.755518 | R44: 47.532749 | S44: 24.400995 | T44: 43.934943 | U44: 53.005733 | V44: 64.827049 | W44: 64.455641 | X44: 45.975917 | AA44: 53.012376 | AB44: 67.651787 | AC44: 51.760537 | AD44: 20.04 | AE44: 45.255909 | AF44: 71.836684 | AG44: -0.28454841 | AH44: 238.16888 | AI44: 237.88433
A45: 1992M11 | B45: 102.16691 | C45: 103.82463 | D45: 51.19839 | E45: 64.628641 | F45: 6.7641077 | G45: 4.8331915 | H45: 25.592165 | I45: 12.13726 | J45: 15.231555 | K45: 29.027628 | L45: 23.313903 | N45: 4.3142499 | O45: 34.268394 | P45: 50.372062 | Q45: 46.204983 | R45: 45.927482 | S45: 25.056981 | T45: 44.375796 | U45: 53.219688 | V45: 65.011388 | W45: 61.41946 | X45: 43.914144 | AA45: 51.181634 | AB45: 65.666383 | AC45: 49.201037 | AD45: 18.9 | AE45: 44.149055 | AF45: 72.112969 | AG45: -3.0539638 | AH45: 231.10018 | AI45: 228.04621
A46: 1992M12 | B46: 105.28656 | C46: 109.63807 | D46: 51.017358 | E46: 64.626145 | F46: 6.7281554 | G46: 4.8652406 | H46: 25.648165 | I46: 12.178758 | J46: 15.354187 | K46: 29.420044 | L46: 23.843613 | N46: 4.2125005 | O46: 34.448619 | P46: 50.413115 | Q46: 49.844504 | R46: 45.927482 | S46: 25.753339 | T46: 44.846028 | U46: 53.34871 | V46: 65.181342 | W46: 63.647381 | X46: 44.786188 | AA46: 52.56927 | AB46: 64.524873 | AC46: 47.294292 | AD46: 17.93 | AE46: 41.831877 | AF46: 72.428042 | AG46: -6.200469 | AH46: 236.45545 | AI46: 230.25498
... A99: 1997M5 | B99: 116.63737 | C99: 118.5134 | D99: 63.202752 | E99: 77.735855 | F99: 5.8898373 | G99: 5.4529127 | H99: 54.615213 | I99: 34.59337 | J99: 33.029849 | K99: 53.49211 | L99: 55.008929 | N99: 5.6005032 | O99: 44.275206 | P99: 58.144397 | Q99: 106.21394 | R99: 50.740537 | S99: 58.537446 | T99: 69.560977 | U99: 66.728014 | V99: 75.675017 | W99: 73.375234 | X99: 53.310893 | AA99: 63.072316 | AB99: 67.261971 | AC99: 51.016289 | AD99: 19.47 | AE99: 45.592799 | AF99: 91.318345 | AG99: 0.8007939 | AH99: 357.00909 | AI99: 357.80988
A100: 1997M6 | B100: 117.1184 | C100: 119.08106 | D100: 63.704658 | E100: 78.240902 | F100: 5.7426398 | G100: 5.4783474 | H100: 57.456233 | I100: 34.870722 | J100: 33.329097 | K100: 56.54891 | L100: 58.313681 | N100: 5.644202 | O100: 44.576547 | P100: 55.785431 | Q100: 95.184022 | R100: 49.668948 | S100: 58.827184 | T100: 69.779461 | U100: 66.95693 | V100: 75.82233 | W100: 70.406054 | X100: 52.80315 | Y100: 54.704081 | Z100: 54.654986 | AA100: 60.881122 | AB100: 66.766427 | AC100: 48.414645 | AD100: 18.02 | AE100: 42.044627 | AF100: 89.529531 | AG100: -0.232442 | AH100: 363.32878 | AI100: 363.09634
A101: 1997M7 | B101: 116.37556 | C101: 118.26981 | D101: 64.159527 | E101: 78.817891 | F101: 5.5028791 | G101: 5.4647776 | H101: 60.872103 | I101: 35.142281 | J101: 33.482177 | K101: 58.981884 | L101: 62.364157 | N101: 5.6124218 | O101: 44.870529 | P101: 55.236437 | Q101: 87.48614 | R101: 49.241739 | S101: 59.106141 | T101: 69.975073 | U101: 67.185746 | V101: 75.985264 | W101: 69.905429 | X101: 52.086145 | Y101: 55.775839 | Z101: 55.681915 | AA101: 59.755813 | AB101: 64.664573 | AC101: 48.699276 | AD101: 18.45 | AE101: 43.433738 | AF101: 88.822162 | AG101: 0.0698292 | AH101: 367.97837 | AI101: 368.0482
A102: 1997M8 | B102: 116.61163 | C102: 118.63994 | D102: 64.272254 | E102: 78.936109 | F102: 5.5307005 | G102: 5.5251061 | H102: 55.867311 | I102: 35.360413 | J102: 33.830891 | K102: 54.703583 | L102: 57.892294 | N102: 5.5878111 | O102: 44.863774 | P102: 55.492076 | Q102: 85.497512 | R102: 50.43242 | S102: 59.381724 | T102: 70.170955 | U102: 67.410531 | V102: 76.115873 | W102: 69.424569 | X102: 52.144268 | Y102: 54.921407 | Z102: 54.840238 | AA102: 59.195684 | AB102: 67.936858 | AC102: 50.134901 | AD102: 18.79 | AE102: 45.009411 | AF102: 85.253824 | AG102: -0.5509408 | AH102: 358.65504 | AI102: 358.1041
A103: 1997M9 | B103: 117.25241 | C103: 119.36389 | D103: 64.528772 | E103: 79.127836 | F103: 5.3717591 | G103: 5.6510541 | H103: 58.327669 | I103: 35.514006 | J103: 33.913264 | K103: 57.365629 | L103: 60.551396 | M103: 97.960637 | N103: 5.5742195 | O103: 44.958641 | P103: 55.534649 | Q103: 86.279562 | R103: 49.696781 | S103: 59.583853 | T103: 70.364467 | U103: 67.694847 | V103: 76.402152 | W103: 69.247847 | X103: 50.049421 | Y103: 54.500681 | Z103: 54.569219 | AA103: 58.521276 | AB103: 73.713847 | AC103: 51.21457 | AD103: 18.73 | AE103: 44.674223 | AF103: 83.11069 | AG103: -2.8928255 | AH103: 368.05497 | AI103: 365.16214
A104: 1997M10 | B104: 115.70794 | C104: 117.69454 | D104: 65.030411 | E104: 79.668424 | F104: 5.2531931 | G104: 5.6141527 | H104: 53.207984 | I104: 35.779995 | J104: 34.21364 | K104: 52.764228 | L104: 55.497028 | M104: 98.015185 | N104: 5.5431238 | O104: 45.367465 | P104: 56.232248 | Q104: 81.608033 | R104: 49.013749 | S104: 59.800218 | T104: 70.527232 | U104: 68.098209 | V104: 76.62991 | W104: 69.291961 | X104: 48.669989 | Y104: 56.102787 | Z104: 55.964456 | AA104: 57.886403 | AB104: 75.372533 | AC104: 53.839557 | AD104: 20.12 | AE104: 47.627142 | AF104: 80.064804 | AG104: -1.3734407 | AH104: 371.34705 | AI104: 369.97361
A105: 1997M11 | B105: 116.79364 | C105: 118.93823 | D105: 64.731105 | E105: 79.418678 | F105: 5.1590144 | G105: 5.7913802 | H105: 53.81673 | I105: 35.955226 | J105: 34.324625 | K105: 52.295906 | L105: 56.255426 | M105: 98.082438 | N105: 5.5007101 | O105: 45.250908 | P105: 55.11331 | Q105: 80.609775 | R105: 45.464208 | S105: 60.380562 | T105: 70.807619 | U105: 68.375648 | V105: 76.806188 | W105: 69.876563 | X105: 47.388004 | Y105: 55.636118 | Z105: 55.355288 | AA105: 57.596667 | AB105: 74.239468 | AC105: 51.521199 | AD105: 19.16 | AE105: 45.229031 | AF105: 80.2356 | AG105: -0.2688218 | AH105: 365.37477 | AI105: 365.10594
A106: 1997M12 | B106: 118.50874 | C106: 120.90879 | D106: 65.081312 | E106: 79.621339 | F106: 5.0871236 | G106: 6.2360627 | H106: 54.710325 | I106: 36.229611 | J106: 34.526461 | K106: 52.501067 | L106: 57.750608 | M106: 98.131345 | N106: 5.4765739 | O106: 45.337936 | P106: 53.847692 | Q106: 87.071179 | R106: 43.941184 | S106: 60.584144 | T106: 70.936265 | U106: 68.623863 | V106: 76.979125 | W106: 74.381816 | X106: 45.282332 | Y106: 54.446384 | Z106: 54.109819 | AA106: 58.886805 | AB106: 66.289227 | AC106: 46.558745 | AD106: 17.24 | AE106: 41.275286 | AF106: 74.80659 | AG106: -5.7862563 | AH106: 365.85933 | AI106: 360.07307
A107: 1998M1 | B107: 116.6655 | C107: 118.76208 | D107: 64.973153 | E107: 79.730891 | F107: 4.9720455 | G107: 7.4142219 | H107: 56.929221 | I107: 36.559388 | J107: 34.766912 | K107: 53.579452 | L107: 59.260211 | M107: 97.760697 | N107: 5.72536 | O107: 45.268542 | P107: 50.933295 | Q107: 88.744152 | R107: 43.747141 | S107: 60.931841 | T107: 71.167006 | U107: 68.929011 | V107: 77.19076 | W107: 71.298246 | X107: 43.93987 | Y107: 53.547793 | Z107: 53.263857 | AA107: 57.075773 | AB107: 62.779441 | AC107: 42.048358 | AD107: 15.07 | AE107: 36.334001 | AF107: 71.973685 | AG107: -1.9150058 | AH107: 354.60352 | AI107: 352.68851
A108: 1998M2 | B108: 118.96713 | C108: 121.31661 | D108: 64.984579 | E108: 79.650892 | F108: 4.9305251 | G108: 7.6673379 | H108: 60.404005 | I108: 36.77702 | J108: 34.89552 | K108: 57.451573 | L108: 63.188792 | M108: 97.78998 | N108: 5.7702548 | O108: 45.217346 | P108: 50.350631 | Q108: 88.94927 | R108: 44.628215 | S108: 61.285969 | T108: 71.38535 | U108: 69.419281 | V108: 77.469947 | W108: 70.75354 | X108: 43.210952 | Y108: 53.474177 | Z108: 53.17833 | AA108: 57.166802 | AB108: 61.995499 | AC108: 40.491216 | AD108: 14.18 | AE108: 34.030727 | AF108: 75.198986 | AG108: 2.7589303 | AH108: 357.33858 | AI108: 360.09751
A109: 1998M3 | B109: 117.97729 | C109: 120.35637 | D109: 65.058198 | E109: 79.462607 | F109: 4.878083 | G109: 7.4262378 | H109: 62.887991 | I109: 37.011363 | J109: 35.048926 | K109: 59.483327 | L109: 66.116118 | M109: 97.780672 | N109: 5.8352317 | O109: 45.321263 | P109: 49.65403 | Q109: 83.04897 | R109: 43.499707 | S109: 61.55354 | T109: 71.54731 | U109: 69.72959 | V109: 77.678883 | W109: 71.402764 | X109: 43.543011 | Y109: 53.835437 | Z109: 53.515823 | AA109: 57.308833 | AB109: 61.387567 | AC109: 38.581555 | AD109: 13.24 | AE109: 31.902448 | AF109: 74.171997 | AG109: -0.8378667 | AH109: 357.20911 | AI109: 356.37124
A110: 1998M4 | B110: 118.66535 | C110: 121.1572 | D110: 65.243353 | E110: 79.585121 | F110: 4.8514594 | G110: 7.4274765 | H110: 62.969076 | I110: 37.2641 | J110: 35.250105 | K110: 59.713083 | L110: 65.714161 | M110: 96.636535 | N110: 5.8761445 | O110: 45.909706 | P110: 50.698175 | Q110: 82.654235 | R110: 43.473756 | S110: 61.77412 | T110: 71.67337 | U110: 70.0365 | V110: 77.848691 | W110: 73.511708 | X110: 43.842567 | Y110: 53.815302 | Z110: 53.475749 | AA110: 58.660146 | AB110: 62.633579 | AC110: 39.181388 | AD110: 13.39 | AE110: 32.288465 | AF110: 73.728173 | AG110: 1.6225924 | AH110: 353.86827 | AI110: 355.49086
A111: 1998M5 | B111: 118.42783 | C111: 120.94182 | D111: 64.981397 | E111: 79.464787 | F111: 4.838405 | G111: 7.9113827 | H111: 61.814663 | I111: 37.527234 | J111: 35.433689 | K111: 57.31839 | L111: 63.951761 | M111: 96.697493 | N111: 5.9023912 | O111: 46.022881 | P111: 50.507945 | Q111: 80.043073 | R111: 43.048977 | S111: 62.103232 | T111: 71.898371 | U111: 70.343128 | V111: 78.037808 | W111: 73.883179 | X111: 42.34175 | Y111: 52.826672 | Z111: 52.436661 | AA111: 58.275822 | AB111: 58.917268 | AC111: 39.271911 | AD111: 13.97 | AE111: 33.690444 | AF111: 72.956108 | AG111: 0.9245554 | AH111: 349.8019 | AI111: 350.72646
A112: 1998M6 | B112: 118.6566 | C112: 121.23305 | D112: 64.986876 | E112: 79.371281 | F112: 4.7346244 | G112: 7.9085309 | H112: 61.386447 | I112: 37.779791 | J112: 35.642676 | K112: 57.039275 | L112: 64.101919 | M112: 96.744022 | N112: 5.9035069 | O112: 45.897126 | P112: 48.340105 | Q112: 75.205592 | R112: 42.616359 | S112: 62.404778 | T112: 72.067769 | U112: 70.683594 | V112: 78.226749 | W112: 71.865318 | X112: 40.491138 | Y112: 51.59711 | Z112: 51.273086 | AA112: 56.472656 | AB112: 58.75343 | AC112: 36.576578 | AD112: 12.48 | AE112: 30.355427 | AF112: 71.911061 | AG112: -1.273611 | AH112: 348.29246 | AI112: 347.01885
A113: 1998M7 | B113: 118.49303 | C113: 121.1444 | D113: 65.116768 | E113: 79.506608 | F113: 4.7363767 | G113: 8.0845567 | H113: 62.310486 | I113: 38.058436 | J113: 35.716515 | K113: 57.481633 | L113: 64.638825 | M113: 96.457889 | N113: 5.9150467 | O113: 46.099348 | P113: 47.398414 | Q113: 71.809018 | R113: 42.010944 | S113: 62.750618 | T113: 72.25781 | U113: 71.099464 | V113: 78.438507 | W113: 68.944023 | X113: 40.4321 | Y113: 51.10349 | Z113: 50.829237 | AA113: 54.766781 | AB113: 57.753628 | AC113: 36.740261 | AD113: 12.72 | AE113: 30.999288 | AF113: 69.680821 | AG113: 1.5217271 | AH113: 343.59119 | AI113: 345.11292
A114: 1998M8 | B114: 117.684 | C114: 120.09032 | D114: 64.960707 | E114: 79.267959 | F114: 4.5837505 | G114: 8.8622354 | H114: 52.054988 | I114: 38.210628 | J114: 35.946463 | K114: 47.874111 | L114: 53.776618 | M114: 96.483593 | N114: 5.901627 | O114: 46.321141 | P114: 45.95825 | Q114: 73.599146 | R114: 39.105784 | S114: 63.061528 | T114: 72.400635 | U114: 71.463883 | V114: 78.667639 | W114: 66.529833 | X114: 39.77086 | Y114: 50.802694 | Z114: 50.378791 | AA114: 53.353368 | AB114: 53.259919 | AC114: 35.261402 | AD114: 12.49 | AE114: 30.542438 | AF114: 69.738012 | AG114: -0.5129983 | AH114: 339.50313 | AI114: 338.99013
... A361: 2019M3 | B361: 110.07746 | C361: 113.51816 | D361: 132.42932 | E361: 123.92256 | F361: 2.2890951 | G361: 3.1449702 | H361: 200.64177 | I361: 185.31279 | J361: 206.31406 | K361: 130.06357 | L361: 157.71566 | M361: 121.72595 | N361: 5.0728347 | O361: 80.22797 | P361: 120.26465 | Q361: 81.672673 | R361: 128.61521 | S361: 170.15612 | T361: 156.60395 | U361: 127.31332 | V361: 121.77907 | W361: 99.372528 | X361: 136.3354 | Y361: 51.502797 | Z361: 51.276956 | AA361: 107.82633 | AB361: 102.54173 | AC361: 138.25637 | AD361: 63.789841 | AE361: 148.86005 | AF361: 105.22629 | AG361: -5.865852 | AH361: 1238.7038 | AI361: 1229.916
A362: 2019m4 | B362: 110.43722 | C362: 114.26388 | D362: 132.31727 | E362: 123.59182 | F362: 2.2229008 | G362: 3.2150048 | H362: 205.24686 | I362: 186.38703 | J362: 207.38144 | K362: 133.46652 | L362: 162.2796 | O362: 80.291373 | P362: 123.83996 | Q362: 81.459685 | R362: 116.65315 | S362: 170.86246 | T362: 157.26 | U362: 127.55298 | V362: 122.01064 | W362: 102.9241 | X362: 139.58372 | Y362: 50.694767 | Z362: 50.598874 | AA362: 110.06277 | AB362: 96.214792 | AC362: 143.76829 | AD362: 68.571667 | AE362: 160.45415 | AF362: 105.75931 | AG362: -54.892821 | AH362: 1269.7616 | AI362: 1211.9469
A363: 2019m5 | B363: 110.53685 | C363: 114.51691 | D363: 132.51547 | E363: 124.05808 | F363: 2.2379414 | G363: 3.2956181 | H363: 195.18043 | I363: 187.54226 | J363: 208.57285 | K363: 124.64793 | L363: 151.94759 | O363: 80.817183 | P363: 120.80558 | Q363: 81.225961 | R363: 114.93908 | S363: 171.50368 | T363: 157.80862 | U363: 127.7133 | V363: 122.13418 | W363: 99.497096 | X363: 138.82798 | Y363: 50.138745 | Z363: 50.224923 | AA363: 107.94329 | AB363: 91.076104 | AC363: 139.41056 | AD363: 66.876957 | AE363: 157.12436 | AF363: 104.07285 | AG363: -18.392426 | AH363: 1252.5888 | AI363: 1230.4544
A364: 2019m6 | B364: 109.12077 | C364: 112.55431 | F364: 2.0337607 | G364: 3.2454678 | H364: 204.21063 | J364: 210.55166 | K364: 132.54105 | L364: 159.83665 | P364: 114.99807 | Q364: 84.414438 | R364: 104.39347 | S364: 171.98934 | T364: 158.30772 | U364: 128.02704 | V364: 122.41596 | W364: 98.39 | X364: 141.33562 | Y364: 49.681762 | Z364: 49.713033 | AA364: 109.09803 | AB364: 78.387763 | AC364: 123.53232 | AD364: 59.729 | AE364: 139.91704 | AF364: 104.37517
A365: 2019m7
A366: 2019m8
A367: 2019m9
A368: 2019m10
A369: 2019m11
A370: 2019m12

Sheet OECD
B1: OECDCLI | C1: CHEM
A2: ='Monthly Haver'!A5 -> Jan-1999 | B2: 99.47476 | C2: 95.61
A3: ='Monthly Haver'!A6 -> Feb-1999 | B3: 99.66687 | C3: 96.34
A4: ='Monthly Haver'!A7 -> Mar-1999 | B4: 99.85615 | C4: 96.64
A5: ='Monthly Haver'!A8 -> Apr-1999 | B5: 100.0378 | C5: 97.25
A6: ='Monthly Haver'!A9 -> May-1999 | B6: 100.2077 | C6: 98.12
A7: ='Monthly Haver'!A10 -> Jun-1999 | B7: 100.3658 | C7: 98.7
A8: ='Monthly Haver'!A11 -> Jul-1999 | B8: 100.5119 | C8: 98.78
A9: ='Monthly Haver'!A12 -> Aug-1999 | B9: 100.6493 | C9: 98.8
A10: ='Monthly Haver'!A13 -> Sep-1999 | B10: 100.7834 | C10: 98.59
A11: ='Monthly Haver'!A14 -> Oct-1999 | B11: 100.92 | C11: 99.03
A12: ='Monthly Haver'!A15 -> Nov-1999 | B12: 101.0557 | C12: 100.26
A13: ='Monthly Haver'!A16 -> Dec-1999 | B13: 101.1789 | C13: 100.67
... A246: ='Monthly Haver'!A249 -> May-2019 | B246: 99.0301 | C246: 122.38
A247: ='Monthly Haver'!A250 -> Jun-2019 | C247: 122.19

Sheet GDS_Quarterly
A1: EcDatabase | B1: ID:GDS_LIVE | C1: ID:GDS_LIVE | D1: ID:GDS_LIVE | E1: ID:GDS_LIVE | F1: ID:GDS_LIVE | G1: ID:GDS_LIVE | H1: ID:GDS_LIVE | I1: ID:GDS_LIVE | J1: ID:GDS_LIVE | K1: ID:GDS_LIVE | L1: ID:GDS_LIVE | M1: ID:GDS_LIVE | N1: ID:GDS_LIVE | O1: ID:GDS_LIVE | P1: ID:GDS_LIVE | Q1: ID:GDS_LIVE | R1: ID:GDS_LIVE | S1: ID:GDS_LIVE | T1: ID:GDS_LIVE | U1: ID:GDS_LIVE | V1: ID:GDS_LIVE | W1: ID:GDS_LIVE | X1: ID:GDS_LIVE | Y1: ID:GDS_LIVE | Z1: ID:GDS_LIVE | AA1: ID:GDS_LIVE | AB1: ID:GDS_LIVE | AC1: ID:GDS_LIVE | AD1: ID:GDS_LIVE | AE1: ID:GDS_LIVE | AF1: ID:GDS_LIVE | AG1: ID:GDS_LIVE | AH1: ID:GDS_LIVE | AI1: ID:GDS_LIVE | AJ1: ID:GDS_LIVE | AK1: ID:GDS_LIVE | AL1: ID:GDS_LIVE | AM1: ID:GDS_LIVE | AN1: ID:GDS_LIVE | AO1: ID:GDS_LIVE | AP1: ID:GDS_LIVE | AQ1: ID:GDS_LIVE | AR1: ID:GDS_LIVE | AS1: ID:GDS_LIVE | AT1: ID:GDS_LIVE | AU1: ID:GDS_LIVE | AV1: ID:GDS_LIVE | AW1: ID:GDS_LIVE | AX1: ID:GDS_LIVE | AY1: ID:GDS_LIVE | AZ1: ID:GDS_LIVE | BA1: ID:GDS_LIVE | BB1: ID:GDS_LIVE | BC1: ID:GDS_LIVE
A2: Series_code | B2: 001ACC_PPPWGT.Q | C2: 001ACC.Q | D2: 001AIP.Q | E2: 001AIP_GDPWGT.Q | F2: 001BCA.Q | G2: 001BCA_GDP.Q | H2: 001FIGB.Q | I2: 001FIPR.Q | J2: 001FISI.Q | K2: 001FMB.Q | L2: 001FMN.Q | M2: 001FMSCID.Q | N2: 001FMSCIL.Q | O2: 001LE.Q | P2: 001LUR.Q | Q2: 001NCP_R.Q | R2: 001NCP_R_GDPWGT.Q | S2: 001NFI_R.Q | T2: 001NFI_R_GDPWGT.Q | U2: 001NGDP_R.Q | V2: 001NGDP_R_GDPWGT.Q | W2: 001NGDP_RF.Q | X2: 001NGDP_RF_GDPWGT.Q | Y2: 001NGDPD.Q | Z2: 001NM_R.Q | AA2: 001NM_R_GDPWGT.Q | AB2: 001NM_R_TMWGT.Q | AC2: 001NRS.Q | AD2: 001NTDD_R.Q | AE2: 001NTDD_R_GDPWGT.Q | AF2: 001NX_R.Q | AG2: 001NX_R_GDPWGT.Q | AH2: 001NX_R_TXWGT.Q | AI2: 001PALLFNFW.Q | AJ2: 001PBEVEW.Q | AK2: 001PCOALW.Q | AL2: 001PCPI.Q | AM2: 001PCPI_GDPWGT.Q | AN2: 001PCPIF.Q | AO2: 001PCPIX.Q | AP2: 001.Q | AQ2: 001PFOODW.Q | AR2: 001PMETAW.Q | AS2: 001PMI.Q | AT2: 001PMI_PPPWGT.Q | AU2: 001PNFUELW.Q | AV2: 001PNGASW.Q | AW2: 001PNRGW.Q | AX2: 001POILAPSP.Q | AY2: 001POILAPSPW.Q | AZ2: 001PRAWMW.Q | BA2: 001TG.Q | BB2: 001TMG.Q | BC2: 001TXG.Q
A3: Country | B3: World | C3: World | D3: World | E3: World | F3: World | G3: World | H3: World | I3: World | J3: World | K3: World | L3: World | M3: World | N3: World | O3: World | P3: World | Q3: World | R3: World | S3: World | T3: World | U3: World | V3: World | W3: World | X3: World | Y3: World | Z3: World | AA3: World | AB3: World | AC3: World | AD3: World | AE3: World | AF3: World | AG3: World | AH3: World | AI3: World | AJ3: World | AK3: World | AL3: World | AM3: World | AN3: World | AO3: World | AP3: World | AQ3: World | AR3: World | AS3: World | AT3: World | AU3: World | AV3: World | AW3: World | AX3: World | AY3: World | AZ3: World | BA3: World | BB3: World | BC3: World
A4: Indicator | B4: ACC_PPPWGT | C4: ACC | D4: AIP | E4: AIP_GDPWGT | F4: BCA | G4: BCA_GDP | H4: FIGB | I4: FIPR | J4: FISI | K4: FMB | L4: FMN | M4: FMSCID | N4: FMSCIL | O4: LE | P4: LUR | Q4: NCP_R | R4: NCP_R_GDPWGT | S4: NFI_R | T4: NFI_R_GDPWGT | U4: NGDP_R | V4: NGDP_R_GDPWGT | W4: NGDP_RF | X4: NGDP_RF_GDPWGT | Y4: NGDPD | Z4: NM_R | AA4: NM_R_GDPWGT | AB4: NM_R_TMWGT | AC4: NRS | AD4: NTDD_R | AE4: NTDD_R_GDPWGT | AF4: NX_R | AG4: NX_R_GDPWGT | AH4: NX_R_TXWGT | AI4: PALLFNFW | AJ4: PBEVEW | AK4: PCOALW | AL4: PCPI | AM4: PCPI_GDPWGT | AN4: PCPIF | AO4: PCPIX | AP4: PCPIX_GDPWGT | AQ4: PFOODW | AR4: PMETAW | AS4: PMI | AT4: PMI_PPPWGT | AU4: PNFUELW | AV4: PNGASW | AW4: PNRGW | AX4: POILAPSP | AY4: POILAPSPW | AZ4: PRAWMW | BA4: TG | BB4: TMG | BC4: TXG
A5: Indicator.Descriptor | B5: Consumer confidence, PPP weighted | C5: Consumer confidence | D5: Industrial production | E5: Industrial production, MER weighted | F5: Current account balance | G5: Current account balance, percent of GDP | H5: Long-term interest rate | I5: Policy-related interest rate | J5: Benchmark stock market index | K5: Broad money | L5: Narrow money | M5: Morgan Stanley MSCI stock price index in US dollars | N5: Morgan Stanley MSCI stock price index in national currency | O5: Employment | P5: Unemployment rate | Q5: Real private consumption | R5: Real private consumption, MER weighted | S5: Real gross fixed capital formation | T5: Real gross fixed capital formation, MER weighted | U5: Real gross domestic product | V5: Real gross domestic product, MER weighted | W5: Real gross domestic product, with projections from WEO | X5: Real gross domestic product, with projections from WEO, MER weighted | Y5: Nominal gross domestic product, US dollars | Z5: Real imports | AA5: Real imports, MER weighted | AB5: Real imports, imports weighted | AC5: Retail sales | AD5: Real total domestic demand | AE5: Real total domestic demand, MER weighted | AF5: Real exports | AG5: Real exports, MER weighted | AH5: Real exports, exports weighted | AI5: Commodity price: all primary commodities | AJ5: Commodity price: beverage | AK5: Commodity price: coal | AL5: Consumer price index | AM5: Consumer price index, MER weighted | AN5: Consumer price index, with projections from WEO | AO5: Core consumer price index | AP5: Core consumer price index, GDP weighted | AQ5: Commodity price: food | AR5: Commodity price: metals | AS5: Manufacturing PMI | AT5: Manufacturing PMI, PPP weighted | AU5: Commodity price: non-fuel primary commodities | AV5: Commodity price: natural gas | AW5: Commodity price: energy | AX5: Commodity price: petroleum, US dollar per barrel | AY5: Commodity price: petroleum | AZ5: Commodity price: raw materials | BA5: Merchandise trade balance | BB5: Merchandise imports | BC5: Merchandise exports
A6: Frequency | B6: Quarterly | C6: Quarterly | D6: Quarterly | E6: Quarterly | F6: Quarterly | G6: Quarterly | H6: Quarterly | I6: Quarterly | J6: Quarterly | K6: Quarterly | L6: Quarterly | M6: Quarterly | N6: Quarterly | O6: Quarterly | P6: Quarterly | Q6: Quarterly | R6: Quarterly | S6: Quarterly | T6: Quarterly | U6: Quarterly | V6: Quarterly | W6: Quarterly | X6: Quarterly | Y6: Quarterly | Z6: Quarterly | AA6: Quarterly | AB6: Quarterly | AC6: Quarterly | AD6: Quarterly | AE6: Quarterly | AF6: Quarterly | AG6: Quarterly | AH6: Quarterly | AI6: Quarterly | AJ6: Quarterly | AK6: Quarterly | AL6: Quarterly | AM6: Quarterly | AN6: Quarterly | AO6: Quarterly | AP6: Quarterly | AQ6: Quarterly | AR6: Quarterly | AS6: Quarterly | AT6: Quarterly | AU6: Quarterly | AV6: Quarterly | AW6: Quarterly | AX6: Quarterly | AY6: Quarterly | AZ6: Quarterly | BA6: Quarterly | BB6: Quarterly | BC6: Quarterly
A7: Scale | B7: Units | C7: Units | D7: Units | E7: Units | F7: Billions | G7: Units | H7: Units | I7: Units | J7: Units | K7: Units | L7: Units | M7: Units | N7: Units | O7: Units | P7: Units | Q7: Units | R7: Units | S7: Units | T7: Units | U7: Units | V7: Units | W7: Units | X7: Units | Y7: Billions | Z7: Units | AA7: Units | AB7: Units | AC7: Units | AD7: Units | AE7: Units | AF7: Units | AG7: Units | AH7: Units | AI7: Units | AJ7: Units | AK7: Units | AL7: Units | AM7: Units | AN7: Units | AO7: Units | AP7: Units | AQ7: Units | AR7: Units | AS7: Units | AT7: Units | AU7: Units | AV7: Units | AW7: Units | AX7: Units | AY7: Units | AZ7: Units | BA7: Billions | BB7: Billions | BC7: Billions
A8: Display_scale | B8: Units | C8: Units | D8: Units | E8: Units | F8: Billions | G8: Units | H8: Units | I8: Units | J8: Units | K8: Units | L8: Units | M8: Units | N8: Units | O8: Units | P8: Units | Q8: Units | R8: Units | S8: Units | T8: Units | U8: Units | V8: Units | W8: Units | X8: Units | Y8: Billions | Z8: Units | AA8: Units | AB8: Units | AC8: Units | AD8: Units | AE8: Units | AF8: Units | AG8: Units | AH8: Units | AI8: Units | AJ8: Units | AK8: Units | AL8: Units | AM8: Units | AN8: Units | AO8: Units | AP8: Units | AQ8: Units | AR8: Units | AS8: Units | AT8: Units | AU8: Units | AV8: Units | AW8: Units | AX8: Units | AY8: Units | AZ8: Units | BA8: Billions | BB8: Billions | BC8: Billions
A9: 1990Q1 | B9: 114.81458 | C9: 124.23793 | D9: 49.543569 | E9: 63.693418 | F9: -39.255759 | G9: -1.1070738 | H9: 8.5848539 | I9: 12.864381 | J9: 23.145268 | K9: 10.025448 | L9: 11.045264 | M9: 25.142776 | N9: 17.109457 | P9: 3.3596746 | Q9: 47.213154 | R9: 56.509996 | S9: 43.033553 | T9: 60.016458 | U9: 48.867596 | V9: 58.366689 | W9: 49.847183 | X9: 58.892925 | Y9: 3545.9027 | Z9: 22.176265 | AA9: 30.685512 | AB9: 29.593931 | AC9: 29.924551 | AD9: 48.72105 | AE9: 58.87154 | AF9: 24.032993 | AG9: 30.286245 | AH9: 29.10378 | AJ9: 51.195456 | AK9: 51.172528 | AL9: 11.632715 | AM9: 30.458228 | AN9: 4.4961391 | AO9: 46.453311 | AP9: 57.798054 | AX9: 19.463333 | AZ9: 73.492273 | BA9: -12.141878 | BB9: 585.33681 | BC9: 573.19493
A10: 1990Q2 | B10: 113.91851 | C10: 122.64313 | D10: 49.631064 | E10: 64.092978 | F10: -31.430276 | G10: -0.88760047 | H10: 8.8719619 | I10: 10.073586 | J10: 24.52828 | K10: 10.313142 | L10: 11.35778 | M10: 27.336733 | N10: 18.433619 | P10: 3.4080065 | Q10: 47.754054 | R10: 57.172254 | S10: 42.616422 | T10: 59.619449 | U10: 49.095601 | V10: 58.814317 | W10: 50.04317 | X10: 59.334551 | Y10: 3541.0387 | Z10: 22.257271 | AA10: 30.836931 | AB10: 29.805988 | AC10: 30.209748 | AD10: 49.140282 | AE10: 59.414058 | AF10: 24.166015 | AG10: 30.66399 | AH10: 29.386309 | AJ10: 55.091301 | AK10: 53.525874 | AL10: 12.319803 | AM10: 31.787864 | AN10: 4.8678908 | AO10: 47.060121 | AP10: 58.502332 | AX10: 15.82 | AZ10: 75.668164 | BA10: -11.382597 | BB10: 587.12433 | BC10: 575.74174
A11: 1990Q3 | B11: 109.81497 | C11: 115.72729 | D11: 50.142599 | E11: 64.592385 | F11: -31.237681 | G11: -0.84665026 | H11: 9.0598497 | I11: 10.064082 | J11: 20.322 | K11: 10.58601 | L11: 11.564105 | M11: 22.81548 | N11: 15.093753 | P11: 3.4641267 | Q11: 48.061523 | R11: 57.488324 | S11: 44.237978 | T11: 60.369761 | U11: 49.478952 | V11: 59.170489 | W11: 50.414594 | X11: 59.675153 | Y11: 3689.5614 | Z11: 22.433731 | AA11: 30.718787 | AB11: 29.656426 | AC11: 30.689903 | AD11: 49.28461 | AE11: 59.528847 | AF11: 24.666766 | AG11: 30.955463 | AH11: 29.688249 | AJ11: 54.592727 | AK11: 55.284677 | AL11: 13.109537 | AM11: 33.37838 | AN11: 5.4112631 | AO11: 47.718522 | AP11: 59.290774 | AX11: 25.656667 | AZ11: 74.436365 | BA11: -16.835791 | BB11: 617.57585 | BC11: 601.68436
A12: 1990Q4 | B12: 101.76666 | C12: 102.12379 | D12: 50.042665 | E12: 64.320218 | F12: -33.159288 | G12: -0.86638058 | H12: 8.7501985 | I12: 9.4835588 | J12: 22.023779 | K12: 10.770466 | L12: 11.834423 | M12: 24.648403 | N12: 16.536699 | P12: 3.5665332 | Q12: 47.922831 | R12: 57.245434 | S12: 43.876755 | T12: 59.939964 | U12: 49.558716 | V12: 59.085121 | W12: 50.421766 | X12: 59.537559 | Y12: 3827.3351 | Z12: 22.495745 | AA12: 30.784818 | AB12: 29.751411 | AC12: 31.127424 | AD12: 49.275118 | AE12: 59.29664 | AF12: 25.074553 | AG12: 31.489048 | AH12: 30.169817 | AJ12: 56.046732 | AK12: 55.284677 | AL12: 13.800501 | AM12: 34.760953 | AN12: 5.7936466 | AO12: 48.382109 | AP12: 59.990004 | AX12: 31 | AZ12: 72.947571 | BA12: -30.972843 | BB12: 665.58748 | BC12: 635.95803
A13: 1991Q1 | B13: 102.73417 | C13: 103.86483 | D13: 50.478485 | E13: 63.667661 | F13: -4.1932369 | G13: -0.10919638 | H13: 8.1966541 | I13: 9.3903565 | J13: 24.496246 | K13: 10.984087 | L13: 12.154684 | M13: 28.011989 | N13: 19.681913 | P13: 3.9373106 | Q13: 47.980265 | R13: 57.182458 | S13: 43.300805 | T13: 59.222435 | U13: 49.404762 | V13: 58.978466 | W13: 50.239496 | X13: 59.420541 | Y13: 3840.0878 | Z13: 22.095941 | AA13: 30.111318 | AB13: 29.389667 | AC13: 31.341535 | AD13: 49.093789 | AE13: 59.151987 | AF13: 25.366421 | AG13: 31.611776 | AH13: 30.243687 | AJ13: 53.346582 | AK13: 54.270686 | AL13: 14.445018 | AM13: 36.006287 | AN13: 6.2272566 | AO13: 49.133436 | AP13: 60.882398 | AX13: 19.85 | AY13: 45.410521 | AZ13: 71.599601 | BA13: -23.081549 | BB13: 654.04908 | BC13: 632.08703
A14: 1991Q2 | B14: 106.23945 | C14: 109.91899 | D14: 50.430795 | E14: 63.782447 | F14: 3.4235451 | G14: 0.089640492 | H14: 8.2547536 | I14: 7.8304916 | J14: 23.917544 | K14: 11.203662 | L14: 12.516554 | M14: 27.643224 | N14: 19.752751 | P14: 4.0440994 | Q14: 48.676546 | R14: 57.860738 | S14: 43.523647 | T14: 59.157494 | U14: 49.993065 | V14: 59.508944 | W14: 50.776754 | X14: 59.913956 | Y14: 3819.1949 | Z14: 22.753903 | AA14: 30.717096 | AB14: 29.907087 | AC14: 32.000185 | AD14: 49.458381 | AE14: 59.539585 | AF14: 26.167902 | AG14: 32.485815 | AH14: 31.195026 | AJ14: 49.446021 | AK14: 52.242706 | AL14: 14.946606 | AM14: 36.943752 | AN14: 6.5482095 | AO14: 49.736466 | AP14: 61.486397 | AX14: 18.33 | AY14: 44.329788 | AZ14: 72.920081 | BA14: -13.454414 | BB14: 620.83394 | BC14: 608.38993
A15: 1991Q3 | B15: 105.40232 | C15: 108.9886 | D15: 50.737314 | E15: 64.27598 | F15: -5.9988232 | G15: -0.15490388 | H15: 8.0522684 | I15: 7.4189562 | J15: 25.319556 | K15: 11.350167 | L15: 12.851402 | M15: 29.226159 | N15: 20.828689 | P15: 3.9717112 | Q15: 49.175219 | R15: 58.240522 | S15: 43.865126 | T15: 59.378974 | U15: 50.447177 | V15: 59.840195 | W15: 51.105778 | X15: 60.172062 | Y15: 3872.61 | Z15: 23.386984 | AA15: 31.50917 | AB15: 30.64075 | AC15: 32.313589 | AD15: 50.016138 | AE15: 59.906659 | AF15: 26.346602 | AG15: 32.954794 | AH15: 31.570362 | AJ15: 48.005646 | AK15: 52.242706 | AL15: 15.529641 | AM15: 37.938395 | AN15: 6.928802 | AO15: 50.402624 | AP15: 62.179646 | AX15: 19.423333 | AY15: 47.03393 | AZ15: 71.59588 | BA15: -15.733423 | BB15: 636.04746 | BC15: 621.23164
A16: 1991Q4 | B16: 100.04477 | C16: 99.591284 | D16: 50.817804 | E16: 64.222788 | F16: 6.3305686 | G16: 0.15824233 | H16: 7.5008702 | I16: 6.7312866 | J16: 26.040758 | K16: 11.56187 | L16: 13.443819 | M16: 30.888271 | N16: 22.173155 | P16: 4.043199 | Q16: 49.389551 | R16: 58.475583 | S16: 44.024761 | T16: 59.480259 | U16: 50.755856 | V16: 60.145983 | W16: 51.264521 | X16: 60.402676 | Y16: 4000.5532 | Z16: 24.004902 | AA16: 32.11125 | AB16: 31.073851 | AC16: 32.487908 | AD16: 50.258247 | AE16: 60.147382 | AF16: 27.076521 | AG16: 33.726313 | AH16: 32.165116 | AJ16: 50.707911 | AK16: 52.242706 | AL16: 16.260367 | AM16: 39.240951 | AN16: 7.4683642 | AO16: 51.012675 | AP16: 62.8095 | AX16: 19.866667 | AY16: 46.499278 | AZ16: 69.219185 | BA16: -7.3196917 | BB16: 657.83602 | BC16: 651.59333
A17: 1992Q1 | B17: 98.883867 | C17: 97.636527 | D17: 50.970213 | E17: 63.95163 | F17: -0.55699872 | G17: -0.01376483 | H17: 7.3377428 | I17: 6.1356179 | J17: 25.969368 | K17: 11.738885 | L17: 14.005233 | M17: 29.051359 | N17: 21.988755 | P17: 4.235292 | Q17: 49.707166 | R17: 59.080594 | S17: 44.474776 | T17: 59.642454 | U17: 51.303559 | V17: 60.674661 | W17: 51.700956 | X17: 60.877891 | Y17: 4046.5353 | Z17: 24.410789 | AA17: 32.417886 | AB17: 31.535796 | AC17: 33.26623 | AD17: 50.700822 | AE17: 60.594367 | AF17: 27.734928 | AG17: 34.368537 | AH17: 32.847723 | AI17: 50.731816 | AJ17: 45.531943 | AK17: 52.242706 | AL17: 19.520497 | AM17: 40.405256 | AN17: 10.328507 | AO17: 51.54993 | AP17: 63.368479 | AQ17: 68.228817 | AR17: 47.829402 | AU17: 55.064845 | AV17: 51.653864 | AW17: 44.4642 | AX17: 17.506667 | AY17: 40.826794 | AZ17: 67.992599 | BA17: -6.7463757 | BB17: 672.00505 | BC17: 666.18998
A18: 1992Q2 | B18: 103.85662 | C18: 106.58647 | D18: 51.038083 | E18: 64.189 | F18: -8.1588637 | G18: -0.19927004 | H18: 7.3622655 | I18: 5.7340045 | J18: 24.879787 | K18: 11.858085 | L18: 14.372014 | M18: 28.651934 | N18: 21.559301 | P18: 4.2989204 | Q18: 50.248779 | R18: 59.453362 | S18: 45.318427 | T18: 60.572698 | U18: 51.70608 | V18: 61.045247 | W18: 52.095497 | X18: 61.242742 | Y18: 4094.3756 | Z18: 24.941736 | AA18: 32.955228 | AB18: 32.136411 | AC18: 33.454474 | AD18: 51.251135 | AE18: 61.067545 | AF18: 27.770895 | AG18: 34.506094 | AH18: 33.058597 | AI18: 52.220999 | AJ18: 41.181354 | AK18: 51.725258 | AL18: 21.303963 | AM18: 41.655352 | AN18: 11.881795 | AO18: 52.122006 | AP18: 63.959788 | AQ18: 66.779779 | AR18: 48.653229 | AU18: 54.622327 | AV18: 54.199501 | AW18: 48.747539 | AX18: 19.683333 | AY18: 45.857339 | AZ18: 72.528259 | BA18: -13.827279 | BB18: 690.05847 | BC18: 676.91339
A19: 1992Q3 | B19: 100.93323 | C19: 101.15397 | D19: 51.060217 | E19: 64.541654 | F19: -12.519936 | G19: -0.29603088 | H19: 6.8119417 | I19: 5.2009416 | J19: 25.090362 | K19: 12.012471 | L19: 14.851905 | M19: 29.106346 | N19: 22.245608 | P19: 4.2712 | Q19: 50.733559 | R19: 59.91778 | S19: 45.659699 | T19: 60.681714 | U19: 52.226489 | V19: 61.564755 | W19: 52.609751 | X19: 61.757173 | Y19: 4229.267 | Z19: 25.162273 | AA19: 33.124311 | AB19: 32.319471 | AC19: 33.829943 | AD19: 51.586703 | AE19: 61.447461 | AF19: 28.412891 | AG19: 35.081155 | AH19: 33.524871 | AI19: 52.702734 | AJ19: 41.845637 | AK19: 49.138015 | AL19: 23.027261 | AM19: 42.909358 | AN19: 13.432753 | AO19: 52.640988 | AP19: 64.4507 | AQ19: 65.123837 | AR19: 50.141161 | AU19: 54.133223 | AV19: 61.388955 | AW19: 50.633568 | AX19: 19.996667 | AY19: 44.615931 | AZ19: 72.227941 | BA19: -11.471184 | BB19: 721.87484 | BC19: 710.40366
A20: 1992Q4 | B20: 102.33896 | C20: 104.14419 | D20: 51.187015 | E20: 64.680283 | F20: -7.9097396 | G20: -0.18856099 | H20: 6.7309871 | I20: 4.8720293 | J20: 25.648165 | K20: 12.178758 | L20: 15.354187 | M20: 29.420044 | N20: 23.843613 | P20: 4.270111 | Q20: 51.279695 | R20: 60.348071 | S20: 46.04224 | T20: 60.893651 | U20: 52.542999 | V20: 61.879444 | W20: 52.900559 | X20: 62.059262 | Y20: 4194.7911 | Z20: 25.808859 | AA20: 33.644294 | AB20: 32.775308 | AC20: 34.517759 | AD20: 51.825889 | AE20: 61.727352 | AF20: 29.160345 | AG20: 35.700995 | AH20: 34.211445 | AI20: 51.095287 | AJ20: 46.601668 | AK20: 46.462571 | AL20: 25.070438 | AM20: 44.385589 | AN20: 15.414476 | AO20: 53.191377 | AP20: 65.006593 | AQ20: 63.174161 | AR20: 44.892083 | AU20: 52.254426 | AV20: 65.947681 | AW20: 49.418622 | AX20: 18.956667 | AY20: 43.745614 | AZ20: 72.125898 | BA20: -9.5389812 | BB20: 705.7245 | BC20: 696.18552
A21: 1993Q1 | B21: 103.28358 | C21: 105.50307 | D21: 51.456025 | E21: 65.206656 | F21: -5.7889336 | G21: -0.13270668 | H21: 6.2886614 | I21: 4.5051941 | J21: 27.216309 | K21: 12.521533 | L21: 16.261236 | M21: 31.640155 | N21: 25.823279 | P21: 4.9578331 | Q21: 52.38473 | R21: 61.180688 | S21: 47.257362 | T21: 61.643774 | U21: 53.058638 | V21: 62.276622 | W21: 53.425308 | X21: 62.454339 | Y21: 4362.2022 | Z21: 26.773131 | AA21: 34.484987 | AB21: 33.599607 | AC21: 35.084701 | AD21: 52.43743 | AE21: 62.118957 | AF21: 30.676384 | AG21: 36.882946 | AH21: 35.402158 | AI21: 50.644328 | AJ21: 45.135889 | AK21: 44.024943 | AL21: 27.077135 | AM21: 46.239148 | AN21: 17.395715 | AO21: 53.802632 | AP21: 65.551842 | AQ21: 65.013755 | AR21: 43.882471 | AU21: 53.071062 | AV21: 63.018192 | AW21: 47.13412 | AX21: 17.99 | AY21: 42.3372 | AZ21: 76.160493 | BA21: -0.13737414 | BB21: 688.28771 | BC21: 688.15033
A22: 1993Q2 | B22: 101.70071 | C22: 102.80689 | D22: 51.759427 | E22: 65.620864 | F22: -18.902314 | G22: -0.41735363 | H22: 6.1333659 | I22: 4.2824862 | J22: 28.614134 | K22: 17.900804 | L22: 17.405939 | M22: 33.813582 | N22: 27.905879 | P22: 4.9799711 | Q22: 52.955516 | R22: 61.602848 | S22: 47.947664 | T22: 62.104034 | U22: 53.561063 | V22: 62.636205 | W22: 53.903603 | X22: 62.798067 | Y22: 4529.0881 | Z22: 27.350709 | AA22: 35.007546 | AB22: 34.097449 | AC22: 35.840682 | AD22: 53.043257 | AE22: 62.557418 | AF22: 30.629767 | AG22: 36.913983 | AH22: 35.596648 | AI22: 51.610714 | AJ22: 42.162183 | AK22: 43.073674 | AL22: 29.623242 | AM22: 48.860628 | AN22: 20.209737 | AO22: 54.479092 | AP22: 66.17047 | AQ22: 66.540142 | AR22: 40.780315 | AU22: 54.410937 | AV22: 65.690285 | AW22: 47.560264 | AX22: 17.993333 | AY22: 41.253286 | AZ22: 86.622907 | BA22: -3.2751474 | BB22: 718.27794 | BC22: 715.00279
A23: 1993Q3 | B23: 101.37593 | C23: 102.20039 | D23: 52.10847 | E23: 65.993367 | F23: -18.38323 | G23: -0.39848368 | H23: 5.6764784 | I23: 4.246356 | J23: 29.842721 | K23: 21.897411 | L23: 18.632359 | M23: 35.582017 | N23: 30.294617 | P23: 4.9859578 | Q23: 53.612658 | R23: 62.208647 | S23: 48.548322 | T23: 62.424253 | U23: 54.00852 | V23: 62.988877 | W23: 54.326158 | X23: 63.136903 | Y23: 4613.2957 | Z23: 28.398042 | AA23: 35.798385 | AB23: 34.745763 | AC23: 36.287346 | AD23: 53.586082 | AE23: 62.95204 | AF23: 31.106428 | AG23: 37.22398 | AH23: 35.96091 | AI23: 50.169321 | AJ23: 50.310757 | AK23: 43.073674 | AL23: 33.020855 | AM23: 52.204397 | AN23: 24.321191 | AO23: 55.107824 | AP23: 66.692189 | AQ23: 65.741628 | AR23: 39.651704 | AU23: 54.181431 | AV23: 65.329983 | AW23: 44.365908 | AX23: 16.2 | AY23: 37.405873 | AZ23: 85.740496 | BA23: -0.9280207 | BB23: 719.4434 | BC23: 718.51538
A24: 1993Q4 | B24: 104.09099 | C24: 106.88906 | D24: 52.795506 | E24: 66.506168 | F24: -22.242136 | G24: -0.47595198 | H24: 5.396311 | I24: 4.0308559 | J24: 31.980782 | K24: 22.915175 | L24: 25.702131 | M24: 37.688247 | N24: 33.521877 | P24: 4.9895965 | Q24: 54.39721 | R24: 63.01843 | S24: 49.633712 | T24: 63.570415 | U24: 54.618373 | V24: 63.642574 | W24: 54.922415 | X24: 63.784469 | Y24: 4673.189 | Z24: 29.19429 | AA24: 36.793748 | AB24: 35.637924 | AC24: 36.775133 | AD24: 54.233206 | AE24: 63.650822 | AF24: 31.96819 | AG24: 37.997081 | AH24: 36.678928 | AI24: 49.13424 | AJ24: 54.312888 | AK24: 42.944312 | AL24: 36.627997 | AM24: 55.444831 | AN24: 29.102519 | AO24: 55.68689 | AP24: 67.220069 | AQ24: 66.977366 | AR24: 37.491932 | AU24: 54.302194 | AV24: 63.126565 | AW24: 41.658927 | AX24: 14.963333 | AY24: 34.768052 | AZ24: 83.352583 | BA24: 2.0472488 | BB24: 733.10339 | BC24: 735.15063
A25: 1994Q1 | B25: 107.27148 | C25: 107.3545 | D25: 53.601973 | E25: 67.352393 | F25: -8.9315559 | G25: -0.19016194 | H25: 6.0862052 | I25: 3.9692599 | J25: 31.719941 | K25: 26.998908 | L25: 26.418419 | M25: 37.403979 | N25: 33.964043 | P25: 5.317353 | Q25: 54.757301 | R25: 63.567442 | S25: 50.412085 | T25: 64.22534 | U25: 55.303131 | V25: 64.409459 | W25: 55.60729 | X25: 64.550487 | Y25: 4696.8156 | Z25: 29.714035 | AA25: 37.749846 | AB25: 36.603148 | AC25: 37.815973 | AD25: 54.979944 | AE25: 64.474649 | AF25: 32.423018 | AG25: 38.822519 | AH25: 37.370013 | AI25: 50.282822 | AJ25: 54.613994 | AK25: 42.716948 | AL25: 39.558836 | AM25: 57.599749 | AN25: 33.071157 | AO25: 56.291453 | AP25: 67.691988 | AQ25: 70.659261 | AR25: 41.210151 | AU25: 57.408866 | AV25: 63.361327 | AW25: 39.975184 | AX25: 13.87 | AY25: 32.400629 | AZ25: 87.670608 | BA25: -2.4439925 | BB25: 749.68625 | BC25: 747.24225
A26: 1994Q2 | B26: 108.78786 | C26: 109.62817 | D26: 54.70511 | E26: 68.757297 | F26: -13.87402 | G26: -0.28658773 | H26: 6.9594424 | I26: 4.3601309 | J26: 31.767208 | K26: 27.577798 | L26: 26.863127 | M26: 37.903152 | N26: 34.995558 | P26: 5.2586965 | Q26: 55.30653 | R26: 64.080239 | S26: 51.502182 | T26: 65.395034 | U26: 55.922723 | V26: 64.974598 | W26: 56.199111 | X26: 65.101822 | Y26: 4841.1076 | Z26: 30.808043 | AA26: 38.956784 | AB26: 37.920106 | AC26: 38.664271 | AD26: 55.586186 | AE26: 65.132176 | AF26: 33.980877 | AG26: 40.050873 | AH26: 38.598788 | AI26: 52.232472 | AJ26: 73.330981 | AK26: 43.818486 | AL26: 42.837971 | AM26: 59.648523 | AN26: 38.038283 | AO26: 56.867237 | AP26: 68.188581 | AQ26: 69.144028 | AR26: 44.029156 | AU26: 58.609812 | AV26: 57.867371 | AW26: 43.007813 | AX26: 16.27 | AY26: 37.247286 | AZ26: 96.131796 | BA26: 1.4201055 | BB26: 797.51042 | BC26: 798.93053
A27: 1994Q3 | B27: 107.85237 | C27: 109.41571 | D27: 55.748458 | E27: 69.829727 | F27: -11.437137 | G27: -0.22712719 | H27: 7.5206977 | I27: 4.6276801 | J27: 33.978356 | K27: 28.158165 | L27: 27.85068 | M27: 40.162714 | N27: 36.801173 | P27: 5.2480264 | Q27: 56.128652 | R27: 64.758026 | S27: 52.255412 | T27: 66.180033 | U27: 56.634995 | V27: 65.657659 | W27: 56.883526 | X27: 65.770746 | Y27: 5035.565 | Z27: 31.637741 | AA27: 39.930079 | AB27: 38.773522 | AC27: 39.729414 | AD27: 56.167379 | AE27: 65.692271 | AF27: 35.040536 | AG27: 41.213674 | AH27: 39.588877 | AI27: 53.91198 | AJ27: 118.69993 | AK27: 45.865544 | AL27: 45.176338 | AM27: 61.148659 | AN27: 40.890376 | AO27: 57.490943 | AP27: 68.697638 | AQ27: 67.821314 | AR27: 48.093674 | AU27: 60.666079 | AV27: 56.124686 | AW27: 44.142348 | AX27: 17.05 | AY27: 37.902343 | AZ27: 96.457375 | BA27: -3.3813787 | BB27: 845.66779 | BC27: 842.28642
A28: 1994Q4 | B28: 109.9953 | C28: 111.51628 | D28: 56.956952 | E28: 71.301774 | F28: -28.986087 | G28: -0.56370965 | H28: 7.8541827 | I28: 5.0660336 | J28: 33.331333 | K28: 28.576711 | L28: 27.972456 | M28: 38.558486 | N28: 35.743483 | P28: 5.0784233 | Q28: 56.817735 | R28: 65.359892 | S28: 53.455595 | T28: 67.249669 | U28: 57.345192 | V28: 66.284697 | W28: 57.56994 | X28: 66.384972 | Y28: 5142.0242 | Z28: 33.477235 | AA28: 41.550376 | AB28: 40.398274 | AC28: 40.522081 | AD28: 56.888589 | AE28: 66.342279 | AF28: 36.310414 | AG28: 42.35062 | AH28: 40.796405 | AI28: 54.580459 | AJ28: 105.66132 | AK28: 48.454747 | AL28: 47.089031 | AM28: 62.235434 | AN28: 43.450604 | AO28: 58.135099 | AP28: 69.219334 | AQ28: 68.562837 | AR28: 55.404847 | AU28: 62.153231 | AV28: 54.790314 | AW28: 43.626638 | AX28: 16.603333 | AY28: 36.697972 | AZ28: 95.652185 | BA28: -10.495864 | BB28: 895.80915 | BC28: 885.31328
... A38: 1997Q2 | B38: 116.06652 | C38: 117.89883 | D38: 63.357631 | E38: 77.818757 | F38: 0.52341606 | G38: 0.0069140625 | H38: 5.8706682 | I38: 5.58432 | J38: 57.456233 | K38: 34.870722 | L38: 33.329097 | M38: 56.54891 | N38: 58.313681 | P38: 5.6105066 | Q38: 61.764066 | R38: 70.040299 | S38: 59.632372 | T38: 74.305234 | U38: 62.887893 | V38: 71.76666 | W38: 62.899902 | X38: 71.78101 | Y38: 7570.3113 | Z38: 41.547776 | AA38: 50.845788 | AB38: 49.859182 | AC38: 44.357988 | AD38: 61.870472 | AE38: 71.416414 | AF38: 45.613633 | AG38: 52.553432 | AH38: 50.645277 | AI38: 56.892477 | AJ38: 96.610058 | AK38: 50.423874 | AL38: 58.564063 | AM38: 69.592334 | AN38: 57.342509 | AO38: 66.717359 | AP38: 75.665273 | AQ38: 72.986216 | AR38: 52.592666 | AU38: 62.24462 | AV38: 66.16305 | AW38: 49.150741 | AX38: 18.49 | AY38: 43.384475 | AZ38: 90.148852 | BA38: -5.0194138 | BB38: 1082.1384 | BC38: 1077.119
A39: 1997Q3 | B39: 116.74654 | C39: 118.75788 | D39: 64.320185 | E39: 78.960612 | F39: -2.0100424 | G39: -0.026580674 | H39: 5.4684462 | I39: 5.5469793 | J39: 58.327669 | K39: 35.514006 | L39: 33.913264 | M39: 57.365629 | N39: 60.551396 | P39: 5.5914841 | Q39: 62.460022 | R39: 70.668505 | S39: 60.546939 | T39: 75.3007 | U39: 63.517771 | V39: 72.398492 | W39: 63.527267 | X39: 72.411293 | Y39: 7562.0446 | Z39: 42.778286 | AA39: 52.13647 | AB39: 51.1386 | AC39: 44.897648 | AD39: 62.495887 | AE39: 72.04954 | AF39: 46.698594 | AG39: 53.561238 | AH39: 51.478765 | AI39: 55.421054 | AJ39: 86.421071 | AK39: 49.790313 | AL39: 59.357239 | AM39: 70.170165 | AN39: 58.179666 | AO39: 67.430375 | AP39: 76.167763 | AQ39: 69.525948 | AR39: 51.426611 | AS39: 55.065976 | AT39: 55.030458 | AU39: 59.157591 | AV39: 68.77176 | AW39: 50.016249 | AX39: 18.656667 | AY39: 44.372457 | AZ39: 85.728892 | BA39: -3.3739371 | BB39: 1094.6884 | BC39: 1091.3144
A40: 1997Q4 | B40: 117.00344 | C40: 119.18052 | D40: 64.947609 | E40: 79.56948 | F40: -5.6756858 | G40: -0.075168145 | H40: 5.1664437 | I40: 5.8805319 | J40: 54.710325 | K40: 36.229611 | L40: 34.526461 | M40: 52.501067 | N40: 57.750608 | O40: 98.076323 | P40: 5.5068026 | Q40: 63.052588 | R40: 71.230959 | S40: 61.03468 | T40: 75.921291 | U40: 64.135767 | V40: 72.978584 | W40: 64.143883 | X40: 72.9903 | Y40: 7550.653 | Z40: 43.847486 | AA40: 52.869778 | AB40: 51.762054 | AC40: 45.31877 | AD40: 63.104429 | AE40: 72.604537 | AF40: 47.456861 | AG40: 54.306939 | AH40: 52.430769 | AI40: 55.064417 | AJ40: 83.096329 | AK40: 46.139714 | AL40: 60.254975 | AM40: 70.757039 | AN40: 59.158614 | AO40: 68.365906 | AP40: 76.805074 | AQ40: 71.183447 | AR40: 47.113442 | AS40: 55.395096 | AT40: 55.143188 | AU40: 58.123292 | AV40: 71.967076 | AW40: 50.639834 | AX40: 18.84 | AY40: 44.710486 | AZ40: 78.368998 | BA40: -7.4285188 | BB40: 1102.5811 | BC40: 1095.1526
A41: 1998Q1 | B41: 117.86997 | C41: 120.14502 | D41: 65.00531 | E41: 79.614797 | F41: -17.495168 | G41: -0.23656288 | H41: 4.9268845 | I41: 7.5025992 | J41: 62.887991 | K41: 37.011363 | L41: 35.048926 | M41: 59.483327 | N41: 66.116118 | O41: 97.777116 | P41: 5.7769488 | Q41: 62.912367 | R41: 71.259276 | S41: 61.229445 | T41: 76.239318 | U41: 64.1545 | V41: 73.0338 | W41: 64.189987 | X41: 73.062341 | Y41: 7395.5678 | Z41: 45.008628 | AA41: 53.971502 | AB41: 51.931365 | AC41: 45.26905 | AD41: 63.050769 | AE41: 72.690152 | AF41: 48.24563 | AG41: 54.786955 | AH41: 52.739682 | AI41: 50.312652 | AJ41: 86.91413 | AK41: 43.958354 | AL41: 61.257117 | AM41: 71.366555 | AN41: 60.196032 | AO41: 69.359294 | AP41: 77.44653 | AQ41: 71.151517 | AR41: 43.564611 | AS41: 53.619136 | AT41: 53.319337 | AU41: 57.183802 | AV41: 62.054169 | AW41: 40.37371 | AX41: 14.163333 | AY41: 34.089059 | AZ41: 73.781556 | BA41: 0.0060578 | BB41: 1069.1512 | BC41: 1069.1573
A42: 1998Q2 | B42: 118.58326 | C42: 121.11069 | D42: 65.070542 | E42: 79.47373 | F42: -16.556712 | G42: -0.22308394 | H42: 4.8081629 | I42: 7.74913 | J42: 61.386447 | K42: 37.779791 | L42: 35.642676 | M42: 57.039275 | N42: 64.101919 | O42: 96.692683 | P42: 5.8940142 | Q42: 63.710218 | R42: 71.96753 | S42: 61.329199 | T42: 76.607637 | U42: 64.39067 | V42: 73.323314 | W42: 64.43753 | X42: 73.358899 | Y42: 7421.7408 | Z42: 45.117562 | AA42: 54.090081 | AB42: 51.826076 | AC42: 45.943237 | AD42: 63.353917 | AE42: 73.027108 | AF42: 47.791331 | AG42: 54.560474 | AH42: 52.272622 | AI42: 49.848742 | AJ42: 79.300967 | AK42: 43.046364 | AL42: 62.094043 | AM42: 71.879836 | AN42: 61.104438 | AO42: 70.354407 | AP42: 78.037749 | AQ42: 73.086735 | AR42: 42.225152 | AS42: 52.746362 | AT42: 52.395166 | AU42: 57.802875 | AV42: 60.101426 | AW42: 38.343293 | AX42: 13.28 | AY42: 32.111445 | AZ42: 72.865114 | BA42: 1.2735368 | BB42: 1051.9626 | BC42: 1053.2362
A43: 1998Q3 | B43: 117.46068 | C43: 119.89665 | D43: 65.098642 | E43: 79.478529 | F43: -21.076306 | G43: -0.28514051 | H43: 4.5044982 | I43: 8.9280128 | J43: 50.862811 | K43: 38.433772 | L43: 36.154053 | M43: 48.658626 | N43: 53.530388 | O43: 96.490753 | P43: 5.910443 | Q43: 64.419775 | R43: 72.693107 | S43: 61.772898 | T43: 77.357677 | U43: 64.732013 | V43: 73.783837 | W43: 64.792801 | X43: 73.828247 | Y43: 7391.551 | Z43: 44.861609 | AA43: 54.247753 | AB43: 51.41945 | AC43: 46.428425 | AD43: 63.535709 | AE43: 73.459515 | AF43: 48.533815 | AG43: 54.790961 | AH43: 52.406234 | AI43: 46.704414 | AJ43: 72.218148 | AK43: 40.319462 | AL43: 63.309242 | AM43: 72.53254 | AN43: 62.458647 | AO43: 71.396233 | AP43: 78.635873 | AQ43: 66.993627 | AR43: 40.096272 | AS43: 50.473244 | AT43: 50.108467 | AU43: 53.678919 | AV43: 55.349863 | AW43: 36.615972 | AX43: 13.003333 | AY43: 31.447843 | AZ43: 70.101985 | BA43: 0.4381368 | BB43: 1032.5707 | BC43: 1033.0089
A44: 1998Q4 | B44: 113.83154 | C44: 117.03749 | D44: 65.40845 | E44: 79.654185 | F44: -24.844116 | G44: -0.3189453 | H44: 4.0458849 | I44: 7.4180618 | J44: 59.083448 | K44: 39.390522 | L44: 36.973789 | M44: 59.73604 | N44: 63.314726 | O44: 91.164035 | P44: 5.9009699 | Q44: 64.512305 | R44: 73.068351 | S44: 61.852459 | T44: 77.900835 | U44: 65.30301 | V44: 74.404544 | W44: 65.367478 | X44: 74.451143 | Y44: 7789.46 | Z44: 44.432107 | AA44: 54.378245 | AB44: 51.271346 | AC44: 47.336275 | AD44: 64.142846 | AE44: 74.190801 | AF44: 48.508017 | AG44: 55.045089 | AH44: 52.699654 | AI44: 45.28768 | AJ44: 70.78806 | AK44: 39.422316 | AL44: 64.777684 | AM44: 73.376711 | AN44: 64.006725 | AO44: 72.979953 | AP44: 79.362209 | AQ44: 67.109746 | AR44: 38.253864 | AS44: 47.489751 | AT44: 47.359723 | AU44: 53.062905 | AV44: 52.310551 | AW44: 34.041018 | AX44: 11.85 | AY44: 27.468552 | AZ44: 68.594988 | BA44: 0.8463912 | BB44: 1054.3734 | BC44: 1055.2198
A45: 1999Q1 | B45: 115.1168 | C45: 119.37603 | D45: 66.086884 | E45: 80.420753 | F45: -44.964606 | G45: -0.58431556 | H45: 4.30392 | I45: 5.8591847 | J45: 65.382372 | K45: 40.079624 | L45: 38.085259 | M45: 62.673719 | N45: 69.195037 | O45: 91.925607 | P45: 6.1930905 | Q45: 65.4856 | R45: 73.832662 | S45: 62.168444 | T45: 78.289912 | U45: 65.837487 | V45: 74.840694 | W45: 65.889406 | X45: 74.879659 | Y45: 7695.2608 | Z45: 44.858827 | AA45: 55.161241 | AB45: 51.846529 | AC45: 48.547818 | AD45: 64.744007 | AE45: 74.721129 | AF45: 48.704807 | AG45: 55.282993 | AH45: 53.0429 | AI45: 43.577208 | AJ45: 66.978686 | AK45: 38.783476 | AL45: 65.50583 | AM45: 73.798799 | AN45: 64.854515 | AO45: 73.696272 | AP45: 79.799965 | AQ45: 63.131155 | AR45: 36.87191 | AS45: 49.991232 | AT45: 50.076621 | AU45: 50.883877 | AV45: 49.435003 | AW45: 33.008298 | AX45: 11.643333 | AY45: 27.325469 | AZ45: 70.010596 | BA45: -23.807876 | BB45: 1053.6226 | BC45: 1029.8148
A46: 1999Q2 | B46: 116.57227 | C46: 120.835 | D46: 67.009715 | E46: 81.181855 | F46: -34.430546 | G46: -0.45135419 | H46: 4.5455102 | I46: 5.0709603 | J46: 73.648655 | K46: 40.947443 | L46: 39.000316 | M46: 69.054998 | N46: 77.306735 | O46: 91.101485 | P46: 6.1537895 | Q46: 66.127168 | R46: 74.548323 | S46: 63.110807 | T46: 79.332377 | U46: 66.487827 | V46: 75.435941 | W46: 66.528758 | X46: 75.468302 | Y46: 7628.2766 | Z46: 46.131572 | AA46: 56.56245 | AB46: 53.452127 | AC46: 49.442105 | AD46: 65.528507 | AE46: 75.392705 | AF46: 49.321184 | AG46: 56.139748 | AH46: 53.894594 | AI46: 46.738513 | AJ46: 60.791796 | AK46: 38.115968 | AL46: 66.204673 | AM46: 74.303437 | AN46: 65.623862 | AO46: 74.298722 | AP46: 80.221056 | AQ46: 61.417138 | AR46: 39.258281 | AS46: 52.663726 | AT46: 52.711832 | AU46: 50.130971 | AV46: 55.833913 | AW46: 41.831411 | AX46: 16.03 | AY46: 38.578353 | AZ46: 70.653989 | BA46: -32.357248 | BB46: 1077.7655 | BC46: 1045.4082
A47: 1999Q3 | B47: 116.58872 | C47: 120.65954 | D47: 68.104372 | E47: 82.398093 | F47: -47.164832 | G47: -0.60600866 | H47: 5.0252919 | I47: 4.8200446 | J47: 71.071066 | K47: 41.707872 | L47: 39.759653 | M47: 67.988862 | N47: 74.339988 | O47: 90.793812 | P47: 6.0846694 | Q47: 66.678917 | R47: 75.260885 | S47: 63.828781 | T47: 80.30056 | U47: 67.295614 | V47: 76.3051 | W47: 67.336521 | X47: 76.337386 | Y47: 7782.8644 | Z47: 47.434504 | AA47: 58.165438 | AB47: 55.018014 | AC47: 50.38588 | AD47: 66.116644 | AE47: 76.143452 | AF47: 51.293454 | AG47: 58.054977 | AH47: 55.935878 | AI47: 50.365907 | AJ47: 54.650712 | AK47: 36.581733 | AL47: 66.95205 | AM47: 74.861891 | AN47: 66.440782 | AO47: 74.839227 | AP47: 80.618662 | AQ47: 60.133058 | AR47: 43.441775 | AS47: 54.734197 | AT47: 54.737567 | AU47: 49.796608 | AV47: 63.302413 | AW47: 51.189383 | AX47: 20.443333 | AY47: 48.725894 | AZ47: 70.689782 | BA47: -31.198158 | BB47: 1131.4546 | BC47: 1100.2565
A48: 1999Q4 | B48: 117.29515 | C48: 121.23453 | D48: 69.482043 | E48: 83.982385 | F48: -55.894931 | G48: -0.69767911 | H48: 5.2040297 | I48: 4.9723817 | J48: 84.742722 | K48: 42.594125 | L48: 41.221036 | M48: 81.800515 | N48: 90.14852 | O48: 90.619955 | P48: 5.9845935 | Q48: 67.69708 | R48: 76.177337 | S48: 64.722822 | T48: 81.108559 | U48: 68.313427 | V48: 77.3522 | W48: 68.350479 | X48: 77.382079 | Y48: 8011.5528 | Z48: 49.007056 | AA48: 59.963632 | AB48: 56.907996 | AC48: 51.528706 | AD48: 67.071702 | AE48: 77.170714 | AF48: 53.191166 | AG48: 59.970634 | AH48: 57.806448 | AI48: 53.957226 | AJ48: 60.017196 | AK48: 35.769861 | AL48: 67.658733 | AM48: 75.425728 | AN48: 67.22651 | AO48: 75.539359 | AP48: 81.113709 | AQ48: 60.251134 | AR48: 45.986144 | AS48: 57.160647 | AT48: 57.060071 | AU48: 51.361151 | AV48: 67.638583 | AW48: 57.712382 | AX48: 23.806667 | AY48: 55.977589 | AZ48: 72.781576 | BA48: -33.485644 | BB48: 1193.4022 | BC48: 1159.9166
A49: 2000Q1 | B49: 118.4264 | C49: 123.64278 | D49: 70.535514 | E49: 84.991837 | F49: -67.774692 | G49: -0.8434948 | H49: 5.4509211 | I49: 5.1069292 | J49: 87.116989 | K49: 43.374835 | L49: 41.854333 | M49: 82.953727 | N49: 92.665396 | O49: 90.337286 | P49: 6.0615046 | Q49: 68.728171 | R49: 77.209763 | S49: 66.405659 | T49: 82.895849 | U49: 69.21508 | V49: 78.209604 | W49: 69.241742 | X49: 78.233979 | Y49: 8034.9863 | Z49: 51.16643 | AA49: 61.948651 | AB49: 58.987277 | AC49: 52.395222 | AD49: 68.065675 | AE49: 78.069103 | AF49: 54.935087 | AG49: 61.785268 | AH49: 59.65336 | AI49: 58.059386 | AJ49: 52.952902 | AK49: 36.22532 | AL49: 68.357769 | AM49: 76.029687 | AN49: 67.996224 | AO49: 76.19478 | AP49: 81.572184 | AQ49: 61.859577 | AR49: 49.768508 | AS49: 55.955602 | AT49: 55.946165 | AU49: 52.971489 | AV49: 79.369951 | AW49: 65.418899 | AX49: 26.616667 | AY49: 63.799923 | AZ49: 74.002809 | BA49: -56.388599 | BB49: 1252.9883 | BC49: 1196.5997
A50: 2000Q2 | B50: 118.18194 | C50: 123.2934 | D50: 72.080807 | E50: 86.616305 | F50: -65.257197 | G50: -0.81442377 | H50: 5.2424959 | I50: 5.4373188 | J50: 83.034268 | K50: 44.062132 | L50: 42.331515 | M50: 79.700635 | N50: 90.176504 | O50: 89.866301 | P50: 5.8810785 | Q50: 69.270367 | R50: 77.764006 | S50: 67.284042 | T50: 83.896339 | U50: 70.0574 | V50: 79.106542 | W50: 70.087869 | X50: 79.132738 | Y50: 8012.6833 | Z50: 52.296049 | AA50: 63.701689 | AB50: 60.602382 | AC50: 53.106271 | AD50: 68.842043 | AE50: 78.914605 | AF50: 56.497747 | AG50: 63.592947 | AH50: 61.50444 | AI50: 59.760518 | AJ50: 49.023264 | AK50: 38.323365 | AL50: 69.150166 | AM50: 76.545762 | AN50: 68.855223 | AO50: 76.733801 | AP50: 81.954061 | AQ50: 64.276696 | AR50: 47.798111 | AS50: 55.690028 | AT50: 55.796617 | AU50: 53.63432 | AV50: 95.560348 | AW50: 68.621905 | AX50: 26.766667 | AY50: 65.429664 | AZ50: 75.650981 | BA50: -66.873584 | BB50: 1289.9729 | BC50: 1223.0993
A51: 2000Q3 | B51: 118.54483 | C51: 123.72963 | D51: 72.869825 | E51: 87.265337 | F51: -74.212133 | G51: -0.92701383 | H51: 5.1509661 | I51: 5.6078442 | J51: 81.165884 | K51: 44.800095 | L51: 42.89767 | M51: 73.519838 | N51: 85.727476 | O51: 89.627413 | P51: 5.8105699 | Q51: 70.070867 | R51: 78.430645 | S51: 67.752954 | T51: 84.219804 | U51: 70.585794 | V51: 79.516129 | W51: 70.610941 | X51: 79.539179 | Y51: 8005.5044 | Z51: 54.556964 | AA51: 65.883441 | AB51: 62.749796 | AC51: 53.927422 | AD51: 69.466908 | AE51: 79.422497 | AF51: 57.81223 | AG51: 65.102602 | AH51: 63.151481 | AI51: 62.091962 | AJ51: 45.380846 | AK51: 39.58965 | AL51: 70.047583 | AM51: 77.26148 | AN51: 69.834922 | AO51: 77.34787 | AP51: 82.406502 | AQ51: 59.753272 | AR51: 48.058775 | AS51: 54.010513 | AT51: 54.33929 | AU51: 51.38867 | AV51: 112.15494 | AW51: 77.574 | AX51: 29.883333 | AY51: 74.065831 | AZ51: 72.450799 | BA51: -77.577853 | BB51: 1333.1423 | BC51: 1255.5644
... A125: 2019Q1 | B125: 110.27242 | C125: 113.83154 | D125: 131.75516 | E125: 123.45851 | F125: 138.7434 | G125: 0.70195473 | H125: 2.3651998 | I125: 3.0936183 | J125: 200.64177 | K125: 185.31279 | L125: 206.31406 | M125: 130.06357 | N125: 157.71566 | O125: 121.65005 | P125: 5.0896177 | Q125: 137.20525 | R125: 126.66053 | S125: 138.01169 | T125: 131.54782 | U125: 134.64187 | V125: 125.99628 | W125: 134.62621 | X125: 125.9752 | Y125: 19765.291 | Z125: 143.41154 | AA125: 137.70351 | AB125: 138.90572 | AC125: 79.493571 | AD125: 134.62852 | AE125: 125.52237 | AF125: 144.09549 | AG125: 139.15366 | AH125: 140.12614 | AI125: 118.97431 | AJ125: 82.964959 | AK125: 136.35597 | AL125: 169.40546 | AM125: 155.92198 | AN125: 42.660755 | AO125: 127.11993 | AP125: 121.6198 | AQ125: 100.24693 | AR125: 131.96216 | AS125: 51.630584 | AT125: 51.268454 | AU125: 107.29434 | AV125: 115.66248 | AW125: 135.86909 | AX125: 60.442111 | AY125: 140.93723 | AZ125: 103.96316 | BA125: -73.495145 | BB125: 3749.9007 | BC125: 3667.6399
A126: 2019Q2 | B126: 110.03162 | C126: 113.77837 | H126: 2.1648676 | I126: 3.2520302 | J126: 204.21063 | L126: 210.55166 | M126: 132.54105 | N126: 159.83665 | W126: 135.71429 | X126: 126.75431 | AI126: 119.8812 | AJ126: 82.366695 | AK126: 111.99523 | AL126: 171.45182 | AM126: 157.79211 | AN126: 44.270069 | AO126: 127.76444 | AP126: 122.18693 | AQ126: 100.2704 | AR126: 139.91578 | AS126: 50.171758 | AT126: 50.178944 | AU126: 109.0347 | AV126: 88.559553 | AW126: 135.57039 | AX126: 65.059208 | AY126: 152.49851 | AZ126: 104.73578
A127: 2019Q3 | W127: 136.92454 | X127: 127.66259 | AN127: 45.930484
A128: 2019Q4 | W128: 138.02959 | X128: 128.44555 | AN128: 47.56355
A129: 2020Q1 | W129: 139.24886 | X129: 129.36742 | AN129: 48.982035
A130: 2020Q2 | W130: 140.45782 | X130: 130.27635 | AN130: 50.567254
A131: 2020Q3 | W131: 141.64287 | X131: 131.16228 | AN131: 52.244041
A132: 2020Q4 | W132: 142.83555 | X132: 132.0499 | AN132: 53.864419

Sheet Sheet1

Sheet Commodity_Prices
A1: EcDatabase | B1: ID:PRIMARY_COMMODITY_PRICE_SYSTEM_LIVE | C1: ID:PRIMARY_COMMODITY_PRICE_SYSTEM_LIVE | D1: ID:PRIMARY_COMMODITY_PRICE_SYSTEM_LIVE | E1: ID:PRIMARY_COMMODITY_PRICE_SYSTEM_LIVE | F1: ID:PRIMARY_COMMODITY_PRICE_SYSTEM_LIVE | G1: ID:PRIMARY_COMMODITY_PRICE_SYSTEM_LIVE | H1: ID:PRIMARY_COMMODITY_PRICE_SYSTEM_LIVE | I1: ID:PRIMARY_COMMODITY_PRICE_SYSTEM_LIVE | J1: ID:PRIMARY_COMMODITY_PRICE_SYSTEM_LIVE | K1: ID:PRIMARY_COMMODITY_PRICE_SYSTEM_LIVE | L1: ID:PRIMARY_COMMODITY_PRICE_SYSTEM_LIVE | M1: ID:PRIMARY_COMMODITY_PRICE_SYSTEM_LIVE | N1: ID:PRIMARY_COMMODITY_PRICE_SYSTEM_LIVE | O1: ID:PRIMARY_COMMODITY_PRICE_SYSTEM_LIVE | P1: ID:PRIMARY_COMMODITY_PRICE_SYSTEM_LIVE | Q1: ID:PRIMARY_COMMODITY_PRICE_SYSTEM_LIVE | R1: ID:PRIMARY_COMMODITY_PRICE_SYSTEM_LIVE | S1: ID:PRIMARY_COMMODITY_PRICE_SYSTEM_LIVE | T1: ID:PRIMARY_COMMODITY_PRICE_SYSTEM_LIVE
A2: Series_code | B2: PALUM_USD.M | C2: PCOALAU_USD.M | D2: PCOALSA_USD.M | E2: PCOPP_USD.M | F2: PGOLD_USD.M | G2: PIORECR_USD.M | H2: PNGASEU_USD.M | I2: PNGASJP_USD.M | J2: PNGASUS_USD.M | K2: PNICK_USD.M | L2: POILBRE_USD.M | M2: POILDUB_USD.M | N2: POILWTI_USD.M | O2: PPALLA_USD.M | P2: PPLAT_USD.M | Q2: PSILVER_USD.M | R2: POILAPSP_USD.M | S2: PALLFNF_Index.M | T2: PFOOD_Index.M
A3: Commodity | B3: PALUM | C3: PCOALAU | D3: PCOALSA | E3: PCOPP | F3: PGOLD | G3: PIORECR | H3: PNGASEU | I3: PNGASJP | J3: PNGASUS | K3: PNICK | L3: POILBRE | M3: POILDUB | N3: POILWTI | O3: PPALLA | P3: PPLAT | Q3: PSILVER | R3: POILAPSP | S3: PALLFNF | T3: PFOOD
A4: Data Type | B4: USD | C4: USD | D4: USD | E4: USD | F4: USD | G4: USD | H4: USD | I4: USD | J4: USD | K4: USD | L4: USD | M4: USD | N4: USD | O4: USD | P4: USD | Q4: USD | R4: USD | S4: Index | T4: Index
A5: Frequency | B5: Monthly | C5: Monthly | D5: Monthly | E5: Monthly | F5: Monthly | G5: Monthly | H5: Monthly | I5: Monthly | J5: Monthly | K5: Monthly | L5: Monthly | M5: Monthly | N5: Monthly | O5: Monthly | P5: Monthly | Q5: Monthly | R5: Monthly | S5: Monthly | T5: Monthly
A6: Scale | B6: Units | C6: Units | D6: Units | E6: Units | F6: Units | G6: Units | H6: Units | I6: Units | J6: Units | K6: Units | L6: Units | M6: Units | N6: Units | O6: Units | P6: Units | Q6: Units | R6: Units | S6: Units | T6: Units
A7: Display_scale | B7: Units | C7: Units | D7: Units | E7: Units | F7: Units | G7: Units | H7: Units | I7: Units | J7: Units | K7: Units | L7: Units | M7: Units | N7: Units | O7: Units | P7: Units | Q7: Units | R7: Units | S7: Units | T7: Units
A8: 1990M1 | B8: 1528 | C8: 38 | D8: 31 | E8: 2365.557 | F8: 409.81906 | G8: 14.05 | H8: 1.73 | K8: 7056 | L8: 21.25 | M8: 17.57 | N8: 22.96 | O8: 135.41304 | P8: 497.65652 | Q8: 5.2475455 | R8: 20.59
A9: 1990M2 | B9: 1454 | C9: 38 | D9: 31 | E9: 2358.9434 | F9: 417.18106 | G9: 14.05 | H9: 1.73 | K9: 6977 | L9: 19.93 | M9: 17 | N9: 22.12 | O9: 135.4375 | P9: 516.1 | Q9: 5.28935 | R9: 19.68
A10: 1990M3 | B10: 1567 | C10: 38 | D10: 31 | E10: 2625.7027 | F10: 392.70334 | G10: 14.05 | H10: 1.73 | K10: 9267 | L10: 18.37 | M10: 15.59 | N10: 20.41 | O10: 130.28182 | P10: 497.06364 | Q10: 5.0768864 | R10: 18.12
A11: 1990M4 | B11: 1526 | C11: 38 | D11: 31 | E11: 2685.2269 | F11: 374.29211 | G11: 14.05 | H11: 2.1099998 | K11: 8939 | L11: 16.49 | M11: 14.05 | N11: 18.43 | O11: 126.95952 | P11: 478.14762 | Q11: 5.059 | R11: 16.32
A12: 1990M5 | B12: 1527 | C12: 40.5 | D12: 32.5 | E12: 2740.3424 | F12: 369.19763 | G12: 14.05 | H12: 2.1099998 | K12: 8698 | L12: 16.34 | M12: 14.03 | N12: 18.25 | O12: 119.64348 | P12: 488.55435 | Q12: 5.0730476 | R12: 16.21
A13: 1990M6 | B13: 1566 | C13: 40.5 | D13: 34 | E13: 2583.8149 | F13: 352.52762 | G13: 14.05 | H13: 2.1099998 | K13: 8422 | L13: 15.05 | M13: 13.05 | N13: 16.69 | O13: 115.45952 | P13: 481.11429 | Q13: 4.9182857 | R13: 14.93
A14: 1990M7 | B14: 1571 | C14: 40.5 | D14: 34 | E14: 2769.003 | F14: 362.49857 | G14: 14.05 | H14: 1.9199999 | K14: 9318 | L14: 17.14 | M14: 14.88 | N14: 18.42 | O14: 117.09318 | P14: 478.78864 | Q14: 4.871 | R14: 16.81
A15: 1990M8 | B15: 1782 | C15: 40.5 | D15: 34 | E15: 2956.3956 | F15: 394.63181 | G15: 14.05 | H15: 1.9199999 | K15: 10957 | L15: 27.32 | M15: 25.06 | N15: 27.23 | O15: 115.41304 | P15: 492.73478 | Q15: 5.0018409 | R15: 26.54
A16: 1990M9 | B16: 2067 | C16: 40.5 | D16: 34 | E16: 3040.1708 | F16: 389.755 | G16: 14.05 | H16: 1.9199999 | K16: 10844 | L16: 35.03 | M16: 32.03 | N16: 33.8 | O16: 105.066 | P16: 461.665 | Q16: 4.803775 | R16: 33.62
A17: 1990M10 | B17: 1946 | C17: 40.5 | D17: 34 | E17: 2742.547 | F17: 380.99521 | G17: 14.05 | H17: 2.3799998 | K17: 9145 | L17: 36.09 | M17: 32.34 | N17: 36.13 | O17: 95.493478 | P17: 424.94565 | Q17: 4.3891087 | R17: 34.85
A18: 1990M11 | B18: 1618 | C18: 40.5 | D18: 34 | E18: 2583.8149 | F18: 381.7941 | G18: 14.05 | H18: 2.3799998 | K18: 8587 | L18: 33.2 | M18: 28.98 | N18: 32.44 | O18: 93.586364 | P18: 422.23636 | Q18: 4.1728864 | R18: 31.54
A19: 1990M12 | B19: 1522 | C19: 40.5 | D19: 34 | E19: 2484.607 | F19: 376.68234 | G19: 14.05 | H19: 2.3799998 | K19: 8158 | L19: 28.32 | M19: 24.18 | N19: 27.33 | O19: 89.078571 | P19: 420.07143 | Q19: 4.0788158 | R19: 26.61
A20: 1991M1 | B20: 1515 | C20: 40.5 | D20: 34 | E20: 2447.1282 | F20: 383.70227 | G20: 15.03 | H20: 2.9599999 | J20: 1.43 | K20: 8569 | L20: 23.54 | M20: 19.68 | N20: 25.2 | O20: 86.765217 | P20: 407.83565 | Q20: 4.0504091 | R20: 22.81
A21: 1991M2 | B21: 1505 | C21: 40.5 | D21: 34 | E21: 2447.1282 | F21: 364.39166 | G21: 15.03 | H21: 2.9599999 | J21: 1.41375 | K21: 8672 | L21: 19.58 | M21: 15.51 | N21: 20.5 | O21: 84.3925 | P21: 386.7875 | Q21: 3.73765 | R21: 18.53
A22: 1991M3 | B22: 1496 | C22: 39.5 | D22: 31 | E22: 2409.6494 | F22: 362.7608 | G22: 15.03 | H22: 2.9599999 | J22: 1.356 | K22: 8700 | L22: 19.13 | M22: 15.65 | N22: 19.87 | O22: 86.419048 | P22: 399.98571 | Q22: 3.948125 | R22: 18.21
A23: 1991M4 | B23: 1392 | C23: 39.5 | D23: 31 | E23: 2471.3793 | F23: 358.32333 | G23: 15.03 | H23: 3.4100003 | J23: 1.3625 | K23: 9023 | L23: 19.13 | M23: 15.55 | N23: 20.77 | O23: 96.375 | P23: 396.88182 | Q23: 3.9821429 | R23: 18.49
A24: 1991M5 | B24: 1299.95 | C24: 39.5 | D24: 31 | E24: 2340.4247 | F24: 356.96429 | G24: 15.03 | H24: 3.4100003 | J24: 1.336 | K24: 8499.6094 | L24: 19.16 | M24: 15.77 | N24: 21.24 | O24: 95.304348 | P24: 389.63913 | Q24: 4.047 | R24: 18.72
A25: 1991M6 | B25: 1283.55 | C25: 39.5 | D25: 31 | E25: 2218.068 | F25: 366.91 | G25: 15.03 | H25: 3.4100003 | J25: 1.2511667 | K25: 8296.5 | L25: 18.08 | M25: 15.03 | N25: 20.21 | O25: 97.1475 | P25: 376.055 | Q25: 4.3929 | R25: 17.78
A26: 1991M7 | B26: 1297.5466 | C26: 39.5 | D26: 31 | E26: 2231.2553 | F26: 367.79227 | G26: 15.03 | H26: 3.1200002 | J26: 1.1485 | K26: 8515.2012 | L26: 19.42 | M26: 16.13 | N26: 21.52 | O26: 94.487826 | P26: 376.03478 | Q26: 4.3475 | R26: 19.02
A27: 1991M8 | B27: 1259.6934 | C27: 39.5 | D27: 31 | E27: 2236.1868 | F27: 356.66953 | G27: 15.03 | H27: 3.1200002 | J27: 1.3028 | K27: 8154.75 | L27: 19.73 | M27: 16.47 | N27: 21.7 | O27: 82.772727 | P27: 346.34773 | Q27: 3.9575 | R27: 19.3
A28: 1991M9 | B28: 1212.0952 | C28: 39.5 | D28: 31 | E28: 2318.583 | F28: 348.74286 | G28: 15.03 | H28: 3.1200002 | J28: 1.473125 | K28: 7675.9531 | L28: 20.48 | M28: 17.5 | N28: 21.86 | O28: 81.954762 | P28: 349.34048 | Q28: 4.0374762 | R28: 19.95
A29: 1991M10 | B29: 1152.9546 | C29: 39.5 | D29: 31 | E29: 2360.6456 | F29: 358.81436 | G29: 15.03 | H29: 2.5400001 | J29: 1.682 | K29: 7453.8633 | L29: 22.25 | M29: 19.12 | N29: 23.3 | O29: 85.282609 | P29: 362.48261 | Q29: 4.1153913 | R29: 21.56
A30: 1991M11 | B30: 1134.925 | C30: 39.5 | D30: 31 | E30: 2375.6604 | F30: 359.59 | G30: 15.03 | H30: 2.5400001 | J30: 1.8052 | K30: 7258.5 | L30: 21 | M30: 17.76 | N30: 22.46 | O30: 85.242857 | P30: 365.10952 | Q30: 4.0722857 | R30: 20.41
A31: 1991M12 | B31: 1099.5264 | C31: 39.5 | D31: 31 | E31: 2205.9185 | F31: 361.53201 | G31: 15.03 | H31: 2.5400001 | J31: 1.848 | K31: 7140.2637 | L31: 18.28 | M31: 15.11 | N31: 19.51 | O31: 82.375 | P31: 353.29545 | Q31: 3.947075 | R31: 17.63
A32: 1992M1 | B32: 1181.2273 | C32: 39.5 | D32: 31 | E32: 2150.5796 | F32: 354.70096 | G32: 14.31 | H32: 2.3799998 | I32: 3.8 | J32: 1.4405 | K32: 7531.1367 | L32: 18.55 | M32: 15.25 | N32: 18.76 | O32: 82.936957 | P32: 341.18696 | Q32: 4.1214091 | R32: 17.52 | S32: 50.724146 | T32: 67.512992
A33: 1992M2 | B33: 1270.75 | C33: 39.5 | D33: 31 | E33: 2208.8923 | F33: 353.78 | G33: 14.31 | H33: 2.3799998 | I33: 3.55 | J33: 1.18 | K33: 7888 | L33: 18.48 | M33: 15.46 | N33: 18.99 | O33: 85.4225 | P33: 362.1225 | Q33: 4.1457 | R33: 17.65 | S33: 50.722601 | T33: 68.127248
A34: 1992M3 | B34: 1282.0227 | C34: 39.5 | D34: 31 | E34: 2231.7855 | F34: 344.18332 | G34: 14.31 | H34: 2.3799998 | I34: 3.45 | J34: 1.26 | K34: 7430.4551 | L34: 17.59 | M34: 15.56 | N34: 18.92 | O34: 84.459091 | P34: 356.93864 | Q34: 4.1104318 | R34: 17.35 | S34: 50.748701 | T34: 69.04621
A35: 1992M4 | B35: 1317.125 | C35: 39.5 | D35: 31 | E35: 2214.1668 | F35: 338.69159 | G35: 14.31 | H35: 2.3399997 | I35: 3.45 | J35: 1.3905 | K35: 7417.9512 | L35: 19.06 | M35: 16.67 | N35: 20.23 | O35: 83.313636 | P35: 347.3 | Q35: 4.0525 | R35: 18.65 | S35: 51.1747 | T35: 66.211724
A36: 1992M5 | B36: 1306.7107 | C36: 39.5 | D36: 31 | E36: 2219.3151 | F36: 337.09894 | G36: 14.31 | H36: 2.3399997 | I36: 3.585 | J36: 1.5533 | K36: 7333.9473 | L36: 20.03 | M36: 17.57 | N36: 20.97 | O36: 82.840476 | P36: 358.5881 | Q36: 4.0746053 | R36: 19.52 | S36: 52.635726 | T36: 68.556314
A37: 1992M6 | B37: 1275.2727 | C37: 39.5 | D37: 29 | E37: 2296.4419 | F37: 341.02191 | G37: 14.31 | H37: 2.3399997 | I37: 3.72 | J37: 1.5915 | K37: 7202.3633 | L37: 21.28 | M37: 18.98 | N37: 22.37 | O37: 80.643182 | P37: 369.12727 | Q37: 4.0639091 | R37: 20.88 | S37: 52.852571 | T37: 65.571299
A38: 1992M7 | B38: 1314.3479 | C38: 39.5 | D38: 27 | E38: 2527.285 | F38: 352.25449 | G38: 14.31 | H38: 2.3900002 | I38: 3.94 | J38: 1.6832 | K38: 7516.1738 | L38: 20.34 | M38: 18.44 | N38: 21.77 | O38: 87.023913 | P38: 383.12174 | Q38: 3.9675217 | R38: 20.18 | S38: 52.518993 | T38: 64.267139
A39: 1992M8 | B39: 1305.55 | C39: 39.5 | D39: 27 | E39: 2513.47 | F39: 342.89285 | G39: 14.31 | H39: 2.3900002 | I39: 3.96 | J39: 1.914 | K39: 7279.75 | L39: 19.77 | M39: 17.78 | N39: 21.31 | O39: 85.530952 | P39: 359.55238 | Q39: 3.818425 | R39: 19.62 | S39: 52.580209 | T39: 65.663962
A40: 1992M9 | B40: 1270.2144 | C40: 39.5 | D40: 27 | E40: 2419.6142 | F40: 345.0065 | G40: 14.31 | H40: 2.3900002 | I40: 3.98 | J40: 2.088 | K40: 6918.5723 | L40: 20.31 | M40: 18.36 | N40: 21.9 | O40: 90.9 | P40: 362.14318 | Q40: 3.7701591 | R40: 20.19 | S40: 53.009 | T40: 65.440411
A41: 1992M10 | B41: 1180.8411 | C41: 37.25 | D41: 27 | E41: 2262.457 | F41: 344.8924 | G41: 14.31 | H41: 2.3500002 | I41: 3.87 | J41: 2.4164 | K41: 6322.5 | L41: 20.26 | M41: 18.16 | N41: 21.69 | O41: 94.688636 | P41: 358.06818 | Q41: 3.7497727 | R41: 20.04 | S41: 52.500685 | T41: 64.455641
A42: 1992M11 | B42: 1162.2144 | C42: 35 | D42: 27 | E42: 2161.7891 | F42: 335.05054 | G42: 14.31 | H42: 2.3500002 | I42: 3.84 | J42: 2.278 | K42: 5593.7148 | L42: 19.15 | M42: 17.21 | N42: 20.33 | O42: 94.464286 | P42: 356.10952 | Q42: 3.7710238 | R42: 18.9 | S42: 50.372062 | T42: 61.41946
A43: 1992M12 | B43: 1209.0238 | C43: 35 | D43: 27 | E43: 2211.9503 | F43: 334.80713 | G43: 14.31 | H43: 2.3500002 | I43: 3.78 | J43: 2.21275 | K43: 5751.1904 | L43: 18.15 | M43: 16.22 | N43: 19.42 | O43: 106.63043 | P43: 361.97174 | Q43: 3.7264524 | R43: 17.93 | S43: 50.413115 | T43: 63.647381
... A360: 2019M5 | B360: 1781.2619 | C360: 89.564286 | D360: 65.757619 | E360: 6017.9048 | F360: 1283.9476 | G360: 101.76087 | H360: 4.3591307 | I360: 5.0332609 | J360: 2.6278636 | K360: 12016.31 | L360: 70.526522 | M360: 69.37087 | N360: 60.733478 | O360: 1331.4348 | P360: 831.82609 | Q360: 14.625476 | R360: 66.876957 | S360: 121.5594 | T360: 102.13913
A361: 2019M6 | O361: 1344.3333 | P361: 814.33333
A362: 2019M7
A363: 2019M8
A364: 2019M9
A365: 2019M10
A366: 2019M11
A367: 2019M12
A368: 2020M1
A369: 2020M2
A370: 2020M3
A371: 2020M4
A372: 2020M5
A373: 2020M6
... A379: 2020M12

Sheet Monthly Haver
A1: Jan-1999 !M | B1: .excel_last | C1: SGBLTO@MKTPMI | D1: SGBLTP@MKTPMI | E1: SGBLTX@MKTPMI | F1: SGBLTPO@MKTPMI | G1: SGBLTE@MKTPMI | H1: SGBLM@MKTPMI | I1: SGBLMSF@MKTPMI | J1: SGBLS@MKTPMI | K1: FXDUSBC@USECON | L1: BDIM@BALTIC
A2: .DESC | C2: Global PMI: Composite New Orders (SA, 50+=Expansion) | D2: Global PMI: Composite Input Prices (SA, 50+=Expansion) | E2: Global PMI: Composite New Export Orders (SA, 50+=Expansion) | F2: Global PMI: Composite Output Prices (SA, 50+=Expansion) | G2: Global PMI: Composite Employment (SA, 50+=Expansion) | H2: Global Manufacturing PMI Using Markit Mfg for U.S. (SA, 50+=Expansion) | I2: Global PMI: Manufacturing Stock of Finished Goods (SA, 50+=Expansion) | J2: Global PMI: Services Business Activity (SA, 50+=Expansion) | K2: JPMorgan Real Broad Effective Exchange Rate Index, PPI Based: US (2010=100) | L2: Baltic Exchange Dry Index (Jan-04-85=1000)
A3: .T1 | C3: Jul-1998 | D3: Jul-1998 | E3: Sep-2014 | F3: Oct-2009 | G3: Jul-1998 | H3: Jan-1998 | I3: May-2007 | J3: Jul-1998 | K3: Jan-1990 | L3: Jan-1985
A4: .TN | C4: Jun-2019 | D4: Jun-2019 | E4: Jun-2019 | F4: Jun-2019 | G4: Jun-2019 | H4: Jun-2019 | I4: Jun-2019 | J4: Jun-2019 | K4: Jun-2019 | L4: Jun-2019
A5: Jan-1999 | B5: 36191 | C5: 53.5976 | D5: 42.7203 | E5: #N/A | F5: #N/A | G5: 50.8256 | H5: 48.7254 | I5: #N/A | J5: 55.6953 | K5: 104.74784 | L5: 803
A6: Feb-1999 | B6: 36219 | C6: 54.1254 | D6: 42.8611 | E6: #N/A | F6: #N/A | G6: 51.4539 | H6: 49.8581 | I6: #N/A | J6: 55.325 | K6: 105.57661 | L6: 836
A7: Mar-1999 | B7: 36250 | C7: 55.3837 | D7: 46.3136 | E7: #N/A | F7: #N/A | G7: 51.4596 | H7: 50.7334 | I7: #N/A | J7: 56.9761 | K7: 106.59589 | L7: 967
A8: Apr-1999 | B8: 36280 | C8: 55.9987 | D8: 49.0474 | E8: #N/A | F8: #N/A | G8: 52.0892 | H8: 51.2542 | I8: #N/A | J8: 57.5913 | K8: 106.42206 | L8: 924
A9: May-1999 | B9: 36311 | C9: 55.9166 | D9: 51.0918 | E9: #N/A | F9: #N/A | G9: 52.6932 | H9: 52.3421 | I9: #N/A | J9: 56.5726 | K9: 107.02515 | L9: 1063
A10: Jun-1999 | B10: 36341 | C10: 57.8804 | D10: 52.1057 | E10: #N/A | F10: #N/A | G10: 53.68 | H10: 53.5438 | I10: #N/A | J10: 57.4603 | K10: 108.0101 | L10: 989
A11: Jul-1999 | B11: 36372 | C11: 57.3138 | D11: 54.7592 | E11: #N/A | F11: #N/A | G11: 53.4233 | H11: 53.1272 | I11: #N/A | J11: 59.4464 | K11: 107.85083 | L11: 977
A12: Aug-1999 | B12: 36403 | C12: 58.4475 | D12: 56.783 | E12: #N/A | F12: #N/A | G12: 53.5661 | H12: 54.0798 | I12: #N/A | J12: 59.4645 | K12: 107.48695 | L12: 1046
A13: Sep-1999 | B13: 36433 | C13: 60.0914 | D13: 60.6433 | E13: #N/A | F13: #N/A | G13: 53.5119 | H13: 55.6868 | I13: #N/A | J13: 59.0417 | K13: 106.8969 | L13: 1146
A14: Oct-1999 | B14: 36464 | C14: 60.8236 | D14: 60.5633 | E14: #N/A | F14: #N/A | G14: 54.1096 | H14: 56.535 | I14: #N/A | J14: 60.3565 | K14: 105.97901 | L14: 1339
A15: Nov-1999 | B15: 36494 | C15: 58.6858 | D15: 60.7025 | E15: #N/A | F15: #N/A | G15: 53.7353 | H15: 56.9861 | I15: #N/A | J15: 58.1496 | K15: 106.29201 | L15: 1334
A16: Dec-1999 | B16: 36525 | C16: 60.1055 | D16: 61.061 | E16: #N/A | F16: #N/A | G16: 55.1018 | H16: 57.0833 | I16: #N/A | J16: 59.6569 | K16: 105.52177 | L16: 1343
... A104: Apr-2007 | B104: 39202 | C104: 56.2146 | D104: 60.4583 | E104: #N/A | F104: #N/A | G104: 53.6109 | H104: 53.5228 | I104: #N/A | J104: 56.6072 | K104: 103.99567 | L104: 5754
A105: May-2007 | B105: 39233 | C105: 57.2497 | D105: 60.9893 | E105: #N/A | F105: #N/A | G105: 54.5019 | H105: 53.3255 | I105: 49.159 | J105: 57.7971 | K105: 104.02268 | L105: 6402
A106: Jun-2007 | B106: 39263 | C106: 57.8046 | D106: 61.0211 | E106: #N/A | F106: #N/A | G106: 55.134 | H106: 53.7078 | I106: 49.2891 | J106: 59.1229 | K106: 104.2627 | L106: 5772
A107: Jul-2007 | B107: 39294 | C107: 56.453 | D107: 59.8442 | E107: #N/A | F107: #N/A | G107: 54.0004 | H107: 52.9236 | I107: 49.2811 | J107: 57.351 | K107: 103.3034 | L107: 6572
A108: Aug-2007 | B108: 39325 | C108: 56.9251 | D108: 59.6259 | E108: #N/A | F108: #N/A | G108: 52.8507 | H108: 52.6029 | I108: 47.9335 | J108: 56.5272 | K108: 102.35385 | L108: 7195
A109: Sep-2007 | B109: 39355 | C109: 53.9399 | D109: 61.6813 | E109: #N/A | F109: #N/A | G109: 54.2622 | H109: 52.6837 | I109: 48.4004 | J109: 53.9496 | K109: 101.06376 | L109: 8574
A110: Oct-2007 | B110: 39386 | C110: 55.1334 | D110: 62.5568 | E110: #N/A | F110: #N/A | G110: 54.344 | H110: 52.3405 | I110: 48.1615 | J110: 54.3423 | K110: 99.58237 | L110: 10426
A111: Nov-2007 | B111: 39416 | C111: 53.5419 | D111: 66.3275 | E111: #N/A | F111: #N/A | G111: 53.546 | H111: 52.3511 | I111: 48.489 | J111: 54.4281 | K111: 99.74316 | L111: 10543
A112: Dec-2007 | B112: 39447 | C112: 52.8519 | D112: 66.0345 | E112: #N/A | F112: #N/A | G112: 53.4799 | H112: 51.9675 | I112: 48.0861 | J112: 53.1903 | K112: 99.67216 | L112: 9854
A113: Jan-2008 | B113: 39478 | C113: 49.252 | D113: 65.8991 | E113: #N/A | F113: #N/A | G113: 50.909 | H113: 52.1121 | I113: 47.885 | J113: 47.07 | K113: 99.15559 | L113: 7170
A114: Feb-2008 | B114: 39507 | C114: 51.5088 | D114: 64.6164 | E114: #N/A | F114: #N/A | G114: 51.0203 | H114: 50.7353 | I114: 49.3341 | J114: 51.913 | K114: 98.86312 | L114: 6874
A115: Mar-2008 | B115: 39538 | C115: 50.9263 | D115: 66.7556 | E115: #N/A | F115: #N/A | G115: 51.2793 | H115: 50.6227 | I115: 49.2764 | J115: 51.4812 | K115: 98.22704 | L115: 8063
A116: Apr-2008 | B116: 39568 | C116: 50.9577 | D116: 67.1589 | E116: #N/A | F116: #N/A | G116: 52.232 | H116: 50.1224 | I116: 48.128 | J116: 51.2114 | K116: 97.91501 | L116: 8287
... A133: Sep-2009 | B133: 40086 | C133: 53.4704 | D133: 50.1765 | E133: #N/A | F133: #N/A | G133: 48.318 | H133: 53.7834 | I133: 46.0672 | J133: 52.1114 | K133: 97.86272 | L133: 2351
A134: Oct-2009 | B134: 40117 | C134: 54.2298 | D134: 51.4854 | E134: #N/A | F134: 47.4524 | G134: 48.1578 | H134: 54.5335 | I134: 46.6717 | J134: 52.8913 | K134: 97.2983 | L134: 2746
A135: Nov-2009 | B135: 40147 | C135: 54.357 | D135: 51.3398 | E135: #N/A | F135: 47.2055 | G135: 48.5399 | H135: 54.0821 | I135: 46.8985 | J135: 52.894 | K135: 97.78118 | L135: 3941
A136: Dec-2009 | B136: 40178 | C136: 55.1017 | D136: 52.1927 | E136: #N/A | F136: 48.1541 | G136: 48.6012 | H136: 54.7643 | I136: 45.79 | J136: 53.9632 | K136: 98.0557 | L136: 3605
A137: Jan-2010 | B137: 40209 | C137: 55.57 | D137: 54.7875 | E137: #N/A | F137: 48.9468 | G137: 49.2475 | H137: 55.4503 | I137: 47.3101 | J137: 54.0538 | K137: 99.6734 | L137: 3168
A138: Feb-2010 | B138: 40237 | C138: 55.2885 | D138: 54.5609 | E138: #N/A | F138: 49.0096 | G138: 49.5792 | H138: 54.9788 | I138: 48.0807 | J138: 54.962 | K138: 100.55208 | L138: 2678
A139: Mar-2010 | B139: 40268 | C139: 56.7793 | D139: 55.6551 | E139: #N/A | F139: 49.6817 | G139: 50.6878 | H139: 55.97 | I139: 47.6633 | J139: 55.872 | K139: 100.33268 | L139: 3209
A140: Apr-2010 | B140: 40298 | C140: 56.8113 | D140: 56.9429 | E140: #N/A | F140: 50.5478 | G140: 51.1027 | H140: 56.7153 | I140: 48.0096 | J140: 56.1704 | K140: 99.56115 | L140: 3043
A141: May-2010 | B141: 40329 | C141: 55.3209 | D141: 56.1253 | E141: #N/A | F141: 50.2307 | G141: 51.6021 | H141: 55.5405 | I141: 48.8757 | J141: 55.6098 | K141: 102.36575 | L141: 3838
A142: Jun-2010 | B142: 40359 | C142: 54.205 | D142: 54.1502 | E142: #N/A | F142: 49.8955 | G142: 51.6521 | H142: 53.9852 | I142: 49.508 | J142: 55.0345 | K142: 102.65441 | L142: 3088
A143: Jul-2010 | B143: 40390 | C143: 54.4226 | D143: 53.8858 | E143: #N/A | F143: 50.3207 | G143: 51.3005 | H143: 54.0477 | I143: 49.0262 | J143: 55.013 | K143: 101.23376 | L143: 1910
A144: Aug-2010 | B144: 40421 | C144: 54.1986 | D144: 54.939 | E144: #N/A | F144: 50.4184 | G144: 51.6478 | H144: 53.0908 | I144: 48.6181 | J144: 55.0408 | K144: 100.96192 | L144: 2432
A145: Sep-2010 | B145: 40451 | C145: 53.3741 | D145: 54.6631 | E145: #N/A | F145: 50.0972 | G145: 51.2335 | H145: 52.7652 | I145: 49.1082 | J145: 54.2037 | K145: 99.35241 | L145: 2712
... A192: Aug-2014 | B192: 41882 | C192: 54.6743 | D192: 53.8269 | E192: #N/A | F192: 51.0675 | G192: 51.3151 | H192: 52.4035 | I192: 49.8942 | J192: 55.484 | K192: 104.59131 | L192: 937
A193: Sep-2014 | B193: 41912 | C193: 54.8755 | D193: 53.3929 | E193: 52.3088 | F193: 51.7287 | G193: 51.6317 | H193: 52.0353 | I193: 49.7708 | J193: 55.3659 | K193: 105.82471 | L193: 1123
A194: Oct-2014 | B194: 41943 | C194: 53.8832 | D194: 53.0976 | E194: 51.1607 | F194: 50.4087 | G194: 51.4137 | H194: 52.0789 | I194: 50.2409 | J194: 53.8012 | K194: 106.26865 | L194: 1101
A195: Nov-2014 | B195: 41973 | C195: 53.2927 | D195: 52.6063 | E195: 50.6402 | F195: 50.8075 | G195: 51.6449 | H195: 51.6615 | I195: 49.8007 | J195: 53.5855 | K195: 107.22946 | L195: 1332
A196: Dec-2014 | B196: 42004 | C196: 52.2019 | D196: 52.5609 | E196: 51.118 | F196: 50.1336 | G196: 51.1617 | H196: 51.4416 | I196: 49.693 | J196: 52.6896 | K196: 108.11974 | L196: 910
A197: Jan-2015 | B197: 42035 | C197: 52.1236 | D197: 50.3182 | E197: 50.814 | F197: 49.8878 | G197: 51.4899 | H197: 51.5355 | I197: 49.3953 | J197: 52.8736 | K197: 108.27573 | L197: 725
A198: Feb-2015 | B198: 42063 | C198: 53.8234 | D198: 51.1193 | E198: 50.9073 | F198: 50.5376 | G198: 51.5824 | H198: 51.8489 | I198: 49.8427 | J198: 54.1084 | K198: 109.15011 | L198: 539
A199: Mar-2015 | B199: 42094 | C199: 54.207 | D199: 52.3222 | E199: 50.6608 | F199: 50.5216 | G199: 51.5883 | H199: 51.4627 | I199: 49.3099 | J199: 54.9811 | K199: 110.80977 | L199: 576
A200: Apr-2015 | B200: 42124 | C200: 53.7868 | D200: 52.4971 | E200: 50.3322 | F200: 50.8181 | G200: 52.0928 | H200: 50.7937 | I200: 49.4661 | J200: 54.7169 | K200: 109.32732 | L200: 591
A201: May-2015 | B201: 42155 | C201: 53.2829 | D201: 53.5065 | E201: 50.0079 | F201: 50.8416 | G201: 52.3059 | H201: 51.0151 | I201: 49.1002 | J201: 53.9694 | K201: 110.09854 | L201: 597
A202: Jun-2015 | B202: 42185 | C202: 53.198 | D202: 54.1216 | E202: 50.9088 | F202: 51.1123 | G202: 51.5805 | H202: 50.9126 | I202: 49.0972 | J202: 53.2875 | K202: 111.99104 | L202: 699
A203: Jul-2015 | B203: 42216 | C203: 53.8277 | D203: 53.432 | E203: 50.116 | F203: 50.7253 | G203: 51.681 | H203: 50.7364 | I203: 49.3622 | J203: 53.8229 | K203: 113.38924 | L203: 975
A204: Aug-2015 | B204: 42247 | C204: 53.0026 | D204: 52.205 | E204: 49.8374 | F204: 50.0872 | G204: 51.6499 | H204: 50.4321 | I204: 48.7483 | J204: 54.092 | K204: 115.05919 | L204: 1066
... A250: Jun-2019 | B250: 43646 | C250: 51.614 | D250: 53.7104 | E250: 49.0546 | F250: 51.5534 | G250: 51.3163 | H250: 49.3994 | I250: 49.3243 | J250: 51.8967 | K250: 114.40336 | L250: 1174

Sheet Quarterly Haver
A1: 1999/Q1 *Q | B1: .excel_first | C1: S001XDIR@G10 | D1: S001XHPR@G10
A2: .DESC | C2: Real Household Personal Disposable Income: World (SA, 2005=100) | D2: Real House Price Index: World (SA, 2005=100)
A3: .T1 | C3: Q1-1975 | D3: Q1-1975
A4: 1999/Q1 | B4: 36161 | C4: 90.78 | D4: 79.11
A5: 1999/Q2 | B5: 36251 | C5: 91.21 | D5: 79.57
A6: 1999/Q3 | B6: 36342 | C6: 91.6 | D6: 80.17
A7: 1999/Q4 | B7: 36434 | C7: 92.31 | D7: 80.64
A8: 2000/Q1 | B8: 36526 | C8: 92.62 | D8: 81.07
A9: 2000/Q2 | B9: 36617 | C9: 93.26 | D9: 81.79
A10: 2000/Q3 | B10: 36708 | C10: 93.68 | D10: 82.14
A11: 2000/Q4 | B11: 36800 | C11: 94.18 | D11: 82.67
A12: 2001/Q1 | B12: 36892 | C12: 94.75 | D12: 83.25
A13: 2001/Q2 | B13: 36982 | C13: 94.74 | D13: 83.79
A14: 2001/Q3 | B14: 37073 | C14: 95.47 | D14: 84.6
A15: 2001/Q4 | B15: 37165 | C15: 95.57 | D15: 85.2
... A84: 2019/Q1 | B84: 43466 | C84: 116.43 | D84: 107.08
A85: 2019/Q2 | B85: 43556 | C85: #N/A | D85: #N/A

Sheet Monthly
B1: PMINO | C1: PMIALL | D1: PMINXO | E1: EMPPMI | F1: PMIM | G1: Inve | H1: PMIS | I1: Sales | J1: INDPRO | K1: BOPTIMP | L1: BOPTEXP | M1: UNRATE | N1: ECC | O1: LRIR | P1: STIR | Q1: CPI | R1: CCPI | S1: Food | T1: Metal | U1: COMPNF | V1: Energy | W1: Oil | X1: Raw | Y1: OECDCLI | Z1: REERUS | AA1: CHEM
A2: ='Monthly Haver'!A5 -> Jan-1999 | B2: ='Monthly Haver'!C5 -> 53.5976 | C2: ='Monthly Haver'!D5 -> 42.7203 | D2: ='Monthly Haver'!E5 -> #N/A | E2: ='Monthly Haver'!G5 -> 50.8256 | F2: ='Monthly Haver'!H5 -> 48.7254 | G2: ='Monthly Haver'!I5 -> #N/A | H2: ='Monthly Haver'!J5 -> 55.6953 | I2: =GDS_Monthly!O119 -> 48.077038 | J2: =GDS_Monthly!D119 -> 65.769752 | K2: =GDS_Monthly!AH119 -> 349.18549 | L2: =GDS_Monthly!AI119 -> 344.37955 | M2: =GDS_Monthly!N119 -> 6.1873546 | N2: =GDS_Monthly!C119 -> 118.64823 | O2: =GDS_Monthly!F119 -> 4.1411999 | P2: =GDS_Monthly!G119 -> 5.8914995 | Q2: =GDS_Monthly!T119 -> 73.68393 | R2: =GDS_Monthly!V119 -> 79.695601 | S2: =GDS_Monthly!W119 -> 67.003805 | T2: =GDS_Monthly!X119 -> 36.397902 | U2: =GDS_Monthly!AA119 -> 52.616127 | V2: =GDS_Monthly!AC119 -> 32.584569 | W2: =GDS_Monthly!AE119 -> 26.140204 | X2: =GDS_Monthly!AF119 -> 69.791518 | Y2: =OECD!B2 -> 99.47476 | Z2: ='Monthly Haver'!K5 -> 104.74784 | AA2: =OECD!C2 -> 95.61
A3: ='Monthly Haver'!A6 -> Feb-1999 | B3: ='Monthly Haver'!C6 -> 54.1254 | C3: ='Monthly Haver'!D6 -> 42.8611 | D3: ='Monthly Haver'!E6 -> #N/A | E3: ='Monthly Haver'!G6 -> 51.4539 | F3: ='Monthly Haver'!H6 -> 49.8581 | G3: ='Monthly Haver'!I6 -> #N/A | H3: ='Monthly Haver'!J6 -> 55.325 | I3: =GDS_Monthly!O120 -> 48.406006 | J3: =GDS_Monthly!D120 -> 66.075294 | K3: =GDS_Monthly!AH120 -> 350.14039 | L3: =GDS_Monthly!AI120 -> 338.62962 | M3: =GDS_Monthly!N120 -> 6.1959605 | N3: =GDS_Monthly!C120 -> 119.73876 | O3: =GDS_Monthly!F120 -> 4.3355312 | P3: =GDS_Monthly!G120 -> 5.6829416 | Q3: =GDS_Monthly!T120 -> 73.779357 | R3: =GDS_Monthly!V120 -> 79.780902 | S3: =GDS_Monthly!W120 -> 62.091429 | T3: =GDS_Monthly!X120 -> 36.917985 | U3: =GDS_Monthly!AA120 -> 50.415246 | V3: =GDS_Monthly!AC120 -> 31.458463 | W3: =GDS_Monthly!AE120 -> 25.242365 | X3: =GDS_Monthly!AF120 -> 69.661742 | Y3: =OECD!B3 -> 99.66687 | Z3: ='Monthly Haver'!K6 -> 105.57661 | AA3: =OECD!C3 -> 96.34
A4: ='Monthly Haver'!A7 -> Mar-1999 | B4: ='Monthly Haver'!C7 -> 55.3837 | C4: ='Monthly Haver'!D7 -> 46.3136 | D4: ='Monthly Haver'!E7 -> #N/A | E4: ='Monthly Haver'!G7 -> 51.4596 | F4: ='Monthly Haver'!H7 -> 50.7334 | G4: ='Monthly Haver'!I7 -> #N/A | H4: ='Monthly Haver'!J7 -> 56.9761 | I4: =GDS_Monthly!O121 -> 49.16041 | J4: =GDS_Monthly!D121 -> 66.415605 | K4: =GDS_Monthly!AH121 -> 354.29676 | L4: =GDS_Monthly!AI121 -> 346.8056 | M4: =GDS_Monthly!N121 -> 6.1959564 | N4: =GDS_Monthly!C121 -> 119.74111 | O4: =GDS_Monthly!F121 -> 4.4350289 | P4: =GDS_Monthly!G121 -> 6.0031129 | Q4: =GDS_Monthly!T121 -> 73.933111 | R4: =GDS_Monthly!V121 -> 79.923392 | S4: =GDS_Monthly!W121 -> 60.29823 | T4: =GDS_Monthly!X121 -> 37.299843 | U4: =GDS_Monthly!AA121 -> 49.620259 | V4: =GDS_Monthly!AC121 -> 34.981861 | W4: =GDS_Monthly!AE121 -> 30.593839 | X4: =GDS_Monthly!AF121 -> 70.57853 | Y4: =OECD!B4 -> 99.85615 | Z4: ='Monthly Haver'!K7 -> 106.59589 | AA4: =OECD!C4 -> 96.64
A5: ='Monthly Haver'!A8 -> Apr-1999 | B5: ='Monthly Haver'!C8 -> 55.9987 | C5: ='Monthly Haver'!D8 -> 49.0474 | D5: ='Monthly Haver'!E8 -> #N/A | E5: ='Monthly Haver'!G8 -> 52.0892 | F5: ='Monthly Haver'!H8 -> 51.2542 | G5: ='Monthly Haver'!I8 -> #N/A | H5: ='Monthly Haver'!J8 -> 57.5913 | I5: =GDS_Monthly!O122 -> 49.075054 | J5: =GDS_Monthly!D122 -> 66.629597 | K5: =GDS_Monthly!AH122 -> 351.9353 | L5: =GDS_Monthly!AI122 -> 345.62785 | M5: =GDS_Monthly!N122 -> 6.1866463 | N5: =GDS_Monthly!C122 -> 120.24442 | O5: =GDS_Monthly!F122 -> 4.3134206 | P5: =GDS_Monthly!G122 -> 5.3771072 | Q5: =GDS_Monthly!T122 -> 74.215742 | R5: =GDS_Monthly!V122 -> 80.100241 | S5: =GDS_Monthly!W122 -> 61.554135 | T5: =GDS_Monthly!X122 -> 38.769809 | U5: =GDS_Monthly!AA122 -> 50.212478 | V5: =GDS_Monthly!AC122 -> 40.728868 | W5: =GDS_Monthly!AE122 -> 37.660442 | X5: =GDS_Monthly!AF122 -> 69.408326 | Y5: =OECD!B5 -> 100.0378 | Z5: ='Monthly Haver'!K8 -> 106.42206 | AA5: =OECD!C5 -> 97.25
A6: ='Monthly Haver'!A9 -> May-1999 | B6: ='Monthly Haver'!C9 -> 55.9166 | C6: ='Monthly Haver'!D9 -> 51.0918 | D6: ='Monthly Haver'!E9 -> #N/A | E6: ='Monthly Haver'!G9 -> 52.6932 | F6: ='Monthly Haver'!H9 -> 52.3421 | G6: ='Monthly Haver'!I9 -> #N/A | H6: ='Monthly Haver'!J9 -> 56.5726 | I6: =GDS_Monthly!O123 -> 49.382125 | J6: =GDS_Monthly!D123 -> 67.10158 | K6: =GDS_Monthly!AH123 -> 358.04078 | L6: =GDS_Monthly!AI123 -> 348.3689 | M6: =GDS_Monthly!N123 -> 6.1382055 | N6: =GDS_Monthly!C123 -> 120.84511 | O6: =GDS_Monthly!F123 -> 4.5000857 | P6: =GDS_Monthly!G123 -> 4.9508609 | Q6: =GDS_Monthly!T123 -> 74.300179 | R6: =GDS_Monthly!V123 -> 80.22882 | S6: =GDS_Monthly!W123 -> 62.21842 | T6: =GDS_Monthly!X123 -> 39.98686 | U6: =GDS_Monthly!AA123 -> 50.768578 | V6: =GDS_Monthly!AC123 -> 42.045514 | W6: =GDS_Monthly!AE123 -> 38.766827 | X6: =GDS_Monthly!AF123 -> 71.430794 | Y6: =OECD!B6 -> 100.2077 | Z6: ='Monthly Haver'!K9 -> 107.02515 | AA6: =OECD!C6 -> 98.12
A7: ='Monthly Haver'!A10 -> Jun-1999 | B7: ='Monthly Haver'!C10 -> 57.8804 | C7: ='Monthly Haver'!D10 -> 52.1057 | D7: ='Monthly Haver'!E10 -> #N/A | E7: ='Monthly Haver'!G10 -> 53.68 | F7: ='Monthly Haver'!H10 -> 53.5438 | G7: ='Monthly Haver'!I10 -> #N/A | H7: ='Monthly Haver'!J10 -> 57.4603 | I7: =GDS_Monthly!O124 -> 49.869137 | J7: =GDS_Monthly!D124 -> 67.297968 | K7: =GDS_Monthly!AH124 -> 367.78941 | L7: =GDS_Monthly!AI124 -> 351.41149 | M7: =GDS_Monthly!N124 -> 6.1365166 | N7: =GDS_Monthly!C124 -> 121.41547 | O7: =GDS_Monthly!F124 -> 4.8230243 | P7: =GDS_Monthly!G124 -> 4.8849127 | Q7: =GDS_Monthly!T124 -> 74.394391 | R7: =GDS_Monthly!V124 -> 80.334105 | S7: =GDS_Monthly!W124 -> 60.478859 | T7: =GDS_Monthly!X124 -> 39.018173 | U7: =GDS_Monthly!AA124 -> 49.411856 | V7: =GDS_Monthly!AC124 -> 42.719851 | W7: =GDS_Monthly!AE124 -> 39.30779 | X7: =GDS_Monthly!AF124 -> 71.122848 | Y7: =OECD!B7 -> 100.3658 | Z7: ='Monthly Haver'!K10 -> 108.0101 | AA7: =OECD!C7 -> 98.7
A8: ='Monthly Haver'!A11 -> Jul-1999 | B8: ='Monthly Haver'!C11 -> 57.3138 | C8: ='Monthly Haver'!D11 -> 54.7592 | D8: ='Monthly Haver'!E11 -> #N/A | E8: ='Monthly Haver'!G11 -> 53.4233 | F8: ='Monthly Haver'!H11 -> 53.1272 | G8: ='Monthly Haver'!I11 -> #N/A | H8: ='Monthly Haver'!J11 -> 59.4464 | I8: =GDS_Monthly!O125 -> 50.15593 | J8: =GDS_Monthly!D125 -> 67.70597 | K8: =GDS_Monthly!AH125 -> 368.50261 | L8: =GDS_Monthly!AI125 -> 360.31608 | M8: =GDS_Monthly!N125 -> 6.1104934 | N8: =GDS_Monthly!C125 -> 120.79869 | O8: =GDS_Monthly!F125 -> 4.9034123 | P8: =GDS_Monthly!G125 -> 4.7486677 | Q8: =GDS_Monthly!T125 -> 74.643657 | R8: =GDS_Monthly!V125 -> 80.483604 | S8: =GDS_Monthly!W125 -> 58.803777 | T8: =GDS_Monthly!X125 -> 41.904733 | U8: =GDS_Monthly!AA125 -> 48.820283 | V8: =GDS_Monthly!AC125 -> 47.300332 | W8: =GDS_Monthly!AE125 -> 45.405164 | X8: =GDS_Monthly!AF125 -> 70.073576 | Y8: =OECD!B8 -> 100.5119 | Z8: ='Monthly Haver'!K11 -> 107.85083 | AA8: =OECD!C8 -> 98.78
A9: ='Monthly Haver'!A12 -> Aug-1999 | B9: ='Monthly Haver'!C12 -> 58.4475 | C9: ='Monthly Haver'!D12 -> 56.783 | D9: ='Monthly Haver'!E12 -> #N/A | E9: ='Monthly Haver'!G12 -> 53.5661 | F9: ='Monthly Haver'!H12 -> 54.0798 | G9: ='Monthly Haver'!I12 -> #N/A | H9: ='Monthly Haver'!J12 -> 59.4645 | I9: =GDS_Monthly!O126 -> 50.509429 | J9: =GDS_Monthly!D126 -> 68.083457 | K9: =GDS_Monthly!AH126 -> 376.68885 | L9: =GDS_Monthly!AI126 -> 366.10527 | M9: =GDS_Monthly!N126 -> 6.0866329 | N9: =GDS_Monthly!C126 -> 120.798 | O9: =GDS_Monthly!F126 -> 5.0665058 | P9: =GDS_Monthly!G126 -> 4.8153151 | Q9: =GDS_Monthly!T126 -> 74.856086 | R9: =GDS_Monthly!V126 -> 80.577421 | S9: =GDS_Monthly!W126 -> 60.470523 | T9: =GDS_Monthly!X126 -> 43.136454 | U9: =GDS_Monthly!AA126 -> 49.795764 | V9: =GDS_Monthly!AC126 -> 51.401241 | W9: =GDS_Monthly!AE126 -> 48.046108 | X9: =GDS_Monthly!AF126 -> 69.962439 | Y9: =OECD!B9 -> 100.6493 | Z9: ='Monthly Haver'!K12 -> 107.48695 | AA9: =OECD!C9 -> 98.8
A10: ='Monthly Haver'!A13 -> Sep-1999 | B10: ='Monthly Haver'!C13 -> 60.0914 | C10: ='Monthly Haver'!D13 -> 60.6433 | D10: ='Monthly Haver'!E13 -> #N/A | E10: ='Monthly Haver'!G13 -> 53.5119 | F10: ='Monthly Haver'!H13 -> 55.6868 | G10: ='Monthly Haver'!I13 -> #N/A | H10: ='Monthly Haver'!J13 -> 59.0417 | I10: =GDS_Monthly!O127 -> 50.49228 | J10: =GDS_Monthly!D127 -> 68.523687 | K10: =GDS_Monthly!AH127 -> 386.26317 | L10: =GDS_Monthly!AI127 -> 373.83512 | M10: =GDS_Monthly!N127 -> 6.056882 | N10: =GDS_Monthly!C127 -> 120.38194 | O10: =GDS_Monthly!F127 -> 5.1059576 | P10: =GDS_Monthly!G127 -> 4.8961511 | Q10: =GDS_Monthly!T127 -> 75.085929 | R10: =GDS_Monthly!V127 -> 80.794963 | S10: =GDS_Monthly!W127 -> 61.124873 | T10: =GDS_Monthly!X127 -> 45.284139 | U10: =GDS_Monthly!AA127 -> 50.773776 | V10: =GDS_Monthly!AC127 -> 54.866576 | W10: =GDS_Monthly!AE127 -> 52.726411 | X10: =GDS_Monthly!AF127 -> 72.033331 | Y10: =OECD!B10 -> 100.7834 | Z10: ='Monthly Haver'!K13 -> 106.8969 | AA10: =OECD!C10 -> 98.59
A11: ='Monthly Haver'!A14 -> Oct-1999 | B11: ='Monthly Haver'!C14 -> 60.8236 | C11: ='Monthly Haver'!D14 -> 60.5633 | D11: ='Monthly Haver'!E14 -> #N/A | E11: ='Monthly Haver'!G14 -> 54.1096 | F11: ='Monthly Haver'!H14 -> 56.535 | G11: ='Monthly Haver'!I14 -> #N/A | H11: ='Monthly Haver'!J14 -> 60.3565 | I11: =GDS_Monthly!O128 -> 51.101104 | J11: =GDS_Monthly!D128 -> 68.804682 | K11: =GDS_Monthly!AH128 -> 392.29851 | L11: =GDS_Monthly!AI128 -> 382.25044 | M11: =GDS_Monthly!N128 -> 6.0400035 | N11: =GDS_Monthly!C128 -> 119.67405 | O11: =GDS_Monthly!F128 -> 5.2650195 | P11: =GDS_Monthly!G128 -> 4.8657785 | Q11: =GDS_Monthly!T128 -> 75.269866 | R11: =GDS_Monthly!V128 -> 80.967736 | S11: =GDS_Monthly!W128 -> 60.768282 | T11: =GDS_Monthly!X128 -> 45.088045 | U11: =GDS_Monthly!AA128 -> 51.496589 | V11: =GDS_Monthly!AC128 -> 55.667194 | W11: =GDS_Monthly!AE128 -> 51.797968 | X11: =GDS_Monthly!AF128 -> 73.127539 | Y11: =OECD!B11 -> 100.92 | Z11: ='Monthly Haver'!K14 -> 105.97901 | AA11: =OECD!C11 -> 99.03
A12: ='Monthly Haver'!A15 -> Nov-1999 | B12: ='Monthly Haver'!C15 -> 58.6858 | C12: ='Monthly Haver'!D15 -> 60.7025 | D12: ='Monthly Haver'!E15 -> #N/A | E12: ='Monthly Haver'!G15 -> 53.7353 | F12: ='Monthly Haver'!H15 -> 56.9861 | G12: ='Monthly Haver'!I15 -> #N/A | H12: ='Monthly Haver'!J15 -> 58.1496 | I12: =GDS_Monthly!O129 -> 51.39213 | J12: =GDS_Monthly!D129 -> 69.593045 | K12: =GDS_Monthly!AH129 -> 398.3272 | L12: =GDS_Monthly!AI129 -> 386.34115 | M12: =GDS_Monthly!N129 -> 5.9962185 | N12: =GDS_Monthly!C129 -> 121.3529 | O12: =GDS_Monthly!F129 -> 5.1110059 | P12: =GDS_Monthly!G129 -> 5.0125876 | Q12: =GDS_Monthly!T129 -> 75.423186 | R12: =GDS_Monthly!V129 -> 81.113496 | S12: =GDS_Monthly!W129 -> 59.846721 | T12: =GDS_Monthly!X129 -> 45.822383 | U12: =GDS_Monthly!AA129 -> 51.154741 | V12: =GDS_Monthly!AC129 -> 58.050902 | W12: =GDS_Monthly!AE129 -> 57.073002 | X12: =GDS_Monthly!AF129 -> 72.918189 | Y12: =OECD!B12 -> 101.0557 | Z12: ='Monthly Haver'!K15 -> 106.29201 | AA12: =OECD!C12 -> 100.26
A13: ='Monthly Haver'!A16 -> Dec-1999 | B13: ='Monthly Haver'!C16 -> 60.1055 | C13: ='Monthly Haver'!D16 -> 61.061 | D13: ='Monthly Haver'!E16 -> #N/A | E13: ='Monthly Haver'!G16 -> 55.1018 | F13: ='Monthly Haver'!H16 -> 57.0833 | G13: ='Monthly Haver'!I16 -> #N/A | H13: ='Monthly Haver'!J16 -> 59.6569 | I13: =GDS_Monthly!O130 -> 52.092885 | J13: =GDS_Monthly!D130 -> 70.048401 | K13: =GDS_Monthly!AH130 -> 402.7765 | L13: =GDS_Monthly!AI130 -> 391.32497 | M13: =GDS_Monthly!N130 -> 5.9175586 | N13: =GDS_Monthly!C130 -> 122.67664 | O13: =GDS_Monthly!F130 -> 5.2360637 | P13: =GDS_Monthly!G130 -> 5.0387791 | Q13: =GDS_Monthly!T130 -> 75.584131 | R13: =GDS_Monthly!V130 -> 81.259895 | S13: =GDS_Monthly!W130 -> 60.138399 | T13: =GDS_Monthly!X130 -> 47.048003 | U13: =GDS_Monthly!AA130 -> 51.432125 | V13: =GDS_Monthly!AC130 -> 59.419051 | W13: =GDS_Monthly!AE130 -> 59.061798 | X13: =GDS_Monthly!AF130 -> 72.298999 | Y13: =OECD!B13 -> 101.1789 | Z13: ='Monthly Haver'!K16 -> 105.52177 | AA13: =OECD!C13 -> 100.67
... A244: ='Monthly Haver'!A247 -> Mar-2019 | B244: ='Monthly Haver'!C247 -> 52.7619 | C244: ='Monthly Haver'!D247 -> 54.4813 | D244: ='Monthly Haver'!E247 -> 49.3697 | E244: ='Monthly Haver'!G247 -> 51.6983 | F244: ='Monthly Haver'!H247 -> 50.4671 | G244: ='Monthly Haver'!I247 -> 50.0226 | H244: ='Monthly Haver'!J247 -> 53.6803 | I244: =GDS_Monthly!O361 -> 80.22797 | J244: =GDS_Monthly!D361 -> 132.42932 | K244: =GDS_Monthly!AH361 -> 1238.7038 | L244: =GDS_Monthly!AI361 -> 1229.916 | M244: =GDS_Monthly!N361 -> 5.0728347 | N244: =GDS_Monthly!C361 -> 113.51816 | O244: =GDS_Monthly!F361 -> 2.2890951 | P244: =GDS_Monthly!G361 -> 3.1449702 | Q244: =GDS_Monthly!T361 -> 156.60395 | R244: =GDS_Monthly!V361 -> 121.77907 | S244: =GDS_Monthly!W361 -> 99.372528 | T244: =GDS_Monthly!X361 -> 136.3354 | U244: =GDS_Monthly!AA361 -> 107.82633 | V244: =GDS_Monthly!AC361 -> 138.25637 | W244: =GDS_Monthly!AE361 -> 148.86005 | X244: =GDS_Monthly!AF361 -> 105.22629 | Y244: =OECD!B244 -> 99.14242 | Z244: ='Monthly Haver'!K247 -> 114.24212 | AA244: =OECD!C244 -> 122.17
A245: ='Monthly Haver'!A248 -> Apr-2019 | B245: ='Monthly Haver'!C248 -> 52.1603 | C245: ='Monthly Haver'!D248 -> 54.3991 | D245: ='Monthly Haver'!E248 -> 49.4335 | E245: ='Monthly Haver'!G248 -> 51.8311 | F245: ='Monthly Haver'!H248 -> 50.4081 | G245: ='Monthly Haver'!I248 -> 49.5417 | H245: ='Monthly Haver'!J248 -> 52.7489 | I245: ='Monthly Haver'!K248 -> 114.19804 | J245: =GDS_Monthly!D362 -> 132.31727 | K245: =GDS_Monthly!AH362 -> 1269.7616 | L245: =GDS_Monthly!AI362 -> 1211.9469 | N245: =GDS_Monthly!C362 -> 114.26388 | O245: =GDS_Monthly!F362 -> 2.2229008 | P245: =GDS_Monthly!G362 -> 3.2150048 | Q245: =GDS_Monthly!T362 -> 157.26 | R245: =GDS_Monthly!V362 -> 122.01064 | S245: =GDS_Monthly!W362 -> 102.9241 | T245: =GDS_Monthly!X362 -> 139.58372 | U245: =GDS_Monthly!AA362 -> 110.06277 | V245: =GDS_Monthly!AC362 -> 143.76829 | W245: =GDS_Monthly!AE362 -> 160.45415 | X245: =GDS_Monthly!AF362 -> 105.75931 | Y245: =OECD!B245 -> 99.08336 | Z245: ='Monthly Haver'!K248 -> 114.19804 | AA245: =OECD!C245 -> 122.79
A246: ='Monthly Haver'!A249 -> May-2019 | B246: ='Monthly Haver'!C249 -> 51.2808 | C246: ='Monthly Haver'!D249 -> 53.8632 | D246: ='Monthly Haver'!E249 -> 49.3222 | E246: ='Monthly Haver'!G249 -> 51.59 | F246: ='Monthly Haver'!H249 -> 49.7902 | G246: ='Monthly Haver'!I249 -> 49.1141 | H246: ='Monthly Haver'!J249 -> 51.5959 | I246: ='Monthly Haver'!K249 -> 115.07291 | J246: =GDS_Monthly!D363 -> 132.51547 | K246: =GDS_Monthly!AH363 -> 1252.5888 | L246: =GDS_Monthly!AI363 -> 1230.4544 | N246: =GDS_Monthly!C363 -> 114.51691 | O246: =GDS_Monthly!F363 -> 2.2379414 | P246: =GDS_Monthly!G363 -> 3.2956181 | Q246: =GDS_Monthly!T363 -> 157.80862 | R246: =GDS_Monthly!V363 -> 122.13418 | S246: =GDS_Monthly!W363 -> 99.497096 | T246: =GDS_Monthly!X363 -> 138.82798 | U246: =GDS_Monthly!AA363 -> 107.94329 | V246: =GDS_Monthly!AC363 -> 139.41056 | W246: =GDS_Monthly!AE363 -> 157.12436 | X246: =GDS_Monthly!AF363 -> 104.07285 | Z246: ='Monthly Haver'!K249 -> 115.07291 | AA246: =OECD!C246 -> 122.38
A247: ='Monthly Haver'!A250 -> Jun-2019 | B247: ='Monthly Haver'!C250 -> 51.614 | C247: ='Monthly Haver'!D250 -> 53.7104 | D247: ='Monthly Haver'!E250 -> 49.0546 | E247: ='Monthly Haver'!G250 -> 51.3163 | F247: ='Monthly Haver'!H250 -> 49.3994 | G247: ='Monthly Haver'!I250 -> 49.3243 | H247: ='Monthly Haver'!J250 -> 51.8967 | I247: ='Monthly Haver'!K250 -> 114.40336 | N247: =GDS_Monthly!C364 -> 112.55431 | O247: =GDS_Monthly!F364 -> 2.0337607 | P247: =GDS_Monthly!G364 -> 3.2454678 | Q247: =GDS_Monthly!T364 -> 158.30772 | R247: =GDS_Monthly!V364 -> 122.41596 | S247: =GDS_Monthly!W364 -> 98.39 | T247: =GDS_Monthly!X364 -> 141.33562 | U247: =GDS_Monthly!AA364 -> 109.09803 | V247: =GDS_Monthly!AC364 -> 123.53232 | W247: =GDS_Monthly!AE364 -> 139.91704 | X247: =GDS_Monthly!AF364 -> 104.37517 | Z247: ='Monthly Haver'!K250 -> 114.40336 | AA247: =OECD!C247 -> 122.19

Sheet Quarterly
B1: House | C1: RINC | D1: NGDPR
A2: 1999/Q1 | B2: ='Quarterly Haver'!C4 -> 90.78 | C2: ='Quarterly Haver'!D4 -> 79.11 | D2: =GDS_Quarterly!V45 -> 74.840694
A3: 1999/Q2 | B3: ='Quarterly Haver'!C5 -> 91.21 | C3: ='Quarterly Haver'!D5 -> 79.57 | D3: =GDS_Quarterly!V46 -> 75.435941
A4: 1999/Q3 | B4: ='Quarterly Haver'!C6 -> 91.6 | C4: ='Quarterly Haver'!D6 -> 80.17 | D4: =GDS_Quarterly!V47 -> 76.3051
A5: 1999/Q4 | B5: ='Quarterly Haver'!C7 -> 92.31 | C5: ='Quarterly Haver'!D7 -> 80.64 | D5: =GDS_Quarterly!V48 -> 77.3522
A6: 2000/Q1 | B6: ='Quarterly Haver'!C8 -> 92.62 | C6: ='Quarterly Haver'!D8 -> 81.07 | D6: =GDS_Quarterly!V49 -> 78.209604
A7: 2000/Q2 | B7: ='Quarterly Haver'!C9 -> 93.26 | C7: ='Quarterly Haver'!D9 -> 81.79 | D7: =GDS_Quarterly!V50 -> 79.106542
A8: 2000/Q3 | B8: ='Quarterly Haver'!C10 -> 93.68 | C8: ='Quarterly Haver'!D10 -> 82.14 | D8: =GDS_Quarterly!V51 -> 79.516129
A9: 2000/Q4 | B9: ='Quarterly Haver'!C11 -> 94.18 | C9: ='Quarterly Haver'!D11 -> 82.67 | D9: =GDS_Quarterly!V52 -> 80.047337
A10: 2001/Q1 | B10: ='Quarterly Haver'!C12 -> 94.75 | C10: ='Quarterly Haver'!D12 -> 83.25 | D10: =GDS_Quarterly!V53 -> 80.343371
A11: 2001/Q2 | B11: ='Quarterly Haver'!C13 -> 94.74 | C11: ='Quarterly Haver'!D13 -> 83.79 | D11: =GDS_Quarterly!V54 -> 80.571894
A12: 2001/Q3 | B12: ='Quarterly Haver'!C14 -> 95.47 | C12: ='Quarterly Haver'!D14 -> 84.6 | D12: =GDS_Quarterly!V55 -> 80.481747
A13: 2001/Q4 | B13: ='Quarterly Haver'!C15 -> 95.57 | C13: ='Quarterly Haver'!D15 -> 85.2 | D13: =GDS_Quarterly!V56 -> 80.678962
... A82: 2019/Q1 | B82: ='Quarterly Haver'!C84 -> 116.43 | C82: ='Quarterly Haver'!D84 -> 107.08 | D82: =GDS_Quarterly!V125 -> 125.99628
A83: 2019/Q2

Sheet data
A1: date | B1: PMINO | C1: PMIALL | D1: PMINXO | E1: EMPPMI | F1: PMIM | G1: Inve | H1: PMIS | I1: Sales | J1: INDPRO | K1: BOPTIMP | L1: BOPTEXP | M1: UNRATE | N1: ECC | O1: LRIR | P1: STIR | Q1: CPI | R1: CCPI | S1: Food | T1: Metal | U1: COMPNF | V1: Energy | W1: Oil | X1: Raw | Y1: OECDCLI | Z1: CHEM | AA1: REERUS | AB1: BDIY | AC1: House | AD1: RINC | AE1: NGDPR
A2: 36161 | B2: ='Monthly Haver'!C5 -> 53.5976 | C2: ='Monthly Haver'!D5 -> 42.7203 | D2: ='Monthly Haver'!E5 -> #N/A | E2: ='Monthly Haver'!G5 -> 50.8256 | F2: ='Monthly Haver'!H5 -> 48.7254 | G2: ='Monthly Haver'!I5 -> #N/A | H2: ='Monthly Haver'!J5 -> 55.6953 | I2: =GDS_Monthly!O119 -> 48.077038 | J2: =GDS_Monthly!D119 -> 65.769752 | K2: =GDS_Monthly!AH119 -> 349.18549 | L2: =GDS_Monthly!AI119 -> 344.37955 | M2: =GDS_Monthly!N119 -> 6.1873546 | N2: =GDS_Monthly!C119 -> 118.64823 | O2: =GDS_Monthly!F119 -> 4.1411999 | P2: =GDS_Monthly!G119 -> 5.8914995 | Q2: =GDS_Monthly!T119 -> 73.68393 | R2: =GDS_Monthly!V119 -> 79.695601 | S2: =GDS_Monthly!W119 -> 67.003805 | T2: =GDS_Monthly!X119 -> 36.397902 | U2: =GDS_Monthly!AA119 -> 52.616127 | V2: =GDS_Monthly!AC119 -> 32.584569 | W2: =GDS_Monthly!AE119 -> 26.140204 | X2: =GDS_Monthly!AF119 -> 69.791518 | Y2: =OECD!B2 -> 99.47476 | Z2: =OECD!C2 -> 95.61 | AA2: ='Monthly Haver'!K5 -> 104.74784 | AB2: ='Monthly Haver'!L5 -> 803
A3: 36192 | B3: ='Monthly Haver'!C6 -> 54.1254 | C3: ='Monthly Haver'!D6 -> 42.8611 | D3: ='Monthly Haver'!E6 -> #N/A | E3: ='Monthly Haver'!G6 -> 51.4539 | F3: ='Monthly Haver'!H6 -> 49.8581 | G3: ='Monthly Haver'!I6 -> #N/A | H3: ='Monthly Haver'!J6 -> 55.325 | I3: =GDS_Monthly!O120 -> 48.406006 | J3: =GDS_Monthly!D120 -> 66.075294 | K3: =GDS_Monthly!AH120 -> 350.14039 | L3: =GDS_Monthly!AI120 -> 338.62962 | M3: =GDS_Monthly!N120 -> 6.1959605 | N3: =GDS_Monthly!C120 -> 119.73876 | O3: =GDS_Monthly!F120 -> 4.3355312 | P3: =GDS_Monthly!G120 -> 5.6829416 | Q3: =GDS_Monthly!T120 -> 73.779357 | R3: =GDS_Monthly!V120 -> 79.780902 | S3: =GDS_Monthly!W120 -> 62.091429 | T3: =GDS_Monthly!X120 -> 36.917985 | U3: =GDS_Monthly!AA120 -> 50.415246 | V3: =GDS_Monthly!AC120 -> 31.458463 | W3: =GDS_Monthly!AE120 -> 25.242365 | X3: =GDS_Monthly!AF120 -> 69.661742 | Y3: =OECD!B3 -> 99.66687 | Z3: =OECD!C3 -> 96.34 | AA3: ='Monthly Haver'!K6 -> 105.57661 | AB3: ='Monthly Haver'!L6 -> 836
A4: 36220 | B4: ='Monthly Haver'!C7 -> 55.3837 | C4: ='Monthly Haver'!D7 -> 46.3136 | D4: ='Monthly Haver'!E7 -> #N/A | E4: ='Monthly Haver'!G7 -> 51.4596 | F4: ='Monthly Haver'!H7 -> 50.7334 | G4: ='Monthly Haver'!I7 -> #N/A | H4: ='Monthly Haver'!J7 -> 56.9761 | I4: =GDS_Monthly!O121 -> 49.16041 | J4: =GDS_Monthly!D121 -> 66.415605 | K4: =GDS_Monthly!AH121 -> 354.29676 | L4: =GDS_Monthly!AI121 -> 346.8056 | M4: =GDS_Monthly!N121 -> 6.1959564 | N4: =GDS_Monthly!C121 -> 119.74111 | O4: =GDS_Monthly!F121 -> 4.4350289 | P4: =GDS_Monthly!G121 -> 6.0031129 | Q4: =GDS_Monthly!T121 -> 73.933111 | R4: =GDS_Monthly!V121 -> 79.923392 | S4: =GDS_Monthly!W121 -> 60.29823 | T4: =GDS_Monthly!X121 -> 37.299843 | U4: =GDS_Monthly!AA121 -> 49.620259 | V4: =GDS_Monthly!AC121 -> 34.981861 | W4: =GDS_Monthly!AE121 -> 30.593839 | X4: =GDS_Monthly!AF121 -> 70.57853 | Y4: =OECD!B4 -> 99.85615 | Z4: =OECD!C4 -> 96.64 | AA4: ='Monthly Haver'!K7 -> 106.59589 | AB4: ='Monthly Haver'!L7 -> 967 | AC4: =Quarterly!B2 -> 90.78 | AD4: =Quarterly!C2 -> 79.11 | AE4: =Quarterly!D2 -> 74.840694
A5: 36251 | B5: ='Monthly Haver'!C8 -> 55.9987 | C5: ='Monthly Haver'!D8 -> 49.0474 | D5: ='Monthly Haver'!E8 -> #N/A | E5: ='Monthly Haver'!G8 -> 52.0892 | F5: ='Monthly Haver'!H8 -> 51.2542 | G5: ='Monthly Haver'!I8 -> #N/A | H5: ='Monthly Haver'!J8 -> 57.5913 | I5: =GDS_Monthly!O122 -> 49.075054 | J5: =GDS_Monthly!D122 -> 66.629597 | K5: =GDS_Monthly!AH122 -> 351.9353 | L5: =GDS_Monthly!AI122 -> 345.62785 | M5: =GDS_Monthly!N122 -> 6.1866463 | N5: =GDS_Monthly!C122 -> 120.24442 | O5: =GDS_Monthly!F122 -> 4.3134206 | P5: =GDS_Monthly!G122 -> 5.3771072 | Q5: =GDS_Monthly!T122 -> 74.215742 | R5: =GDS_Monthly!V122 -> 80.100241 | S5: =GDS_Monthly!W122 -> 61.554135 | T5: =GDS_Monthly!X122 -> 38.769809 | U5: =GDS_Monthly!AA122 -> 50.212478 | V5: =GDS_Monthly!AC122 -> 40.728868 | W5: =GDS_Monthly!AE122 -> 37.660442 | X5: =GDS_Monthly!AF122 -> 69.408326 | Y5: =OECD!B5 -> 100.0378 | Z5: =OECD!C5 -> 97.25 | AA5: ='Monthly Haver'!K8 -> 106.42206 | AB5: ='Monthly Haver'!L8 -> 924
A6: 36281 | B6: ='Monthly Haver'!C9 -> 55.9166 | C6: ='Monthly Haver'!D9 -> 51.0918 | D6: ='Monthly Haver'!E9 -> #N/A | E6: ='Monthly Haver'!G9 -> 52.6932 | F6: ='Monthly Haver'!H9 -> 52.3421 | G6: ='Monthly Haver'!I9 -> #N/A | H6: ='Monthly Haver'!J9 -> 56.5726 | I6: =GDS_Monthly!O123 -> 49.382125 | J6: =GDS_Monthly!D123 -> 67.10158 | K6: =GDS_Monthly!AH123 -> 358.04078 | L6: =GDS_Monthly!AI123 -> 348.3689 | M6: =GDS_Monthly!N123 -> 6.1382055 | N6: =GDS_Monthly!C123 -> 120.84511 | O6: =GDS_Monthly!F123 -> 4.5000857 | P6: =GDS_Monthly!G123 -> 4.9508609 | Q6: =GDS_Monthly!T123 -> 74.300179 | R6: =GDS_Monthly!V123 -> 80.22882 | S6: =GDS_Monthly!W123 -> 62.21842 | T6: =GDS_Monthly!X123 -> 39.98686 | U6: =GDS_Monthly!AA123 -> 50.768578 | V6: =GDS_Monthly!AC123 -> 42.045514 | W6: =GDS_Monthly!AE123 -> 38.766827 | X6: =GDS_Monthly!AF123 -> 71.430794 | Y6: =OECD!B6 -> 100.2077 | Z6: =OECD!C6 -> 98.12 | AA6: ='Monthly Haver'!K9 -> 107.02515 | AB6: ='Monthly Haver'!L9 -> 1063
A7: 36312 | B7: ='Monthly Haver'!C10 -> 57.8804 | C7: ='Monthly Haver'!D10 -> 52.1057 | D7: ='Monthly Haver'!E10 -> #N/A | E7: ='Monthly Haver'!G10 -> 53.68 | F7: ='Monthly Haver'!H10 -> 53.5438 | G7: ='Monthly Haver'!I10 -> #N/A | H7: ='Monthly Haver'!J10 -> 57.4603 | I7: =GDS_Monthly!O124 -> 49.869137 | J7: =GDS_Monthly!D124 -> 67.297968 | K7: =GDS_Monthly!AH124 -> 367.78941 | L7: =GDS_Monthly!AI124 -> 351.41149 | M7: =GDS_Monthly!N124 -> 6.1365166 | N7: =GDS_Monthly!C124 -> 121.41547 | O7: =GDS_Monthly!F124 -> 4.8230243 | P7: =GDS_Monthly!G124 -> 4.8849127 | Q7: =GDS_Monthly!T124 -> 74.394391 | R7: =GDS_Monthly!V124 -> 80.334105 | S7: =GDS_Monthly!W124 -> 60.478859 | T7: =GDS_Monthly!X124 -> 39.018173 | U7: =GDS_Monthly!AA124 -> 49.411856 | V7: =GDS_Monthly!AC124 -> 42.719851 | W7: =GDS_Monthly!AE124 -> 39.30779 | X7: =GDS_Monthly!AF124 -> 71.122848 | Y7: =OECD!B7 -> 100.3658 | Z7: =OECD!C7 -> 98.7 | AA7: ='Monthly Haver'!K10 -> 108.0101 | AB7: ='Monthly Haver'!L10 -> 989 | AC7: =Quarterly!B3 -> 91.21 | AD7: =Quarterly!C3 -> 79.57 | AE7: =Quarterly!D3 -> 75.435941
A8: 36342 | B8: ='Monthly Haver'!C11 -> 57.3138 | C8: ='Monthly Haver'!D11 -> 54.7592 | D8: ='Monthly Haver'!E11 -> #N/A | E8: ='Monthly Haver'!G11 -> 53.4233 | F8: ='Monthly Haver'!H11 -> 53.1272 | G8: ='Monthly Haver'!I11 -> #N/A | H8: ='Monthly Haver'!J11 -> 59.4464 | I8: =GDS_Monthly!O125 -> 50.15593 | J8: =GDS_Monthly!D125 -> 67.70597 | K8: =GDS_Monthly!AH125 -> 368.50261 | L8: =GDS_Monthly!AI125 -> 360.31608 | M8: =GDS_Monthly!N125 -> 6.1104934 | N8: =GDS_Monthly!C125 -> 120.79869 | O8: =GDS_Monthly!F125 -> 4.9034123 | P8: =GDS_Monthly!G125 -> 4.7486677 | Q8: =GDS_Monthly!T125 -> 74.643657 | R8: =GDS_Monthly!V125 -> 80.483604 | S8: =GDS_Monthly!W125 -> 58.803777 | T8: =GDS_Monthly!X125 -> 41.904733 | U8: =GDS_Monthly!AA125 -> 48.820283 | V8: =GDS_Monthly!AC125 -> 47.300332 | W8: =GDS_Monthly!AE125 -> 45.405164 | X8: =GDS_Monthly!AF125 -> 70.073576 | Y8: =OECD!B8 -> 100.5119 | Z8: =OECD!C8 -> 98.78 | AA8: ='Monthly Haver'!K11 -> 107.85083 | AB8: ='Monthly Haver'!L11 -> 977
A9: 36373 | B9: ='Monthly Haver'!C12 -> 58.4475 | C9: ='Monthly Haver'!D12 -> 56.783 | D9: ='Monthly Haver'!E12 -> #N/A | E9: ='Monthly Haver'!G12 -> 53.5661 | F9: ='Monthly Haver'!H12 -> 54.0798 | G9: ='Monthly Haver'!I12 -> #N/A | H9: ='Monthly Haver'!J12 -> 59.4645 | I9: =GDS_Monthly!O126 -> 50.509429 | J9: =GDS_Monthly!D126 -> 68.083457 | K9: =GDS_Monthly!AH126 -> 376.68885 | L9: =GDS_Monthly!AI126 -> 366.10527 | M9: =GDS_Monthly!N126 -> 6.0866329 | N9: =GDS_Monthly!C126 -> 120.798 | O9: =GDS_Monthly!F126 -> 5.0665058 | P9: =GDS_Monthly!G126 -> 4.8153151 | Q9: =GDS_Monthly!T126 -> 74.856086 | R9: =GDS_Monthly!V126 -> 80.577421 | S9: =GDS_Monthly!W126 -> 60.470523 | T9: =GDS_Monthly!X126 -> 43.136454 | U9: =GDS_Monthly!AA126 -> 49.795764 | V9: =GDS_Monthly!AC126 -> 51.401241 | W9: =GDS_Monthly!AE126 -> 48.046108 | X9: =GDS_Monthly!AF126 -> 69.962439 | Y9: =OECD!B9 -> 100.6493 | Z9: =OECD!C9 -> 98.8 | AA9: ='Monthly Haver'!K12 -> 107.48695 | AB9: ='Monthly Haver'!L12 -> 1046
A10: 36404 | B10: ='Monthly Haver'!C13 -> 60.0914 | C10: ='Monthly Haver'!D13 -> 60.6433 | D10: ='Monthly Haver'!E13 -> #N/A | E10: ='Monthly Haver'!G13 -> 53.5119 | F10: ='Monthly Haver'!H13 -> 55.6868 | G10: ='Monthly Haver'!I13 -> #N/A | H10: ='Monthly Haver'!J13 -> 59.0417 | I10: =GDS_Monthly!O127 -> 50.49228 | J10: =GDS_Monthly!D127 -> 68.523687 | K10: =GDS_Monthly!AH127 -> 386.26317 | L10: =GDS_Monthly!AI127 -> 373.83512 | M10: =GDS_Monthly!N127 -> 6.056882 | N10: =GDS_Monthly!C127 -> 120.38194 | O10: =GDS_Monthly!F127 -> 5.1059576 | P10: =GDS_Monthly!G127 -> 4.8961511 | Q10: =GDS_Monthly!T127 -> 75.085929 | R10: =GDS_Monthly!V127 -> 80.794963 | S10: =GDS_Monthly!W127 -> 61.124873 | T10: =GDS_Monthly!X127 -> 45.284139 | U10: =GDS_Monthly!AA127 -> 50.773776 | V10: =GDS_Monthly!AC127 -> 54.866576 | W10: =GDS_Monthly!AE127 -> 52.726411 | X10: =GDS_Monthly!AF127 -> 72.033331 | Y10: =OECD!B10 -> 100.7834 | Z10: =OECD!C10 -> 98.59 | AA10: ='Monthly Haver'!K13 -> 106.8969 | AB10: ='Monthly Haver'!L13 -> 1146 | AC10: =Quarterly!B4 -> 91.6 | AD10: =Quarterly!C4 -> 80.17 | AE10: =Quarterly!D4 -> 76.3051
A11: 36434 | B11: ='Monthly Haver'!C14 -> 60.8236 | C11: ='Monthly Haver'!D14 -> 60.5633 | D11: ='Monthly Haver'!E14 -> #N/A | E11: ='Monthly Haver'!G14 -> 54.1096 | F11: ='Monthly Haver'!H14 -> 56.535 | G11: ='Monthly Haver'!I14 -> #N/A | H11: ='Monthly Haver'!J14 -> 60.3565 | I11: =GDS_Monthly!O128 -> 51.101104 | J11: =GDS_Monthly!D128 -> 68.804682 | K11: =GDS_Monthly!AH128 -> 392.29851 | L11: =GDS_Monthly!AI128 -> 382.25044 | M11: =GDS_Monthly!N128 -> 6.0400035 | N11: =GDS_Monthly!C128 -> 119.67405 | O11: =GDS_Monthly!F128 -> 5.2650195 | P11: =GDS_Monthly!G128 -> 4.8657785 | Q11: =GDS_Monthly!T128 -> 75.269866 | R11: =GDS_Monthly!V128 -> 80.967736 | S11: =GDS_Monthly!W128 -> 60.768282 | T11: =GDS_Monthly!X128 -> 45.088045 | U11: =GDS_Monthly!AA128 -> 51.496589 | V11: =GDS_Monthly!AC128 -> 55.667194 | W11: =GDS_Monthly!AE128 -> 51.797968 | X11: =GDS_Monthly!AF128 -> 73.127539 | Y11: =OECD!B11 -> 100.92 | Z11: =OECD!C11 -> 99.03 | AA11: ='Monthly Haver'!K14 -> 105.97901 | AB11: ='Monthly Haver'!L14 -> 1339
A12: 36465 | B12: ='Monthly Haver'!C15 -> 58.6858 | C12: ='Monthly Haver'!D15 -> 60.7025 | D12: ='Monthly Haver'!E15 -> #N/A | E12: ='Monthly Haver'!G15 -> 53.7353 | F12: ='Monthly Haver'!H15 -> 56.9861 | G12: ='Monthly Haver'!I15 -> #N/A | H12: ='Monthly Haver'!J15 -> 58.1496 | I12: =GDS_Monthly!O129 -> 51.39213 | J12: =GDS_Monthly!D129 -> 69.593045 | K12: =GDS_Monthly!AH129 -> 398.3272 | L12: =GDS_Monthly!AI129 -> 386.34115 | M12: =GDS_Monthly!N129 -> 5.9962185 | N12: =GDS_Monthly!C129 -> 121.3529 | O12: =GDS_Monthly!F129 -> 5.1110059 | P12: =GDS_Monthly!G129 -> 5.0125876 | Q12: =GDS_Monthly!T129 -> 75.423186 | R12: =GDS_Monthly!V129 -> 81.113496 | S12: =GDS_Monthly!W129 -> 59.846721 | T12: =GDS_Monthly!X129 -> 45.822383 | U12: =GDS_Monthly!AA129 -> 51.154741 | V12: =GDS_Monthly!AC129 -> 58.050902 | W12: =GDS_Monthly!AE129 -> 57.073002 | X12: =GDS_Monthly!AF129 -> 72.918189 | Y12: =OECD!B12 -> 101.0557 | Z12: =OECD!C12 -> 100.26 | AA12: ='Monthly Haver'!K15 -> 106.29201 | AB12: ='Monthly Haver'!L15 -> 1334
A13: 36495 | B13: ='Monthly Haver'!C16 -> 60.1055 | C13: ='Monthly Haver'!D16 -> 61.061 | D13: ='Monthly Haver'!E16 -> #N/A | E13: ='Monthly Haver'!G16 -> 55.1018 | F13: ='Monthly Haver'!H16 -> 57.0833 | G13: ='Monthly Haver'!I16 -> #N/A | H13: ='Monthly Haver'!J16 -> 59.6569 | I13: =GDS_Monthly!O130 -> 52.092885 | J13: =GDS_Monthly!D130 -> 70.048401 | K13: =GDS_Monthly!AH130 -> 402.7765 | L13: =GDS_Monthly!AI130 -> 391.32497 | M13: =GDS_Monthly!N130 -> 5.9175586 | N13: =GDS_Monthly!C130 -> 122.67664 | O13: =GDS_Monthly!F130 -> 5.2360637 | P13: =GDS_Monthly!G130 -> 5.0387791 | Q13: =GDS_Monthly!T130 -> 75.584131 | R13: =GDS_Monthly!V130 -> 81.259895 | S13: =GDS_Monthly!W130 -> 60.138399 | T13: =GDS_Monthly!X130 -> 47.048003 | U13: =GDS_Monthly!AA130 -> 51.432125 | V13: =GDS_Monthly!AC130 -> 59.419051 | W13: =GDS_Monthly!AE130 -> 59.061798 | X13: =GDS_Monthly!AF130 -> 72.298999 | Y13: =OECD!B13 -> 101.1789 | Z13: =OECD!C13 -> 100.67 | AA13: ='Monthly Haver'!K16 -> 105.52177 | AB13: ='Monthly Haver'!L16 -> 1343 | AC13: =Quarterly!B5 -> 92.31 | AD13: =Quarterly!C5 -> 80.64 | AE13: =Quarterly!D5 -> 77.3522
A14: 36526 | B14: ='Monthly Haver'!C17 -> 59.7214 | C14: ='Monthly Haver'!D17 -> 62.9701 | D14: ='Monthly Haver'!E17 -> #N/A | E14: ='Monthly Haver'!G17 -> 54.1181 | F14: ='Monthly Haver'!H17 -> 55.3667 | G14: ='Monthly Haver'!I17 -> #N/A | H14: ='Monthly Haver'!J17 -> 57.9939 | I14: =GDS_Monthly!O131 -> 51.968852 | J14: =GDS_Monthly!D131 -> 69.948356 | K14: =GDS_Monthly!AH131 -> 411.62879 | L14: =GDS_Monthly!AI131 -> 395.758 | M14: =GDS_Monthly!N131 -> 6.0557452 | N14: =GDS_Monthly!C131 -> 124.77493 | O14: =GDS_Monthly!F131 -> 5.558823 | P14: =GDS_Monthly!G131 -> 4.994757 | Q14: =GDS_Monthly!T131 -> 75.804844 | R14: =GDS_Monthly!V131 -> 81.447876 | S14: =GDS_Monthly!W131 -> 60.989121 | T14: =GDS_Monthly!X131 -> 49.224077 | U14: =GDS_Monthly!AA131 -> 52.005077 | V14: =GDS_Monthly!AC131 -> 62.420219 | W14: =GDS_Monthly!AE131 -> 59.634459 | X14: =GDS_Monthly!AF131 -> 71.264288 | Y14: =OECD!B14 -> 101.2785 | Z14: =OECD!C14 -> 100.84 | AA14: ='Monthly Haver'!K17 -> 105.34898 | AB14: ='Monthly Haver'!L17 -> 1371
A15: 36557 | B15: ='Monthly Haver'!C18 -> 58.9174 | C15: ='Monthly Haver'!D18 -> 65.123 | D15: ='Monthly Haver'!E18 -> #N/A | E15: ='Monthly Haver'!G18 -> 54.6487 | F15: ='Monthly Haver'!H18 -> 55.2976 | G15: ='Monthly Haver'!I18 -> #N/A | H15: ='Monthly Haver'!J18 -> 58.2848 | I15: =GDS_Monthly!O132 -> 52.57472 | J15: =GDS_Monthly!D132 -> 70.626537 | K15: =GDS_Monthly!AH132 -> 419.8679 | L15: =GDS_Monthly!AI132 -> 400.5614 | M15: =GDS_Monthly!N132 -> 6.0939709 | N15: =GDS_Monthly!C132 -> 123.62122 | O15: =GDS_Monthly!F132 -> 5.4796886 | P15: =GDS_Monthly!G132 -> 5.1296117 | Q15: =GDS_Monthly!T132 -> 76.032179 | R15: =GDS_Monthly!V132 -> 81.554432 | S15: =GDS_Monthly!W132 -> 61.737525 | T15: =GDS_Monthly!X132 -> 50.275821 | U15: =GDS_Monthly!AA132 -> 53.28564 | V15: =GDS_Monthly!AC132 -> 66.611449 | W15: =GDS_Monthly!AE132 -> 65.421333 | X15: =GDS_Monthly!AF132 -> 74.784893 | Y15: =OECD!B15 -> 101.3352 | Z15: =OECD!C15 -> 100.41 | AA15: ='Monthly Haver'!K18 -> 107.37936 | AB15: ='Monthly Haver'!L18 -> 1393
A16: 36586 | B16: ='Monthly Haver'!C19 -> 60.2247 | C16: ='Monthly Haver'!D19 -> 67.6544 | D16: ='Monthly Haver'!E19 -> #N/A | E16: ='Monthly Haver'!G19 -> 55.2528 | F16: ='Monthly Haver'!H19 -> 55.6432 | G16: ='Monthly Haver'!I19 -> #N/A | H16: ='Monthly Haver'!J19 -> 60.3654 | I16: =GDS_Monthly!O133 -> 52.642093 | J16: =GDS_Monthly!D133 -> 71.031649 | K16: =GDS_Monthly!AH133 -> 421.49161 | L16: =GDS_Monthly!AI133 -> 400.2803 | M16: =GDS_Monthly!N133 -> 6.0347977 | N16: =GDS_Monthly!C133 -> 122.5322 | O16: =GDS_Monthly!F133 -> 5.3142515 | P16: =GDS_Monthly!G133 -> 5.1964189 | Q16: =GDS_Monthly!T133 -> 76.252037 | R16: =GDS_Monthly!V133 -> 81.714243 | S16: =GDS_Monthly!W133 -> 62.852084 | T16: =GDS_Monthly!X133 -> 49.805626 | U16: =GDS_Monthly!AA133 -> 53.623751 | V16: =GDS_Monthly!AC133 -> 67.225029 | W16: =GDS_Monthly!AE133 -> 66.343979 | X16: =GDS_Monthly!AF133 -> 75.959245 | Y16: =OECD!B16 -> 101.3501 | Z16: =OECD!C16 -> 101.06 | AA16: ='Monthly Haver'!K19 -> 107.6039 | AB16: ='Monthly Haver'!L19 -> 1621 | AC16: =Quarterly!B6 -> 92.62 | AD16: =Quarterly!C6 -> 81.07 | AE16: =Quarterly!D6 -> 78.209604
A17: 36617 | B17: ='Monthly Haver'!C20 -> 60.3385 | C17: ='Monthly Haver'!D20 -> 64.9144 | D17: ='Monthly Haver'!E20 -> #N/A | E17: ='Monthly Haver'!G20 -> 55.7743 | F17: ='Monthly Haver'!H20 -> 55.9987 | G17: ='Monthly Haver'!I20 -> #N/A | H17: ='Monthly Haver'!J20 -> 61.1896 | I17: =GDS_Monthly!O134 -> 52.812581 | J17: =GDS_Monthly!D134 -> 71.603604 | K17: =GDS_Monthly!AH134 -> 419.81718 | L17: =GDS_Monthly!AI134 -> 398.96674 | M17: =GDS_Monthly!N134 -> 5.9011947 | N17: =GDS_Monthly!C134 -> 122.53862 | O17: =GDS_Monthly!F134 -> 5.1670327 | P17: =GDS_Monthly!G134 -> 5.2904901 | Q17: =GDS_Monthly!T134 -> 76.343107 | R17: =GDS_Monthly!V134 -> 81.802822 | S17: =GDS_Monthly!W134 -> 65.620616 | T17: =GDS_Monthly!X134 -> 47.738663 | U17: =GDS_Monthly!AA134 -> 54.216292 | V17: =GDS_Monthly!AC134 -> 61.406298 | W17: =GDS_Monthly!AE134 -> 56.789454 | X17: =GDS_Monthly!AF134 -> 75.442087 | Y17: =OECD!B17 -> 101.3254 | Z17: =OECD!C17 -> 101.16 | AA17: ='Monthly Haver'!K20 -> 107.93076 | AB17: ='Monthly Haver'!L20 -> 1667
A18: 36647 | B18: ='Monthly Haver'!C21 -> 58.7486 | C18: ='Monthly Haver'!D21 -> 64.1095 | D18: ='Monthly Haver'!E21 -> #N/A | E18: ='Monthly Haver'!G21 -> 55.4879 | F18: ='Monthly Haver'!H21 -> 54.8953 | G18: ='Monthly Haver'!I21 -> #N/A | H18: ='Monthly Haver'!J21 -> 60.0442 | I18: =GDS_Monthly!O135 -> 53.058477 | J18: =GDS_Monthly!D135 -> 72.248563 | K18: =GDS_Monthly!AH135 -> 429.87162 | L18: =GDS_Monthly!AI135 -> 407.68689 | M18: =GDS_Monthly!N135 -> 5.8812789 | N18: =GDS_Monthly!C135 -> 124.44341 | O18: =GDS_Monthly!F135 -> 5.3815822 | P18: =GDS_Monthly!G135 -> 5.438324 | Q18: =GDS_Monthly!T135 -> 76.478122 | R18: =GDS_Monthly!V135 -> 81.948747 | S18: =GDS_Monthly!W135 -> 64.699432 | T18: =GDS_Monthly!X135 -> 48.89688 | U18: =GDS_Monthly!AA135 -> 53.981809 | V18: =GDS_Monthly!AC135 -> 68.959928 | W18: =GDS_Monthly!AE135 -> 67.346607 | X18: =GDS_Monthly!AF135 -> 76.366215 | Y18: =OECD!B18 -> 101.2619 | Z18: =OECD!C18 -> 100.53 | AA18: ='Monthly Haver'!K21 -> 110.65881 | AB18: ='Monthly Haver'!L21 -> 1602
A19: 36678 | B19: ='Monthly Haver'!C22 -> 57.7838 | C19: ='Monthly Haver'!D22 -> 63.6168 | D19: ='Monthly Haver'!E22 -> #N/A | E19: ='Monthly Haver'!G22 -> 55.34 | F19: ='Monthly Haver'!H22 -> 53.8387 | G19: ='Monthly Haver'!I22 -> #N/A | H19: ='Monthly Haver'!J22 -> 60.0799 | I19: =GDS_Monthly!O136 -> 53.447755 | J19: =GDS_Monthly!D136 -> 72.390256 | K19: =GDS_Monthly!AH136 -> 440.28409 | L19: =GDS_Monthly!AI136 -> 416.44567 | M19: =GDS_Monthly!N136 -> 5.8607619 | N19: =GDS_Monthly!C136 -> 122.89815 | O19: =GDS_Monthly!F136 -> 5.1788728 | P19: =GDS_Monthly!G136 -> 5.5831424 | Q19: =GDS_Monthly!T136 -> 76.816057 | R19: =GDS_Monthly!V136 -> 82.110614 | S19: =GDS_Monthly!W136 -> 62.510041 | T19: =GDS_Monthly!X136 -> 46.758789 | U19: =GDS_Monthly!AA136 -> 52.70486 | V19: =GDS_Monthly!AC136 -> 75.499491 | W19: =GDS_Monthly!AE136 -> 72.152931 | X19: =GDS_Monthly!AF136 -> 75.144639 | Y19: =OECD!B19 -> 101.1674 | Z19: =OECD!C19 -> 100.36 | AA19: ='Monthly Haver'!K22 -> 111.02235 | AB19: ='Monthly Haver'!L22 -> 1589 | AC19: =Quarterly!B7 -> 93.26 | AD19: =Quarterly!C7 -> 81.79 | AE19: =Quarterly!D7 -> 79.106542
A20: 36708 | B20: ='Monthly Haver'!C23 -> 58.13 | C20: ='Monthly Haver'!D23 -> 62.6538 | D20: ='Monthly Haver'!E23 -> #N/A | E20: ='Monthly Haver'!G23 -> 54.0334 | F20: ='Monthly Haver'!H23 -> 54.2621 | G20: ='Monthly Haver'!I23 -> #N/A | H20: ='Monthly Haver'!J23 -> 57.7018 | I20: =GDS_Monthly!O137 -> 53.605511 | J20: =GDS_Monthly!D137 -> 72.625104 | K20: =GDS_Monthly!AH137 -> 440.99594 | L20: =GDS_Monthly!AI137 -> 414.20484 | M20: =GDS_Monthly!N137 -> 5.8360978 | N20: =GDS_Monthly!C137 -> 124.04487 | O20: =GDS_Monthly!F137 -> 5.195001 | P20: =GDS_Monthly!G137 -> 5.4860479 | Q20: =GDS_Monthly!T137 -> 77.084292 | R20: =GDS_Monthly!V137 -> 82.23398 | S20: =GDS_Monthly!W137 -> 60.617604 | T20: =GDS_Monthly!X137 -> 47.341899 | U20: =GDS_Monthly!AA137 -> 51.906612 | V20: =GDS_Monthly!AC137 -> 73.041609 | W20: =GDS_Monthly!AE137 -> 68.971892 | X20: =GDS_Monthly!AF137 -> 73.574183 | Y20: =OECD!B20 -> 101.0446 | Z20: =OECD!C20 -> 99.81 | AA20: ='Monthly Haver'!K23 -> 110.71349 | AB20: ='Monthly Haver'!L23 -> 1618
A21: 36739 | B21: ='Monthly Haver'!C24 -> 57.7219 | C21: ='Monthly Haver'!D24 -> 59.6302 | D21: ='Monthly Haver'!E24 -> #N/A | E21: ='Monthly Haver'!G24 -> 54.6141 | F21: ='Monthly Haver'!H24 -> 52.7484 | G21: ='Monthly Haver'!I24 -> #N/A | H21: ='Monthly Haver'!J24 -> 60.6218 | I21: =GDS_Monthly!O138 -> 53.826579 | J21: =GDS_Monthly!D138 -> 73.026122 | K21: =GDS_Monthly!AH138 -> 447.93717 | L21: =GDS_Monthly!AI138 -> 422.47828 | M21: =GDS_Monthly!N138 -> 5.8340207 | N21: =GDS_Monthly!C138 -> 123.54828 | O21: =GDS_Monthly!F138 -> 5.1093118 | P21: =GDS_Monthly!G138 -> 5.6633347 | Q21: =GDS_Monthly!T138 -> 77.204472 | R21: =GDS_Monthly!V138 -> 82.397817 | S21: =GDS_Monthly!W138 -> 59.573262 | T21: =GDS_Monthly!X138 -> 47.330524 | U21: =GDS_Monthly!AA138 -> 51.008041 | V21: =GDS_Monthly!AC138 -> 76.558522 | W21: =GDS_Monthly!AE138 -> 72.866485 | X21: =GDS_Monthly!AF138 -> 71.061274 | Y21: =OECD!B21 -> 100.894 | Z21: =OECD!C21 -> 99.36 | AA21: ='Monthly Haver'!K24 -> 110.67493 | AB21: ='Monthly Haver'!L24 -> 1639
A22: 36770 | B22: ='Monthly Haver'!C25 -> 57.0564 | C22: ='Monthly Haver'!D25 -> 62.436 | D22: ='Monthly Haver'!E25 -> #N/A | E22: ='Monthly Haver'!G25 -> 54.4621 | F22: ='Monthly Haver'!H25 -> 52.1272 | G22: ='Monthly Haver'!I25 -> #N/A | H22: ='Monthly Haver'!J25 -> 59.1884 | I22: =GDS_Monthly!O139 -> 54.350175 | J22: =GDS_Monthly!D139 -> 72.958248 | K22: =GDS_Monthly!AH139 -> 444.20918 | L22: =GDS_Monthly!AI139 -> 418.88132 | M22: =GDS_Monthly!N139 -> 5.7615912 | N22: =GDS_Monthly!C139 -> 123.59574 | O22: =GDS_Monthly!F139 -> 5.1485854 | P22: =GDS_Monthly!G139 -> 5.6741499 | Q22: =GDS_Monthly!T139 -> 77.495676 | R22: =GDS_Monthly!V139 -> 82.587708 | S22: =GDS_Monthly!W139 -> 59.068949 | T22: =GDS_Monthly!X139 -> 49.503901 | U22: =GDS_Monthly!AA139 -> 51.251356 | V22: =GDS_Monthly!AC139 -> 83.121869 | W22: =GDS_Monthly!AE139 -> 80.359117 | X22: =GDS_Monthly!AF139 -> 72.716941 | Y22: =OECD!B22 -> 100.7088 | Z22: =OECD!C22 -> 99.81 | AA22: ='Monthly Haver'!K25 -> 112.69999 | AB22: ='Monthly Haver'!L25 -> 1712 | AC22: =Quarterly!B8 -> 93.68 | AD22: =Quarterly!C8 -> 82.14 | AE22: =Quarterly!D8 -> 79.516129
A23: 36800 | B23: ='Monthly Haver'!C26 -> 56.1107 | C23: ='Monthly Haver'!D26 -> 62.0493 | D23: ='Monthly Haver'!E26 -> #N/A | E23: ='Monthly Haver'!G26 -> 54.3997 | F23: ='Monthly Haver'!H26 -> 51.1515 | G23: ='Monthly Haver'!I26 -> #N/A | H23: ='Monthly Haver'!J26 -> 58.3064 | I23: =GDS_Monthly!O140 -> 54.420354 | J23: =GDS_Monthly!D140 -> 73.140851 | K23: =GDS_Monthly!AH140 -> 445.48884 | L23: =GDS_Monthly!AI140 -> 417.96496 | M23: =GDS_Monthly!N140 -> 5.7143732 | N23: =GDS_Monthly!C140 -> 122.04502 | O23: =GDS_Monthly!F140 -> 5.1475417 | P23: =GDS_Monthly!G140 -> 5.7512098 | Q23: =GDS_Monthly!T140 -> 77.625903 | R23: =GDS_Monthly!V140 -> 82.707889 | S23: =GDS_Monthly!W140 -> 58.764964 | T23: =GDS_Monthly!X140 -> 46.642271 | U23: =GDS_Monthly!AA140 -> 50.385336 | V23: =GDS_Monthly!AC140 -> 82.635599 | W23: =GDS_Monthly!AE140 -> 79.171231 | X23: =GDS_Monthly!AF140 -> 71.511905 | Y23: =OECD!B23 -> 100.4807 | Z23: =OECD!C23 -> 98.93 | AA23: ='Monthly Haver'!K26 -> 114.52119 | AB23: ='Monthly Haver'!L26 -> 1734
A24: 36831 | B24: ='Monthly Haver'!C27 -> 54.8676 | C24: ='Monthly Haver'!D27 -> 59.7087 | D24: ='Monthly Haver'!E27 -> #N/A | E24: ='Monthly Haver'!G27 -> 54.1276 | F24: ='Monthly Haver'!H27 -> 50.7463 | G24: ='Monthly Haver'!I27 -> #N/A | H24: ='Monthly Haver'!J27 -> 58.2362 | I24: =GDS_Monthly!O141 -> 54.72007 | J24: =GDS_Monthly!D141 -> 73.468059 | K24: =GDS_Monthly!AH141 -> 446.28907 | L24: =GDS_Monthly!AI141 -> 416.89373 | M24: =GDS_Monthly!N141 -> 5.6596537 | N24: =GDS_Monthly!C141 -> 121.17975 | O24: =GDS_Monthly!F141 -> 5.0789812 | P24: =GDS_Monthly!G141 -> 5.7827941 | Q24: =GDS_Monthly!T141 -> 77.85689 | R24: =GDS_Monthly!V141 -> 82.910976 | S24: =GDS_Monthly!W141 -> 59.456653 | T24: =GDS_Monthly!X141 -> 45.256696 | U24: =GDS_Monthly!AA141 -> 50.474045 | V24: =GDS_Monthly!AC141 -> 85.150599 | W24: =GDS_Monthly!AE141 -> 81.702649 | X24: =GDS_Monthly!AF141 -> 73.199228 | Y24: =OECD!B24 -> 100.2145 | Z24: =OECD!C24 -> 97.98 | AA24: ='Monthly Haver'!K27 -> 114.70364 | AB24: ='Monthly Haver'!L27 -> 1722
A25: 36861 | B25: ='Monthly Haver'!C28 -> 52.9055 | C25: ='Monthly Haver'!D28 -> 59.8906 | D25: ='Monthly Haver'!E28 -> #N/A | E25: ='Monthly Haver'!G28 -> 52.0189 | F25: ='Monthly Haver'!H28 -> 47.8504 | G25: ='Monthly Haver'!I28 -> #N/A | H25: ='Monthly Haver'!J28 -> 56.9885 | I25: =GDS_Monthly!O142 -> 54.890252 | J25: =GDS_Monthly!D142 -> 73.618516 | K25: =GDS_Monthly!AH142 -> 445.32931 | L25: =GDS_Monthly!AI142 -> 421.57181 | M25: =GDS_Monthly!N142 -> 5.5706165 | N25: =GDS_Monthly!C142 -> 120.16304 | O25: =GDS_Monthly!F142 -> 4.752543 | P25: =GDS_Monthly!G142 -> 5.7556289 | Q25: =GDS_Monthly!T142 -> 78.037996 | R25: =GDS_Monthly!V142 -> 82.959667 | S25: =GDS_Monthly!W142 -> 62.821884 | T25: =GDS_Monthly!X142 -> 46.413625 | U25: =GDS_Monthly!AA142 -> 52.044348 | V25: =GDS_Monthly!AC142 -> 84.12611 | W25: =GDS_Monthly!AE142 -> 63.259156 | X25: =GDS_Monthly!AF142 -> 68.309323 | Y25: =OECD!B25 -> 99.92323 | Z25: =OECD!C25 -> 96.4 | AA25: ='Monthly Haver'!K28 -> 115.36116 | AB25: ='Monthly Haver'!L28 -> 1609 | AC25: =Quarterly!B9 -> 94.18 | AD25: =Quarterly!C9 -> 82.67 | AE25: =Quarterly!D9 -> 80.047337
A26: 36892 | B26: ='Monthly Haver'!C29 -> 50.3995 | C26: ='Monthly Haver'!D29 -> 59.8419 | D26: ='Monthly Haver'!E29 -> #N/A | E26: ='Monthly Haver'!G29 -> 51.6143 | F26: ='Monthly Haver'!H29 -> 46.672 | G26: ='Monthly Haver'!I29 -> #N/A | H26: ='Monthly Haver'!J29 -> 53.5145 | I26: =GDS_Monthly!O143 -> 55.346654 | J26: =GDS_Monthly!D143 -> 72.947617 | K26: =GDS_Monthly!AH143 -> 447.49148 | L26: =GDS_Monthly!AI143 -> 421.20307 | M26: =GDS_Monthly!N143 -> 5.7313648 | N26: =GDS_Monthly!C143 -> 117.17811 | O26: =GDS_Monthly!F143 -> 4.6487619 | P26: =GDS_Monthly!G143 -> 5.3618166 | Q26: =GDS_Monthly!T143 -> 78.212996 | R26: =GDS_Monthly!V143 -> 83.127185 | S26: =GDS_Monthly!W143 -> 61.25194 | T26: =GDS_Monthly!X143 -> 46.202093 | U26: =GDS_Monthly!AA143 -> 51.896816 | V26: =GDS_Monthly!AC143 -> 83.181449 | W26: =GDS_Monthly!AE143 -> 64.557624 | X26: =GDS_Monthly!AF143 -> 71.442514 | Y26: =OECD!B26 -> 99.63953 | Z26: =OECD!C26 -> 96.53 | AA26: ='Monthly Haver'!K29 -> 118.40696 | AB26: ='Monthly Haver'!L29 -> 1566
A27: 36923 | B27: ='Monthly Haver'!C30 -> 50.6972 | C27: ='Monthly Haver'!D30 -> 56.0585 | D27: ='Monthly Haver'!E30 -> #N/A | E27: ='Monthly Haver'!G30 -> 50.0667 | F27: ='Monthly Haver'!H30 -> 46.1243 | G27: ='Monthly Haver'!I30 -> #N/A | H27: ='Monthly Haver'!J30 -> 52.5185 | I27: =GDS_Monthly!O144 -> 55.62763 | J27: =GDS_Monthly!D144 -> 73.202991 | K27: =GDS_Monthly!AH144 -> 436.04902 | L27: =GDS_Monthly!AI144 -> 416.92825 | M27: =GDS_Monthly!N144 -> 5.7467695 | N27: =GDS_Monthly!C144 -> 115.32827 | O27: =GDS_Monthly!F144 -> 4.5838122 | P27: =GDS_Monthly!G144 -> 5.3745508 | Q27: =GDS_Monthly!T144 -> 78.354846 | R27: =GDS_Monthly!V144 -> 83.282432 | S27: =GDS_Monthly!W144 -> 60.297016 | T27: =GDS_Monthly!X144 -> 45.4812 | U27: =GDS_Monthly!AA144 -> 51.247229 | V27: =GDS_Monthly!AC144 -> 76.91737 | W27: =GDS_Monthly!AE144 -> 68.241037 | X27: =GDS_Monthly!AF144 -> 70.969655 | Y27: =OECD!B27 -> 99.39224 | Z27: =OECD!C27 -> 95.49 | AA27: ='Monthly Haver'!K30 -> 116.84528 | AB27: ='Monthly Haver'!L30 -> 1479
A28: 36951 | B28: ='Monthly Haver'!C31 -> 50.776 | C28: ='Monthly Haver'!D31 -> 53.3783 | D28: ='Monthly Haver'!E31 -> #N/A | E28: ='Monthly Haver'!G31 -> 50.0283 | F28: ='Monthly Haver'!H31 -> 46.3132 | G28: ='Monthly Haver'!I31 -> #N/A | H28: ='Monthly Haver'!J31 -> 51.2981 | I28: =GDS_Monthly!O145 -> 55.587954 | J28: =GDS_Monthly!D145 -> 72.830454 | K28: =GDS_Monthly!AH145 -> 430.80769 | L28: =GDS_Monthly!AI145 -> 407.72012 | M28: =GDS_Monthly!N145 -> 5.8119153 | N28: =GDS_Monthly!C145 -> 117.07217 | O28: =GDS_Monthly!F145 -> 4.4478674 | P28: =GDS_Monthly!G145 -> 5.111165 | Q28: =GDS_Monthly!T145 -> 78.483552 | R28: =GDS_Monthly!V145 -> 83.46347 | S28: =GDS_Monthly!W145 -> 61.75394 | T28: =GDS_Monthly!X145 -> 43.998092 | U28: =GDS_Monthly!AA145 -> 51.115773 | V28: =GDS_Monthly!AC145 -> 72.361527 | W28: =GDS_Monthly!AE145 -> 63.398528 | X28: =GDS_Monthly!AF145 -> 67.420782 | Y28: =OECD!B28 -> 99.19456 | Z28: =OECD!C28 -> 94.09 | AA28: ='Monthly Haver'!K31 -> 117.21037 | AB28: ='Monthly Haver'!L31 -> 1502 | AC28: =Quarterly!B10 -> 94.75 | AD28: =Quarterly!C10 -> 83.25 | AE28: =Quarterly!D10 -> 80.343371
A29: 36982 | B29: ='Monthly Haver'!C32 -> 48.3893 | C29: ='Monthly Haver'!D32 -> 51.5303 | D29: ='Monthly Haver'!E32 -> #N/A | E29: ='Monthly Haver'!G32 -> 47.997 | F29: ='Monthly Haver'!H32 -> 45.6612 | G29: ='Monthly Haver'!I32 -> #N/A | H29: ='Monthly Haver'!J32 -> 49.7308 | I29: =GDS_Monthly!O146 -> 55.912462 | J29: =GDS_Monthly!D146 -> 72.39903 | K29: =GDS_Monthly!AH146 -> 420.7671 | L29: =GDS_Monthly!AI146 -> 398.20469 | M29: =GDS_Monthly!N146 -> 5.7691768 | N29: =GDS_Monthly!C146 -> 114.74707 | O29: =GDS_Monthly!F146 -> 4.6583345 | P29: =GDS_Monthly!G146 -> 4.9052027 | Q29: =GDS_Monthly!T146 -> 78.74712 | R29: =GDS_Monthly!V146 -> 83.692438 | S29: =GDS_Monthly!W146 -> 62.182541 | T29: =GDS_Monthly!X146 -> 43.583063 | U29: =GDS_Monthly!AA146 -> 51.025736 | V29: =GDS_Monthly!AC146 -> 73.375902 | W29: =GDS_Monthly!AE146 -> 65.630559 | X29: =GDS_Monthly!AF146 -> 68.901251 | Y29: =OECD!B29 -> 99.04559 | Z29: =OECD!C29 -> 93.48 | AA29: ='Monthly Haver'!K32 -> 118.0537 | AB29: ='Monthly Haver'!L32 -> 1440
A30: 37012 | B30: ='Monthly Haver'!C33 -> 49.1348 | C30: ='Monthly Haver'!D33 -> 52.8848 | D30: ='Monthly Haver'!E33 -> #N/A | E30: ='Monthly Haver'!G33 -> 47.5177 | F30: ='Monthly Haver'!H33 -> 44.7586 | G30: ='Monthly Haver'!I33 -> #N/A | H30: ='Monthly Haver'!J33 -> 49.4231 | I30: =GDS_Monthly!O147 -> 56.302466 | J30: =GDS_Monthly!D147 -> 72.580763 | K30: =GDS_Monthly!AH147 -> 416.10956 | L30: =GDS_Monthly!AI147 -> 396.65529 | M30: =GDS_Monthly!N147 -> 5.8218612 | N30: =GDS_Monthly!C147 -> 116.17409 | O30: =GDS_Monthly!F147 -> 4.8068785 | P30: =GDS_Monthly!G147 -> 4.6028662 | Q30: =GDS_Monthly!T147 -> 79.056318 | R30: =GDS_Monthly!V147 -> 83.847642 | S30: =GDS_Monthly!W147 -> 63.66863 | T30: =GDS_Monthly!X147 -> 44.887397 | U30: =GDS_Monthly!AA147 -> 51.752933 | V30: =GDS_Monthly!AC147 -> 73.758302 | W30: =GDS_Monthly!AE147 -> 70.73505 | X30: =GDS_Monthly!AF147 -> 67.967114 | Y30: =OECD!B30 -> 98.93497 | Z30: =OECD!C30 -> 93.87 | AA30: ='Monthly Haver'!K33 -> 117.89464 | AB30: ='Monthly Haver'!L33 -> 1448
A31: 37043 | B31: ='Monthly Haver'!C34 -> 50.8044 | C31: ='Monthly Haver'!D34 -> 50.7478 | D31: ='Monthly Haver'!E34 -> #N/A | E31: ='Monthly Haver'!G34 -> 46.9482 | F31: ='Monthly Haver'!H34 -> 45.634 | G31: ='Monthly Haver'!I34 -> #N/A | H31: ='Monthly Haver'!J34 -> 51.9596 | I31: =GDS_Monthly!O148 -> 56.501988 | J31: =GDS_Monthly!D148 -> 72.385448 | K31: =GDS_Monthly!AH148 -> 410.44511 | L31: =GDS_Monthly!AI148 -> 390.27714 | M31: =GDS_Monthly!N148 -> 5.7877099 | N31: =GDS_Monthly!C148 -> 116.69368 | O31: =GDS_Monthly!F148 -> 4.7156293 | P31: =GDS_Monthly!G148 -> 4.5422933 | Q31: =GDS_Monthly!T148 -> 79.233072 | R31: =GDS_Monthly!V148 -> 84.063391 | S31: =GDS_Monthly!W148 -> 63.445325 | T31: =GDS_Monthly!X148 -> 43.086933 | U31: =GDS_Monthly!AA148 -> 50.926029 | V31: =GDS_Monthly!AC148 -> 71.154271 | W31: =GDS_Monthly!AE148 -> 69.920647 | X31: =GDS_Monthly!AF148 -> 68.563413 | Y31: =OECD!B31 -> 98.83767 | Z31: =OECD!C31 -> 93.61 | AA31: ='Monthly Haver'!K34 -> 117.75114 | AB31: ='Monthly Haver'!L34 -> 1377 | AC31: =Quarterly!B11 -> 94.74 | AD31: =Quarterly!C11 -> 83.79 | AE31: =Quarterly!D11 -> 80.571894
A32: 37073 | B32: ='Monthly Haver'!C35 -> 49.0456 | C32: ='Monthly Haver'!D35 -> 47.4851 | D32: ='Monthly Haver'!E35 -> #N/A | E32: ='Monthly Haver'!G35 -> 47.5518 | F32: ='Monthly Haver'!H35 -> 45.7464 | G32: ='Monthly Haver'!I35 -> #N/A | H32: ='Monthly Haver'!J35 -> 49.5353 | I32: =GDS_Monthly!O149 -> 56.389524 | J32: =GDS_Monthly!D149 -> 71.734964 | K32: =GDS_Monthly!AH149 -> 403.384 | L32: =GDS_Monthly!AI149 -> 382.15181 | M32: =GDS_Monthly!N149 -> 5.9844426 | N32: =GDS_Monthly!C149 -> 115.92867 | O32: =GDS_Monthly!F149 -> 4.8644617 | P32: =GDS_Monthly!G149 -> 4.4914427 | Q32: =GDS_Monthly!T149 -> 79.255572 | R32: =GDS_Monthly!V149 -> 84.249721 | S32: =GDS_Monthly!W149 -> 64.995086 | T32: =GDS_Monthly!X149 -> 41.076991 | U32: =GDS_Monthly!AA149 -> 50.926556 | V32: =GDS_Monthly!AC149 -> 64.966556 | W32: =GDS_Monthly!AE149 -> 64.280784 | X32: =GDS_Monthly!AF149 -> 66.219002 | Y32: =OECD!B32 -> 98.74675 | Z32: =OECD!C32 -> 93.36 | AA32: ='Monthly Haver'!K35 -> 116.59186 | AB32: ='Monthly Haver'!L35 -> 1221
A33: 37104 | B33: ='Monthly Haver'!C36 -> 49.402 | C33: ='Monthly Haver'!D36 -> 45.6908 | D33: ='Monthly Haver'!E36 -> #N/A | E33: ='Monthly Haver'!G36 -> 47.8176 | F33: ='Monthly Haver'!H36 -> 47.6073 | G33: ='Monthly Haver'!I36 -> #N/A | H33: ='Monthly Haver'!J36 -> 48.7541 | I33: =GDS_Monthly!O150 -> 56.654156 | J33: =GDS_Monthly!D150 -> 72.339018 | K33: =GDS_Monthly!AH150 -> 408.44241 | L33: =GDS_Monthly!AI150 -> 391.19001 | M33: =GDS_Monthly!N150 -> 6.0031881 | N33: =GDS_Monthly!C150 -> 115.13709 | O33: =GDS_Monthly!F150 -> 4.5464574 | P33: =GDS_Monthly!G150 -> 4.2917694 | Q33: =GDS_Monthly!T150 -> 79.358232 | R33: =GDS_Monthly!V150 -> 84.408957 | S33: =GDS_Monthly!W150 -> 64.857527 | T33: =GDS_Monthly!X150 -> 39.745044 | U33: =GDS_Monthly!AA150 -> 50.444076 | V33: =GDS_Monthly!AC150 -> 66.102523 | W33: =GDS_Monthly!AE150 -> 65.642332 | X33: =GDS_Monthly!AF150 -> 64.801689 | Y33: =OECD!B33 -> 98.66246 | Z33: =OECD!C33 -> 93.24 | AA33: ='Monthly Haver'!K36 -> 115.02386 | AB33: ='Monthly Haver'!L36 -> 980
A34: 37135 | B34: ='Monthly Haver'!C37 -> 49.4776 | C34: ='Monthly Haver'!D37 -> 46.1145 | D34: ='Monthly Haver'!E37 -> #N/A | E34: ='Monthly Haver'!G37 -> 47.7734 | F34: ='Monthly Haver'!H37 -> 46.739 | G34: ='Monthly Haver'!I37 -> #N/A | H34: ='Monthly Haver'!J37 -> 49.2236 | I34: =GDS_Monthly!O151 -> 56.402903 | J34: =GDS_Monthly!D151 -> 71.80638 | K34: =GDS_Monthly!AH151 -> 397.6128 | L34: =GDS_Monthly!AI151 -> 381.03881 | M34: =GDS_Monthly!N151 -> 6.0567974 | N34: =GDS_Monthly!C151 -> 110.58596 | O34: =GDS_Monthly!F151 -> 4.4445436 | P34: =GDS_Monthly!G151 -> 3.9870959 | Q34: =GDS_Monthly!T151 -> 79.529203 | R34: =GDS_Monthly!V151 -> 84.568606 | S34: =GDS_Monthly!W151 -> 62.502099 | T34: =GDS_Monthly!X151 -> 38.523538 | U34: =GDS_Monthly!AA151 -> 49.118497 | V34: =GDS_Monthly!AC151 -> 62.719315 | W34: =GDS_Monthly!AE151 -> 63.119649 | X34: =GDS_Monthly!AF151 -> 63.115046 | Y34: =OECD!B34 -> 98.60294 | Z34: =OECD!C34 -> 91.9 | AA34: ='Monthly Haver'!K37 -> 115.00246 | AB34: ='Monthly Haver'!L37 -> 945 | AC34: =Quarterly!B12 -> 95.47 | AD34: =Quarterly!C12 -> 84.6 | AE34: =Quarterly!D12 -> 80.481747
A35: 37165 | B35: ='Monthly Haver'!C38 -> 41.7728 | C35: ='Monthly Haver'!D38 -> 41.566 | D35: ='Monthly Haver'!E38 -> #N/A | E35: ='Monthly Haver'!G38 -> 44.861 | F35: ='Monthly Haver'!H38 -> 41.0222 | G35: ='Monthly Haver'!I38 -> #N/A | H35: ='Monthly Haver'!J38 -> 42.8904 | I35: =GDS_Monthly!O152 -> 57.437947 | J35: =GDS_Monthly!D152 -> 71.586573 | K35: =GDS_Monthly!AH152 -> 400.48011 | L35: =GDS_Monthly!AI152 -> 384.13171 | M35: =GDS_Monthly!N152 -> 6.1883396 | N35: =GDS_Monthly!C152 -> 107.14213 | O35: =GDS_Monthly!F152 -> 4.4424703 | P35: =GDS_Monthly!G152 -> 3.7499945 | Q35: =GDS_Monthly!T152 -> 79.533055 | R35: =GDS_Monthly!V152 -> 84.733812 | S35: =GDS_Monthly!W152 -> 61.225784 | T35: =GDS_Monthly!X152 -> 37.289399 | U35: =GDS_Monthly!AA152 -> 47.941167 | V35: =GDS_Monthly!AC152 -> 55.431303 | W35: =GDS_Monthly!AE152 -> 52.573031 | X35: =GDS_Monthly!AF152 -> 60.097596 | Y35: =OECD!B35 -> 98.61269 | Z35: =OECD!C35 -> 91.22 | AA35: ='Monthly Haver'!K38 -> 113.80118 | AB35: ='Monthly Haver'!L38 -> 898
A36: 37196 | B36: ='Monthly Haver'!C39 -> 46.0247 | C36: ='Monthly Haver'!D39 -> 40.3969 | D36: ='Monthly Haver'!E39 -> #N/A | E36: ='Monthly Haver'!G39 -> 44.9218 | F36: ='Monthly Haver'!H39 -> 43.4857 | G36: ='Monthly Haver'!I39 -> #N/A | H36: ='Monthly Haver'!J39 -> 48.4776 | I36: =GDS_Monthly!O153 -> 57.591058 | J36: =GDS_Monthly!D153 -> 71.532397 | K36: =GDS_Monthly!AH153 -> 391.59469 | L36: =GDS_Monthly!AI153 -> 376.95736 | M36: =GDS_Monthly!N153 -> 6.219402 | N36: =GDS_Monthly!C153 -> 106.30676 | O36: =GDS_Monthly!F153 -> 4.2353148 | P36: =GDS_Monthly!G153 -> 3.4615398 | Q36: =GDS_Monthly!T153 -> 79.586012 | R36: =GDS_Monthly!V153 -> 84.891457 | S36: =GDS_Monthly!W153 -> 59.841797 | T36: =GDS_Monthly!X153 -> 38.560568 | U36: =GDS_Monthly!AA153 -> 47.538209 | V36: =GDS_Monthly!AC153 -> 50.46601 | W36: =GDS_Monthly!AE153 -> 47.766394 | X36: =GDS_Monthly!AF153 -> 61.003305 | Y36: =OECD!B36 -> 98.71382 | Z36: =OECD!C36 -> 92.02 | AA36: ='Monthly Haver'!K39 -> 114.14745 | AB36: ='Monthly Haver'!L39 -> 855
A37: 37226 | B37: ='Monthly Haver'!C40 -> 48.4487 | C37: ='Monthly Haver'!D40 -> 41.403 | D37: ='Monthly Haver'!E40 -> #N/A | E37: ='Monthly Haver'!G40 -> 45.3677 | F37: ='Monthly Haver'!H40 -> 44.0697 | G37: ='Monthly Haver'!I40 -> #N/A | H37: ='Monthly Haver'!J40 -> 50.2193 | I37: =GDS_Monthly!O154 -> 57.580693 | J37: =GDS_Monthly!D154 -> 71.303279 | K37: =GDS_Monthly!AH154 -> 382.26214 | L37: =GDS_Monthly!AI154 -> 372.87321 | M37: =GDS_Monthly!N154 -> 6.232181 | N37: =GDS_Monthly!C154 -> 109.21425 | O37: =GDS_Monthly!F154 -> 4.6677554 | P37: =GDS_Monthly!G154 -> 3.4050126 | Q37: =GDS_Monthly!T154 -> 79.673595 | R37: =GDS_Monthly!V154 -> 85.05342 | S37: =GDS_Monthly!W154 -> 59.490952 | T37: =GDS_Monthly!X154 -> 39.096092 | U37: =GDS_Monthly!AA154 -> 47.554038 | V37: =GDS_Monthly!AC154 -> 49.7152 | W37: =GDS_Monthly!AE154 -> 47.55058 | X37: =GDS_Monthly!AF154 -> 60.474278 | Y37: =OECD!B37 -> 98.89492 | Z37: =OECD!C37 -> 92.66 | AA37: ='Monthly Haver'!K40 -> 113.26548 | AB37: ='Monthly Haver'!L40 -> 870 | AC37: =Quarterly!B13 -> 95.57 | AD37: =Quarterly!C13 -> 85.2 | AE37: =Quarterly!D13 -> 80.678962
A38: 37257 | B38: ='Monthly Haver'!C41 -> 49.7059 | C38: ='Monthly Haver'!D41 -> 46.8692 | D38: ='Monthly Haver'!E41 -> #N/A | E38: ='Monthly Haver'!G41 -> 45.6848 | F38: ='Monthly Haver'!H41 -> 46.4923 | G38: ='Monthly Haver'!I41 -> #N/A | H38: ='Monthly Haver'!J41 -> 50.2709 | I38: =GDS_Monthly!O155 -> 57.634534 | J38: =GDS_Monthly!D155 -> 72.080363 | K38: =GDS_Monthly!AH155 -> 387.65102 | L38: =GDS_Monthly!AI155 -> 378.95353 | M38: =GDS_Monthly!N155 -> 6.4198886 | N38: =GDS_Monthly!C155 -> 110.81452 | O38: =GDS_Monthly!F155 -> 4.6756531 | P38: =GDS_Monthly!G155 -> 3.1968906 | Q38: =GDS_Monthly!T155 -> 79.930122 | R38: =GDS_Monthly!V155 -> 85.274073 | S38: =GDS_Monthly!W155 -> 61.176328 | T38: =GDS_Monthly!X155 -> 40.402698 | U38: =GDS_Monthly!AA155 -> 48.732879 | V38: =GDS_Monthly!AC155 -> 49.582558 | W38: =GDS_Monthly!AE155 -> 49.577973 | X38: =GDS_Monthly!AF155 -> 60.919209 | Y38: =OECD!B38 -> 99.11817 | Z38: =OECD!C38 -> 93.56 | AA38: ='Monthly Haver'!K41 -> 114.50681 | AB38: ='Monthly Haver'!L41 -> 931
A39: 37288 | B39: ='Monthly Haver'!C42 -> 54.3932 | C39: ='Monthly Haver'!D42 -> 46.4743 | D39: ='Monthly Haver'!E42 -> #N/A | E39: ='Monthly Haver'!G42 -> 46.4192 | F39: ='Monthly Haver'!H42 -> 49.0902 | G39: ='Monthly Haver'!I42 -> #N/A | H39: ='Monthly Haver'!J42 -> 55.1924 | I39: =GDS_Monthly!O156 -> 57.647547 | J39: =GDS_Monthly!D156 -> 72.37329 | K39: =GDS_Monthly!AH156 -> 397.6287 | L39: =GDS_Monthly!AI156 -> 380.37316 | M39: =GDS_Monthly!N156 -> 6.4263576 | N39: =GDS_Monthly!C156 -> 110.03191 | O39: =GDS_Monthly!F156 -> 4.6552129 | P39: =GDS_Monthly!G156 -> 3.2283237 | Q39: =GDS_Monthly!T156 -> 80.023822 | R39: =GDS_Monthly!V156 -> 85.44658 | S39: =GDS_Monthly!W156 -> 61.102395 | T39: =GDS_Monthly!X156 -> 40.603342 | U39: =GDS_Monthly!AA156 -> 49.125465 | V39: =GDS_Monthly!AC156 -> 51.270496 | W39: =GDS_Monthly!AE156 -> 52.030861 | X39: =GDS_Monthly!AF156 -> 63.197901 | Y39: =OECD!B39 -> 99.3416 | Z39: =OECD!C39 -> 93.85 | AA39: ='Monthly Haver'!K42 -> 114.91902 | AB39: ='Monthly Haver'!L42 -> 960
A40: 37316 | B40: ='Monthly Haver'!C43 -> 55.9122 | C40: ='Monthly Haver'!D43 -> 49.28 | D40: ='Monthly Haver'!E43 -> #N/A | E40: ='Monthly Haver'!G43 -> 47.9763 | F40: ='Monthly Haver'!H43 -> 51.0085 | G40: ='Monthly Haver'!I43 -> #N/A | H40: ='Monthly Haver'!J43 -> 55.4237 | I40: =GDS_Monthly!O157 -> 57.998497 | J40: =GDS_Monthly!D157 -> 72.816722 | K40: =GDS_Monthly!AH157 -> 400.88401 | L40: =GDS_Monthly!AI157 -> 389.74439 | M40: =GDS_Monthly!N157 -> 6.4439842 | N40: =GDS_Monthly!C157 -> 114.39479 | O40: =GDS_Monthly!F157 -> 4.8861923 | P40: =GDS_Monthly!G157 -> 3.6060902 | Q40: =GDS_Monthly!T157 -> 80.223684 | R40: =GDS_Monthly!V157 -> 85.531752 | S40: =GDS_Monthly!W157 -> 63.718582 | T40: =GDS_Monthly!X157 -> 41.968439 | U40: =GDS_Monthly!AA157 -> 50.739552 | V40: =GDS_Monthly!AC157 -> 59.613536 | W40: =GDS_Monthly!AE157 -> 61.33856 | X40: =GDS_Monthly!AF157 -> 62.177913 | Y40: =OECD!B40 -> 99.51686 | Z40: =OECD!C40 -> 94.79 | AA40: ='Monthly Haver'!K43 -> 114.84131 | AB40: ='Monthly Haver'!L43 -> 1065 | AC40: =Quarterly!B14 -> 96.13 | AD40: =Quarterly!C14 -> 86.15 | AE40: =Quarterly!D14 -> 81.167841
A41: 37347 | B41: ='Monthly Haver'!C44 -> 56.8187 | C41: ='Monthly Haver'!D44 -> 53.1068 | D41: ='Monthly Haver'!E44 -> #N/A | E41: ='Monthly Haver'!G44 -> 49.4381 | F41: ='Monthly Haver'!H44 -> 51.9532 | G41: ='Monthly Haver'!I44 -> #N/A | H41: ='Monthly Haver'!J44 -> 55.1924 | I41: =GDS_Monthly!O158 -> 58.490383 | J41: =GDS_Monthly!D158 -> 73.518017 | K41: =GDS_Monthly!AH158 -> 418.46972 | L41: =GDS_Monthly!AI158 -> 402.21628 | M41: =GDS_Monthly!N158 -> 6.5097315 | N41: =GDS_Monthly!C158 -> 113.4519 | O41: =GDS_Monthly!F158 -> 4.8558732 | P41: =GDS_Monthly!G158 -> 3.5314233 | Q41: =GDS_Monthly!T158 -> 80.578337 | R41: =GDS_Monthly!V158 -> 85.699371 | S41: =GDS_Monthly!W158 -> 63.436993 | T41: =GDS_Monthly!X158 -> 41.988458 | U41: =GDS_Monthly!AA158 -> 50.776241 | V41: =GDS_Monthly!AC158 -> 63.67392 | W41: =GDS_Monthly!AE158 -> 65.635461 | X41: =GDS_Monthly!AF158 -> 62.959154 | Y41: =OECD!B41 -> 99.60199 | Z41: =OECD!C41 -> 95.37 | AA41: ='Monthly Haver'!K44 -> 114.60213 | AB41: ='Monthly Haver'!L44 -> 1077
A42: 37377 | B42: ='Monthly Haver'!C45 -> 56.7117 | C42: ='Monthly Haver'!D45 -> 54.0376 | D42: ='Monthly Haver'!E45 -> #N/A | E42: ='Monthly Haver'!G45 -> 50.4234 | F42: ='Monthly Haver'!H45 -> 53.1445 | G42: ='Monthly Haver'!I45 -> #N/A | H42: ='Monthly Haver'!J45 -> 57.6536 | I42: =GDS_Monthly!O159 -> 58.509616 | J42: =GDS_Monthly!D159 -> 73.9014 | K42: =GDS_Monthly!AH159 -> 423.4983 | L42: =GDS_Monthly!AI159 -> 407.96828 | M42: =GDS_Monthly!N159 -> 6.4782354 | N42: =GDS_Monthly!C159 -> 114.05436 | O42: =GDS_Monthly!F159 -> 4.8117411 | P42: =GDS_Monthly!G159 -> 3.5315981 | Q42: =GDS_Monthly!T159 -> 80.699273 | R42: =GDS_Monthly!V159 -> 85.812579 | S42: =GDS_Monthly!W159 -> 62.587395 | T42: =GDS_Monthly!X159 -> 41.47037 | U42: =GDS_Monthly!AA159 -> 50.438214 | V42: =GDS_Monthly!AC159 -> 64.466222 | W42: =GDS_Monthly!AE159 -> 65.233812 | X42: =GDS_Monthly!AF159 -> 63.342585 | Y42: =OECD!B42 -> 99.58717 | Z42: =OECD!C42 -> 96.3 | AA42: ='Monthly Haver'!K45 -> 113.06977 | AB42: ='Monthly Haver'!L45 -> 1033
A43: 37408 | B43: ='Monthly Haver'!C46 -> 56.3609 | C43: ='Monthly Haver'!D46 -> 54.2991 | D43: ='Monthly Haver'!E46 -> #N/A | E43: ='Monthly Haver'!G46 -> 48.3701 | F43: ='Monthly Haver'!H46 -> 53.4952 | G43: ='Monthly Haver'!I46 -> #N/A | H43: ='Monthly Haver'!J46 -> 54.9187 | I43: =GDS_Monthly!O160 -> 58.553486 | J43: =GDS_Monthly!D160 -> 73.931483 | K43: =GDS_Monthly!AH160 -> 427.37239 | L43: =GDS_Monthly!AI160 -> 411.01178 | M43: =GDS_Monthly!N160 -> 6.4907826 | N43: =GDS_Monthly!C160 -> 113.07376 | O43: =GDS_Monthly!F160 -> 4.6974013 | P43: =GDS_Monthly!G160 -> 3.5793696 | Q43: =GDS_Monthly!T160 -> 80.816357 | R43: =GDS_Monthly!V160 -> 85.952831 | S43: =GDS_Monthly!W160 -> 61.833848 | T43: =GDS_Monthly!X160 -> 42.379224 | U43: =GDS_Monthly!AA160 -> 50.737977 | V43: =GDS_Monthly!AC160 -> 61.473099 | W43: =GDS_Monthly!AE160 -> 61.088995 | X43: =GDS_Monthly!AF160 -> 66.593378 | Y43: =OECD!B43 -> 99.48796 | Z43: =OECD!C43 -> 96.57 | AA43: ='Monthly Haver'!K46 -> 111.99416 | AB43: ='Monthly Haver'!L46 -> 995 | AC43: =Quarterly!B15 -> 96.43 | AD43: =Quarterly!C15 -> 87.07 | AE43: =Quarterly!D15 -> 81.836026
A44: 37438 | B44: ='Monthly Haver'!C47 -> 52.524 | C44: ='Monthly Haver'!D47 -> 57.509 | D44: ='Monthly Haver'!E47 -> #N/A | E44: ='Monthly Haver'!G47 -> 48.4841 | F44: ='Monthly Haver'!H47 -> 51.2427 | G44: ='Monthly Haver'!I47 -> #N/A | H44: ='Monthly Haver'!J47 -> 52.2299 | I44: =GDS_Monthly!O161 -> 59.006082 | J44: =GDS_Monthly!D161 -> 74.364372 | K44: =GDS_Monthly!AH161 -> 442.51466 | L44: =GDS_Monthly!AI161 -> 427.16061 | M44: =GDS_Monthly!N161 -> 6.5102471 | N44: =GDS_Monthly!C161 -> 110.46611 | O44: =GDS_Monthly!F161 -> 4.5220357 | P44: =GDS_Monthly!G161 -> 3.6725504 | Q44: =GDS_Monthly!T161 -> 81.11397 | R44: =GDS_Monthly!V161 -> 86.084747 | S44: =GDS_Monthly!W161 -> 63.886987 | T44: =GDS_Monthly!X161 -> 41.884458 | U44: =GDS_Monthly!AA161 -> 51.750085 | V44: =GDS_Monthly!AC161 -> 63.70658 | W44: =GDS_Monthly!AE161 -> 62.780297 | X44: =GDS_Monthly!AF161 -> 69.51953 | Y44: =OECD!B44 -> 99.3388 | Z44: =OECD!C44 -> 95.72 | AA44: ='Monthly Haver'!K47 -> 110.34676 | AB44: ='Monthly Haver'!L47 -> 989
A45: 37469 | B45: ='Monthly Haver'!C48 -> 52.2755 | C45: ='Monthly Haver'!D48 -> 53.9542 | D45: ='Monthly Haver'!E48 -> #N/A | E45: ='Monthly Haver'!G48 -> 48.4744 | F45: ='Monthly Haver'!H48 -> 50.5435 | G45: ='Monthly Haver'!I48 -> #N/A | H45: ='Monthly Haver'!J48 -> 51.7864 | I45: =GDS_Monthly!O162 -> 59.530919 | J45: =GDS_Monthly!D162 -> 74.48919 | K45: =GDS_Monthly!AH162 -> 437.65263 | L45: =GDS_Monthly!AI162 -> 421.02303 | M45: =GDS_Monthly!N162 -> 6.4821552 | N45: =GDS_Monthly!C162 -> 109.66187 | O45: =GDS_Monthly!F162 -> 4.2581933 | P45: =GDS_Monthly!G162 -> 3.5591526 | Q45: =GDS_Monthly!T162 -> 81.313488 | R45: =GDS_Monthly!V162 -> 86.283522 | S45: =GDS_Monthly!W162 -> 63.806457 | T45: =GDS_Monthly!X162 -> 40.12803 | U45: =GDS_Monthly!AA162 -> 51.496368 | V45: =GDS_Monthly!AC162 -> 64.74497 | W45: =GDS_Monthly!AE162 -> 65.719212 | X45: =GDS_Monthly!AF162 -> 70.977621 | Y45: =OECD!B45 -> 99.1754 | Z45: =OECD!C45 -> 95.41 | AA45: ='Monthly Haver'!K48 -> 111.62193 | AB45: ='Monthly Haver'!L48 -> 1002
A46: 37500 | B46: ='Monthly Haver'!C49 -> 52.7736 | C46: ='Monthly Haver'!D49 -> 53.4978 | D46: ='Monthly Haver'!E49 -> #N/A | E46: ='Monthly Haver'!G49 -> 47.8141 | F46: ='Monthly Haver'!H49 -> 49.6431 | G46: ='Monthly Haver'!I49 -> #N/A | H46: ='Monthly Haver'!J49 -> 53.2569 | I46: =GDS_Monthly!O163 -> 59.398159 | J46: =GDS_Monthly!D163 -> 74.721747 | K46: =GDS_Monthly!AH163 -> 442.25984 | L46: =GDS_Monthly!AI163 -> 427.06609 | M46: =GDS_Monthly!N163 -> 6.4996422 | N46: =GDS_Monthly!C163 -> 109.62045 | O46: =GDS_Monthly!F163 -> 4.0150897 | P46: =GDS_Monthly!G163 -> 3.522534 | Q46: =GDS_Monthly!T163 -> 81.459046 | R46: =GDS_Monthly!V163 -> 86.35929 | S46: =GDS_Monthly!W163 -> 64.338773 | T46: =GDS_Monthly!X163 -> 40.108176 | U46: =GDS_Monthly!AA163 -> 52.287201 | V46: =GDS_Monthly!AC163 -> 69.059763 | W46: =GDS_Monthly!AE163 -> 69.384655 | X46: =GDS_Monthly!AF163 -> 74.079898 | Y46: =OECD!B46 -> 99.02045 | Z46: =OECD!C46 -> 94.97 | AA46: ='Monthly Haver'!K49 -> 112.49283 | AB46: ='Monthly Haver'!L49 -> 1182 | AC46: =Quarterly!B16 -> 96.43 | AD46: =Quarterly!C16 -> 88.09 | AE46: =Quarterly!D16 -> 82.332843
A47: 37530 | B47: ='Monthly Haver'!C50 -> 51.9621 | C47: ='Monthly Haver'!D50 -> 53.2344 | D47: ='Monthly Haver'!E50 -> #N/A | E47: ='Monthly Haver'!G50 -> 47.9275 | F47: ='Monthly Haver'!H50 -> 49.1926 | G47: ='Monthly Haver'!I50 -> #N/A | H47: ='Monthly Haver'!J50 -> 52.3923 | I47: =GDS_Monthly!O164 -> 59.746024 | J47: =GDS_Monthly!D164 -> 74.908434 | K47: =GDS_Monthly!AH164 -> 443.0383 | L47: =GDS_Monthly!AI164 -> 425.96532 | M47: =GDS_Monthly!N164 -> 6.528311 | N47: =GDS_Monthly!C164 -> 105.64252 | O47: =GDS_Monthly!F164 -> 4.095969 | P47: =GDS_Monthly!G164 -> 3.5560586 | Q47: =GDS_Monthly!T164 -> 81.611801 | R47: =GDS_Monthly!V164 -> 86.495082 | S47: =GDS_Monthly!W164 -> 66.91437 | T47: =GDS_Monthly!X164 -> 40.439486 | U47: =GDS_Monthly!AA164 -> 53.523059 | V47: =GDS_Monthly!AC164 -> 70.189663 | W47: =GDS_Monthly!AE164 -> 67.744915 | X47: =GDS_Monthly!AF164 -> 73.634415 | Y47: =OECD!B47 -> 98.88687 | Z47: =OECD!C47 -> 94.37 | AA47: ='Monthly Haver'!K50 -> 113.67635 | AB47: ='Monthly Haver'!L50 -> 1365
A48: 37561 | B48: ='Monthly Haver'!C51 -> 53.3031 | C48: ='Monthly Haver'!D51 -> 53.1446 | D48: ='Monthly Haver'!E51 -> #N/A | E48: ='Monthly Haver'!G51 -> 47.5544 | F48: ='Monthly Haver'!H51 -> 48.9969 | G48: ='Monthly Haver'!I51 -> #N/A | H48: ='Monthly Haver'!J51 -> 54.8537 | I48: =GDS_Monthly!O165 -> 60.164215 | J48: =GDS_Monthly!D165 -> 75.24154 | K48: =GDS_Monthly!AH165 -> 453.411 | L48: =GDS_Monthly!AI165 -> 431.78086 | M48: =GDS_Monthly!N165 -> 6.5605379 | N48: =GDS_Monthly!C165 -> 107.0388 | O48: =GDS_Monthly!F165 -> 4.0794593 | P48: =GDS_Monthly!G165 -> 3.3372259 | Q48: =GDS_Monthly!T165 -> 81.851191 | R48: =GDS_Monthly!V165 -> 86.664176 | S48: =GDS_Monthly!W165 -> 65.671442 | T48: =GDS_Monthly!X165 -> 42.267609 | U48: =GDS_Monthly!AA165 -> 53.295969 | V48: =GDS_Monthly!AC165 -> 65.499321 | W48: =GDS_Monthly!AE165 -> 60.396898 | X48: =GDS_Monthly!AF165 -> 73.46601 | Y48: =OECD!B48 -> 98.77787 | Z48: =OECD!C48 -> 95.19 | AA48: ='Monthly Haver'!K51 -> 112.41809 | AB48: ='Monthly Haver'!L51 -> 1460
A49: 37591 | B49: ='Monthly Haver'!C52 -> 53.5905 | C49: ='Monthly Haver'!D52 -> 53.2145 | D49: ='Monthly Haver'!E52 -> #N/A | E49: ='Monthly Haver'!G52 -> 48.1742 | F49: ='Monthly Haver'!H52 -> 50.1488 | G49: ='Monthly Haver'!I52 -> #N/A | H49: ='Monthly Haver'!J52 -> 53.8282 | I49: =GDS_Monthly!O166 -> 60.289848 | J49: =GDS_Monthly!D166 -> 74.523103 | K49: =GDS_Monthly!AH166 -> 451.93639 | L49: =GDS_Monthly!AI166 -> 429.15927 | M49: =GDS_Monthly!N166 -> 6.6152675 | N49: =GDS_Monthly!C166 -> 105.67842 | O49: =GDS_Monthly!F166 -> 3.9698848 | P49: =GDS_Monthly!G166 -> 3.2717793 | Q49: =GDS_Monthly!T166 -> 82.045243 | R49: =GDS_Monthly!V166 -> 86.80682 | S49: =GDS_Monthly!W166 -> 66.695143 | T49: =GDS_Monthly!X166 -> 42.317469 | U49: =GDS_Monthly!AA166 -> 53.986244 | V49: =GDS_Monthly!AC166 -> 72.642371 | W49: =GDS_Monthly!AE166 -> 67.45441 | X49: =GDS_Monthly!AF166 -> 73.890282 | Y49: =OECD!B49 -> 98.67928 | Z49: =OECD!C49 -> 95.46 | AA49: ='Monthly Haver'!K52 -> 111.39195 | AB49: ='Monthly Haver'!L52 -> 1666 | AC49: =Quarterly!B17 -> 96.71 | AD49: =Quarterly!C17 -> 88.92 | AE49: =Quarterly!D17 -> 82.644925
A50: 37622 | B50: ='Monthly Haver'!C53 -> 53.2984 | C50: ='Monthly Haver'!D53 -> 54.6668 | D50: ='Monthly Haver'!E53 -> #N/A | E50: ='Monthly Haver'!G53 -> 49.3404 | F50: ='Monthly Haver'!H53 -> 50.0711 | G50: ='Monthly Haver'!I53 -> #N/A | H50: ='Monthly Haver'!J53 -> 54.0219 | I50: =GDS_Monthly!O167 -> 60.754456 | J50: =GDS_Monthly!D167 -> 75.868327 | K50: =GDS_Monthly!AH167 -> 475.6412 | L50: =GDS_Monthly!AI167 -> 451.02936 | M50: =GDS_Monthly!N167 -> 6.6411152 | N50: =GDS_Monthly!C167 -> 105.01209 | O50: =GDS_Monthly!F167 -> 3.8998256 | P50: =GDS_Monthly!G167 -> 3.3175989 | Q50: =GDS_Monthly!T167 -> 82.374638 | R50: =GDS_Monthly!V167 -> 86.945111 | S50: =GDS_Monthly!W167 -> 66.956524 | T50: =GDS_Monthly!X167 -> 44.545787 | U50: =GDS_Monthly!AA167 -> 55.318794 | V50: =GDS_Monthly!AC167 -> 80.490252 | W50: =GDS_Monthly!AE167 -> 72.887892 | X50: =GDS_Monthly!AF167 -> 75.818524 | Y50: =OECD!B50 -> 98.58562 | Z50: =OECD!C50 -> 95.87 | AA50: ='Monthly Haver'!K53 -> 111.2868 | AB50: ='Monthly Haver'!L53 -> 1694
A51: 37653 | B51: ='Monthly Haver'!C54 -> 52.0202 | C51: ='Monthly Haver'!D54 -> 57.8562 | D51: ='Monthly Haver'!E54 -> #N/A | E51: ='Monthly Haver'!G54 -> 47.8727 | F51: ='Monthly Haver'!H54 -> 49.0505 | G51: ='Monthly Haver'!I54 -> #N/A | H51: ='Monthly Haver'!J54 -> 53.1736 | I51: =GDS_Monthly!O168 -> 60.975794 | J51: =GDS_Monthly!D168 -> 76.362741 | K51: =GDS_Monthly!AH168 -> 476.50599 | L51: =GDS_Monthly!AI168 -> 455.84701 | M51: =GDS_Monthly!N168 -> 6.6542491 | N51: =GDS_Monthly!C168 -> 101.13823 | O51: =GDS_Monthly!F168 -> 3.7647917 | P51: =GDS_Monthly!G168 -> 3.2970547 | Q51: =GDS_Monthly!T168 -> 82.669427 | R51: =GDS_Monthly!V168 -> 87.048934 | S51: =GDS_Monthly!W168 -> 67.639729 | T51: =GDS_Monthly!X168 -> 45.921225 | U51: =GDS_Monthly!AA168 -> 56.189505 | V51: =GDS_Monthly!AC168 -> 91.76203 | W51: =GDS_Monthly!AE168 -> 77.812541 | X51: =GDS_Monthly!AF168 -> 76.401557 | Y51: =OECD!B51 -> 98.51174 | Z51: =OECD!C51 -> 95.57 | AA51: ='Monthly Haver'!K54 -> 112.31287 | AB51: ='Monthly Haver'!L54 -> 1674
A52: 37681 | B52: ='Monthly Haver'!C55 -> 49.0449 | C52: ='Monthly Haver'!D55 -> 58.6644 | D52: ='Monthly Haver'!E55 -> #N/A | E52: ='Monthly Haver'!G55 -> 47.7156 | F52: ='Monthly Haver'!H55 -> 47.4906 | G52: ='Monthly Haver'!I55 -> #N/A | H52: ='Monthly Haver'!J55 -> 47.0537 | I52: =GDS_Monthly!O169 -> 61.307849 | J52: =GDS_Monthly!D169 -> 76.362918 | K52: =GDS_Monthly!AH169 -> 481.68683 | L52: =GDS_Monthly!AI169 -> 450.92705 | M52: =GDS_Monthly!N169 -> 6.6771938 | N52: =GDS_Monthly!C169 -> 100.16443 | O52: =GDS_Monthly!F169 -> 3.7789074 | P52: =GDS_Monthly!G169 -> 3.2267947 | Q52: =GDS_Monthly!T169 -> 82.881693 | R52: =GDS_Monthly!V169 -> 87.141067 | S52: =GDS_Monthly!W169 -> 67.493948 | T52: =GDS_Monthly!X169 -> 45.151397 | U52: =GDS_Monthly!AA169 -> 55.719633 | V52: =GDS_Monthly!AC169 -> 81.450087 | W52: =GDS_Monthly!AE169 -> 71.806319 | X52: =GDS_Monthly!AF169 -> 75.989059 | Y52: =OECD!B52 -> 98.49016 | Z52: =OECD!C52 -> 95.54 | AA52: ='Monthly Haver'!K55 -> 114.44224 | AB52: ='Monthly Haver'!L55 -> 1850 | AC52: =Quarterly!B18 -> 96.49 | AD52: =Quarterly!C18 -> 89.37 | AE52: =Quarterly!D18 -> 82.954274
A53: 37712 | B53: ='Monthly Haver'!C56 -> 49.2196 | C53: ='Monthly Haver'!D56 -> 55.1322 | D53: ='Monthly Haver'!E56 -> #N/A | E53: ='Monthly Haver'!G56 -> 47.9125 | F53: ='Monthly Haver'!H56 -> 47.7363 | G53: ='Monthly Haver'!I56 -> #N/A | H53: ='Monthly Haver'!J56 -> 49.6302 | I53: =GDS_Monthly!O170 -> 61.438674 | J53: =GDS_Monthly!D170 -> 76.202784 | K53: =GDS_Monthly!AH170 -> 475.98812 | L53: =GDS_Monthly!AI170 -> 453.66227 | M53: =GDS_Monthly!N170 -> 6.6798942 | N53: =GDS_Monthly!C170 -> 105.48216 | O53: =GDS_Monthly!F170 -> 3.8269269 | P53: =GDS_Monthly!G170 -> 3.1850525 | Q53: =GDS_Monthly!T170 -> 82.782137 | R53: =GDS_Monthly!V170 -> 87.232679 | S53: =GDS_Monthly!W170 -> 68.785437 | T53: =GDS_Monthly!X170 -> 43.642008 | U53: =GDS_Monthly!AA170 -> 55.794685 | V53: =GDS_Monthly!AC170 -> 71.476581 | W53: =GDS_Monthly!AE170 -> 60.683694 | X53: =GDS_Monthly!AF170 -> 77.515072 | Y53: =OECD!B53 -> 98.54743 | Z53: =OECD!C53 -> 95.72 | AA53: ='Monthly Haver'!K56 -> 110.57749 | AB53: ='Monthly Haver'!L56 -> 2064
A54: 37742 | B54: ='Monthly Haver'!C57 -> 52.0866 | C54: ='Monthly Haver'!D57 -> 49.9297 | D54: ='Monthly Haver'!E57 -> #N/A | E54: ='Monthly Haver'!G57 -> 47.9043 | F54: ='Monthly Haver'!H57 -> 48.5345 | G54: ='Monthly Haver'!I57 -> #N/A | H54: ='Monthly Haver'!J57 -> 52.3357 | I54: =GDS_Monthly!O171 -> 61.464917 | J54: =GDS_Monthly!D171 -> 76.008886 | K54: =GDS_Monthly!AH171 -> 482.07818 | L54: =GDS_Monthly!AI171 -> 460.50931 | M54: =GDS_Monthly!N171 -> 6.726817 | N54: =GDS_Monthly!C171 -> 106.39555 | O54: =GDS_Monthly!F171 -> 3.5050652 | P54: =GDS_Monthly!G171 -> 3.0861374 | Q54: =GDS_Monthly!T171 -> 82.773052 | R54: =GDS_Monthly!V171 -> 87.363366 | S54: =GDS_Monthly!W171 -> 68.979887 | T54: =GDS_Monthly!X171 -> 45.38297 | U54: =GDS_Monthly!AA171 -> 56.257468 | V54: =GDS_Monthly!AC171 -> 73.565354 | W54: =GDS_Monthly!AE171 -> 60.031044 | X54: =GDS_Monthly!AF171 -> 74.864642 | Y54: =OECD!B54 -> 98.67501 | Z54: =OECD!C54 -> 96.46 | AA54: ='Monthly Haver'!K57 -> 107.80908 | AB54: ='Monthly Haver'!L57 -> 2231
A55: 37773 | B55: ='Monthly Haver'!C58 -> 53.1992 | C55: ='Monthly Haver'!D58 -> 50.5913 | D55: ='Monthly Haver'!E58 -> #N/A | E55: ='Monthly Haver'!G58 -> 48.8498 | F55: ='Monthly Haver'!H58 -> 49.0534 | G55: ='Monthly Haver'!I58 -> #N/A | H55: ='Monthly Haver'!J58 -> 55.6037 | I55: =GDS_Monthly!O172 -> 62.111532 | J55: =GDS_Monthly!D172 -> 76.39924 | K55: =GDS_Monthly!AH172 -> 483.82072 | L55: =GDS_Monthly!AI172 -> 463.66495 | M55: =GDS_Monthly!N172 -> 6.7878641 | N55: =GDS_Monthly!C172 -> 106.85315 | O55: =GDS_Monthly!F172 -> 3.3189313 | P55: =GDS_Monthly!G172 -> 2.8376278 | Q55: =GDS_Monthly!T172 -> 82.831964 | R55: =GDS_Monthly!V172 -> 87.439007 | S55: =GDS_Monthly!W172 -> 68.420964 | T55: =GDS_Monthly!X172 -> 46.380451 | U55: =GDS_Monthly!AA172 -> 56.157644 | V55: =GDS_Monthly!AC172 -> 76.804902 | W55: =GDS_Monthly!AE172 -> 63.936055 | X55: =GDS_Monthly!AF172 -> 76.350811 | Y55: =OECD!B55 -> 98.86115 | Z55: =OECD!C55 -> 97.21 | AA55: ='Monthly Haver'!K58 -> 108.757 | AB55: ='Monthly Haver'!L58 -> 2136 | AC55: =Quarterly!B19 -> 97.05 | AD55: =Quarterly!C19 -> 90.43 | AE55: =Quarterly!D19 -> 83.474988
A56: 37803 | B56: ='Monthly Haver'!C59 -> 56.773 | C56: ='Monthly Haver'!D59 -> 49.6561 | D56: ='Monthly Haver'!E59 -> #N/A | E56: ='Monthly Haver'!G59 -> 49.3854 | F56: ='Monthly Haver'!H59 -> 50.442 | G56: ='Monthly Haver'!I59 -> #N/A | H56: ='Monthly Haver'!J59 -> 58.5182 | I56: =GDS_Monthly!O173 -> 62.640589 | J56: =GDS_Monthly!D173 -> 77.177224 | K56: =GDS_Monthly!AH173 -> 487.58836 | L56: =GDS_Monthly!AI173 -> 468.84484 | M56: =GDS_Monthly!N173 -> 6.7673884 | N56: =GDS_Monthly!C173 -> 105.27246 | O56: =GDS_Monthly!F173 -> 3.791824 | P56: =GDS_Monthly!G173 -> 2.752806 | Q56: =GDS_Monthly!T173 -> 83.007558 | R56: =GDS_Monthly!V173 -> 87.587428 | S56: =GDS_Monthly!W173 -> 65.76397 | T56: =GDS_Monthly!X173 -> 47.005523 | U56: =GDS_Monthly!AA173 -> 55.105159 | V56: =GDS_Monthly!AC173 -> 75.83765 | W56: =GDS_Monthly!AE173 -> 66.277428 | X56: =GDS_Monthly!AF173 -> 76.820276 | Y56: =OECD!B56 -> 99.09087 | Z56: =OECD!C56 -> 98.07 | AA56: ='Monthly Haver'!K59 -> 109.08845 | AB56: ='Monthly Haver'!L59 -> 2192
A57: 37834 | B57: ='Monthly Haver'!C60 -> 59.9233 | C57: ='Monthly Haver'!D60 -> 52.1859 | D57: ='Monthly Haver'!E60 -> #N/A | E57: ='Monthly Haver'!G60 -> 50.515 | F57: ='Monthly Haver'!H60 -> 52.3762 | G57: ='Monthly Haver'!I60 -> #N/A | H57: ='Monthly Haver'!J60 -> 60.5147 | I57: =GDS_Monthly!O174 -> 63.25484 | J57: =GDS_Monthly!D174 -> 77.141861 | K57: =GDS_Monthly!AH174 -> 473.93087 | L57: =GDS_Monthly!AI174 -> 462.10477 | M57: =GDS_Monthly!N174 -> 6.7635524 | N57: =GDS_Monthly!C174 -> 106.6613 | O57: =GDS_Monthly!F174 -> 4.0670803 | P57: =GDS_Monthly!G174 -> 2.6574148 | Q57: =GDS_Monthly!T174 -> 83.213674 | R57: =GDS_Monthly!V174 -> 87.676957 | S57: =GDS_Monthly!W174 -> 66.160756 | T57: =GDS_Monthly!X174 -> 48.042891 | U57: =GDS_Monthly!AA174 -> 55.682293 | V57: =GDS_Monthly!AC174 -> 77.80035 | W57: =GDS_Monthly!AE174 -> 69.461268 | X57: =GDS_Monthly!AF174 -> 77.650758 | Y57: =OECD!B57 -> 99.34694 | Z57: =OECD!C57 -> 98.52 | AA57: ='Monthly Haver'!K60 -> 110.40733 | AB57: ='Monthly Haver'!L60 -> 2286
A58: 37865 | B58: ='Monthly Haver'!C61 -> 58.5695 | C58: ='Monthly Haver'!D61 -> 54.1345 | D58: ='Monthly Haver'!E61 -> #N/A | E58: ='Monthly Haver'!G61 -> 50.0927 | F58: ='Monthly Haver'!H61 -> 52.4912 | G58: ='Monthly Haver'!I61 -> #N/A | H58: ='Monthly Haver'!J61 -> 60.2523 | I58: =GDS_Monthly!O175 -> 63.625112 | J58: =GDS_Monthly!D175 -> 77.812514 | K58: =GDS_Monthly!AH175 -> 499.30736 | L58: =GDS_Monthly!AI175 -> 481.43572 | M58: =GDS_Monthly!N175 -> 6.7649692 | N58: =GDS_Monthly!C175 -> 105.47968 | O58: =GDS_Monthly!F175 -> 4.04022 | P58: =GDS_Monthly!G175 -> 2.5928324 | Q58: =GDS_Monthly!T175 -> 83.426975 | R58: =GDS_Monthly!V175 -> 87.778451 | S58: =GDS_Monthly!W175 -> 72.327667 | T58: =GDS_Monthly!X175 -> 48.74995 | U58: =GDS_Monthly!AA175 -> 59.267557 | V58: =GDS_Monthly!AC175 -> 72.634857 | W58: =GDS_Monthly!AE175 -> 62.538034 | X58: =GDS_Monthly!AF175 -> 79.225378 | Y58: =OECD!B58 -> 99.61718 | Z58: =OECD!C58 -> 99.58 | AA58: ='Monthly Haver'!K61 -> 109.30088 | AB58: ='Monthly Haver'!L61 -> 2463 | AC58: =Quarterly!B20 -> 97.67 | AD58: =Quarterly!C20 -> 91.22 | AE58: =Quarterly!D20 -> 84.557792
A59: 37895 | B59: ='Monthly Haver'!C62 -> 61.1091 | C59: ='Monthly Haver'!D62 -> 54.5367 | D59: ='Monthly Haver'!E62 -> #N/A | E59: ='Monthly Haver'!G62 -> 51.6787 | F59: ='Monthly Haver'!H62 -> 54.6923 | G59: ='Monthly Haver'!I62 -> #N/A | H59: ='Monthly Haver'!J62 -> 61.4265 | I59: =GDS_Monthly!O176 -> 64.028999 | J59: =GDS_Monthly!D176 -> 78.75099 | K59: =GDS_Monthly!AH176 -> 515.58454 | L59: =GDS_Monthly!AI176 -> 498.04953 | M59: =GDS_Monthly!N176 -> 6.7235594 | N59: =GDS_Monthly!C176 -> 106.87009 | O59: =GDS_Monthly!F176 -> 4.0740114 | P59: =GDS_Monthly!G176 -> 2.5556408 | Q59: =GDS_Monthly!T176 -> 83.483181 | R59: =GDS_Monthly!V176 -> 87.878588 | S59: =GDS_Monthly!W176 -> 75.768352 | T59: =GDS_Monthly!X176 -> 51.909958 | U59: =GDS_Monthly!AA176 -> 61.688603 | V59: =GDS_Monthly!AC176 -> 76.389471 | W59: =GDS_Monthly!AE176 -> 65.680893 | X59: =GDS_Monthly!AF176 -> 83.039186 | Y59: =OECD!B59 -> 99.88125 | Z59: =OECD!C59 -> 100.42 | AA59: ='Monthly Haver'!K62 -> 107.82919 | AB59: ='Monthly Haver'!L62 -> 4163
A60: 37926 | B60: ='Monthly Haver'!C63 -> 61.4528 | C60: ='Monthly Haver'!D63 -> 56.1739 | D60: ='Monthly Haver'!E63 -> #N/A | E60: ='Monthly Haver'!G63 -> 52.9532 | F60: ='Monthly Haver'!H63 -> 56.3787 | G60: ='Monthly Haver'!I63 -> #N/A | H60: ='Monthly Haver'!J63 -> 59.8619 | I60: =GDS_Monthly!O177 -> 63.995852 | J60: =GDS_Monthly!D177 -> 78.666847 | K60: =GDS_Monthly!AH177 -> 515.92069 | L60: =GDS_Monthly!AI177 -> 497.67908 | M60: =GDS_Monthly!N177 -> 6.6676705 | N60: =GDS_Monthly!C177 -> 109.80951 | O60: =GDS_Monthly!F177 -> 4.1456315 | P60: =GDS_Monthly!G177 -> 2.5314748 | Q60: =GDS_Monthly!T177 -> 83.632641 | R60: =GDS_Monthly!V177 -> 87.948206 | S60: =GDS_Monthly!W177 -> 73.488631 | T60: =GDS_Monthly!X177 -> 54.645296 | U60: =GDS_Monthly!AA177 -> 61.443882 | V60: =GDS_Monthly!AC177 -> 76.609654 | W60: =GDS_Monthly!AE177 -> 65.810034 | X60: =GDS_Monthly!AF177 -> 83.453041 | Y60: =OECD!B60 -> 100.1177 | Z60: =OECD!C60 -> 101.38 | AA60: ='Monthly Haver'!K63 -> 107.18974 | AB60: ='Monthly Haver'!L63 -> 4250
A61: 37956 | B61: ='Monthly Haver'!C64 -> 61.3864 | C61: ='Monthly Haver'!D64 -> 57.463 | D61: ='Monthly Haver'!E64 -> #N/A | E61: ='Monthly Haver'!G64 -> 53.3313 | F61: ='Monthly Haver'!H64 -> 57.3487 | G61: ='Monthly Haver'!I64 -> #N/A | H61: ='Monthly Haver'!J64 -> 58.8222 | I61: =GDS_Monthly!O178 -> 64.486385 | J61: =GDS_Monthly!D178 -> 79.69776 | K61: =GDS_Monthly!AH178 -> 544.1454 | L61: =GDS_Monthly!AI178 -> 527.25938 | M61: =GDS_Monthly!N178 -> 6.6287804 | N61: =GDS_Monthly!C178 -> 110.54565 | O61: =GDS_Monthly!F178 -> 4.0859272 | P61: =GDS_Monthly!G178 -> 2.5337041 | Q61: =GDS_Monthly!T178 -> 83.835146 | R61: =GDS_Monthly!V178 -> 88.047572 | S61: =GDS_Monthly!W178 -> 72.943296 | T61: =GDS_Monthly!X178 -> 59.217722 | U61: =GDS_Monthly!AA178 -> 62.361554 | V61: =GDS_Monthly!AC178 -> 83.000744 | W61: =GDS_Monthly!AE178 -> 66.1564 | X61: =GDS_Monthly!AF178 -> 81.470136 | Y61: =OECD!B61 -> 100.311 | Z61: =OECD!C61 -> 101.94 | AA61: ='Monthly Haver'!K64 -> 105.89693 | AB61: ='Monthly Haver'!L64 -> 4609 | AC61: =Quarterly!B21 -> 97.98 | AD61: =Quarterly!C21 -> 92.56 | AE61: =Quarterly!D21 -> 85.609271
A62: 37987 | B62: ='Monthly Haver'!C65 -> 62.997 | C62: ='Monthly Haver'!D65 -> 59.8881 | D62: ='Monthly Haver'!E65 -> #N/A | E62: ='Monthly Haver'!G65 -> 53.5634 | F62: ='Monthly Haver'!H65 -> 57.4034 | G62: ='Monthly Haver'!I65 -> #N/A | H62: ='Monthly Haver'!J65 -> 63.822 | I62: =GDS_Monthly!O179 -> 65.18305 | J62: =GDS_Monthly!D179 -> 80.082683 | K62: =GDS_Monthly!AH179 -> 551.00929 | L62: =GDS_Monthly!AI179 -> 529.25164 | M62: =GDS_Monthly!N179 -> 6.691015 | N62: =GDS_Monthly!C179 -> 111.3337 | O62: =GDS_Monthly!F179 -> 4.0499519 | P62: =GDS_Monthly!G179 -> 2.552729 | Q62: =GDS_Monthly!T179 -> 84.049207 | R62: =GDS_Monthly!V179 -> 88.203396 | S62: =GDS_Monthly!W179 -> 74.314286 | T62: =GDS_Monthly!X179 -> 64.337303 | U62: =GDS_Monthly!AA179 -> 64.478537 | V62: =GDS_Monthly!AC179 -> 86.244799 | W62: =GDS_Monthly!AE179 -> 68.048035 | X62: =GDS_Monthly!AF179 -> 83.777163 | Y62: =OECD!B62 -> 100.4542 | Z62: =OECD!C62 -> 102.69 | AA62: ='Monthly Haver'!K65 -> 104.86236 | AB62: ='Monthly Haver'!L65 -> 5234
A63: 38018 | B63: ='Monthly Haver'!C66 -> 60.1005 | C63: ='Monthly Haver'!D66 -> 60.5912 | D63: ='Monthly Haver'!E66 -> #N/A | E63: ='Monthly Haver'!G66 -> 52.7766 | F63: ='Monthly Haver'!H66 -> 56.3988 | G63: ='Monthly Haver'!I66 -> #N/A | H63: ='Monthly Haver'!J66 -> 60.2597 | I63: =GDS_Monthly!O180 -> 65.998996 | J63: =GDS_Monthly!D180 -> 80.390023 | K63: =GDS_Monthly!AH180 -> 569.07123 | L63: =GDS_Monthly!AI180 -> 545.14641 | M63: =GDS_Monthly!N180 -> 6.6686616 | N63: =GDS_Monthly!C180 -> 108.98666 | O63: =GDS_Monthly!F180 -> 3.9916713 | P63: =GDS_Monthly!G180 -> 2.5533572 | Q63: =GDS_Monthly!T180 -> 84.222771 | R63: =GDS_Monthly!V180 -> 88.332297 | S63: =GDS_Monthly!W180 -> 74.915534 | T63: =GDS_Monthly!X180 -> 67.686744 | U63: =GDS_Monthly!AA180 -> 65.380648 | V63: =GDS_Monthly!AC180 -> 84.316824 | W63: =GDS_Monthly!AE180 -> 67.84845 | X63: =GDS_Monthly!AF180 -> 85.733717 | Y63: =OECD!B63 -> 100.542 | Z63: =OECD!C63 -> 103.43 | AA63: ='Monthly Haver'!K66 -> 105.00616 | AB63: ='Monthly Haver'!L66 -> 5450
A64: 38047 | B64: ='Monthly Haver'!C67 -> 59.8424 | C64: ='Monthly Haver'!D67 -> 64.555 | D64: ='Monthly Haver'!E67 -> #N/A | E64: ='Monthly Haver'!G67 -> 53.4547 | F64: ='Monthly Haver'!H67 -> 56.9415 | G64: ='Monthly Haver'!I67 -> #N/A | H64: ='Monthly Haver'!J67 -> 59.4727 | I64: =GDS_Monthly!O181 -> 66.318007 | J64: =GDS_Monthly!D181 -> 80.633678 | K64: =GDS_Monthly!AH181 -> 573.16211 | L64: =GDS_Monthly!AI181 -> 547.25082 | M64: =GDS_Monthly!N181 -> 6.6758388 | N64: =GDS_Monthly!C181 -> 107.84556 | O64: =GDS_Monthly!F181 -> 3.8432813 | P64: =GDS_Monthly!G181 -> 2.5322114 | Q64: =GDS_Monthly!T181 -> 84.414133 | R64: =GDS_Monthly!V181 -> 88.497956 | S64: =GDS_Monthly!W181 -> 79.888253 | T64: =GDS_Monthly!X181 -> 67.603596 | U64: =GDS_Monthly!AA181 -> 67.689023 | V64: =GDS_Monthly!AC181 -> 87.764426 | W64: =GDS_Monthly!AE181 -> 74.057952 | X64: =GDS_Monthly!AF181 -> 85.334698 | Y64: =OECD!B64 -> 100.5792 | Z64: =OECD!C64 -> 104.3 | AA64: ='Monthly Haver'!K67 -> 105.79173 | AB64: ='Monthly Haver'!L67 -> 5131 | AC64: =Quarterly!B22 -> 98.4 | AD64: =Quarterly!C22 -> 93.24 | AE64: =Quarterly!D22 -> 86.349635
A65: 38078 | B65: ='Monthly Haver'!C68 -> 60.2149 | C65: ='Monthly Haver'!D68 -> 66.6788 | D65: ='Monthly Haver'!E68 -> #N/A | E65: ='Monthly Haver'!G68 -> 54.3846 | F65: ='Monthly Haver'!H68 -> 57.5131 | G65: ='Monthly Haver'!I68 -> #N/A | H65: ='Monthly Haver'!J68 -> 60.5737 | I65: =GDS_Monthly!O182 -> 66.616046 | J65: =GDS_Monthly!D182 -> 81.385877 | K65: =GDS_Monthly!AH182 -> 581.12624 | L65: =GDS_Monthly!AI182 -> 554.65482 | M65: =GDS_Monthly!N182 -> 6.6761635 | N65: =GDS_Monthly!C182 -> 108.99571 | O65: =GDS_Monthly!F182 -> 4.1676757 | P65: =GDS_Monthly!G182 -> 2.5000458 | Q65: =GDS_Monthly!T182 -> 84.60034 | R65: =GDS_Monthly!V182 -> 88.65576 | S65: =GDS_Monthly!W182 -> 81.598087 | T65: =GDS_Monthly!X182 -> 66.23998 | U65: =GDS_Monthly!AA182 -> 68.041908 | V65: =GDS_Monthly!AC182 -> 89.681737 | W65: =GDS_Monthly!AE182 -> 74.82629 | X65: =GDS_Monthly!AF182 -> 85.070455 | Y65: =OECD!B65 -> 100.5778 | Z65: =OECD!C65 -> 104.5 | AA65: ='Monthly Haver'!K68 -> 106.77522 | AB65: ='Monthly Haver'!L68 -> 4494
A66: 38108 | B66: ='Monthly Haver'!C69 -> 59.547 | C66: ='Monthly Haver'!D69 -> 67.9741 | D66: ='Monthly Haver'!E69 -> #N/A | E66: ='Monthly Haver'!G69 -> 54.7411 | F66: ='Monthly Haver'!H69 -> 57.6535 | G66: ='Monthly Haver'!I69 -> #N/A | H66: ='Monthly Haver'!J69 -> 59.921 | I66: =GDS_Monthly!O183 -> 66.839416 | J66: =GDS_Monthly!D183 -> 81.671091 | K66: =GDS_Monthly!AH183 -> 581.16237 | L66: =GDS_Monthly!AI183 -> 560.45466 | M66: =GDS_Monthly!N183 -> 6.6082547 | N66: =GDS_Monthly!C183 -> 109.23652 | O66: =GDS_Monthly!F183 -> 4.3999606 | P66: =GDS_Monthly!G183 -> 2.5306899 | Q66: =GDS_Monthly!T183 -> 84.854069 | R66: =GDS_Monthly!V183 -> 88.765391 | S66: =GDS_Monthly!W183 -> 82.236167 | T66: =GDS_Monthly!X183 -> 62.285987 | U66: =GDS_Monthly!AA183 -> 67.343731 | V66: =GDS_Monthly!AC183 -> 98.390902 | W66: =GDS_Monthly!AE183 -> 83.738409 | X66: =GDS_Monthly!AF183 -> 87.956893 | Y66: =OECD!B66 -> 100.5507 | Z66: =OECD!C66 -> 104.98 | AA66: ='Monthly Haver'!K69 -> 109.33208 | AB66: ='Monthly Haver'!L69 -> 3596
A67: 38139 | B67: ='Monthly Haver'!C70 -> 59.1365 | C67: ='Monthly Haver'!D70 -> 67.903 | D67: ='Monthly Haver'!E70 -> #N/A | E67: ='Monthly Haver'!G70 -> 54.7361 | F67: ='Monthly Haver'!H70 -> 56.1194 | G67: ='Monthly Haver'!I70 -> #N/A | H67: ='Monthly Haver'!J70 -> 57.6871 | I67: =GDS_Monthly!O184 -> 67.264041 | J67: =GDS_Monthly!D184 -> 81.687306 | K67: =GDS_Monthly!AH184 -> 602.5525 | L67: =GDS_Monthly!AI184 -> 568.86969 | M67: =GDS_Monthly!N184 -> 6.6053579 | N67: =GDS_Monthly!C184 -> 111.21634 | O67: =GDS_Monthly!F184 -> 4.4812207 | P67: =GDS_Monthly!G184 -> 2.630963 | Q67: =GDS_Monthly!T184 -> 85.099352 | R67: =GDS_Monthly!V184 -> 88.929923 | S67: =GDS_Monthly!W184 -> 78.183222 | T67: =GDS_Monthly!X184 -> 65.540191 | U67: =GDS_Monthly!AA184 -> 66.321395 | V67: =GDS_Monthly!AC184 -> 96.114393 | W67: =GDS_Monthly!AE184 -> 78.64642 | X67: =GDS_Monthly!AF184 -> 87.237329 | Y67: =OECD!B67 -> 100.5088 | Z67: =OECD!C67 -> 104.79 | AA67: ='Monthly Haver'!K70 -> 108.60087 | AB67: ='Monthly Haver'!L70 -> 2902 | AC67: =Quarterly!B23 -> 99.01 | AD67: =Quarterly!C23 -> 94.3 | AE67: =Quarterly!D23 -> 87.004201
A68: 38169 | B68: ='Monthly Haver'!C71 -> 59.8228 | C68: ='Monthly Haver'!D71 -> 66.5957 | D68: ='Monthly Haver'!E71 -> #N/A | E68: ='Monthly Haver'!G71 -> 52.3963 | F68: ='Monthly Haver'!H71 -> 56.3147 | G68: ='Monthly Haver'!I71 -> #N/A | H68: ='Monthly Haver'!J71 -> 60.1086 | I68: =GDS_Monthly!O185 -> 67.823759 | J68: =GDS_Monthly!D185 -> 82.296484 | K68: =GDS_Monthly!AH185 -> 601.04863 | L68: =GDS_Monthly!AI185 -> 574.26957 | M68: =GDS_Monthly!N185 -> 6.488227 | N68: =GDS_Monthly!C185 -> 112.1145 | O68: =GDS_Monthly!F185 -> 4.3459861 | P68: =GDS_Monthly!G185 -> 2.6384689 | Q68: =GDS_Monthly!T185 -> 85.226789 | R68: =GDS_Monthly!V185 -> 89.060451 | S68: =GDS_Monthly!W185 -> 75.408641 | T68: =GDS_Monthly!X185 -> 68.331077 | U68: =GDS_Monthly!AA185 -> 65.593156 | V68: =GDS_Monthly!AC185 -> 100.31401 | W68: =GDS_Monthly!AE185 -> 83.295592 | X68: =GDS_Monthly!AF185 -> 84.760641 | Y68: =OECD!B68 -> 100.4577 | Z68: =OECD!C68 -> 105.31 | AA68: ='Monthly Haver'!K71 -> 107.48143 | AB68: ='Monthly Haver'!L71 -> 3778
A69: 38200 | B69: ='Monthly Haver'!C72 -> 57.6305 | C69: ='Monthly Haver'!D72 -> 67.4934 | D69: ='Monthly Haver'!E72 -> #N/A | E69: ='Monthly Haver'!G72 -> 53.7178 | F69: ='Monthly Haver'!H72 -> 55.2416 | G69: ='Monthly Haver'!I72 -> #N/A | H69: ='Monthly Haver'!J72 -> 57.7518 | I69: =GDS_Monthly!O186 -> 67.963997 | J69: =GDS_Monthly!D186 -> 82.185292 | K69: =GDS_Monthly!AH186 -> 600.45883 | L69: =GDS_Monthly!AI186 -> 569.14817 | M69: =GDS_Monthly!N186 -> 6.4836545 | N69: =GDS_Monthly!C186 -> 110.50143 | O69: =GDS_Monthly!F186 -> 4.1797511 | P69: =GDS_Monthly!G186 -> 2.7391494 | Q69: =GDS_Monthly!T186 -> 85.364819 | R69: =GDS_Monthly!V186 -> 89.161566 | S69: =GDS_Monthly!W186 -> 71.567492 | T69: =GDS_Monthly!X186 -> 66.553173 | U69: =GDS_Monthly!AA186 -> 63.657799 | V69: =GDS_Monthly!AC186 -> 106.30566 | W69: =GDS_Monthly!AE186 -> 93.069202 | X69: =GDS_Monthly!AF186 -> 84.27062 | Y69: =OECD!B69 -> 100.4039 | Z69: =OECD!C69 -> 105.7 | AA69: ='Monthly Haver'!K72 -> 107.68157 | AB69: ='Monthly Haver'!L72 -> 4169
A70: 38231 | B70: ='Monthly Haver'!C73 -> 57.2014 | C70: ='Monthly Haver'!D73 -> 65.6032 | D70: ='Monthly Haver'!E73 -> #N/A | E70: ='Monthly Haver'!G73 -> 54.5402 | F70: ='Monthly Haver'!H73 -> 54.3541 | G70: ='Monthly Haver'!I73 -> #N/A | H70: ='Monthly Haver'!J73 -> 57.4744 | I70: =GDS_Monthly!O187 -> 68.89557 | J70: =GDS_Monthly!D187 -> 82.810007 | K70: =GDS_Monthly!AH187 -> 610.98485 | L70: =GDS_Monthly!AI187 -> 579.0411 | M70: =GDS_Monthly!N187 -> 6.4678864 | N70: =GDS_Monthly!C187 -> 109.9712 | O70: =GDS_Monthly!F187 -> 4.0725424 | P70: =GDS_Monthly!G187 -> 2.8344171 | Q70: =GDS_Monthly!T187 -> 85.56392 | R70: =GDS_Monthly!V187 -> 89.325462 | S70: =GDS_Monthly!W187 -> 72.30571 | T70: =GDS_Monthly!X187 -> 67.110516 | U70: =GDS_Monthly!AA187 -> 64.201963 | V70: =GDS_Monthly!AC187 -> 104.62432 | W70: =GDS_Monthly!AE187 -> 91.875717 | X70: =GDS_Monthly!AF187 -> 84.15022 | Y70: =OECD!B70 -> 100.3622 | Z70: =OECD!C70 -> 106.32 | AA70: ='Monthly Haver'!K73 -> 106.54417 | AB70: ='Monthly Haver'!L73 -> 4141 | AC70: =Quarterly!B24 -> 99.3 | AD70: =Quarterly!C24 -> 95.9 | AE70: =Quarterly!D24 -> 87.714654
A71: 38261 | B71: ='Monthly Haver'!C74 -> 57.3986 | C71: ='Monthly Haver'!D74 -> 69.3571 | D71: ='Monthly Haver'!E74 -> #N/A | E71: ='Monthly Haver'!G74 -> 54.5733 | F71: ='Monthly Haver'!H74 -> 53.6267 | G71: ='Monthly Haver'!I74 -> #N/A | H71: ='Monthly Haver'!J74 -> 58.236 | I71: =GDS_Monthly!O188 -> 69.28068 | J71: =GDS_Monthly!D188 -> 83.212717 | K71: =GDS_Monthly!AH188 -> 626.53834 | L71: =GDS_Monthly!AI188 -> 593.03126 | M71: =GDS_Monthly!N188 -> 6.4131851 | N71: =GDS_Monthly!C188 -> 109.3927 | O71: =GDS_Monthly!F188 -> 4.0037803 | P71: =GDS_Monthly!G188 -> 2.8532556 | Q71: =GDS_Monthly!T188 -> 85.897868 | R71: =GDS_Monthly!V188 -> 89.476763 | S71: =GDS_Monthly!W188 -> 71.638728 | T71: =GDS_Monthly!X188 -> 70.176892 | U71: =GDS_Monthly!AA188 -> 64.719694 | V71: =GDS_Monthly!AC188 -> 118.03434 | W71: =GDS_Monthly!AE188 -> 102.44019 | X71: =GDS_Monthly!AF188 -> 83.675186 | Y71: =OECD!B71 -> 100.3329 | Z71: =OECD!C71 -> 106.82 | AA71: ='Monthly Haver'!K74 -> 106.16199 | AB71: ='Monthly Haver'!L74 -> 4539
A72: 38292 | B72: ='Monthly Haver'!C75 -> 56.6369 | C72: ='Monthly Haver'!D75 -> 67.0422 | D72: ='Monthly Haver'!E75 -> #N/A | E72: ='Monthly Haver'!G75 -> 54.191 | F72: ='Monthly Haver'!H75 -> 52.9771 | G72: ='Monthly Haver'!I75 -> #N/A | H72: ='Monthly Haver'!J75 -> 59.1069 | I72: =GDS_Monthly!O189 -> 69.71415 | J72: =GDS_Monthly!D189 -> 83.107116 | K72: =GDS_Monthly!AH189 -> 649.84852 | L72: =GDS_Monthly!AI189 -> 613.07856 | M72: =GDS_Monthly!N189 -> 6.416888 | N72: =GDS_Monthly!C189 -> 109.5024 | O72: =GDS_Monthly!F189 -> 4.0101374 | P72: =GDS_Monthly!G189 -> 2.9632576 | Q72: =GDS_Monthly!T189 -> 86.139939 | R72: =GDS_Monthly!V189 -> 89.619444 | S72: =GDS_Monthly!W189 -> 73.557128 | T72: =GDS_Monthly!X189 -> 70.338653 | U72: =GDS_Monthly!AA189 -> 66.034822 | V72: =GDS_Monthly!AC189 -> 109.62584 | W72: =GDS_Monthly!AE189 -> 90.040383 | X72: =GDS_Monthly!AF189 -> 81.351092 | Y72: =OECD!B72 -> 100.3136 | Z72: =OECD!C72 -> 107.57 | AA72: ='Monthly Haver'!K75 -> 104.87344 | AB72: ='Monthly Haver'!L75 -> 5309
A73: 38322 | B73: ='Monthly Haver'!C76 -> 58.3642 | C73: ='Monthly Haver'!D76 -> 65.6102 | D73: ='Monthly Haver'!E76 -> #N/A | E73: ='Monthly Haver'!G76 -> 53.5789 | F73: ='Monthly Haver'!H76 -> 53.3556 | G73: ='Monthly Haver'!I76 -> #N/A | H73: ='Monthly Haver'!J76 -> 60.3055 | I73: =GDS_Monthly!O190 -> 70.380701 | J73: =GDS_Monthly!D190 -> 83.823321 | K73: =GDS_Monthly!AH190 -> 653.97172 | L73: =GDS_Monthly!AI190 -> 624.85855 | M73: =GDS_Monthly!N190 -> 6.399185 | N73: =GDS_Monthly!C190 -> 111.6077 | O73: =GDS_Monthly!F190 -> 3.9086505 | P73: =GDS_Monthly!G190 -> 3.0556733 | Q73: =GDS_Monthly!T190 -> 86.18397 | R73: =GDS_Monthly!V190 -> 89.762698 | S73: =GDS_Monthly!W190 -> 77.43877 | T73: =GDS_Monthly!X190 -> 70.563798 | U73: =GDS_Monthly!AA190 -> 67.780899 | V73: =GDS_Monthly!AC190 -> 104.28917 | W73: =GDS_Monthly!AE190 -> 82.105592 | X73: =GDS_Monthly!AF190 -> 78.404359 | Y73: =OECD!B73 -> 100.2903 | Z73: =OECD!C73 -> 108.74 | AA73: ='Monthly Haver'!K76 -> 103.07322 | AB73: ='Monthly Haver'!L76 -> 5519 | AC73: =Quarterly!B25 -> 99.69 | AD73: =Quarterly!C25 -> 96.72 | AE73: =Quarterly!D25 -> 88.368601
A74: 38353 | B74: ='Monthly Haver'!C77 -> 58.5724 | C74: ='Monthly Haver'!D77 -> 64.247 | D74: ='Monthly Haver'!E77 -> #N/A | E74: ='Monthly Haver'!G77 -> 54.873 | F74: ='Monthly Haver'!H77 -> 53.3392 | G74: ='Monthly Haver'!I77 -> #N/A | H74: ='Monthly Haver'!J77 -> 59.0926 | I74: =GDS_Monthly!O191 -> 71.00556 | J74: =GDS_Monthly!D191 -> 84.532695 | K74: =GDS_Monthly!AH191 -> 650.15127 | L74: =GDS_Monthly!AI191 -> 617.724 | M74: =GDS_Monthly!N191 -> 6.4143874 | N74: =GDS_Monthly!C191 -> 111.91058 | O74: =GDS_Monthly!F191 -> 3.913667 | P74: =GDS_Monthly!G191 -> 3.0910548 | Q74: =GDS_Monthly!T191 -> 86.217155 | R74: =GDS_Monthly!V191 -> 89.919233 | S74: =GDS_Monthly!W191 -> 77.483421 | T74: =GDS_Monthly!X191 -> 77.734825 | U74: =GDS_Monthly!AA191 -> 69.112516 | V74: =GDS_Monthly!AC191 -> 109.68673 | W74: =GDS_Monthly!AE191 -> 91.388984 | X74: =GDS_Monthly!AF191 -> 82.135662 | Y74: =OECD!B74 -> 100.2486 | Z74: =OECD!C74 -> 108.18 | AA74: ='Monthly Haver'!K77 -> 103.63329 | AB74: ='Monthly Haver'!L77 -> 4502
A75: 38384 | B75: ='Monthly Haver'!C78 -> 58.8373 | C75: ='Monthly Haver'!D78 -> 63.8704 | D75: ='Monthly Haver'!E78 -> #N/A | E75: ='Monthly Haver'!G78 -> 57.1416 | F75: ='Monthly Haver'!H78 -> 53.1659 | G75: ='Monthly Haver'!I78 -> #N/A | H75: ='Monthly Haver'!J78 -> 58.6751 | I75: =GDS_Monthly!O192 -> 71.304593 | J75: =GDS_Monthly!D192 -> 84.837328 | K75: =GDS_Monthly!AH192 -> 654.1116 | L75: =GDS_Monthly!AI192 -> 620.09783 | M75: =GDS_Monthly!N192 -> 6.4018837 | N75: =GDS_Monthly!C192 -> 111.78911 | O75: =GDS_Monthly!F192 -> 3.8880904 | P75: =GDS_Monthly!G192 -> 3.1787731 | Q75: =GDS_Monthly!T192 -> 86.498219 | R75: =GDS_Monthly!V192 -> 90.022229 | S75: =GDS_Monthly!W192 -> 80.079776 | T75: =GDS_Monthly!X192 -> 80.009994 | U75: =GDS_Monthly!AA192 -> 71.07694 | V75: =GDS_Monthly!AC192 -> 111.8372 | W75: =GDS_Monthly!AE192 -> 94.726472 | X75: =GDS_Monthly!AF192 -> 82.210298 | Y75: =OECD!B75 -> 100.1818 | Z75: =OECD!C75 -> 109.29 | AA75: ='Monthly Haver'!K78 -> 103.89552 | AB75: ='Monthly Haver'!L78 -> 4532
A76: 38412 | B76: ='Monthly Haver'!C79 -> 57.6552 | C76: ='Monthly Haver'!D79 -> 62.4973 | D76: ='Monthly Haver'!E79 -> #N/A | E76: ='Monthly Haver'!G79 -> 55.9927 | F76: ='Monthly Haver'!H79 -> 53.3691 | G76: ='Monthly Haver'!I79 -> #N/A | H76: ='Monthly Haver'!J79 -> 58.3654 | I76: =GDS_Monthly!O193 -> 71.766487 | J76: =GDS_Monthly!D193 -> 84.938922 | K76: =GDS_Monthly!AH193 -> 673.25832 | L76: =GDS_Monthly!AI193 -> 635.63973 | M76: =GDS_Monthly!N193 -> 6.3646613 | N76: =GDS_Monthly!C193 -> 111.23282 | O76: =GDS_Monthly!F193 -> 4.0964017 | P76: =GDS_Monthly!G193 -> 3.2637468 | Q76: =GDS_Monthly!T193 -> 86.735304 | R76: =GDS_Monthly!V193 -> 90.169397 | S76: =GDS_Monthly!W193 -> 81.512352 | T76: =GDS_Monthly!X193 -> 82.993805 | U76: =GDS_Monthly!AA193 -> 73.173236 | V76: =GDS_Monthly!AC193 -> 125.78819 | W76: =GDS_Monthly!AE193 -> 108.13514 | X76: =GDS_Monthly!AF193 -> 86.86156 | Y76: =OECD!B76 -> 100.1031 | Z76: =OECD!C76 -> 109.48 | AA76: ='Monthly Haver'!K79 -> 103.83706 | AB76: ='Monthly Haver'!L79 -> 4678 | AC76: =Quarterly!B26 -> 99.38 | AD76: =Quarterly!C26 -> 98.04 | AE76: =Quarterly!D26 -> 89.152565
A77: 38443 | B77: ='Monthly Haver'!C80 -> 55.8936 | C77: ='Monthly Haver'!D80 -> 60.6961 | D77: ='Monthly Haver'!E80 -> #N/A | E77: ='Monthly Haver'!G80 -> 54.1483 | F77: ='Monthly Haver'!H80 -> 51.9064 | G77: ='Monthly Haver'!I80 -> #N/A | H77: ='Monthly Haver'!J80 -> 56.5683 | I77: =GDS_Monthly!O194 -> 72.448602 | J77: =GDS_Monthly!D194 -> 85.684267 | K77: =GDS_Monthly!AH194 -> 682.70476 | L77: =GDS_Monthly!AI194 -> 645.23286 | M77: =GDS_Monthly!N194 -> 6.3253863 | N77: =GDS_Monthly!C194 -> 110.01756 | O77: =GDS_Monthly!F194 -> 3.9561713 | P77: =GDS_Monthly!G194 -> 3.2613838 | Q77: =GDS_Monthly!T194 -> 86.944272 | R77: =GDS_Monthly!V194 -> 90.266668 | S77: =GDS_Monthly!W194 -> 79.312799 | T77: =GDS_Monthly!X194 -> 82.036843 | U77: =GDS_Monthly!AA194 -> 71.689842 | V77: =GDS_Monthly!AC194 -> 127.00292 | W77: =GDS_Monthly!AE194 -> 108.67103 | X77: =GDS_Monthly!AF194 -> 84.983677 | Y77: =OECD!B77 -> 100.0342 | Z77: =OECD!C77 -> 109.43 | AA77: ='Monthly Haver'!K80 -> 104.71813 | AB77: ='Monthly Haver'!L80 -> 4532
A78: 38473 | B78: ='Monthly Haver'!C81 -> 56.0128 | C78: ='Monthly Haver'!D81 -> 56.0624 | D78: ='Monthly Haver'!E81 -> #N/A | E78: ='Monthly Haver'!G81 -> 53.0499 | F78: ='Monthly Haver'!H81 -> 51.3967 | G78: ='Monthly Haver'!I81 -> #N/A | H78: ='Monthly Haver'!J81 -> 55.968 | I78: =GDS_Monthly!O195 -> 72.273377 | J78: =GDS_Monthly!D195 -> 85.462512 | K78: =GDS_Monthly!AH195 -> 680.60729 | L78: =GDS_Monthly!AI195 -> 643.51803 | M78: =GDS_Monthly!N195 -> 6.3342861 | N78: =GDS_Monthly!C195 -> 111.13938 | O78: =GDS_Monthly!F195 -> 3.7834795 | P78: =GDS_Monthly!G195 -> 3.3415511 | Q78: =GDS_Monthly!T195 -> 87.007296 | R78: =GDS_Monthly!V195 -> 90.40044 | S78: =GDS_Monthly!W195 -> 80.268147 | T78: =GDS_Monthly!X195 -> 81.234578 | U78: =GDS_Monthly!AA195 -> 72.018087 | V78: =GDS_Monthly!AC195 -> 120.4276 | W78: =GDS_Monthly!AE195 -> 103.67401 | X78: =GDS_Monthly!AF195 -> 85.685353 | Y78: =OECD!B78 -> 99.99854 | Z78: =OECD!C78 -> 108.73 | AA78: ='Monthly Haver'!K81 -> 105.01679 | AB78: ='Monthly Haver'!L81 -> 3667
A79: 38504 | B79: ='Monthly Haver'!C82 -> 56.7948 | C79: ='Monthly Haver'!D82 -> 55.4746 | D79: ='Monthly Haver'!E82 -> #N/A | E79: ='Monthly Haver'!G82 -> 54.9759 | F79: ='Monthly Haver'!H82 -> 52.1885 | G79: ='Monthly Haver'!I82 -> #N/A | H79: ='Monthly Haver'!J82 -> 57.8881 | I79: =GDS_Monthly!O196 -> 73.272901 | J79: =GDS_Monthly!D196 -> 85.935166 | K79: =GDS_Monthly!AH196 -> 678.14656 | L79: =GDS_Monthly!AI196 -> 639.29279 | M79: =GDS_Monthly!N196 -> 6.3047833 | N79: =GDS_Monthly!C196 -> 111.89891 | O79: =GDS_Monthly!F196 -> 3.6471275 | P79: =GDS_Monthly!G196 -> 3.4218761 | Q79: =GDS_Monthly!T196 -> 87.084415 | R79: =GDS_Monthly!V196 -> 90.44654 | S79: =GDS_Monthly!W196 -> 76.867304 | T79: =GDS_Monthly!X196 -> 81.884274 | U79: =GDS_Monthly!AA196 -> 70.783974 | V79: =GDS_Monthly!AC196 -> 131.8127 | W79: =GDS_Monthly!AE196 -> 119.0815 | X79: =GDS_Monthly!AF196 -> 85.86972 | Y79: =OECD!B79 -> 100.0135 | Z79: =OECD!C79 -> 109.08 | AA79: ='Monthly Haver'!K82 -> 106.20629 | AB79: ='Monthly Haver'!L82 -> 2746 | AC79: =Quarterly!B27 -> 99.84 | AD79: =Quarterly!C27 -> 99.48 | AE79: =Quarterly!D27 -> 89.931892
