Workbook
Name _DLX1.USE: #REF!
Name _DLX2.USE: 'Monthly Haver'!$1:$4
Name _DLX3.USE: 'Quarterly Haver'!$A$1:$W$3

Sheet GDS_Monthly
A1: EcDatabase | B1: ID:GDS_LIVE | C1: ID:GDS_LIVE | D1: ID:GDS_LIVE | E1: ID:GDS_LIVE | F1: ID:GDS_LIVE | G1: ID:GDS_LIVE | H1: ID:GDS_LIVE | I1: ID:GDS_LIVE | J1: ID:GDS_LIVE | K1: ID:GDS_LIVE | L1: ID:GDS_LIVE | M1: ID:GDS_LIVE | N1: ID:GDS_LIVE | O1: ID:GDS_LIVE | P1: ID:GDS_LIVE | Q1: ID:GDS_LIVE | R1: ID:GDS_LIVE | S1: ID:GDS_LIVE | T1: ID:GDS_LIVE | U1: ID:GDS_LIVE | V1: ID:GDS_LIVE | W1: ID:GDS_LIVE | X1: ID:GDS_LIVE | Y1: ID:GDS_LIVE | Z1: ID:GDS_LIVE | AA1: ID:GDS_LIVE | AB1: ID:GDS_LIVE | AC1: ID:GDS_LIVE | AD1: ID:GDS_LIVE | AE1: ID:GDS_LIVE | AF1: ID:GDS_LIVE | AG1: ID:GDS_LIVE | AH1: ID:GDS_LIVE | AI1: ID:GDS_LIVE
A2: Series_code | B2: 001ACC_PPPWGT.M | C2: 001ACC.M | D2: 001AIP.M | E2: 001AIP_GDPWGT.M | F2: 001FIGB.M | G2: 001FIPR.M | H2: 001FISI.M | I2: 001FMB.M | J2: 001FMN.M | K2: 001FMSCID.M | L2: 001FMSCIL.M | M2: 001LE.M | N2: 001LUR.M | O2: 001NRS.M | P2: 001PALLFNFW.M | Q2: 001PBEVEW.M | R2: 001PCOALW.M | S2: 001PCPI.M | T2: 001PCPI_GDPWGT.M | U2: 001PCPIX.M | V2: 001.M | W2: 001PFOODW.M | X2: 001PMETAW.M | Y2: 001PMI.M | Z2: 001PMI_PPPWGT.M | AA2: 001PNFUELW.M | AB2: 001PNGASW.M | AC2: 001PNRGW.M | AD2: 001POILAPSP.M | AE2: 001POILAPSPW.M | AF2: 001PRAWMW.M | AG2: 001TG.M | AH2: 001TMG.M | AI2: 001TXG.M
A3: Country | B3: World | C3: World | D3: World | E3: World | F3: World | G3: World | H3: World | I3: World | J3: World | K3: World | L3: World | M3: World | N3: World | O3: World | P3: World | Q3: World | R3: World | S3: World | T3: World | U3: World | V3: World | W3: World | X3: World | Y3: World | Z3: World | AA3: World | AB3: World | AC3: World | AD3: World | AE3: World | AF3: World | AG3: World | AH3: World | AI3: World
A4: Country.Name | B4: World | C4: World | D4: World | E4: World | F4: World | G4: World | H4: World | I4: World | J4: World | K4: World | L4: World | M4: World | N4: World | O4: World | P4: World | Q4: World | R4: World | S4: World | T4: World | U4: World | V4: World | W4: World | X4: World | Y4: World | Z4: World | AA4: World | AB4: World | AC4: World | AD4: World | AE4: World | AF4: World | AG4: World | AH4: World | AI4: World
A5: Indicator | B5: ACC_PPPWGT | C5: ACC | D5: AIP | E5: AIP_GDPWGT | F5: FIGB | G5: FIPR | H5: FISI | I5: FMB | J5: FMN | K5: FMSCID | L5: FMSCIL | M5: LE | N5: LUR | O5: NRS | P5: PALLFNFW | Q5: PBEVEW | R5: PCOALW | S5: PCPI | T5: PCPI_GDPWGT | U5: PCPIX | V5: PCPIX_GDPWGT | W5: PFOODW | X5: PMETAW | Y5: PMI | Z5: PMI_PPPWGT | AA5: PNFUELW | AB5: PNGASW | AC5: PNRGW | AD5: POILAPSP | AE5: POILAPSPW | AF5: PRAWMW | AG5: TG | AH5: TMG | AI5: TXG
A6: Indicator.Code | B6: ACC_PPPWGT | C6: ACC | D6: AIP | E6: AIP_GDPWGT | F6: FIGB | G6: FIPR | H6: FISI | I6: FMB | J6: FMN | K6: FMSCID | L6: FMSCIL | M6: LE | N6: LUR | O6: NRS | P6: PALLFNFW | Q6: PBEVEW | R6: PCOALW | S6: PCPI | T6: PCPI_GDPWGT | U6: PCPIX | V6: PCPIX_GDPWGT | W6: PFOODW | X6: PMETAW | Y6: PMI | Z6: PMI_PPPWGT | AA6: PNFUELW | AB6: PNGASW | AC6: PNRGW | AD6: POILAPSP | AE6: POILAPSPW | AF6: PRAWMW | AG6: TG | AH6: TMG | AI6: TXG
A7: Indicator.Descriptor | B7: Consumer confidence, PPP weighted | C7: Consumer confidence | D7: Industrial production | E7: Industrial production, MER weighted | F7: Long-term interest rate | G7: Policy-related interest rate | H7: Benchmark stock market index | I7: Broad money | J7: Narrow money | K7: Morgan Stanley MSCI stock price index in US dollars | L7: Morgan Stanley MSCI stock price index in national currency | M7: Employment | N7: Unemployment rate | O7: Retail sales | P7: Commodity price: all primary commodities | Q7: Commodity price: beverage | R7: Commodity price: coal | S7: Consumer price index | T7: Consumer price index, MER weighted | U7: Core consumer price index | V7: Core consumer price index, GDP weighted | W7: Commodity price: food | X7: Commodity price: metals | Y7: Manufacturing PMI | Z7: Manufacturing PMI, PPP weighted | AA7: Commodity price: non-fuel primary commodities | AB7: Commodity price: natural gas | AC7: Commodity price: energy | AD7: Commodity price: petroleum, US dollar per barrel | AE7: Commodity price: petroleum | AF7: Commodity price: raw materials | AG7: Merchandise trade balance | AH7: Merchandise imports | AI7: Merchandise exports
A8: Frequency | B8: Monthly | C8: Monthly | D8: Monthly | E8: Monthly | F8: Monthly | G8: Monthly | H8: Monthly | I8: Monthly | J8: Monthly | K8: Monthly | L8: Monthly | M8: Monthly | N8: Monthly | O8: Monthly | P8: Monthly | Q8: Monthly | R8: Monthly | S8: Monthly | T8: Monthly | U8: Monthly | V8: Monthly | W8: Monthly | X8: Monthly | Y8: Monthly | Z8: Monthly | AA8: Monthly | AB8: Monthly | AC8: Monthly | AD8: Monthly | AE8: Monthly | AF8: Monthly | AG8: Monthly | AH8: Monthly | AI8: Monthly
A9: Scale | B9: Units | C9: Units | D9: Units | E9: Units | F9: Units | G9: Units | H9: Units | I9: Units | J9: Units | K9: Units | L9: Units | M9: Units | N9: Units | O9: Units | P9: Units | Q9: Units | R9: Units | S9: Units | T9: Units | U9: Units | V9: Units | W9: Units | X9: Units | Y9: Units | Z9: Units | AA9: Units | AB9: Units | AC9: Units | AD9: Units | AE9: Units | AF9: Units | AG9: Billions | AH9: Billions | AI9: Billions
A10: Display_scale | B10: Units | C10: Units | D10: Units | E10: Units | F10: Units | G10: Units | H10: Units | I10: Units | J10: Units | K10: Units | L10: Units | M10: Units | N10: Units | O10: Units | P10: Units | Q10: Units | R10: Units | S10: Units | T10: Units | U10: Units | V10: Units | W10: Units | X10: Units | Y10: Units | Z10: Units | AA10: Units | AB10: Units | AC10: Units | AD10: Units | AE10: Units | AF10: Units | AG10: Billions | AH10: Billions | AI10: Billions
A11: 1990M1 | B11: 114.26463 | C11: 123.43022 | D11: 49.373068 | E11: 63.263084 | F11: 8.323664 | G11: 12.046458 | H11: 23.792103 | I11: 9.7663488 | J11: 10.911992 | K11: 27.282369 | L11: 17.279113 | M11: 81.080056 | N11: 3.3688556 | Q11: 49.20388 | R11: 51.172528 | S11: 11.636356 | T11: 30.225858 | U11: 47.247042 | V11: 57.862272 | AD11: 20.59 | AF11: 72.855085 | AG11: -5.0335787 | AH11: 196.38481 | AI11: 191.35123
A12: 1990M2 | B12: 114.33734 | C12: 123.48367 | D12: 49.582408 | E12: 63.587981 | F12: 8.5701345 | G12: 12.811761 | H12: 23.474586 | I12: 9.9135879 | J12: 10.992793 | K12: 26.764041 | L12: 17.859719 | M12: 81.703794 | N12: 3.3654726 | Q12: 49.947777 | R12: 51.172528 | S12: 11.771227 | T12: 30.521308 | U12: 47.441222 | V12: 58.101556 | AD12: 19.68 | AF12: 73.449658 | AG12: -2.9189287 | AH12: 193.68674 | AI12: 190.76781
A13: 1990M3 | B13: 115.12952 | C13: 124.95586 | D13: 49.87727 | E13: 64.179296 | F13: 8.8640729 | G13: 13.737382 | H13: 23.048825 | I13: 10.002343 | J13: 11.147585 | K13: 25.138839 | L13: 17.108852 | M13: 81.95714 | N13: 3.3468002 | Q13: 54.434712 | R13: 51.172528 | S13: 12.444696 | T13: 31.733288 | U13: 47.662526 | V13: 58.377687 | AD13: 18.12 | AF13: 74.172077 | AG13: -4.3576504 | AH13: 195.41389 | AI13: 191.05624
A14: 1990M4 | B14: 114.22148 | C14: 123.21768 | D14: 49.262783 | E14: 63.606555 | F14: 9.0542255 | G14: 10.216768 | H14: 22.498329 | I14: 10.139628 | J14: 11.298593 | K14: 25.177875 | L14: 17.192593 | M14: 82.357685 | N14: 3.3997466 | Q14: 56.292064 | R14: 51.172528 | S14: 12.545076 | T14: 31.929521 | U14: 47.86742 | V14: 58.603466 | AD14: 16.32 | AF14: 76.022077 | AG14: -4.8716052 | AH14: 192.9747 | AI14: 188.10309
A15: 1990M5 | B15: 114.08956 | C15: 123.03385 | D15: 49.879239 | E15: 64.189096 | F15: 8.8861221 | G15: 9.8641319 | H15: 24.678425 | I15: 10.198687 | J15: 11.362863 | K15: 27.69119 | L15: 18.723617 | M15: 82.477082 | N15: 3.4192908 | Q15: 55.920823 | R15: 54.120417 | S15: 12.657056 | T15: 32.167761 | U15: 48.054379 | V15: 58.801065 | AD15: 16.21 | AF15: 75.418959 | AG15: -5.4577123 | AH15: 200.14548 | AI15: 194.68777
A16: 1990M6 | B16: 112.86521 | C16: 120.87103 | D16: 49.93695 | E16: 64.411191 | F16: 8.6788407 | G16: 10.142622 | H16: 24.468707 | I16: 10.290694 | J16: 11.463502 | K16: 27.335213 | L16: 18.434519 | M16: 82.556306 | N16: 3.4074475 | Q16: 53.061015 | R16: 55.284677 | S16: 12.772721 | T16: 32.423467 | U16: 48.291541 | V16: 59.067568 | AD16: 14.93 | AF16: 75.563455 | AG16: -1.0163899 | AH16: 193.96258 | AI16: 192.94619
A17: 1990M7 | B17: 112.78358 | C17: 120.74384 | D17: 50.030674 | E17: 64.415656 | F17: 8.7403436 | G17: 9.9579222 | H17: 24.696283 | I17: 10.373357 | J17: 11.502069 | K17: 27.746394 | L17: 18.523374 | M17: 82.713743 | N17: 3.4275145 | Q17: 52.830834 | R17: 55.284677 | S17: 13.155994 | T17: 33.119466 | U17: 48.503311 | V17: 59.337706 | AD17: 16.81 | AF17: 76.236284 | AG17: -4.568308 | AH17: 199.85918 | AI17: 195.29087
A18: 1990M8 | B18: 108.17004 | C18: 112.68192 | D18: 50.269507 | E18: 64.700889 | F18: 9.1118153 | G18: 9.7714184 | H18: 22.176611 | I18: 10.468343 | J18: 11.603811 | K18: 25.110873 | L18: 16.692975 | M18: 82.693623 | N18: 3.4594441 | Q18: 54.507742 | R18: 55.284677 | S18: 13.446916 | T18: 33.797205 | U18: 48.757985 | V18: 59.652243 | AD18: 26.54 | AF18: 73.868209 | AG18: -7.548359 | AH18: 209.49247 | AI18: 202.42481
A19: 1990M9 | B19: 107.89813 | C19: 113.02926 | D19: 50.2996 | E19: 64.567872 | F19: 9.3303678 | G19: 10.466012 | H19: 20.261359 | I19: 10.560172 | J19: 11.670862 | K19: 22.814 | L19: 15.094139 | M19: 82.643044 | N19: 3.5081315 | Q19: 56.439606 | R19: 55.284677 | S19: 13.772519 | T19: 34.394458 | U19: 48.977705 | V19: 59.874835 | AD19: 33.62 | AF19: 73.204601 | AG19: -4.7183941 | AH19: 208.23271 | AI19: 203.97791
A20: 1990M10 | B20: 101.69647 | C20: 102.17398 | D20: 50.39912 | E20: 64.700691 | F20: 9.1290741 | G20: 9.9007028 | H20: 21.317148 | I20: 10.626389 | J20: 11.728933 | K20: 24.122569 | L20: 15.740032 | M20: 82.501739 | N20: 3.5357895 | Q20: 56.63649 | R20: 55.284677 | S20: 13.921279 | T20: 34.729373 | U20: 49.206028 | V20: 60.094099 | AD20: 34.85 | AF20: 73.155127 | AG20: -11.439028 | AH20: 224.80416 | AI20: 213.84453
A21: 1990M11 | B21: 101.59472 | C21: 101.76927 | D21: 50.020814 | E21: 64.26483 | F21: 8.75802 | G21: 9.411279 | H21: 21.287443 | I21: 10.674368 | J21: 11.82289 | K21: 24.143126 | L21: 16.022611 | M21: 82.591849 | N21: 3.575767 | Q21: 55.621551 | R21: 55.284677 | S21: 14.182217 | T21: 35.198282 | U21: 49.409033 | V21: 60.296318 | AD21: 31.54 | AF21: 73.029421 | AG21: -12.740631 | AH21: 226.21262 | AI21: 213.90199
A22: 1990M12 | B22: 101.75224 | C22: 101.9674 | D22: 49.892126 | E22: 63.915307 | F22: 8.3662984 | G22: 9.1426827 | H22: 21.933351 | I22: 10.747179 | J22: 11.945251 | K22: 24.645852 | L22: 16.53637 | M22: 82.673156 | N22: 3.5904697 | Q22: 55.882156 | R22: 55.284677 | S22: 14.403888 | T22: 35.593541 | U22: 49.636155 | V22: 60.548269 | AD22: 26.61 | AF22: 72.658165 | AG22: -6.705504 | AH22: 214.48589 | AI22: 208.21439
A23: 1991M1 | B23: 99.904302 | C23: 98.963857 | D23: 50.747193 | E23: 63.835284 | F23: 8.3136686 | G23: 9.412147 | H23: 22.191026 | I23: 10.821023 | J23: 12.032754 | K23: 25.858524 | L23: 17.532666 | M23: 82.844274 | N23: 3.8673046 | Q23: 54.152241 | R23: 55.284677 | S23: 14.621475 | T23: 36.050952 | U23: 49.960967 | V23: 60.957015 | AD23: 22.81 | AE23: 51.895164 | AF23: 71.245906 | AG23: -10.246718 | AH23: 225.44573 | AI23: 215.60341
A24: 1991M2 | B24: 100.96674 | C24: 100.87018 | D24: 50.52348 | E24: 63.68767 | F24: 8.0397546 | G24: 9.6127573 | H24: 24.146844 | I24: 10.89197 | J24: 12.184811 | K24: 28.234565 | L24: 19.275695 | M24: 82.844331 | N24: 3.9295921 | Q24: 52.871024 | R24: 55.284677 | S24: 14.869108 | T24: 36.516064 | U24: 50.214283 | V24: 61.243507 | AD24: 18.53 | AE24: 41.623317 | AF24: 72.488907 | AG24: -8.3386206 | AH24: 218.87019 | AI24: 210.87937
A25: 1991M3 | B25: 107.05537 | C25: 111.27839 | D25: 50.333723 | E25: 63.383655 | F25: 8.239066 | G25: 9.2125234 | H25: 24.4134 | I25: 10.957662 | J25: 12.265427 | K25: 28.011022 | L25: 19.683323 | M25: 82.828955 | N25: 4.0170687 | Q25: 53.016481 | R25: 52.242706 | S25: 15.044756 | T25: 36.828993 | U25: 50.390576 | V25: 61.430117 | AD25: 18.21 | AE25: 42.713082 | AF25: 71.063991 | AG25: -4.6778698 | AH25: 209.88529 | AI25: 205.57472
A26: 1991M4 | B26: 106.54678 | C26: 110.55536 | D26: 50.281803 | E26: 63.482142 | F26: 8.1915197 | G26: 7.9690305 | H26: 24.395545 | I26: 11.031071 | J26: 12.351706 | K26: 28.233458 | L26: 19.833218 | M26: 82.881747 | N26: 4.0339042 | Q26: 52.103358 | R26: 52.242706 | S26: 15.231675 | T26: 37.176733 | U26: 50.531865 | V26: 61.556683 | AD26: 18.49 | AE26: 44.273197 | AF26: 71.897367 | AG26: -5.1484774 | AH26: 206.17964 | AI26: 201.36416
A27: 1991M5 | B27: 105.7765 | C27: 109.00304 | D27: 50.495472 | E27: 63.986469 | F27: 8.1932169 | G27: 7.7954514 | H27: 25.101678 | I27: 11.112941 | J27: 12.505604 | K27: 29.219699 | L27: 20.668098 | M27: 82.821498 | N27: 4.0774253 | Q27: 48.774236 | R27: 52.242706 | S27: 15.342237 | T27: 37.4003 | U27: 50.793609 | V27: 61.807601 | AD27: 18.72 | AE27: 45.108066 | AF27: 72.823651 | AG27: -5.3268246 | AH27: 210.05599 | AI27: 205.10467
A28: 1991M6 | B28: 106.11954 | C28: 109.8483 | D28: 50.685422 | E28: 63.773231 | F28: 8.3817849 | G28: 7.8349017 | H28: 23.848407 | I28: 11.177839 | J28: 12.632306 | K28: 27.64234 | L28: 19.754628 | M28: 82.857766 | N28: 4.0231949 | Q28: 47.46047 | R28: 52.242706 | S28: 15.519202 | T28: 37.710648 | U28: 51.020038 | V28: 62.041292 | AD28: 17.78 | AE28: 43.608103 | AF28: 74.039224 | AG28: -2.9471217 | AH28: 204.5661 | AI28: 201.92088
A29: 1991M7 | B29: 105.86967 | C29: 109.75141 | D29: 50.876631 | E29: 64.328114 | F29: 8.3331844 | G29: 7.6497919 | H29: 24.956447 | I29: 11.23252 | J29: 12.725871 | K29: 28.951373 | L29: 20.669017 | M29: 82.770792 | N29: 3.9273901 | Q29: 45.930383 | R29: 52.242706 | S29: 15.759571 | T29: 38.088271 | U29: 51.26753 | V29: 62.273606 | AD29: 19.02 | AE29: 46.598285 | AF29: 72.267005 | AG29: -6.6242043 | AH29: 211.17367 | AI29: 204.87297
A30: 1991M8 | B30: 105.42458 | C30: 109.1287 | D30: 50.693852 | E30: 64.061363 | F30: 8.0410372 | G30: 7.5331555 | H30: 24.948298 | I30: 11.268009 | J30: 12.861592 | K30: 29.007244 | L30: 20.777752 | M30: 82.854299 | N30: 3.975763 | Q30: 47.387427 | R30: 52.242706 | S30: 15.963186 | T30: 38.454865 | U30: 51.441949 | V30: 62.470308 | AD30: 19.3 | AE30: 46.77816 | AF30: 71.029708 | AG30: -4.4024016 | AH30: 210.95699 | AI30: 206.86609
A31: 1991M9 | B31: 104.86761 | C31: 107.8504 | D31: 50.810871 | E31: 64.320508 | F31: 7.7846416 | G31: 7.1938334 | H31: 25.252212 | I31: 11.32418 | J31: 12.968305 | K31: 29.224076 | L31: 20.829253 | M31: 82.981104 | N31: 4.0146664 | Q31: 50.699127 | R31: 52.242706 | S31: 16.12185 | T31: 38.725055 | U31: 51.644707 | V31: 62.718693 | AD31: 19.95 | AE31: 47.725344 | AF31: 71.490928 | AG31: -4.6671969 | AH31: 213.88295 | AI31: 209.49836
A32: 1991M10 | B32: 101.48308 | C32: 102.00356 | D32: 51.015106 | E32: 64.395463 | F32: 7.6430148 | G32: 7.0513179 | H32: 26.020507 | I32: 11.393074 | J32: 13.229762 | K32: 29.75936 | L32: 21.348462 | M32: 83.08598 | N32: 4.0199583 | Q32: 49.690825 | R32: 52.242706 | S32: 16.437139 | T32: 39.272224 | U32: 51.854683 | V32: 62.897651 | AD32: 21.56 | AE32: 51.2623 | AF32: 70.083241 | AG32: -4.0199373 | AH32: 217.42571 | AI32: 213.70088
A33: 1991M11 | B33: 99.500857 | C33: 98.517895 | D33: 51.002728 | E33: 64.332826 | F33: 7.5594833 | G33: 6.7887872 | H33: 24.637211 | I33: 11.460838 | J33: 13.409447 | K33: 28.425931 | L33: 20.462706 | M33: 83.070715 | N33: 4.0453083 | Q33: 51.331064 | R33: 52.242706 | S33: 16.717709 | T33: 39.799074 | U33: 52.063073 | V33: 63.12383 | AD33: 20.41 | AE33: 47.715173 | AF33: 68.819061 | AG33: -1.1984588 | AH33: 220.2292 | AI33: 219.36324
A34: 1991M12 | B34: 99.224558 | C34: 98.246289 | D34: 50.610352 | E34: 63.833969 | F34: 7.3023264 | G34: 6.4824864 | H34: 26.006905 | I34: 11.536941 | J34: 13.569935 | K34: 30.888157 | L34: 22.174654 | M34: 82.991285 | N34: 4.0665032 | Q34: 51.101844 | R34: 52.242706 | S34: 16.95425 | T34: 40.173664 | U34: 52.246397 | V34: 63.302154 | AD34: 17.63 | AE34: 40.52036 | AF34: 68.755252 | AG34: -2.0864155 | AH34: 220.16971 | AI34: 218.5327
A35: 1992M1 | B35: 98.528361 | C35: 96.95769 | D35: 50.870273 | E35: 63.742584 | F35: 7.1715464 | G35: 6.1545573 | H35: 26.491494 | I35: 11.590866 | J35: 13.7764 | K35: 30.933791 | L35: 22.629282 | M35: 83.051439 | N35: 4.1345617 | P35: 50.254019 | Q35: 48.467677 | R35: 52.242706 | S35: 19.437947 | T35: 40.520456 | U35: 52.415968 | V35: 63.464959 | W35: 65.8159 | X35: 46.948673 | AA35: 53.878233 | AB35: 54.51602 | AC35: 45.011688 | AD35: 17.52 | AE35: 40.225371 | AF35: 67.201791 | AG35: -3.5624729 | AH35: 223.08563 | AI35: 219.76875
A36: 1992M2 | B36: 98.029969 | C36: 95.888164 | D36: 51.126879 | E36: 63.991257 | F36: 7.3549699 | G36: 6.1724543 | H36: 26.497097 | I36: 11.662883 | J36: 13.962783 | K36: 30.207302 | L36: 22.48542 | M36: 83.081817 | N36: 4.2768695 | P36: 50.247364 | Q36: 44.121634 | R36: 52.242706 | S36: 20.050797 | T36: 40.945017 | U36: 52.575926 | V36: 63.63192 | W36: 66.411709 | X36: 48.319412 | AA36: 54.31691 | AB36: 49.91186 | AC36: 44.36087 | AD36: 17.65 | AE36: 41.089686 | AF36: 68.202929 | AG36: -0.31315782 | AH36: 226.46113 | AI36: 226.49927
A37: 1992M3 | B37: 100.38045 | C37: 100.25818 | D37: 51.147522 | E37: 64.04875 | F37: 7.4888812 | G37: 6.1570527 | H37: 25.958013 | I37: 11.715211 | J37: 14.13337 | K37: 29.051796 | L37: 21.991082 | M37: 83.144534 | N37: 4.2960534 | P37: 50.273464 | Q37: 44.006519 | R37: 52.242706 | S37: 20.689405 | T37: 41.338497 | U37: 52.818345 | V37: 63.884856 | W37: 67.330671 | X37: 48.220121 | AA37: 54.596682 | AB37: 50.533712 | AC37: 44.020041 | AD37: 17.35 | AE37: 41.165326 | AF37: 68.573076 | AG37: -2.954955 | AH37: 222.47059 | AI37: 219.85003
A38: 1992M4 | B38: 102.70405 | C38: 104.46636 | D38: 51.208948 | E38: 64.279492 | F38: 7.4651584 | G38: 5.8096008 | H38: 25.885881 | I38: 11.757077 | J38: 14.268491 | K38: 29.218581 | L38: 22.264797 | M38: 83.216594 | N38: 4.2817709 | P38: 50.689243 | Q38: 42.97254 | R38: 52.242706 | S38: 21.259907 | T38: 41.745005 | U38: 52.983283 | V38: 64.0517 | W38: 64.459292 | X38: 48.628629 | AA38: 53.543374 | AB38: 51.972758 | AC38: 46.560816 | AD38: 18.65 | AE38: 44.087573 | AF38: 72.508877 | AG38: -4.1153961 | AH38: 227.16108 | AI38: 223.41298
A39: 1992M5 | B39: 104.46594 | C39: 107.65004 | D39: 50.954306 | E39: 63.853834 | F39: 7.3539937 | G39: 5.7414934 | H39: 26.284304 | I39: 11.794808 | J39: 14.416428 | K39: 30.004958 | L39: 22.671053 | M39: 83.254239 | N39: 4.3513274 | P39: 52.134939 | Q39: 40.89879 | R39: 52.242706 | S39: 21.868983 | T39: 42.214681 | U39: 53.180868 | V39: 64.247868 | W39: 66.748541 | X39: 48.605568 | AA39: 54.577398 | AB39: 54.754973 | AC39: 48.601984 | AD39: 19.52 | AE39: 45.566176 | AF39: 72.273732 | AG39: -2.7737231 | AH39: 226.48434 | AI39: 224.02552
A40: 1992M6 | B40: 104.58569 | C40: 107.73399 | D40: 51.08569 | E40: 64.30902 | F40: 7.2696369 | G40: 5.7284058 | H40: 24.939879 | I40: 11.832685 | J40: 14.501339 | K40: 28.653464 | L40: 21.56172 | M40: 83.279109 | N40: 4.2651362 | P40: 52.346674 | Q40: 39.672732 | R40: 50.690361 | S40: 22.518425 | T40: 42.620573 | U40: 53.338532 | V40: 64.417631 | W40: 63.74508 | X40: 48.725491 | AA40: 53.222498 | AB40: 55.870772 | AC40: 51.079817 | AD40: 20.88 | AE40: 47.918269 | AF40: 72.802168 | AG40: -6.9170601 | AH40: 236.15737 | AI40: 229.24031
A41: 1992M7 | B41: 101.56556 | C41: 102.18731 | D41: 51.167725 | E41: 64.632609 | F41: 6.9673886 | G41: 5.4070015 | H41: 24.910165 | I41: 11.879575 | J41: 14.641857 | K41: 28.905603 | L41: 21.901368 | M41: 83.305294 | N41: 4.2334123 | P41: 51.987545 | Q41: 41.552698 | R41: 49.138015 | S41: 23.075021 | T41: 42.997309 | U41: 53.516065 | V41: 64.578556 | W41: 62.348687 | X41: 50.821035 | AA41: 53.176006 | AB41: 58.465806 | AC41: 50.268468 | AD41: 20.18 | AE41: 45.305162 | AF41: 73.511163 | AG41: -5.2604489 | AH41: 241.81775 | AI41: 236.5573
A42: 1992M8 | B42: 100.96797 | C42: 101.1364 | D42: 50.846098 | E42: 63.992327 | F42: 6.7859375 | G42: 5.3135609 | H42: 25.113142 | I42: 11.932051 | J42: 14.795958 | K42: 29.448503 | L42: 22.172313 | M42: 83.347597 | N42: 4.2938507 | P42: 51.997661 | Q42: 41.845957 | R42: 49.138015 | S42: 23.595826 | T42: 43.417394 | U42: 53.701595 | V42: 64.739297 | W42: 63.561043 | X42: 50.472097 | AA42: 53.35017 | AB42: 61.642172 | AC42: 50.041292 | AD42: 19.62 | AE42: 43.653153 | AF42: 71.685422 | AG42: -3.2896562 | AH42: 238.48611 | AI42: 235.19646
A43: 1992M9 | B43: 100.44161 | C43: 100.30304 | D43: 51.31057 | E43: 64.868808 | F43: 6.6854317 | G43: 5.6248856 | H43: 25.058766 | I43: 11.991291 | J43: 14.983063 | K43: 29.108061 | L43: 22.248486 | M43: 83.371379 | N43: 4.2880537 | P43: 52.426452 | Q43: 42.138255 | R43: 49.138015 | S43: 24.216998 | T43: 43.923679 | U43: 53.828889 | V43: 64.836442 | W43: 63.337492 | X43: 49.130352 | AA43: 53.004068 | AB43: 64.058887 | AC43: 51.590944 | AD43: 20.19 | AE43: 44.889477 | AF43: 71.487238 | AG43: -3.0269589 | AH43: 241.45995 | AI43: 238.43299
A44: 1992M10 | B44: 99.66253 | C44: 99.054499 | D44: 51.391292 | E44: 64.742782 | F44: 6.7016489 | G44: 4.9369389 | H44: 24.905384 | I44: 12.070708 | J44: 15.252449 | K44: 28.561684 | L44: 22.493589 | M44: 83.396366 | N44: 4.284135 | P44: 51.918137 | Q44: 43.755518 | R44: 47.532749 | S44: 25.030254 | T44: 44.479548 | U44: 54.040638 | V44: 65.077451 | W44: 62.352722 | X44: 45.975917 | AA44: 52.027091 | AB44: 67.651787 | AC44: 51.760537 | AD44: 20.04 | AE44: 45.255909 | AF44: 71.836684 | AG44: -0.29990841 | AH44: 238.12141 | AI44: 237.8215
A45: 1992M11 | B45: 102.23492 | C45: 103.87323 | D45: 51.259439 | E45: 64.58721 | F45: 6.764898 | G45: 4.8523074 | H45: 25.597885 | I45: 12.116835 | J45: 15.367916 | K45: 29.026304 | L45: 23.316046 | M45: 83.451486 | N45: 4.3147571 | P45: 49.861055 | Q45: 46.204983 | R45: 45.927482 | S45: 25.723944 | T45: 44.940261 | U45: 54.250058 | V45: 65.251162 | W45: 59.574794 | X45: 43.914144 | AA45: 50.317349 | AB45: 65.666383 | AC45: 49.201037 | AD45: 18.9 | AE45: 44.149055 | AF45: 72.112969 | AG45: -2.9503938 | AH45: 230.94933 | AI45: 227.99893
A46: 1992M12 | B46: 105.31411 | C46: 109.65775 | D46: 51.086265 | E46: 64.585253 | F46: 6.7288757 | G46: 4.8833251 | H46: 25.639143 | I46: 12.164012 | J46: 15.497241 | K46: 29.418506 | L46: 23.8457 | M46: 83.462679 | N46: 4.2129669 | P46: 49.891888 | Q46: 49.844504 | R46: 45.927482 | S46: 26.451396 | T46: 45.422438 | U46: 54.366737 | V46: 65.415136 | W46: 61.765822 | X46: 44.786188 | AA46: 51.6877 | AB46: 64.524873 | AC46: 47.294292 | AD46: 17.93 | AE46: 41.831877 | AF46: 72.428042 | AG46: -6.235119 | AH46: 236.41298 | AI46: 230.17786
... A69: 1994M11 | B69: 110.7139 | C69: 112.32113 | D69: 56.956637 | E69: 71.212526 | F69: 7.8978763 | G69: 5.1570522 | H69: 33.039958 | I69: 28.341238 | J69: 28.153998 | K69: 38.88023 | L69: 35.693101 | M69: 85.070043 | N69: 5.0729819 | P69: 53.581798 | Q69: 106.58584 | R69: 47.288528 | S69: 48.252156 | T69: 62.937186 | U69: 59.041266 | V69: 69.34308 | W69: 63.450015 | X69: 56.158088 | AA69: 59.855395 | AB69: 54.331559 | AC69: 44.5072 | AD69: 17.2 | AE69: 37.907163 | AF69: 94.575507 | AG69: -3.0796019 | AH69: 298.93358 | AI69: 295.85397
A70: 1994M12 | B70: 111.36716 | C70: 112.89211 | D70: 57.565077 | E70: 71.904966 | F70: 7.8146516 | G70: 5.2570624 | H70: 33.337011 | I70: 28.492526 | J70: 28.186371 | K70: 38.557301 | L70: 35.748417 | M70: 85.144 | N70: 5.0149306 | O70: 39.488625 | P70: 54.610053 | Q70: 94.983662 | R70: 50.593143 | S70: 48.850307 | T70: 63.266464 | U70: 59.177368 | V70: 69.482906 | W70: 68.608014 | X70: 58.490422 | AA70: 62.504774 | AB70: 55.710089 | AC70: 43.190541 | AD70: 16.13 | AE70: 36.027207 | AF70: 98.501305 | AG70: -5.6165649 | AH70: 305.45266 | AI70: 299.8361
A71: 1995M1 | B71: 110.9038 | C71: 112.58696 | D71: 57.474733 | E71: 71.457009 | F71: 7.839783 | G71: 6.1327358 | H71: 32.413486 | I71: 28.536322 | J71: 28.034227 | K71: 37.174584 | L71: 34.496025 | M71: 85.075251 | N71: 5.4367978 | O71: 39.415613 | P71: 55.249719 | Q71: 97.049685 | R71: 52.85894 | S71: 49.404435 | T71: 63.618518 | U71: 59.36809 | V71: 69.712831 | W71: 66.717331 | X71: 62.257141 | AA71: 62.768986 | AB71: 54.838874 | AC71: 44.373292 | AD71: 16.88 | AE71: 37.336547 | AF71: 101.29931 | AG71: 3.1833631 | AH71: 299.53428 | AI71: 302.71764
A72: 1995M2 | B72: 110.38772 | C72: 111.98677 | D72: 57.515648 | E72: 71.655345 | F72: 7.6446537 | G72: 6.3638438 | H72: 32.171377 | I72: 28.696035 | J72: 28.240754 | K72: 37.069574 | L72: 34.231581 | M72: 85.153995 | N72: 5.4072631 | O72: 39.547834 | P72: 55.627552 | Q72: 97.775147 | R72: 53.603752 | S72: 49.899428 | T72: 63.893935 | U72: 59.660281 | V72: 69.977294 | W72: 67.498901 | X72: 58.108061 | AA72: 62.636419 | AB72: 56.037269 | AC72: 45.489406 | AD72: 17.44 | AE72: 38.272142 | AF72: 104.03088 | AG72: 4.107407 | AH72: 309.05593 | AI72: 313.16334
A73: 1995M3 | B73: 110.49892 | C73: 112.12917 | D73: 57.347459 | E73: 71.728708 | F73: 7.5377649 | G73: 8.4190572 | H73: 32.569764 | I73: 28.802973 | J73: 28.271585 | K73: 38.667632 | L73: 34.74634 | M73: 85.20556 | N73: 5.4150874 | O73: 39.877016 | P73: 56.227397 | Q73: 103.37787 | R73: 54.332884 | S73: 50.44687 | T73: 64.194303 | U73: 59.975764 | V73: 70.201765 | W73: 68.659738 | X73: 56.360972 | AA73: 63.508448 | AB73: 57.181878 | AC73: 45.695542 | AD73: 17.35 | AE73: 36.64229 | AF73: 108.30471 | AG73: 1.3783587 | AH73: 320.48249 | AI73: 321.86085
A74: 1995M4 | B74: 111.52694 | C74: 113.29582 | D74: 57.899506 | E74: 72.117436 | F74: 7.3049387 | G74: 8.2964217 | H74: 33.727903 | I74: 28.970466 | J74: 28.428161 | K74: 40.002382 | L74: 35.575472 | M74: 85.258504 | N74: 5.4462743 | O74: 39.747963 | P74: 56.753436 | Q74: 101.54617 | R74: 53.635113 | S74: 51.027784 | T74: 64.5375 | U74: 60.375457 | V74: 70.516042 | W74: 66.095772 | X74: 56.665862 | AA74: 62.564066 | AB74: 59.470229 | AC74: 48.34851 | AD74: 18.77 | AE74: 38.60433 | AF74: 109.41539 | AG74: 0.2266121 | AH74: 323.02044 | AI74: 323.24705
A75: 1995M5 | B75: 110.91756 | C75: 112.5856 | D75: 57.759314 | E75: 71.911927 | F75: 6.9200554 | G75: 7.4143552 | H75: 34.137369 | I75: 29.215053 | J75: 28.581314 | K75: 40.578073 | L75: 36.252113 | M75: 85.28853 | N75: 5.4305379 | O75: 40.330191 | P75: 55.984419 | Q75: 99.308714 | R75: 54.826577 | S75: 51.58383 | T75: 64.830805 | U75: 60.756572 | V75: 70.762361 | W75: 65.280025 | X75: 54.93148 | AA75: 61.568632 | AB75: 59.408658 | AC75: 47.906999 | AD75: 18.43 | AE75: 38.350316 | AF75: 109.40255 | AG75: -3.8338896 | AH75: 330.94826 | AI75: 327.11437
A76: 1995M6 | B76: 109.14279 | C76: 110.63532 | D76: 58.028911 | E76: 72.071152 | F76: 6.6708559 | G76: 7.0818613 | H76: 33.879404 | I76: 29.466038 | J76: 28.671096 | K76: 40.699816 | L76: 36.401407 | M76: 85.362091 | N76: 5.4638962 | O76: 40.651286 | P76: 55.322192 | Q76: 91.230409 | R76: 56.168102 | S76: 52.129563 | T76: 65.169914 | U76: 61.100714 | V76: 71.036553 | W76: 66.257765 | X76: 57.080115 | AA76: 61.632772 | AB76: 59.630732 | AC76: 46.1941 | AD76: 17.33 | AE76: 35.945169 | AF76: 105.08598 | AG76: -3.344116 | AH76: 332.83312 | AI76: 329.489
A77: 1995M7 | B77: 110.555 | C77: 112.35741 | D77: 57.985485 | E77: 71.873657 | F77: 6.6930105 | G77: 6.600293 | H77: 36.019982 | I77: 29.669956 | J77: 28.838711 | K77: 42.550531 | L77: 38.358827 | M77: 85.462837 | N77: 5.4885637 | O77: 40.759688 | P77: 54.811747 | Q77: 85.907981 | R77: 57.345846 | S77: 52.594127 | T77: 65.388823 | U77: 61.38312 | V77: 71.251063 | W77: 69.14212 | X77: 59.434986 | AA77: 62.604648 | AB77: 56.584449 | AC77: 43.539517 | AD77: 16.06 | AE77: 33.429677 | AF77: 99.109049 | AG77: -5.7647056 | AH77: 329.44199 | AI77: 323.67728
A78: 1995M8 | B78: 110.66807 | C78: 112.56354 | D78: 58.209261 | E78: 72.228388 | F78: 6.726165 | G78: 6.4414957 | H78: 36.370712 | I78: 29.913572 | J78: 29.089117 | K78: 41.621095 | L78: 38.774766 | M78: 85.493819 | N78: 5.5119176 | O78: 40.794863 | P78: 55.035556 | Q78: 91.565362 | R78: 56.875282 | S78: 52.989185 | T78: 65.609248 | U78: 61.628306 | V78: 71.478601 | W78: 68.893005 | X78: 59.841723 | AA78: 62.502541 | AB78: 56.564252 | AC78: 44.234755 | AD78: 16.49 | AE78: 35.389869 | AF78: 94.680057 | AG78: -3.7470304 | AH78: 331.29169 | AI78: 327.54466
A79: 1995M9 | B79: 109.41103 | C79: 111.13752 | D79: 58.264276 | E79: 72.25723 | F79: 6.5035452 | G79: 6.2547846 | H79: 36.778788 | I79: 30.124828 | J79: 29.226492 | K79: 42.487474 | L79: 39.575076 | M79: 85.550291 | N79: 5.5316574 | O79: 41.013484 | P79: 55.088734 | Q79: 83.065101 | R79: 57.089474 | S79: 53.432556 | T79: 65.915282 | U79: 61.945684 | V79: 71.743845 | W79: 69.282698 | X79: 57.060503 | AA79: 62.079171 | AB79: 57.975905 | AC79: 44.977245 | AD79: 16.77 | AE79: 36.631648 | AF79: 95.414814 | AG79: -0.1286494 | AH79: 330.09236 | AI79: 329.96371
A80: 1995M10 | B80: 109.15882 | C80: 110.85589 | D80: 58.076945 | E80: 72.066759 | F80: 6.4594723 | G80: 6.4736416 | H80: 36.202352 | I80: 30.310817 | J80: 29.310226 | K80: 41.372957 | L80: 38.981293 | M80: 85.585554 | N80: 5.6014229 | O80: 40.640587 | P80: 55.007793 | Q80: 81.48656 | R80: 56.978301 | S80: 53.766461 | T80: 66.068576 | U80: 62.189655 | V80: 71.913563 | W80: 70.553608 | X80: 55.276278 | AA80: 62.292011 | AB80: 60.55189 | AC80: 44.47136 | AD80: 16.18 | AE80: 35.006635 | AF80: 93.782378 | AG80: -5.0094898 | AH80: 333.34947 | AI80: 328.33999
A81: 1995M11 | B81: 110.38652 | C81: 112.25485 | D81: 58.613988 | E81: 72.603683 | F81: 6.299066 | G81: 6.8780033 | H81: 37.516157 | I81: 30.561888 | J81: 29.463674 | K81: 42.333187 | L81: 40.165441 | M81: 85.626184 | N81: 5.6031646 | O81: 41.193389 | P81: 55.877564 | Q81: 80.893213 | R81: 56.242113 | S81: 54.079366 | T81: 66.285528 | U81: 62.4288 | V81: 72.128645 | W81: 70.063595 | X81: 57.043953 | AA81: 62.825797 | AB81: 62.477886 | AC81: 45.827123 | AD81: 16.82 | AE81: 36.468003 | AF81: 98.199841 | AG81: -1.6660195 | AH81: 335.68824 | AI81: 334.02222
... A99: 1997M5 | B99: 116.65241 | C99: 118.53078 | D99: 63.249884 | E99: 77.720346 | F99: 5.8901545 | G99: 5.4554555 | H99: 54.641729 | I99: 34.49347 | J99: 33.087327 | K99: 53.516913 | L99: 55.041454 | M99: 87.459564 | N99: 5.603573 | O99: 43.088698 | P99: 57.38913 | Q99: 106.21394 | R99: 50.740537 | S99: 59.639789 | T99: 70.231797 | U99: 67.840225 | V99: 75.844742 | W99: 70.648824 | X99: 53.310893 | AA99: 61.794906 | AB99: 67.261971 | AC99: 51.016289 | AD99: 19.47 | AE99: 45.592799 | AF99: 91.318345 | AG99: 0.1641339 | AH99: 357.05975 | AI99: 357.22388
A100: 1997M6 | B100: 117.06128 | C100: 119.06034 | D100: 63.735268 | E100: 78.198897 | F100: 5.7429757 | G100: 5.4764062 | H100: 57.485343 | I100: 34.768736 | J100: 33.39039 | K100: 56.575687 | L100: 58.348607 | M100: 87.521706 | N100: 5.6473721 | O100: 43.33646 | P100: 55.020963 | Q100: 95.184022 | R100: 49.668948 | S100: 59.929121 | T100: 70.450109 | U100: 68.086007 | V100: 76.003909 | W100: 67.646427 | X100: 52.80315 | Y100: 52.864943 | Z100: 52.801686 | AA100: 59.588149 | AB100: 66.766427 | AC100: 48.414645 | AD100: 18.02 | AE100: 42.044627 | AF100: 89.529531 | AG100: -1.295222 | AH100: 363.041 | AI100: 361.74578
A101: 1997M7 | B101: 116.28503 | C101: 118.23049 | D101: 64.191313 | E101: 78.76983 | F101: 5.5032444 | G101: 5.4620727 | H101: 60.905418 | I101: 35.019885 | J101: 33.553044 | K101: 59.010064 | L101: 62.402243 | M101: 87.599092 | N101: 5.6158251 | O101: 43.51468 | P101: 54.453574 | Q101: 87.48614 | R101: 49.241739 | S101: 60.205367 | T101: 70.644497 | U101: 68.3012 | V101: 76.14849 | W101: 67.079398 | X101: 52.086145 | Y101: 53.843079 | Z101: 53.733243 | AA101: 58.431728 | AB101: 64.664573 | AC101: 48.699276 | AD101: 18.45 | AE101: 43.433738 | AF101: 88.822162 | AG101: -0.5548508 | AH101: 367.41948 | AI101: 366.86463
A102: 1997M8 | B102: 116.47195 | C102: 118.58424 | D102: 64.295679 | E102: 78.888031 | F102: 5.5310609 | G102: 5.5220032 | H102: 55.896918 | I102: 35.24647 | J102: 33.89436 | K102: 54.728206 | L102: 57.926035 | M102: 87.672103 | N102: 5.5916167 | O102: 43.489193 | P102: 54.722499 | Q102: 85.497512 | R102: 50.43242 | S102: 60.483774 | T102: 70.841325 | U102: 68.520197 | V102: 76.280151 | W102: 66.6465 | X102: 52.144268 | Y102: 53.033917 | Z102: 52.938372 | AA102: 57.894071 | AB102: 67.936858 | AC102: 50.134901 | AD102: 18.79 | AE102: 45.009411 | AF102: 85.253824 | AG102: -0.7492208 | AH102: 357.40129 | AI102: 356.65207
A103: 1997M9 | B103: 117.04693 | C103: 119.27115 | D103: 64.576011 | E103: 79.106554 | F103: 5.3721036 | G103: 5.6476141 | H103: 58.362527 | I103: 35.404611 | J103: 33.983995 | K103: 57.396383 | L103: 60.591781 | M103: 87.755465 | N103: 5.5781008 | O103: 43.710789 | P103: 54.812084 | Q103: 86.279562 | R103: 49.696781 | S103: 60.698714 | T103: 71.038416 | U103: 68.790746 | V103: 76.56565 | W103: 66.639483 | X103: 50.049421 | Y103: 52.730211 | Z103: 52.871174 | AA103: 57.299175 | AB103: 73.713847 | AC103: 51.21457 | AD103: 18.73 | AE103: 44.674223 | AF103: 83.11069 | AG103: -2.3768755 | AH103: 366.62359 | AI103: 364.24671
A104: 1997M10 | B104: 115.46755 | C104: 117.57286 | D104: 65.051656 | E104: 79.617678 | F104: 5.2534712 | G104: 5.6111095 | H104: 53.240805 | I104: 35.661327 | J104: 34.273034 | K104: 52.79743 | L104: 55.538215 | M104: 87.822792 | N104: 5.5467982 | O104: 44.062444 | P104: 55.48311 | Q104: 81.608033 | R104: 49.013749 | S104: 60.933259 | T104: 71.209989 | U104: 69.167939 | V104: 76.783384 | W104: 66.587675 | X104: 48.669989 | Y104: 54.249747 | Z104: 54.187142 | AA104: 56.619359 | AB104: 75.372533 | AC104: 53.839557 | AD104: 20.12 | AE104: 47.627142 | AF104: 80.064804 | AG104: -1.3343507 | AH104: 370.29988 | AI104: 368.96553
A105: 1997M11 | B105: 116.4919 | C105: 118.78546 | D105: 64.752081 | E105: 79.370104 | F105: 5.1593525 | G105: 5.7885452 | H105: 53.852315 | I105: 35.827689 | J105: 34.359395 | K105: 52.333974 | L105: 56.300572 | M105: 87.925683 | N105: 5.5044114 | O105: 43.787112 | P105: 54.348842 | Q105: 80.609775 | R105: 45.464208 | S105: 61.119745 | T105: 71.336387 | U105: 69.408723 | V105: 76.942017 | W105: 67.116935 | X105: 47.388004 | Y105: 53.805827 | Z105: 53.600704 | AA105: 56.303693 | AB105: 74.239468 | AC105: 51.521199 | AD105: 19.16 | AE105: 45.229031 | AF105: 80.2356 | AG105: -0.5904818 | AH105: 364.77726 | AI105: 364.18677
A106: 1997M12 | B106: 118.14216 | C106: 120.72724 | D106: 65.110155 | E106: 79.576537 | F106: 5.0874152 | G106: 6.2290291 | H106: 54.747937 | I106: 36.092541 | J106: 34.568498 | K106: 52.544136 | L106: 57.798165 | M106: 88.011419 | N106: 5.480269 | O106: 43.940349 | P106: 53.081179 | Q106: 87.071179 | R106: 43.941184 | S106: 61.332648 | T106: 71.467906 | U106: 69.631642 | V106: 77.106312 | W106: 71.614808 | X106: 45.282332 | Y106: 52.656442 | Z106: 52.393952 | AA106: 57.590374 | AB106: 66.289227 | AC106: 46.558745 | AD106: 17.24 | AE106: 41.275286 | AF106: 74.80659 | AG106: -5.2346663 | AH106: 364.59629 | AI106: 359.36162
A107: 1998M1 | B107: 116.30138 | C107: 118.55983 | D107: 64.998757 | E107: 79.683656 | F107: 4.9722919 | G107: 7.4087817 | H107: 56.966409 | I107: 36.417574 | J107: 34.659066 | K107: 53.618067 | L107: 59.305702 | M107: 88.210674 | N107: 5.7249334 | O107: 43.989344 | P107: 50.166782 | Q107: 88.744152 | R107: 43.747141 | S107: 61.687861 | T107: 71.70099 | U107: 69.853386 | V107: 77.286125 | W107: 68.531239 | X107: 43.93987 | Y107: 51.768383 | Z107: 51.54593 | AA107: 55.779342 | AB107: 62.779441 | AC107: 42.048358 | AD107: 15.07 | AE107: 36.334001 | AF107: 71.973685 | AG107: -1.7174158 | AH107: 353.61207 | AI107: 351.89465
A108: 1998M2 | B108: 118.53878 | C108: 121.07424 | D108: 64.99871 | E108: 79.602664 | F108: 4.9307706 | G108: 7.6623775 | H108: 60.441422 | I108: 36.624302 | J108: 34.811071 | K108: 57.491261 | L108: 63.234242 | M108: 88.279364 | N108: 5.7702986 | O108: 43.951733 | P108: 49.584119 | Q108: 88.94927 | R108: 44.628215 | S108: 62.047066 | T108: 71.92053 | U108: 70.137156 | V108: 77.47543 | W108: 67.986532 | X108: 43.210952 | Y108: 51.723728 | Z108: 51.489616 | AA108: 55.870371 | AB108: 61.995499 | AC108: 40.491216 | AD108: 14.18 | AE108: 34.030727 | AF108: 75.198986 | AG108: 2.5402703 | AH108: 356.83887 | AI108: 359.37914
A109: 1998M3 | B109: 117.54943 | C109: 120.11948 | D109: 65.079524 | E109: 79.412771 | F109: 4.8783286 | G109: 7.4217885 | H109: 62.929324 | I109: 36.871013 | J109: 34.962388 | K109: 59.525698 | L109: 66.167295 | M109: 88.310274 | N109: 5.8353216 | O109: 44.086781 | P109: 48.887518 | Q109: 83.04897 | R109: 43.499707 | S109: 62.317661 | T109: 72.084544 | U109: 70.345074 | V109: 77.646517 | W109: 68.635756 | X109: 43.543011 | Y109: 52.085138 | Z109: 51.827533 | AA109: 56.012402 | AB109: 61.387567 | AC109: 38.581555 | AD109: 13.24 | AE109: 31.902448 | AF109: 74.171997 | AG109: -0.6733667 | AH109: 356.64922 | AI109: 355.97585
A110: 1998M4 | B110: 118.17288 | C110: 120.87815 | D110: 65.264038 | E110: 79.534455 | F110: 4.8516662 | G110: 7.4236967 | H110: 63.011167 | I110: 37.114693 | J110: 35.139268 | K110: 59.757478 | L110: 65.767542 | M110: 88.35358 | N110: 5.8758634 | O110: 44.538723 | P110: 49.931662 | Q110: 82.654235 | R110: 43.473756 | S110: 62.536259 | T110: 72.207918 | U110: 70.598425 | V110: 77.79168 | W110: 70.744701 | X110: 43.842567 | Y110: 52.103175 | Z110: 51.821967 | AA110: 57.363715 | AB110: 62.633579 | AC110: 39.181388 | AD110: 13.39 | AE110: 32.288465 | AF110: 73.728173 | AG110: 1.2943724 | AH110: 353.09491 | AI110: 354.38928
A111: 1998M5 | B111: 117.91082 | C111: 120.64446 | D111: 64.974177 | E111: 79.385446 | F111: 4.8386136 | G111: 7.9084491 | H111: 61.857841 | I111: 37.38023 | J111: 35.349201 | K111: 57.365007 | L111: 64.008146 | M111: 88.447167 | N111: 5.9018513 | O111: 44.827717 | P111: 49.741432 | Q111: 80.043073 | R111: 43.048977 | S111: 62.868302 | T111: 72.433334 | U111: 70.849751 | V111: 77.952962 | W111: 71.116171 | X111: 42.34175 | Y111: 51.156805 | Z111: 50.823714 | AA111: 56.979391 | AB111: 58.917268 | AC111: 39.271911 | AD111: 13.97 | AE111: 33.690444 | AF111: 72.956108 | AG111: 1.0845254 | AH111: 349.12058 | AI111: 350.20511
... A370: 2019m12 | B370: 110.35046 | C370: 114.01443 | D370: 132.74844 | E370: 123.72076 | F370: 1.868678 | G370: 2.6892117 | H370: 218.71011 | I370: 195.71894 | J370: 221.01851 | K370: 141.28138 | L370: 170.88263 | M370: 107.93624 | N370: 4.9814986 | O370: 73.386832 | P370: 119.91371 | Q370: 91.493483 | R370: 114.8053 | S370: 132.32962 | T370: 125.61524 | U370: 130.05728 | V370: 124.06317 | W370: 103.73136 | X370: 131.21475 | Y370: 49.850081 | Z370: 50.043195 | AA370: 111.30344 | AB370: 87.368769 | AC370: 132.36824 | AD370: 63.396515 | AE370: 149.21508 | AF370: 99.143821 | AG370: 4.005938 | AH370: 1219.4924 | AI370: 1219.8299
A371: 2020M1 | B371: 110.72312 | C371: 114.64715 | D371: 127.98143 | E371: 120.39171 | F371: 1.8092977 | G371: 2.539106 | H371: 215.06539 | I371: 197.17607 | J371: 221.37686 | K371: 137.84869 | L371: 168.02217 | O371: 68.370956 | P371: 119.47235 | Q371: 89.241629 | R371: 119.17806 | S371: 132.7344 | T371: 125.92503 | U371: 130.33981 | V371: 124.27878 | W371: 105.36145 | X371: 133.35122 | Y371: 49.960485 | Z371: 50.374017 | AA371: 113.98178 | AB371: 76.919241 | AC371: 127.41432 | AD371: 61.683043 | AE371: 145.13586 | AF371: 100.3346 | AG371: -40.98738 | AH371: 1222.9439 | AI371: 1175.1977
A372: 2020M2 | B372: 110.47523 | C372: 114.56554 | F372: 1.614533 | G372: 2.3853783 | H372: 198.63462 | I372: 198.5466 | J372: 224.08882 | K372: 127.58893 | L372: 157.04402 | P372: 111.03641 | Q372: 88.380684 | R372: 114.73678 | S372: 133.15171 | T372: 126.26048 | U372: 130.55587 | V372: 124.47677 | W372: 101.49738 | X372: 126.00289 | Y372: 48.293265 | Z372: 48.03123 | AA372: 111.53698 | AB372: 61.641185 | AC372: 110.31233 | AD372: 53.3725 | AE372: 126.5287 | AF372: 98.733021
A373: 2020M3 | G373: 1.8756743
A374: 2020M4
A375: 2020M5
A376: 2020M6
A377: 2020M7
A378: 2020M8
A379: 2020M9
A380: 2020M10
A381: 2020M11
A382: 2020M12

Sheet Bloomberg
C1: Baltic
B3: month info
B4: year info
A5: 0 | B5: Security | C5: BDIY Index
A6: 2 | B6: Fields | C6: px_last
A7: 3 | B7: Start Date | C7: 43800
A8: 4 | B8: End Date
A9: D,W,M,Q,S,Y | B9: Per= | C9: D
A10: N,C,T,W,A | B10: Days= | C10: N
A11: C,P,E,B | B11: Fill= | C11: C
A12: TRUE,FALSE | B12: Dts= | C12: TRUE
A13: P,Y | B13: QtTyp=
A14: C,A,R,D | B14: Sort=
A15: USD | B15: Curr=
A16: G=Avg C=Last | B16: Quote= | C16: G
A17: Bloomberg Description | C17: =_xll.BDP(C5,"long_comp_name") -> #NAME?
B18: =_xll.BDH(C5,C6,C7,C8,$B$9&C9,$B$10&C10,$B$11&C11,$B$12&C12,$B$13&C13,$B$14&C14,$B$15&C15,$B$16&C16,"cols=2;rows=60") -> #NAME? | C18: 1568
B19: 43802 | C19: 1606
B20: 43803 | C20: 1599
B21: 43804 | C21: 1575
B22: 43805 | C22: 1558
B23: 43808 | C23: 1551
B24: 43809 | C24: 1528
B25: 43810 | C25: 1460
B26: 43811 | C26: 1388
B27: 43812 | C27: 1355
B28: 43815 | C28: 1315
B29: 43816 | C29: 1281
B30: 43817 | C30: 1221
... B61: 43860 | C61: 498
B62: 43861 | C62: 487 | E62: January Average | F62: =AVERAGE(C40:C62) -> 718
B63: 43864 | C63: 466 | E63: Feb Average | F63: =AVERAGE(C63:C77) -> 440
B64: 43865 | C64: 453
B65: 43866 | C65: 430
B66: 43867 | C66: 431
B67: 43868 | C67: 415
B68: 43871 | C68: 411
B69: 43872 | C69: 418
B70: 43873 | C70: 421
B71: 43874 | C71: 421
B72: 43875 | C72: 425
B73: 43878 | C73: 434
B74: 43879 | C74: 450
B75: 43880 | C75: 465
... B77: 43882 | C77: 480

Sheet OECD
B1: OECDCLI | C1: CHEM
A2: ='Monthly Haver'!A5 -> Jan-1999 | B2: 99.50104 | C2: 95.61 | E2: CHEM: Comes from https://www.americanchemistry.com/CAB-vs-Industrial-Production/
A3: ='Monthly Haver'!A6 -> Feb-1999 | B3: 99.68887 | C3: 96.34 | E3: Download worksheet, look for CAB variable (first variable column).
A4: ='Monthly Haver'!A7 -> Mar-1999 | B4: 99.87469 | C4: 96.64
A5: ='Monthly Haver'!A8 -> Apr-1999 | B5: 100.0538 | C5: 97.25
A6: ='Monthly Haver'!A9 -> May-1999 | B6: 100.2218 | C6: 98.12
A7: ='Monthly Haver'!A10 -> Jun-1999 | B7: 100.3789 | C7: 98.7 | E7: OECDCLI: https://data.oecd.org/leadind/composite-leading-indicator-cli.htm
A8: ='Monthly Haver'!A11 -> Jul-1999 | B8: 100.5246 | C8: 98.78
A9: ='Monthly Haver'!A12 -> Aug-1999 | B9: 100.6616 | C9: 98.8
A10: ='Monthly Haver'!A13 -> Sep-1999 | B10: 100.7954 | C10: 98.59
A11: ='Monthly Haver'!A14 -> Oct-1999 | B11: 100.9314 | C11: 99.03
A12: ='Monthly Haver'!A15 -> Nov-1999 | B12: 101.0658 | C12: 100.26
A13: ='Monthly Haver'!A16 -> Dec-1999 | B13: 101.1871 | C13: 100.67
A14: ='Monthly Haver'!A17 -> Jan-2000 | B14: 101.2855 | C14: 100.84
A15: ='Monthly Haver'!A18 -> Feb-2000 | B15: 101.343 | C15: 100.41
A16: ='Monthly Haver'!A19 -> Mar-2000 | B16: 101.3606 | C16: 101.06
A17: ='Monthly Haver'!A20 -> Apr-2000 | B17: 101.3398 | C17: 101.16
A18: ='Monthly Haver'!A21 -> May-2000 | B18: 101.2792 | C18: 100.53
A19: ='Monthly Haver'!A22 -> Jun-2000 | B19: 101.1854 | C19: 100.36
... A242: ='Monthly Haver'!A245 -> Jan-2019 | B242: 99.54697 | C242: 121.4
A243: ='Monthly Haver'!A246 -> Feb-2019 | B243: 99.45459 | C243: 121.42 | G243: Sources:
A244: ='Monthly Haver'!A247 -> Mar-2019 | B244: 99.38396 | C244: 122.17 | G244: https://www.americanchemistry.com/CAB-vs-Industrial-Production/
A245: ='Monthly Haver'!A248 -> Apr-2019 | B245: 99.32558 | C245: 122.79
A246: ='Monthly Haver'!A249 -> May-2019 | B246: 99.26957 | C246: 122.29
A247: ='Monthly Haver'!A250 -> Jun-2019 | B247: 99.21947 | C247: 122.42
A248: ='Monthly Haver'!A251 -> Jul-2019 | B248: 99.18283 | C248: 122.93
A249: ='Monthly Haver'!A252 -> Aug-2019 | B249: 99.16628 | C249: 122.33
A250: ='Monthly Haver'!A253 -> Sep-2019 | B250: 99.17904 | C250: 122.57
A251: ='Monthly Haver'!A254 -> Oct-2019 | B251: 99.23029 | C251: 121.97
A252: ='Monthly Haver'!A255 -> Nov-2019 | B252: 99.31636 | C252: 122.42
A253: ='Monthly Haver'!A256 -> Dec-2019 | B253: 99.43238 | C253: 122.74
A254: ='Monthly Haver'!A257 -> Jan-2020 | C254: 124.64
A255: ='Monthly Haver'!A258 -> Feb-2020 | C255: 124.08

Sheet GDS_Quarterly
A1: EcDatabase | B1: ID:GDS_LIVE | C1: ID:GDS_LIVE | D1: ID:GDS_LIVE | E1: ID:GDS_LIVE | F1: ID:GDS_LIVE | G1: ID:GDS_LIVE | H1: ID:GDS_LIVE | I1: ID:GDS_LIVE | J1: ID:GDS_LIVE | K1: ID:GDS_LIVE | L1: ID:GDS_LIVE | M1: ID:GDS_LIVE | N1: ID:GDS_LIVE | O1: ID:GDS_LIVE | P1: ID:GDS_LIVE | Q1: ID:GDS_LIVE | R1: ID:GDS_LIVE | S1: ID:GDS_LIVE | T1: ID:GDS_LIVE | U1: ID:GDS_LIVE | V1: ID:GDS_LIVE | W1: ID:GDS_LIVE | X1: ID:GDS_LIVE | Y1: ID:GDS_LIVE | Z1: ID:GDS_LIVE | AA1: ID:GDS_LIVE | AB1: ID:GDS_LIVE | AC1: ID:GDS_LIVE | AD1: ID:GDS_LIVE | AE1: ID:GDS_LIVE | AF1: ID:GDS_LIVE | AG1: ID:GDS_LIVE | AH1: ID:GDS_LIVE | AI1: ID:GDS_LIVE | AJ1: ID:GDS_LIVE | AK1: ID:GDS_LIVE | AL1: ID:GDS_LIVE | AM1: ID:GDS_LIVE | AN1: ID:GDS_LIVE | AO1: ID:GDS_LIVE | AP1: ID:GDS_LIVE | AQ1: ID:GDS_LIVE | AR1: ID:GDS_LIVE | AS1: ID:GDS_LIVE | AT1: ID:GDS_LIVE | AU1: ID:GDS_LIVE | AV1: ID:GDS_LIVE | AW1: ID:GDS_LIVE | AX1: ID:GDS_LIVE | AY1: ID:GDS_LIVE | AZ1: ID:GDS_LIVE | BA1: ID:GDS_LIVE | BB1: ID:GDS_LIVE | BC1: ID:GDS_LIVE
A2: Series_code | B2: 001ACC_PPPWGT.Q | C2: 001ACC.Q | D2: 001AIP.Q | E2: 001AIP_GDPWGT.Q | F2: 001BCA.Q | G2: 001BCA_GDP.Q | H2: 001FIGB.Q | I2: 001FIPR.Q | J2: 001FISI.Q | K2: 001FMB.Q | L2: 001FMN.Q | M2: 001FMSCID.Q | N2: 001FMSCIL.Q | O2: 001LE.Q | P2: 001LUR.Q | Q2: 001NCP_R.Q | R2: 001NCP_R_GDPWGT.Q | S2: 001NFI_R.Q | T2: 001NFI_R_GDPWGT.Q | U2: 001NGDP_R.Q | V2: 001NGDP_R_GDPWGT.Q | W2: 001NGDP_RF.Q | X2: 001NGDP_RF_GDPWGT.Q | Y2: 001NGDPD.Q | Z2: 001NM_R.Q | AA2: 001NM_R_GDPWGT.Q | AB2: 001NM_R_TMWGT.Q | AC2: 001NRS.Q | AD2: 001NTDD_R.Q | AE2: 001NTDD_R_GDPWGT.Q | AF2: 001NX_R.Q | AG2: 001NX_R_GDPWGT.Q | AH2: 001NX_R_TXWGT.Q | AI2: 001PALLFNFW.Q | AJ2: 001PBEVEW.Q | AK2: 001PCOALW.Q | AL2: 001PCPI.Q | AM2: 001PCPI_GDPWGT.Q | AN2: 001PCPIF.Q | AO2: 001PCPIX.Q | AP2: 001.Q | AQ2: 001PFOODW.Q | AR2: 001PMETAW.Q | AS2: 001PMI.Q | AT2: 001PMI_PPPWGT.Q | AU2: 001PNFUELW.Q | AV2: 001PNGASW.Q | AW2: 001PNRGW.Q | AX2: 001POILAPSP.Q | AY2: 001POILAPSPW.Q | AZ2: 001PRAWMW.Q | BA2: 001TG.Q | BB2: 001TMG.Q | BC2: 001TXG.Q
A3: Country | B3: World | C3: World | D3: World | E3: World | F3: World | G3: World | H3: World | I3: World | J3: World | K3: World | L3: World | M3: World | N3: World | O3: World | P3: World | Q3: World | R3: World | S3: World | T3: World | U3: World | V3: World | W3: World | X3: World | Y3: World | Z3: World | AA3: World | AB3: World | AC3: World | AD3: World | AE3: World | AF3: World | AG3: World | AH3: World | AI3: World | AJ3: World | AK3: World | AL3: World | AM3: World | AN3: World | AO3: World | AP3: World | AQ3: World | AR3: World | AS3: World | AT3: World | AU3: World | AV3: World | AW3: World | AX3: World | AY3: World | AZ3: World | BA3: World | BB3: World | BC3: World
A4: Indicator | B4: ACC_PPPWGT | C4: ACC | D4: AIP | E4: AIP_GDPWGT | F4: BCA | G4: BCA_GDP | H4: FIGB | I4: FIPR | J4: FISI | K4: FMB | L4: FMN | M4: FMSCID | N4: FMSCIL | O4: LE | P4: LUR | Q4: NCP_R | R4: NCP_R_GDPWGT | S4: NFI_R | T4: NFI_R_GDPWGT | U4: NGDP_R | V4: NGDP_R_GDPWGT | W4: NGDP_RF | X4: NGDP_RF_GDPWGT | Y4: NGDPD | Z4: NM_R | AA4: NM_R_GDPWGT | AB4: NM_R_TMWGT | AC4: NRS | AD4: NTDD_R | AE4: NTDD_R_GDPWGT | AF4: NX_R | AG4: NX_R_GDPWGT | AH4: NX_R_TXWGT | AI4: PALLFNFW | AJ4: PBEVEW | AK4: PCOALW | AL4: PCPI | AM4: PCPI_GDPWGT | AN4: PCPIF | AO4: PCPIX | AP4: PCPIX_GDPWGT | AQ4: PFOODW | AR4: PMETAW | AS4: PMI | AT4: PMI_PPPWGT | AU4: PNFUELW | AV4: PNGASW | AW4: PNRGW | AX4: POILAPSP | AY4: POILAPSPW | AZ4: PRAWMW | BA4: TG | BB4: TMG | BC4: TXG
A5: Indicator.Descriptor | B5: Consumer confidence, PPP weighted | C5: Consumer confidence | D5: Industrial production | E5: Industrial production, MER weighted | F5: Current account balance | G5: Current account balance, percent of GDP | H5: Long-term interest rate | I5: Policy-related interest rate | J5: Benchmark stock market index | K5: Broad money | L5: Narrow money | M5: Morgan Stanley MSCI stock price index in US dollars | N5: Morgan Stanley MSCI stock price index in national currency | O5: Employment | P5: Unemployment rate | Q5: Real private consumption | R5: Real private consumption, MER weighted | S5: Real gross fixed capital formation | T5: Real gross fixed capital formation, MER weighted | U5: Real gross domestic product | V5: Real gross domestic product, MER weighted | W5: Real gross domestic product, with projections from WEO | X5: Real gross domestic product, with projections from WEO, MER weighted | Y5: Nominal gross domestic product, US dollars | Z5: Real imports | AA5: Real imports, MER weighted | AB5: Real imports, imports weighted | AC5: Retail sales | AD5: Real total domestic demand | AE5: Real total domestic demand, MER weighted | AF5: Real exports | AG5: Real exports, MER weighted | AH5: Real exports, exports weighted | AI5: Commodity price: all primary commodities | AJ5: Commodity price: beverage | AK5: Commodity price: coal | AL5: Consumer price index | AM5: Consumer price index, MER weighted | AN5: Consumer price index, with projections from WEO | AO5: Core consumer price index | AP5: Core consumer price index, GDP weighted | AQ5: Commodity price: food | AR5: Commodity price: metals | AS5: Manufacturing PMI | AT5: Manufacturing PMI, PPP weighted | AU5: Commodity price: non-fuel primary commodities | AV5: Commodity price: natural gas | AW5: Commodity price: energy | AX5: Commodity price: petroleum, US dollar per barrel | AY5: Commodity price: petroleum | AZ5: Commodity price: raw materials | BA5: Merchandise trade balance | BB5: Merchandise imports | BC5: Merchandise exports
A6: Frequency | B6: Quarterly | C6: Quarterly | D6: Quarterly | E6: Quarterly | F6: Quarterly | G6: Quarterly | H6: Quarterly | I6: Quarterly | J6: Quarterly | K6: Quarterly | L6: Quarterly | M6: Quarterly | N6: Quarterly | O6: Quarterly | P6: Quarterly | Q6: Quarterly | R6: Quarterly | S6: Quarterly | T6: Quarterly | U6: Quarterly | V6: Quarterly | W6: Quarterly | X6: Quarterly | Y6: Quarterly | Z6: Quarterly | AA6: Quarterly | AB6: Quarterly | AC6: Quarterly | AD6: Quarterly | AE6: Quarterly | AF6: Quarterly | AG6: Quarterly | AH6: Quarterly | AI6: Quarterly | AJ6: Quarterly | AK6: Quarterly | AL6: Quarterly | AM6: Quarterly | AN6: Quarterly | AO6: Quarterly | AP6: Quarterly | AQ6: Quarterly | AR6: Quarterly | AS6: Quarterly | AT6: Quarterly | AU6: Quarterly | AV6: Quarterly | AW6: Quarterly | AX6: Quarterly | AY6: Quarterly | AZ6: Quarterly | BA6: Quarterly | BB6: Quarterly | BC6: Quarterly
A7: Scale | B7: Units | C7: Units | D7: Units | E7: Units | F7: Billions | G7: Units | H7: Units | I7: Units | J7: Units | K7: Units | L7: Units | M7: Units | N7: Units | O7: Units | P7: Units | Q7: Units | R7: Units | S7: Units | T7: Units | U7: Units | V7: Units | W7: Units | X7: Units | Y7: Billions | Z7: Units | AA7: Units | AB7: Units | AC7: Units | AD7: Units | AE7: Units | AF7: Units | AG7: Units | AH7: Units | AI7: Units | AJ7: Units | AK7: Units | AL7: Units | AM7: Units | AN7: Units | AO7: Units | AP7: Units | AQ7: Units | AR7: Units | AS7: Units | AT7: Units | AU7: Units | AV7: Units | AW7: Units | AX7: Units | AY7: Units | AZ7: Units | BA7: Billions | BB7: Billions | BC7: Billions
A8: Display_scale | B8: Units | C8: Units | D8: Units | E8: Units | F8: Billions | G8: Units | H8: Units | I8: Units | J8: Units | K8: Units | L8: Units | M8: Units | N8: Units | O8: Units | P8: Units | Q8: Units | R8: Units | S8: Units | T8: Units | U8: Units | V8: Units | W8: Units | X8: Units | Y8: Billions | Z8: Units | AA8: Units | AB8: Units | AC8: Units | AD8: Units | AE8: Units | AF8: Units | AG8: Units | AH8: Units | AI8: Units | AJ8: Units | AK8: Units | AL8: Units | AM8: Units | AN8: Units | AO8: Units | AP8: Units | AQ8: Units | AR8: Units | AS8: Units | AT8: Units | AU8: Units | AV8: Units | AW8: Units | AX8: Units | AY8: Units | AZ8: Units | BA8: Billions | BB8: Billions | BC8: Billions
A9: 1990Q1 | B9: 114.57716 | C9: 123.95658 | D9: 49.610915 | E9: 63.676787 | F9: -39.321559 | G9: -1.1090686 | H9: 8.5859571 | I9: 12.8652 | J9: 23.048825 | K9: 10.002343 | L9: 11.147585 | M9: 25.138839 | N9: 17.108852 | O9: 81.58033 | P9: 3.3603761 | Q9: 47.454501 | R9: 56.619681 | S9: 42.902703 | T9: 59.965452 | U9: 48.90739 | V9: 58.402007 | W9: 49.885179 | X9: 58.92731 | Y9: 3545.4578 | Z9: 22.271797 | AA9: 30.804851 | AB9: 29.797069 | AD9: 48.879127 | AE9: 58.941664 | AF9: 23.76231 | AG9: 30.227676 | AH9: 29.113541 | AJ9: 51.195456 | AK9: 51.172528 | AL9: 11.95076 | AM9: 30.826818 | AN9: 4.5174393 | AO9: 47.450264 | AP9: 58.113838 | AX9: 19.463333 | AZ9: 73.492273 | BA9: -12.310158 | BB9: 585.48544 | BC9: 573.17528
A10: 1990Q2 | B10: 113.72542 | C10: 122.37419 | D10: 49.692991 | E10: 64.068947 | F10: -31.530476 | G10: -0.8903193 | H10: 8.8730628 | I10: 10.074507 | J10: 24.468707 | K10: 10.290694 | L10: 11.463502 | M10: 27.335213 | N10: 18.434519 | O10: 82.463691 | P10: 3.4088283 | Q10: 47.996259 | R10: 57.280292 | S10: 42.482857 | T10: 59.560934 | U10: 49.132618 | V10: 58.84342 | W10: 50.078028 | X10: 59.362381 | Y10: 3541.4796 | Z10: 22.353061 | AA10: 30.956948 | AB10: 30.010831 | AD10: 49.303633 | AE10: 59.489536 | AF10: 23.892262 | AG10: 30.603044 | AH10: 29.39376 | AJ10: 55.091301 | AK10: 53.525874 | AL10: 12.658284 | AM10: 32.173583 | AN10: 4.8907648 | AO10: 48.071113 | AP10: 58.824033 | AX10: 15.82 | AZ10: 75.668164 | BA10: -11.345707 | BB10: 587.08275 | BC10: 575.73705
A11: 1990Q3 | B11: 109.61725 | C11: 115.48501 | D11: 50.199927 | E11: 64.561472 | F11: -31.341681 | G11: -0.84952419 | H11: 9.0608422 | I11: 10.065118 | J11: 20.261359 | K11: 10.560172 | L11: 11.670862 | M11: 22.814 | N11: 15.094139 | O11: 82.68347 | P11: 3.46503 | Q11: 48.308419 | R11: 57.602174 | S11: 44.098994 | T11: 60.310768 | U11: 49.514114 | V11: 59.197831 | W11: 50.447389 | X11: 59.701264 | Y11: 3689.3218 | Z11: 22.529919 | AA11: 30.83848 | AB11: 29.859349 | AD11: 49.461895 | AE11: 59.627623 | AF11: 24.380517 | AG11: 30.886802 | AH11: 29.669397 | AJ11: 54.592727 | AK11: 55.284677 | AL11: 13.458476 | AM11: 33.770376 | AN11: 5.4327878 | AO11: 48.746334 | AP11: 59.621595 | AX11: 25.656667 | AZ11: 74.436365 | BA11: -16.835061 | BB11: 617.58435 | BC11: 601.69359
A12: 1990Q4 | B12: 101.68114 | C12: 101.97022 | D12: 50.10402 | E12: 64.293609 | F12: -33.280688 | G12: -0.86949116 | H12: 8.7511308 | I12: 9.4848882 | J12: 21.933351 | K12: 10.747179 | L12: 11.945251 | M12: 24.645852 | N12: 16.53637 | O12: 82.588915 | P12: 3.5673421 | Q12: 48.169026 | R12: 57.35894 | S12: 43.739078 | T12: 59.88237 | U12: 49.584453 | V12: 59.100944 | W12: 50.443883 | X12: 59.551707 | Y12: 3827.6051 | Z12: 22.594528 | AA12: 30.906512 | AB12: 29.961992 | AD12: 49.425737 | AE12: 59.352199 | AF12: 24.801093 | AG12: 31.437589 | AH12: 30.21401 | AJ12: 56.046732 | AK12: 55.284677 | AL12: 14.169128 | AM12: 35.173732 | AN12: 5.8224907 | AO12: 49.417072 | AP12: 60.312896 | AX12: 31 | AZ12: 72.947571 | BA12: -30.885163 | BB12: 665.50267 | BC12: 635.9609
A13: 1991Q1 | B13: 102.64214 | C13: 103.70414 | D13: 50.534799 | E13: 63.635536 | F13: -4.2691369 | G13: -0.1112018 | H13: 8.1974964 | I13: 9.4124759 | J13: 24.4134 | K13: 10.957662 | L13: 12.265427 | M13: 28.011022 | N13: 19.683323 | O13: 82.839187 | P13: 3.9379885 | Q13: 48.222368 | R13: 57.288128 | S13: 43.158562 | T13: 59.154513 | U13: 49.439196 | V13: 59.001864 | W13: 50.271907 | X13: 59.442887 | Y13: 3839.0898 | Z13: 22.184072 | AA13: 30.217621 | AB13: 29.576016 | AD13: 49.248609 | AE13: 59.21465 | AF13: 25.073097 | AG13: 31.539852 | AH13: 30.241904 | AJ13: 53.346582 | AK13: 54.270686 | AL13: 14.845113 | AM13: 36.465336 | AN13: 6.2696693 | AO13: 50.188609 | AP13: 61.210213 | AX13: 19.85 | AY13: 45.410521 | AZ13: 71.599601 | BA13: -23.263209 | BB13: 654.20121 | BC13: 632.0575
A14: 1991Q2 | B14: 106.14761 | C14: 109.80223 | D14: 50.487566 | E14: 63.747281 | F14: 3.3422451 | G14: 0.087525572 | H14: 8.2555072 | I14: 7.8664612 | J14: 23.848407 | K14: 11.177839 | L14: 12.632306 | M14: 27.64234 | N14: 19.754628 | O14: 82.85367 | P14: 4.0448415 | Q14: 48.919939 | R14: 57.967412 | S14: 43.368928 | T14: 59.087744 | U14: 50.027521 | V14: 59.53345 | W14: 50.809346 | X14: 59.937718 | Y14: 3818.5927 | Z14: 22.830031 | AA14: 30.819553 | AB14: 30.104496 | AD14: 49.625971 | AE14: 59.61803 | AF14: 25.888054 | AG14: 32.424379 | AH14: 31.194186 | AJ14: 49.446021 | AK14: 52.242706 | AL14: 15.364372 | AM14: 37.429227 | AN14: 6.5921321 | AO14: 50.781838 | AP14: 61.801858 | AX14: 18.33 | AY14: 44.329788 | AZ14: 72.920081 | BA14: -13.422424 | BB14: 620.80173 | BC14: 608.38971
A15: 1991Q3 | B15: 105.38728 | C15: 108.91017 | D15: 50.793785 | E15: 64.236662 | F15: -6.0306232 | G15: -0.15571677 | H15: 8.0529544 | I15: 7.4589269 | J15: 25.252212 | K15: 11.32418 | L15: 12.968305 | M15: 29.224076 | N15: 20.829253 | O15: 82.868732 | P15: 3.9726065 | Q15: 49.386586 | R15: 58.331711 | S15: 43.729284 | T15: 59.320526 | U15: 50.481992 | V15: 59.869153 | W15: 51.138992 | X15: 60.200869 | Y15: 3872.8156 | Z15: 23.491438 | AA15: 31.630021 | AB15: 30.843919 | AD15: 50.192894 | AE15: 60.012121 | AF15: 26.052484 | AG15: 32.886647 | AH15: 31.574332 | AJ15: 48.005646 | AK15: 52.242706 | AL15: 15.948203 | AM15: 38.42273 | AN15: 6.9683222 | AO15: 51.451395 | AP15: 62.487536 | AX15: 19.423333 | AY15: 47.03393 | AZ15: 71.59588 | BA15: -15.693803 | BB15: 636.01362 | BC15: 621.23742
A16: 1991Q4 | B16: 100.0695 | C16: 99.589247 | D16: 50.876062 | E16: 64.187419 | F16: 6.2783686 | G16: 0.15690032 | H16: 7.5016082 | I16: 6.7741972 | J16: 26.006905 | K16: 11.536941 | L16: 13.569935 | M16: 30.888157 | N16: 22.174654 | O16: 83.049327 | P16: 4.0439232 | Q16: 49.618253 | R16: 58.57445 | S16: 43.999846 | T16: 59.486362 | U16: 50.793182 | V16: 60.180055 | W16: 51.300929 | X16: 60.437241 | Y16: 4001.5015 | Z16: 24.121961 | AA16: 32.238018 | AB16: 31.276994 | AD16: 50.411298 | AE16: 60.206084 | AF16: 26.749704 | AG16: 33.643549 | AH16: 32.171823 | AJ16: 50.707911 | AK16: 52.242706 | AL16: 16.703033 | AM16: 39.748321 | AN16: 7.5211591 | AO16: 52.054717 | AP16: 63.107878 | AX16: 19.866667 | AY16: 46.499278 | AZ16: 69.219185 | BA16: -7.3048117 | BB16: 657.82463 | BC16: 651.59682
A17: 1992Q1 | B17: 98.979594 | C17: 97.701345 | D17: 51.048225 | E17: 63.92753 | F17: -0.54879872 | G17: -0.013563717 | H17: 7.3384658 | I17: 6.1613548 | J17: 25.958013 | K17: 11.715211 | L17: 14.13337 | M17: 29.051796 | N17: 21.991082 | O17: 83.092596 | P17: 4.2358282 | Q17: 49.975695 | R17: 59.198762 | S17: 44.335697 | T17: 59.591735 | U17: 51.33632 | V17: 60.693203 | W17: 51.732251 | X17: 60.896221 | Y17: 4046.0791 | Z17: 24.506206 | AA17: 32.529187 | AB17: 31.729678 | AD17: 50.869186 | AE17: 60.671003 | AF17: 27.431198 | AG17: 34.290457 | AH17: 32.832818 | AI17: 50.258283 | AJ17: 45.531943 | AK17: 52.242706 | AL17: 20.059383 | AM17: 40.934657 | AN17: 10.419023 | AO17: 52.603413 | AP17: 63.660579 | AQ17: 66.519427 | AR17: 47.829402 | AU17: 54.263942 | AV17: 51.653864 | AW17: 44.4642 | AX17: 17.506667 | AY17: 40.826794 | AZ17: 67.992599 | BA17: -6.8305857 | BB17: 672.01734 | BC17: 666.11806
A18: 1992Q2 | B18: 103.91856 | C18: 106.6168 | D18: 51.082981 | E18: 64.147448 | F18: -8.2186637 | G18: -0.20072862 | H18: 7.3629297 | I18: 5.7598333 | J18: 24.939879 | K18: 11.832685 | L18: 14.501339 | M18: 28.653464 | N18: 21.56172 | O18: 83.249981 | P18: 4.2994115 | Q18: 50.49074 | R18: 59.556844 | S18: 45.143591 | T18: 60.506912 | U18: 51.749078 | V18: 61.074851 | W18: 52.137748 | X18: 61.272429 | Y18: 4094.4154 | Z18: 25.018509 | AA18: 33.060568 | AB18: 32.342648 | AD18: 51.430872 | AE18: 61.15527 | AF18: 27.501555 | AG18: 34.445037 | AH18: 33.047754 | AI18: 51.723619 | AJ18: 41.181354 | AK18: 51.725258 | AL18: 21.882438 | AM18: 42.19342 | AN18: 11.982565 | AO18: 53.167561 | AP18: 64.239066 | AQ18: 64.984304 | AR18: 48.653229 | AU18: 53.78109 | AV18: 54.199501 | AW18: 48.747539 | AX18: 19.683333 | AY18: 45.857339 | AZ18: 72.528259 | BA18: -13.806179 | BB18: 689.80279 | BC18: 676.67881
A19: 1992Q3 | B19: 100.99172 | C19: 101.20892 | D19: 51.108131 | E19: 64.497915 | F19: -12.672036 | G19: -0.29963426 | H19: 6.8129193 | I19: 5.4484827 | J19: 25.058766 | K19: 11.991291 | L19: 14.983063 | M19: 29.108061 | N19: 22.248486 | O19: 83.341424 | P19: 4.2717723 | Q19: 50.959187 | R19: 60.013287 | S19: 45.491978 | T19: 60.621606 | U19: 52.277747 | V19: 61.59549 | W19: 52.66082 | X19: 61.788012 | Y19: 4229.1681 | Z19: 25.255727 | AA19: 33.239037 | AB19: 32.526455 | AD19: 51.782821 | AE19: 61.580107 | AF19: 28.111755 | AG19: 35.007429 | AH19: 33.514844 | AI19: 52.13722 | AJ19: 41.845637 | AK19: 49.138015 | AL19: 23.629282 | AM19: 43.446128 | AN19: 13.540622 | AO19: 53.682183 | AP19: 64.718098 | AQ19: 63.082407 | AR19: 50.141161 | AU19: 53.176748 | AV19: 61.388955 | AW19: 50.633568 | AX19: 19.996667 | AY19: 44.615931 | AZ19: 72.227941 | BA19: -11.577064 | BB19: 721.76381 | BC19: 710.18675
A20: 1992Q4 | B20: 102.40385 | C20: 104.19516 | D20: 51.245665 | E20: 64.638415 | F20: -7.9428396 | G20: -0.18932182 | H20: 6.7318076 | I20: 4.8908571 | J20: 25.639143 | K20: 12.164012 | L20: 15.497241 | M20: 29.418506 | N20: 23.8457 | O20: 83.436844 | P20: 4.2706197 | Q20: 51.502053 | R20: 60.443607 | S20: 45.966834 | T20: 60.887704 | U20: 52.595833 | V20: 61.9166 | W20: 52.953234 | X20: 62.096682 | Y20: 4195.4169 | Z20: 25.922482 | AA20: 33.766728 | AB20: 32.987577 | AD20: 51.980817 | AE20: 61.782192 | AF20: 28.837971 | AG20: 35.621344 | AH20: 34.213053 | AI20: 50.557026 | AJ20: 46.601668 | AK20: 46.462571 | AL20: 25.735198 | AM20: 44.947416 | AN20: 15.560854 | AO20: 54.219145 | AP20: 65.247916 | AQ20: 61.231113 | AR20: 44.892083 | AU20: 51.344047 | AV20: 65.947681 | AW20: 49.418622 | AX20: 18.956667 | AY20: 43.745614 | AZ20: 72.125898 | BA20: -9.4854212 | BB20: 705.48371 | BC20: 695.99829
A21: 1993Q1 | B21: 103.24847 | C21: 105.51122 | D21: 51.487975 | E21: 65.158724 | F21: -5.7876936 | G21: -0.13269153 | H21: 6.2895059 | I21: 4.5145208 | J21: 27.21316 | K21: 12.50483 | L21: 16.407767 | M21: 31.639239 | N21: 25.826285 | O21: 83.554679 | P21: 4.9602999 | Q21: 52.640917 | R21: 61.292826 | S21: 47.14364 | T21: 61.592522 | U21: 53.111071 | V21: 62.308641 | W21: 53.477523 | X21: 62.486482 | Y21: 4361.7656 | Z21: 26.897003 | AA21: 34.593486 | AB21: 33.780769 | AD21: 52.604998 | AE21: 62.197379 | AF21: 30.382313 | AG21: 36.817071 | AH21: 35.403096 | AI21: 50.034526 | AJ21: 45.135889 | AK21: 44.024943 | AL21: 27.808968 | AM21: 46.829245 | AN21: 17.57456 | AO21: 54.798433 | AP21: 65.778121 | AQ21: 62.812453 | AR21: 43.882471 | AU21: 52.039682 | AV21: 63.018192 | AW21: 47.13412 | AX21: 17.99 | AY21: 42.3372 | AZ21: 76.160493 | BA21: -0.19124414 | BB21: 687.8729 | BC21: 687.68165
A22: 1993Q2 | B22: 101.749 | C22: 102.87849 | D22: 51.796828 | E22: 65.576903 | F22: -19.011224 | G22: -0.41978226 | H22: 6.1341952 | I22: 4.2917927 | J22: 28.6376 | K22: 17.852794 | L22: 17.561017 | M22: 33.813197 | N22: 27.909577 | O22: 83.694154 | P22: 4.9812768 | Q22: 53.222521 | R22: 61.72581 | S22: 47.784674 | T22: 62.025543 | U22: 53.615739 | V22: 62.671143 | W22: 53.958127 | X22: 62.833186 | Y22: 4528.8297 | Z22: 27.444794 | AA22: 35.099275 | AB22: 34.268182 | AD22: 53.206911 | AE22: 62.63286 | AF22: 30.354299 | AG22: 36.843324 | AH22: 35.571613 | AI22: 50.992396 | AJ22: 42.162183 | AK22: 43.073674 | AL22: 30.417039 | AM22: 49.476246 | AN22: 20.42259 | AO22: 55.469412 | AP22: 66.390493 | AQ22: 64.308096 | AR22: 40.780315 | AU22: 53.365152 | AV22: 65.690285 | AW22: 47.560264 | AX22: 17.993333 | AY22: 41.253286 | AZ22: 86.622907 | BA22: -3.4746474 | BB22: 717.91602 | BC22: 714.44137
A23: 1993Q3 | B23: 101.43717 | C23: 102.29282 | D23: 52.147282 | E23: 65.946824 | F23: -18.41809 | G23: -0.39928018 | H23: 5.677141 | I23: 4.2543031 | J23: 29.880758 | K23: 21.832706 | L23: 18.795 | M23: 35.582569 | N23: 30.299742 | O23: 83.902125 | P23: 4.986375 | Q23: 53.896423 | R23: 62.332828 | S23: 48.346594 | T23: 62.320425 | U23: 54.067867 | V23: 63.024689 | W23: 54.385599 | X23: 63.172901 | Y23: 4612.8236 | Z23: 28.4596 | AA23: 35.88201 | AB23: 34.9352 | AD23: 53.733707 | AE23: 63.024283 | AF23: 30.795054 | AG23: 37.152911 | AH23: 35.958918 | AI23: 49.595479 | AJ23: 50.310757 | AK23: 43.073674 | AL23: 33.886944 | AM23: 52.843346 | AN23: 24.600056 | AO23: 56.076753 | AP23: 66.889485 | AQ23: 63.670136 | AR23: 39.651704 | AU23: 53.210871 | AV23: 65.329983 | AW23: 44.365908 | AX23: 16.2 | AY23: 37.405873 | AZ23: 85.740496 | BA23: -0.9447507 | BB23: 718.93549 | BC23: 717.99074
A24: 1993Q4 | B24: 104.15099 | C24: 106.98842 | D24: 52.828155 | E24: 66.455809 | F24: -22.279986 | G24: -0.47682848 | H24: 5.3968968 | I24: 4.0395384 | J24: 32.042274 | K24: 22.854827 | L24: 25.921096 | M24: 37.684721 | N24: 33.524496 | O24: 84.048738 | P24: 4.9896452 | Q24: 54.630786 | R24: 63.121061 | S24: 49.494438 | T24: 63.530318 | U24: 54.674231 | V24: 63.679982 | W24: 54.978026 | X24: 63.822091 | Y24: 4672.5366 | Z24: 29.271835 | AA24: 36.886785 | AB24: 35.827522 | AD24: 54.387403 | AE24: 63.732312 | AF24: 31.668269 | AG24: 37.927463 | AH24: 36.672803 | AI24: 48.580649 | AJ24: 54.312888 | AK24: 42.944312 | AL24: 37.592803 | AM24: 56.120641 | AN24: 29.460842 | AO24: 56.636658 | AP24: 67.395588 | AQ24: 64.978977 | AR24: 37.491932 | AU24: 53.365886 | AV24: 63.126565 | AW24: 41.658927 | AX24: 14.963333 | AY24: 34.768052 | AZ24: 83.352583 | BA24: 2.4185888 | BB24: 732.1666 | BC24: 734.58518
A25: 1994Q1 | B25: 107.36886 | C25: 107.41858 | D25: 53.634238 | E25: 67.323183 | F25: -8.7345659 | G25: -0.18598883 | H25: 6.0863743 | I25: 3.9730805 | J25: 31.728389 | K25: 26.897378 | L25: 26.568753 | M25: 37.402626 | N25: 33.968623 | O25: 84.423521 | P25: 5.3174852 | Q25: 55.004444 | R25: 63.679636 | S25: 50.30673 | T25: 64.170732 | U25: 55.357627 | V25: 64.443543 | W25: 55.661376 | X25: 64.584698 | Y25: 4696.2852 | Z25: 29.879196 | AA25: 37.880387 | AB25: 36.796127 | AD25: 55.135578 | AE25: 64.544005 | AF25: 32.192312 | AG25: 38.784959 | AH25: 37.373901 | AI25: 49.703681 | AJ25: 54.613994 | AK25: 42.716948 | AL25: 40.607174 | AM25: 58.301998 | AN25: 33.496127 | AO25: 57.215119 | AP25: 67.835323 | AQ25: 68.568639 | AR25: 41.210151 | AU25: 56.429343 | AV25: 63.361327 | AW25: 39.975184 | AX25: 13.87 | AY25: 32.400629 | AZ25: 87.670608 | BA25: -2.1554525 | BB25: 748.78378 | BC25: 746.62832
A26: 1994Q2 | B26: 108.77435 | C26: 109.64331 | D26: 54.751041 | E26: 68.739901 | F26: -13.97817 | G26: -0.28879549 | H26: 6.9597779 | I26: 4.3642008 | J26: 31.809771 | K26: 27.508793 | L26: 27.066818 | M26: 37.901309 | N26: 34.999701 | O26: 84.641415 | P26: 5.2586926 | Q26: 55.486939 | R26: 64.164266 | S26: 51.330566 | T26: 65.314858 | U26: 55.976299 | V26: 65.00473 | W26: 56.252092 | X26: 65.131973 | Y26: 4840.1622 | Z26: 30.899304 | AA26: 39.054808 | AB26: 38.119965 | AD26: 55.740955 | AE26: 65.20271 | AF26: 33.8106 | AG26: 40.031659 | AH26: 38.58444 | AI26: 51.592128 | AJ26: 73.330981 | AK26: 43.818486 | AL26: 43.96514 | AM26: 60.367451 | AN26: 38.545627 | AO26: 57.775896 | AP26: 68.316383 | AQ26: 66.832474 | AR26: 44.029156 | AU26: 57.526776 | AV26: 57.867371 | AW26: 43.007813 | AX26: 16.27 | AY26: 37.247286 | AZ26: 96.131796 | BA26: 1.2714055 | BB26: 796.94559 | BC26: 798.217
A27: 1994Q3 | B27: 107.85682 | C27: 109.41925 | D27: 55.792834 | E27: 69.810736 | F27: -11.579537 | G27: -0.22999331 | H27: 7.5210742 | I27: 4.6320622 | J27: 34.013745 | K27: 28.074749 | L27: 28.066447 | M27: 40.157584 | N27: 36.802396 | O27: 84.779237 | P27: 5.2480783 | Q27: 56.435045 | R27: 64.892774 | S27: 52.01315 | T27: 66.070513 | U27: 56.702932 | V27: 65.701311 | W27: 56.951785 | X27: 65.814704 | Y27: 5034.7279 | Z27: 31.71023 | AA27: 40.020234 | AB27: 38.971956 | AD27: 56.330936 | AE27: 65.772738 | AF27: 34.770004 | AG27: 41.16815 | AH27: 39.60127 | AI27: 53.248013 | AJ27: 118.69993 | AK27: 45.865544 | AL27: 46.317076 | AM27: 61.862273 | AN27: 41.413241 | AO27: 58.381509 | AP27: 68.814325 | AQ27: 65.424484 | AR27: 48.093674 | AU27: 59.543089 | AV27: 56.124686 | AW27: 44.142348 | AX27: 17.05 | AY27: 37.902343 | AZ27: 96.457375 | BA27: -3.3664787 | BB27: 844.76697 | BC27: 841.4005
A28: 1994Q4 | B28: 109.98042 | C28: 111.49418 | D28: 56.993701 | E28: 71.272003 | F28: -29.106937 | G28: -0.56613454 | H28: 7.8544488 | I28: 5.0711117 | J28: 33.337011 | K28: 28.492526 | L28: 28.186371 | M28: 38.557301 | N28: 35.748417 | O28: 85.059932 | P28: 5.0782535 | Q28: 57.148192 | R28: 65.50151 | S28: 53.285493 | T28: 67.194471 | U28: 57.396018 | V28: 66.311079 | W28: 57.619736 | X28: 66.411255 | Y28: 5141.3462 | Z28: 33.581246 | AA28: 41.657732 | AB28: 40.614016 | AD28: 57.040181 | AE28: 66.411186 | AF28: 36.09869 | AG28: 42.324993 | AH28: 40.796419 | AI28: 53.890599 | AJ28: 105.66132 | AK28: 48.454747 | AL28: 48.203235 | AM28: 62.92802 | AN28: 43.904545 | AO28: 59.005054 | AP28: 69.330158 | AQ28: 66.072537 | AR28: 55.404847 | AU28: 60.986447 | AV28: 54.790314 | AW28: 43.626638 | AX28: 16.603333 | AY28: 36.697972 | AZ28: 95.652185 | BA28: -10.118334 | BB28: 894.66472 | BC28: 884.54638
A29: 1995Q1 | B29: 110.59681 | C29: 112.2343 | D29: 57.445947 | E29: 71.613688 | F29: -10.343759 | G29: -0.14646236 | H29: 7.6740672 | I29: 6.9718789 | J29: 32.569764 | K29: 28.802973 | L29: 28.271585 | M29: 38.667632 | N29: 34.74634 | O29: 85.144935 | P29: 5.4197161 | Q29: 57.540985 | R29: 65.806257 | S29: 53.26313 | T29: 67.118094 | U29: 57.980309 | V29: 66.776957 | W29: 58.187639 | X29: 66.867122 | Y29: 7062.4011 | Z29: 34.203493 | AA29: 42.361249 | AB29: 41.174644 | AC29: 39.613488 | AD29: 57.364061 | AE29: 66.679281 | AF29: 37.095588 | AG29: 43.310238 | AH29: 41.863445 | AI29: 55.701556 | AJ29: 99.400901 | AK29: 53.598526 | AL29: 49.916911 | AM29: 63.902252 | AN29: 46.117104 | AO29: 59.668045 | AP29: 69.963963 | AQ29: 67.625323 | AR29: 58.908725 | AU29: 62.971284 | AV29: 56.01934 | AW29: 45.18608 | AX29: 17.223333 | AY29: 37.416993 | AZ29: 104.54496 | BA29: 8.6691288 | BB29: 929.07269 | BC29: 937.74182
A30: 1995Q2 | B30: 110.5291 | C30: 112.17225 | D30: 57.89591 | E30: 72.033505 | F30: -19.366068 | G30: -0.25910504 | H30: 6.9652833 | I30: 7.5975461 | J30: 33.879404 | K30: 29.466038 | L30: 28.671096 | M30: 40.699816 | N30: 36.401407 | O30: 85.303041 | P30: 5.4469028 | Q30: 57.961986 | R30: 66.324699 | S30: 53.982813 | T30: 67.498994 | U30: 58.369817 | V30: 67.138526 | W30: 58.529023 | X30: 67.209779 | Y30: 7474.2151 | Z30: 35.125243 | AA30: 43.239657 | AB30: 42.227034 | AC30: 40.243147 | AD30: 57.941713 | AE30: 67.244003 | AF30: 37.777109 | AG30: 43.946874 | AH30: 42.360295 | AI30: 56.020016 | AJ30: 97.361764 | AK30: 54.876597 | AL30: 51.580392 | AM30: 64.846073 | AN30: 48.326914 | AO30: 60.744248 | AP30: 70.771652 | AQ30: 65.877854 | AR30: 56.225819 | AU30: 61.921823 | AV30: 59.503206 | AW30: 47.483203 | AX30: 18.176667 | AY30: 37.633271 | AZ30: 107.96797 | BA30: -6.9513935 | BB30: 986.80182 | BC30: 979.85042
A31: 1995Q3 | B31: 110.21137 | C31: 112.01949 | D31: 58.153007 | E31: 72.119758 | F31: -14.015629 | G31: -0.18898649 | H31: 6.6409069 | I31: 6.4321911 | J31: 36.778788 | K31: 30.124828 | L31: 29.226492 | M31: 42.487474 | N31: 39.575076 | O31: 85.502316 | P31: 5.5107129 | Q31: 58.522959 | R31: 66.738848 | S31: 53.973716 | T31: 68.07629 | U31: 58.875356 | V31: 67.670022 | W31: 59.007505 | X31: 67.732366 | Y31: 7416.2067 | Z31: 35.620379 | AA31: 43.87497 | AB31: 42.919116 | AC31: 40.856012 | AD31: 58.350402 | AE31: 67.669074 | AF31: 38.159647 | AG31: 44.603565 | AH31: 43.553829 | AI31: 54.978679 | AJ31: 86.846148 | AK31: 57.103534 | AL31: 53.00529 | AM31: 65.637784 | AN31: 50.189574 | AO31: 61.65237 | AP31: 71.49117 | AQ31: 69.105941 | AR31: 58.779071 | AU31: 62.395453 | AV31: 57.041536 | AW31: 44.250506 | AX31: 16.44 | AY31: 35.150398 | AZ31: 96.401307 | BA31: -9.6403854 | BB31: 990.82604 | BC31: 981.18565
A32: 1995Q4 | B32: 109.78129 | C32: 111.55389 | D32: 58.59508 | E32: 72.64615 | F32: -10.551183 | G32: -0.14261878 | H32: 6.2823168 | I32: 6.6678421 | J32: 38.55462 | K32: 30.836202 | L32: 29.741424 | M32: 43.425746 | N32: 41.386892 | O32: 85.631225 | P32: 5.5967743 | Q32: 58.911912 | R32: 67.185584 | S32: 55.274761 | T32: 69.17658 | U32: 59.236154 | V32: 68.038537 | W32: 59.327392 | X32: 68.085707 | Y32: 7398.172 | Z32: 36.276773 | AA32: 44.72738 | AB32: 43.641685 | AC32: 41.052738 | AD32: 58.699765 | AE32: 68.061492 | AF32: 38.639988 | AG32: 45.112154 | AH32: 44.017194 | AI32: 56.490424 | AJ32: 77.718999 | AK32: 56.156185 | AL32: 54.054033 | AM32: 66.276855 | AN32: 51.550011 | AO32: 62.421664 | AP32: 72.109816 | AQ32: 72.025159 | AR32: 56.156229 | AU32: 63.280644 | AV32: 64.942259 | AW32: 46.668545 | AX32: 16.976667 | AY32: 36.87293 | AZ32: 96.309526 | BA32: -7.6068583 | BB32: 1002.1575 | BC32: 994.55067
A33: 1996Q1 | B33: 108.90941 | C33: 110.15735 | D33: 59.118182 | E33: 73.022688 | F33: -19.15674 | G33: -0.25957522 | H33: 6.1318475 | I33: 6.6490072 | J33: 41.849177 | K33: 31.501342 | L33: 30.179236 | M33: 45.361077 | N33: 43.812214 | O33: 86.207752 | P33: 5.5523826 | Q33: 59.671018 | R33: 67.778858 | S33: 55.653223 | T33: 69.850308 | U33: 59.79031 | V33: 68.556434 | W33: 59.818727 | X33: 68.580266 | Y33: 7380.0342 | Z33: 37.125532 | AA33: 45.696284 | AB33: 44.688911 | AC33: 41.567792 | AD33: 59.185401 | AE33: 68.551723 | AF33: 39.485932 | AG33: 45.923624 | AH33: 44.965898 | AI33: 59.29158 | AJ33: 72.893951 | AK33: 54.35076 | AL33: 54.986237 | AM33: 67.014294 | AN33: 52.693056 | AO33: 63.322446 | AP33: 72.768145 | AQ33: 75.317844 | AR33: 54.195055 | AU33: 64.324933 | AV33: 80.384877 | AW33: 52.010965 | AX33: 18.313333 | AY33: 40.492783 | AZ33: 95.380567 | BA33: -12.83216 | BB33: 1017.8364 | BC33: 1005.0043
A34: 1996Q2 | B34: 110.63121 | C34: 112.07654 | D34: 59.928965 | E34: 73.783275 | F34: -29.744221 | G34: -0.39532677 | H34: 6.4650677 | I34: 6.3817603 | J34: 44.339739 | K34: 32.117467 | L34: 30.692988 | M34: 47.644344 | N34: 46.508521 | O34: 86.435519 | P34: 5.5940314 | Q34: 60.141087 | R34: 68.35107 | S34: 56.845127 | T34: 71.667128 | U34: 60.512687 | V34: 69.364214 | W34: 60.541228 | X34: 69.387847 | Y34: 7523.9583 | Z34: 37.697265 | AA34: 46.496292 | AB34: 45.485563 | AC34: 42.197603 | AD34: 59.901172 | AE34: 69.383127 | AF34: 39.979543 | AG34: 46.359238 | AH34: 45.418139 | AI34: 59.763206 | AJ34: 74.435982 | AK34: 53.226851 | AL34: 56.07309 | AM34: 67.760762 | AN34: 53.845636 | AO34: 64.18897 | AP34: 73.363542 | AQ34: 79.149183 | AR34: 53.301133 | AU34: 65.499738 | AV34: 68.800912 | AW34: 51.465461 | AX34: 19.486667 | AY34: 43.647121 | AZ34: 95.292647 | BA34: -21.011862 | BB34: 1025.6018 | BC34: 1004.59
A35: 1996Q3 | B35: 112.26036 | C35: 113.96815 | D35: 60.448728 | E35: 74.527981 | F35: -31.9932 | G35: -0.41888087 | H35: 6.3288935 | I35: 6.2080817 | J35: 44.950803 | K35: 32.704481 | L35: 31.144987 | M35: 47.243705 | N35: 46.381521 | O35: 86.714502 | P35: 5.5358027 | Q35: 60.52784 | R35: 68.750551 | S35: 57.614529 | T35: 72.533278 | U35: 61.038058 | V35: 69.884226 | W35: 61.061763 | X35: 69.905196 | Y35: 7637.7801 | Z35: 38.747864 | AA35: 47.452638 | AB35: 46.391913 | AC35: 42.551209 | AD35: 60.387435 | AE35: 69.8801 | AF35: 41.556594 | AG35: 47.466502 | AH35: 46.273864 | AI35: 58.79486 | AJ35: 68.735574 | AK35: 52.54152 | AL35: 57.014246 | AM35: 68.354431 | AN35: 54.859112 | AO35: 65.037686 | AP35: 73.942394 | AQ35: 75.82815 | AR35: 48.014356 | AU35: 62.640612 | AV35: 66.404608 | AW35: 53.232078 | AX35: 20.63 | AY35: 46.055409 | AZ35: 94.600387 | BA35: -14.070196 | BB35: 1033.5062 | BC35: 1019.436
A36: 1996Q4 | B36: 112.53552 | C36: 114.24661 | D36: 61.200926 | E36: 75.414955 | F36: -31.26305 | G36: -0.40663765 | H36: 5.860278 | I36: 5.9511492 | J36: 46.664233 | K36: 33.409491 | L36: 31.769451 | M36: 48.347118 | N36: 47.963509 | O36: 86.912764 | P36: 5.4588106 | Q36: 61.164649 | R36: 69.372905 | S36: 58.639109 | T36: 73.22442 | U36: 61.708152 | V36: 70.540688 | W36: 61.726113 | X36: 70.558463 | Y36: 7688.1837 | Z36: 39.782086 | AA36: 48.630669 | AB36: 47.576763 | AC36: 43.115528 | AD36: 60.973696 | AE36: 70.43858 | AF36: 42.566411 | AG36: 49.175892 | AH36: 47.459011 | AI36: 60.509418 | AJ36: 66.050179 | AK36: 52.5987 | AL36: 57.827717 | AM36: 68.977769 | AN36: 55.730208 | AO36: 65.717896 | AP36: 74.469082 | AQ36: 70.266876 | AR36: 48.245684 | AU36: 59.807898 | AV36: 82.453389 | AW36: 61.524147 | AX36: 23.063333 | AY36: 51.800672 | AZ36: 93.519181 | BA36: -16.305219 | BB36: 1064.5153 | BC36: 1048.2101
A37: 1997Q1 | B37: 114.35325 | C37: 116.11163 | D37: 62.16156 | E37: 76.633358 | F37: -16.348082 | G37: -0.21789417 | H37: 5.8351904 | I37: 5.860732 | J37: 50.437048 | K37: 34.057075 | L37: 32.709297 | M37: 49.419648 | N37: 50.994752 | O37: 87.201869 | P37: 5.5508306 | Q37: 61.71576 | R37: 70.000269 | S37: 58.604369 | T37: 73.131841 | U37: 62.137682 | V37: 70.969791 | W37: 62.153062 | X37: 70.986043 | Y37: 7502.7623 | Z37: 40.709637 | AA37: 49.811161 | AB37: 48.693111 | AC37: 43.045465 | AD37: 61.425343 | AE37: 70.833189 | AF37: 43.525453 | AG37: 50.424304 | AH37: 48.704487 | AI37: 59.386114 | AJ37: 77.01896 | AK37: 51.141847 | AL37: 58.792362 | AM37: 69.631526 | AN37: 56.864809 | AO37: 66.807361 | AP37: 75.128804 | AQ37: 73.523529 | AR37: 52.491388 | AU37: 62.148736 | AV37: 73.904389 | AW37: 55.390052 | AX37: 21.083333 | AY37: 49.031321 | AZ37: 93.501119 | BA37: -21.902095 | BB37: 1071.7711 | BC37: 1049.869
A38: 1997Q2 | B38: 116.078 | C38: 117.9135 | D38: 63.392727 | E38: 77.78397 | F38: 0.76504108 | G38: 0.010116391 | H38: 5.8710191 | I38: 5.586599 | J38: 57.485343 | K38: 34.768736 | L38: 33.39039 | M38: 56.575687 | N38: 58.348607 | O38: 87.452471 | P38: 5.6134673 | Q38: 61.955824 | R38: 70.124885 | S38: 59.551908 | T38: 74.238305 | U38: 62.921627 | V38: 71.767504 | W38: 62.933842 | X38: 71.781846 | Y38: 7562.3916 | Z38: 41.605926 | AA38: 50.891584 | AB38: 49.917758 | AC38: 43.124301 | AD38: 61.961196 | AE38: 71.432315 | AF38: 45.446064 | AG38: 52.4975 | AH38: 50.523431 | AI38: 56.137209 | AJ38: 96.610058 | AK38: 50.423874 | AL38: 59.668473 | AM38: 70.26476 | AN38: 57.675423 | AO38: 67.832996 | AP38: 75.838525 | AQ38: 70.2598 | AR38: 52.592666 | AU38: 60.967208 | AV38: 66.16305 | AW38: 49.150741 | AX38: 18.49 | AY38: 43.384475 | AZ38: 90.148852 | BA38: -6.9623738 | BB38: 1081.4362 | BC38: 1074.4738
A39: 1997Q3 | B39: 116.6013 | C39: 118.69529 | D39: 64.354334 | E39: 78.921472 | F39: -2.3606312 | G39: -0.031235372 | H39: 5.468803 | I39: 5.5438967 | J39: 58.362527 | K39: 35.404611 | L39: 33.983995 | M39: 57.396383 | N39: 60.591781 | O39: 87.675553 | P39: 5.5951809 | Q39: 62.740256 | R39: 70.810033 | S39: 60.570131 | T39: 75.346529 | U39: 63.557049 | V39: 72.405358 | W39: 63.566787 | X39: 72.418172 | Y39: 7557.5574 | Z39: 42.858458 | AA39: 52.202238 | AB39: 51.193573 | AC39: 43.571554 | AD39: 62.60277 | AE39: 72.082809 | AF39: 46.462245 | AG39: 53.482026 | AH39: 51.355924 | AI39: 54.662719 | AJ39: 86.421071 | AK39: 49.790313 | AL39: 60.462618 | AM39: 70.841413 | AN39: 58.516026 | AO39: 68.537381 | AP39: 76.33143 | AQ39: 66.78846 | AR39: 51.426611 | AS39: 53.202402 | AT39: 53.180929 | AU39: 57.874991 | AV39: 68.77176 | AW39: 50.016249 | AX39: 18.656667 | AY39: 44.372457 | AZ39: 85.728892 | BA39: -3.6809471 | BB39: 1091.4444 | BC39: 1087.7634
A40: 1997Q4 | B40: 116.70054 | C40: 119.02852 | D40: 64.971298 | E40: 79.52144 | F40: -5.2126556 | G40: -0.069100796 | H40: 5.1667463 | I40: 5.8762279 | J40: 54.747937 | K40: 36.092541 | L40: 34.568498 | M40: 52.544136 | N40: 57.798165 | O40: 87.919965 | P40: 5.5104929 | Q40: 63.360402 | R40: 71.411754 | S40: 61.033145 | T40: 75.94999 | U40: 64.155839 | V40: 72.983395 | W40: 64.164052 | X40: 72.995117 | Y40: 7543.5536 | Z40: 43.900738 | AA40: 52.936126 | AB40: 51.792086 | AC40: 43.929968 | AD40: 63.199322 | AE40: 72.647717 | AF40: 47.217194 | AG40: 54.211339 | AH40: 52.203155 | AI40: 54.304377 | AJ40: 83.096329 | AK40: 46.139714 | AL40: 61.128551 | AM40: 71.338094 | AN40: 59.231227 | AO40: 69.402768 | AP40: 76.943904 | AQ40: 68.439806 | AR40: 47.113442 | AS40: 53.570672 | AT40: 53.393933 | AU40: 56.837809 | AV40: 71.967076 | AW40: 50.639834 | AX40: 18.84 | AY40: 44.710486 | AZ40: 78.368998 | BA40: -7.1594988 | BB40: 1099.6734 | BC40: 1092.5139
A41: 1998Q1 | B41: 117.4632 | C41: 119.91785 | D41: 65.025664 | E41: 79.566364 | F41: -18.078521 | G41: -0.24457642 | H41: 4.9271304 | I41: 7.4976493 | J41: 62.929324 | K41: 36.871013 | L41: 34.962388 | M41: 59.525698 | N41: 66.167295 | O41: 88.266771 | P41: 5.7768512 | Q41: 63.231297 | R41: 71.420069 | S41: 61.226124 | T41: 76.280572 | U41: 64.206867 | V41: 73.065338 | W41: 64.2427 | X41: 73.093995 | Y41: 7391.7675 | Z41: 44.9962 | AA41: 54.012986 | AB41: 51.937909 | AC41: 44.009286 | AD41: 63.175468 | AE41: 72.748453 | AF41: 47.997011 | AG41: 54.719731 | AH41: 52.573134 | AI41: 49.546139 | AJ41: 86.91413 | AK41: 43.958354 | AL41: 62.017529 | AM41: 71.902022 | AN41: 60.184132 | AO41: 70.111872 | AP41: 77.469357 | AQ41: 68.384509 | AR41: 43.564611 | AS41: 51.859083 | AT41: 51.621026 | AU41: 55.887372 | AV41: 62.054169 | AW41: 40.37371 | AX41: 14.163333 | AY41: 34.089059 | AZ41: 73.781556 | BA41: 0.1494878 | BB41: 1067.1002 | BC41: 1067.2496
A42: 1998Q2 | B42: 118.07178 | C42: 120.81904 | D42: 65.081623 | E42: 79.410854 | F42: -14.801952 | G42: -0.19954874 | H42: 4.8083712 | I42: 7.7462742 | J42: 61.431417 | K42: 37.638373 | L42: 35.56453 | M42: 57.089044 | N42: 64.162361 | O42: 88.442774 | P42: 5.8936093 | Q42: 63.970099 | R42: 72.111908 | S42: 61.365065 | T42: 76.659704 | U42: 64.43747 | V42: 73.352784 | W42: 64.484655 | X42: 73.388487 | Y42: 7417.7127 | Z42: 45.123818 | AA42: 54.114537 | AB42: 51.752485 | AC42: 44.686611 | AD42: 63.481512 | AE42: 73.081704 | AF42: 47.584202 | AG42: 54.503489 | AH42: 52.074835 | AI42: 49.078823 | AJ42: 79.300967 | AK42: 43.046364 | AL42: 62.861205 | AM42: 72.415859 | AN42: 61.09868 | AO42: 70.853516 | AP42: 77.94981 | AQ42: 70.307433 | AR42: 42.225152 | AS42: 51.088462 | AT42: 50.798952 | AU42: 56.500684 | AV42: 60.101426 | AW42: 38.343293 | AX42: 13.28 | AY42: 32.111445 | AZ42: 72.865114 | BA42: 1.4245268 | BB42: 1049.7455 | BC42: 1051.17
A43: 1998Q3 | B43: 116.93836 | C43: 119.5873 | D43: 65.116332 | E43: 79.425105 | F43: -20.661722 | G43: -0.27962455 | H43: 4.5047261 | I43: 8.9286266 | J43: 50.896284 | K43: 38.288944 | L43: 36.075034 | M43: 48.697278 | N43: 53.576492 | O43: 88.696532 | P43: 5.9098902 | Q43: 64.728515 | R43: 72.880564 | S43: 61.821381 | T43: 77.413595 | U43: 64.78954 | V43: 73.824981 | W43: 64.850752 | X43: 73.869565 | Y43: 7389.0943 | Z43: 44.879578 | AA43: 54.26012 | AB43: 51.347332 | AC43: 45.429079 | AD43: 63.684017 | AE43: 73.534302 | AF43: 48.225298 | AG43: 54.685938 | AH43: 52.181868 | AI43: 45.974695 | AJ43: 72.218148 | AK43: 40.319462 | AL43: 64.097917 | AM43: 73.074626 | AN43: 62.463923 | AO43: 71.609148 | AP43: 78.420532 | AQ43: 64.359441 | AR43: 40.096272 | AS43: 48.876389 | AT43: 48.580232 | AU43: 52.444719 | AV43: 55.349863 | AW43: 36.615972 | AX43: 13.003333 | AY43: 31.447843 | AZ43: 70.101985 | BA43: 0.7673468 | BB43: 1030.8312 | BC43: 1031.5985
A44: 1998Q4 | B44: 113.38042 | C44: 116.74823 | D44: 65.424391 | E44: 79.598083 | F44: -24.617608 | G44: -0.3161677 | H44: 4.046062 | I44: 7.4187552 | J44: 59.118914 | K44: 39.213897 | L44: 36.857951 | M44: 59.775858 | N44: 63.363195 | O44: 88.921856 | P44: 5.8994851 | Q44: 64.797339 | R44: 73.257828 | S44: 61.78608 | T44: 77.831101 | U44: 65.338559 | V44: 74.423611 | W44: 65.403293 | X44: 74.470294 | Y44: 7786.2501 | Z44: 44.465351 | AA44: 54.41223 | AB44: 51.203746 | AC44: 46.275582 | AD44: 64.278506 | AE44: 74.249203 | AF44: 48.202972 | AG44: 54.936971 | AH44: 52.433514 | AI44: 44.626097 | AJ44: 70.78806 | AK44: 39.422316 | AL44: 65.601615 | AM44: 73.929981 | AN44: 64.026194 | AO44: 73.15084 | AP44: 79.122162 | AQ44: 64.721519 | AR44: 38.253864 | AS44: 45.934115 | AT44: 45.870785 | AU44: 51.943945 | AV44: 52.310551 | AW44: 34.041018 | AX44: 11.85 | AY44: 27.468552 | AZ44: 68.594988 | BA44: 0.9526312 | BB44: 1052.4381 | BC44: 1053.3907
A45: 1999Q1 | B45: 115.0832 | C45: 119.3204 | D45: 66.092996 | E45: 80.348174 | F45: -45.935228 | G45: -0.59701617 | H45: 4.3039749 | I45: 5.8599847 | J45: 65.422299 | K45: 39.899845 | L45: 37.857433 | M45: 62.717817 | N45: 69.250893 | O45: 89.128618 | P45: 6.1854302 | Q45: 65.76315 | R45: 73.998229 | S45: 62.25526 | T45: 78.308562 | U45: 65.88929 | V45: 74.884141 | W45: 65.941581 | X45: 74.923279 | Y45: 7694.1347 | Z45: 44.845832 | AA45: 55.165306 | AB45: 51.825876 | AC45: 47.198551 | AD45: 64.878471 | AE45: 74.794349 | AF45: 48.430966 | AG45: 55.184721 | AH45: 52.78947 | AI45: 42.921981 | AJ45: 66.978686 | AK45: 38.783476 | AL45: 66.341298 | AM45: 74.354784 | AN45: 64.87127 | AO45: 73.873067 | AP45: 79.570756 | AQ45: 60.765877 | AR45: 36.87191 | AS45: 48.257645 | AT45: 48.451932 | AU45: 49.775669 | AV45: 49.435003 | AW45: 33.008298 | AX45: 11.643333 | AY45: 27.325469 | AZ45: 70.010596 | BA45: -24.285886 | BB45: 1051.7935 | BC45: 1027.5076
A46: 1999Q2 | B46: 116.52788 | C46: 120.78157 | D46: 67.031786 | E46: 81.132966 | F46: -33.041522 | G46: -0.43338733 | H46: 4.5456086 | I46: 5.0716027 | J46: 73.682984 | K46: 40.754547 | L46: 38.776597 | M46: 69.086703 | N46: 77.351934 | O46: 89.250494 | P46: 6.1453808 | Q46: 66.532865 | R46: 74.782049 | S46: 63.18382 | T46: 79.347229 | U46: 66.527361 | V46: 75.464053 | W46: 66.568552 | X46: 75.49652 | Y46: 7624.0166 | Z46: 46.134961 | AA46: 56.597775 | AB46: 53.398258 | AC46: 47.955118 | AD46: 65.661046 | AE46: 75.4657 | AF46: 49.094331 | AG46: 56.068565 | AH46: 53.688101 | AI46: 46.056831 | AJ46: 60.791796 | AK46: 38.115968 | AL46: 67.05873 | AM46: 74.866877 | AN46: 65.659886 | AO46: 74.498618 | AP46: 80.007779 | AQ46: 58.956356 | AR46: 39.258281 | AS46: 50.849641 | AT46: 51.019778 | AU46: 48.978016 | AV46: 55.833913 | AW46: 41.831411 | AX46: 16.03 | AY46: 38.578353 | AZ46: 70.653989 | BA46: -32.794948 | BB46: 1075.7598 | BC46: 1042.9648
A47: 1999Q3 | B47: 116.56145 | C47: 120.60901 | D47: 68.120553 | E47: 82.3361 | F47: -46.793636 | G47: -0.60150293 | H47: 5.025422 | I47: 4.8206515 | J47: 71.104663 | K47: 41.49521 | L47: 39.509312 | M47: 68.023688 | N47: 74.385675 | O47: 89.380434 | P47: 6.0754923 | Q47: 67.012367 | R47: 75.454445 | S47: 63.947939 | T47: 80.346698 | U47: 67.353218 | V47: 76.352561 | W47: 67.394515 | X47: 76.385024 | Y47: 7779.4527 | Z47: 47.488409 | AA47: 58.214495 | AB47: 55.026274 | AC47: 48.768926 | AD47: 66.29726 | AE47: 76.240239 | AF47: 50.906649 | AG47: 57.922093 | AH47: 55.666969 | AI47: 49.677326 | AJ47: 54.650712 | AK47: 36.581733 | AL47: 67.822676 | AM47: 75.43255 | AN47: 66.487134 | AO47: 75.061282 | AP47: 80.416476 | AQ47: 57.647374 | AR47: 43.441775 | AS47: 52.891932 | AT47: 53.025041 | AU47: 48.631986 | AV47: 63.302413 | AW47: 51.189383 | AX47: 20.443333 | AY47: 48.725894 | AZ47: 70.689782 | BA47: -31.540408 | BB47: 1130.1733 | BC47: 1098.6328
A48: 1999Q4 | B48: 117.26961 | C48: 121.19173 | D48: 69.506503 | E48: 83.925853 | F48: -55.293609 | G48: -0.69047616 | H48: 5.2041171 | I48: 4.9728171 | J48: 84.788143 | K48: 42.398472 | L48: 40.983033 | M48: 81.848512 | N48: 90.212154 | O48: 89.563436 | P48: 5.974519 | Q48: 67.99791 | R48: 76.341608 | S48: 64.76155 | T48: 81.135917 | U48: 68.340634 | V48: 77.366935 | W48: 68.377846 | X48: 77.396864 | Y48: 8008.0403 | Z48: 49.089381 | AA48: 60.032215 | AB48: 56.912719 | AC48: 49.851726 | AD48: 67.237798 | AE48: 77.252671 | AF48: 52.804162 | AG48: 59.810252 | AH48: 57.49092 | AI48: 53.274179 | AJ48: 60.017196 | AK48: 35.769861 | AL48: 68.540553 | AM48: 76.001093 | AN48: 67.270827 | AO48: 75.752552 | AP48: 80.908701 | AQ48: 57.785426 | AR48: 45.986144 | AS48: 55.239865 | AT48: 55.281109 | AU48: 50.205889 | AV48: 67.638583 | AW48: 57.712382 | AX48: 23.806667 | AY48: 55.977589 | AZ48: 72.781576 | BA48: -33.072864 | BB48: 1191.5529 | BC48: 1158.48
A49: 2000Q1 | B49: 118.40051 | C49: 123.59442 | D49: 70.58263 | E49: 84.93457 | F49: -67.238346 | G49: -0.83728812 | H49: 5.4509674 | I49: 5.1075743 | J49: 87.156983 | K49: 43.151065 | L49: 41.5648 | M49: 83.006066 | N49: 92.735521 | O49: 89.923842 | P49: 6.0510076 | Q49: 69.01074 | R49: 77.359574 | S49: 66.583569 | T49: 83.008342 | U49: 69.263485 | V49: 78.24454 | W49: 69.290452 | X49: 78.269029 | Y49: 8030.4908 | Z49: 51.134099 | AA49: 61.937524 | AB49: 58.888847 | AC49: 50.633841 | AD49: 68.219054 | AE49: 78.146005 | AF49: 54.583188 | AG49: 61.653527 | AH49: 59.351962 | AI49: 57.367482 | AJ49: 52.952902 | AK49: 36.22532 | AL49: 69.239647 | AM49: 76.604392 | AN49: 68.027565 | AO49: 76.43193 | AP49: 81.377934 | AQ49: 59.361895 | AR49: 49.768508 | AS49: 54.003824 | AT49: 54.22236 | AU49: 51.801246 | AV49: 79.369951 | AW49: 65.418899 | AX49: 26.616667 | AY49: 63.799923 | AZ49: 74.002809 | BA49: -57.222169 | BB49: 1250.9536 | BC49: 1193.7314
A50: 2000Q2 | B50: 118.13922 | C50: 123.22643 | D50: 72.093654 | E50: 86.540061 | F50: -64.042429 | G50: -0.79972699 | H50: 5.2424908 | I50: 5.4379665 | J50: 83.071567 | K50: 43.847011 | L50: 42.036893 | M50: 79.743716 | N50: 90.238298 | O50: 90.164843 | P50: 5.8703801 | Q50: 69.574526 | R50: 77.930831 | S50: 67.426386 | T50: 83.976344 | U50: 70.09952 | V50: 79.135579 | W50: 70.130253 | X50: 79.161871 | Y50: 8008.0364 | Z50: 52.318478 | AA50: 63.745975 | AB50: 60.578575 | AC50: 51.395852 | AD50: 68.990845 | AE50: 78.986462 | AF50: 56.219725 | AG50: 63.522038 | AH50: 61.272221 | AI50: 59.06044 | AJ50: 49.023264 | AK50: 38.323365 | AL50: 69.843936 | AM50: 77.019459 | AN50: 68.69372 | AO50: 76.961547 | AP50: 81.765754 | AQ50: 61.749511 | AR50: 47.798111 | AS50: 53.834095 | AT50: 54.164046 | AU50: 52.450254 | AV50: 95.560348 | AW50: 68.621905 | AX50: 26.766667 | AY50: 65.429664 | AZ50: 75.650981 | BA50: -67.168944 | BB50: 1287.665 | BC50: 1220.4961
... A128: 2019Q4 | B128: 110.02359 | C128: 113.65779 | D128: 132.44902 | E128: 123.62322 | F128: 138.0866 | G128: 0.68507905 | H128: 1.7904125 | I128: 2.740323 | J128: 218.71011 | K128: 195.71894 | L128: 221.01851 | M128: 141.28138 | N128: 170.88263 | O128: 107.84061 | P128: 4.999095 | Q128: 140.20766 | R128: 129.19678 | S128: 142.04764 | T128: 134.50736 | U128: 137.92095 | V128: 128.38093 | W128: 137.90913 | X128: 128.37205 | Y128: 20156.302 | Z128: 143.56294 | AA128: 138.59441 | AB128: 139.55262 | AC128: 72.976426 | AD128: 137.82737 | AE128: 127.90924 | AF128: 144.42699 | AG128: 139.87747 | AH128: 141.36958 | AI128: 116.6143 | AJ128: 88.242411 | AK128: 108.86301 | AL128: 131.86562 | AM128: 125.27519 | AN128: 132.77873 | AO128: 129.82598 | AP128: 123.87033 | AQ128: 100.05663 | AR128: 130.03397 | AS128: 49.92129 | AT128: 49.999422 | AU128: 109.20895 | AV128: 89.021923 | AW128: 127.32594 | AX128: 60.370842 | AY128: 142.4523 | AZ128: 98.079961 | BA128: -0.758268 | BB128: 3640.9065 | BC128: 3628.8735
A129: 2020Q1 | I129: 2.2667195 | W129: 133.71841 | X129: 125.31326 | AN129: 133.79096
A130: 2020Q2 | W130: 136.1786 | X130: 126.03583 | AN130: 133.71699
A131: 2020Q3 | W131: 138.69282 | X131: 128.03389 | AN131: 134.36076
A132: 2020Q4 | W132: 140.55385 | X132: 129.56916 | AN132: 135.40267

Sheet Sheet1

Sheet Commodity_Prices
A1: EcDatabase | B1: ID:PRIMARY_COMMODITY_PRICE_SYSTEM_LIVE | C1: ID:PRIMARY_COMMODITY_PRICE_SYSTEM_LIVE | D1: ID:PRIMARY_COMMODITY_PRICE_SYSTEM_LIVE | E1: ID:PRIMARY_COMMODITY_PRICE_SYSTEM_LIVE | F1: ID:PRIMARY_COMMODITY_PRICE_SYSTEM_LIVE | G1: ID:PRIMARY_COMMODITY_PRICE_SYSTEM_LIVE | H1: ID:PRIMARY_COMMODITY_PRICE_SYSTEM_LIVE | I1: ID:PRIMARY_COMMODITY_PRICE_SYSTEM_LIVE | J1: ID:PRIMARY_COMMODITY_PRICE_SYSTEM_LIVE | K1: ID:PRIMARY_COMMODITY_PRICE_SYSTEM_LIVE | L1: ID:PRIMARY_COMMODITY_PRICE_SYSTEM_LIVE | M1: ID:PRIMARY_COMMODITY_PRICE_SYSTEM_LIVE | N1: ID:PRIMARY_COMMODITY_PRICE_SYSTEM_LIVE | O1: ID:PRIMARY_COMMODITY_PRICE_SYSTEM_LIVE | P1: ID:PRIMARY_COMMODITY_PRICE_SYSTEM_LIVE | Q1: ID:PRIMARY_COMMODITY_PRICE_SYSTEM_LIVE | R1: ID:PRIMARY_COMMODITY_PRICE_SYSTEM_LIVE | S1: ID:PRIMARY_COMMODITY_PRICE_SYSTEM_LIVE | T1: ID:PRIMARY_COMMODITY_PRICE_SYSTEM_LIVE
A2: Series_code | B2: PALUM_USD.M | C2: PCOALAU_USD.M | D2: PCOALSA_USD.M | E2: PCOPP_USD.M | F2: PGOLD_USD.M | G2: PIORECR_USD.M | H2: PNGASEU_USD.M | I2: PNGASJP_USD.M | J2: PNGASUS_USD.M | K2: PNICK_USD.M | L2: POILBRE_USD.M | M2: POILDUB_USD.M | N2: POILWTI_USD.M | O2: PPALLA_USD.M | P2: PPLAT_USD.M | Q2: PSILVER_USD.M | R2: POILAPSP_USD.M | S2: PALLFNF_Index.M | T2: PFOOD_Index.M
A3: Commodity | B3: PALUM | C3: PCOALAU | D3: PCOALSA | E3: PCOPP | F3: PGOLD | G3: PIORECR | H3: PNGASEU | I3: PNGASJP | J3: PNGASUS | K3: PNICK | L3: POILBRE | M3: POILDUB | N3: POILWTI | O3: PPALLA | P3: PPLAT | Q3: PSILVER | R3: POILAPSP | S3: PALLFNF | T3: PFOOD
A4: Data Type | B4: USD | C4: USD | D4: USD | E4: USD | F4: USD | G4: USD | H4: USD | I4: USD | J4: USD | K4: USD | L4: USD | M4: USD | N4: USD | O4: USD | P4: USD | Q4: USD | R4: USD | S4: Index | T4: Index
A5: Frequency | B5: Monthly | C5: Monthly | D5: Monthly | E5: Monthly | F5: Monthly | G5: Monthly | H5: Monthly | I5: Monthly | J5: Monthly | K5: Monthly | L5: Monthly | M5: Monthly | N5: Monthly | O5: Monthly | P5: Monthly | Q5: Monthly | R5: Monthly | S5: Monthly | T5: Monthly
A6: Scale | B6: Units | C6: Units | D6: Units | E6: Units | F6: Units | G6: Units | H6: Units | I6: Units | J6: Units | K6: Units | L6: Units | M6: Units | N6: Units | O6: Units | P6: Units | Q6: Units | R6: Units | S6: Units | T6: Units
A7: Display_scale | B7: Units | C7: Units | D7: Units | E7: Units | F7: Units | G7: Units | H7: Units | I7: Units | J7: Units | K7: Units | L7: Units | M7: Units | N7: Units | O7: Units | P7: Units | Q7: Units | R7: Units | S7: Units | T7: Units
A8: 1990M1 | B8: 1528 | C8: 38 | D8: 31 | E8: 2365.557 | F8: 409.81906 | G8: 14.05 | H8: 1.73 | K8: 7056 | L8: 21.25 | M8: 17.57 | N8: 22.96 | O8: 135.41304 | P8: 497.65652 | Q8: 5.2475455 | R8: 20.59
A9: 1990M2 | B9: 1454 | C9: 38 | D9: 31 | E9: 2358.9434 | F9: 417.18106 | G9: 14.05 | H9: 1.73 | K9: 6977 | L9: 19.93 | M9: 17 | N9: 22.12 | O9: 135.4375 | P9: 516.1 | Q9: 5.28935 | R9: 19.68
A10: 1990M3 | B10: 1567 | C10: 38 | D10: 31 | E10: 2625.7027 | F10: 392.70334 | G10: 14.05 | H10: 1.73 | K10: 9267 | L10: 18.37 | M10: 15.59 | N10: 20.41 | O10: 130.28182 | P10: 497.06364 | Q10: 5.0768864 | R10: 18.12
A11: 1990M4 | B11: 1526 | C11: 38 | D11: 31 | E11: 2685.2269 | F11: 374.29211 | G11: 14.05 | H11: 2.1099998 | K11: 8939 | L11: 16.49 | M11: 14.05 | N11: 18.43 | O11: 126.95952 | P11: 478.14762 | Q11: 5.059 | R11: 16.32
A12: 1990M5 | B12: 1527 | C12: 40.5 | D12: 32.5 | E12: 2740.3424 | F12: 369.19763 | G12: 14.05 | H12: 2.1099998 | K12: 8698 | L12: 16.34 | M12: 14.03 | N12: 18.25 | O12: 119.64348 | P12: 488.55435 | Q12: 5.0730476 | R12: 16.21
A13: 1990M6 | B13: 1566 | C13: 40.5 | D13: 34 | E13: 2583.8149 | F13: 352.52762 | G13: 14.05 | H13: 2.1099998 | K13: 8422 | L13: 15.05 | M13: 13.05 | N13: 16.69 | O13: 115.45952 | P13: 481.11429 | Q13: 4.9182857 | R13: 14.93
A14: 1990M7 | B14: 1571 | C14: 40.5 | D14: 34 | E14: 2769.003 | F14: 362.49857 | G14: 14.05 | H14: 1.9199999 | K14: 9318 | L14: 17.14 | M14: 14.88 | N14: 18.42 | O14: 117.09318 | P14: 478.78864 | Q14: 4.871 | R14: 16.81
A15: 1990M8 | B15: 1782 | C15: 40.5 | D15: 34 | E15: 2956.3956 | F15: 394.63181 | G15: 14.05 | H15: 1.9199999 | K15: 10957 | L15: 27.32 | M15: 25.06 | N15: 27.23 | O15: 115.41304 | P15: 492.73478 | Q15: 5.0018409 | R15: 26.54
A16: 1990M9 | B16: 2067 | C16: 40.5 | D16: 34 | E16: 3040.1708 | F16: 389.755 | G16: 14.05 | H16: 1.9199999 | K16: 10844 | L16: 35.03 | M16: 32.03 | N16: 33.8 | O16: 105.066 | P16: 461.665 | Q16: 4.803775 | R16: 33.62
A17: 1990M10 | B17: 1946 | C17: 40.5 | D17: 34 | E17: 2742.547 | F17: 380.99521 | G17: 14.05 | H17: 2.3799998 | K17: 9145 | L17: 36.09 | M17: 32.34 | N17: 36.13 | O17: 95.493478 | P17: 424.94565 | Q17: 4.3891087 | R17: 34.85
A18: 1990M11 | B18: 1618 | C18: 40.5 | D18: 34 | E18: 2583.8149 | F18: 381.7941 | G18: 14.05 | H18: 2.3799998 | K18: 8587 | L18: 33.2 | M18: 28.98 | N18: 32.44 | O18: 93.586364 | P18: 422.23636 | Q18: 4.1728864 | R18: 31.54
A19: 1990M12 | B19: 1522 | C19: 40.5 | D19: 34 | E19: 2484.607 | F19: 376.68234 | G19: 14.05 | H19: 2.3799998 | K19: 8158 | L19: 28.32 | M19: 24.18 | N19: 27.33 | O19: 89.078571 | P19: 420.07143 | Q19: 4.0788158 | R19: 26.61
A20: 1991M1 | B20: 1515 | C20: 40.5 | D20: 34 | E20: 2447.1282 | F20: 383.70227 | G20: 15.03 | H20: 2.9599999 | J20: 1.43 | K20: 8569 | L20: 23.54 | M20: 19.68 | N20: 25.2 | O20: 86.765217 | P20: 407.83565 | Q20: 4.0504091 | R20: 22.81
A21: 1991M2 | B21: 1505 | C21: 40.5 | D21: 34 | E21: 2447.1282 | F21: 364.39166 | G21: 15.03 | H21: 2.9599999 | J21: 1.41375 | K21: 8672 | L21: 19.58 | M21: 15.51 | N21: 20.5 | O21: 84.3925 | P21: 386.7875 | Q21: 3.73765 | R21: 18.53
A22: 1991M3 | B22: 1496 | C22: 39.5 | D22: 31 | E22: 2409.6494 | F22: 362.7608 | G22: 15.03 | H22: 2.9599999 | J22: 1.356 | K22: 8700 | L22: 19.13 | M22: 15.65 | N22: 19.87 | O22: 86.419048 | P22: 399.98571 | Q22: 3.948125 | R22: 18.21
A23: 1991M4 | B23: 1392 | C23: 39.5 | D23: 31 | E23: 2471.3793 | F23: 358.32333 | G23: 15.03 | H23: 3.4100003 | J23: 1.3625 | K23: 9023 | L23: 19.13 | M23: 15.55 | N23: 20.77 | O23: 96.375 | P23: 396.88182 | Q23: 3.9821429 | R23: 18.49
A24: 1991M5 | B24: 1299.95 | C24: 39.5 | D24: 31 | E24: 2340.4247 | F24: 356.96429 | G24: 15.03 | H24: 3.4100003 | J24: 1.336 | K24: 8499.6094 | L24: 19.16 | M24: 15.77 | N24: 21.24 | O24: 95.304348 | P24: 389.63913 | Q24: 4.047 | R24: 18.72
A25: 1991M6 | B25: 1283.55 | C25: 39.5 | D25: 31 | E25: 2218.068 | F25: 366.91 | G25: 15.03 | H25: 3.4100003 | J25: 1.2511667 | K25: 8296.5 | L25: 18.08 | M25: 15.03 | N25: 20.21 | O25: 97.1475 | P25: 376.055 | Q25: 4.3929 | R25: 17.78
A26: 1991M7 | B26: 1297.5466 | C26: 39.5 | D26: 31 | E26: 2231.2553 | F26: 367.79227 | G26: 15.03 | H26: 3.1200002 | J26: 1.1485 | K26: 8515.2012 | L26: 19.42 | M26: 16.13 | N26: 21.52 | O26: 94.487826 | P26: 376.03478 | Q26: 4.3475 | R26: 19.02
A27: 1991M8 | B27: 1259.6934 | C27: 39.5 | D27: 31 | E27: 2236.1868 | F27: 356.66953 | G27: 15.03 | H27: 3.1200002 | J27: 1.3028 | K27: 8154.75 | L27: 19.73 | M27: 16.47 | N27: 21.7 | O27: 82.772727 | P27: 346.34773 | Q27: 3.9575 | R27: 19.3
A28: 1991M9 | B28: 1212.0952 | C28: 39.5 | D28: 31 | E28: 2318.583 | F28: 348.74286 | G28: 15.03 | H28: 3.1200002 | J28: 1.473125 | K28: 7675.9531 | L28: 20.48 | M28: 17.5 | N28: 21.86 | O28: 81.954762 | P28: 349.34048 | Q28: 4.0374762 | R28: 19.95
A29: 1991M10 | B29: 1152.9546 | C29: 39.5 | D29: 31 | E29: 2360.6456 | F29: 358.81436 | G29: 15.03 | H29: 2.5400001 | J29: 1.682 | K29: 7453.8633 | L29: 22.25 | M29: 19.12 | N29: 23.3 | O29: 85.282609 | P29: 362.48261 | Q29: 4.1153913 | R29: 21.56
A30: 1991M11 | B30: 1134.925 | C30: 39.5 | D30: 31 | E30: 2375.6604 | F30: 359.59 | G30: 15.03 | H30: 2.5400001 | J30: 1.8052 | K30: 7258.5 | L30: 21 | M30: 17.76 | N30: 22.46 | O30: 85.242857 | P30: 365.10952 | Q30: 4.0722857 | R30: 20.41
A31: 1991M12 | B31: 1099.5264 | C31: 39.5 | D31: 31 | E31: 2205.9185 | F31: 361.53201 | G31: 15.03 | H31: 2.5400001 | J31: 1.848 | K31: 7140.2637 | L31: 18.28 | M31: 15.11 | N31: 19.51 | O31: 82.375 | P31: 353.29545 | Q31: 3.947075 | R31: 17.63
A32: 1992M1 | B32: 1181.2273 | C32: 39.5 | D32: 31 | E32: 2150.5796 | F32: 354.70096 | G32: 14.31 | H32: 2.3799998 | I32: 3.8 | J32: 1.4405 | K32: 7531.1367 | L32: 18.55 | M32: 15.25 | N32: 18.76 | O32: 82.936957 | P32: 341.18696 | Q32: 4.1214091 | R32: 17.52 | S32: 50.254019 | T32: 65.8159
A33: 1992M2 | B33: 1270.75 | C33: 39.5 | D33: 31 | E33: 2208.8923 | F33: 353.78 | G33: 14.31 | H33: 2.3799998 | I33: 3.55 | J33: 1.18 | K33: 7888 | L33: 18.48 | M33: 15.46 | N33: 18.99 | O33: 85.4225 | P33: 362.1225 | Q33: 4.1457 | R33: 17.65 | S33: 50.247364 | T33: 66.411709
A34: 1992M3 | B34: 1282.0227 | C34: 39.5 | D34: 31 | E34: 2231.7855 | F34: 344.18332 | G34: 14.31 | H34: 2.3799998 | I34: 3.45 | J34: 1.26 | K34: 7430.4551 | L34: 17.59 | M34: 15.56 | N34: 18.92 | O34: 84.459091 | P34: 356.93864 | Q34: 4.1104318 | R34: 17.35 | S34: 50.273464 | T34: 67.330671
A35: 1992M4 | B35: 1317.125 | C35: 39.5 | D35: 31 | E35: 2214.1668 | F35: 338.69159 | G35: 14.31 | H35: 2.3399997 | I35: 3.45 | J35: 1.3905 | K35: 7417.9512 | L35: 19.06 | M35: 16.67 | N35: 20.23 | O35: 83.313636 | P35: 347.3 | Q35: 4.0525 | R35: 18.65 | S35: 50.689243 | T35: 64.459292
A36: 1992M5 | B36: 1306.7107 | C36: 39.5 | D36: 31 | E36: 2219.3151 | F36: 337.09894 | G36: 14.31 | H36: 2.3399997 | I36: 3.585 | J36: 1.5533 | K36: 7333.9473 | L36: 20.03 | M36: 17.57 | N36: 20.97 | O36: 82.840476 | P36: 358.5881 | Q36: 4.0746053 | R36: 19.52 | S36: 52.134939 | T36: 66.748541
A37: 1992M6 | B37: 1275.2727 | C37: 39.5 | D37: 29 | E37: 2296.4419 | F37: 341.02191 | G37: 14.31 | H37: 2.3399997 | I37: 3.72 | J37: 1.5915 | K37: 7202.3633 | L37: 21.28 | M37: 18.98 | N37: 22.37 | O37: 80.643182 | P37: 369.12727 | Q37: 4.0639091 | R37: 20.88 | S37: 52.346674 | T37: 63.74508
A38: 1992M7 | B38: 1314.3479 | C38: 39.5 | D38: 27 | E38: 2527.285 | F38: 352.25449 | G38: 14.31 | H38: 2.3900002 | I38: 3.94 | J38: 1.6832 | K38: 7516.1738 | L38: 20.34 | M38: 18.44 | N38: 21.77 | O38: 87.023913 | P38: 383.12174 | Q38: 3.9675217 | R38: 20.18 | S38: 51.987545 | T38: 62.348687
A39: 1992M8 | B39: 1305.55 | C39: 39.5 | D39: 27 | E39: 2513.47 | F39: 342.89285 | G39: 14.31 | H39: 2.3900002 | I39: 3.96 | J39: 1.914 | K39: 7279.75 | L39: 19.77 | M39: 17.78 | N39: 21.31 | O39: 85.530952 | P39: 359.55238 | Q39: 3.818425 | R39: 19.62 | S39: 51.997661 | T39: 63.561043
A40: 1992M9 | B40: 1270.2144 | C40: 39.5 | D40: 27 | E40: 2419.6142 | F40: 345.0065 | G40: 14.31 | H40: 2.3900002 | I40: 3.98 | J40: 2.088 | K40: 6918.5723 | L40: 20.31 | M40: 18.36 | N40: 21.9 | O40: 90.9 | P40: 362.14318 | Q40: 3.7701591 | R40: 20.19 | S40: 52.426452 | T40: 63.337492
A41: 1992M10 | B41: 1180.8411 | C41: 37.25 | D41: 27 | E41: 2262.457 | F41: 344.8924 | G41: 14.31 | H41: 2.3500002 | I41: 3.87 | J41: 2.4164 | K41: 6322.5 | L41: 20.26 | M41: 18.16 | N41: 21.69 | O41: 94.688636 | P41: 358.06818 | Q41: 3.7497727 | R41: 20.04 | S41: 51.918137 | T41: 62.352722
A42: 1992M11 | B42: 1162.2144 | C42: 35 | D42: 27 | E42: 2161.7891 | F42: 335.05054 | G42: 14.31 | H42: 2.3500002 | I42: 3.84 | J42: 2.278 | K42: 5593.7148 | L42: 19.15 | M42: 17.21 | N42: 20.33 | O42: 94.464286 | P42: 356.10952 | Q42: 3.7710238 | R42: 18.9 | S42: 49.861055 | T42: 59.574794
A43: 1992M12 | B43: 1209.0238 | C43: 35 | D43: 27 | E43: 2211.9503 | F43: 334.80713 | G43: 14.31 | H43: 2.3500002 | I43: 3.78 | J43: 2.21275 | K43: 5751.1904 | L43: 18.15 | M43: 16.22 | N43: 19.42 | O43: 106.63043 | P43: 361.97174 | Q43: 3.7264524 | R43: 17.93 | S43: 49.891888 | T43: 61.765822
... A369: 2020M2 | B369: 1688.095 | C369: 71.050179 | D369: 82.515 | E369: 5687.75 | F369: 1597.1025 | G369: 87.625 | H369: 2.9951981 | I369: 2.92025 | J369: 1.9157895 | K369: 12715.55 | L369: 55.0035 | M369: 54.5125 | N369: 50.6015 | O369: 2524.7 | P369: 961.325 | Q369: 17.922 | R369: 53.3725 | S369: 111.03641 | T369: 101.49738
A370: 2020M3
A371: 2020M4
A372: 2020M5
A373: 2020M6
A374: 2020M7
A375: 2020M8
A376: 2020M9
A377: 2020M10
A378: 2020M11
A379: 2020M12

Sheet Monthly Haver
A1: Jan-1999 !M | B1: .excel_last | C1: SGBLTO@MKTPMI | D1: SGBLTP@MKTPMI | E1: SGBLTX@MKTPMI | F1: SGBLTPO@MKTPMI | G1: SGBLTE@MKTPMI | H1: SGBLM@MKTPMI | I1: SGBLMSF@MKTPMI | J1: SGBLS@MKTPMI | K1: FXDUSBC@USECON | L1: BDIM@BALTIC
A2: .DESC | C2: Global PMI: Composite New Orders (SA, 50+=Expansion) | D2: Global PMI: Composite Input Prices (SA, 50+=Expansion) | E2: Global PMI: Composite New Export Orders (SA, 50+=Expansion) | F2: Global PMI: Composite Output Prices (SA, 50+=Expansion) | G2: Global PMI: Composite Employment (SA, 50+=Expansion) | H2: Global Manufacturing PMI Using Markit Mfg for U.S. (SA, 50+=Expansion) | I2: Global PMI: Manufacturing Stock of Finished Goods (SA, 50+=Expansion) | J2: Global PMI: Services Business Activity (SA, 50+=Expansion) | K2: JPMorgan Real Broad Effective Exchange Rate Index, PPI Based: US (2010=100) | L2: Baltic Exchange Dry Index (Jan-04-85=1000)
A3: .T1 | C3: Jul-1998 | D3: Jul-1998 | E3: Sep-2014 | F3: Oct-2009 | G3: Jul-1998 | H3: Jan-1998 | I3: May-2007 | J3: Jul-1998 | K3: Jan-1990 | L3: Jan-1985
A4: .TN | C4: Feb-2020 | D4: Feb-2020 | E4: Feb-2020 | F4: Feb-2020 | G4: Feb-2020 | H4: Feb-2020 | I4: Feb-2020 | J4: Feb-2020 | K4: Feb-2020 | L4: Feb-2020
A5: Jan-1999 | B5: 36191 | C5: 53.5978 | D5: 42.7209 | E5: #N/A | F5: #N/A | G5: 50.8253 | H5: 48.725 | I5: #N/A | J5: 55.6953 | K5: 104.75529 | L5: 803
A6: Feb-1999 | B6: 36219 | C6: 54.1231 | D6: 42.8621 | E6: #N/A | F6: #N/A | G6: 51.455 | H6: 49.8555 | I6: #N/A | J6: 55.325 | K6: 105.58412 | L6: 836
A7: Mar-1999 | B7: 36250 | C7: 55.3852 | D7: 46.3136 | E7: #N/A | F7: #N/A | G7: 51.4599 | H7: 50.7358 | I7: #N/A | J7: 56.9761 | K7: 106.60348 | L7: 967
A8: Apr-1999 | B8: 36280 | C8: 55.9986 | D8: 49.0474 | E8: #N/A | F8: #N/A | G8: 52.0895 | H8: 51.2547 | I8: #N/A | J8: 57.5913 | K8: 106.42934 | L8: 924
A9: May-1999 | B9: 36311 | C9: 55.9159 | D9: 51.0911 | E9: #N/A | F9: #N/A | G9: 52.6932 | H9: 52.3408 | I9: #N/A | J9: 56.5726 | K9: 107.03248 | L9: 1063
A10: Jun-1999 | B10: 36341 | C10: 57.88 | D10: 52.1056 | E10: #N/A | F10: #N/A | G10: 53.6803 | H10: 53.5422 | I10: #N/A | J10: 57.4603 | K10: 108.01749 | L10: 989
A11: Jul-1999 | B11: 36372 | C11: 57.3146 | D11: 54.7592 | E11: #N/A | F11: #N/A | G11: 53.4229 | H11: 53.1277 | I11: #N/A | J11: 59.4464 | K11: 107.85762 | L11: 977
A12: Aug-1999 | B12: 36403 | C12: 58.4455 | D12: 56.7833 | E12: #N/A | F12: #N/A | G12: 53.5661 | H12: 54.0786 | I12: #N/A | J12: 59.4645 | K12: 107.49371 | L12: 1046
A13: Sep-1999 | B13: 36433 | C13: 60.0929 | D13: 60.644 | E13: #N/A | F13: #N/A | G13: 53.5116 | H13: 55.688 | I13: #N/A | J13: 59.0417 | K13: 106.90362 | L13: 1146
A14: Oct-1999 | B14: 36464 | C14: 60.8225 | D14: 60.5628 | E14: #N/A | F14: #N/A | G14: 54.1088 | H14: 56.5329 | I14: #N/A | J14: 60.3565 | K14: 105.98497 | L14: 1339
A15: Nov-1999 | B15: 36494 | C15: 58.687 | D15: 60.7023 | E15: #N/A | F15: #N/A | G15: 53.7348 | H15: 56.9871 | I15: #N/A | J15: 58.1496 | K15: 106.29799 | L15: 1334
A16: Dec-1999 | B16: 36525 | C16: 60.1061 | D16: 61.0619 | E16: #N/A | F16: #N/A | G16: 55.1017 | H16: 57.0854 | I16: #N/A | J16: 59.6569 | K16: 105.52769 | L16: 1343
... A104: Apr-2007 | B104: 39202 | C104: 56.2138 | D104: 60.4599 | E104: #N/A | F104: #N/A | G104: 53.6109 | H104: 53.5203 | I104: #N/A | J104: 56.6072 | K104: 103.9773 | L104: 5754
A105: May-2007 | B105: 39233 | C105: 57.25 | D105: 60.9897 | E105: #N/A | F105: #N/A | G105: 54.502 | H105: 53.3258 | I105: 49.159 | J105: 57.7971 | K105: 104.00438 | L105: 6402
A106: Jun-2007 | B106: 39263 | C106: 57.8048 | D106: 61.0218 | E106: #N/A | F106: #N/A | G106: 55.1342 | H106: 53.7082 | I106: 49.2891 | J106: 59.1229 | K106: 104.24436 | L106: 5772
A107: Jul-2007 | B107: 39294 | C107: 56.4532 | D107: 59.8465 | E107: #N/A | F107: #N/A | G107: 54.0007 | H107: 52.9248 | I107: 49.2811 | J107: 57.351 | K107: 103.2842 | L107: 6572
A108: Aug-2007 | B108: 39325 | C108: 56.925 | D108: 59.6262 | E108: #N/A | F108: #N/A | G108: 52.8511 | H108: 52.6039 | I108: 47.9335 | J108: 56.5272 | K108: 102.35413 | L108: 7195
A109: Sep-2007 | B109: 39355 | C109: 53.9399 | D109: 61.6808 | E109: #N/A | F109: #N/A | G109: 54.2619 | H109: 52.6841 | I109: 48.4004 | J109: 53.9496 | K109: 101.04508 | L109: 8574
A110: Oct-2007 | B110: 39386 | C110: 55.133 | D110: 62.557 | E110: #N/A | F110: #N/A | G110: 54.3432 | H110: 52.3402 | I110: 48.1615 | J110: 54.3423 | K110: 99.58279 | L110: 10426
A111: Nov-2007 | B111: 39416 | C111: 53.5425 | D111: 66.3279 | E111: #N/A | F111: #N/A | G111: 53.546 | H111: 52.3529 | I111: 48.489 | J111: 54.4281 | K111: 99.74359 | L111: 10543
A112: Dec-2007 | B112: 39447 | C112: 52.8517 | D112: 66.0312 | E112: #N/A | F112: #N/A | G112: 53.4801 | H112: 51.9671 | I112: 48.0861 | J112: 53.1903 | K112: 99.65421 | L112: 9854
A113: Jan-2008 | B113: 39478 | C113: 49.2513 | D113: 65.8975 | E113: #N/A | F113: #N/A | G113: 50.9091 | H113: 52.1113 | I113: 47.885 | J113: 47.07 | K113: 99.1375 | L113: 7170
A114: Feb-2008 | B114: 39507 | C114: 51.5096 | D114: 64.6156 | E114: #N/A | F114: #N/A | G114: 51.0205 | H114: 50.7361 | I114: 49.3341 | J114: 51.913 | K114: 98.8452 | L114: 6874
A115: Mar-2008 | B115: 39538 | C115: 50.9264 | D115: 66.7563 | E115: #N/A | F115: #N/A | G115: 51.279 | H115: 50.6212 | I115: 49.2764 | J115: 51.4812 | K115: 98.20934 | L115: 8063
A116: Apr-2008 | B116: 39568 | C116: 50.9574 | D116: 67.1607 | E116: #N/A | F116: #N/A | G116: 52.2321 | H116: 50.121 | I116: 48.128 | J116: 51.2114 | K116: 97.9127 | L116: 8287
... A133: Sep-2009 | B133: 40086 | C133: 53.4706 | D133: 50.1763 | E133: #N/A | F133: #N/A | G133: 48.3176 | H133: 53.784 | I133: 46.0672 | J133: 52.1113 | K133: 97.84504 | L133: 2351
A134: Oct-2009 | B134: 40117 | C134: 54.2296 | D134: 51.4855 | E134: #N/A | F134: 47.4527 | G134: 48.1571 | H134: 54.534 | I134: 46.6717 | J134: 52.8913 | K134: 97.29799 | L134: 2746
A135: Nov-2009 | B135: 40147 | C135: 54.3577 | D135: 51.3401 | E135: #N/A | F135: 47.2058 | G135: 48.54 | H135: 54.0846 | I135: 46.8985 | J135: 52.8939 | K135: 97.76302 | L135: 3941
A136: Dec-2009 | B136: 40178 | C136: 55.1019 | D136: 52.1905 | E136: #N/A | F136: 48.1546 | G136: 48.602 | H136: 54.7653 | I136: 45.79 | J136: 53.9632 | K136: 98.05538 | L136: 3605
A137: Jan-2010 | B137: 40209 | C137: 55.5688 | D137: 54.7859 | E137: #N/A | F137: 48.9474 | G137: 49.2478 | H137: 55.449 | I137: 47.3101 | J137: 54.0539 | K137: 99.67355 | L137: 3168
A138: Feb-2010 | B138: 40237 | C138: 55.2888 | D138: 54.56 | E138: #N/A | F138: 49.0099 | G138: 49.5796 | H138: 54.9766 | I138: 48.0807 | J138: 54.9621 | K138: 100.55223 | L138: 2678
A139: Mar-2010 | B139: 40268 | C139: 56.7794 | D139: 55.6564 | E139: #N/A | F139: 49.6819 | G139: 50.6875 | H139: 55.9679 | I139: 47.6633 | J139: 55.8719 | K139: 100.33282 | L139: 3209
A140: Apr-2010 | B140: 40298 | C140: 56.8107 | D140: 56.9448 | E140: #N/A | F140: 50.5477 | G140: 51.1026 | H140: 56.713 | I140: 48.0096 | J140: 56.1704 | K140: 99.561 | L140: 3043
A141: May-2010 | B141: 40329 | C141: 55.3211 | D141: 56.1257 | E141: #N/A | F141: 50.2309 | G141: 51.6021 | H141: 55.5403 | I141: 48.8757 | J141: 55.61 | K141: 102.36559 | L141: 3838
A142: Jun-2010 | B142: 40359 | C142: 54.2049 | D142: 54.1513 | E142: #N/A | F142: 49.8968 | G142: 51.652 | H142: 53.984 | I142: 49.508 | J142: 55.0344 | K142: 102.65426 | L142: 3088
A143: Jul-2010 | B143: 40390 | C143: 54.4224 | D143: 53.8869 | E143: #N/A | F143: 50.3205 | G143: 51.3004 | H143: 54.047 | I143: 49.0262 | J143: 55.013 | K143: 101.23415 | L143: 1910
A144: Aug-2010 | B144: 40421 | C144: 54.1987 | D144: 54.9388 | E144: #N/A | F144: 50.4147 | G144: 51.6478 | H144: 53.093 | I144: 48.6181 | J144: 55.0408 | K144: 100.9623 | L144: 2432
A145: Sep-2010 | B145: 40451 | C145: 53.3743 | D145: 54.663 | E145: #N/A | F145: 50.0976 | G145: 51.2331 | H145: 52.7667 | I145: 49.1082 | J145: 54.2036 | K145: 99.35278 | L145: 2712
... A192: Aug-2014 | B192: 41882 | C192: 54.6749 | D192: 53.8271 | E192: #N/A | F192: 51.0598 | G192: 51.3145 | H192: 52.4015 | I192: 49.8942 | J192: 55.4818 | K192: 104.59177 | L192: 937
A193: Sep-2014 | B193: 41912 | C193: 54.8719 | D193: 53.3914 | E193: 52.3144 | F193: 51.732 | G193: 51.6299 | H193: 52.0306 | I193: 49.7711 | J193: 55.3725 | K193: 105.82613 | L193: 1123
A194: Oct-2014 | B194: 41943 | C194: 53.8828 | D194: 53.0991 | E194: 51.1515 | F194: 50.4068 | G194: 51.4139 | H194: 52.0748 | I194: 50.2413 | J194: 53.8026 | K194: 106.26819 | L194: 1101
A195: Nov-2014 | B195: 41973 | C195: 53.2892 | D195: 52.6064 | E195: 50.6397 | F195: 50.8073 | G195: 51.643 | H195: 51.6649 | I195: 49.8011 | J195: 53.5846 | K195: 107.22943 | L195: 1332
A196: Dec-2014 | B196: 42004 | C196: 52.1999 | D196: 52.5613 | E196: 51.1211 | F196: 50.1369 | G196: 51.164 | H196: 51.4481 | I196: 49.6919 | J196: 52.6864 | K196: 108.11974 | L196: 910
A197: Jan-2015 | B197: 42035 | C197: 52.1092 | D197: 50.2576 | E197: 50.7977 | F197: 49.839 | G197: 51.4749 | H197: 51.4892 | I197: 49.41 | J197: 52.9013 | K197: 108.27733 | L197: 725
A198: Feb-2015 | B198: 42063 | C198: 53.8366 | D198: 51.0728 | E198: 50.8606 | F198: 50.5255 | G198: 51.5707 | H198: 51.8045 | I198: 49.8626 | J198: 54.1057 | K198: 109.15075 | L198: 539
A199: Mar-2015 | B199: 42094 | C199: 54.1723 | D199: 52.2803 | E199: 50.6275 | F199: 50.5022 | G199: 51.5554 | H199: 51.3975 | I199: 49.3258 | J199: 54.998 | K199: 110.81075 | L199: 576
A200: Apr-2015 | B200: 42124 | C200: 53.7497 | D200: 52.4441 | E200: 50.3257 | F200: 50.7862 | G200: 52.0561 | H200: 50.7325 | I200: 49.4761 | J200: 54.6993 | K200: 109.32864 | L200: 591
A201: May-2015 | B201: 42155 | C201: 53.2612 | D201: 53.4647 | E201: 49.9356 | F201: 50.8285 | G201: 52.2778 | H201: 50.9555 | I201: 49.093 | J201: 53.989 | K201: 110.09966 | L201: 597
A202: Jun-2015 | B202: 42185 | C202: 53.1794 | D202: 54.0799 | E202: 50.8915 | F202: 51.0888 | G202: 51.5421 | H202: 50.8662 | I202: 49.0799 | J202: 53.2992 | K202: 111.99244 | L202: 699
A203: Jul-2015 | B203: 42216 | C203: 53.7926 | D203: 53.3661 | E203: 50.0804 | F203: 50.6861 | G203: 51.6444 | H203: 50.665 | I203: 49.3823 | J203: 53.8168 | K203: 113.38926 | L203: 975
A204: Aug-2015 | B204: 42247 | C204: 52.9669 | D204: 52.1617 | E204: 49.7855 | F204: 50.0495 | G204: 51.6118 | H204: 50.3521 | I204: 48.7848 | J204: 54.1035 | K204: 115.06005 | L204: 1066
... A258: Feb-2020 | B258: 43890 | C258: 46.3441 | D258: 52.4902 | E258: 45.1792 | F258: 50.5906 | G258: 49.7814 | H258: 47.1678 | I258: 48.1155 | J258: 47.1239 | K258: 115.21493 | L258: 461
A259: 43891

Sheet Quarterly Haver
A1: 1999/Q1 *Q | B1: .excel_first | C1: S001XDIR@G10 | D1: S001XHPR@G10
A2: .DESC | C2: Real Household Personal Disposable Income: World (SA, 2005=100) | D2: Real House Price Index: World (SA, 2005=100)
A3: .T1 | C3: Q1-1975 | D3: Q1-1975
A4: 1999/Q1 | B4: 36161 | C4: 90.89 | D4: 79.09
A5: 1999/Q2 | B5: 36251 | C5: 91.28 | D5: 79.57
A6: 1999/Q3 | B6: 36342 | C6: 91.69 | D6: 80.19
A7: 1999/Q4 | B7: 36434 | C7: 92.42 | D7: 80.65
A8: 2000/Q1 | B8: 36526 | C8: 92.66 | D8: 81.08
A9: 2000/Q2 | B9: 36617 | C9: 93.27 | D9: 81.77
A10: 2000/Q3 | B10: 36708 | C10: 93.74 | D10: 82.13
A11: 2000/Q4 | B11: 36800 | C11: 94.19 | D11: 82.64
A12: 2001/Q1 | B12: 36892 | C12: 94.87 | D12: 83.24
A13: 2001/Q2 | B13: 36982 | C13: 94.56 | D13: 83.74
A14: 2001/Q3 | B14: 37073 | C14: 95.66 | D14: 84.57
A15: 2001/Q4 | B15: 37165 | C15: 95.36 | D15: 85.16
... A86: 2019/Q3 | B86: 43647 | C86: 119.1 | D86: 108.55
A87: 2019/Q4 | B87: 43739 | C87: #N/A | D87: #N/A

Sheet Monthly
B1: PMINO | C1: PMIALL | D1: PMINXO | E1: EMPPMI | F1: PMIM | G1: Inve | H1: PMIS | I1: Sales | J1: INDPRO | K1: BOPTIMP | L1: BOPTEXP | M1: UNRATE | N1: ECC | O1: LRIR | P1: STIR | Q1: CPI | R1: CCPI | S1: Food | T1: Metal | U1: COMPNF | V1: Energy | W1: Oil | X1: Raw | Y1: OECDCLI | Z1: REERUS | AA1: CHEM
A2: ='Monthly Haver'!A5 -> Jan-1999 | B2: ='Monthly Haver'!C5 -> 53.5978 | C2: ='Monthly Haver'!D5 -> 42.7209 | D2: ='Monthly Haver'!E5 -> #N/A | E2: ='Monthly Haver'!G5 -> 50.8253 | F2: ='Monthly Haver'!H5 -> 48.725 | G2: ='Monthly Haver'!I5 -> #N/A | H2: ='Monthly Haver'!J5 -> 55.6953 | I2: =GDS_Monthly!O119 -> 46.798567 | J2: =GDS_Monthly!D119 -> 65.766691 | K2: =GDS_Monthly!AH119 -> 348.53117 | L2: =GDS_Monthly!AI119 -> 343.30954 | M2: =GDS_Monthly!N119 -> 6.1802983 | N2: =GDS_Monthly!C119 -> 118.5965 | O2: =GDS_Monthly!F119 -> 4.1412506 | P2: =GDS_Monthly!G119 -> 5.8924084 | Q2: =GDS_Monthly!T119 -> 74.240079 | R2: =GDS_Monthly!V119 -> 79.457888 | S2: =GDS_Monthly!W119 -> 64.630327 | T2: =GDS_Monthly!X119 -> 36.397902 | U2: =GDS_Monthly!AA119 -> 51.504077 | V2: =GDS_Monthly!AC119 -> 32.584569 | W2: =GDS_Monthly!AE119 -> 26.140204 | X2: =GDS_Monthly!AF119 -> 69.791518 | Y2: =OECD!B2 -> 99.50104 | Z2: ='Monthly Haver'!K5 -> 104.75529 | AA2: =OECD!C2 -> 95.61
A3: ='Monthly Haver'!A6 -> Feb-1999 | B3: ='Monthly Haver'!C6 -> 54.1231 | C3: ='Monthly Haver'!D6 -> 42.8621 | D3: ='Monthly Haver'!E6 -> #N/A | E3: ='Monthly Haver'!G6 -> 51.455 | F3: ='Monthly Haver'!H6 -> 49.8555 | G3: ='Monthly Haver'!I6 -> #N/A | H3: ='Monthly Haver'!J6 -> 55.325 | I3: =GDS_Monthly!O120 -> 47.090048 | J3: =GDS_Monthly!D120 -> 66.078072 | K3: =GDS_Monthly!AH120 -> 349.50295 | L3: =GDS_Monthly!AI120 -> 337.65464 | M3: =GDS_Monthly!N120 -> 6.188384 | N3: =GDS_Monthly!C120 -> 119.68398 | O3: =GDS_Monthly!F120 -> 4.3355725 | P3: =GDS_Monthly!G120 -> 5.6835612 | Q3: =GDS_Monthly!T120 -> 74.333259 | R3: =GDS_Monthly!V120 -> 79.54662 | S3: =GDS_Monthly!W120 -> 59.730251 | T3: =GDS_Monthly!X120 -> 36.917985 | U3: =GDS_Monthly!AA120 -> 49.308959 | V3: =GDS_Monthly!AC120 -> 31.458463 | W3: =GDS_Monthly!AE120 -> 25.242365 | X3: =GDS_Monthly!AF120 -> 69.661742 | Y3: =OECD!B3 -> 99.68887 | Z3: ='Monthly Haver'!K6 -> 105.58412 | AA3: =OECD!C3 -> 96.34
A4: ='Monthly Haver'!A7 -> Mar-1999 | B4: ='Monthly Haver'!C7 -> 55.3852 | C4: ='Monthly Haver'!D7 -> 46.3136 | D4: ='Monthly Haver'!E7 -> #N/A | E4: ='Monthly Haver'!G7 -> 51.4599 | F4: ='Monthly Haver'!H7 -> 50.7358 | G4: ='Monthly Haver'!I7 -> #N/A | H4: ='Monthly Haver'!J7 -> 56.9761 | I4: =GDS_Monthly!O121 -> 47.707038 | J4: =GDS_Monthly!D121 -> 66.434224 | K4: =GDS_Monthly!AH121 -> 353.75933 | L4: =GDS_Monthly!AI121 -> 346.54339 | M4: =GDS_Monthly!N121 -> 6.1876084 | N4: =GDS_Monthly!C121 -> 119.68072 | O4: =GDS_Monthly!F121 -> 4.4351016 | P4: =GDS_Monthly!G121 -> 6.0039844 | Q4: =GDS_Monthly!T121 -> 74.491016 | R4: =GDS_Monthly!V121 -> 79.707758 | S4: =GDS_Monthly!W121 -> 57.937052 | T4: =GDS_Monthly!X121 -> 37.299843 | U4: =GDS_Monthly!AA121 -> 48.513972 | V4: =GDS_Monthly!AC121 -> 34.981861 | W4: =GDS_Monthly!AE121 -> 30.593839 | X4: =GDS_Monthly!AF121 -> 70.57853 | Y4: =OECD!B4 -> 99.87469 | Z4: ='Monthly Haver'!K7 -> 106.60348 | AA4: =OECD!C4 -> 96.64
A5: ='Monthly Haver'!A8 -> Apr-1999 | B5: ='Monthly Haver'!C8 -> 55.9986 | C5: ='Monthly Haver'!D8 -> 49.0474 | D5: ='Monthly Haver'!E8 -> #N/A | E5: ='Monthly Haver'!G8 -> 52.0895 | F5: ='Monthly Haver'!H8 -> 51.2547 | G5: ='Monthly Haver'!I8 -> #N/A | H5: ='Monthly Haver'!J8 -> 57.5913 | I5: =GDS_Monthly!O122 -> 47.641381 | J5: =GDS_Monthly!D122 -> 66.654924 | K5: =GDS_Monthly!AH122 -> 351.52124 | L5: =GDS_Monthly!AI122 -> 345.01638 | M5: =GDS_Monthly!N122 -> 6.1780133 | N5: =GDS_Monthly!C122 -> 120.19433 | O5: =GDS_Monthly!F122 -> 4.3134968 | P5: =GDS_Monthly!G122 -> 5.3779158 | Q5: =GDS_Monthly!T122 -> 74.77595 | R5: =GDS_Monthly!V122 -> 79.890023 | S5: =GDS_Monthly!W122 -> 59.170834 | T5: =GDS_Monthly!X122 -> 38.769809 | U5: =GDS_Monthly!AA122 -> 49.095826 | V5: =GDS_Monthly!AC122 -> 40.728868 | W5: =GDS_Monthly!AE122 -> 37.660442 | X5: =GDS_Monthly!AF122 -> 69.408326 | Y5: =OECD!B5 -> 100.0538 | Z5: ='Monthly Haver'!K8 -> 106.42934 | AA5: =OECD!C5 -> 97.25
A6: ='Monthly Haver'!A9 -> May-1999 | B6: ='Monthly Haver'!C9 -> 55.9159 | C6: ='Monthly Haver'!D9 -> 51.0911 | D6: ='Monthly Haver'!E9 -> #N/A | E6: ='Monthly Haver'!G9 -> 52.6932 | F6: ='Monthly Haver'!H9 -> 52.3408 | G6: ='Monthly Haver'!I9 -> #N/A | H6: ='Monthly Haver'!J9 -> 56.5726 | I6: =GDS_Monthly!O123 -> 47.958598 | J6: =GDS_Monthly!D123 -> 67.105889 | K6: =GDS_Monthly!AH123 -> 357.45037 | L6: =GDS_Monthly!AI123 -> 347.63978 | M6: =GDS_Monthly!N123 -> 6.1298479 | N6: =GDS_Monthly!C123 -> 120.78991 | O6: =GDS_Monthly!F123 -> 4.5002013 | P6: =GDS_Monthly!G123 -> 4.951413 | Q6: =GDS_Monthly!T123 -> 74.86219 | R6: =GDS_Monthly!V123 -> 80.011264 | S6: =GDS_Monthly!W123 -> 59.728118 | T6: =GDS_Monthly!X123 -> 39.98686 | U6: =GDS_Monthly!AA123 -> 49.601793 | V6: =GDS_Monthly!AC123 -> 42.045514 | W6: =GDS_Monthly!AE123 -> 38.766827 | X6: =GDS_Monthly!AF123 -> 71.430794 | Y6: =OECD!B6 -> 100.2218 | Z6: ='Monthly Haver'!K9 -> 107.03248 | AA6: =OECD!C6 -> 98.12
A7: ='Monthly Haver'!A10 -> Jun-1999 | B7: ='Monthly Haver'!C10 -> 57.88 | C7: ='Monthly Haver'!D10 -> 52.1056 | D7: ='Monthly Haver'!E10 -> #N/A | E7: ='Monthly Haver'!G10 -> 53.6803 | F7: ='Monthly Haver'!H10 -> 53.5422 | G7: ='Monthly Haver'!I10 -> #N/A | H7: ='Monthly Haver'!J10 -> 57.4603 | I7: =GDS_Monthly!O124 -> 48.265373 | J7: =GDS_Monthly!D124 -> 67.334546 | K7: =GDS_Monthly!AH124 -> 366.78818 | L7: =GDS_Monthly!AI124 -> 350.30868 | M7: =GDS_Monthly!N124 -> 6.1282811 | N7: =GDS_Monthly!C124 -> 121.36047 | O7: =GDS_Monthly!F124 -> 4.8231277 | P7: =GDS_Monthly!G124 -> 4.8854794 | Q7: =GDS_Monthly!T124 -> 74.96249 | R7: =GDS_Monthly!V124 -> 80.12205 | S7: =GDS_Monthly!W124 -> 57.970115 | T7: =GDS_Monthly!X124 -> 39.018173 | U7: =GDS_Monthly!AA124 -> 48.23643 | V7: =GDS_Monthly!AC124 -> 42.719851 | W7: =GDS_Monthly!AE124 -> 39.30779 | X7: =GDS_Monthly!AF124 -> 71.122848 | Y7: =OECD!B7 -> 100.3789 | Z7: ='Monthly Haver'!K10 -> 108.01749 | AA7: =OECD!C7 -> 98.7
A8: ='Monthly Haver'!A11 -> Jul-1999 | B8: ='Monthly Haver'!C11 -> 57.3146 | C8: ='Monthly Haver'!D11 -> 54.7592 | D8: ='Monthly Haver'!E11 -> #N/A | E8: ='Monthly Haver'!G11 -> 53.4229 | F8: ='Monthly Haver'!H11 -> 53.1277 | G8: ='Monthly Haver'!I11 -> #N/A | H8: ='Monthly Haver'!J11 -> 59.4464 | I8: =GDS_Monthly!O125 -> 48.568561 | J8: =GDS_Monthly!D125 -> 67.702661 | K8: =GDS_Monthly!AH125 -> 368.14642 | L8: =GDS_Monthly!AI125 -> 360.15832 | M8: =GDS_Monthly!N125 -> 6.1016194 | N8: =GDS_Monthly!C125 -> 120.75109 | O8: =GDS_Monthly!F125 -> 4.9035408 | P8: =GDS_Monthly!G125 -> 4.749271 | Q8: =GDS_Monthly!T125 -> 75.212716 | R8: =GDS_Monthly!V125 -> 80.274977 | S8: =GDS_Monthly!W125 -> 56.295033 | T8: =GDS_Monthly!X125 -> 41.904733 | U8: =GDS_Monthly!AA125 -> 47.644857 | V8: =GDS_Monthly!AC125 -> 47.300332 | W8: =GDS_Monthly!AE125 -> 45.405164 | X8: =GDS_Monthly!AF125 -> 70.073576 | Y8: =OECD!B8 -> 100.5246 | Z8: ='Monthly Haver'!K11 -> 107.85762 | AA8: =OECD!C8 -> 98.78
A9: ='Monthly Haver'!A12 -> Aug-1999 | B9: ='Monthly Haver'!C12 -> 58.4455 | C9: ='Monthly Haver'!D12 -> 56.7833 | D9: ='Monthly Haver'!E12 -> #N/A | E9: ='Monthly Haver'!G12 -> 53.5661 | F9: ='Monthly Haver'!H12 -> 54.0786 | G9: ='Monthly Haver'!I12 -> #N/A | H9: ='Monthly Haver'!J12 -> 59.4645 | I9: =GDS_Monthly!O126 -> 48.86523 | J9: =GDS_Monthly!D126 -> 68.116441 | K9: =GDS_Monthly!AH126 -> 376.04072 | L9: =GDS_Monthly!AI126 -> 365.35816 | M9: =GDS_Monthly!N126 -> 6.0777222 | N9: =GDS_Monthly!C126 -> 120.74856 | O9: =GDS_Monthly!F126 -> 5.0666091 | P9: =GDS_Monthly!G126 -> 4.815968 | Q9: =GDS_Monthly!T126 -> 75.426542 | R9: =GDS_Monthly!V126 -> 80.379334 | S9: =GDS_Monthly!W126 -> 57.952559 | T9: =GDS_Monthly!X126 -> 43.136454 | U9: =GDS_Monthly!AA126 -> 48.616018 | V9: =GDS_Monthly!AC126 -> 51.401241 | W9: =GDS_Monthly!AE126 -> 48.046108 | X9: =GDS_Monthly!AF126 -> 69.962439 | Y9: =OECD!B9 -> 100.6616 | Z9: ='Monthly Haver'!K12 -> 107.49371 | AA9: =OECD!C9 -> 98.8
A10: ='Monthly Haver'!A13 -> Sep-1999 | B10: ='Monthly Haver'!C13 -> 60.0929 | C10: ='Monthly Haver'!D13 -> 60.644 | D10: ='Monthly Haver'!E13 -> #N/A | E10: ='Monthly Haver'!G13 -> 53.5116 | F10: ='Monthly Haver'!H13 -> 55.688 | G10: ='Monthly Haver'!I13 -> #N/A | H10: ='Monthly Haver'!J13 -> 59.0417 | I10: =GDS_Monthly!O127 -> 48.872986 | J10: =GDS_Monthly!D127 -> 68.542555 | K10: =GDS_Monthly!AH127 -> 385.98611 | L10: =GDS_Monthly!AI127 -> 373.11636 | M10: =GDS_Monthly!N127 -> 6.0471354 | N10: =GDS_Monthly!C127 -> 120.32739 | O10: =GDS_Monthly!F127 -> 5.106116 | P10: =GDS_Monthly!G127 -> 4.8967155 | Q10: =GDS_Monthly!T127 -> 75.658393 | R10: =GDS_Monthly!V127 -> 80.595118 | S10: =GDS_Monthly!W127 -> 58.694531 | T10: =GDS_Monthly!X127 -> 45.284139 | U10: =GDS_Monthly!AA127 -> 49.635083 | V10: =GDS_Monthly!AC127 -> 54.866576 | W10: =GDS_Monthly!AE127 -> 52.726411 | X10: =GDS_Monthly!AF127 -> 72.033331 | Y10: =OECD!B10 -> 100.7954 | Z10: ='Monthly Haver'!K13 -> 106.90362 | AA10: =OECD!C10 -> 98.59
A11: ='Monthly Haver'!A14 -> Oct-1999 | B11: ='Monthly Haver'!C14 -> 60.8225 | C11: ='Monthly Haver'!D14 -> 60.5628 | D11: ='Monthly Haver'!E14 -> #N/A | E11: ='Monthly Haver'!G14 -> 54.1088 | F11: ='Monthly Haver'!H14 -> 56.5329 | G11: ='Monthly Haver'!I14 -> #N/A | H11: ='Monthly Haver'!J14 -> 60.3565 | I11: =GDS_Monthly!O128 -> 49.519842 | J11: =GDS_Monthly!D128 -> 68.798138 | K11: =GDS_Monthly!AH128 -> 391.70971 | L11: =GDS_Monthly!AI128 -> 382.24569 | M11: =GDS_Monthly!N128 -> 6.0298892 | N11: =GDS_Monthly!C128 -> 119.63202 | O11: =GDS_Monthly!F128 -> 5.2651836 | P11: =GDS_Monthly!G128 -> 4.8662165 | Q11: =GDS_Monthly!T128 -> 75.844546 | R11: =GDS_Monthly!V128 -> 80.763693 | S11: =GDS_Monthly!W128 -> 58.351763 | T11: =GDS_Monthly!X128 -> 45.088045 | U11: =GDS_Monthly!AA128 -> 50.364373 | V11: =GDS_Monthly!AC128 -> 55.667194 | W11: =GDS_Monthly!AE128 -> 51.797968 | X11: =GDS_Monthly!AF128 -> 73.127539 | Y11: =OECD!B11 -> 100.9314 | Z11: ='Monthly Haver'!K14 -> 105.98497 | AA11: =OECD!C11 -> 99.03
A12: ='Monthly Haver'!A15 -> Nov-1999 | B12: ='Monthly Haver'!C15 -> 58.687 | C12: ='Monthly Haver'!D15 -> 60.7023 | D12: ='Monthly Haver'!E15 -> #N/A | E12: ='Monthly Haver'!G15 -> 53.7348 | F12: ='Monthly Haver'!H15 -> 56.9871 | G12: ='Monthly Haver'!I15 -> #N/A | H12: ='Monthly Haver'!J15 -> 58.1496 | I12: =GDS_Monthly!O129 -> 49.685402 | J12: =GDS_Monthly!D129 -> 69.639348 | K12: =GDS_Monthly!AH129 -> 397.60195 | L12: =GDS_Monthly!AI129 -> 385.7613 | M12: =GDS_Monthly!N129 -> 5.9864186 | N12: =GDS_Monthly!C129 -> 121.30928 | O12: =GDS_Monthly!F129 -> 5.1110627 | P12: =GDS_Monthly!G129 -> 5.0130161 | Q12: =GDS_Monthly!T129 -> 75.998945 | R12: =GDS_Monthly!V129 -> 80.906541 | S12: =GDS_Monthly!W129 -> 57.356419 | T12: =GDS_Monthly!X129 -> 45.822383 | U12: =GDS_Monthly!AA129 -> 49.987955 | V12: =GDS_Monthly!AC129 -> 58.050902 | W12: =GDS_Monthly!AE129 -> 57.073002 | X12: =GDS_Monthly!AF129 -> 72.918189 | Y12: =OECD!B12 -> 101.0658 | Z12: ='Monthly Haver'!K15 -> 106.29799 | AA12: =OECD!C12 -> 100.26
A13: ='Monthly Haver'!A16 -> Dec-1999 | B13: ='Monthly Haver'!C16 -> 60.1061 | C13: ='Monthly Haver'!D16 -> 61.0619 | D13: ='Monthly Haver'!E16 -> #N/A | E13: ='Monthly Haver'!G16 -> 55.1017 | F13: ='Monthly Haver'!H16 -> 57.0854 | G13: ='Monthly Haver'!I16 -> #N/A | H13: ='Monthly Haver'!J16 -> 59.6569 | I13: =GDS_Monthly!O130 -> 50.349934 | J13: =GDS_Monthly!D130 -> 70.082023 | K13: =GDS_Monthly!AH130 -> 402.2412 | L13: =GDS_Monthly!AI130 -> 390.473 | M13: =GDS_Monthly!N130 -> 5.9072491 | N13: =GDS_Monthly!C130 -> 122.6339 | O13: =GDS_Monthly!F130 -> 5.236105 | P13: =GDS_Monthly!G130 -> 5.0392185 | Q13: =GDS_Monthly!T130 -> 76.159788 | R13: =GDS_Monthly!V130 -> 81.05587 | S13: =GDS_Monthly!W130 -> 57.648097 | T13: =GDS_Monthly!X130 -> 47.048003 | U13: =GDS_Monthly!AA130 -> 50.26534 | V13: =GDS_Monthly!AC130 -> 59.419051 | W13: =GDS_Monthly!AE130 -> 59.061798 | X13: =GDS_Monthly!AF130 -> 72.298999 | Y13: =OECD!B13 -> 101.1871 | Z13: ='Monthly Haver'!K16 -> 105.52769 | AA13: =OECD!C13 -> 100.67
... A256: ='Monthly Haver'!A259 -> 43891 | B256: ='Monthly Haver'!C259 -> 0 | C256: ='Monthly Haver'!D259 -> 0 | D256: ='Monthly Haver'!E259 -> 0 | E256: ='Monthly Haver'!G259 -> 0 | F256: ='Monthly Haver'!H259 -> 0 | G256: ='Monthly Haver'!I259 -> 0 | H256: ='Monthly Haver'!J259 -> 0 | I256: =GDS_Monthly!O373 -> 0 | J256: =GDS_Monthly!D373 -> 0 | K256: =GDS_Monthly!AH373 -> 0 | L256: =GDS_Monthly!AI373 -> 0 | M256: =GDS_Monthly!N373 -> 0 | N256: =GDS_Monthly!C373 -> 0 | O256: =GDS_Monthly!F373 -> 0 | P256: =GDS_Monthly!G373 -> 1.8756743 | Q256: =GDS_Monthly!T373 -> 0 | R256: =GDS_Monthly!V373 -> 0 | S256: =GDS_Monthly!W373 -> 0 | T256: =GDS_Monthly!X373 -> 0 | U256: =GDS_Monthly!AA373 -> 0 | V256: =GDS_Monthly!AC373 -> 0 | W256: =GDS_Monthly!AE373 -> 0 | X256: =GDS_Monthly!AF373 -> 0 | Y256: =OECD!B256 -> 0 | Z256: ='Monthly Haver'!K259 -> 0 | AA256: =OECD!C256 -> 0

Sheet Quarterly
B1: House | C1: RINC | D1: NGDPR | E1: GPMGDP
A2: 1999/Q1 | B2: ='Quarterly Haver'!C4 -> 90.89 | C2: ='Quarterly Haver'!D4 -> 79.09 | D2: =GDS_Quarterly!V45 -> 74.884141
A3: 1999/Q2 | B3: ='Quarterly Haver'!C5 -> 91.28 | C3: ='Quarterly Haver'!D5 -> 79.57 | D3: =GDS_Quarterly!V46 -> 75.464053
A4: 1999/Q3 | B4: ='Quarterly Haver'!C6 -> 91.69 | C4: ='Quarterly Haver'!D6 -> 80.19 | D4: =GDS_Quarterly!V47 -> 76.352561
A5: 1999/Q4 | B5: ='Quarterly Haver'!C7 -> 92.42 | C5: ='Quarterly Haver'!D7 -> 80.65 | D5: =GDS_Quarterly!V48 -> 77.366935
A6: 2000/Q1 | B6: ='Quarterly Haver'!C8 -> 92.66 | C6: ='Quarterly Haver'!D8 -> 81.08 | D6: =GDS_Quarterly!V49 -> 78.24454
A7: 2000/Q2 | B7: ='Quarterly Haver'!C9 -> 93.27 | C7: ='Quarterly Haver'!D9 -> 81.77 | D7: =GDS_Quarterly!V50 -> 79.135579
A8: 2000/Q3 | B8: ='Quarterly Haver'!C10 -> 93.74 | C8: ='Quarterly Haver'!D10 -> 82.13 | D8: =GDS_Quarterly!V51 -> 79.553245
A9: 2000/Q4 | B9: ='Quarterly Haver'!C11 -> 94.19 | C9: ='Quarterly Haver'!D11 -> 82.64 | D9: =GDS_Quarterly!V52 -> 80.060844
A10: 2001/Q1 | B10: ='Quarterly Haver'!C12 -> 94.87 | C10: ='Quarterly Haver'!D12 -> 83.24 | D10: =GDS_Quarterly!V53 -> 80.389859
A11: 2001/Q2 | B11: ='Quarterly Haver'!C13 -> 94.56 | C11: ='Quarterly Haver'!D13 -> 83.74 | D11: =GDS_Quarterly!V54 -> 80.603238
A12: 2001/Q3 | B12: ='Quarterly Haver'!C14 -> 95.66 | C12: ='Quarterly Haver'!D14 -> 84.57 | D12: =GDS_Quarterly!V55 -> 80.530172
A13: 2001/Q4 | B13: ='Quarterly Haver'!C15 -> 95.36 | C13: ='Quarterly Haver'!D15 -> 85.16 | D13: =GDS_Quarterly!V56 -> 80.704556
... A62: 2014/Q1 | B62: ='Quarterly Haver'!C64 -> 107.12 | C62: ='Quarterly Haver'!D64 -> 92.51 | D62: =GDS_Quarterly!V105 -> 109.62108
A63: 2014/Q2 | B63: ='Quarterly Haver'!C65 -> 107.73 | C63: ='Quarterly Haver'!D65 -> 93.14 | D63: =GDS_Quarterly!V106 -> 110.30751 | E63: 3.9615565
A64: 2014/Q3 | B64: ='Quarterly Haver'!C66 -> 108.49 | C64: ='Quarterly Haver'!D66 -> 93.74 | D64: =GDS_Quarterly!V107 -> 111.23298 | E64: 4.2095703
A65: 2014/Q4 | B65: ='Quarterly Haver'!C67 -> 109.27 | C65: ='Quarterly Haver'!D67 -> 94.28 | D65: =GDS_Quarterly!V108 -> 112.00907 | E65: 3.6929339
A66: 2015/Q1 | B66: ='Quarterly Haver'!C68 -> 110.19 | C66: ='Quarterly Haver'!D68 -> 95.24 | D66: =GDS_Quarterly!V109 -> 112.87329 | E66: 3.7225542
A67: 2015/Q2 | B67: ='Quarterly Haver'!C69 -> 110.75 | C67: ='Quarterly Haver'!D69 -> 96.06 | D67: =GDS_Quarterly!V110 -> 113.57745 | E67: 3.7494042
A68: 2015/Q3 | B68: ='Quarterly Haver'!C70 -> 111.3 | C68: ='Quarterly Haver'!D70 -> 97 | D68: =GDS_Quarterly!V111 -> 114.27872 | E68: 3.4666354
A69: 2015/Q4 | B69: ='Quarterly Haver'!C71 -> 111.48 | C69: ='Quarterly Haver'!D71 -> 97.78 | D69: =GDS_Quarterly!V112 -> 114.74083 | E69: 2.7711883
A70: 2016/Q1 | B70: ='Quarterly Haver'!C72 -> 111.78 | C70: ='Quarterly Haver'!D72 -> 98.91 | D70: =GDS_Quarterly!V113 -> 115.51006 | E70: 4.0979582
A71: 2016/Q2 | B71: ='Quarterly Haver'!C73 -> 111.91 | C71: ='Quarterly Haver'!D73 -> 100.06 | D71: =GDS_Quarterly!V114 -> 116.23234 | E71: 3.6700243
A72: 2016/Q3 | B72: ='Quarterly Haver'!C74 -> 112.26 | C72: ='Quarterly Haver'!D74 -> 101.19 | D72: =GDS_Quarterly!V115 -> 116.99329 | E72: 3.6174157
A73: 2016/Q4 | B73: ='Quarterly Haver'!C75 -> 112.52 | C73: ='Quarterly Haver'!D75 -> 101.83 | D73: =GDS_Quarterly!V116 -> 118.00064 | E73: 4.1765519
A74: 2017/Q1 | B74: ='Quarterly Haver'!C76 -> 113.27 | C74: ='Quarterly Haver'!D76 -> 102.58 | D74: =GDS_Quarterly!V117 -> 118.98984 | E74: 3.6282714
... A84: 2019/Q3 | B84: ='Quarterly Haver'!C86 -> 119.1 | C84: ='Quarterly Haver'!D86 -> 108.55 | D84: =GDS_Quarterly!V127 -> 127.80662 | E84: 3.0027111
A85: 2019/Q4 | D85: =GDS_Quarterly!V128 -> 128.38093 | E85: 2.6073257

Sheet data
A1: date | B1: PMINO | C1: PMIALL | D1: PMINXO | E1: EMPPMI | F1: PMIM | G1: Inve | H1: PMIS | I1: Sales | J1: INDPRO | K1: BOPTIMP | L1: BOPTEXP | M1: UNRATE | N1: ECC | O1: LRIR | P1: STIR | Q1: CPI | R1: CCPI | S1: Food | T1: Metal | U1: COMPNF | V1: Energy | W1: Oil | X1: Raw | Y1: OECDCLI | Z1: CHEM | AA1: REERUS | AB1: BDIY | AC1: House | AD1: RINC | AE1: NGDPR | AF1: GDPGPM
A2: 36161 | B2: ='Monthly Haver'!C5 -> 53.5978 | C2: ='Monthly Haver'!D5 -> 42.7209 | D2: ='Monthly Haver'!E5 -> #N/A | E2: ='Monthly Haver'!G5 -> 50.8253 | F2: ='Monthly Haver'!H5 -> 48.725 | G2: ='Monthly Haver'!I5 -> #N/A | H2: ='Monthly Haver'!J5 -> 55.6953 | I2: =GDS_Monthly!O119 -> 46.798567 | J2: =GDS_Monthly!D119 -> 65.766691 | K2: =GDS_Monthly!AH119 -> 348.53117 | L2: =GDS_Monthly!AI119 -> 343.30954 | M2: =GDS_Monthly!N119 -> 6.1802983 | N2: =GDS_Monthly!C119 -> 118.5965 | O2: =GDS_Monthly!F119 -> 4.1412506 | P2: =GDS_Monthly!G119 -> 5.8924084 | Q2: =GDS_Monthly!T119 -> 74.240079 | R2: =GDS_Monthly!V119 -> 79.457888 | S2: =GDS_Monthly!W119 -> 64.630327 | T2: =GDS_Monthly!X119 -> 36.397902 | U2: =GDS_Monthly!AA119 -> 51.504077 | V2: =GDS_Monthly!AC119 -> 32.584569 | W2: =GDS_Monthly!AE119 -> 26.140204 | X2: =GDS_Monthly!AF119 -> 69.791518 | Y2: =OECD!B2 -> 99.50104 | Z2: =OECD!C2 -> 95.61 | AA2: ='Monthly Haver'!K5 -> 104.75529 | AB2: ='Monthly Haver'!L5 -> 803
A3: 36192 | B3: ='Monthly Haver'!C6 -> 54.1231 | C3: ='Monthly Haver'!D6 -> 42.8621 | D3: ='Monthly Haver'!E6 -> #N/A | E3: ='Monthly Haver'!G6 -> 51.455 | F3: ='Monthly Haver'!H6 -> 49.8555 | G3: ='Monthly Haver'!I6 -> #N/A | H3: ='Monthly Haver'!J6 -> 55.325 | I3: =GDS_Monthly!O120 -> 47.090048 | J3: =GDS_Monthly!D120 -> 66.078072 | K3: =GDS_Monthly!AH120 -> 349.50295 | L3: =GDS_Monthly!AI120 -> 337.65464 | M3: =GDS_Monthly!N120 -> 6.188384 | N3: =GDS_Monthly!C120 -> 119.68398 | O3: =GDS_Monthly!F120 -> 4.3355725 | P3: =GDS_Monthly!G120 -> 5.6835612 | Q3: =GDS_Monthly!T120 -> 74.333259 | R3: =GDS_Monthly!V120 -> 79.54662 | S3: =GDS_Monthly!W120 -> 59.730251 | T3: =GDS_Monthly!X120 -> 36.917985 | U3: =GDS_Monthly!AA120 -> 49.308959 | V3: =GDS_Monthly!AC120 -> 31.458463 | W3: =GDS_Monthly!AE120 -> 25.242365 | X3: =GDS_Monthly!AF120 -> 69.661742 | Y3: =OECD!B3 -> 99.68887 | Z3: =OECD!C3 -> 96.34 | AA3: ='Monthly Haver'!K6 -> 105.58412 | AB3: ='Monthly Haver'!L6 -> 836
A4: 36220 | B4: ='Monthly Haver'!C7 -> 55.3852 | C4: ='Monthly Haver'!D7 -> 46.3136 | D4: ='Monthly Haver'!E7 -> #N/A | E4: ='Monthly Haver'!G7 -> 51.4599 | F4: ='Monthly Haver'!H7 -> 50.7358 | G4: ='Monthly Haver'!I7 -> #N/A | H4: ='Monthly Haver'!J7 -> 56.9761 | I4: =GDS_Monthly!O121 -> 47.707038 | J4: =GDS_Monthly!D121 -> 66.434224 | K4: =GDS_Monthly!AH121 -> 353.75933 | L4: =GDS_Monthly!AI121 -> 346.54339 | M4: =GDS_Monthly!N121 -> 6.1876084 | N4: =GDS_Monthly!C121 -> 119.68072 | O4: =GDS_Monthly!F121 -> 4.4351016 | P4: =GDS_Monthly!G121 -> 6.0039844 | Q4: =GDS_Monthly!T121 -> 74.491016 | R4: =GDS_Monthly!V121 -> 79.707758 | S4: =GDS_Monthly!W121 -> 57.937052 | T4: =GDS_Monthly!X121 -> 37.299843 | U4: =GDS_Monthly!AA121 -> 48.513972 | V4: =GDS_Monthly!AC121 -> 34.981861 | W4: =GDS_Monthly!AE121 -> 30.593839 | X4: =GDS_Monthly!AF121 -> 70.57853 | Y4: =OECD!B4 -> 99.87469 | Z4: =OECD!C4 -> 96.64 | AA4: ='Monthly Haver'!K7 -> 106.60348 | AB4: ='Monthly Haver'!L7 -> 967 | AC4: =Quarterly!B2 -> 90.89 | AD4: =Quarterly!C2 -> 79.09 | AE4: =Quarterly!D2 -> 74.884141 | AF4: 8.096402
A5: 36251 | B5: ='Monthly Haver'!C8 -> 55.9986 | C5: ='Monthly Haver'!D8 -> 49.0474 | D5: ='Monthly Haver'!E8 -> #N/A | E5: ='Monthly Haver'!G8 -> 52.0895 | F5: ='Monthly Haver'!H8 -> 51.2547 | G5: ='Monthly Haver'!I8 -> #N/A | H5: ='Monthly Haver'!J8 -> 57.5913 | I5: =GDS_Monthly!O122 -> 47.641381 | J5: =GDS_Monthly!D122 -> 66.654924 | K5: =GDS_Monthly!AH122 -> 351.52124 | L5: =GDS_Monthly!AI122 -> 345.01638 | M5: =GDS_Monthly!N122 -> 6.1780133 | N5: =GDS_Monthly!C122 -> 120.19433 | O5: =GDS_Monthly!F122 -> 4.3134968 | P5: =GDS_Monthly!G122 -> 5.3779158 | Q5: =GDS_Monthly!T122 -> 74.77595 | R5: =GDS_Monthly!V122 -> 79.890023 | S5: =GDS_Monthly!W122 -> 59.170834 | T5: =GDS_Monthly!X122 -> 38.769809 | U5: =GDS_Monthly!AA122 -> 49.095826 | V5: =GDS_Monthly!AC122 -> 40.728868 | W5: =GDS_Monthly!AE122 -> 37.660442 | X5: =GDS_Monthly!AF122 -> 69.408326 | Y5: =OECD!B5 -> 100.0538 | Z5: =OECD!C5 -> 97.25 | AA5: ='Monthly Haver'!K8 -> 106.42934 | AB5: ='Monthly Haver'!L8 -> 924
A6: 36281 | B6: ='Monthly Haver'!C9 -> 55.9159 | C6: ='Monthly Haver'!D9 -> 51.0911 | D6: ='Monthly Haver'!E9 -> #N/A | E6: ='Monthly Haver'!G9 -> 52.6932 | F6: ='Monthly Haver'!H9 -> 52.3408 | G6: ='Monthly Haver'!I9 -> #N/A | H6: ='Monthly Haver'!J9 -> 56.5726 | I6: =GDS_Monthly!O123 -> 47.958598 | J6: =GDS_Monthly!D123 -> 67.105889 | K6: =GDS_Monthly!AH123 -> 357.45037 | L6: =GDS_Monthly!AI123 -> 347.63978 | M6: =GDS_Monthly!N123 -> 6.1298479 | N6: =GDS_Monthly!C123 -> 120.78991 | O6: =GDS_Monthly!F123 -> 4.5002013 | P6: =GDS_Monthly!G123 -> 4.951413 | Q6: =GDS_Monthly!T123 -> 74.86219 | R6: =GDS_Monthly!V123 -> 80.011264 | S6: =GDS_Monthly!W123 -> 59.728118 | T6: =GDS_Monthly!X123 -> 39.98686 | U6: =GDS_Monthly!AA123 -> 49.601793 | V6: =GDS_Monthly!AC123 -> 42.045514 | W6: =GDS_Monthly!AE123 -> 38.766827 | X6: =GDS_Monthly!AF123 -> 71.430794 | Y6: =OECD!B6 -> 100.2218 | Z6: =OECD!C6 -> 98.12 | AA6: ='Monthly Haver'!K9 -> 107.03248 | AB6: ='Monthly Haver'!L9 -> 1063
A7: 36312 | B7: ='Monthly Haver'!C10 -> 57.88 | C7: ='Monthly Haver'!D10 -> 52.1056 | D7: ='Monthly Haver'!E10 -> #N/A | E7: ='Monthly Haver'!G10 -> 53.6803 | F7: ='Monthly Haver'!H10 -> 53.5422 | G7: ='Monthly Haver'!I10 -> #N/A | H7: ='Monthly Haver'!J10 -> 57.4603 | I7: =GDS_Monthly!O124 -> 48.265373 | J7: =GDS_Monthly!D124 -> 67.334546 | K7: =GDS_Monthly!AH124 -> 366.78818 | L7: =GDS_Monthly!AI124 -> 350.30868 | M7: =GDS_Monthly!N124 -> 6.1282811 | N7: =GDS_Monthly!C124 -> 121.36047 | O7: =GDS_Monthly!F124 -> 4.8231277 | P7: =GDS_Monthly!G124 -> 4.8854794 | Q7: =GDS_Monthly!T124 -> 74.96249 | R7: =GDS_Monthly!V124 -> 80.12205 | S7: =GDS_Monthly!W124 -> 57.970115 | T7: =GDS_Monthly!X124 -> 39.018173 | U7: =GDS_Monthly!AA124 -> 48.23643 | V7: =GDS_Monthly!AC124 -> 42.719851 | W7: =GDS_Monthly!AE124 -> 39.30779 | X7: =GDS_Monthly!AF124 -> 71.122848 | Y7: =OECD!B7 -> 100.3789 | Z7: =OECD!C7 -> 98.7 | AA7: ='Monthly Haver'!K10 -> 108.01749 | AB7: ='Monthly Haver'!L10 -> 989 | AC7: =Quarterly!B3 -> 91.28 | AD7: =Quarterly!C3 -> 79.57 | AE7: =Quarterly!D3 -> 75.464053 | AF7: 4.1375112
A8: 36342 | B8: ='Monthly Haver'!C11 -> 57.3146 | C8: ='Monthly Haver'!D11 -> 54.7592 | D8: ='Monthly Haver'!E11 -> #N/A | E8: ='Monthly Haver'!G11 -> 53.4229 | F8: ='Monthly Haver'!H11 -> 53.1277 | G8: ='Monthly Haver'!I11 -> #N/A | H8: ='Monthly Haver'!J11 -> 59.4464 | I8: =GDS_Monthly!O125 -> 48.568561 | J8: =GDS_Monthly!D125 -> 67.702661 | K8: =GDS_Monthly!AH125 -> 368.14642 | L8: =GDS_Monthly!AI125 -> 360.15832 | M8: =GDS_Monthly!N125 -> 6.1016194 | N8: =GDS_Monthly!C125 -> 120.75109 | O8: =GDS_Monthly!F125 -> 4.9035408 | P8: =GDS_Monthly!G125 -> 4.749271 | Q8: =GDS_Monthly!T125 -> 75.212716 | R8: =GDS_Monthly!V125 -> 80.274977 | S8: =GDS_Monthly!W125 -> 56.295033 | T8: =GDS_Monthly!X125 -> 41.904733 | U8: =GDS_Monthly!AA125 -> 47.644857 | V8: =GDS_Monthly!AC125 -> 47.300332 | W8: =GDS_Monthly!AE125 -> 45.405164 | X8: =GDS_Monthly!AF125 -> 70.073576 | Y8: =OECD!B8 -> 100.5246 | Z8: =OECD!C8 -> 98.78 | AA8: ='Monthly Haver'!K11 -> 107.85762 | AB8: ='Monthly Haver'!L11 -> 977
A9: 36373 | B9: ='Monthly Haver'!C12 -> 58.4455 | C9: ='Monthly Haver'!D12 -> 56.7833 | D9: ='Monthly Haver'!E12 -> #N/A | E9: ='Monthly Haver'!G12 -> 53.5661 | F9: ='Monthly Haver'!H12 -> 54.0786 | G9: ='Monthly Haver'!I12 -> #N/A | H9: ='Monthly Haver'!J12 -> 59.4645 | I9: =GDS_Monthly!O126 -> 48.86523 | J9: =GDS_Monthly!D126 -> 68.116441 | K9: =GDS_Monthly!AH126 -> 376.04072 | L9: =GDS_Monthly!AI126 -> 365.35816 | M9: =GDS_Monthly!N126 -> 6.0777222 | N9: =GDS_Monthly!C126 -> 120.74856 | O9: =GDS_Monthly!F126 -> 5.0666091 | P9: =GDS_Monthly!G126 -> 4.815968 | Q9: =GDS_Monthly!T126 -> 75.426542 | R9: =GDS_Monthly!V126 -> 80.379334 | S9: =GDS_Monthly!W126 -> 57.952559 | T9: =GDS_Monthly!X126 -> 43.136454 | U9: =GDS_Monthly!AA126 -> 48.616018 | V9: =GDS_Monthly!AC126 -> 51.401241 | W9: =GDS_Monthly!AE126 -> 48.046108 | X9: =GDS_Monthly!AF126 -> 69.962439 | Y9: =OECD!B9 -> 100.6616 | Z9: =OECD!C9 -> 98.8 | AA9: ='Monthly Haver'!K12 -> 107.49371 | AB9: ='Monthly Haver'!L12 -> 1046
A10: 36404 | B10: ='Monthly Haver'!C13 -> 60.0929 | C10: ='Monthly Haver'!D13 -> 60.644 | D10: ='Monthly Haver'!E13 -> #N/A | E10: ='Monthly Haver'!G13 -> 53.5116 | F10: ='Monthly Haver'!H13 -> 55.688 | G10: ='Monthly Haver'!I13 -> #N/A | H10: ='Monthly Haver'!J13 -> 59.0417 | I10: =GDS_Monthly!O127 -> 48.872986 | J10: =GDS_Monthly!D127 -> 68.542555 | K10: =GDS_Monthly!AH127 -> 385.98611 | L10: =GDS_Monthly!AI127 -> 373.11636 | M10: =GDS_Monthly!N127 -> 6.0471354 | N10: =GDS_Monthly!C127 -> 120.32739 | O10: =GDS_Monthly!F127 -> 5.106116 | P10: =GDS_Monthly!G127 -> 4.8967155 | Q10: =GDS_Monthly!T127 -> 75.658393 | R10: =GDS_Monthly!V127 -> 80.595118 | S10: =GDS_Monthly!W127 -> 58.694531 | T10: =GDS_Monthly!X127 -> 45.284139 | U10: =GDS_Monthly!AA127 -> 49.635083 | V10: =GDS_Monthly!AC127 -> 54.866576 | W10: =GDS_Monthly!AE127 -> 52.726411 | X10: =GDS_Monthly!AF127 -> 72.033331 | Y10: =OECD!B10 -> 100.7954 | Z10: =OECD!C10 -> 98.59 | AA10: ='Monthly Haver'!K13 -> 106.90362 | AB10: ='Monthly Haver'!L13 -> 1146 | AC10: =Quarterly!B4 -> 91.69 | AD10: =Quarterly!C4 -> 80.19 | AE10: =Quarterly!D4 -> 76.352561 | AF10: 5.003416
A11: 36434 | B11: ='Monthly Haver'!C14 -> 60.8225 | C11: ='Monthly Haver'!D14 -> 60.5628 | D11: ='Monthly Haver'!E14 -> #N/A | E11: ='Monthly Haver'!G14 -> 54.1088 | F11: ='Monthly Haver'!H14 -> 56.5329 | G11: ='Monthly Haver'!I14 -> #N/A | H11: ='Monthly Haver'!J14 -> 60.3565 | I11: =GDS_Monthly!O128 -> 49.519842 | J11: =GDS_Monthly!D128 -> 68.798138 | K11: =GDS_Monthly!AH128 -> 391.70971 | L11: =GDS_Monthly!AI128 -> 382.24569 | M11: =GDS_Monthly!N128 -> 6.0298892 | N11: =GDS_Monthly!C128 -> 119.63202 | O11: =GDS_Monthly!F128 -> 5.2651836 | P11: =GDS_Monthly!G128 -> 4.8662165 | Q11: =GDS_Monthly!T128 -> 75.844546 | R11: =GDS_Monthly!V128 -> 80.763693 | S11: =GDS_Monthly!W128 -> 58.351763 | T11: =GDS_Monthly!X128 -> 45.088045 | U11: =GDS_Monthly!AA128 -> 50.364373 | V11: =GDS_Monthly!AC128 -> 55.667194 | W11: =GDS_Monthly!AE128 -> 51.797968 | X11: =GDS_Monthly!AF128 -> 73.127539 | Y11: =OECD!B11 -> 100.9314 | Z11: =OECD!C11 -> 99.03 | AA11: ='Monthly Haver'!K14 -> 105.98497 | AB11: ='Monthly Haver'!L14 -> 1339
A12: 36465 | B12: ='Monthly Haver'!C15 -> 58.687 | C12: ='Monthly Haver'!D15 -> 60.7023 | D12: ='Monthly Haver'!E15 -> #N/A | E12: ='Monthly Haver'!G15 -> 53.7348 | F12: ='Monthly Haver'!H15 -> 56.9871 | G12: ='Monthly Haver'!I15 -> #N/A | H12: ='Monthly Haver'!J15 -> 58.1496 | I12: =GDS_Monthly!O129 -> 49.685402 | J12: =GDS_Monthly!D129 -> 69.639348 | K12: =GDS_Monthly!AH129 -> 397.60195 | L12: =GDS_Monthly!AI129 -> 385.7613 | M12: =GDS_Monthly!N129 -> 5.9864186 | N12: =GDS_Monthly!C129 -> 121.30928 | O12: =GDS_Monthly!F129 -> 5.1110627 | P12: =GDS_Monthly!G129 -> 5.0130161 | Q12: =GDS_Monthly!T129 -> 75.998945 | R12: =GDS_Monthly!V129 -> 80.906541 | S12: =GDS_Monthly!W129 -> 57.356419 | T12: =GDS_Monthly!X129 -> 45.822383 | U12: =GDS_Monthly!AA129 -> 49.987955 | V12: =GDS_Monthly!AC129 -> 58.050902 | W12: =GDS_Monthly!AE129 -> 57.073002 | X12: =GDS_Monthly!AF129 -> 72.918189 | Y12: =OECD!B12 -> 101.0658 | Z12: =OECD!C12 -> 100.26 | AA12: ='Monthly Haver'!K15 -> 106.29799 | AB12: ='Monthly Haver'!L15 -> 1334
A13: 36495 | B13: ='Monthly Haver'!C16 -> 60.1061 | C13: ='Monthly Haver'!D16 -> 61.0619 | D13: ='Monthly Haver'!E16 -> #N/A | E13: ='Monthly Haver'!G16 -> 55.1017 | F13: ='Monthly Haver'!H16 -> 57.0854 | G13: ='Monthly Haver'!I16 -> #N/A | H13: ='Monthly Haver'!J16 -> 59.6569 | I13: =GDS_Monthly!O130 -> 50.349934 | J13: =GDS_Monthly!D130 -> 70.082023 | K13: =GDS_Monthly!AH130 -> 402.2412 | L13: =GDS_Monthly!AI130 -> 390.473 | M13: =GDS_Monthly!N130 -> 5.9072491 | N13: =GDS_Monthly!C130 -> 122.6339 | O13: =GDS_Monthly!F130 -> 5.236105 | P13: =GDS_Monthly!G130 -> 5.0392185 | Q13: =GDS_Monthly!T130 -> 76.159788 | R13: =GDS_Monthly!V130 -> 81.05587 | S13: =GDS_Monthly!W130 -> 57.648097 | T13: =GDS_Monthly!X130 -> 47.048003 | U13: =GDS_Monthly!AA130 -> 50.26534 | V13: =GDS_Monthly!AC130 -> 59.419051 | W13: =GDS_Monthly!AE130 -> 59.061798 | X13: =GDS_Monthly!AF130 -> 72.298999 | Y13: =OECD!B13 -> 101.1871 | Z13: =OECD!C13 -> 100.67 | AA13: ='Monthly Haver'!K16 -> 105.52769 | AB13: ='Monthly Haver'!L16 -> 1343 | AC13: =Quarterly!B5 -> 92.42 | AD13: =Quarterly!C5 -> 80.65 | AE13: =Quarterly!D5 -> 77.366935 | AF13: 6.2985714
A14: 36526 | B14: ='Monthly Haver'!C17 -> 59.7223 | C14: ='Monthly Haver'!D17 -> 62.9708 | D14: ='Monthly Haver'!E17 -> #N/A | E14: ='Monthly Haver'!G17 -> 54.1178 | F14: ='Monthly Haver'!H17 -> 55.3682 | G14: ='Monthly Haver'!I17 -> #N/A | H14: ='Monthly Haver'!J17 -> 57.9939 | I14: =GDS_Monthly!O131 -> 50.176158 | J14: =GDS_Monthly!D131 -> 69.956239 | K14: =GDS_Monthly!AH131 -> 410.72767 | L14: =GDS_Monthly!AI131 -> 394.41377 | M14: =GDS_Monthly!N131 -> 6.0451954 | N14: =GDS_Monthly!C131 -> 124.73363 | O14: =GDS_Monthly!F131 -> 5.5589142 | P14: =GDS_Monthly!G131 -> 4.9952789 | Q14: =GDS_Monthly!T131 -> 76.378345 | R14: =GDS_Monthly!V131 -> 81.243416 | S14: =GDS_Monthly!W131 -> 58.498819 | T14: =GDS_Monthly!X131 -> 49.224077 | U14: =GDS_Monthly!AA131 -> 50.838291 | V14: =GDS_Monthly!AC131 -> 62.420219 | W14: =GDS_Monthly!AE131 -> 59.634459 | X14: =GDS_Monthly!AF131 -> 71.264288 | Y14: =OECD!B14 -> 101.2855 | Z14: =OECD!C14 -> 100.84 | AA14: ='Monthly Haver'!K17 -> 105.35406 | AB14: ='Monthly Haver'!L17 -> 1371
A15: 36557 | B15: ='Monthly Haver'!C18 -> 58.9161 | C15: ='Monthly Haver'!D18 -> 65.125 | D15: ='Monthly Haver'!E18 -> #N/A | E15: ='Monthly Haver'!G18 -> 54.6501 | F15: ='Monthly Haver'!H18 -> 55.2975 | G15: ='Monthly Haver'!I18 -> #N/A | H15: ='Monthly Haver'!J18 -> 58.2848 | I15: =GDS_Monthly!O132 -> 50.781313 | J15: =GDS_Monthly!D132 -> 70.745572 | K15: =GDS_Monthly!AH132 -> 418.8283 | L15: =GDS_Monthly!AI132 -> 399.54289 | M15: =GDS_Monthly!N132 -> 6.0835886 | N15: =GDS_Monthly!C132 -> 123.57431 | O15: =GDS_Monthly!F132 -> 5.4797378 | P15: =GDS_Monthly!G132 -> 5.1302965 | Q15: =GDS_Monthly!T132 -> 76.604845 | R15: =GDS_Monthly!V132 -> 81.364571 | S15: =GDS_Monthly!W132 -> 59.247223 | T15: =GDS_Monthly!X132 -> 50.275821 | U15: =GDS_Monthly!AA132 -> 52.118855 | V15: =GDS_Monthly!AC132 -> 66.611449 | W15: =GDS_Monthly!AE132 -> 65.421333 | X15: =GDS_Monthly!AF132 -> 74.784893 | Y15: =OECD!B15 -> 101.343 | Z15: =OECD!C15 -> 100.41 | AA15: ='Monthly Haver'!K18 -> 107.38453 | AB15: ='Monthly Haver'!L18 -> 1393
A16: 36586 | B16: ='Monthly Haver'!C19 -> 60.2266 | C16: ='Monthly Haver'!D19 -> 67.6545 | D16: ='Monthly Haver'!E19 -> #N/A | E16: ='Monthly Haver'!G19 -> 55.2532 | F16: ='Monthly Haver'!H19 -> 55.6455 | G16: ='Monthly Haver'!I19 -> #N/A | H16: ='Monthly Haver'!J19 -> 60.3654 | I16: =GDS_Monthly!O133 -> 50.944052 | J16: =GDS_Monthly!D133 -> 71.04608 | K16: =GDS_Monthly!AH133 -> 421.39759 | L16: =GDS_Monthly!AI133 -> 399.77473 | M16: =GDS_Monthly!N133 -> 6.0242389 | N16: =GDS_Monthly!C133 -> 122.47531 | O16: =GDS_Monthly!F133 -> 5.3142501 | P16: =GDS_Monthly!G133 -> 5.1971473 | Q16: =GDS_Monthly!T133 -> 76.829987 | R16: =GDS_Monthly!V133 -> 81.525814 | S16: =GDS_Monthly!W133 -> 60.339642 | T16: =GDS_Monthly!X133 -> 49.805626 | U16: =GDS_Monthly!AA133 -> 52.446592 | V16: =GDS_Monthly!AC133 -> 67.225029 | W16: =GDS_Monthly!AE133 -> 66.343979 | X16: =GDS_Monthly!AF133 -> 75.959245 | Y16: =OECD!B16 -> 101.3606 | Z16: =OECD!C16 -> 101.06 | AA16: ='Monthly Haver'!K19 -> 107.60909 | AB16: ='Monthly Haver'!L19 -> 1621 | AC16: =Quarterly!B6 -> 92.66 | AD16: =Quarterly!C6 -> 81.08 | AE16: =Quarterly!D6 -> 78.24454 | AF16: 5.3384295
A17: 36617 | B17: ='Monthly Haver'!C20 -> 60.3376 | C17: ='Monthly Haver'!D20 -> 64.9139 | D17: ='Monthly Haver'!E20 -> #N/A | E17: ='Monthly Haver'!G20 -> 55.7746 | F17: ='Monthly Haver'!H20 -> 55.998 | G17: ='Monthly Haver'!I20 -> #N/A | H17: ='Monthly Haver'!J20 -> 61.1896 | I17: =GDS_Monthly!O134 -> 51.089472 | J17: =GDS_Monthly!D134 -> 71.603873 | K17: =GDS_Monthly!AH134 -> 419.03335 | L17: =GDS_Monthly!AI134 -> 397.73526 | M17: =GDS_Monthly!N134 -> 5.8905387 | N17: =GDS_Monthly!C134 -> 122.4792 | O17: =GDS_Monthly!F134 -> 5.1670629 | P17: =GDS_Monthly!G134 -> 5.2911187 | Q17: =GDS_Monthly!T134 -> 76.810269 | R17: =GDS_Monthly!V134 -> 81.613219 | S17: =GDS_Monthly!W134 -> 63.093431 | T17: =GDS_Monthly!X134 -> 47.738663 | U17: =GDS_Monthly!AA134 -> 53.032226 | V17: =GDS_Monthly!AC134 -> 61.406298 | W17: =GDS_Monthly!AE134 -> 56.789454 | X17: =GDS_Monthly!AF134 -> 75.442087 | Y17: =OECD!B17 -> 101.3398 | Z17: =OECD!C17 -> 101.16 | AA17: ='Monthly Haver'!K20 -> 107.9357 | AB17: ='Monthly Haver'!L20 -> 1667
A18: 36647 | B18: ='Monthly Haver'!C21 -> 58.7485 | C18: ='Monthly Haver'!D21 -> 64.1096 | D18: ='Monthly Haver'!E21 -> #N/A | E18: ='Monthly Haver'!G21 -> 55.4881 | F18: ='Monthly Haver'!H21 -> 54.8952 | G18: ='Monthly Haver'!I21 -> #N/A | H18: ='Monthly Haver'!J21 -> 60.0442 | I18: =GDS_Monthly!O135 -> 51.36414 | J18: =GDS_Monthly!D135 -> 72.267812 | K18: =GDS_Monthly!AH135 -> 429.03424 | L18: =GDS_Monthly!AI135 -> 406.90142 | M18: =GDS_Monthly!N135 -> 5.8705114 | N18: =GDS_Monthly!C135 -> 124.37239 | O18: =GDS_Monthly!F135 -> 5.3815595 | P18: =GDS_Monthly!G135 -> 5.4390043 | Q18: =GDS_Monthly!T135 -> 76.950422 | R18: =GDS_Monthly!V135 -> 81.757797 | S18: =GDS_Monthly!W135 -> 62.172247 | T18: =GDS_Monthly!X135 -> 48.89688 | U18: =GDS_Monthly!AA135 -> 52.797742 | V18: =GDS_Monthly!AC135 -> 68.959928 | W18: =GDS_Monthly!AE135 -> 67.346607 | X18: =GDS_Monthly!AF135 -> 76.366215 | Y18: =OECD!B18 -> 101.2792 | Z18: =OECD!C18 -> 100.53 | AA18: ='Monthly Haver'!K21 -> 110.66388 | AB18: ='Monthly Haver'!L21 -> 1602
A19: 36678 | B19: ='Monthly Haver'!C22 -> 57.7828 | C19: ='Monthly Haver'!D22 -> 63.6164 | D19: ='Monthly Haver'!E22 -> #N/A | E19: ='Monthly Haver'!G22 -> 55.3404 | F19: ='Monthly Haver'!H22 -> 53.8364 | G19: ='Monthly Haver'!I22 -> #N/A | H19: ='Monthly Haver'!J22 -> 60.0799 | I19: =GDS_Monthly!O136 -> 51.733945 | J19: =GDS_Monthly!D136 -> 72.409277 | K19: =GDS_Monthly!AH136 -> 439.59744 | L19: =GDS_Monthly!AI136 -> 415.8594 | M19: =GDS_Monthly!N136 -> 5.8500903 | N19: =GDS_Monthly!C136 -> 122.82768 | O19: =GDS_Monthly!F136 -> 5.1788501 | P19: =GDS_Monthly!G136 -> 5.5837764 | Q19: =GDS_Monthly!T136 -> 77.297687 | R19: =GDS_Monthly!V136 -> 81.926246 | S19: =GDS_Monthly!W136 -> 59.982856 | T19: =GDS_Monthly!X136 -> 46.758789 | U19: =GDS_Monthly!AA136 -> 51.520794 | V19: =GDS_Monthly!AC136 -> 75.499491 | W19: =GDS_Monthly!AE136 -> 72.152931 | X19: =GDS_Monthly!AF136 -> 75.144639 | Y19: =OECD!B19 -> 101.1854 | Z19: =OECD!C19 -> 100.36 | AA19: ='Monthly Haver'!K22 -> 111.02743 | AB19: ='Monthly Haver'!L22 -> 1589 | AC19: =Quarterly!B7 -> 93.27 | AD19: =Quarterly!C7 -> 81.77 | AE19: =Quarterly!D7 -> 79.135579 | AF19: 5.031488
A20: 36708 | B20: ='Monthly Haver'!C23 -> 58.1305 | C20: ='Monthly Haver'!D23 -> 62.654 | D20: ='Monthly Haver'!E23 -> #N/A | E20: ='Monthly Haver'!G23 -> 54.033 | F20: ='Monthly Haver'!H23 -> 54.2619 | G20: ='Monthly Haver'!I23 -> #N/A | H20: ='Monthly Haver'!J23 -> 57.7018 | I20: =GDS_Monthly!O137 -> 51.988911 | J20: =GDS_Monthly!D137 -> 72.624944 | K20: =GDS_Monthly!AH137 -> 440.56235 | L20: =GDS_Monthly!AI137 -> 413.20757 | M20: =GDS_Monthly!N137 -> 5.8257868 | N20: =GDS_Monthly!C137 -> 123.97266 | O20: =GDS_Monthly!F137 -> 5.1949882 | P20: =GDS_Monthly!G137 -> 5.4866403 | Q20: =GDS_Monthly!T137 -> 77.564953 | R20: =GDS_Monthly!V137 -> 82.044023 | S20: =GDS_Monthly!W137 -> 58.090687 | T20: =GDS_Monthly!X137 -> 47.341899 | U20: =GDS_Monthly!AA137 -> 50.722671 | V20: =GDS_Monthly!AC137 -> 73.041609 | W20: =GDS_Monthly!AE137 -> 68.971892 | X20: =GDS_Monthly!AF137 -> 73.574183 | Y20: =OECD!B20 -> 101.061 | Z20: =OECD!C20 -> 99.81 | AA20: ='Monthly Haver'!K23 -> 110.71677 | AB20: ='Monthly Haver'!L23 -> 1618
A21: 36739 | B21: ='Monthly Haver'!C24 -> 57.7197 | C21: ='Monthly Haver'!D24 -> 59.6309 | D21: ='Monthly Haver'!E24 -> #N/A | E21: ='Monthly Haver'!G24 -> 54.614 | F21: ='Monthly Haver'!H24 -> 52.7467 | G21: ='Monthly Haver'!I24 -> #N/A | H21: ='Monthly Haver'!J24 -> 60.6218 | I21: =GDS_Monthly!O138 -> 52.172916 | J21: =GDS_Monthly!D138 -> 73.043339 | K21: =GDS_Monthly!AH138 -> 447.25166 | L21: =GDS_Monthly!AI138 -> 421.74277 | M21: =GDS_Monthly!N138 -> 5.8237091 | N21: =GDS_Monthly!C138 -> 123.48507 | O21: =GDS_Monthly!F138 -> 5.109367 | P21: =GDS_Monthly!G138 -> 5.6640235 | Q21: =GDS_Monthly!T138 -> 77.688729 | R21: =GDS_Monthly!V138 -> 82.200556 | S21: =GDS_Monthly!W138 -> 57.046077 | T21: =GDS_Monthly!X138 -> 47.330524 | U21: =GDS_Monthly!AA138 -> 49.823975 | V21: =GDS_Monthly!AC138 -> 76.558522 | W21: =GDS_Monthly!AE138 -> 72.866485 | X21: =GDS_Monthly!AF138 -> 71.061274 | Y21: =OECD!B21 -> 100.9082 | Z21: =OECD!C21 -> 99.36 | AA21: ='Monthly Haver'!K24 -> 110.67823 | AB21: ='Monthly Haver'!L24 -> 1639
A22: 36770 | B22: ='Monthly Haver'!C25 -> 57.058 | C22: ='Monthly Haver'!D25 -> 62.4361 | D22: ='Monthly Haver'!E25 -> #N/A | E22: ='Monthly Haver'!G25 -> 54.462 | F22: ='Monthly Haver'!H25 -> 52.1289 | G22: ='Monthly Haver'!I25 -> #N/A | H22: ='Monthly Haver'!J25 -> 59.1884 | I22: =GDS_Monthly!O139 -> 52.686412 | J22: =GDS_Monthly!D139 -> 72.965545 | K22: =GDS_Monthly!AH139 -> 443.67022 | L22: =GDS_Monthly!AI139 -> 418.21104 | M22: =GDS_Monthly!N139 -> 5.7514554 | N22: =GDS_Monthly!C139 -> 123.52879 | O22: =GDS_Monthly!F139 -> 5.1486397 | P22: =GDS_Monthly!G139 -> 5.674745 | Q22: =GDS_Monthly!T139 -> 77.981047 | R22: =GDS_Monthly!V139 -> 82.394058 | S22: =GDS_Monthly!W139 -> 56.554047 | T22: =GDS_Monthly!X139 -> 49.503901 | U22: =GDS_Monthly!AA139 -> 50.073045 | V22: =GDS_Monthly!AC139 -> 83.121869 | W22: =GDS_Monthly!AE139 -> 80.359117 | X22: =GDS_Monthly!AF139 -> 72.716941 | Y22: =OECD!B22 -> 100.7208 | Z22: =OECD!C22 -> 99.81 | AA22: ='Monthly Haver'!K25 -> 112.70334 | AB22: ='Monthly Haver'!L25 -> 1712 | AC22: =Quarterly!B8 -> 93.74 | AD22: =Quarterly!C8 -> 82.13 | AE22: =Quarterly!D8 -> 79.553245 | AF22: 3.1388242
A23: 36800 | B23: ='Monthly Haver'!C26 -> 56.1097 | C23: ='Monthly Haver'!D26 -> 62.049 | D23: ='Monthly Haver'!E26 -> #N/A | E23: ='Monthly Haver'!G26 -> 54.3992 | F23: ='Monthly Haver'!H26 -> 51.15 | G23: ='Monthly Haver'!I26 -> #N/A | H23: ='Monthly Haver'!J26 -> 58.3064 | I23: =GDS_Monthly!O140 -> 52.824041 | J23: =GDS_Monthly!D140 -> 73.155888 | K23: =GDS_Monthly!AH140 -> 444.74976 | L23: =GDS_Monthly!AI140 -> 417.99235 | M23: =GDS_Monthly!N140 -> 5.7037175 | N23: =GDS_Monthly!C140 -> 121.97587 | O23: =GDS_Monthly!F140 -> 5.147001 | P23: =GDS_Monthly!G140 -> 5.7516998 | Q23: =GDS_Monthly!T140 -> 78.111605 | R23: =GDS_Monthly!V140 -> 82.514801 | S23: =GDS_Monthly!W140 -> 56.219321 | T23: =GDS_Monthly!X140 -> 46.642271 | U23: =GDS_Monthly!AA140 -> 49.192622 | V23: =GDS_Monthly!AC140 -> 82.635599 | W23: =GDS_Monthly!AE140 -> 79.171231 | X23: =GDS_Monthly!AF140 -> 71.511905 | Y23: =OECD!B23 -> 100.4908 | Z23: =OECD!C23 -> 98.93 | AA23: ='Monthly Haver'!K26 -> 114.52209 | AB23: ='Monthly Haver'!L26 -> 1734
A24: 36831 | B24: ='Monthly Haver'!C27 -> 54.8683 | C24: ='Monthly Haver'!D27 -> 59.7087 | D24: ='Monthly Haver'!E27 -> #N/A | E24: ='Monthly Haver'!G27 -> 54.1268 | F24: ='Monthly Haver'!H27 -> 50.7467 | G24: ='Monthly Haver'!I27 -> #N/A | H24: ='Monthly Haver'!J27 -> 58.2362 | I24: =GDS_Monthly!O141 -> 53.185491 | J24: =GDS_Monthly!D141 -> 73.505122 | K24: =GDS_Monthly!AH141 -> 445.89885 | L24: =GDS_Monthly!AI141 -> 416.36563 | M24: =GDS_Monthly!N141 -> 5.6488894 | N24: =GDS_Monthly!C141 -> 121.10394 | O24: =GDS_Monthly!F141 -> 5.0784778 | P24: =GDS_Monthly!G141 -> 5.7833266 | Q24: =GDS_Monthly!T141 -> 78.343168 | R24: =GDS_Monthly!V141 -> 82.71185 | S24: =GDS_Monthly!W141 -> 56.874127 | T24: =GDS_Monthly!X141 -> 45.256696 | U24: =GDS_Monthly!AA141 -> 49.26405 | V24: =GDS_Monthly!AC141 -> 85.150599 | W24: =GDS_Monthly!AE141 -> 81.702649 | X24: =GDS_Monthly!AF141 -> 73.199228 | Y24: =OECD!B24 -> 100.2229 | Z24: =OECD!C24 -> 97.98 | AA24: ='Monthly Haver'!K27 -> 114.70455 | AB24: ='Monthly Haver'!L27 -> 1722
A25: 36861 | B25: ='Monthly Haver'!C28 -> 52.9053 | C25: ='Monthly Haver'!D28 -> 59.8902 | D25: ='Monthly Haver'!E28 -> #N/A | E25: ='Monthly Haver'!G28 -> 52.0186 | F25: ='Monthly Haver'!H28 -> 47.8511 | G25: ='Monthly Haver'!I28 -> #N/A | H25: ='Monthly Haver'!J28 -> 56.9885 | I25: =GDS_Monthly!O142 -> 53.302244 | J25: =GDS_Monthly!D142 -> 73.620412 | K25: =GDS_Monthly!AH142 -> 444.42847 | L25: =GDS_Monthly!AI142 -> 420.47497 | M25: =GDS_Monthly!N142 -> 5.5596627 | N25: =GDS_Monthly!C142 -> 120.07657 | O25: =GDS_Monthly!F142 -> 4.7521486 | P25: =GDS_Monthly!G142 -> 5.7562082 | Q25: =GDS_Monthly!T142 -> 78.522684 | R25: =GDS_Monthly!V142 -> 82.763051 | S25: =GDS_Monthly!W142 -> 60.217218 | T25: =GDS_Monthly!X142 -> 46.413625 | U25: =GDS_Monthly!AA142 -> 50.823979 | V25: =GDS_Monthly!AC142 -> 84.12611 | W25: =GDS_Monthly!AE142 -> 63.259156 | X25: =GDS_Monthly!AF142 -> 68.309323 | Y25: =OECD!B25 -> 99.93034 | Z25: =OECD!C25 -> 96.4 | AA25: ='Monthly Haver'!K28 -> 115.36207 | AB25: ='Monthly Haver'!L28 -> 1609 | AC25: =Quarterly!B9 -> 94.19 | AD25: =Quarterly!C9 -> 82.64 | AE25: =Quarterly!D9 -> 80.060844 | AF25: 2.831619
A26: 36892 | B26: ='Monthly Haver'!C29 -> 50.4007 | C26: ='Monthly Haver'!D29 -> 59.8426 | D26: ='Monthly Haver'!E29 -> #N/A | E26: ='Monthly Haver'!G29 -> 51.614 | F26: ='Monthly Haver'!H29 -> 46.6736 | G26: ='Monthly Haver'!I29 -> #N/A | H26: ='Monthly Haver'!J29 -> 53.5145 | I26: =GDS_Monthly!O143 -> 53.764579 | J26: =GDS_Monthly!D143 -> 72.974549 | K26: =GDS_Monthly!AH143 -> 446.7043 | L26: =GDS_Monthly!AI143 -> 420.84894 | M26: =GDS_Monthly!N143 -> 5.7207861 | N26: =GDS_Monthly!C143 -> 117.10012 | O26: =GDS_Monthly!F143 -> 4.6486254 | P26: =GDS_Monthly!G143 -> 5.3621466 | Q26: =GDS_Monthly!T143 -> 78.697527 | R26: =GDS_Monthly!V143 -> 82.930413 | S26: =GDS_Monthly!W143 -> 58.583315 | T26: =GDS_Monthly!X143 -> 46.202093 | U26: =GDS_Monthly!AA143 -> 50.64648 | V26: =GDS_Monthly!AC143 -> 83.181449 | W26: =GDS_Monthly!AE143 -> 64.557624 | X26: =GDS_Monthly!AF143 -> 71.442514 | Y26: =OECD!B26 -> 99.64638 | Z26: =OECD!C26 -> 96.53 | AA26: ='Monthly Haver'!K29 -> 118.40965 | AB26: ='Monthly Haver'!L29 -> 1566
A27: 36923 | B27: ='Monthly Haver'!C30 -> 50.6961 | C27: ='Monthly Haver'!D30 -> 56.06 | D27: ='Monthly Haver'!E30 -> #N/A | E27: ='Monthly Haver'!G30 -> 50.0679 | F27: ='Monthly Haver'!H30 -> 46.1233 | G27: ='Monthly Haver'!I30 -> #N/A | H27: ='Monthly Haver'!J30 -> 52.5185 | I27: =GDS_Monthly!O144 -> 54.06587 | J27: =GDS_Monthly!D144 -> 73.165997 | K27: =GDS_Monthly!AH144 -> 435.01892 | L27: =GDS_Monthly!AI144 -> 416.03695 | M27: =GDS_Monthly!N144 -> 5.7360373 | N27: =GDS_Monthly!C144 -> 115.25609 | O27: =GDS_Monthly!F144 -> 4.5837045 | P27: =GDS_Monthly!G144 -> 5.3748198 | Q27: =GDS_Monthly!T144 -> 78.830266 | R27: =GDS_Monthly!V144 -> 83.071764 | S27: =GDS_Monthly!W144 -> 57.566908 | T27: =GDS_Monthly!X144 -> 45.4812 | U27: =GDS_Monthly!AA144 -> 49.968087 | V27: =GDS_Monthly!AC144 -> 76.91737 | W27: =GDS_Monthly!AE144 -> 68.241037 | X27: =GDS_Monthly!AF144 -> 70.969655 | Y27: =OECD!B27 -> 99.40015 | Z27: =OECD!C27 -> 95.49 | AA27: ='Monthly Haver'!K30 -> 116.84794 | AB27: ='Monthly Haver'!L30 -> 1479
A28: 36951 | B28: ='Monthly Haver'!C31 -> 50.7784 | C28: ='Monthly Haver'!D31 -> 53.3781 | D28: ='Monthly Haver'!E31 -> #N/A | E28: ='Monthly Haver'!G31 -> 50.0285 | F28: ='Monthly Haver'!H31 -> 46.3158 | G28: ='Monthly Haver'!I31 -> #N/A | H28: ='Monthly Haver'!J31 -> 51.2981 | I28: =GDS_Monthly!O145 -> 54.102856 | J28: =GDS_Monthly!D145 -> 72.829265 | K28: =GDS_Monthly!AH145 -> 430.79794 | L28: =GDS_Monthly!AI145 -> 407.463 | M28: =GDS_Monthly!N145 -> 5.8012311 | N28: =GDS_Monthly!C145 -> 117.0193 | O28: =GDS_Monthly!F145 -> 4.447699 | P28: =GDS_Monthly!G145 -> 5.1112704 | Q28: =GDS_Monthly!T145 -> 78.965663 | R28: =GDS_Monthly!V145 -> 83.252309 | S28: =GDS_Monthly!W145 -> 58.986932 | T28: =GDS_Monthly!X145 -> 43.998092 | U28: =GDS_Monthly!AA145 -> 49.819342 | V28: =GDS_Monthly!AC145 -> 72.361527 | W28: =GDS_Monthly!AE145 -> 63.398528 | X28: =GDS_Monthly!AF145 -> 67.420782 | Y28: =OECD!B28 -> 99.20429 | Z28: =OECD!C28 -> 94.09 | AA28: ='Monthly Haver'!K31 -> 117.21304 | AB28: ='Monthly Haver'!L31 -> 1502 | AC28: =Quarterly!B10 -> 94.87 | AD28: =Quarterly!C10 -> 83.24 | AE28: =Quarterly!D10 -> 80.389859 | AF28: 1.8286258
A29: 36982 | B29: ='Monthly Haver'!C32 -> 48.3887 | C29: ='Monthly Haver'!D32 -> 51.5304 | D29: ='Monthly Haver'!E32 -> #N/A | E29: ='Monthly Haver'!G32 -> 47.9972 | F29: ='Monthly Haver'!H32 -> 45.661 | G29: ='Monthly Haver'!I32 -> #N/A | H29: ='Monthly Haver'!J32 -> 49.7308 | I29: =GDS_Monthly!O146 -> 54.300763 | J29: =GDS_Monthly!D146 -> 72.403777 | K29: =GDS_Monthly!AH146 -> 420.24987 | L29: =GDS_Monthly!AI146 -> 397.21286 | M29: =GDS_Monthly!N146 -> 5.7580679 | N29: =GDS_Monthly!C146 -> 114.6768 | O29: =GDS_Monthly!F146 -> 4.6581414 | P29: =GDS_Monthly!G146 -> 4.9050427 | Q29: =GDS_Monthly!T146 -> 79.233715 | R29: =GDS_Monthly!V146 -> 83.457663 | S29: =GDS_Monthly!W146 -> 59.415534 | T29: =GDS_Monthly!X146 -> 43.583063 | U29: =GDS_Monthly!AA146 -> 49.729305 | V29: =GDS_Monthly!AC146 -> 73.375902 | W29: =GDS_Monthly!AE146 -> 65.630559 | X29: =GDS_Monthly!AF146 -> 68.901251 | Y29: =OECD!B29 -> 99.05669 | Z29: =OECD!C29 -> 93.48 | AA29: ='Monthly Haver'!K32 -> 118.05614 | AB29: ='Monthly Haver'!L32 -> 1440
A30: 37012 | B30: ='Monthly Haver'!C33 -> 49.1345 | C30: ='Monthly Haver'!D33 -> 52.8845 | D30: ='Monthly Haver'!E33 -> #N/A | E30: ='Monthly Haver'!G33 -> 47.5178 | F30: ='Monthly Haver'!H33 -> 44.7577 | G30: ='Monthly Haver'!I33 -> #N/A | H30: ='Monthly Haver'!J33 -> 49.4231 | I30: =GDS_Monthly!O147 -> 54.78373 | J30: =GDS_Monthly!D147 -> 72.572162 | K30: =GDS_Monthly!AH147 -> 415.64726 | L30: =GDS_Monthly!AI147 -> 396.12808 | M30: =GDS_Monthly!N147 -> 5.8111765 | N30: =GDS_Monthly!C147 -> 116.13958 | O30: =GDS_Monthly!F147 -> 4.8067438 | P30: =GDS_Monthly!G147 -> 4.6025303 | Q30: =GDS_Monthly!T147 -> 79.554539 | R30: =GDS_Monthly!V147 -> 83.626744 | S30: =GDS_Monthly!W147 -> 60.901622 | T30: =GDS_Monthly!X147 -> 44.887397 | U30: =GDS_Monthly!AA147 -> 50.456502 | V30: =GDS_Monthly!AC147 -> 73.758302 | W30: =GDS_Monthly!AE147 -> 70.73505 | X30: =GDS_Monthly!AF147 -> 67.967114 | Y30: =OECD!B30 -> 98.94745 | Z30: =OECD!C30 -> 93.87 | AA30: ='Monthly Haver'!K33 -> 117.89707 | AB30: ='Monthly Haver'!L33 -> 1448
A31: 37043 | B31: ='Monthly Haver'!C34 -> 50.8036 | C31: ='Monthly Haver'!D34 -> 50.7474 | D31: ='Monthly Haver'!E34 -> #N/A | E31: ='Monthly Haver'!G34 -> 46.9487 | F31: ='Monthly Haver'!H34 -> 45.6322 | G31: ='Monthly Haver'!I34 -> #N/A | H31: ='Monthly Haver'!J34 -> 51.9596 | I31: =GDS_Monthly!O148 -> 55.042304 | J31: =GDS_Monthly!D148 -> 72.368832 | K31: =GDS_Monthly!AH148 -> 409.56113 | L31: =GDS_Monthly!AI148 -> 389.67946 | M31: =GDS_Monthly!N148 -> 5.7769906 | N31: =GDS_Monthly!C148 -> 116.65422 | O31: =GDS_Monthly!F148 -> 4.7156118 | P31: =GDS_Monthly!G148 -> 4.5418522 | Q31: =GDS_Monthly!T148 -> 79.742391 | R31: =GDS_Monthly!V148 -> 83.860782 | S31: =GDS_Monthly!W148 -> 60.678317 | T31: =GDS_Monthly!X148 -> 43.086933 | U31: =GDS_Monthly!AA148 -> 49.629598 | V31: =GDS_Monthly!AC148 -> 71.154271 | W31: =GDS_Monthly!AE148 -> 69.920647 | X31: =GDS_Monthly!AF148 -> 68.563413 | Y31: =OECD!B31 -> 98.8525 | Z31: =OECD!C31 -> 93.61 | AA31: ='Monthly Haver'!K34 -> 117.75357 | AB31: ='Monthly Haver'!L34 -> 1377 | AC31: =Quarterly!B11 -> 94.56 | AD31: =Quarterly!C11 -> 83.74 | AE31: =Quarterly!D11 -> 80.603238 | AF31: 1.9835864
A32: 37073 | B32: ='Monthly Haver'!C35 -> 49.0458 | C32: ='Monthly Haver'!D35 -> 47.4859 | D32: ='Monthly Haver'!E35 -> #N/A | E32: ='Monthly Haver'!G35 -> 47.5515 | F32: ='Monthly Haver'!H35 -> 45.7461 | G32: ='Monthly Haver'!I35 -> #N/A | H32: ='Monthly Haver'!J35 -> 49.5353 | I32: =GDS_Monthly!O149 -> 54.93228 | J32: =GDS_Monthly!D149 -> 71.744909 | K32: =GDS_Monthly!AH149 -> 402.89239 | L32: =GDS_Monthly!AI149 -> 381.13564 | M32: =GDS_Monthly!N149 -> 5.97362 | N32: =GDS_Monthly!C149 -> 115.91216 | O32: =GDS_Monthly!F149 -> 4.8644393 | P32: =GDS_Monthly!G149 -> 4.4911541 | Q32: =GDS_Monthly!T149 -> 79.7632 | R32: =GDS_Monthly!V149 -> 84.044723 | S32: =GDS_Monthly!W149 -> 62.228079 | T32: =GDS_Monthly!X149 -> 41.076991 | U32: =GDS_Monthly!AA149 -> 49.630125 | V32: =GDS_Monthly!AC149 -> 64.966556 | W32: =GDS_Monthly!AE149 -> 64.280784 | X32: =GDS_Monthly!AF149 -> 66.219002 | Y32: =OECD!B32 -> 98.76515 | Z32: =OECD!C32 -> 93.36 | AA32: ='Monthly Haver'!K35 -> 116.59327 | AB32: ='Monthly Haver'!L35 -> 1221
A33: 37104 | B33: ='Monthly Haver'!C36 -> 49.3999 | C33: ='Monthly Haver'!D36 -> 45.6912 | D33: ='Monthly Haver'!E36 -> #N/A | E33: ='Monthly Haver'!G36 -> 47.8177 | F33: ='Monthly Haver'!H36 -> 47.6059 | G33: ='Monthly Haver'!I36 -> #N/A | H33: ='Monthly Haver'!J36 -> 48.7541 | I33: =GDS_Monthly!O150 -> 55.183508 | J33: =GDS_Monthly!D150 -> 72.347956 | K33: =GDS_Monthly!AH150 -> 407.99097 | L33: =GDS_Monthly!AI150 -> 390.59732 | M33: =GDS_Monthly!N150 -> 5.9925186 | N33: =GDS_Monthly!C150 -> 115.11301 | O33: =GDS_Monthly!F150 -> 4.5464799 | P33: =GDS_Monthly!G150 -> 4.291444 | Q33: =GDS_Monthly!T150 -> 79.868881 | R33: =GDS_Monthly!V150 -> 84.210302 | S33: =GDS_Monthly!W150 -> 62.275 | T33: =GDS_Monthly!X150 -> 39.745044 | U33: =GDS_Monthly!AA150 -> 49.234081 | V33: =GDS_Monthly!AC150 -> 66.102523 | W33: =GDS_Monthly!AE150 -> 65.642332 | X33: =GDS_Monthly!AF150 -> 64.801689 | Y33: =OECD!B33 -> 98.68546 | Z33: =OECD!C33 -> 93.24 | AA33: ='Monthly Haver'!K36 -> 115.02526 | AB33: ='Monthly Haver'!L36 -> 980
A34: 37135 | B34: ='Monthly Haver'!C37 -> 49.479 | C34: ='Monthly Haver'!D37 -> 46.1139 | D34: ='Monthly Haver'!E37 -> #N/A | E34: ='Monthly Haver'!G37 -> 47.7733 | F34: ='Monthly Haver'!H37 -> 46.7402 | G34: ='Monthly Haver'!I37 -> #N/A | H34: ='Monthly Haver'!J37 -> 49.2236 | I34: =GDS_Monthly!O151 -> 55.054174 | J34: =GDS_Monthly!D151 -> 71.789707 | K34: =GDS_Monthly!AH151 -> 396.78411 | L34: =GDS_Monthly!AI151 -> 380.30754 | M34: =GDS_Monthly!N151 -> 6.046103 | N34: =GDS_Monthly!C151 -> 110.54523 | O34: =GDS_Monthly!F151 -> 4.4446166 | P34: =GDS_Monthly!G151 -> 3.9867143 | Q34: =GDS_Monthly!T151 -> 80.03876 | R34: =GDS_Monthly!V151 -> 84.382676 | S34: =GDS_Monthly!W151 -> 60.20242 | T34: =GDS_Monthly!X151 -> 38.523538 | U34: =GDS_Monthly!AA151 -> 48.041025 | V34: =GDS_Monthly!AC151 -> 62.719315 | W34: =GDS_Monthly!AE151 -> 63.119649 | X34: =GDS_Monthly!AF151 -> 63.115046 | Y34: =OECD!B34 -> 98.62989 | Z34: =OECD!C34 -> 91.9 | AA34: ='Monthly Haver'!K37 -> 115.00387 | AB34: ='Monthly Haver'!L37 -> 945 | AC34: =Quarterly!B12 -> 95.66 | AD34: =Quarterly!C12 -> 84.57 | AE34: =Quarterly!D12 -> 80.530172 | AF34: 0.88840616
A35: 37165 | B35: ='Monthly Haver'!C38 -> 41.7723 | C35: ='Monthly Haver'!D38 -> 41.566 | D35: ='Monthly Haver'!E38 -> #N/A | E35: ='Monthly Haver'!G38 -> 44.8608 | F35: ='Monthly Haver'!H38 -> 41.0217 | G35: ='Monthly Haver'!I38 -> #N/A | H35: ='Monthly Haver'!J38 -> 42.8904 | I35: =GDS_Monthly!O152 -> 55.244763 | J35: =GDS_Monthly!D152 -> 71.581039 | K35: =GDS_Monthly!AH152 -> 399.77567 | L35: =GDS_Monthly!AI152 -> 384.34306 | M35: =GDS_Monthly!N152 -> 6.1776573 | N35: =GDS_Monthly!C152 -> 107.13028 | O35: =GDS_Monthly!F152 -> 4.4424701 | P35: =GDS_Monthly!G152 -> 3.7493931 | Q35: =GDS_Monthly!T152 -> 80.03892 | R35: =GDS_Monthly!V152 -> 84.547318 | S35: =GDS_Monthly!W152 -> 59.030629 | T35: =GDS_Monthly!X152 -> 37.289399 | U35: =GDS_Monthly!AA152 -> 46.912667 | V35: =GDS_Monthly!AC152 -> 55.431303 | W35: =GDS_Monthly!AE152 -> 52.573031 | X35: =GDS_Monthly!AF152 -> 60.097596 | Y35: =OECD!B35 -> 98.64216 | Z35: =OECD!C35 -> 91.22 | AA35: ='Monthly Haver'!K38 -> 113.80347 | AB35: ='Monthly Haver'!L38 -> 898
A36: 37196 | B36: ='Monthly Haver'!C39 -> 46.0247 | C36: ='Monthly Haver'!D39 -> 40.3969 | D36: ='Monthly Haver'!E39 -> #N/A | E36: ='Monthly Haver'!G39 -> 44.921 | F36: ='Monthly Haver'!H39 -> 43.4854 | G36: ='Monthly Haver'!I39 -> #N/A | H36: ='Monthly Haver'!J39 -> 48.4776 | I36: =GDS_Monthly!O153 -> 55.692319 | J36: =GDS_Monthly!D153 -> 71.542998 | K36: =GDS_Monthly!AH153 -> 390.98356 | L36: =GDS_Monthly!AI153 -> 376.42922 | M36: =GDS_Monthly!N153 -> 6.2087357 | N36: =GDS_Monthly!C153 -> 106.30621 | O36: =GDS_Monthly!F153 -> 4.2352469 | P36: =GDS_Monthly!G153 -> 3.4608157 | Q36: =GDS_Monthly!T153 -> 80.088969 | R36: =GDS_Monthly!V153 -> 84.718991 | S36: =GDS_Monthly!W153 -> 57.812665 | T36: =GDS_Monthly!X153 -> 38.560568 | U36: =GDS_Monthly!AA153 -> 46.587496 | V36: =GDS_Monthly!AC153 -> 50.46601 | W36: =GDS_Monthly!AE153 -> 47.766394 | X36: =GDS_Monthly!AF153 -> 61.003305 | Y36: =OECD!B36 -> 98.74303 | Z36: =OECD!C36 -> 92.02 | AA36: ='Monthly Haver'!K39 -> 114.14976 | AB36: ='Monthly Haver'!L39 -> 855
A37: 37226 | B37: ='Monthly Haver'!C40 -> 48.4486 | C37: ='Monthly Haver'!D40 -> 41.4029 | D37: ='Monthly Haver'!E40 -> #N/A | E37: ='Monthly Haver'!G40 -> 45.3675 | F37: ='Monthly Haver'!H40 -> 44.0694 | G37: ='Monthly Haver'!I40 -> #N/A | H37: ='Monthly Haver'!J40 -> 50.2193 | I37: =GDS_Monthly!O154 -> 55.778346 | J37: =GDS_Monthly!D154 -> 71.279976 | K37: =GDS_Monthly!AH154 -> 381.49528 | L37: =GDS_Monthly!AI154 -> 372.30871 | M37: =GDS_Monthly!N154 -> 6.2211345 | N37: =GDS_Monthly!C154 -> 109.22368 | O37: =GDS_Monthly!F154 -> 4.6676498 | P37: =GDS_Monthly!G154 -> 3.4042566 | Q37: =GDS_Monthly!T154 -> 80.172158 | R37: =GDS_Monthly!V154 -> 84.888043 | S37: =GDS_Monthly!W154 -> 57.541376 | T37: =GDS_Monthly!X154 -> 39.096092 | U37: =GDS_Monthly!AA154 -> 46.6406 | V37: =GDS_Monthly!AC154 -> 49.7152 | W37: =GDS_Monthly!AE154 -> 47.55058 | X37: =GDS_Monthly!AF154 -> 60.474278 | Y37: =OECD!B37 -> 98.92091 | Z37: =OECD!C37 -> 92.66 | AA37: ='Monthly Haver'!K40 -> 113.26776 | AB37: ='Monthly Haver'!L40 -> 870 | AC37: =Quarterly!B13 -> 95.36 | AD37: =Quarterly!C13 -> 85.16 | AE37: =Quarterly!D13 -> 80.704556 | AF37: 1.8425459
A38: 37257 | B38: ='Monthly Haver'!C41 -> 49.7067 | C38: ='Monthly Haver'!D41 -> 46.8696 | D38: ='Monthly Haver'!E41 -> #N/A | E38: ='Monthly Haver'!G41 -> 45.6847 | F38: ='Monthly Haver'!H41 -> 46.4935 | G38: ='Monthly Haver'!I41 -> #N/A | H38: ='Monthly Haver'!J41 -> 50.2709 | I38: =GDS_Monthly!O155 -> 56.463259 | J38: =GDS_Monthly!D155 -> 72.069059 | K38: =GDS_Monthly!AH155 -> 387.00442 | L38: =GDS_Monthly!AI155 -> 378.54322 | M38: =GDS_Monthly!N155 -> 6.4098082 | N38: =GDS_Monthly!C155 -> 110.89384 | O38: =GDS_Monthly!F155 -> 4.6756696 | P38: =GDS_Monthly!G155 -> 3.1959601 | Q38: =GDS_Monthly!T155 -> 80.424412 | R38: =GDS_Monthly!V155 -> 85.086322 | S38: =GDS_Monthly!W155 -> 59.197919 | T38: =GDS_Monthly!X155 -> 40.402698 | U38: =GDS_Monthly!AA155 -> 47.805931 | V38: =GDS_Monthly!AC155 -> 49.582558 | W38: =GDS_Monthly!AE155 -> 49.577973 | X38: =GDS_Monthly!AF155 -> 60.919209 | Y38: =OECD!B38 -> 99.13857 | Z38: =OECD!C38 -> 93.56 | AA38: ='Monthly Haver'!K41 -> 114.5098 | AB38: ='Monthly Haver'!L41 -> 931
A39: 37288 | B39: ='Monthly Haver'!C42 -> 54.393 | C39: ='Monthly Haver'!D42 -> 46.4752 | D39: ='Monthly Haver'!E42 -> #N/A | E39: ='Monthly Haver'!G42 -> 46.4199 | F39: ='Monthly Haver'!H42 -> 49.0902 | G39: ='Monthly Haver'!I42 -> #N/A | H39: ='Monthly Haver'!J42 -> 55.1924 | I39: =GDS_Monthly!O156 -> 56.364704 | J39: =GDS_Monthly!D156 -> 72.344983 | K39: =GDS_Monthly!AH156 -> 396.59662 | L39: =GDS_Monthly!AI156 -> 379.76059 | M39: =GDS_Monthly!N156 -> 6.4162599 | N39: =GDS_Monthly!C156 -> 110.08289 | O39: =GDS_Monthly!F156 -> 4.6552395 | P39: =GDS_Monthly!G156 -> 3.6475844 | Q39: =GDS_Monthly!T156 -> 80.515495 | R39: =GDS_Monthly!V156 -> 85.260042 | S39: =GDS_Monthly!W156 -> 59.467522 | T39: =GDS_Monthly!X156 -> 40.603342 | U39: =GDS_Monthly!AA156 -> 48.359475 | V39: =GDS_Monthly!AC156 -> 51.270496 | W39: =GDS_Monthly!AE156 -> 52.030861 | X39: =GDS_Monthly!AF156 -> 63.197901 | Y39: =OECD!B39 -> 99.35554 | Z39: =OECD!C39 -> 93.85 | AA39: ='Monthly Haver'!K42 -> 114.92203 | AB39: ='Monthly Haver'!L42 -> 960
A40: 37316 | B40: ='Monthly Haver'!C43 -> 55.9141 | C40: ='Monthly Haver'!D43 -> 49.2797 | D40: ='Monthly Haver'!E43 -> #N/A | E40: ='Monthly Haver'!G43 -> 47.9765 | F40: ='Monthly Haver'!H43 -> 51.011 | G40: ='Monthly Haver'!I43 -> #N/A | H40: ='Monthly Haver'!J43 -> 55.4237 | I40: =GDS_Monthly!O157 -> 56.745052 | J40: =GDS_Monthly!D157 -> 72.816526 | K40: =GDS_Monthly!AH157 -> 400.09178 | L40: =GDS_Monthly!AI157 -> 389.25862 | M40: =GDS_Monthly!N157 -> 6.4339669 | N40: =GDS_Monthly!C157 -> 114.46145 | O40: =GDS_Monthly!F157 -> 4.8862475 | P40: =GDS_Monthly!G157 -> 3.6055888 | Q40: =GDS_Monthly!T157 -> 80.712188 | R40: =GDS_Monthly!V157 -> 85.321665 | S40: =GDS_Monthly!W157 -> 62.297235 | T40: =GDS_Monthly!X157 -> 41.968439 | U40: =GDS_Monthly!AA157 -> 50.073606 | V40: =GDS_Monthly!AC157 -> 59.613536 | W40: =GDS_Monthly!AE157 -> 61.33856 | X40: =GDS_Monthly!AF157 -> 62.177913 | Y40: =OECD!B40 -> 99.52464 | Z40: =OECD!C40 -> 94.79 | AA40: ='Monthly Haver'!K43 -> 114.84431 | AB40: ='Monthly Haver'!L43 -> 1065 | AC40: =Quarterly!B14 -> 96.23 | AD40: =Quarterly!C14 -> 86.15 | AE40: =Quarterly!D14 -> 81.178151 | AF40: 3.3692314
A41: 37347 | B41: ='Monthly Haver'!C44 -> 56.8182 | C41: ='Monthly Haver'!D44 -> 53.1075 | D41: ='Monthly Haver'!E44 -> #N/A | E41: ='Monthly Haver'!G44 -> 49.4383 | F41: ='Monthly Haver'!H44 -> 51.9533 | G41: ='Monthly Haver'!I44 -> #N/A | H41: ='Monthly Haver'!J44 -> 55.1924 | I41: =GDS_Monthly!O158 -> 57.240504 | J41: =GDS_Monthly!D158 -> 73.489111 | K41: =GDS_Monthly!AH158 -> 417.90757 | L41: =GDS_Monthly!AI158 -> 401.2312 | M41: =GDS_Monthly!N158 -> 6.5028249 | N41: =GDS_Monthly!C158 -> 113.49485 | O41: =GDS_Monthly!F158 -> 4.8559381 | P41: =GDS_Monthly!G158 -> 3.5308732 | Q41: =GDS_Monthly!T158 -> 81.078545 | R41: =GDS_Monthly!V158 -> 85.522962 | S41: =GDS_Monthly!W158 -> 62.471345 | T41: =GDS_Monthly!X158 -> 41.988458 | U41: =GDS_Monthly!AA158 -> 50.323805 | V41: =GDS_Monthly!AC158 -> 63.67392 | W41: =GDS_Monthly!AE158 -> 65.635461 | X41: =GDS_Monthly!AF158 -> 62.959154 | Y41: =OECD!B41 -> 99.60524 | Z41: =OECD!C41 -> 95.37 | AA41: ='Monthly Haver'!K44 -> 114.60591 | AB41: ='Monthly Haver'!L44 -> 1077
A42: 37377 | B42: ='Monthly Haver'!C45 -> 56.7109 | C42: ='Monthly Haver'!D45 -> 54.0371 | D42: ='Monthly Haver'!E45 -> #N/A | E42: ='Monthly Haver'!G45 -> 50.4233 | F42: ='Monthly Haver'!H45 -> 53.1425 | G42: ='Monthly Haver'!I45 -> #N/A | H42: ='Monthly Haver'!J45 -> 57.6536 | I42: =GDS_Monthly!O159 -> 57.459068 | J42: =GDS_Monthly!D159 -> 73.882793 | K42: =GDS_Monthly!AH159 -> 422.68852 | L42: =GDS_Monthly!AI159 -> 407.38283 | M42: =GDS_Monthly!N159 -> 6.4713232 | N42: =GDS_Monthly!C159 -> 114.11231 | O42: =GDS_Monthly!F159 -> 4.8118495 | P42: =GDS_Monthly!G159 -> 3.5310491 | Q42: =GDS_Monthly!T159 -> 81.217566 | R42: =GDS_Monthly!V159 -> 85.64657 | S42: =GDS_Monthly!W159 -> 61.743798 | T42: =GDS_Monthly!X159 -> 41.47037 | U42: =GDS_Monthly!AA159 -> 50.042962 | V42: =GDS_Monthly!AC159 -> 64.466222 | W42: =GDS_Monthly!AE159 -> 65.233812 | X42: =GDS_Monthly!AF159 -> 63.342585 | Y42: =OECD!B42 -> 99.58871 | Z42: =OECD!C42 -> 96.3 | AA42: ='Monthly Haver'!K45 -> 113.0735 | AB42: ='Monthly Haver'!L45 -> 1033
A43: 37408 | B43: ='Monthly Haver'!C46 -> 56.3607 | C43: ='Monthly Haver'!D46 -> 54.2985 | D43: ='Monthly Haver'!E46 -> #N/A | E43: ='Monthly Haver'!G46 -> 48.3703 | F43: ='Monthly Haver'!H46 -> 53.4948 | G43: ='Monthly Haver'!I46 -> #N/A | H43: ='Monthly Haver'!J46 -> 54.9187 | I43: =GDS_Monthly!O160 -> 57.353694 | J43: =GDS_Monthly!D160 -> 73.917864 | K43: =GDS_Monthly!AH160 -> 426.44708 | L43: =GDS_Monthly!AI160 -> 410.23682 | M43: =GDS_Monthly!N160 -> 6.4839314 | N43: =GDS_Monthly!C160 -> 113.11138 | O43: =GDS_Monthly!F160 -> 4.6975143 | P43: =GDS_Monthly!G160 -> 3.5788517 | Q43: =GDS_Monthly!T160 -> 81.347467 | R43: =GDS_Monthly!V160 -> 85.801017 | S43: =GDS_Monthly!W160 -> 61.145857 | T43: =GDS_Monthly!X160 -> 42.379224 | U43: =GDS_Monthly!AA160 -> 50.415631 | V43: =GDS_Monthly!AC160 -> 61.473099 | W43: =GDS_Monthly!AE160 -> 61.088995 | X43: =GDS_Monthly!AF160 -> 66.593378 | Y43: =OECD!B43 -> 99.4905 | Z43: =OECD!C43 -> 96.57 | AA43: ='Monthly Haver'!K46 -> 111.99786 | AB43: ='Monthly Haver'!L46 -> 995 | AC43: =Quarterly!B15 -> 96.47 | AD43: =Quarterly!C15 -> 87.04 | AE43: =Quarterly!D15 -> 81.84987 | AF43: 4.3446296
A44: 37438 | B44: ='Monthly Haver'!C47 -> 52.5238 | C44: ='Monthly Haver'!D47 -> 57.5109 | D44: ='Monthly Haver'!E47 -> #N/A | E44: ='Monthly Haver'!G47 -> 48.4838 | F44: ='Monthly Haver'!H47 -> 51.2426 | G44: ='Monthly Haver'!I47 -> #N/A | H44: ='Monthly Haver'!J47 -> 52.2299 | I44: =GDS_Monthly!O161 -> 57.728609 | J44: =GDS_Monthly!D161 -> 74.336178 | K44: =GDS_Monthly!AH161 -> 441.51776 | L44: =GDS_Monthly!AI161 -> 426.0817 | M44: =GDS_Monthly!N161 -> 6.504102 | N44: =GDS_Monthly!C161 -> 110.49768 | O44: =GDS_Monthly!F161 -> 4.5221826 | P44: =GDS_Monthly!G161 -> 3.6720713 | Q44: =GDS_Monthly!T161 -> 81.542634 | R44: =GDS_Monthly!V161 -> 85.935672 | S44: =GDS_Monthly!W161 -> 63.147709 | T44: =GDS_Monthly!X161 -> 41.884458 | U44: =GDS_Monthly!AA161 -> 51.403709 | V44: =GDS_Monthly!AC161 -> 63.70658 | W44: =GDS_Monthly!AE161 -> 62.780297 | X44: =GDS_Monthly!AF161 -> 69.51953 | Y44: =OECD!B44 -> 99.3437 | Z44: =OECD!C44 -> 95.72 | AA44: ='Monthly Haver'!K47 -> 110.35115 | AB44: ='Monthly Haver'!L47 -> 989
A45: 37469 | B45: ='Monthly Haver'!C48 -> 52.2742 | C45: ='Monthly Haver'!D48 -> 53.9541 | D45: ='Monthly Haver'!E48 -> #N/A | E45: ='Monthly Haver'!G48 -> 48.4742 | F45: ='Monthly Haver'!H48 -> 50.5425 | G45: ='Monthly Haver'!I48 -> #N/A | H45: ='Monthly Haver'!J48 -> 51.7864 | I45: =GDS_Monthly!O162 -> 58.038038 | J45: =GDS_Monthly!D162 -> 74.469891 | K45: =GDS_Monthly!AH162 -> 436.74669 | L45: =GDS_Monthly!AI162 -> 420.45761 | M45: =GDS_Monthly!N162 -> 6.4760523 | N45: =GDS_Monthly!C162 -> 109.69746 | O45: =GDS_Monthly!F162 -> 4.2583486 | P45: =GDS_Monthly!G162 -> 3.558623 | Q45: =GDS_Monthly!T162 -> 81.747032 | R45: =GDS_Monthly!V162 -> 86.142657 | S45: =GDS_Monthly!W162 -> 62.971955 | T45: =GDS_Monthly!X162 -> 40.12803 | U45: =GDS_Monthly!AA162 -> 51.105377 | V45: =GDS_Monthly!AC162 -> 64.74497 | W45: =GDS_Monthly!AE162 -> 65.719212 | X45: =GDS_Monthly!AF162 -> 70.977621 | Y45: =OECD!B45 -> 99.18281 | Z45: =OECD!C45 -> 95.41 | AA45: ='Monthly Haver'!K48 -> 111.62637 | AB45: ='Monthly Haver'!L48 -> 1002
A46: 37500 | B46: ='Monthly Haver'!C49 -> 52.7744 | C46: ='Monthly Haver'!D49 -> 53.4973 | D46: ='Monthly Haver'!E49 -> #N/A | E46: ='Monthly Haver'!G49 -> 47.8139 | F46: ='Monthly Haver'!H49 -> 49.6431 | G46: ='Monthly Haver'!I49 -> #N/A | H46: ='Monthly Haver'!J49 -> 53.2569 | I46: =GDS_Monthly!O163 -> 58.214834 | J46: =GDS_Monthly!D163 -> 74.71886 | K46: =GDS_Monthly!AH163 -> 441.2379 | L46: =GDS_Monthly!AI163 -> 425.89295 | M46: =GDS_Monthly!N163 -> 6.4939172 | N46: =GDS_Monthly!C163 -> 109.64023 | O46: =GDS_Monthly!F163 -> 4.0152367 | P46: =GDS_Monthly!G163 -> 3.522057 | Q46: =GDS_Monthly!T163 -> 81.890802 | R46: =GDS_Monthly!V163 -> 86.21907 | S46: =GDS_Monthly!W163 -> 63.556124 | T46: =GDS_Monthly!X163 -> 40.108176 | U46: =GDS_Monthly!AA163 -> 51.920506 | V46: =GDS_Monthly!AC163 -> 69.059763 | W46: =GDS_Monthly!AE163 -> 69.384655 | X46: =GDS_Monthly!AF163 -> 74.079898 | Y46: =OECD!B46 -> 99.02942 | Z46: =OECD!C46 -> 94.97 | AA46: ='Monthly Haver'!K49 -> 112.49731 | AB46: ='Monthly Haver'!L49 -> 1182 | AC46: =Quarterly!B16 -> 96.38 | AD46: =Quarterly!C16 -> 88.05 | AE46: =Quarterly!D16 -> 82.347798 | AF46: 3.4716421
A47: 37530 | B47: ='Monthly Haver'!C50 -> 51.9616 | C47: ='Monthly Haver'!D50 -> 53.2343 | D47: ='Monthly Haver'!E50 -> #N/A | E47: ='Monthly Haver'!G50 -> 47.9277 | F47: ='Monthly Haver'!H50 -> 49.1919 | G47: ='Monthly Haver'!I50 -> #N/A | H47: ='Monthly Haver'!J50 -> 52.3923 | I47: =GDS_Monthly!O164 -> 58.593967 | J47: =GDS_Monthly!D164 -> 74.873381 | K47: =GDS_Monthly!AH164 -> 442.19646 | L47: =GDS_Monthly!AI164 -> 425.84132 | M47: =GDS_Monthly!N164 -> 6.5220665 | N47: =GDS_Monthly!C164 -> 105.69984 | O47: =GDS_Monthly!F164 -> 4.0961521 | P47: =GDS_Monthly!G164 -> 3.5556168 | Q47: =GDS_Monthly!T164 -> 82.04043 | R47: =GDS_Monthly!V164 -> 86.354299 | S47: =GDS_Monthly!W164 -> 66.079389 | T47: =GDS_Monthly!X164 -> 40.439486 | U47: =GDS_Monthly!AA164 -> 53.131844 | V47: =GDS_Monthly!AC164 -> 70.189663 | W47: =GDS_Monthly!AE164 -> 67.744915 | X47: =GDS_Monthly!AF164 -> 73.634415 | Y47: =OECD!B47 -> 98.89712 | Z47: =OECD!C47 -> 94.37 | AA47: ='Monthly Haver'!K50 -> 113.6806 | AB47: ='Monthly Haver'!L50 -> 1365
A48: 37561 | B48: ='Monthly Haver'!C51 -> 53.303 | C48: ='Monthly Haver'!D51 -> 53.1443 | D48: ='Monthly Haver'!E51 -> #N/A | E48: ='Monthly Haver'!G51 -> 47.5537 | F48: ='Monthly Haver'!H51 -> 48.9967 | G48: ='Monthly Haver'!I51 -> #N/A | H48: ='Monthly Haver'!J51 -> 54.8537 | I48: =GDS_Monthly!O165 -> 59.010804 | J48: =GDS_Monthly!D165 -> 75.210808 | K48: =GDS_Monthly!AH165 -> 452.2513 | L48: =GDS_Monthly!AI165 -> 431.05544 | M48: =GDS_Monthly!N165 -> 6.5543123 | N48: =GDS_Monthly!C165 -> 107.11779 | O48: =GDS_Monthly!F165 -> 4.0796778 | P48: =GDS_Monthly!G165 -> 3.3366643 | Q48: =GDS_Monthly!T165 -> 82.277568 | R48: =GDS_Monthly!V165 -> 86.529861 | S48: =GDS_Monthly!W165 -> 64.738062 | T48: =GDS_Monthly!X165 -> 42.267609 | U48: =GDS_Monthly!AA165 -> 52.858651 | V48: =GDS_Monthly!AC165 -> 65.499321 | W48: =GDS_Monthly!AE165 -> 60.396898 | X48: =GDS_Monthly!AF165 -> 73.46601 | Y48: =OECD!B48 -> 98.78994 | Z48: =OECD!C48 -> 95.19 | AA48: ='Monthly Haver'!K51 -> 112.4223 | AB48: ='Monthly Haver'!L51 -> 1460
A49: 37591 | B49: ='Monthly Haver'!C52 -> 53.5903 | C49: ='Monthly Haver'!D52 -> 53.2144 | D49: ='Monthly Haver'!E52 -> #N/A | E49: ='Monthly Haver'!G52 -> 48.1742 | F49: ='Monthly Haver'!H52 -> 50.1483 | G49: ='Monthly Haver'!I52 -> #N/A | H49: ='Monthly Haver'!J52 -> 53.8282 | I49: =GDS_Monthly!O166 -> 58.887084 | J49: =GDS_Monthly!D166 -> 74.506804 | K49: =GDS_Monthly!AH166 -> 450.80743 | L49: =GDS_Monthly!AI166 -> 428.12203 | M49: =GDS_Monthly!N166 -> 6.6091258 | N49: =GDS_Monthly!C166 -> 105.76374 | O49: =GDS_Monthly!F166 -> 3.9701217 | P49: =GDS_Monthly!G166 -> 3.2713878 | Q49: =GDS_Monthly!T166 -> 82.468469 | R49: =GDS_Monthly!V166 -> 86.677117 | S49: =GDS_Monthly!W166 -> 65.685024 | T49: =GDS_Monthly!X166 -> 42.317469 | U49: =GDS_Monthly!AA166 -> 53.512971 | V49: =GDS_Monthly!AC166 -> 72.642371 | W49: =GDS_Monthly!AE166 -> 67.45441 | X49: =GDS_Monthly!AF166 -> 73.890282 | Y49: =OECD!B49 -> 98.69359 | Z49: =OECD!C49 -> 95.46 | AA49: ='Monthly Haver'!K52 -> 111.39613 | AB49: ='Monthly Haver'!L52 -> 1666 | AC49: =Quarterly!B17 -> 96.73 | AD49: =Quarterly!C17 -> 88.89 | AE49: =Quarterly!D17 -> 82.660627 | AF49: 2.4451578
A50: 37622 | B50: ='Monthly Haver'!C53 -> 53.2991 | C50: ='Monthly Haver'!D53 -> 54.6673 | D50: ='Monthly Haver'!E53 -> #N/A | E50: ='Monthly Haver'!G53 -> 49.3405 | F50: ='Monthly Haver'!H53 -> 50.0723 | G50: ='Monthly Haver'!I53 -> #N/A | H50: ='Monthly Haver'!J53 -> 54.0219 | I50: =GDS_Monthly!O167 -> 59.679075 | J50: =GDS_Monthly!D167 -> 75.854377 | K50: =GDS_Monthly!AH167 -> 474.57654 | L50: =GDS_Monthly!AI167 -> 450.07935 | M50: =GDS_Monthly!N167 -> 6.6352404 | N50: =GDS_Monthly!C167 -> 105.11394 | O50: =GDS_Monthly!F167 -> 3.9001178 | P50: =GDS_Monthly!G167 -> 3.3171993 | Q50: =GDS_Monthly!T167 -> 82.793253 | R50: =GDS_Monthly!V167 -> 86.823809 | S50: =GDS_Monthly!W167 -> 65.987927 | T50: =GDS_Monthly!X167 -> 44.545787 | U50: =GDS_Monthly!AA167 -> 54.864976 | V50: =GDS_Monthly!AC167 -> 80.490252 | W50: =GDS_Monthly!AE167 -> 72.887892 | X50: =GDS_Monthly!AF167 -> 75.818524 | Y50: =OECD!B50 -> 98.60216 | Z50: =OECD!C50 -> 95.87 | AA50: ='Monthly Haver'!K53 -> 111.2911 | AB50: ='Monthly Haver'!L53 -> 1694
A51: 37653 | B51: ='Monthly Haver'!C54 -> 52.0212 | C51: ='Monthly Haver'!D54 -> 57.8572 | D51: ='Monthly Haver'!E54 -> #N/A | E51: ='Monthly Haver'!G54 -> 47.8731 | F51: ='Monthly Haver'!H54 -> 49.052 | G51: ='Monthly Haver'!I54 -> #N/A | H51: ='Monthly Haver'!J54 -> 53.1736 | I51: =GDS_Monthly!O168 -> 60.042111 | J51: =GDS_Monthly!D168 -> 76.302766 | K51: =GDS_Monthly!AH168 -> 475.28878 | L51: =GDS_Monthly!AI168 -> 454.7867 | M51: =GDS_Monthly!N168 -> 6.6484254 | N51: =GDS_Monthly!C168 -> 101.21542 | O51: =GDS_Monthly!F168 -> 3.7650621 | P51: =GDS_Monthly!G168 -> 3.2965685 | Q51: =GDS_Monthly!T168 -> 83.088308 | R51: =GDS_Monthly!V168 -> 86.942821 | S51: =GDS_Monthly!W168 -> 66.252296 | T51: =GDS_Monthly!X168 -> 45.921225 | U51: =GDS_Monthly!AA168 -> 55.539449 | V51: =GDS_Monthly!AC168 -> 91.76203 | W51: =GDS_Monthly!AE168 -> 77.812541 | X51: =GDS_Monthly!AF168 -> 76.401557 | Y51: =OECD!B51 -> 98.53093 | Z51: =OECD!C51 -> 95.57 | AA51: ='Monthly Haver'!K54 -> 112.3172 | AB51: ='Monthly Haver'!L54 -> 1674
A52: 37681 | B52: ='Monthly Haver'!C55 -> 49.0471 | C52: ='Monthly Haver'!D55 -> 58.6644 | D52: ='Monthly Haver'!E55 -> #N/A | E52: ='Monthly Haver'!G55 -> 47.7158 | F52: ='Monthly Haver'!H55 -> 47.4936 | G52: ='Monthly Haver'!I55 -> #N/A | H52: ='Monthly Haver'!J55 -> 47.0537 | I52: =GDS_Monthly!O169 -> 60.289677 | J52: =GDS_Monthly!D169 -> 76.333103 | K52: =GDS_Monthly!AH169 -> 480.86 | L52: =GDS_Monthly!AI169 -> 449.7238 | M52: =GDS_Monthly!N169 -> 6.671226 | N52: =GDS_Monthly!C169 -> 100.25274 | O52: =GDS_Monthly!F169 -> 3.7792156 | P52: =GDS_Monthly!G169 -> 3.2263636 | Q52: =GDS_Monthly!T169 -> 83.298463 | R52: =GDS_Monthly!V169 -> 87.029916 | S52: =GDS_Monthly!W169 -> 66.016239 | T52: =GDS_Monthly!X169 -> 45.151397 | U52: =GDS_Monthly!AA169 -> 55.027279 | V52: =GDS_Monthly!AC169 -> 81.450087 | W52: =GDS_Monthly!AE169 -> 71.806319 | X52: =GDS_Monthly!AF169 -> 75.989059 | Y52: =OECD!B52 -> 98.5119 | Z52: =OECD!C52 -> 95.54 | AA52: ='Monthly Haver'!K55 -> 114.44666 | AB52: ='Monthly Haver'!L55 -> 1850 | AC52: =Quarterly!B18 -> 96.42 | AD52: =Quarterly!C18 -> 89.38 | AE52: =Quarterly!D18 -> 82.954764 | AF52: 2.9898158
A53: 37712 | B53: ='Monthly Haver'!C56 -> 49.2188 | C53: ='Monthly Haver'!D56 -> 55.1328 | D53: ='Monthly Haver'!E56 -> #N/A | E53: ='Monthly Haver'!G56 -> 47.9127 | F53: ='Monthly Haver'!H56 -> 47.7358 | G53: ='Monthly Haver'!I56 -> #N/A | H53: ='Monthly Haver'!J56 -> 49.6302 | I53: =GDS_Monthly!O170 -> 60.274669 | J53: =GDS_Monthly!D170 -> 76.193918 | K53: =GDS_Monthly!AH170 -> 474.66358 | L53: =GDS_Monthly!AI170 -> 452.77084 | M53: =GDS_Monthly!N170 -> 6.6739164 | N53: =GDS_Monthly!C170 -> 105.57217 | O53: =GDS_Monthly!F170 -> 3.8272807 | P53: =GDS_Monthly!G170 -> 3.1845969 | Q53: =GDS_Monthly!T170 -> 83.204593 | R53: =GDS_Monthly!V170 -> 87.137459 | S53: =GDS_Monthly!W170 -> 67.563604 | T53: =GDS_Monthly!X170 -> 43.642008 | U53: =GDS_Monthly!AA170 -> 55.222217 | V53: =GDS_Monthly!AC170 -> 71.476581 | W53: =GDS_Monthly!AE170 -> 60.683694 | X53: =GDS_Monthly!AF170 -> 77.515072 | Y53: =OECD!B53 -> 98.57051 | Z53: =OECD!C53 -> 95.72 | AA53: ='Monthly Haver'!K56 -> 110.58292 | AB53: ='Monthly Haver'!L56 -> 2064
A54: 37742 | B54: ='Monthly Haver'!C57 -> 52.0859 | C54: ='Monthly Haver'!D57 -> 49.929 | D54: ='Monthly Haver'!E57 -> #N/A | E54: ='Monthly Haver'!G57 -> 47.9042 | F54: ='Monthly Haver'!H57 -> 48.5326 | G54: ='Monthly Haver'!I57 -> #N/A | H54: ='Monthly Haver'!J57 -> 52.3357 | I54: =GDS_Monthly!O171 -> 60.231469 | J54: =GDS_Monthly!D171 -> 76.000028 | K54: =GDS_Monthly!AH171 -> 481.37156 | L54: =GDS_Monthly!AI171 -> 460.04979 | M54: =GDS_Monthly!N171 -> 6.7209206 | N54: =GDS_Monthly!C171 -> 106.50462 | O54: =GDS_Monthly!F171 -> 3.5054518 | P54: =GDS_Monthly!G171 -> 3.085625 | Q54: =GDS_Monthly!T171 -> 83.145461 | R54: =GDS_Monthly!V171 -> 87.26993 | S54: =GDS_Monthly!W171 -> 68.001437 | T54: =GDS_Monthly!X171 -> 45.38297 | U54: =GDS_Monthly!AA171 -> 55.799033 | V54: =GDS_Monthly!AC171 -> 73.565354 | W54: =GDS_Monthly!AE171 -> 60.031044 | X54: =GDS_Monthly!AF171 -> 74.864642 | Y54: =OECD!B54 -> 98.69794 | Z54: =OECD!C54 -> 96.46 | AA54: ='Monthly Haver'!K57 -> 107.81438 | AB54: ='Monthly Haver'!L57 -> 2231
A55: 37773 | B55: ='Monthly Haver'!C58 -> 53.1987 | C55: ='Monthly Haver'!D58 -> 50.5906 | D55: ='Monthly Haver'!E58 -> #N/A | E55: ='Monthly Haver'!G58 -> 48.8499 | F55: ='Monthly Haver'!H58 -> 49.0527 | G55: ='Monthly Haver'!I58 -> #N/A | H55: ='Monthly Haver'!J58 -> 55.6037 | I55: =GDS_Monthly!O172 -> 60.857315 | J55: =GDS_Monthly!D172 -> 76.390893 | K55: =GDS_Monthly!AH172 -> 482.82714 | L55: =GDS_Monthly!AI172 -> 462.26698 | M55: =GDS_Monthly!N172 -> 6.7820797 | N55: =GDS_Monthly!C172 -> 106.9494 | O55: =GDS_Monthly!F172 -> 3.3193437 | P55: =GDS_Monthly!G172 -> 2.8371511 | Q55: =GDS_Monthly!T172 -> 83.212082 | R55: =GDS_Monthly!V172 -> 87.354288 | S55: =GDS_Monthly!W172 -> 67.562137 | T55: =GDS_Monthly!X172 -> 46.380451 | U55: =GDS_Monthly!AA172 -> 55.755257 | V55: =GDS_Monthly!AC172 -> 76.804902 | W55: =GDS_Monthly!AE172 -> 63.936055 | X55: =GDS_Monthly!AF172 -> 76.350811 | Y55: =OECD!B55 -> 98.88338 | Z55: =OECD!C55 -> 97.21 | AA55: ='Monthly Haver'!K58 -> 108.76234 | AB55: ='Monthly Haver'!L58 -> 2136 | AC55: =Quarterly!B19 -> 96.98 | AD55: =Quarterly!C19 -> 90.39 | AE55: =Quarterly!D19 -> 83.480198 | AF55: 2.7005227
A56: 37803 | B56: ='Monthly Haver'!C59 -> 56.7727 | C56: ='Monthly Haver'!D59 -> 49.6581 | D56: ='Monthly Haver'!E59 -> #N/A | E56: ='Monthly Haver'!G59 -> 49.3851 | F56: ='Monthly Haver'!H59 -> 50.442 | G56: ='Monthly Haver'!I59 -> #N/A | H56: ='Monthly Haver'!J59 -> 58.5182 | I56: =GDS_Monthly!O173 -> 61.260019 | J56: =GDS_Monthly!D173 -> 77.149131 | K56: =GDS_Monthly!AH173 -> 486.61867 | L56: =GDS_Monthly!AI173 -> 467.72889 | M56: =GDS_Monthly!N173 -> 6.7621865 | N56: =GDS_Monthly!C173 -> 105.35857 | O56: =GDS_Monthly!F173 -> 3.7921649 | P56: =GDS_Monthly!G173 -> 2.7521746 | Q56: =GDS_Monthly!T173 -> 83.385082 | R56: =GDS_Monthly!V173 -> 87.50407 | S56: =GDS_Monthly!W173 -> 64.700086 | T56: =GDS_Monthly!X173 -> 47.005523 | U56: =GDS_Monthly!AA173 -> 54.606696 | V56: =GDS_Monthly!AC173 -> 75.83765 | W56: =GDS_Monthly!AE173 -> 66.277428 | X56: =GDS_Monthly!AF173 -> 76.820276 | Y56: =OECD!B56 -> 99.11143 | Z56: =OECD!C56 -> 98.07 | AA56: ='Monthly Haver'!K59 -> 109.09367 | AB56: ='Monthly Haver'!L59 -> 2192
A57: 37834 | B57: ='Monthly Haver'!C60 -> 59.922 | C57: ='Monthly Haver'!D60 -> 52.1856 | D57: ='Monthly Haver'!E60 -> #N/A | E57: ='Monthly Haver'!G60 -> 50.5148 | F57: ='Monthly Haver'!H60 -> 52.375 | G57: ='Monthly Haver'!I60 -> #N/A | H57: ='Monthly Haver'!J60 -> 60.5147 | I57: =GDS_Monthly!O174 -> 61.849184 | J57: =GDS_Monthly!D174 -> 77.104932 | K57: =GDS_Monthly!AH174 -> 472.64445 | L57: =GDS_Monthly!AI174 -> 460.73248 | M57: =GDS_Monthly!N174 -> 6.7599052 | N57: =GDS_Monthly!C174 -> 106.75779 | O57: =GDS_Monthly!F174 -> 4.0673842 | P57: =GDS_Monthly!G174 -> 2.6567248 | Q57: =GDS_Monthly!T174 -> 83.593968 | R57: =GDS_Monthly!V174 -> 87.597592 | S57: =GDS_Monthly!W174 -> 65.127403 | T57: =GDS_Monthly!X174 -> 48.042891 | U57: =GDS_Monthly!AA174 -> 55.198135 | V57: =GDS_Monthly!AC174 -> 77.80035 | W57: =GDS_Monthly!AE174 -> 69.461268 | X57: =GDS_Monthly!AF174 -> 77.650758 | Y57: =OECD!B57 -> 99.36485 | Z57: =OECD!C57 -> 98.52 | AA57: ='Monthly Haver'!K60 -> 110.41261 | AB57: ='Monthly Haver'!L60 -> 2286
A58: 37865 | B58: ='Monthly Haver'!C61 -> 58.57 | C58: ='Monthly Haver'!D61 -> 54.134 | D58: ='Monthly Haver'!E61 -> #N/A | E58: ='Monthly Haver'!G61 -> 50.0923 | F58: ='Monthly Haver'!H61 -> 52.4907 | G58: ='Monthly Haver'!I61 -> #N/A | H58: ='Monthly Haver'!J61 -> 60.2523 | I58: =GDS_Monthly!O175 -> 62.301659 | J58: =GDS_Monthly!D175 -> 77.809617 | K58: =GDS_Monthly!AH175 -> 497.90352 | L58: =GDS_Monthly!AI175 -> 480.14586 | M58: =GDS_Monthly!N175 -> 6.7587703 | N58: =GDS_Monthly!C175 -> 105.55093 | O58: =GDS_Monthly!F175 -> 4.0405586 | P58: =GDS_Monthly!G175 -> 2.592101 | Q58: =GDS_Monthly!T175 -> 83.805835 | R58: =GDS_Monthly!V175 -> 87.710279 | S58: =GDS_Monthly!W175 -> 71.488982 | T58: =GDS_Monthly!X175 -> 48.74995 | U58: =GDS_Monthly!AA175 -> 58.874606 | V58: =GDS_Monthly!AC175 -> 72.634857 | W58: =GDS_Monthly!AE175 -> 62.538034 | X58: =GDS_Monthly!AF175 -> 79.225378 | Y58: =OECD!B58 -> 99.63192 | Z58: =OECD!C58 -> 99.58 | AA58: ='Monthly Haver'!K61 -> 109.3061 | AB58: ='Monthly Haver'!L61 -> 2463 | AC58: =Quarterly!B20 -> 97.77 | AD58: =Quarterly!C20 -> 91.2 | AE58: =Quarterly!D20 -> 84.569959 | AF58: 6.3961061
A59: 37895 | B59: ='Monthly Haver'!C62 -> 61.1086 | C59: ='Monthly Haver'!D62 -> 54.5365 | D59: ='Monthly Haver'!E62 -> #N/A | E59: ='Monthly Haver'!G62 -> 51.679 | F59: ='Monthly Haver'!H62 -> 54.6915 | G59: ='Monthly Haver'!I62 -> #N/A | H59: ='Monthly Haver'!J62 -> 61.4265 | I59: =GDS_Monthly!O176 -> 62.766192 | J59: =GDS_Monthly!D176 -> 78.717926 | K59: =GDS_Monthly!AH176 -> 514.84739 | L59: =GDS_Monthly!AI176 -> 497.94158 | M59: =GDS_Monthly!N176 -> 6.7191191 | N59: =GDS_Monthly!C176 -> 106.95175 | O59: =GDS_Monthly!F176 -> 4.0744179 | P59: =GDS_Monthly!G176 -> 2.5548832 | Q59: =GDS_Monthly!T176 -> 83.85847 | R59: =GDS_Monthly!V176 -> 87.820485 | S59: =GDS_Monthly!W176 -> 74.891508 | T59: =GDS_Monthly!X176 -> 51.909958 | U59: =GDS_Monthly!AA176 -> 61.277774 | V59: =GDS_Monthly!AC176 -> 76.389471 | W59: =GDS_Monthly!AE176 -> 65.680893 | X59: =GDS_Monthly!AF176 -> 83.039186 | Y59: =OECD!B59 -> 99.89217 | Z59: =OECD!C59 -> 100.42 | AA59: ='Monthly Haver'!K62 -> 107.83472 | AB59: ='Monthly Haver'!L62 -> 4163
A60: 37926 | B60: ='Monthly Haver'!C63 -> 61.4526 | C60: ='Monthly Haver'!D63 -> 56.1732 | D60: ='Monthly Haver'!E63 -> #N/A | E60: ='Monthly Haver'!G63 -> 52.9525 | F60: ='Monthly Haver'!H63 -> 56.3784 | G60: ='Monthly Haver'!I63 -> #N/A | H60: ='Monthly Haver'!J63 -> 59.8619 | I60: =GDS_Monthly!O177 -> 62.766278 | J60: =GDS_Monthly!D177 -> 78.630024 | K60: =GDS_Monthly!AH177 -> 514.68908 | L60: =GDS_Monthly!AI177 -> 496.7961 | M60: =GDS_Monthly!N177 -> 6.6643166 | N60: =GDS_Monthly!C177 -> 109.90479 | O60: =GDS_Monthly!F177 -> 4.1460694 | P60: =GDS_Monthly!G177 -> 2.5307875 | Q60: =GDS_Monthly!T177 -> 84.005242 | R60: =GDS_Monthly!V177 -> 87.894848 | S60: =GDS_Monthly!W177 -> 72.54646 | T60: =GDS_Monthly!X177 -> 54.645296 | U60: =GDS_Monthly!AA177 -> 61.002445 | V60: =GDS_Monthly!AC177 -> 76.609654 | W60: =GDS_Monthly!AE177 -> 65.810034 | X60: =GDS_Monthly!AF177 -> 83.453041 | Y60: =OECD!B60 -> 100.1242 | Z60: =OECD!C60 -> 101.38 | AA60: ='Monthly Haver'!K63 -> 107.19524 | AB60: ='Monthly Haver'!L63 -> 4250
A61: 37956 | B61: ='Monthly Haver'!C64 -> 61.3861 | C61: ='Monthly Haver'!D64 -> 57.4628 | D61: ='Monthly Haver'!E64 -> #N/A | E61: ='Monthly Haver'!G64 -> 53.3316 | F61: ='Monthly Haver'!H64 -> 57.3482 | G61: ='Monthly Haver'!I64 -> #N/A | H61: ='Monthly Haver'!J64 -> 58.8222 | I61: =GDS_Monthly!O178 -> 62.887522 | J61: =GDS_Monthly!D178 -> 79.677375 | K61: =GDS_Monthly!AH178 -> 542.65255 | L61: =GDS_Monthly!AI178 -> 526.00488 | M61: =GDS_Monthly!N178 -> 6.6240618 | N61: =GDS_Monthly!C178 -> 110.64727 | O61: =GDS_Monthly!F178 -> 4.0863221 | P61: =GDS_Monthly!G178 -> 2.5330181 | Q61: =GDS_Monthly!T178 -> 84.205191 | R61: =GDS_Monthly!V178 -> 87.991235 | S61: =GDS_Monthly!W178 -> 71.890856 | T61: =GDS_Monthly!X178 -> 59.217722 | U61: =GDS_Monthly!AA178 -> 61.868453 | V61: =GDS_Monthly!AC178 -> 83.000744 | W61: =GDS_Monthly!AE178 -> 66.1564 | X61: =GDS_Monthly!AF178 -> 81.470136 | Y61: =OECD!B61 -> 100.3136 | Z61: =OECD!C61 -> 101.94 | AA61: ='Monthly Haver'!K64 -> 105.90237 | AB61: ='Monthly Haver'!L64 -> 4609 | AC61: =Quarterly!B21 -> 97.9 | AD61: =Quarterly!C21 -> 92.55 | AE61: =Quarterly!D21 -> 85.614872 | AF61: 6.1926395
A62: 37987 | B62: ='Monthly Haver'!C65 -> 62.9974 | C62: ='Monthly Haver'!D65 -> 59.8884 | D62: ='Monthly Haver'!E65 -> #N/A | E62: ='Monthly Haver'!G65 -> 53.5635 | F62: ='Monthly Haver'!H65 -> 57.4045 | G62: ='Monthly Haver'!I65 -> #N/A | H62: ='Monthly Haver'!J65 -> 63.822 | I62: =GDS_Monthly!O179 -> 64.259201 | J62: =GDS_Monthly!D179 -> 80.060546 | K62: =GDS_Monthly!AH179 -> 550.43982 | L62: =GDS_Monthly!AI179 -> 527.66204 | M62: =GDS_Monthly!N179 -> 6.6858455 | N62: =GDS_Monthly!C179 -> 111.46647 | O62: =GDS_Monthly!F179 -> 4.0503077 | P62: =GDS_Monthly!G179 -> 2.5519028 | Q62: =GDS_Monthly!T179 -> 84.415223 | R62: =GDS_Monthly!V179 -> 88.149931 | S62: =GDS_Monthly!W179 -> 73.403979 | T62: =GDS_Monthly!X179 -> 64.337303 | U62: =GDS_Monthly!AA179 -> 64.052029 | V62: =GDS_Monthly!AC179 -> 86.244799 | W62: =GDS_Monthly!AE179 -> 68.048035 | X62: =GDS_Monthly!AF179 -> 83.777163 | Y62: =OECD!B62 -> 100.4536 | Z62: =OECD!C62 -> 102.69 | AA62: ='Monthly Haver'!K65 -> 104.8681 | AB62: ='Monthly Haver'!L65 -> 5234
A63: 38018 | B63: ='Monthly Haver'!C66 -> 60.1017 | C63: ='Monthly Haver'!D66 -> 60.5921 | D63: ='Monthly Haver'!E66 -> #N/A | E63: ='Monthly Haver'!G66 -> 52.7769 | F63: ='Monthly Haver'!H66 -> 56.4012 | G63: ='Monthly Haver'!I66 -> #N/A | H63: ='Monthly Haver'!J66 -> 60.2597 | I63: =GDS_Monthly!O180 -> 64.790068 | J63: =GDS_Monthly!D180 -> 80.450229 | K63: =GDS_Monthly!AH180 -> 566.67375 | L63: =GDS_Monthly!AI180 -> 542.48756 | M63: =GDS_Monthly!N180 -> 6.6634621 | N63: =GDS_Monthly!C180 -> 109.08943 | O63: =GDS_Monthly!F180 -> 3.9920509 | P63: =GDS_Monthly!G180 -> 2.5526153 | Q63: =GDS_Monthly!T180 -> 84.586954 | R63: =GDS_Monthly!V180 -> 88.271879 | S63: =GDS_Monthly!W180 -> 74.045577 | T63: =GDS_Monthly!X180 -> 67.686744 | U63: =GDS_Monthly!AA180 -> 64.973046 | V63: =GDS_Monthly!AC180 -> 84.316824 | W63: =GDS_Monthly!AE180 -> 67.84845 | X63: =GDS_Monthly!AF180 -> 85.733717 | Y63: =OECD!B63 -> 100.54 | Z63: =OECD!C63 -> 103.43 | AA63: ='Monthly Haver'!K66 -> 105.01191 | AB63: ='Monthly Haver'!L66 -> 5450
A64: 38047 | B64: ='Monthly Haver'!C67 -> 59.8445 | C64: ='Monthly Haver'!D67 -> 64.5556 | D64: ='Monthly Haver'!E67 -> #N/A | E64: ='Monthly Haver'!G67 -> 53.4551 | F64: ='Monthly Haver'!H67 -> 56.9446 | G64: ='Monthly Haver'!I67 -> #N/A | H64: ='Monthly Haver'!J67 -> 59.4727 | I64: =GDS_Monthly!O181 -> 65.179394 | J64: =GDS_Monthly!D181 -> 80.596781 | K64: =GDS_Monthly!AH181 -> 572.06431 | L64: =GDS_Monthly!AI181 -> 546.15308 | M64: =GDS_Monthly!N181 -> 6.6706842 | N64: =GDS_Monthly!C181 -> 107.93725 | O64: =GDS_Monthly!F181 -> 3.8436899 | P64: =GDS_Monthly!G181 -> 2.5313003 | Q64: =GDS_Monthly!T181 -> 84.776746 | R64: =GDS_Monthly!V181 -> 88.452928 | S64: =GDS_Monthly!W181 -> 78.580753 | T64: =GDS_Monthly!X181 -> 67.603596 | U64: =GDS_Monthly!AA181 -> 67.076418 | V64: =GDS_Monthly!AC181 -> 87.764426 | W64: =GDS_Monthly!AE181 -> 74.057952 | X64: =GDS_Monthly!AF181 -> 85.334698 | Y64: =OECD!B64 -> 100.5782 | Z64: =OECD!C64 -> 104.3 | AA64: ='Monthly Haver'!K67 -> 105.79753 | AB64: ='Monthly Haver'!L67 -> 5131 | AC64: =Quarterly!B22 -> 98.36 | AD64: =Quarterly!C22 -> 93.21 | AE64: =Quarterly!D22 -> 86.340845 | AF64: 4.1882746
A65: 38078 | B65: ='Monthly Haver'!C68 -> 60.2145 | C65: ='Monthly Haver'!D68 -> 66.6796 | D65: ='Monthly Haver'!E68 -> #N/A | E65: ='Monthly Haver'!G68 -> 54.3848 | F65: ='Monthly Haver'!H68 -> 57.513 | G65: ='Monthly Haver'!I68 -> #N/A | H65: ='Monthly Haver'!J68 -> 60.5737 | I65: =GDS_Monthly!O182 -> 65.579688 | J65: =GDS_Monthly!D182 -> 81.354819 | K65: =GDS_Monthly!AH182 -> 579.93779 | L65: =GDS_Monthly!AI182 -> 553.83428 | M65: =GDS_Monthly!N182 -> 6.6718598 | N65: =GDS_Monthly!C182 -> 109.0556 | O65: =GDS_Monthly!F182 -> 4.1680704 | P65: =GDS_Monthly!G182 -> 2.4990942 | Q65: =GDS_Monthly!T182 -> 84.919668 | R65: =GDS_Monthly!V182 -> 88.601295 | S65: =GDS_Monthly!W182 -> 80.111032 | T65: =GDS_Monthly!X182 -> 66.23998 | U65: =GDS_Monthly!AA182 -> 67.345175 | V65: =GDS_Monthly!AC182 -> 89.681737 | W65: =GDS_Monthly!AE182 -> 74.82629 | X65: =GDS_Monthly!AF182 -> 85.070455 | Y65: =OECD!B65 -> 100.58 | Z65: =OECD!C65 -> 104.5 | AA65: ='Monthly Haver'!K68 -> 106.78036 | AB65: ='Monthly Haver'!L68 -> 4494
A66: 38108 | B66: ='Monthly Haver'!C69 -> 59.5462 | C66: ='Monthly Haver'!D69 -> 67.9732 | D66: ='Monthly Haver'!E69 -> #N/A | E66: ='Monthly Haver'!G69 -> 54.7409 | F66: ='Monthly Haver'!H69 -> 57.6514 | G66: ='Monthly Haver'!I69 -> #N/A | H66: ='Monthly Haver'!J69 -> 59.921 | I66: =GDS_Monthly!O183 -> 65.763963 | J66: =GDS_Monthly!D183 -> 81.642337 | K66: =GDS_Monthly!AH183 -> 579.98875 | L66: =GDS_Monthly!AI183 -> 559.22951 | M66: =GDS_Monthly!N183 -> 6.6040133 | N66: =GDS_Monthly!C183 -> 109.30794 | O66: =GDS_Monthly!F183 -> 4.4003238 | P66: =GDS_Monthly!G183 -> 2.5298568 | Q66: =GDS_Monthly!T183 -> 85.18824 | R66: =GDS_Monthly!V183 -> 88.723375 | S66: =GDS_Monthly!W183 -> 81.190719 | T66: =GDS_Monthly!X183 -> 62.285987 | U66: =GDS_Monthly!AA183 -> 66.853905 | V66: =GDS_Monthly!AC183 -> 98.390902 | W66: =GDS_Monthly!AE183 -> 83.738409 | X66: =GDS_Monthly!AF183 -> 87.956893 | Y66: =OECD!B66 -> 100.5576 | Z66: =OECD!C66 -> 104.98 | AA66: ='Monthly Haver'!K69 -> 109.33734 | AB66: ='Monthly Haver'!L69 -> 3596
