Workbook
Name _DLX1.USE: Haver_M!$A$2:$HO$5
Name _DLX2.USE: Haver_Q!$A$2:$CJ$5
Name EdssBatchRange: #REF!

Sheet Haver_M
C1: RS | D1: LTY | E1: REER | F1: CPI | G1: CORE | H1: IPALL | I1: IPBASIC | J1: IPCAPITAL | K1: IPINTERM | L1: IPCONS | M1: IPDURABLE | N1: IPNONDUR | O1: COREINDUSTRY | P1: CORECOAL | Q1: COREOIL | R1: COREGAS | S1: COREREFINE | T1: COREFERT | U1: CORESTEEL | V1: CORECEMENT | W1: COREELEC | X1: OILCONS | Y1: EXPMERCH | Z1: IMPMERCH | AA1: BOPXSERV | AB1: BOPMSERV | AC1: CONSCONF | AD1: CONSCONFX | AE1: UNCERTAINTY | AF1: PMIALL | AG1: PMIMANU | AH1: PMISERV | AI1: PMIOUTPUT | AJ1: PMINO | AK1: PMIEMPL | AL1: PMIDEL | AM1: PMISTOCKS | AN1: PMIINPUT | AO1: PMIQUANT | AP1: PMISTOCKS | AQ1: PMINEO | AR1: PMIOUTPRICES | AS1: PMIBACK | AT1: PMIORDERSINV | AU1: PMISERVEMPL | AV1: PMISERVPRI | AW1: PMISERNEW | AX1: PMISERVIN | AY1: PMISNEO | AZ1: PMISOUTB | BA1: STOCKS | BB1: CEICLEAD | BC1: BUSINESS | BD1: BUSINESSEXP | BE1: IOS_SURVEY | BF1: Auto_Two | BG1: Auto_Commercial | BH1: Auto_Total | BI1: Auto_Passenger | BN1: Exports_usd | BO1: Imports_USD | BP1: rup_usd | BQ1: Credit_Personal | BR1: Credit_Industry | BS1: Credit_Services | BT1: Credit_Nonfood | BU1: Agri_Production
A2: 10001 !M | B2: .excel_last | C2: N534RP@EMERGEPR | D2: N534RG10@EMERGEPR | E2: N534XJRB@EMERGEPR | F2: N534PC@EMERGEPR | G2: N534PCXG@EMERGEPR | H2: H534D@EMERGEPR | I2: H534DB@EMERGEPR | J2: H534DK@EMERGEPR | K2: H534DI@EMERGEPR | L2: H534DR@EMERGEPR | M2: H534DCD@EMERGEPR | N2: H534DCN@EMERGEPR | O2: H534VI@EMERGEPR | P2: H534OCLI@EMERGEPR | Q2: H534OCOI@EMERGEPR | R2: H534ONGI@EMERGEPR | S2: H534OPRI@EMERGEPR | T2: H534OFTI@EMERGEPR | U2: H534OSTI@EMERGEPR | V2: H534OCNI@EMERGEPR | W2: H534OELI@EMERGEPR | X2: sa(N534CRP@EMERGEPR) | Y2: H534IXD@EMERGEPR | Z2: H534IMD@EMERGEPR | AA2: M534BCSX@EMERGEPR | AB2: M534BCSM@EMERGEPR | AC2: N534VCC@EMERGEPR | AD2: N534VCE@EMERGEPR | AE2: sa(N534VIUC@EMERGEPR) | AF2: S534TG@MKTPMI | AG2: S534M@MKTPMI | AH2: S534S@MKTPMI | AI2: S534MG@MKTPMI | AJ2: S534MO@MKTPMI | AK2: S534ME@MKTPMI | AL2: S534MD@MKTPMI | AM2: S534MSP@MKTPMI | AN2: S534MPI@MKTPMI | AO2: S534MQP@MKTPMI | AP2: S534MSF@MKTPMI | AQ2: S534MX@MKTPMI | AR2: S534MPO@MKTPMI | AS2: S534MB@MKTPMI | AT2: S534OI@MKTPMI | AU2: S534SE@MKTPMI | AV2: S534SPC@MKTPMI | AW2: S534SNB@MKTPMI | AX2: S534SPI@MKTPMI | AY2: S534SX@MKTPMI | AZ2: S534SWO@MKTPMI | BA2: N534FKSV@EMERGEPR | BB2: 6 | BC2: 2 | BD2: 3 | BE2: 4 | BJ2: N534CNHH@EMERGEPR | BK2: N534CNIN@EMERGEPR | BL2: N534CNOP@EMERGEPR | BM2: N534CNF@EMERGEPR | BN2: N534IXD@EMERGEPR | BO2: N534IMD@EMERGEPR | BP2: N534XUSV@EMERGEPR | BU2: N534OASF@EMERGEPR
A3: .DESC | C3: India: Repo Rate (EOP, % per annum) | D3: India: 10-Year Government Bond Yield (EOP, % per annum) | E3: India: JPMorgan Real Broad Effective Exchange Rate Index, PPI Based (2010=100) | F3: India: Consumer Price Index (NSA, 2012=100) | G3: India: CPI Ex Food and Energy (NSA, 2012=100) | H3: India: IP: General Index (SA, Apr.11-Mar.12=100) | I3: India: IP: Basic Goods (SA, Apr.11-Mar.12=100) | J3: India: IP: Capital Goods (SA, Apr.11-Mar.12=100) | K3: India: IP: Intermediate Goods (SA, Apr.11-Mar.12=100) | L3: India: IP: Infrastructure and Construction Goods (SA, Apr.11-Mar.12=100) | M3: India: IP: Consumer Durable Goods (SA, Apr.11-Mar.12=100) | N3: India: IP: Consumer Nondurable Goods (SA, Apr.11-Mar.12=100) | O3: India: Eight Core Industry Infrastructure Index (SA, Apr.11-Mar.12=100) | P3: India: Eight Core Industries Index: Coal (SA, Apr.11-Mar.12=100) | Q3: India: Eight Core Industries Index: Crude Oil (SA, Apr.11-Mar.12=100) | R3: India: Eight Core Industries Index: Natural Gas (SA, Apr.11-Mar.12=100) | S3: India: Eight Core Ind Index: Petroleum Refinery Products(SA, Apr.11-Mar.12=100) | T3: India: Eight Core Industries Index: Fertilizers (SA, Apr.11-Mar.12=100) | U3: India: Eight Core Industries Index: Steel (SA, Apr.11-Mar.12=100) | V3: India: Eight Core Industries Index: Cement (SA, Apr.11-Mar.12=100) | W3: India: Eight Core Industries Index: Electricity (SA, Apr.11-Mar.12=100) | X3: India: Consumption of Petroleum Products (NSA, Thous.Metric Tons) - Seasonal Adjustment, All | Y3: India: Merchandise Exports, f.o.b. (SA, Mil.US$) | Z3: India: Merchandise Imports, c.i.f. (SA, Mil.US$) | AA3: India: BOP: Services: Exports (NSA, Mil.US$) | AB3: India: BOP: Services: Imports (NSA, Mil.US$) | AC3: India: Consumer Confidence Survey: Current Situation Index (NSA, 100=neutral) | AD3: India: Consumer Confidence Survey: Future Expectation Index (NSA, 100=neutral) | AE3: India: News Based Economic Policy Uncertainty Index (Mean=100) - Seasonal Adjustment, All | AF3: India PMI: Composite Output (SA, 50+=Expansion) | AG3: India PMI: Manufacturing (SA, 50+=Expansion) | AH3: India PMI: Services Business Activity (SA, 50+=Expansion) | AI3: India PMI: Manufacturing Output (SA, 50+=Expansion) | AJ3: India PMI: Manufacturing New Orders (SA, 50+=Expansion) | AK3: India PMI: Manufacturing Employment (SA, 50+=Expansion) | AL3: India PMI: Manufacturing Suppliers' Delivery Times (SA, 50+=Contraction) | AM3: India PMI: Manufacturing Stocks of Purchases (SA, 50+=Expansion) | AN3: India PMI: Manufacturing Input Prices (SA, 50+=Expansion) | AO3: India PMI: Manufacturing Quantity of Purchases (SA, 50+=Expansion) | AP3: India PMI: Manufacturing Stocks of Finished Goods (SA, 50+=Expansion) | AQ3: India PMI: Manufacturing New Export Orders (SA, 50+=Expansion) | AR3: India PMI: Manufacturing Output Prices (SA, 50+=Expansion) | AS3: India PMI: Manufacturing Backlogs of Work (SA, 50+=Expansion) | AT3: India: Manufacturing Orders to Inventories (SA, Ratio) | AU3: India PMI: Services Employment (SA, 50+=Expansion) | AV3: India PMI: Services Prices Charged (SA, 50+=Expansion) | AW3: India PMI: Services New Business (SA, 50+=Expansion) | AX3: India PMI: Services Input Prices (SA, 50+=Expansion) | AY3: India PMI: Services New Export Orders (SA, 50+=Expansion) | AZ3: India PMI: Services Outstanding Business (SA, 50+=Expansion) | BA3: India: Stock Prices: BSE Sensex/BSE 30 Index (AVG, 1978-79=100) | BB3: CEIC Leading Indicator: Smoothed: India | BC3: RBI: Industrial Outlook Survey: Business Expectation Index: Assessment for Current Quarter | BD3: RBI Forecast: Industrial Outlook Survey: Business Expectation Index: Expectation for Next Quarter | BE3: RBI Forecast: Industrial Outlook Survey: Overall Business Situation | BF3: Automobile Sales: SIAM: Two Wheelers | BG3: Automobile Sales: SIAM: Commercial Vehicle | BH3: Automobile Sales: SIAM: Total | BI3: Automobile Sales: SIAM: Passenger Vehicle | BJ3: India: Bank Credit Outstanding: Personal Loans (EOP, NSA, Bil.Rupees) | BK3: India: Bank Credit Outstanding: Industry (EOP, NSA, Bil.Rupees) | BL3: India: Bank Credit Outstanding: Services (EOP, NSA, Bil.Rupees) | BM3: India: Bank Credit Outstanding: Nonfood Credit (EOP, NSA, Bil.Rupees) | BN3: India: Merchandise Exports, f.o.b. (NSA, Mil.US$) | BO3: India: Merchandise Imports, c.i.f. (NSA, Mil.US$) | BP3: India: Rupee/US$ Exchange Rate (AVG) | BU3: India: Agricultural Production: Stock of Foodgrains (NSA, Thous.Metric Tons)
A4: .T1 | C4: Apr-2001 | D4: May-1996 | E4: Jan-1990 | F4: Jan-2001 | G4: Jan-2011 | H4: Jan-1971 | I4: Apr-1994 | J4: Apr-1994 | K4: Apr-1994 | L4: Apr-2012 | M4: Apr-1994 | N4: Apr-1994 | O4: Apr-2004 | P4: Apr-2004 | Q4: Apr-2004 | R4: Apr-2004 | S4: Apr-2004 | T4: Apr-2004 | U4: Apr-2004 | V4: Apr-2004 | W4: Apr-2004 | X4: Apr-1998 | Y4: Jan-1968 | Z4: Jan-1968 | AA4: Apr-2011 | AB4: Apr-2011 | AC4: Dec-2010 | AD4: Dec-2010 | AE4: Jan-1997 | AF4: Dec-2005 | AG4: Mar-2005 | AH4: Dec-2005 | AI4: Mar-2005 | AJ4: Mar-2005 | AK4: Mar-2005 | AL4: Mar-2005 | AM4: Mar-2005 | AN4: Mar-2005 | AO4: Mar-2005 | AP4: Mar-2005 | AQ4: Mar-2005 | AR4: Mar-2005 | AS4: Mar-2005 | AT4: Mar-2005 | AU4: Dec-2005 | AV4: Dec-2005 | AW4: Dec-2005 | AX4: Dec-2005 | AY4: Sep-2014 | AZ4: Dec-2005 | BA4: Apr-1979 | BJ4: Apr-2007 | BK4: Apr-2007 | BL4: Apr-2007 | BM4: Apr-2007 | BN4: Jan-1968 | BO4: Jan-1968 | BP4: Mar-1992 | BU4: Apr-1990
A5: .TN | C5: Feb-2020 | D5: Dec-2019 | E5: Jan-2020 | F5: Jan-2020 | G5: Jan-2020 | H5: Dec-2019 | I5: Dec-2019 | J5: Dec-2019 | K5: Dec-2019 | L5: Dec-2019 | M5: Dec-2019 | N5: Dec-2019 | O5: Dec-2019 | P5: Dec-2019 | Q5: Dec-2019 | R5: Dec-2019 | S5: Dec-2019 | T5: Dec-2019 | U5: Dec-2019 | V5: Dec-2019 | W5: Dec-2019 | X5: Jan-2020 | Y5: Jan-2020 | Z5: Jan-2020 | AA5: Dec-2019 | AB5: Dec-2019 | AC5: Jan-2020 | AD5: Jan-2020 | AE5: Jan-2020 | AF5: Jan-2020 | AG5: Jan-2020 | AH5: Jan-2020 | AI5: Jan-2020 | AJ5: Jan-2020 | AK5: Jan-2020 | AL5: Jan-2020 | AM5: Jan-2020 | AN5: Jan-2020 | AO5: Jan-2020 | AP5: Jan-2020 | AQ5: Jan-2020 | AR5: Jan-2020 | AS5: Jan-2020 | AT5: Jan-2020 | AU5: Jan-2020 | AV5: Jan-2020 | AW5: Jan-2020 | AX5: Jan-2020 | AY5: Jan-2020 | AZ5: Jan-2020 | BA5: Jan-2020 | BJ5: Dec-2019 | BK5: Dec-2019 | BL5: Dec-2019 | BM5: Dec-2019 | BN5: Jan-2020 | BO5: Jan-2020 | BP5: Jan-2020 | BU5: Jan-2020
A6: 0001 | B6: 36556 | C6: #N/A | D6: 10.9434 | E6: 91.11364 | F6: #N/A | G6: #N/A | H6: 44.61 | I6: 53.7 | J6: 26.22 | K6: 56.45 | L6: #N/A | M6: 22.46 | N6: 45.74 | O6: #N/A | P6: #N/A | Q6: #N/A | R6: #N/A | S6: #N/A | T6: #N/A | U6: #N/A | V6: #N/A | W6: #N/A | X6: 7897.1824 | Y6: 2739.66 | Z6: 3874.06 | AA6: #N/A | AB6: #N/A | AC6: #N/A | AD6: #N/A | AE6: 58.825769 | AF6: #N/A | AG6: #N/A | AH6: #N/A | AI6: #N/A | AJ6: #N/A | AK6: #N/A | AL6: #N/A | AM6: #N/A | AN6: #N/A | AO6: #N/A | AP6: #N/A | AQ6: #N/A | AR6: #N/A | AS6: #N/A | AT6: #N/A | AU6: #N/A | AV6: #N/A | AW6: #N/A | AX6: #N/A | AY6: #N/A | AZ6: #N/A | BA6: 5407.14 | BB6: =IF(ISNUMBER(VLOOKUP($B6,CEIC_DATA!$I$26:$N$353,Haver_M!BB$2,FALSE)),VLOOKUP($B6,CEIC_DATA!$I$26:$N$353,Haver_M!BB$2,FALSE),NA()) -> 118.54817 | BC6: =IF(ISNUMBER(VLOOKUP($B6,CEIC_DATA!$I$26:$N$353,Haver_M!BC$2,FALSE)),VLOOKUP($B6,CEIC_DATA!$I$26:$N$353,Haver_M!BC$2,FALSE),NA()) -> #N/A | BD6: =IF(ISNUMBER(VLOOKUP($B6,CEIC_DATA!$I$26:$N$353,Haver_M!BD$2,FALSE)),VLOOKUP($B6,CEIC_DATA!$I$26:$N$353,Haver_M!BD$2,FALSE),NA()) -> #N/A | BE6: =IF(ISNUMBER(VLOOKUP($B6,CEIC_DATA!$I$26:$N$353,Haver_M!BE$2,FALSE)),VLOOKUP($B6,CEIC_DATA!$I$26:$N$353,Haver_M!BE$2,FALSE),NA()) -> #N/A | BJ6: #N/A | BK6: #N/A | BL6: #N/A | BM6: #N/A | BN6: 2748 | BO6: 3879 | BP6: 43.55 | BQ6: =IF(ISNUMBER(BJ6),BJ6/$BP6,"") | BR6: =IF(ISNUMBER(BK6),BK6/$BP6,"") | BS6: =IF(ISNUMBER(BL6),BL6/$BP6,"") | BT6: =IF(ISNUMBER(BM6),BM6/$BP6,"") | BU6: 31165
A7: 0002 | B7: 36585 | C7: #N/A | D7: 10.4416 | E7: 92.20659 | F7: #N/A | G7: #N/A | H7: 44.07 | I7: 53.84 | J7: 26.76 | K7: 55.37 | L7: #N/A | M7: 23.3 | N7: 45.97 | O7: #N/A | P7: #N/A | Q7: #N/A | R7: #N/A | S7: #N/A | T7: #N/A | U7: #N/A | V7: #N/A | W7: #N/A | X7: 8487.2218 | Y7: 3406.19 | Z7: 4558.46 | AA7: #N/A | AB7: #N/A | AC7: #N/A | AD7: #N/A | AE7: 56.396633 | AF7: #N/A | AG7: #N/A | AH7: #N/A | AI7: #N/A | AJ7: #N/A | AK7: #N/A | AL7: #N/A | AM7: #N/A | AN7: #N/A | AO7: #N/A | AP7: #N/A | AQ7: #N/A | AR7: #N/A | AS7: #N/A | AT7: #N/A | AU7: #N/A | AV7: #N/A | AW7: #N/A | AX7: #N/A | AY7: #N/A | AZ7: #N/A | BA7: 5650.66 | BB7: =IF(ISNUMBER(VLOOKUP($B7,CEIC_DATA!$I$26:$N$353,Haver_M!BB$2,FALSE)),VLOOKUP($B7,CEIC_DATA!$I$26:$N$353,Haver_M!BB$2,FALSE),NA()) -> 118.91702 | BC7: =IF(ISNUMBER(VLOOKUP($B7,CEIC_DATA!$I$26:$N$353,Haver_M!BC$2,FALSE)),VLOOKUP($B7,CEIC_DATA!$I$26:$N$353,Haver_M!BC$2,FALSE),NA()) -> #N/A | BD7: =IF(ISNUMBER(VLOOKUP($B7,CEIC_DATA!$I$26:$N$353,Haver_M!BD$2,FALSE)),VLOOKUP($B7,CEIC_DATA!$I$26:$N$353,Haver_M!BD$2,FALSE),NA()) -> #N/A | BE7: =IF(ISNUMBER(VLOOKUP($B7,CEIC_DATA!$I$26:$N$353,Haver_M!BE$2,FALSE)),VLOOKUP($B7,CEIC_DATA!$I$26:$N$353,Haver_M!BE$2,FALSE),NA()) -> #N/A | BJ7: #N/A | BK7: #N/A | BL7: #N/A | BM7: #N/A | BN7: 3404 | BO7: 4344 | BP7: 43.6136 | BQ7: =IF(ISNUMBER(BJ7),BJ7/$BP7,"") | BR7: =IF(ISNUMBER(BK7),BK7/$BP7,"") | BS7: =IF(ISNUMBER(BL7),BL7/$BP7,"") | BT7: =IF(ISNUMBER(BM7),BM7/$BP7,"") | BU7: 30452
A8: 0003 | B8: 36616 | C8: #N/A | D8: 10.8663 | E8: 94.05975 | F8: #N/A | G8: #N/A | H8: 45.67 | I8: 55.16 | J8: 26.04 | K8: 56.77 | L8: #N/A | M8: 25.83 | N8: 46.55 | O8: #N/A | P8: #N/A | Q8: #N/A | R8: #N/A | S8: #N/A | T8: #N/A | U8: #N/A | V8: #N/A | W8: #N/A | X8: 8182.9763 | Y8: 3354.8 | Z8: 4577.21 | AA8: #N/A | AB8: #N/A | AC8: #N/A | AD8: #N/A | AE8: 62.373813 | AF8: #N/A | AG8: #N/A | AH8: #N/A | AI8: #N/A | AJ8: #N/A | AK8: #N/A | AL8: #N/A | AM8: #N/A | AN8: #N/A | AO8: #N/A | AP8: #N/A | AQ8: #N/A | AR8: #N/A | AS8: #N/A | AT8: #N/A | AU8: #N/A | AV8: #N/A | AW8: #N/A | AX8: #N/A | AY8: #N/A | AZ8: #N/A | BA8: 5261.77 | BB8: =IF(ISNUMBER(VLOOKUP($B8,CEIC_DATA!$I$26:$N$353,Haver_M!BB$2,FALSE)),VLOOKUP($B8,CEIC_DATA!$I$26:$N$353,Haver_M!BB$2,FALSE),NA()) -> 118.53685 | BC8: =IF(ISNUMBER(VLOOKUP($B8,CEIC_DATA!$I$26:$N$353,Haver_M!BC$2,FALSE)),VLOOKUP($B8,CEIC_DATA!$I$26:$N$353,Haver_M!BC$2,FALSE),NA()) -> 122.8 | BD8: =IF(ISNUMBER(VLOOKUP($B8,CEIC_DATA!$I$26:$N$353,Haver_M!BD$2,FALSE)),VLOOKUP($B8,CEIC_DATA!$I$26:$N$353,Haver_M!BD$2,FALSE),NA()) -> #N/A | BE8: =IF(ISNUMBER(VLOOKUP($B8,CEIC_DATA!$I$26:$N$353,Haver_M!BE$2,FALSE)),VLOOKUP($B8,CEIC_DATA!$I$26:$N$353,Haver_M!BE$2,FALSE),NA()) -> #N/A | BJ8: #N/A | BK8: #N/A | BL8: #N/A | BM8: #N/A | BN8: 3860 | BO8: 4871 | BP8: 43.5857 | BQ8: =IF(ISNUMBER(BJ8),BJ8/$BP8,"") | BR8: =IF(ISNUMBER(BK8),BK8/$BP8,"") | BS8: =IF(ISNUMBER(BL8),BL8/$BP8,"") | BT8: =IF(ISNUMBER(BM8),BM8/$BP8,"") | BU8: 28906
A9: 0004 | B9: 36646 | C9: #N/A | D9: 10.3663 | E9: 95.74013 | F9: #N/A | G9: #N/A | H9: 45.86 | I9: 54.3 | J9: 29.41 | K9: 57.06 | L9: #N/A | M9: 24.91 | N9: 46.49 | O9: #N/A | P9: #N/A | Q9: #N/A | R9: #N/A | S9: #N/A | T9: #N/A | U9: #N/A | V9: #N/A | W9: #N/A | X9: 8274.9538 | Y9: 3422.47 | Z9: 4551.49 | AA9: #N/A | AB9: #N/A | AC9: #N/A | AD9: #N/A | AE9: 75.890914 | AF9: #N/A | AG9: #N/A | AH9: #N/A | AI9: #N/A | AJ9: #N/A | AK9: #N/A | AL9: #N/A | AM9: #N/A | AN9: #N/A | AO9: #N/A | AP9: #N/A | AQ9: #N/A | AR9: #N/A | AS9: #N/A | AT9: #N/A | AU9: #N/A | AV9: #N/A | AW9: #N/A | AX9: #N/A | AY9: #N/A | AZ9: #N/A | BA9: 4905.3 | BB9: =IF(ISNUMBER(VLOOKUP($B9,CEIC_DATA!$I$26:$N$353,Haver_M!BB$2,FALSE)),VLOOKUP($B9,CEIC_DATA!$I$26:$N$353,Haver_M!BB$2,FALSE),NA()) -> 117.60795 | BC9: =IF(ISNUMBER(VLOOKUP($B9,CEIC_DATA!$I$26:$N$353,Haver_M!BC$2,FALSE)),VLOOKUP($B9,CEIC_DATA!$I$26:$N$353,Haver_M!BC$2,FALSE),NA()) -> #N/A | BD9: =IF(ISNUMBER(VLOOKUP($B9,CEIC_DATA!$I$26:$N$353,Haver_M!BD$2,FALSE)),VLOOKUP($B9,CEIC_DATA!$I$26:$N$353,Haver_M!BD$2,FALSE),NA()) -> #N/A | BE9: =IF(ISNUMBER(VLOOKUP($B9,CEIC_DATA!$I$26:$N$353,Haver_M!BE$2,FALSE)),VLOOKUP($B9,CEIC_DATA!$I$26:$N$353,Haver_M!BE$2,FALSE),NA()) -> #N/A | BJ9: #N/A | BK9: #N/A | BL9: #N/A | BM9: #N/A | BN9: 3310 | BO9: 4401 | BP9: 43.6388 | BQ9: =IF(ISNUMBER(BJ9),BJ9/$BP9,"") | BR9: =IF(ISNUMBER(BK9),BK9/$BP9,"") | BS9: =IF(ISNUMBER(BL9),BL9/$BP9,"") | BT9: =IF(ISNUMBER(BM9),BM9/$BP9,"") | BU9: 36577
A10: 0005 | B10: 36677 | C10: #N/A | D10: 10.8186 | E10: 96.77981 | F10: #N/A | G10: #N/A | H10: 46.05 | I10: 55.04 | J10: 27.13 | K10: 58.18 | L10: #N/A | M10: 25.83 | N10: 46.12 | O10: #N/A | P10: #N/A | Q10: #N/A | R10: #N/A | S10: #N/A | T10: #N/A | U10: #N/A | V10: #N/A | W10: #N/A | X10: 8384.727 | Y10: 3687.09 | Z10: 4212.82 | AA10: #N/A | AB10: #N/A | AC10: #N/A | AD10: #N/A | AE10: 66.784844 | AF10: #N/A | AG10: #N/A | AH10: #N/A | AI10: #N/A | AJ10: #N/A | AK10: #N/A | AL10: #N/A | AM10: #N/A | AN10: #N/A | AO10: #N/A | AP10: #N/A | AQ10: #N/A | AR10: #N/A | AS10: #N/A | AT10: #N/A | AU10: #N/A | AV10: #N/A | AW10: #N/A | AX10: #N/A | AY10: #N/A | AZ10: #N/A | BA10: 4253.11 | BB10: =IF(ISNUMBER(VLOOKUP($B10,CEIC_DATA!$I$26:$N$353,Haver_M!BB$2,FALSE)),VLOOKUP($B10,CEIC_DATA!$I$26:$N$353,Haver_M!BB$2,FALSE),NA()) -> 116.38076 | BC10: =IF(ISNUMBER(VLOOKUP($B10,CEIC_DATA!$I$26:$N$353,Haver_M!BC$2,FALSE)),VLOOKUP($B10,CEIC_DATA!$I$26:$N$353,Haver_M!BC$2,FALSE),NA()) -> #N/A | BD10: =IF(ISNUMBER(VLOOKUP($B10,CEIC_DATA!$I$26:$N$353,Haver_M!BD$2,FALSE)),VLOOKUP($B10,CEIC_DATA!$I$26:$N$353,Haver_M!BD$2,FALSE),NA()) -> #N/A | BE10: =IF(ISNUMBER(VLOOKUP($B10,CEIC_DATA!$I$26:$N$353,Haver_M!BE$2,FALSE)),VLOOKUP($B10,CEIC_DATA!$I$26:$N$353,Haver_M!BE$2,FALSE),NA()) -> #N/A | BJ10: #N/A | BK10: #N/A | BL10: #N/A | BM10: #N/A | BN10: 3577 | BO10: 4371 | BP10: 43.9829 | BQ10: =IF(ISNUMBER(BJ10),BJ10/$BP10,"") | BR10: =IF(ISNUMBER(BK10),BK10/$BP10,"") | BS10: =IF(ISNUMBER(BL10),BL10/$BP10,"") | BT10: =IF(ISNUMBER(BM10),BM10/$BP10,"") | BU10: 42885
A11: 0006 | B11: 36707 | C11: #N/A | D11: 11.1004 | E11: 93.66655 | F11: #N/A | G11: #N/A | H11: 45.8 | I11: 55.37 | J11: 27.31 | K11: 57.25 | L11: #N/A | M11: 25.58 | N11: 45.87 | O11: #N/A | P11: #N/A | Q11: #N/A | R11: #N/A | S11: #N/A | T11: #N/A | U11: #N/A | V11: #N/A | W11: #N/A | X11: 8235.3562 | Y11: 3631.69 | Z11: 4263.3 | AA11: #N/A | AB11: #N/A | AC11: #N/A | AD11: #N/A | AE11: 117.52526 | AF11: #N/A | AG11: #N/A | AH11: #N/A | AI11: #N/A | AJ11: #N/A | AK11: #N/A | AL11: #N/A | AM11: #N/A | AN11: #N/A | AO11: #N/A | AP11: #N/A | AQ11: #N/A | AR11: #N/A | AS11: #N/A | AT11: #N/A | AU11: #N/A | AV11: #N/A | AW11: #N/A | AX11: #N/A | AY11: #N/A | AZ11: #N/A | BA11: 4675.4 | BB11: =IF(ISNUMBER(VLOOKUP($B11,CEIC_DATA!$I$26:$N$353,Haver_M!BB$2,FALSE)),VLOOKUP($B11,CEIC_DATA!$I$26:$N$353,Haver_M!BB$2,FALSE),NA()) -> 115.04659 | BC11: =IF(ISNUMBER(VLOOKUP($B11,CEIC_DATA!$I$26:$N$353,Haver_M!BC$2,FALSE)),VLOOKUP($B11,CEIC_DATA!$I$26:$N$353,Haver_M!BC$2,FALSE),NA()) -> 115.2 | BD11: =IF(ISNUMBER(VLOOKUP($B11,CEIC_DATA!$I$26:$N$353,Haver_M!BD$2,FALSE)),VLOOKUP($B11,CEIC_DATA!$I$26:$N$353,Haver_M!BD$2,FALSE),NA()) -> 125.5 | BE11: =IF(ISNUMBER(VLOOKUP($B11,CEIC_DATA!$I$26:$N$353,Haver_M!BE$2,FALSE)),VLOOKUP($B11,CEIC_DATA!$I$26:$N$353,Haver_M!BE$2,FALSE),NA()) -> 53.8 | BJ11: #N/A | BK11: #N/A | BL11: #N/A | BM11: #N/A | BN11: 3455 | BO11: 4028 | BP11: 44.6863 | BQ11: =IF(ISNUMBER(BJ11),BJ11/$BP11,"") | BR11: =IF(ISNUMBER(BK11),BK11/$BP11,"") | BS11: =IF(ISNUMBER(BL11),BL11/$BP11,"") | BT11: =IF(ISNUMBER(BM11),BM11/$BP11,"") | BU11: 42247
A12: 0007 | B12: 36738 | C12: #N/A | D12: 11.3 | E12: 93.99963 | F12: #N/A | G12: #N/A | H12: 45.93 | I12: 55.24 | J12: 27.83 | K12: 57.28 | L12: #N/A | M12: 25.32 | N12: 44.75 | O12: #N/A | P12: #N/A | Q12: #N/A | R12: #N/A | S12: #N/A | T12: #N/A | U12: #N/A | V12: #N/A | W12: #N/A | X12: 8201.1603 | Y12: 3516.88 | Z12: 4282.13 | AA12: #N/A | AB12: #N/A | AC12: #N/A | AD12: #N/A | AE12: 67.622725 | AF12: #N/A | AG12: #N/A | AH12: #N/A | AI12: #N/A | AJ12: #N/A | AK12: #N/A | AL12: #N/A | AM12: #N/A | AN12: #N/A | AO12: #N/A | AP12: #N/A | AQ12: #N/A | AR12: #N/A | AS12: #N/A | AT12: #N/A | AU12: #N/A | AV12: #N/A | AW12: #N/A | AX12: #N/A | AY12: #N/A | AZ12: #N/A | BA12: 4647.34 | BB12: =IF(ISNUMBER(VLOOKUP($B12,CEIC_DATA!$I$26:$N$353,Haver_M!BB$2,FALSE)),VLOOKUP($B12,CEIC_DATA!$I$26:$N$353,Haver_M!BB$2,FALSE),NA()) -> 113.73682 | BC12: =IF(ISNUMBER(VLOOKUP($B12,CEIC_DATA!$I$26:$N$353,Haver_M!BC$2,FALSE)),VLOOKUP($B12,CEIC_DATA!$I$26:$N$353,Haver_M!BC$2,FALSE),NA()) -> #N/A | BD12: =IF(ISNUMBER(VLOOKUP($B12,CEIC_DATA!$I$26:$N$353,Haver_M!BD$2,FALSE)),VLOOKUP($B12,CEIC_DATA!$I$26:$N$353,Haver_M!BD$2,FALSE),NA()) -> #N/A | BE12: =IF(ISNUMBER(VLOOKUP($B12,CEIC_DATA!$I$26:$N$353,Haver_M!BE$2,FALSE)),VLOOKUP($B12,CEIC_DATA!$I$26:$N$353,Haver_M!BE$2,FALSE),NA()) -> #N/A | BJ12: #N/A | BK12: #N/A | BL12: #N/A | BM12: #N/A | BN12: 3526 | BO12: 4487 | BP12: 44.7788 | BQ12: =IF(ISNUMBER(BJ12),BJ12/$BP12,"") | BR12: =IF(ISNUMBER(BK12),BK12/$BP12,"") | BS12: =IF(ISNUMBER(BL12),BL12/$BP12,"") | BT12: =IF(ISNUMBER(BM12),BM12/$BP12,"") | BU12: 41250
A13: 0008 | B13: 36769 | C13: #N/A | D13: 11.3715 | E13: 93.4465 | F13: #N/A | G13: #N/A | H13: 45.99 | I13: 55.02 | J13: 27.45 | K13: 58.06 | L13: #N/A | M13: 25.01 | N13: 46.03 | O13: #N/A | P13: #N/A | Q13: #N/A | R13: #N/A | S13: #N/A | T13: #N/A | U13: #N/A | V13: #N/A | W13: #N/A | X13: 8701.667 | Y13: 3651.1 | Z13: 4054.36 | AA13: #N/A | AB13: #N/A | AC13: #N/A | AD13: #N/A | AE13: 63.806214 | AF13: #N/A | AG13: #N/A | AH13: #N/A | AI13: #N/A | AJ13: #N/A | AK13: #N/A | AL13: #N/A | AM13: #N/A | AN13: #N/A | AO13: #N/A | AP13: #N/A | AQ13: #N/A | AR13: #N/A | AS13: #N/A | AT13: #N/A | AU13: #N/A | AV13: #N/A | AW13: #N/A | AX13: #N/A | AY13: #N/A | AZ13: #N/A | BA13: 4330.31 | BB13: =IF(ISNUMBER(VLOOKUP($B13,CEIC_DATA!$I$26:$N$353,Haver_M!BB$2,FALSE)),VLOOKUP($B13,CEIC_DATA!$I$26:$N$353,Haver_M!BB$2,FALSE),NA()) -> 112.67092 | BC13: =IF(ISNUMBER(VLOOKUP($B13,CEIC_DATA!$I$26:$N$353,Haver_M!BC$2,FALSE)),VLOOKUP($B13,CEIC_DATA!$I$26:$N$353,Haver_M!BC$2,FALSE),NA()) -> #N/A | BD13: =IF(ISNUMBER(VLOOKUP($B13,CEIC_DATA!$I$26:$N$353,Haver_M!BD$2,FALSE)),VLOOKUP($B13,CEIC_DATA!$I$26:$N$353,Haver_M!BD$2,FALSE),NA()) -> #N/A | BE13: =IF(ISNUMBER(VLOOKUP($B13,CEIC_DATA!$I$26:$N$353,Haver_M!BE$2,FALSE)),VLOOKUP($B13,CEIC_DATA!$I$26:$N$353,Haver_M!BE$2,FALSE),NA()) -> #N/A | BJ13: #N/A | BK13: #N/A | BL13: #N/A | BM13: #N/A | BN13: 3670 | BO13: 3993 | BP13: 45.68 | BQ13: =IF(ISNUMBER(BJ13),BJ13/$BP13,"") | BR13: =IF(ISNUMBER(BK13),BK13/$BP13,"") | BS13: =IF(ISNUMBER(BL13),BL13/$BP13,"") | BT13: =IF(ISNUMBER(BM13),BM13/$BP13,"") | BU13: 40768
A14: 0009 | B14: 36799 | C14: #N/A | D14: 11.8051 | E14: 94.54199 | F14: #N/A | G14: #N/A | H14: 46.55 | I14: 55.53 | J14: 26.98 | K14: 58.23 | L14: #N/A | M14: 24.47 | N14: 48.02 | O14: #N/A | P14: #N/A | Q14: #N/A | R14: #N/A | S14: #N/A | T14: #N/A | U14: #N/A | V14: #N/A | W14: #N/A | X14: 9044.4752 | Y14: 3758.25 | Z14: 4211.38 | AA14: #N/A | AB14: #N/A | AC14: #N/A | AD14: #N/A | AE14: 49.221947 | AF14: #N/A | AG14: #N/A | AH14: #N/A | AI14: #N/A | AJ14: #N/A | AK14: #N/A | AL14: #N/A | AM14: #N/A | AN14: #N/A | AO14: #N/A | AP14: #N/A | AQ14: #N/A | AR14: #N/A | AS14: #N/A | AT14: #N/A | AU14: #N/A | AV14: #N/A | AW14: #N/A | AX14: #N/A | AY14: #N/A | AZ14: #N/A | BA14: 4416.61 | BB14: =IF(ISNUMBER(VLOOKUP($B14,CEIC_DATA!$I$26:$N$353,Haver_M!BB$2,FALSE)),VLOOKUP($B14,CEIC_DATA!$I$26:$N$353,Haver_M!BB$2,FALSE),NA()) -> 111.82207 | BC14: =IF(ISNUMBER(VLOOKUP($B14,CEIC_DATA!$I$26:$N$353,Haver_M!BC$2,FALSE)),VLOOKUP($B14,CEIC_DATA!$I$26:$N$353,Haver_M!BC$2,FALSE),NA()) -> 116.1 | BD14: =IF(ISNUMBER(VLOOKUP($B14,CEIC_DATA!$I$26:$N$353,Haver_M!BD$2,FALSE)),VLOOKUP($B14,CEIC_DATA!$I$26:$N$353,Haver_M!BD$2,FALSE),NA()) -> 126.1 | BE14: =IF(ISNUMBER(VLOOKUP($B14,CEIC_DATA!$I$26:$N$353,Haver_M!BE$2,FALSE)),VLOOKUP($B14,CEIC_DATA!$I$26:$N$353,Haver_M!BE$2,FALSE),NA()) -> 49 | BJ14: #N/A | BK14: #N/A | BL14: #N/A | BM14: #N/A | BN14: 3848 | BO14: 4249 | BP14: 45.8883 | BQ14: =IF(ISNUMBER(BJ14),BJ14/$BP14,"") | BR14: =IF(ISNUMBER(BK14),BK14/$BP14,"") | BS14: =IF(ISNUMBER(BL14),BL14/$BP14,"") | BT14: =IF(ISNUMBER(BM14),BM14/$BP14,"") | BU14: 40064
A15: 0010 | B15: 36830 | C15: #N/A | D15: 11.6078 | E15: 96.10024 | F15: #N/A | G15: #N/A | H15: 46.87 | I15: 56.6 | J15: 26.79 | K15: 58.53 | L15: #N/A | M15: 24.52 | N15: 48.96 | O15: #N/A | P15: #N/A | Q15: #N/A | R15: #N/A | S15: #N/A | T15: #N/A | U15: #N/A | V15: #N/A | W15: #N/A | X15: 7804.4426 | Y15: 3661.32 | Z15: 4197.55 | AA15: #N/A | AB15: #N/A | AC15: #N/A | AD15: #N/A | AE15: 55.000218 | AF15: #N/A | AG15: #N/A | AH15: #N/A | AI15: #N/A | AJ15: #N/A | AK15: #N/A | AL15: #N/A | AM15: #N/A | AN15: #N/A | AO15: #N/A | AP15: #N/A | AQ15: #N/A | AR15: #N/A | AS15: #N/A | AT15: #N/A | AU15: #N/A | AV15: #N/A | AW15: #N/A | AX15: #N/A | AY15: #N/A | AZ15: #N/A | BA15: 3819.69 | BB15: =IF(ISNUMBER(VLOOKUP($B15,CEIC_DATA!$I$26:$N$353,Haver_M!BB$2,FALSE)),VLOOKUP($B15,CEIC_DATA!$I$26:$N$353,Haver_M!BB$2,FALSE),NA()) -> 111.14065 | BC15: =IF(ISNUMBER(VLOOKUP($B15,CEIC_DATA!$I$26:$N$353,Haver_M!BC$2,FALSE)),VLOOKUP($B15,CEIC_DATA!$I$26:$N$353,Haver_M!BC$2,FALSE),NA()) -> #N/A | BD15: =IF(ISNUMBER(VLOOKUP($B15,CEIC_DATA!$I$26:$N$353,Haver_M!BD$2,FALSE)),VLOOKUP($B15,CEIC_DATA!$I$26:$N$353,Haver_M!BD$2,FALSE),NA()) -> #N/A | BE15: =IF(ISNUMBER(VLOOKUP($B15,CEIC_DATA!$I$26:$N$353,Haver_M!BE$2,FALSE)),VLOOKUP($B15,CEIC_DATA!$I$26:$N$353,Haver_M!BE$2,FALSE),NA()) -> #N/A | BJ15: #N/A | BK15: #N/A | BL15: #N/A | BM15: #N/A | BN15: 3719 | BO15: 4264 | BP15: 46.3445 | BQ15: =IF(ISNUMBER(BJ15),BJ15/$BP15,"") | BR15: =IF(ISNUMBER(BK15),BK15/$BP15,"") | BS15: =IF(ISNUMBER(BL15),BL15/$BP15,"") | BT15: =IF(ISNUMBER(BM15),BM15/$BP15,"") | BU15: 44486
A16: 0011 | B16: 36860 | C16: #N/A | D16: 11.4009 | E16: 95.6523 | F16: #N/A | G16: #N/A | H16: 46.41 | I16: 55.87 | J16: 25.77 | K16: 58.21 | L16: #N/A | M16: 25.4 | N16: 49.36 | O16: #N/A | P16: #N/A | Q16: #N/A | R16: #N/A | S16: #N/A | T16: #N/A | U16: #N/A | V16: #N/A | W16: #N/A | X16: 8274.7941 | Y16: 3789.06 | Z16: 4803.98 | AA16: #N/A | AB16: #N/A | AC16: #N/A | AD16: #N/A | AE16: 82.292219 | AF16: #N/A | AG16: #N/A | AH16: #N/A | AI16: #N/A | AJ16: #N/A | AK16: #N/A | AL16: #N/A | AM16: #N/A | AN16: #N/A | AO16: #N/A | AP16: #N/A | AQ16: #N/A | AR16: #N/A | AS16: #N/A | AT16: #N/A | AU16: #N/A | AV16: #N/A | AW16: #N/A | AX16: #N/A | AY16: #N/A | AZ16: #N/A | BA16: 3928.1 | BB16: =IF(ISNUMBER(VLOOKUP($B16,CEIC_DATA!$I$26:$N$353,Haver_M!BB$2,FALSE)),VLOOKUP($B16,CEIC_DATA!$I$26:$N$353,Haver_M!BB$2,FALSE),NA()) -> 110.53002 | BC16: =IF(ISNUMBER(VLOOKUP($B16,CEIC_DATA!$I$26:$N$353,Haver_M!BC$2,FALSE)),VLOOKUP($B16,CEIC_DATA!$I$26:$N$353,Haver_M!BC$2,FALSE),NA()) -> #N/A | BD16: =IF(ISNUMBER(VLOOKUP($B16,CEIC_DATA!$I$26:$N$353,Haver_M!BD$2,FALSE)),VLOOKUP($B16,CEIC_DATA!$I$26:$N$353,Haver_M!BD$2,FALSE),NA()) -> #N/A | BE16: =IF(ISNUMBER(VLOOKUP($B16,CEIC_DATA!$I$26:$N$353,Haver_M!BE$2,FALSE)),VLOOKUP($B16,CEIC_DATA!$I$26:$N$353,Haver_M!BE$2,FALSE),NA()) -> #N/A | BJ16: #N/A | BK16: #N/A | BL16: #N/A | BM16: #N/A | BN16: 3604 | BO16: 4698 | BP16: 46.7789 | BQ16: =IF(ISNUMBER(BJ16),BJ16/$BP16,"") | BR16: =IF(ISNUMBER(BK16),BK16/$BP16,"") | BS16: =IF(ISNUMBER(BL16),BL16/$BP16,"") | BT16: =IF(ISNUMBER(BM16),BM16/$BP16,"") | BU16: 45510
A17: 0012 | B17: 36891 | C17: #N/A | D17: 10.9359 | E17: 94.82709 | F17: #N/A | G17: #N/A | H17: 46.79 | I17: 55.42 | J17: 27.4 | K17: 58.53 | L17: #N/A | M17: 25.59 | N17: 47.9 | O17: #N/A | P17: #N/A | Q17: #N/A | R17: #N/A | S17: #N/A | T17: #N/A | U17: #N/A | V17: #N/A | W17: #N/A | X17: 8162.7802 | Y17: 3819.91 | Z17: 3973.33 | AA17: #N/A | AB17: #N/A | AC17: #N/A | AD17: #N/A | AE17: 107.32323 | AF17: #N/A | AG17: #N/A | AH17: #N/A | AI17: #N/A | AJ17: #N/A | AK17: #N/A | AL17: #N/A | AM17: #N/A | AN17: #N/A | AO17: #N/A | AP17: #N/A | AQ17: #N/A | AR17: #N/A | AS17: #N/A | AT17: #N/A | AU17: #N/A | AV17: #N/A | AW17: #N/A | AX17: #N/A | AY17: #N/A | AZ17: #N/A | BA17: 4081.42 | BB17: =IF(ISNUMBER(VLOOKUP($B17,CEIC_DATA!$I$26:$N$353,Haver_M!BB$2,FALSE)),VLOOKUP($B17,CEIC_DATA!$I$26:$N$353,Haver_M!BB$2,FALSE),NA()) -> 109.86881 | BC17: =IF(ISNUMBER(VLOOKUP($B17,CEIC_DATA!$I$26:$N$353,Haver_M!BC$2,FALSE)),VLOOKUP($B17,CEIC_DATA!$I$26:$N$353,Haver_M!BC$2,FALSE),NA()) -> 113.9 | BD17: =IF(ISNUMBER(VLOOKUP($B17,CEIC_DATA!$I$26:$N$353,Haver_M!BD$2,FALSE)),VLOOKUP($B17,CEIC_DATA!$I$26:$N$353,Haver_M!BD$2,FALSE),NA()) -> 124.4 | BE17: =IF(ISNUMBER(VLOOKUP($B17,CEIC_DATA!$I$26:$N$353,Haver_M!BE$2,FALSE)),VLOOKUP($B17,CEIC_DATA!$I$26:$N$353,Haver_M!BE$2,FALSE),NA()) -> 51.7 | BJ17: #N/A | BK17: #N/A | BL17: #N/A | BM17: #N/A | BN17: 3657 | BO17: 3976 | BP17: 46.7496 | BQ17: =IF(ISNUMBER(BJ17),BJ17/$BP17,"") | BR17: =IF(ISNUMBER(BK17),BK17/$BP17,"") | BS17: =IF(ISNUMBER(BL17),BL17/$BP17,"") | BT17: =IF(ISNUMBER(BM17),BM17/$BP17,"") | BU17: 45768
A18: 0101 | B18: 36922 | C18: #N/A | D18: 10.4842 | E18: 93.97701 | F18: 46.9 | G18: #N/A | H18: 46.37 | I18: 54.93 | J18: 26.45 | K18: 57.89 | L18: #N/A | M18: 24.5 | N18: 49.62 | O18: #N/A | P18: #N/A | Q18: #N/A | R18: #N/A | S18: #N/A | T18: #N/A | U18: #N/A | V18: #N/A | W18: #N/A | X18: 8410.2443 | Y18: 3649.92 | Z18: 3994.9 | AA18: #N/A | AB18: #N/A | AC18: #N/A | AD18: #N/A | AE18: 103.76458 | AF18: #N/A | AG18: #N/A | AH18: #N/A | AI18: #N/A | AJ18: #N/A | AK18: #N/A | AL18: #N/A | AM18: #N/A | AN18: #N/A | AO18: #N/A | AP18: #N/A | AQ18: #N/A | AR18: #N/A | AS18: #N/A | AT18: #N/A | AU18: #N/A | AV18: #N/A | AW18: #N/A | AX18: #N/A | AY18: #N/A | AZ18: #N/A | BA18: 4152.39 | BB18: =IF(ISNUMBER(VLOOKUP($B18,CEIC_DATA!$I$26:$N$353,Haver_M!BB$2,FALSE)),VLOOKUP($B18,CEIC_DATA!$I$26:$N$353,Haver_M!BB$2,FALSE),NA()) -> 109.07673 | BC18: =IF(ISNUMBER(VLOOKUP($B18,CEIC_DATA!$I$26:$N$353,Haver_M!BC$2,FALSE)),VLOOKUP($B18,CEIC_DATA!$I$26:$N$353,Haver_M!BC$2,FALSE),NA()) -> #N/A | BD18: =IF(ISNUMBER(VLOOKUP($B18,CEIC_DATA!$I$26:$N$353,Haver_M!BD$2,FALSE)),VLOOKUP($B18,CEIC_DATA!$I$26:$N$353,Haver_M!BD$2,FALSE),NA()) -> #N/A | BE18: =IF(ISNUMBER(VLOOKUP($B18,CEIC_DATA!$I$26:$N$353,Haver_M!BE$2,FALSE)),VLOOKUP($B18,CEIC_DATA!$I$26:$N$353,Haver_M!BE$2,FALSE),NA()) -> #N/A | BJ18: #N/A | BK18: #N/A | BL18: #N/A | BM18: #N/A | BN18: 3666 | BO18: 4007 | BP18: 46.5439 | BQ18: =IF(ISNUMBER(BJ18),BJ18/$BP18,"") | BR18: =IF(ISNUMBER(BK18),BK18/$BP18,"") | BS18: =IF(ISNUMBER(BL18),BL18/$BP18,"") | BT18: =IF(ISNUMBER(BM18),BM18/$BP18,"") | BU18: 46558
A19: 0102 | B19: 36950 | C19: #N/A | D19: 10.0447 | E19: 95.06243 | F19: 46.8 | G19: #N/A | H19: 47.15 | I19: 55.3 | J19: 26.5 | K19: 58.86 | L19: #N/A | M19: 26.59 | N19: 50.01 | O19: #N/A | P19: #N/A | Q19: #N/A | R19: #N/A | S19: #N/A | T19: #N/A | U19: #N/A | V19: #N/A | W19: #N/A | X19: 8119.6426 | Y19: 3715.54 | Z19: 3713.63 | AA19: #N/A | AB19: #N/A | AC19: #N/A | AD19: #N/A | AE19: 121.81913 | AF19: #N/A | AG19: #N/A | AH19: #N/A | AI19: #N/A | AJ19: #N/A | AK19: #N/A | AL19: #N/A | AM19: #N/A | AN19: #N/A | AO19: #N/A | AP19: #N/A | AQ19: #N/A | AR19: #N/A | AS19: #N/A | AT19: #N/A | AU19: #N/A | AV19: #N/A | AW19: #N/A | AX19: #N/A | AY19: #N/A | AZ19: #N/A | BA19: 4310.13 | BB19: =IF(ISNUMBER(VLOOKUP($B19,CEIC_DATA!$I$26:$N$353,Haver_M!BB$2,FALSE)),VLOOKUP($B19,CEIC_DATA!$I$26:$N$353,Haver_M!BB$2,FALSE),NA()) -> 108.10665 | BC19: =IF(ISNUMBER(VLOOKUP($B19,CEIC_DATA!$I$26:$N$353,Haver_M!BC$2,FALSE)),VLOOKUP($B19,CEIC_DATA!$I$26:$N$353,Haver_M!BC$2,FALSE),NA()) -> #N/A | BD19: =IF(ISNUMBER(VLOOKUP($B19,CEIC_DATA!$I$26:$N$353,Haver_M!BD$2,FALSE)),VLOOKUP($B19,CEIC_DATA!$I$26:$N$353,Haver_M!BD$2,FALSE),NA()) -> #N/A | BE19: =IF(ISNUMBER(VLOOKUP($B19,CEIC_DATA!$I$26:$N$353,Haver_M!BE$2,FALSE)),VLOOKUP($B19,CEIC_DATA!$I$26:$N$353,Haver_M!BE$2,FALSE),NA()) -> #N/A | BJ19: #N/A | BK19: #N/A | BL19: #N/A | BM19: #N/A | BN19: 3695 | BO19: 3457 | BP19: 46.5167 | BQ19: =IF(ISNUMBER(BJ19),BJ19/$BP19,"") | BR19: =IF(ISNUMBER(BK19),BK19/$BP19,"") | BS19: =IF(ISNUMBER(BL19),BL19/$BP19,"") | BT19: =IF(ISNUMBER(BM19),BM19/$BP19,"") | BU19: 46752
A20: 0103 | B20: 36981 | C20: #N/A | D20: 10.2737 | E20: 96.51569 | F20: 47.1 | G20: #N/A | H20: 46.95 | I20: 55.14 | J20: 25.92 | K20: 60.54 | L20: #N/A | M20: 25.99 | N20: 48.52 | O20: #N/A | P20: #N/A | Q20: #N/A | R20: #N/A | S20: #N/A | T20: #N/A | U20: #N/A | V20: #N/A | W20: #N/A | X20: 8485.7498 | Y20: 3741.73 | Z20: 4323.55 | AA20: #N/A | AB20: #N/A | AC20: #N/A | AD20: #N/A | AE20: 143.45661 | AF20: #N/A | AG20: #N/A | AH20: #N/A | AI20: #N/A | AJ20: #N/A | AK20: #N/A | AL20: #N/A | AM20: #N/A | AN20: #N/A | AO20: #N/A | AP20: #N/A | AQ20: #N/A | AR20: #N/A | AS20: #N/A | AT20: #N/A | AU20: #N/A | AV20: #N/A | AW20: #N/A | AX20: #N/A | AY20: #N/A | AZ20: #N/A | BA20: 3807.64 | BB20: =IF(ISNUMBER(VLOOKUP($B20,CEIC_DATA!$I$26:$N$353,Haver_M!BB$2,FALSE)),VLOOKUP($B20,CEIC_DATA!$I$26:$N$353,Haver_M!BB$2,FALSE),NA()) -> 106.87329 | BC20: =IF(ISNUMBER(VLOOKUP($B20,CEIC_DATA!$I$26:$N$353,Haver_M!BC$2,FALSE)),VLOOKUP($B20,CEIC_DATA!$I$26:$N$353,Haver_M!BC$2,FALSE),NA()) -> 115.2 | BD20: =IF(ISNUMBER(VLOOKUP($B20,CEIC_DATA!$I$26:$N$353,Haver_M!BD$2,FALSE)),VLOOKUP($B20,CEIC_DATA!$I$26:$N$353,Haver_M!BD$2,FALSE),NA()) -> 122.5 | BE20: =IF(ISNUMBER(VLOOKUP($B20,CEIC_DATA!$I$26:$N$353,Haver_M!BE$2,FALSE)),VLOOKUP($B20,CEIC_DATA!$I$26:$N$353,Haver_M!BE$2,FALSE),NA()) -> 49 | BJ20: #N/A | BK20: #N/A | BL20: #N/A | BM20: #N/A | BN20: 4309 | BO20: 4625 | BP20: 46.6205 | BQ20: =IF(ISNUMBER(BJ20),BJ20/$BP20,"") | BR20: =IF(ISNUMBER(BK20),BK20/$BP20,"") | BS20: =IF(ISNUMBER(BL20),BL20/$BP20,"") | BT20: =IF(ISNUMBER(BM20),BM20/$BP20,"") | BU20: 44978
A21: 0104 | B21: 37011 | C21: 8.75 | D21: 10.0779 | E21: 97.44224 | F21: 47.4 | G21: #N/A | H21: 47.04 | I21: 55.86 | J21: 27.95 | K21: 59.6 | L21: #N/A | M21: 26.52 | N21: 47.52 | O21: #N/A | P21: #N/A | Q21: #N/A | R21: #N/A | S21: #N/A | T21: #N/A | U21: #N/A | V21: #N/A | W21: #N/A | X21: 8308.7308 | Y21: 3226.88 | Z21: 4209.42 | AA21: #N/A | AB21: #N/A | AC21: #N/A | AD21: #N/A | AE21: 121.81104 | AF21: #N/A | AG21: #N/A | AH21: #N/A | AI21: #N/A | AJ21: #N/A | AK21: #N/A | AL21: #N/A | AM21: #N/A | AN21: #N/A | AO21: #N/A | AP21: #N/A | AQ21: #N/A | AR21: #N/A | AS21: #N/A | AT21: #N/A | AU21: #N/A | AV21: #N/A | AW21: #N/A | AX21: #N/A | AY21: #N/A | AZ21: #N/A | BA21: 3487.44 | BB21: =IF(ISNUMBER(VLOOKUP($B21,CEIC_DATA!$I$26:$N$353,Haver_M!BB$2,FALSE)),VLOOKUP($B21,CEIC_DATA!$I$26:$N$353,Haver_M!BB$2,FALSE),NA()) -> 105.39878 | BC21: =IF(ISNUMBER(VLOOKUP($B21,CEIC_DATA!$I$26:$N$353,Haver_M!BC$2,FALSE)),VLOOKUP($B21,CEIC_DATA!$I$26:$N$353,Haver_M!BC$2,FALSE),NA()) -> #N/A | BD21: =IF(ISNUMBER(VLOOKUP($B21,CEIC_DATA!$I$26:$N$353,Haver_M!BD$2,FALSE)),VLOOKUP($B21,CEIC_DATA!$I$26:$N$353,Haver_M!BD$2,FALSE),NA()) -> #N/A | BE21: =IF(ISNUMBER(VLOOKUP($B21,CEIC_DATA!$I$26:$N$353,Haver_M!BE$2,FALSE)),VLOOKUP($B21,CEIC_DATA!$I$26:$N$353,Haver_M!BE$2,FALSE),NA()) -> #N/A | BJ21: #N/A | BK21: #N/A | BL21: #N/A | BM21: #N/A | BN21: 3115 | BO21: 4094 | BP21: 46.7835 | BQ21: =IF(ISNUMBER(BJ21),BJ21/$BP21,"") | BR21: =IF(ISNUMBER(BK21),BK21/$BP21,"") | BS21: =IF(ISNUMBER(BL21),BL21/$BP21,"") | BT21: =IF(ISNUMBER(BM21),BM21/$BP21,"") | BU21: 52444
A22: 0105 | B22: 37042 | C22: 8.75 | D22: 9.7149 | E22: 97.51621 | F22: 47.8 | G22: #N/A | H22: 46.86 | I22: 55.5 | J22: 26.1 | K22: 59.65 | L22: #N/A | M22: 27.44 | N22: 46.95 | O22: #N/A | P22: #N/A | Q22: #N/A | R22: #N/A | S22: #N/A | T22: #N/A | U22: #N/A | V22: #N/A | W22: #N/A | X22: 8356.4908 | Y22: 3687.82 | Z22: 4455.23 | AA22: #N/A | AB22: #N/A | AC22: #N/A | AD22: #N/A | AE22: 88.793829 | AF22: #N/A | AG22: #N/A | AH22: #N/A | AI22: #N/A | AJ22: #N/A | AK22: #N/A | AL22: #N/A | AM22: #N/A | AN22: #N/A | AO22: #N/A | AP22: #N/A | AQ22: #N/A | AR22: #N/A | AS22: #N/A | AT22: #N/A | AU22: #N/A | AV22: #N/A | AW22: #N/A | AX22: #N/A | AY22: #N/A | AZ22: #N/A | BA22: 3613.84 | BB22: =IF(ISNUMBER(VLOOKUP($B22,CEIC_DATA!$I$26:$N$353,Haver_M!BB$2,FALSE)),VLOOKUP($B22,CEIC_DATA!$I$26:$N$353,Haver_M!BB$2,FALSE),NA()) -> 103.67671 | BC22: =IF(ISNUMBER(VLOOKUP($B22,CEIC_DATA!$I$26:$N$353,Haver_M!BC$2,FALSE)),VLOOKUP($B22,CEIC_DATA!$I$26:$N$353,Haver_M!BC$2,FALSE),NA()) -> #N/A | BD22: =IF(ISNUMBER(VLOOKUP($B22,CEIC_DATA!$I$26:$N$353,Haver_M!BD$2,FALSE)),VLOOKUP($B22,CEIC_DATA!$I$26:$N$353,Haver_M!BD$2,FALSE),NA()) -> #N/A | BE22: =IF(ISNUMBER(VLOOKUP($B22,CEIC_DATA!$I$26:$N$353,Haver_M!BE$2,FALSE)),VLOOKUP($B22,CEIC_DATA!$I$26:$N$353,Haver_M!BE$2,FALSE),NA()) -> #N/A | BF22: 337038 | BG22: 9137 | BH22: 423736 | BI22: 61818 | BJ22: #N/A | BK22: #N/A | BL22: #N/A | BM22: #N/A | BN22: 3629 | BO22: 4674 | BP22: 46.9202 | BQ22: =IF(ISNUMBER(BJ22),BJ22/$BP22,"") | BR22: =IF(ISNUMBER(BK22),BK22/$BP22,"") | BS22: =IF(ISNUMBER(BL22),BL22/$BP22,"") | BT22: =IF(ISNUMBER(BM22),BM22/$BP22,"") | BU22: 60701
A23: 0106 | B23: 37072 | C23: 8.5 | D23: 9.4551 | E23: 98.84518 | F23: 48.3 | G23: #N/A | H23: 47.17 | I23: 55.4 | J23: 24.9 | K23: 59.36 | L23: #N/A | M23: 27.78 | N23: 50.49 | O23: #N/A | P23: #N/A | Q23: #N/A | R23: #N/A | S23: #N/A | T23: #N/A | U23: #N/A | V23: #N/A | W23: #N/A | X23: 8609.3938 | Y23: 3782.77 | Z23: 4247.93 | AA23: #N/A | AB23: #N/A | AC23: #N/A | AD23: #N/A | AE23: 88.922303 | AF23: #N/A | AG23: #N/A | AH23: #N/A | AI23: #N/A | AJ23: #N/A | AK23: #N/A | AL23: #N/A | AM23: #N/A | AN23: #N/A | AO23: #N/A | AP23: #N/A | AQ23: #N/A | AR23: #N/A | AS23: #N/A | AT23: #N/A | AU23: #N/A | AV23: #N/A | AW23: #N/A | AX23: #N/A | AY23: #N/A | AZ23: #N/A | BA23: 3439.01 | BB23: =IF(ISNUMBER(VLOOKUP($B23,CEIC_DATA!$I$26:$N$353,Haver_M!BB$2,FALSE)),VLOOKUP($B23,CEIC_DATA!$I$26:$N$353,Haver_M!BB$2,FALSE),NA()) -> 101.57751 | BC23: =IF(ISNUMBER(VLOOKUP($B23,CEIC_DATA!$I$26:$N$353,Haver_M!BC$2,FALSE)),VLOOKUP($B23,CEIC_DATA!$I$26:$N$353,Haver_M!BC$2,FALSE),NA()) -> 109.9 | BD23: =IF(ISNUMBER(VLOOKUP($B23,CEIC_DATA!$I$26:$N$353,Haver_M!BD$2,FALSE)),VLOOKUP($B23,CEIC_DATA!$I$26:$N$353,Haver_M!BD$2,FALSE),NA()) -> 120.7 | BE23: =IF(ISNUMBER(VLOOKUP($B23,CEIC_DATA!$I$26:$N$353,Haver_M!BE$2,FALSE)),VLOOKUP($B23,CEIC_DATA!$I$26:$N$353,Haver_M!BE$2,FALSE),NA()) -> 43.7 | BF23: 326699 | BG23: 12262 | BH23: 412217 | BI23: 55946 | BJ23: #N/A | BK23: #N/A | BL23: #N/A | BM23: #N/A | BN23: 3612 | BO23: 4017 | BP23: 47.0038 | BQ23: =IF(ISNUMBER(BJ23),BJ23/$BP23,"") | BR23: =IF(ISNUMBER(BK23),BK23/$BP23,"") | BS23: =IF(ISNUMBER(BL23),BL23/$BP23,"") | BT23: =IF(ISNUMBER(BM23),BM23/$BP23,"") | BU23: 61958
A24: 0107 | B24: 37103 | C24: 8.5 | D24: 9.2609 | E24: 99.14074 | F24: 48.8 | G24: #N/A | H24: 46.86 | I24: 55.32 | J24: 25.39 | K24: 58.94 | L24: #N/A | M24: 29.17 | N24: 47.11 | O24: #N/A | P24: #N/A | Q24: #N/A | R24: #N/A | S24: #N/A | T24: #N/A | U24: #N/A | V24: #N/A | W24: #N/A | X24: 7897.0122 | Y24: 3456.32 | Z24: 4765.93 | AA24: #N/A | AB24: #N/A | AC24: #N/A | AD24: #N/A | AE24: 115.32456 | AF24: #N/A | AG24: #N/A | AH24: #N/A | AI24: #N/A | AJ24: #N/A | AK24: #N/A | AL24: #N/A | AM24: #N/A | AN24: #N/A | AO24: #N/A | AP24: #N/A | AQ24: #N/A | AR24: #N/A | AS24: #N/A | AT24: #N/A | AU24: #N/A | AV24: #N/A | AW24: #N/A | AX24: #N/A | AY24: #N/A | AZ24: #N/A | BA24: 3346.88 | BB24: =IF(ISNUMBER(VLOOKUP($B24,CEIC_DATA!$I$26:$N$353,Haver_M!BB$2,FALSE)),VLOOKUP($B24,CEIC_DATA!$I$26:$N$353,Haver_M!BB$2,FALSE),NA()) -> 99.306173 | BC24: =IF(ISNUMBER(VLOOKUP($B24,CEIC_DATA!$I$26:$N$353,Haver_M!BC$2,FALSE)),VLOOKUP($B24,CEIC_DATA!$I$26:$N$353,Haver_M!BC$2,FALSE),NA()) -> #N/A | BD24: =IF(ISNUMBER(VLOOKUP($B24,CEIC_DATA!$I$26:$N$353,Haver_M!BD$2,FALSE)),VLOOKUP($B24,CEIC_DATA!$I$26:$N$353,Haver_M!BD$2,FALSE),NA()) -> #N/A | BE24: =IF(ISNUMBER(VLOOKUP($B24,CEIC_DATA!$I$26:$N$353,Haver_M!BE$2,FALSE)),VLOOKUP($B24,CEIC_DATA!$I$26:$N$353,Haver_M!BE$2,FALSE),NA()) -> #N/A | BF24: 326878 | BG24: 10660 | BH24: 414085 | BI24: 57654 | BJ24: #N/A | BK24: #N/A | BL24: #N/A | BM24: #N/A | BN24: 3433 | BO24: 4923 | BP24: 47.1393 | BQ24: =IF(ISNUMBER(BJ24),BJ24/$BP24,"") | BR24: =IF(ISNUMBER(BK24),BK24/$BP24,"") | BS24: =IF(ISNUMBER(BL24),BL24/$BP24,"") | BT24: =IF(ISNUMBER(BM24),BM24/$BP24,"") | BU24: 61008
A25: 0108 | B25: 37134 | C25: 8.5 | D25: 9.1394 | E25: 97.71676 | F25: 49.2 | G25: #N/A | H25: 47.28 | I25: 56.84 | J25: 25.28 | K25: 58.79 | L25: #N/A | M25: 28.98 | N25: 48.38 | O25: #N/A | P25: #N/A | Q25: #N/A | R25: #N/A | S25: #N/A | T25: #N/A | U25: #N/A | V25: #N/A | W25: #N/A | X25: 8479.202 | Y25: 3656.43 | Z25: 4430.63 | AA25: #N/A | AB25: #N/A | AC25: #N/A | AD25: #N/A | AE25: 89.27407 | AF25: #N/A | AG25: #N/A | AH25: #N/A | AI25: #N/A | AJ25: #N/A | AK25: #N/A | AL25: #N/A | AM25: #N/A | AN25: #N/A | AO25: #N/A | AP25: #N/A | AQ25: #N/A | AR25: #N/A | AS25: #N/A | AT25: #N/A | AU25: #N/A | AV25: #N/A | AW25: #N/A | AX25: #N/A | AY25: #N/A | AZ25: #N/A | BA25: 3304.99 | BB25: =IF(ISNUMBER(VLOOKUP($B25,CEIC_DATA!$I$26:$N$353,Haver_M!BB$2,FALSE)),VLOOKUP($B25,CEIC_DATA!$I$26:$N$353,Haver_M!BB$2,FALSE),NA()) -> 97.069076 | BC25: =IF(ISNUMBER(VLOOKUP($B25,CEIC_DATA!$I$26:$N$353,Haver_M!BC$2,FALSE)),VLOOKUP($B25,CEIC_DATA!$I$26:$N$353,Haver_M!BC$2,FALSE),NA()) -> #N/A | BD25: =IF(ISNUMBER(VLOOKUP($B25,CEIC_DATA!$I$26:$N$353,Haver_M!BD$2,FALSE)),VLOOKUP($B25,CEIC_DATA!$I$26:$N$353,Haver_M!BD$2,FALSE),NA()) -> #N/A | BE25: =IF(ISNUMBER(VLOOKUP($B25,CEIC_DATA!$I$26:$N$353,Haver_M!BE$2,FALSE)),VLOOKUP($B25,CEIC_DATA!$I$26:$N$353,Haver_M!BE$2,FALSE),NA()) -> #N/A | BF25: 333685 | BG25: 12879 | BH25: 427949 | BI25: 61861 | BJ25: #N/A | BK25: #N/A | BL25: #N/A | BM25: #N/A | BN25: 3647 | BO25: 4372 | BP25: 47.1265 | BQ25: =IF(ISNUMBER(BJ25),BJ25/$BP25,"") | BR25: =IF(ISNUMBER(BK25),BK25/$BP25,"") | BS25: =IF(ISNUMBER(BL25),BL25/$BP25,"") | BT25: =IF(ISNUMBER(BM25),BM25/$BP25,"") | BU25: 59458
A26: 0109 | B26: 37164 | C26: 8.5 | D26: 9.1468 | E26: 96.22923 | F26: 49 | G26: #N/A | H26: 47.45 | I26: 58.18 | J26: 25.16 | K26: 59.67 | L26: #N/A | M26: 29.32 | N26: 45.08 | O26: #N/A | P26: #N/A | Q26: #N/A | R26: #N/A | S26: #N/A | T26: #N/A | U26: #N/A | V26: #N/A | W26: #N/A | X26: 8718.1143 | Y26: 3598.84 | Z26: 3848.47 | AA26: #N/A | AB26: #N/A | AC26: #N/A | AD26: #N/A | AE26: 125.07716 | AF26: #N/A | AG26: #N/A | AH26: #N/A | AI26: #N/A | AJ26: #N/A | AK26: #N/A | AL26: #N/A | AM26: #N/A | AN26: #N/A | AO26: #N/A | AP26: #N/A | AQ26: #N/A | AR26: #N/A | AS26: #N/A | AT26: #N/A | AU26: #N/A | AV26: #N/A | AW26: #N/A | AX26: #N/A | AY26: #N/A | AZ26: #N/A | BA26: 2918.28 | BB26: =IF(ISNUMBER(VLOOKUP($B26,CEIC_DATA!$I$26:$N$353,Haver_M!BB$2,FALSE)),VLOOKUP($B26,CEIC_DATA!$I$26:$N$353,Haver_M!BB$2,FALSE),NA()) -> 95.09125 | BC26: =IF(ISNUMBER(VLOOKUP($B26,CEIC_DATA!$I$26:$N$353,Haver_M!BC$2,FALSE)),VLOOKUP($B26,CEIC_DATA!$I$26:$N$353,Haver_M!BC$2,FALSE),NA()) -> 108.7 | BD26: =IF(ISNUMBER(VLOOKUP($B26,CEIC_DATA!$I$26:$N$353,Haver_M!BD$2,FALSE)),VLOOKUP($B26,CEIC_DATA!$I$26:$N$353,Haver_M!BD$2,FALSE),NA()) -> 118.9 | BE26: =IF(ISNUMBER(VLOOKUP($B26,CEIC_DATA!$I$26:$N$353,Haver_M!BE$2,FALSE)),VLOOKUP($B26,CEIC_DATA!$I$26:$N$353,Haver_M!BE$2,FALSE),NA()) -> 39.7 | BF26: 363861 | BG26: 14317 | BH26: 456341 | BI26: 59498 | BJ26: #N/A | BK26: #N/A | BL26: #N/A | BM26: #N/A | BN26: 3702 | BO26: 3902 | BP26: 47.642 | BQ26: =IF(ISNUMBER(BJ26),BJ26/$BP26,"") | BR26: =IF(ISNUMBER(BK26),BK26/$BP26,"") | BS26: =IF(ISNUMBER(BL26),BL26/$BP26,"") | BT26: =IF(ISNUMBER(BM26),BM26/$BP26,"") | BU26: 58280
A27: 0110 | B27: 37195 | C27: 8.5 | D27: 8.7893 | E27: 97.51282 | F27: 49.5 | G27: #N/A | H27: 47.3 | I27: 57.01 | J27: 25.86 | K27: 57.67 | L27: #N/A | M27: 28.64 | N27: 48.45 | O27: #N/A | P27: #N/A | Q27: #N/A | R27: #N/A | S27: #N/A | T27: #N/A | U27: #N/A | V27: #N/A | W27: #N/A | X27: 8342.8517 | Y27: 3648.16 | Z27: 3987.97 | AA27: #N/A | AB27: #N/A | AC27: #N/A | AD27: #N/A | AE27: 90.841404 | AF27: #N/A | AG27: #N/A | AH27: #N/A | AI27: #N/A | AJ27: #N/A | AK27: #N/A | AL27: #N/A | AM27: #N/A | AN27: #N/A | AO27: #N/A | AP27: #N/A | AQ27: #N/A | AR27: #N/A | AS27: #N/A | AT27: #N/A | AU27: #N/A | AV27: #N/A | AW27: #N/A | AX27: #N/A | AY27: #N/A | AZ27: #N/A | BA27: 2933.55 | BB27: =IF(ISNUMBER(VLOOKUP($B27,CEIC_DATA!$I$26:$N$353,Haver_M!BB$2,FALSE)),VLOOKUP($B27,CEIC_DATA!$I$26:$N$353,Haver_M!BB$2,FALSE),NA()) -> 93.647759 | BC27: =IF(ISNUMBER(VLOOKUP($B27,CEIC_DATA!$I$26:$N$353,Haver_M!BC$2,FALSE)),VLOOKUP($B27,CEIC_DATA!$I$26:$N$353,Haver_M!BC$2,FALSE),NA()) -> #N/A | BD27: =IF(ISNUMBER(VLOOKUP($B27,CEIC_DATA!$I$26:$N$353,Haver_M!BD$2,FALSE)),VLOOKUP($B27,CEIC_DATA!$I$26:$N$353,Haver_M!BD$2,FALSE),NA()) -> #N/A | BE27: =IF(ISNUMBER(VLOOKUP($B27,CEIC_DATA!$I$26:$N$353,Haver_M!BE$2,FALSE)),VLOOKUP($B27,CEIC_DATA!$I$26:$N$353,Haver_M!BE$2,FALSE),NA()) -> #N/A | BF27: 412952 | BG27: 12982 | BH27: 497907 | BI27: 52195 | BJ27: #N/A | BK27: #N/A | BL27: #N/A | BM27: #N/A | BN27: 3718 | BO27: 4093 | BP27: 48.0198 | BQ27: =IF(ISNUMBER(BJ27),BJ27/$BP27,"") | BR27: =IF(ISNUMBER(BK27),BK27/$BP27,"") | BS27: =IF(ISNUMBER(BL27),BL27/$BP27,"") | BT27: =IF(ISNUMBER(BM27),BM27/$BP27,"") | BU27: 62302
A28: 0111 | B28: 37225 | C28: 8.5 | D28: 7.9239 | E28: 98.42142 | F28: 49.9 | G28: #N/A | H28: 48.28 | I28: 57.59 | J28: 26.81 | K28: 59.24 | L28: #N/A | M28: 27.83 | N28: 53.35 | O28: #N/A | P28: #N/A | Q28: #N/A | R28: #N/A | S28: #N/A | T28: #N/A | U28: #N/A | V28: #N/A | W28: #N/A | X28: 8378.7635 | Y28: 3782.36 | Z28: 4251.75 | AA28: #N/A | AB28: #N/A | AC28: #N/A | AD28: #N/A | AE28: 109.01473 | AF28: #N/A | AG28: #N/A | AH28: #N/A | AI28: #N/A | AJ28: #N/A | AK28: #N/A | AL28: #N/A | AM28: #N/A | AN28: #N/A | AO28: #N/A | AP28: #N/A | AQ28: #N/A | AR28: #N/A | AS28: #N/A | AT28: #N/A | AU28: #N/A | AV28: #N/A | AW28: #N/A | AX28: #N/A | AY28: #N/A | AZ28: #N/A | BA28: 3164.25 | BB28: =IF(ISNUMBER(VLOOKUP($B28,CEIC_DATA!$I$26:$N$353,Haver_M!BB$2,FALSE)),VLOOKUP($B28,CEIC_DATA!$I$26:$N$353,Haver_M!BB$2,FALSE),NA()) -> 93.0552 | BC28: =IF(ISNUMBER(VLOOKUP($B28,CEIC_DATA!$I$26:$N$353,Haver_M!BC$2,FALSE)),VLOOKUP($B28,CEIC_DATA!$I$26:$N$353,Haver_M!BC$2,FALSE),NA()) -> #N/A | BD28: =IF(ISNUMBER(VLOOKUP($B28,CEIC_DATA!$I$26:$N$353,Haver_M!BD$2,FALSE)),VLOOKUP($B28,CEIC_DATA!$I$26:$N$353,Haver_M!BD$2,FALSE),NA()) -> #N/A | BE28: =IF(ISNUMBER(VLOOKUP($B28,CEIC_DATA!$I$26:$N$353,Haver_M!BE$2,FALSE)),VLOOKUP($B28,CEIC_DATA!$I$26:$N$353,Haver_M!BE$2,FALSE),NA()) -> #N/A | BF28: 388194 | BG28: 12691 | BH28: 473105 | BI28: 54957 | BJ28: #N/A | BK28: #N/A | BL28: #N/A | BM28: #N/A | BN28: 3576 | BO28: 4158 | BP28: 47.9947 | BQ28: =IF(ISNUMBER(BJ28),BJ28/$BP28,"") | BR28: =IF(ISNUMBER(BK28),BK28/$BP28,"") | BS28: =IF(ISNUMBER(BL28),BL28/$BP28,"") | BT28: =IF(ISNUMBER(BM28),BM28/$BP28,"") | BU28: 59150
A29: 0112 | B29: 37256 | C29: 8.5 | D29: 8.2666 | E29: 99.12557 | F29: 49.7 | G29: #N/A | H29: 48.15 | I29: 57.2 | J29: 25.9 | K29: 59.14 | L29: #N/A | M29: 27.57 | N29: 51.56 | O29: #N/A | P29: #N/A | Q29: #N/A | R29: #N/A | S29: #N/A | T29: #N/A | U29: #N/A | V29: #N/A | W29: #N/A | X29: 8324.8962 | Y29: 3418.02 | Z29: 4108.9 | AA29: #N/A | AB29: #N/A | AC29: #N/A | AD29: #N/A | AE29: 92.307133 | AF29: #N/A | AG29: #N/A | AH29: #N/A | AI29: #N/A | AJ29: #N/A | AK29: #N/A | AL29: #N/A | AM29: #N/A | AN29: #N/A | AO29: #N/A | AP29: #N/A | AQ29: #N/A | AR29: #N/A | AS29: #N/A | AT29: #N/A | AU29: #N/A | AV29: #N/A | AW29: #N/A | AX29: #N/A | AY29: #N/A | AZ29: #N/A | BA29: 3314.88 | BB29: =IF(ISNUMBER(VLOOKUP($B29,CEIC_DATA!$I$26:$N$353,Haver_M!BB$2,FALSE)),VLOOKUP($B29,CEIC_DATA!$I$26:$N$353,Haver_M!BB$2,FALSE),NA()) -> 93.110436 | BC29: =IF(ISNUMBER(VLOOKUP($B29,CEIC_DATA!$I$26:$N$353,Haver_M!BC$2,FALSE)),VLOOKUP($B29,CEIC_DATA!$I$26:$N$353,Haver_M!BC$2,FALSE),NA()) -> 100.7 | BD29: =IF(ISNUMBER(VLOOKUP($B29,CEIC_DATA!$I$26:$N$353,Haver_M!BD$2,FALSE)),VLOOKUP($B29,CEIC_DATA!$I$26:$N$353,Haver_M!BD$2,FALSE),NA()) -> 119.5 | BE29: =IF(ISNUMBER(VLOOKUP($B29,CEIC_DATA!$I$26:$N$353,Haver_M!BE$2,FALSE)),VLOOKUP($B29,CEIC_DATA!$I$26:$N$353,Haver_M!BE$2,FALSE),NA()) -> 42.9 | BF29: 355262 | BG29: 12643 | BH29: 435699 | BI29: 50374 | BJ29: #N/A | BK29: #N/A | BL29: #N/A | BM29: #N/A | BN29: 3250 | BO29: 4079 | BP29: 47.9176 | BQ29: =IF(ISNUMBER(BJ29),BJ29/$BP29,"") | BR29: =IF(ISNUMBER(BK29),BK29/$BP29,"") | BS29: =IF(ISNUMBER(BL29),BL29/$BP29,"") | BT29: =IF(ISNUMBER(BM29),BM29/$BP29,"") | BU29: 58112
A30: 0201 | B30: 37287 | C30: 8.5 | D30: 7.6474 | E30: 98.43303 | F30: 49.5 | G30: #N/A | H30: 48.15 | I30: 57.31 | J30: 25.77 | K30: 59.01 | L30: #N/A | M30: 28.3 | N30: 51.69 | O30: #N/A | P30: #N/A | Q30: #N/A | R30: #N/A | S30: #N/A | T30: #N/A | U30: #N/A | V30: #N/A | W30: #N/A | X30: 8351.6856 | Y30: 4201.29 | Z30: 4221.94 | AA30: #N/A | AB30: #N/A | AC30: #N/A | AD30: #N/A | AE30: 104.03095 | AF30: #N/A | AG30: #N/A | AH30: #N/A | AI30: #N/A | AJ30: #N/A | AK30: #N/A | AL30: #N/A | AM30: #N/A | AN30: #N/A | AO30: #N/A | AP30: #N/A | AQ30: #N/A | AR30: #N/A | AS30: #N/A | AT30: #N/A | AU30: #N/A | AV30: #N/A | AW30: #N/A | AX30: #N/A | AY30: #N/A | AZ30: #N/A | BA30: 3353.31 | BB30: =IF(ISNUMBER(VLOOKUP($B30,CEIC_DATA!$I$26:$N$353,Haver_M!BB$2,FALSE)),VLOOKUP($B30,CEIC_DATA!$I$26:$N$353,Haver_M!BB$2,FALSE),NA()) -> 93.477945 | BC30: =IF(ISNUMBER(VLOOKUP($B30,CEIC_DATA!$I$26:$N$353,Haver_M!BC$2,FALSE)),VLOOKUP($B30,CEIC_DATA!$I$26:$N$353,Haver_M!BC$2,FALSE),NA()) -> #N/A | BD30: =IF(ISNUMBER(VLOOKUP($B30,CEIC_DATA!$I$26:$N$353,Haver_M!BD$2,FALSE)),VLOOKUP($B30,CEIC_DATA!$I$26:$N$353,Haver_M!BD$2,FALSE),NA()) -> #N/A | BE30: =IF(ISNUMBER(VLOOKUP($B30,CEIC_DATA!$I$26:$N$353,Haver_M!BE$2,FALSE)),VLOOKUP($B30,CEIC_DATA!$I$26:$N$353,Haver_M!BE$2,FALSE),NA()) -> #N/A | BF30: 391060 | BG30: 14987 | BH30: 493693 | BI30: 68609 | BJ30: #N/A | BK30: #N/A | BL30: #N/A | BM30: #N/A | BN30: 4253 | BO30: 4243 | BP30: 48.3287 | BQ30: =IF(ISNUMBER(BJ30),BJ30/$BP30,"") | BR30: =IF(ISNUMBER(BK30),BK30/$BP30,"") | BS30: =IF(ISNUMBER(BL30),BL30/$BP30,"") | BT30: =IF(ISNUMBER(BM30),BM30/$BP30,"") | BU30: 56426
A31: 0202 | B31: 37315 | C31: 8.5 | D31: 7.4725 | E31: 98.15047 | F31: 49.4 | G31: #N/A | H31: 48.46 | I31: 57.37 | J31: 26.9 | K31: 59.81 | L31: #N/A | M31: 28.53 | N31: 51.58 | O31: #N/A | P31: #N/A | Q31: #N/A | R31: #N/A | S31: #N/A | T31: #N/A | U31: #N/A | V31: #N/A | W31: #N/A | X31: 8216.0009 | Y31: 3569.87 | Z31: 4104.46 | AA31: #N/A | AB31: #N/A | AC31: #N/A | AD31: #N/A | AE31: 103.68668 | AF31: #N/A | AG31: #N/A | AH31: #N/A | AI31: #N/A | AJ31: #N/A | AK31: #N/A | AL31: #N/A | AM31: #N/A | AN31: #N/A | AO31: #N/A | AP31: #N/A | AQ31: #N/A | AR31: #N/A | AS31: #N/A | AT31: #N/A | AU31: #N/A | AV31: #N/A | AW31: #N/A | AX31: #N/A | AY31: #N/A | AZ31: #N/A | BA31: 3528.58 | BB31: =IF(ISNUMBER(VLOOKUP($B31,CEIC_DATA!$I$26:$N$353,Haver_M!BB$2,FALSE)),VLOOKUP($B31,CEIC_DATA!$I$26:$N$353,Haver_M!BB$2,FALSE),NA()) -> 93.8853 | BC31: =IF(ISNUMBER(VLOOKUP($B31,CEIC_DATA!$I$26:$N$353,Haver_M!BC$2,FALSE)),VLOOKUP($B31,CEIC_DATA!$I$26:$N$353,Haver_M!BC$2,FALSE),NA()) -> #N/A | BD31: =IF(ISNUMBER(VLOOKUP($B31,CEIC_DATA!$I$26:$N$353,Haver_M!BD$2,FALSE)),VLOOKUP($B31,CEIC_DATA!$I$26:$N$353,Haver_M!BD$2,FALSE),NA()) -> #N/A | BE31: =IF(ISNUMBER(VLOOKUP($B31,CEIC_DATA!$I$26:$N$353,Haver_M!BE$2,FALSE)),VLOOKUP($B31,CEIC_DATA!$I$26:$N$353,Haver_M!BE$2,FALSE),NA()) -> #N/A | BF31: 373003 | BG31: 15080 | BH31: 472336 | BI31: 65627 | BJ31: #N/A | BK31: #N/A | BL31: #N/A | BM31: #N/A | BN31: 3535 | BO31: 3759 | BP31: 48.6893 | BQ31: =IF(ISNUMBER(BJ31),BJ31/$BP31,"") | BR31: =IF(ISNUMBER(BK31),BK31/$BP31,"") | BS31: =IF(ISNUMBER(BL31),BL31/$BP31,"") | BT31: =IF(ISNUMBER(BM31),BM31/$BP31,"") | BU31: 54524
A32: 0203 | B32: 37346 | C32: 8 | D32: 7.3437 | E32: 97.70782 | F32: 49.8 | G32: #N/A | H32: 48.59 | I32: 57.44 | J32: 27.22 | K32: 58.66 | L32: #N/A | M32: 28.32 | N32: 52.87 | O32: #N/A | P32: #N/A | Q32: #N/A | R32: #N/A | S32: #N/A | T32: #N/A | U32: #N/A | V32: #N/A | W32: #N/A | X32: 8430.5678 | Y32: 3548.09 | Z32: 4129.8 | AA32: #N/A | AB32: #N/A | AC32: #N/A | AD32: #N/A | AE32: 75.320646 | AF32: #N/A | AG32: #N/A | AH32: #N/A | AI32: #N/A | AJ32: #N/A | AK32: #N/A | AL32: #N/A | AM32: #N/A | AN32: #N/A | AO32: #N/A | AP32: #N/A | AQ32: #N/A | AR32: #N/A | AS32: #N/A | AT32: #N/A | AU32: #N/A | AV32: #N/A | AW32: #N/A | AX32: #N/A | AY32: #N/A | AZ32: #N/A | BA32: 3580.73 | BB32: =IF(ISNUMBER(VLOOKUP($B32,CEIC_DATA!$I$26:$N$353,Haver_M!BB$2,FALSE)),VLOOKUP($B32,CEIC_DATA!$I$26:$N$353,Haver_M!BB$2,FALSE),NA()) -> 94.096981 | BC32: =IF(ISNUMBER(VLOOKUP($B32,CEIC_DATA!$I$26:$N$353,Haver_M!BC$2,FALSE)),VLOOKUP($B32,CEIC_DATA!$I$26:$N$353,Haver_M!BC$2,FALSE),NA()) -> 108.4 | BD32: =IF(ISNUMBER(VLOOKUP($B32,CEIC_DATA!$I$26:$N$353,Haver_M!BD$2,FALSE)),VLOOKUP($B32,CEIC_DATA!$I$26:$N$353,Haver_M!BD$2,FALSE),NA()) -> 105.3 | BE32: =IF(ISNUMBER(VLOOKUP($B32,CEIC_DATA!$I$26:$N$353,Haver_M!BE$2,FALSE)),VLOOKUP($B32,CEIC_DATA!$I$26:$N$353,Haver_M!BE$2,FALSE),NA()) -> 28.5 | BF32: 401274 | BG32: 21893 | BH32: 529126 | BI32: 84668 | BJ32: #N/A | BK32: #N/A | BL32: #N/A | BM32: #N/A | BN32: 4141 | BO32: 4433 | BP32: 48.7371 | BQ32: =IF(ISNUMBER(BJ32),BJ32/$BP32,"") | BR32: =IF(ISNUMBER(BK32),BK32/$BP32,"") | BS32: =IF(ISNUMBER(BL32),BL32/$BP32,"") | BT32: =IF(ISNUMBER(BM32),BM32/$BP32,"") | BU32: 51023
A33: 0204 | B33: 37376 | C33: 8 | D33: 7.3952 | E33: 96.44598 | F33: 50 | G33: #N/A | H33: 49.07 | I33: 58.21 | J33: 27.71 | K33: 60.01 | L33: #N/A | M33: 27.56 | N33: 53 | O33: #N/A | P33: #N/A | Q33: #N/A | R33: #N/A | S33: #N/A | T33: #N/A | U33: #N/A | V33: #N/A | W33: #N/A | X33: 8637.3255 | Y33: 4196.67 | Z33: 4324.17 | AA33: #N/A | AB33: #N/A | AC33: #N/A | AD33: #N/A | AE33: 69.959349 | AF33: #N/A | AG33: #N/A | AH33: #N/A | AI33: #N/A | AJ33: #N/A | AK33: #N/A | AL33: #N/A | AM33: #N/A | AN33: #N/A | AO33: #N/A | AP33: #N/A | AQ33: #N/A | AR33: #N/A | AS33: #N/A | AT33: #N/A | AU33: #N/A | AV33: #N/A | AW33: #N/A | AX33: #N/A | AY33: #N/A | AZ33: #N/A | BA33: 3435.13 | BB33: =IF(ISNUMBER(VLOOKUP($B33,CEIC_DATA!$I$26:$N$353,Haver_M!BB$2,FALSE)),VLOOKUP($B33,CEIC_DATA!$I$26:$N$353,Haver_M!BB$2,FALSE),NA()) -> 93.985893 | BC33: =IF(ISNUMBER(VLOOKUP($B33,CEIC_DATA!$I$26:$N$353,Haver_M!BC$2,FALSE)),VLOOKUP($B33,CEIC_DATA!$I$26:$N$353,Haver_M!BC$2,FALSE),NA()) -> #N/A | BD33: =IF(ISNUMBER(VLOOKUP($B33,CEIC_DATA!$I$26:$N$353,Haver_M!BD$2,FALSE)),VLOOKUP($B33,CEIC_DATA!$I$26:$N$353,Haver_M!BD$2,FALSE),NA()) -> #N/A | BE33: =IF(ISNUMBER(VLOOKUP($B33,CEIC_DATA!$I$26:$N$353,Haver_M!BE$2,FALSE)),VLOOKUP($B33,CEIC_DATA!$I$26:$N$353,Haver_M!BE$2,FALSE),NA()) -> #N/A | BF33: 394382 | BG33: 11965 | BH33: 473400 | BI33: 48351 | BJ33: #N/A | BK33: #N/A | BL33: #N/A | BM33: #N/A | BN33: 4035 | BO33: 4207 | BP33: 48.9183 | BQ33: =IF(ISNUMBER(BJ33),BJ33/$BP33,"") | BR33: =IF(ISNUMBER(BK33),BK33/$BP33,"") | BS33: =IF(ISNUMBER(BL33),BL33/$BP33,"") | BT33: =IF(ISNUMBER(BM33),BM33/$BP33,"") | BU33: 62547
... A56: 0403 | B56: 38077 | C56: 6 | D56: 5.1542 | E56: 95.01288 | F56: 54 | G56: #N/A | H56: 55.09 | I56: 63.75 | J56: 36.36 | K56: 66.21 | L56: #N/A | M56: 31.37 | N56: 59.67 | O56: #N/A | P56: #N/A | Q56: #N/A | R56: #N/A | S56: #N/A | T56: #N/A | U56: #N/A | V56: #N/A | W56: #N/A | X56: 9375.2288 | Y56: 6560.68 | Z56: 7564.6 | AA56: #N/A | AB56: #N/A | AC56: #N/A | AD56: #N/A | AE56: 27.892834 | AF56: #N/A | AG56: #N/A | AH56: #N/A | AI56: #N/A | AJ56: #N/A | AK56: #N/A | AL56: #N/A | AM56: #N/A | AN56: #N/A | AO56: #N/A | AP56: #N/A | AQ56: #N/A | AR56: #N/A | AS56: #N/A | AT56: #N/A | AU56: #N/A | AV56: #N/A | AW56: #N/A | AX56: #N/A | AY56: #N/A | AZ56: #N/A | BA56: 5612.92 | BB56: =IF(ISNUMBER(VLOOKUP($B56,CEIC_DATA!$I$26:$N$353,Haver_M!BB$2,FALSE)),VLOOKUP($B56,CEIC_DATA!$I$26:$N$353,Haver_M!BB$2,FALSE),NA()) -> 103.01402 | BC56: =IF(ISNUMBER(VLOOKUP($B56,CEIC_DATA!$I$26:$N$353,Haver_M!BC$2,FALSE)),VLOOKUP($B56,CEIC_DATA!$I$26:$N$353,Haver_M!BC$2,FALSE),NA()) -> 121.4 | BD56: =IF(ISNUMBER(VLOOKUP($B56,CEIC_DATA!$I$26:$N$353,Haver_M!BD$2,FALSE)),VLOOKUP($B56,CEIC_DATA!$I$26:$N$353,Haver_M!BD$2,FALSE),NA()) -> 122.2 | BE56: =IF(ISNUMBER(VLOOKUP($B56,CEIC_DATA!$I$26:$N$353,Haver_M!BE$2,FALSE)),VLOOKUP($B56,CEIC_DATA!$I$26:$N$353,Haver_M!BE$2,FALSE),NA()) -> 49 | BF56: 505972 | BG56: 33606 | BH56: 687884 | BI56: 115133 | BJ56: #N/A | BK56: #N/A | BL56: #N/A | BM56: #N/A | BN56: 7863 | BO56: 8034 | BP56: 45.0179 | BQ56: =IF(ISNUMBER(BJ56),BJ56/$BP56,"") | BR56: =IF(ISNUMBER(BK56),BK56/$BP56,"") | BS56: =IF(ISNUMBER(BL56),BL56/$BP56,"") | BT56: =IF(ISNUMBER(BM56),BM56/$BP56,"") | BU56: 20647
A57: 0404 | B57: 38107 | C57: 6 | D57: 5.1461 | E57: 98.13307 | F57: 54.2 | G57: #N/A | H57: 57.6 | I57: 64.21 | J57: 36.12 | K57: 72.62 | L57: #N/A | M57: 31.79 | N57: 61.9 | O57: 68.4 | P57: 69.961 | Q57: 88.808 | R57: 67.34 | S57: 77.878 | T57: 94.878 | U57: 53.828 | V57: 54.691 | W57: 66.228 | X57: 9389.9489 | Y57: 5912.58 | Z57: 7229.86 | AA57: #N/A | AB57: #N/A | AC57: #N/A | AD57: #N/A | AE57: 63.386356 | AF57: #N/A | AG57: #N/A | AH57: #N/A | AI57: #N/A | AJ57: #N/A | AK57: #N/A | AL57: #N/A | AM57: #N/A | AN57: #N/A | AO57: #N/A | AP57: #N/A | AQ57: #N/A | AR57: #N/A | AS57: #N/A | AT57: #N/A | AU57: #N/A | AV57: #N/A | AW57: #N/A | AX57: #N/A | AY57: #N/A | AZ57: #N/A | BA57: 5806.24 | BB57: =IF(ISNUMBER(VLOOKUP($B57,CEIC_DATA!$I$26:$N$353,Haver_M!BB$2,FALSE)),VLOOKUP($B57,CEIC_DATA!$I$26:$N$353,Haver_M!BB$2,FALSE),NA()) -> 100.49399 | BC57: =IF(ISNUMBER(VLOOKUP($B57,CEIC_DATA!$I$26:$N$353,Haver_M!BC$2,FALSE)),VLOOKUP($B57,CEIC_DATA!$I$26:$N$353,Haver_M!BC$2,FALSE),NA()) -> #N/A | BD57: =IF(ISNUMBER(VLOOKUP($B57,CEIC_DATA!$I$26:$N$353,Haver_M!BD$2,FALSE)),VLOOKUP($B57,CEIC_DATA!$I$26:$N$353,Haver_M!BD$2,FALSE),NA()) -> #N/A | BE57: =IF(ISNUMBER(VLOOKUP($B57,CEIC_DATA!$I$26:$N$353,Haver_M!BE$2,FALSE)),VLOOKUP($B57,CEIC_DATA!$I$26:$N$353,Haver_M!BE$2,FALSE),NA()) -> #N/A | BF57: 467834 | BG57: 21055 | BH57: 597610 | BI57: 82999 | BJ57: #N/A | BK57: #N/A | BL57: #N/A | BM57: #N/A | BN57: 5643 | BO57: 6987 | BP57: 43.9311 | BQ57: =IF(ISNUMBER(BJ57),BJ57/$BP57,"") | BR57: =IF(ISNUMBER(BK57),BK57/$BP57,"") | BS57: =IF(ISNUMBER(BL57),BL57/$BP57,"") | BT57: =IF(ISNUMBER(BM57),BM57/$BP57,"") | BU57: 32389
A58: 0405 | B58: 38138 | C58: 6 | D58: 5.3016 | E58: 96.01057 | F58: 54.6 | G58: #N/A | H58: 57.31 | I58: 63.23 | J58: 37.35 | K58: 70.5 | L58: #N/A | M58: 32.03 | N58: 62.47 | O58: 67.8 | P58: 66.488 | Q58: 89.065 | R58: 65.87 | S58: 78.308 | T58: 94.387 | U58: 57.314 | V58: 53.905 | W58: 63.202 | X58: 9210.2181 | Y58: 5963.27 | Z58: 7471.15 | AA58: #N/A | AB58: #N/A | AC58: #N/A | AD58: #N/A | AE58: 237.18243 | AF58: #N/A | AG58: #N/A | AH58: #N/A | AI58: #N/A | AJ58: #N/A | AK58: #N/A | AL58: #N/A | AM58: #N/A | AN58: #N/A | AO58: #N/A | AP58: #N/A | AQ58: #N/A | AR58: #N/A | AS58: #N/A | AT58: #N/A | AU58: #N/A | AV58: #N/A | AW58: #N/A | AX58: #N/A | AY58: #N/A | AZ58: #N/A | BA58: 5204.65 | BB58: =IF(ISNUMBER(VLOOKUP($B58,CEIC_DATA!$I$26:$N$353,Haver_M!BB$2,FALSE)),VLOOKUP($B58,CEIC_DATA!$I$26:$N$353,Haver_M!BB$2,FALSE),NA()) -> 97.78932 | BC58: =IF(ISNUMBER(VLOOKUP($B58,CEIC_DATA!$I$26:$N$353,Haver_M!BC$2,FALSE)),VLOOKUP($B58,CEIC_DATA!$I$26:$N$353,Haver_M!BC$2,FALSE),NA()) -> #N/A | BD58: =IF(ISNUMBER(VLOOKUP($B58,CEIC_DATA!$I$26:$N$353,Haver_M!BD$2,FALSE)),VLOOKUP($B58,CEIC_DATA!$I$26:$N$353,Haver_M!BD$2,FALSE),NA()) -> #N/A | BE58: =IF(ISNUMBER(VLOOKUP($B58,CEIC_DATA!$I$26:$N$353,Haver_M!BE$2,FALSE)),VLOOKUP($B58,CEIC_DATA!$I$26:$N$353,Haver_M!BE$2,FALSE),NA()) -> #N/A | BF58: 488541 | BG58: 25055 | BH58: 632123 | BI58: 92176 | BJ58: #N/A | BK58: #N/A | BL58: #N/A | BM58: #N/A | BN58: 5963 | BO58: 8073 | BP58: 45.2508 | BQ58: =IF(ISNUMBER(BJ58),BJ58/$BP58,"") | BR58: =IF(ISNUMBER(BK58),BK58/$BP58,"") | BS58: =IF(ISNUMBER(BL58),BL58/$BP58,"") | BT58: =IF(ISNUMBER(BM58),BM58/$BP58,"") | BU58: 32282
A59: 0406 | B59: 38168 | C59: 6 | D59: 5.8677 | E59: 94.83225 | F59: 55 | G59: #N/A | H59: 57.43 | I59: 63.67 | J59: 38.18 | K59: 71.48 | L59: #N/A | M59: 33.47 | N59: 62.42 | O59: 68.2 | P59: 70.015 | Q59: 88.932 | R59: 65.72 | S59: 76.438 | T59: 98.254 | U59: 57.04 | V59: 52.938 | W59: 64.325 | X59: 9201.7495 | Y59: 6244.49 | Z59: 8944.15 | AA59: #N/A | AB59: #N/A | AC59: #N/A | AD59: #N/A | AE59: 51.625346 | AF59: #N/A | AG59: #N/A | AH59: #N/A | AI59: #N/A | AJ59: #N/A | AK59: #N/A | AL59: #N/A | AM59: #N/A | AN59: #N/A | AO59: #N/A | AP59: #N/A | AQ59: #N/A | AR59: #N/A | AS59: #N/A | AT59: #N/A | AU59: #N/A | AV59: #N/A | AW59: #N/A | AX59: #N/A | AY59: #N/A | AZ59: #N/A | BA59: 4823.87 | BB59: =IF(ISNUMBER(VLOOKUP($B59,CEIC_DATA!$I$26:$N$353,Haver_M!BB$2,FALSE)),VLOOKUP($B59,CEIC_DATA!$I$26:$N$353,Haver_M!BB$2,FALSE),NA()) -> 95.78882 | BC59: =IF(ISNUMBER(VLOOKUP($B59,CEIC_DATA!$I$26:$N$353,Haver_M!BC$2,FALSE)),VLOOKUP($B59,CEIC_DATA!$I$26:$N$353,Haver_M!BC$2,FALSE),NA()) -> 118.4 | BD59: =IF(ISNUMBER(VLOOKUP($B59,CEIC_DATA!$I$26:$N$353,Haver_M!BD$2,FALSE)),VLOOKUP($B59,CEIC_DATA!$I$26:$N$353,Haver_M!BD$2,FALSE),NA()) -> 121.5 | BE59: =IF(ISNUMBER(VLOOKUP($B59,CEIC_DATA!$I$26:$N$353,Haver_M!BE$2,FALSE)),VLOOKUP($B59,CEIC_DATA!$I$26:$N$353,Haver_M!BE$2,FALSE),NA()) -> 47.9 | BF59: 505086 | BG59: 25887 | BH59: 658634 | BI59: 94928 | BJ59: #N/A | BK59: #N/A | BL59: #N/A | BM59: #N/A | BN59: 6068 | BO59: 8717 | BP59: 45.5068 | BQ59: =IF(ISNUMBER(BJ59),BJ59/$BP59,"") | BR59: =IF(ISNUMBER(BK59),BK59/$BP59,"") | BS59: =IF(ISNUMBER(BL59),BL59/$BP59,"") | BT59: =IF(ISNUMBER(BM59),BM59/$BP59,"") | BU59: 30556
A60: 0407 | B60: 38199 | C60: 6 | D60: 6.1935 | E60: 93.65218 | F60: 55.4 | G60: #N/A | H60: 59.38 | I60: 65.56 | J60: 38.25 | K60: 71.84 | L60: #N/A | M60: 35.83 | N60: 64.98 | O60: 70.1 | P60: 75.181 | Q60: 89.16 | R60: 67.141 | S60: 74.3 | T60: 92.439 | U60: 58.804 | V60: 57.822 | W60: 69.17 | X60: 9429.579 | Y60: 5994.97 | Z60: 7948.19 | AA60: #N/A | AB60: #N/A | AC60: #N/A | AD60: #N/A | AE60: 44.113045 | AF60: #N/A | AG60: #N/A | AH60: #N/A | AI60: #N/A | AJ60: #N/A | AK60: #N/A | AL60: #N/A | AM60: #N/A | AN60: #N/A | AO60: #N/A | AP60: #N/A | AQ60: #N/A | AR60: #N/A | AS60: #N/A | AT60: #N/A | AU60: #N/A | AV60: #N/A | AW60: #N/A | AX60: #N/A | AY60: #N/A | AZ60: #N/A | BA60: 4972.88 | BB60: =IF(ISNUMBER(VLOOKUP($B60,CEIC_DATA!$I$26:$N$353,Haver_M!BB$2,FALSE)),VLOOKUP($B60,CEIC_DATA!$I$26:$N$353,Haver_M!BB$2,FALSE),NA()) -> 94.748886 | BC60: =IF(ISNUMBER(VLOOKUP($B60,CEIC_DATA!$I$26:$N$353,Haver_M!BC$2,FALSE)),VLOOKUP($B60,CEIC_DATA!$I$26:$N$353,Haver_M!BC$2,FALSE),NA()) -> #N/A | BD60: =IF(ISNUMBER(VLOOKUP($B60,CEIC_DATA!$I$26:$N$353,Haver_M!BD$2,FALSE)),VLOOKUP($B60,CEIC_DATA!$I$26:$N$353,Haver_M!BD$2,FALSE),NA()) -> #N/A | BE60: =IF(ISNUMBER(VLOOKUP($B60,CEIC_DATA!$I$26:$N$353,Haver_M!BE$2,FALSE)),VLOOKUP($B60,CEIC_DATA!$I$26:$N$353,Haver_M!BE$2,FALSE),NA()) -> #N/A | BF60: 523283 | BG60: 24888 | BH60: 681938 | BI60: 101184 | BJ60: #N/A | BK60: #N/A | BL60: #N/A | BM60: #N/A | BN60: 5819 | BO60: 7872 | BP60: 46.0416 | BQ60: =IF(ISNUMBER(BJ60),BJ60/$BP60,"") | BR60: =IF(ISNUMBER(BK60),BK60/$BP60,"") | BS60: =IF(ISNUMBER(BL60),BL60/$BP60,"") | BT60: =IF(ISNUMBER(BM60),BM60/$BP60,"") | BU60: 27176
A61: 0408 | B61: 38230 | C61: 6 | D61: 6.1545 | E61: 94.38286 | F61: 55.9 | G61: #N/A | H61: 59.75 | I61: 65.05 | J61: 39.32 | K61: 71.91 | L61: #N/A | M61: 35.92 | N61: 66.76 | O61: 68.8 | P61: 70.158 | Q61: 90.453 | R61: 68.412 | S61: 74.709 | T61: 92.94 | U61: 57.048 | V61: 53.709 | W61: 66.332 | X61: 8662.1202 | Y61: 6096.42 | Z61: 8159.77 | AA61: #N/A | AB61: #N/A | AC61: #N/A | AD61: #N/A | AE61: 83.162498 | AF61: #N/A | AG61: #N/A | AH61: #N/A | AI61: #N/A | AJ61: #N/A | AK61: #N/A | AL61: #N/A | AM61: #N/A | AN61: #N/A | AO61: #N/A | AP61: #N/A | AQ61: #N/A | AR61: #N/A | AS61: #N/A | AT61: #N/A | AU61: #N/A | AV61: #N/A | AW61: #N/A | AX61: #N/A | AY61: #N/A | AZ61: #N/A | BA61: 5144.17 | BB61: =IF(ISNUMBER(VLOOKUP($B61,CEIC_DATA!$I$26:$N$353,Haver_M!BB$2,FALSE)),VLOOKUP($B61,CEIC_DATA!$I$26:$N$353,Haver_M!BB$2,FALSE),NA()) -> 94.352552 | BC61: =IF(ISNUMBER(VLOOKUP($B61,CEIC_DATA!$I$26:$N$353,Haver_M!BC$2,FALSE)),VLOOKUP($B61,CEIC_DATA!$I$26:$N$353,Haver_M!BC$2,FALSE),NA()) -> #N/A | BD61: =IF(ISNUMBER(VLOOKUP($B61,CEIC_DATA!$I$26:$N$353,Haver_M!BD$2,FALSE)),VLOOKUP($B61,CEIC_DATA!$I$26:$N$353,Haver_M!BD$2,FALSE),NA()) -> #N/A | BE61: =IF(ISNUMBER(VLOOKUP($B61,CEIC_DATA!$I$26:$N$353,Haver_M!BE$2,FALSE)),VLOOKUP($B61,CEIC_DATA!$I$26:$N$353,Haver_M!BE$2,FALSE),NA()) -> #N/A | BF61: 496606 | BG61: 25985 | BH61: 651068 | BI61: 97823 | BJ61: #N/A | BK61: #N/A | BL61: #N/A | BM61: #N/A | BN61: 5983 | BO61: 8132 | BP61: 46.341 | BQ61: =IF(ISNUMBER(BJ61),BJ61/$BP61,"") | BR61: =IF(ISNUMBER(BK61),BK61/$BP61,"") | BS61: =IF(ISNUMBER(BL61),BL61/$BP61,"") | BT61: =IF(ISNUMBER(BM61),BM61/$BP61,"") | BU61: 23283
A62: 0409 | B62: 38260 | C62: 6 | D62: 6.2446 | E62: 94.23987 | F62: 56 | G62: #N/A | H62: 60.87 | I62: 68.3 | J62: 40.33 | K62: 71.59 | L62: #N/A | M62: 37.09 | N62: 67.42 | O62: 70.4 | P62: 76.033 | Q62: 90.333 | R62: 68.513 | S62: 73.708 | T62: 90.666 | U62: 58.644 | V62: 58.561 | W62: 68.277 | X62: 9390.9436 | Y62: 6786.75 | Z62: 9003.22 | AA62: #N/A | AB62: #N/A | AC62: #N/A | AD62: #N/A | AE62: 47.506499 | AF62: #N/A | AG62: #N/A | AH62: #N/A | AI62: #N/A | AJ62: #N/A | AK62: #N/A | AL62: #N/A | AM62: #N/A | AN62: #N/A | AO62: #N/A | AP62: #N/A | AQ62: #N/A | AR62: #N/A | AS62: #N/A | AT62: #N/A | AU62: #N/A | AV62: #N/A | AW62: #N/A | AX62: #N/A | AY62: #N/A | AZ62: #N/A | BA62: 5423.27 | BB62: =IF(ISNUMBER(VLOOKUP($B62,CEIC_DATA!$I$26:$N$353,Haver_M!BB$2,FALSE)),VLOOKUP($B62,CEIC_DATA!$I$26:$N$353,Haver_M!BB$2,FALSE),NA()) -> 94.27631 | BC62: =IF(ISNUMBER(VLOOKUP($B62,CEIC_DATA!$I$26:$N$353,Haver_M!BC$2,FALSE)),VLOOKUP($B62,CEIC_DATA!$I$26:$N$353,Haver_M!BC$2,FALSE),NA()) -> 116.9 | BD62: =IF(ISNUMBER(VLOOKUP($B62,CEIC_DATA!$I$26:$N$353,Haver_M!BD$2,FALSE)),VLOOKUP($B62,CEIC_DATA!$I$26:$N$353,Haver_M!BD$2,FALSE),NA()) -> 120 | BE62: =IF(ISNUMBER(VLOOKUP($B62,CEIC_DATA!$I$26:$N$353,Haver_M!BE$2,FALSE)),VLOOKUP($B62,CEIC_DATA!$I$26:$N$353,Haver_M!BE$2,FALSE),NA()) -> 44.4 | BF62: 569107 | BG62: 30349 | BH62: 740018 | BI62: 105414 | BJ62: #N/A | BK62: #N/A | BL62: #N/A | BM62: #N/A | BN62: 6919 | BO62: 9420 | BP62: 46.095 | BQ62: =IF(ISNUMBER(BJ62),BJ62/$BP62,"") | BR62: =IF(ISNUMBER(BK62),BK62/$BP62,"") | BS62: =IF(ISNUMBER(BL62),BL62/$BP62,"") | BT62: =IF(ISNUMBER(BM62),BM62/$BP62,"") | BU62: 20338
A63: 0410 | B63: 38291 | C63: 6 | D63: 6.8652 | E63: 93.14046 | F63: 56.5 | G63: #N/A | H63: 60.48 | I63: 66.67 | J63: 39.55 | K63: 72.6 | L63: #N/A | M63: 36.11 | N63: 66.99 | O63: 68.5 | P63: 70.615 | Q63: 89.284 | R63: 65.221 | S63: 75.665 | T63: 96.363 | U63: 56.353 | V63: 57.578 | W63: 64.533 | X63: 9398.3927 | Y63: 6567.5 | Z63: 8681.73 | AA63: #N/A | AB63: #N/A | AC63: #N/A | AD63: #N/A | AE63: 70.75746 | AF63: #N/A | AG63: #N/A | AH63: #N/A | AI63: #N/A | AJ63: #N/A | AK63: #N/A | AL63: #N/A | AM63: #N/A | AN63: #N/A | AO63: #N/A | AP63: #N/A | AQ63: #N/A | AR63: #N/A | AS63: #N/A | AT63: #N/A | AU63: #N/A | AV63: #N/A | AW63: #N/A | AX63: #N/A | AY63: #N/A | AZ63: #N/A | BA63: 5698.64 | BB63: =IF(ISNUMBER(VLOOKUP($B63,CEIC_DATA!$I$26:$N$353,Haver_M!BB$2,FALSE)),VLOOKUP($B63,CEIC_DATA!$I$26:$N$353,Haver_M!BB$2,FALSE),NA()) -> 94.268286 | BC63: =IF(ISNUMBER(VLOOKUP($B63,CEIC_DATA!$I$26:$N$353,Haver_M!BC$2,FALSE)),VLOOKUP($B63,CEIC_DATA!$I$26:$N$353,Haver_M!BC$2,FALSE),NA()) -> #N/A | BD63: =IF(ISNUMBER(VLOOKUP($B63,CEIC_DATA!$I$26:$N$353,Haver_M!BD$2,FALSE)),VLOOKUP($B63,CEIC_DATA!$I$26:$N$353,Haver_M!BD$2,FALSE),NA()) -> #N/A | BE63: =IF(ISNUMBER(VLOOKUP($B63,CEIC_DATA!$I$26:$N$353,Haver_M!BE$2,FALSE)),VLOOKUP($B63,CEIC_DATA!$I$26:$N$353,Haver_M!BE$2,FALSE),NA()) -> #N/A | BF63: 623285 | BG63: 28588 | BH63: 798262 | BI63: 113209 | BJ63: #N/A | BK63: #N/A | BL63: #N/A | BM63: #N/A | BN63: 6519 | BO63: 8989 | BP63: 45.7826 | BQ63: =IF(ISNUMBER(BJ63),BJ63/$BP63,"") | BR63: =IF(ISNUMBER(BK63),BK63/$BP63,"") | BS63: =IF(ISNUMBER(BL63),BL63/$BP63,"") | BT63: =IF(ISNUMBER(BM63),BM63/$BP63,"") | BU63: 23710
A64: 0411 | B64: 38321 | C64: 6 | D64: 7.2053 | E64: 93.18681 | F64: 56.3 | G64: #N/A | H64: 61.31 | I64: 67.45 | J64: 39.13 | K64: 74.89 | L64: #N/A | M64: 37.44 | N64: 69.13 | O64: 70.2 | P64: 72.828 | Q64: 89.554 | R64: 68.047 | S64: 75.626 | T64: 95.411 | U64: 56.672 | V64: 59.753 | W64: 68.538 | X64: 8982.2726 | Y64: 7702.14 | Z64: 9675.94 | AA64: #N/A | AB64: #N/A | AC64: #N/A | AD64: #N/A | AE64: 58.079535 | AF64: #N/A | AG64: #N/A | AH64: #N/A | AI64: #N/A | AJ64: #N/A | AK64: #N/A | AL64: #N/A | AM64: #N/A | AN64: #N/A | AO64: #N/A | AP64: #N/A | AQ64: #N/A | AR64: #N/A | AS64: #N/A | AT64: #N/A | AU64: #N/A | AV64: #N/A | AW64: #N/A | AX64: #N/A | AY64: #N/A | AZ64: #N/A | BA64: 5960.75 | BB64: =IF(ISNUMBER(VLOOKUP($B64,CEIC_DATA!$I$26:$N$353,Haver_M!BB$2,FALSE)),VLOOKUP($B64,CEIC_DATA!$I$26:$N$353,Haver_M!BB$2,FALSE),NA()) -> 94.095435 | BC64: =IF(ISNUMBER(VLOOKUP($B64,CEIC_DATA!$I$26:$N$353,Haver_M!BC$2,FALSE)),VLOOKUP($B64,CEIC_DATA!$I$26:$N$353,Haver_M!BC$2,FALSE),NA()) -> #N/A | BD64: =IF(ISNUMBER(VLOOKUP($B64,CEIC_DATA!$I$26:$N$353,Haver_M!BD$2,FALSE)),VLOOKUP($B64,CEIC_DATA!$I$26:$N$353,Haver_M!BD$2,FALSE),NA()) -> #N/A | BE64: =IF(ISNUMBER(VLOOKUP($B64,CEIC_DATA!$I$26:$N$353,Haver_M!BE$2,FALSE)),VLOOKUP($B64,CEIC_DATA!$I$26:$N$353,Haver_M!BE$2,FALSE),NA()) -> #N/A | BF64: 617097 | BG64: 28761 | BH64: 776734 | BI64: 102425 | BJ64: #N/A | BK64: #N/A | BL64: #N/A | BM64: #N/A | BN64: 7086 | BO64: 9358 | BP64: 45.1251 | BQ64: =IF(ISNUMBER(BJ64),BJ64/$BP64,"") | BR64: =IF(ISNUMBER(BK64),BK64/$BP64,"") | BS64: =IF(ISNUMBER(BL64),BL64/$BP64,"") | BT64: =IF(ISNUMBER(BM64),BM64/$BP64,"") | BU64: 21800
A65: 0412 | B65: 38352 | C65: 6 | D65: 6.591 | E65: 93.70062 | F65: 55.9 | G65: #N/A | H65: 61.48 | I65: 67.42 | J65: 43.8 | K65: 72.96 | L65: #N/A | M65: 37.99 | N65: 66.15 | O65: 70 | P65: 72.323 | Q65: 89.785 | R65: 68.671 | S65: 74.751 | T65: 94.172 | U65: 57.051 | V65: 58.161 | W65: 68.254 | X65: 9454.3101 | Y65: 7519.11 | Z65: 10600.48 | AA65: #N/A | AB65: #N/A | AC65: #N/A | AD65: #N/A | AE65: 54.208721 | AF65: #N/A | AG65: #N/A | AH65: #N/A | AI65: #N/A | AJ65: #N/A | AK65: #N/A | AL65: #N/A | AM65: #N/A | AN65: #N/A | AO65: #N/A | AP65: #N/A | AQ65: #N/A | AR65: #N/A | AS65: #N/A | AT65: #N/A | AU65: #N/A | AV65: #N/A | AW65: #N/A | AX65: #N/A | AY65: #N/A | AZ65: #N/A | BA65: 6393.83 | BB65: =IF(ISNUMBER(VLOOKUP($B65,CEIC_DATA!$I$26:$N$353,Haver_M!BB$2,FALSE)),VLOOKUP($B65,CEIC_DATA!$I$26:$N$353,Haver_M!BB$2,FALSE),NA()) -> 93.563651 | BC65: =IF(ISNUMBER(VLOOKUP($B65,CEIC_DATA!$I$26:$N$353,Haver_M!BC$2,FALSE)),VLOOKUP($B65,CEIC_DATA!$I$26:$N$353,Haver_M!BC$2,FALSE),NA()) -> 122 | BD65: =IF(ISNUMBER(VLOOKUP($B65,CEIC_DATA!$I$26:$N$353,Haver_M!BD$2,FALSE)),VLOOKUP($B65,CEIC_DATA!$I$26:$N$353,Haver_M!BD$2,FALSE),NA()) -> 121.5 | BE65: =IF(ISNUMBER(VLOOKUP($B65,CEIC_DATA!$I$26:$N$353,Haver_M!BE$2,FALSE)),VLOOKUP($B65,CEIC_DATA!$I$26:$N$353,Haver_M!BE$2,FALSE),NA()) -> 47.4 | BF65: 579940 | BG65: 32645 | BH65: 740697 | BI65: 99228 | BJ65: #N/A | BK65: #N/A | BL65: #N/A | BM65: #N/A | BN65: 7357 | BO65: 10457 | BP65: 43.9796 | BQ65: =IF(ISNUMBER(BJ65),BJ65/$BP65,"") | BR65: =IF(ISNUMBER(BK65),BK65/$BP65,"") | BS65: =IF(ISNUMBER(BL65),BL65/$BP65,"") | BT65: =IF(ISNUMBER(BM65),BM65/$BP65,"") | BU65: 21697
A66: 0501 | B66: 38383 | C66: 6 | D66: 6.7091 | E66: 94.85097 | F66: 56.3 | G66: #N/A | H66: 61.44 | I66: 67.24 | J66: 41.84 | K66: 71.29 | L66: #N/A | M66: 36.71 | N66: 70.02 | O66: 70 | P66: 70.035 | Q66: 89.448 | R66: 68.606 | S66: 76.013 | T66: 96.246 | U66: 58.518 | V66: 57.686 | W66: 67.84 | X66: 9406.8997 | Y66: 8057.99 | Z66: 11004.6 | AA66: #N/A | AB66: #N/A | AC66: #N/A | AD66: #N/A | AE66: 53.37299 | AF66: #N/A | AG66: #N/A | AH66: #N/A | AI66: #N/A | AJ66: #N/A | AK66: #N/A | AL66: #N/A | AM66: #N/A | AN66: #N/A | AO66: #N/A | AP66: #N/A | AQ66: #N/A | AR66: #N/A | AS66: #N/A | AT66: #N/A | AU66: #N/A | AV66: #N/A | AW66: #N/A | AX66: #N/A | AY66: #N/A | AZ66: #N/A | BA66: 6306.99 | BB66: =IF(ISNUMBER(VLOOKUP($B66,CEIC_DATA!$I$26:$N$353,Haver_M!BB$2,FALSE)),VLOOKUP($B66,CEIC_DATA!$I$26:$N$353,Haver_M!BB$2,FALSE),NA()) -> 92.729372 | BC66: =IF(ISNUMBER(VLOOKUP($B66,CEIC_DATA!$I$26:$N$353,Haver_M!BC$2,FALSE)),VLOOKUP($B66,CEIC_DATA!$I$26:$N$353,Haver_M!BC$2,FALSE),NA()) -> #N/A | BD66: =IF(ISNUMBER(VLOOKUP($B66,CEIC_DATA!$I$26:$N$353,Haver_M!BD$2,FALSE)),VLOOKUP($B66,CEIC_DATA!$I$26:$N$353,Haver_M!BD$2,FALSE),NA()) -> #N/A | BE66: =IF(ISNUMBER(VLOOKUP($B66,CEIC_DATA!$I$26:$N$353,Haver_M!BE$2,FALSE)),VLOOKUP($B66,CEIC_DATA!$I$26:$N$353,Haver_M!BE$2,FALSE),NA()) -> #N/A | BF66: 564678 | BG66: 32936 | BH66: 741703 | BI66: 112964 | BJ66: #N/A | BK66: #N/A | BL66: #N/A | BM66: #N/A | BN66: 8194 | BO66: 11009 | BP66: 43.7545 | BQ66: =IF(ISNUMBER(BJ66),BJ66/$BP66,"") | BR66: =IF(ISNUMBER(BK66),BK66/$BP66,"") | BS66: =IF(ISNUMBER(BL66),BL66/$BP66,"") | BT66: =IF(ISNUMBER(BM66),BM66/$BP66,"") | BU66: 21549
A67: 0502 | B67: 38411 | C67: 6 | D67: 6.4867 | E67: 94.80468 | F67: 56.3 | G67: #N/A | H67: 62.33 | I67: 66.97 | J67: 45.65 | K67: 73.65 | L67: #N/A | M67: 38.09 | N67: 67.22 | O67: 69.6 | P67: 71.781 | Q67: 87.74 | R67: 63.341 | S67: 75.478 | T67: 89.907 | U67: 58.758 | V67: 57.873 | W67: 68.234 | X67: 9435.3279 | Y67: 8206.19 | Z67: 11665.7 | AA67: #N/A | AB67: #N/A | AC67: #N/A | AD67: #N/A | AE67: 57.545682 | AF67: #N/A | AG67: #N/A | AH67: #N/A | AI67: #N/A | AJ67: #N/A | AK67: #N/A | AL67: #N/A | AM67: #N/A | AN67: #N/A | AO67: #N/A | AP67: #N/A | AQ67: #N/A | AR67: #N/A | AS67: #N/A | AT67: #N/A | AU67: #N/A | AV67: #N/A | AW67: #N/A | AX67: #N/A | AY67: #N/A | AZ67: #N/A | BA67: 6595.05 | BB67: =IF(ISNUMBER(VLOOKUP($B67,CEIC_DATA!$I$26:$N$353,Haver_M!BB$2,FALSE)),VLOOKUP($B67,CEIC_DATA!$I$26:$N$353,Haver_M!BB$2,FALSE),NA()) -> 91.932543 | BC67: =IF(ISNUMBER(VLOOKUP($B67,CEIC_DATA!$I$26:$N$353,Haver_M!BC$2,FALSE)),VLOOKUP($B67,CEIC_DATA!$I$26:$N$353,Haver_M!BC$2,FALSE),NA()) -> #N/A | BD67: =IF(ISNUMBER(VLOOKUP($B67,CEIC_DATA!$I$26:$N$353,Haver_M!BD$2,FALSE)),VLOOKUP($B67,CEIC_DATA!$I$26:$N$353,Haver_M!BD$2,FALSE),NA()) -> #N/A | BE67: =IF(ISNUMBER(VLOOKUP($B67,CEIC_DATA!$I$26:$N$353,Haver_M!BE$2,FALSE)),VLOOKUP($B67,CEIC_DATA!$I$26:$N$353,Haver_M!BE$2,FALSE),NA()) -> #N/A | BF67: 553394 | BG67: 32601 | BH67: 712831 | BI67: 93425 | BJ67: #N/A | BK67: #N/A | BL67: #N/A | BM67: #N/A | BN67: 8046 | BO67: 10357 | BP67: 43.6798 | BQ67: =IF(ISNUMBER(BJ67),BJ67/$BP67,"") | BR67: =IF(ISNUMBER(BK67),BK67/$BP67,"") | BS67: =IF(ISNUMBER(BL67),BL67/$BP67,"") | BT67: =IF(ISNUMBER(BM67),BM67/$BP67,"") | BU67: 19978
A68: 0503 | B68: 38442 | C68: 6 | D68: 6.6853 | E68: 93.46015 | F68: 56.3 | G68: #N/A | H68: 62.95 | I68: 67.94 | J68: 52.68 | K68: 73.36 | L68: #N/A | M68: 37.74 | N68: 66.64 | O68: 70.3 | P68: 70.331 | Q68: 88.6 | R68: 69.819 | S68: 74.598 | T68: 91.521 | U68: 59.685 | V68: 58.118 | W68: 69.604 | X68: 9579.6289 | Y68: 8444.14 | Z68: 11861.42 | AA68: #N/A | AB68: #N/A | AC68: #N/A | AD68: #N/A | AE68: 43.4295 | AF68: #N/A | AG68: 59.6617 | AH68: #N/A | AI68: 64.1682 | AJ68: 68.8 | AK68: 53.9583 | AL68: 55.5439 | AM68: 55.196 | AN68: 69.7388 | AO68: 64.9271 | AP68: 52.0462 | AQ68: 62.4132 | AR68: 64.135 | AS68: 48.8061 | AT68: 1.3219 | AU68: #N/A | AV68: #N/A | AW68: #N/A | AX68: #N/A | AY68: #N/A | AZ68: #N/A | BA68: 6679.18 | BB68: =IF(ISNUMBER(VLOOKUP($B68,CEIC_DATA!$I$26:$N$353,Haver_M!BB$2,FALSE)),VLOOKUP($B68,CEIC_DATA!$I$26:$N$353,Haver_M!BB$2,FALSE),NA()) -> 91.477533 | BC68: =IF(ISNUMBER(VLOOKUP($B68,CEIC_DATA!$I$26:$N$353,Haver_M!BC$2,FALSE)),VLOOKUP($B68,CEIC_DATA!$I$26:$N$353,Haver_M!BC$2,FALSE),NA()) -> 122.5 | BD68: =IF(ISNUMBER(VLOOKUP($B68,CEIC_DATA!$I$26:$N$353,Haver_M!BD$2,FALSE)),VLOOKUP($B68,CEIC_DATA!$I$26:$N$353,Haver_M!BD$2,FALSE),NA()) -> 123.2 | BE68: =IF(ISNUMBER(VLOOKUP($B68,CEIC_DATA!$I$26:$N$353,Haver_M!BE$2,FALSE)),VLOOKUP($B68,CEIC_DATA!$I$26:$N$353,Haver_M!BE$2,FALSE),NA()) -> 47.4 | BF68: 587321 | BG68: 39620 | BH68: 795555 | BI68: 132199 | BJ68: #N/A | BK68: #N/A | BL68: #N/A | BM68: #N/A | BN68: 10155 | BO68: 12369 | BP68: 43.6905 | BQ68: =IF(ISNUMBER(BJ68),BJ68/$BP68,"") | BR68: =IF(ISNUMBER(BK68),BK68/$BP68,"") | BS68: =IF(ISNUMBER(BL68),BL68/$BP68,"") | BT68: =IF(ISNUMBER(BM68),BM68/$BP68,"") | BU68: 17971
A69: 0504 | B69: 38472 | C69: 6 | D69: 7.1866 | E69: 94.4044 | F69: 56.7 | G69: #N/A | H69: 62.69 | I69: 68 | J69: 42.4 | K69: 74.82 | L69: #N/A | M69: 37.5 | N69: 69.14 | O69: 70 | P69: 75.926 | Q69: 88.451 | R69: 66.947 | S69: 71.749 | T69: 92.327 | U69: 58.443 | V69: 60.081 | W69: 68.511 | X69: 8986.4157 | Y69: 8036.1 | Z69: 11723.19 | AA69: #N/A | AB69: #N/A | AC69: #N/A | AD69: #N/A | AE69: 76.389615 | AF69: #N/A | AG69: 57.0801 | AH69: #N/A | AI69: 59.4053 | AJ69: 62.9151 | AK69: 52.3633 | AL69: 48.3516 | AM69: 51.3431 | AN69: 64.4584 | AO69: 57.3106 | AP69: 50.7917 | AQ69: 59.2496 | AR69: 60.4227 | AS69: 48.5549 | AT69: 1.2387 | AU69: #N/A | AV69: #N/A | AW69: #N/A | AX69: #N/A | AY69: #N/A | AZ69: #N/A | BA69: 6379.29 | BB69: =IF(ISNUMBER(VLOOKUP($B69,CEIC_DATA!$I$26:$N$353,Haver_M!BB$2,FALSE)),VLOOKUP($B69,CEIC_DATA!$I$26:$N$353,Haver_M!BB$2,FALSE),NA()) -> 91.400682 | BC69: =IF(ISNUMBER(VLOOKUP($B69,CEIC_DATA!$I$26:$N$353,Haver_M!BC$2,FALSE)),VLOOKUP($B69,CEIC_DATA!$I$26:$N$353,Haver_M!BC$2,FALSE),NA()) -> #N/A | BD69: =IF(ISNUMBER(VLOOKUP($B69,CEIC_DATA!$I$26:$N$353,Haver_M!BD$2,FALSE)),VLOOKUP($B69,CEIC_DATA!$I$26:$N$353,Haver_M!BD$2,FALSE),NA()) -> #N/A | BE69: =IF(ISNUMBER(VLOOKUP($B69,CEIC_DATA!$I$26:$N$353,Haver_M!BE$2,FALSE)),VLOOKUP($B69,CEIC_DATA!$I$26:$N$353,Haver_M!BE$2,FALSE),NA()) -> #N/A | BF69: 579835 | BG69: 19141 | BH69: 720718 | BI69: 93201 | BJ69: #N/A | BK69: #N/A | BL69: #N/A | BM69: #N/A | BN69: 7680 | BO69: 11336 | BP69: 43.7412 | BQ69: =IF(ISNUMBER(BJ69),BJ69/$BP69,"") | BR69: =IF(ISNUMBER(BK69),BK69/$BP69,"") | BS69: =IF(ISNUMBER(BL69),BL69/$BP69,"") | BT69: =IF(ISNUMBER(BM69),BM69/$BP69,"") | BU69: 28490
A70: 0505 | B70: 38503 | C70: 6 | D70: 7.0602 | E70: 95.61932 | F70: 56.4 | G70: #N/A | H70: 63.15 | I70: 68.23 | J70: 46.29 | K70: 74.27 | L70: #N/A | M70: 38.89 | N70: 70.25 | O70: 70.5 | P70: 73.894 | Q70: 87.567 | R70: 68.005 | S70: 73.721 | T70: 93.061 | U70: 57.66 | V70: 62.311 | W70: 69.51 | X70: 9283.4833 | Y70: 7932.98 | Z70: 12252.02 | AA70: #N/A | AB70: #N/A | AC70: #N/A | AD70: #N/A | AE70: 62.801358 | AF70: #N/A | AG70: 57.2858 | AH70: #N/A | AI70: 61.0702 | AJ70: 62.723 | AK70: 52.0818 | AL70: 49.5968 | AM70: 52.2447 | AN70: 59.2746 | AO70: 58.1685 | AP70: 48.0217 | AQ70: 57.9923 | AR70: 56.1716 | AS70: 49.1371 | AT70: 1.3061 | AU70: #N/A | AV70: #N/A | AW70: #N/A | AX70: #N/A | AY70: #N/A | AZ70: #N/A | BA70: 6482.66 | BB70: =IF(ISNUMBER(VLOOKUP($B70,CEIC_DATA!$I$26:$N$353,Haver_M!BB$2,FALSE)),VLOOKUP($B70,CEIC_DATA!$I$26:$N$353,Haver_M!BB$2,FALSE),NA()) -> 91.624583 | BC70: =IF(ISNUMBER(VLOOKUP($B70,CEIC_DATA!$I$26:$N$353,Haver_M!BC$2,FALSE)),VLOOKUP($B70,CEIC_DATA!$I$26:$N$353,Haver_M!BC$2,FALSE),NA()) -> #N/A | BD70: =IF(ISNUMBER(VLOOKUP($B70,CEIC_DATA!$I$26:$N$353,Haver_M!BD$2,FALSE)),VLOOKUP($B70,CEIC_DATA!$I$26:$N$353,Haver_M!BD$2,FALSE),NA()) -> #N/A | BE70: =IF(ISNUMBER(VLOOKUP($B70,CEIC_DATA!$I$26:$N$353,Haver_M!BE$2,FALSE)),VLOOKUP($B70,CEIC_DATA!$I$26:$N$353,Haver_M!BE$2,FALSE),NA()) -> #N/A | BF70: 600111 | BG70: 26197 | BH70: 757192 | BI70: 102440 | BJ70: #N/A | BK70: #N/A | BL70: #N/A | BM70: #N/A | BN70: 7977 | BO70: 13232 | BP70: 43.4889 | BQ70: =IF(ISNUMBER(BJ70),BJ70/$BP70,"") | BR70: =IF(ISNUMBER(BK70),BK70/$BP70,"") | BS70: =IF(ISNUMBER(BL70),BL70/$BP70,"") | BT70: =IF(ISNUMBER(BM70),BM70/$BP70,"") | BU70: 28335
A71: 0506 | B71: 38533 | C71: 6 | D71: 6.8835 | E71: 97.39137 | F71: 56.5 | G71: #N/A | H71: 64.27 | I71: 68.69 | J71: 46.55 | K71: 75.04 | L71: #N/A | M71: 39.21 | N71: 77.98 | O71: 71.3 | P71: 72.455 | Q71: 89.295 | R71: 69.439 | S71: 75.633 | T71: 93.382 | U71: 59.423 | V71: 61.724 | W71: 70.422 | X71: 9406.1419 | Y71: 8002.53 | Z71: 11938.05 | AA71: #N/A | AB71: #N/A | AC71: #N/A | AD71: #N/A | AE71: 65.840052 | AF71: #N/A | AG71: 58.3776 | AH71: #N/A | AI71: 63.0255 | AJ71: 65.8688 | AK71: 52.1859 | AL71: 51.9095 | AM71: 52.0988 | AN71: 55.7761 | AO71: 61.7372 | AP71: 50.6861 | AQ71: 60.3296 | AR71: 52.6888 | AS71: 49.5788 | AT71: 1.2995 | AU71: #N/A | AV71: #N/A | AW71: #N/A | AX71: #N/A | AY71: #N/A | AZ71: #N/A | BA71: 6933.72 | BB71: =IF(ISNUMBER(VLOOKUP($B71,CEIC_DATA!$I$26:$N$353,Haver_M!BB$2,FALSE)),VLOOKUP($B71,CEIC_DATA!$I$26:$N$353,Haver_M!BB$2,FALSE),NA()) -> 92.044013 | BC71: =IF(ISNUMBER(VLOOKUP($B71,CEIC_DATA!$I$26:$N$353,Haver_M!BC$2,FALSE)),VLOOKUP($B71,CEIC_DATA!$I$26:$N$353,Haver_M!BC$2,FALSE),NA()) -> 117.5 | BD71: =IF(ISNUMBER(VLOOKUP($B71,CEIC_DATA!$I$26:$N$353,Haver_M!BD$2,FALSE)),VLOOKUP($B71,CEIC_DATA!$I$26:$N$353,Haver_M!BD$2,FALSE),NA()) -> 120.7 | BE71: =IF(ISNUMBER(VLOOKUP($B71,CEIC_DATA!$I$26:$N$353,Haver_M!BE$2,FALSE)),VLOOKUP($B71,CEIC_DATA!$I$26:$N$353,Haver_M!BE$2,FALSE),NA()) -> 44.3 | BF71: 559378 | BG71: 29609 | BH71: 721552 | BI71: 99528 | BJ71: #N/A | BK71: #N/A | BL71: #N/A | BM71: #N/A | BN71: 7893 | BO71: 11803 | BP71: 43.5836 | BQ71: =IF(ISNUMBER(BJ71),BJ71/$BP71,"") | BR71: =IF(ISNUMBER(BK71),BK71/$BP71,"") | BS71: =IF(ISNUMBER(BL71),BL71/$BP71,"") | BT71: =IF(ISNUMBER(BM71),BM71/$BP71,"") | BU71: 25113
A72: 0507 | B72: 38564 | C72: 6 | D72: 6.9451 | E72: 98.65204 | F72: 57.4 | G72: #N/A | H72: 63.21 | I72: 67.39 | J72: 48.37 | K72: 76.16 | L72: #N/A | M72: 37.21 | N72: 71.32 | O72: 70 | P72: 74.267 | Q72: 85.696 | R72: 67.663 | S72: 76.965 | T72: 93.845 | U72: 58.189 | V72: 59.769 | W72: 68.555 | X72: 9260.7094 | Y72: 7639.79 | Z72: 11490.85 | AA72: #N/A | AB72: #N/A | AC72: #N/A | AD72: #N/A | AE72: 60.372557 | AF72: #N/A | AG72: 58.0059 | AH72: #N/A | AI72: 61.8493 | AJ72: 65.5511 | AK72: 52.7926 | AL72: 53.8168 | AM72: 53.9222 | AN72: 54.627 | AO72: 60.8974 | AP72: 51.0209 | AQ72: 59.6037 | AR72: 52.0833 | AS72: 49.7384 | AT72: 1.2848 | AU72: #N/A | AV72: #N/A | AW72: #N/A | AX72: #N/A | AY72: #N/A | AZ72: #N/A | BA72: 7336.7 | BB72: =IF(ISNUMBER(VLOOKUP($B72,CEIC_DATA!$I$26:$N$353,Haver_M!BB$2,FALSE)),VLOOKUP($B72,CEIC_DATA!$I$26:$N$353,Haver_M!BB$2,FALSE),NA()) -> 92.61576 | BC72: =IF(ISNUMBER(VLOOKUP($B72,CEIC_DATA!$I$26:$N$353,Haver_M!BC$2,FALSE)),VLOOKUP($B72,CEIC_DATA!$I$26:$N$353,Haver_M!BC$2,FALSE),NA()) -> #N/A | BD72: =IF(ISNUMBER(VLOOKUP($B72,CEIC_DATA!$I$26:$N$353,Haver_M!BD$2,FALSE)),VLOOKUP($B72,CEIC_DATA!$I$26:$N$353,Haver_M!BD$2,FALSE),NA()) -> #N/A | BE72: =IF(ISNUMBER(VLOOKUP($B72,CEIC_DATA!$I$26:$N$353,Haver_M!BE$2,FALSE)),VLOOKUP($B72,CEIC_DATA!$I$26:$N$353,Haver_M!BE$2,FALSE),NA()) -> #N/A | BF72: 518805 | BG72: 27279 | BH72: 680905 | BI72: 98907 | BJ72: #N/A | BK72: #N/A | BL72: #N/A | BM72: #N/A | BN72: 7492 | BO72: 11509 | BP72: 43.5361 | BQ72: =IF(ISNUMBER(BJ72),BJ72/$BP72,"") | BR72: =IF(ISNUMBER(BK72),BK72/$BP72,"") | BS72: =IF(ISNUMBER(BL72),BL72/$BP72,"") | BT72: =IF(ISNUMBER(BM72),BM72/$BP72,"") | BU72: 21384
A73: 0508 | B73: 38595 | C73: 6 | D73: 7.1918 | E73: 96.90196 | F73: 57.6 | G73: #N/A | H73: 64.83 | I73: 69.42 | J73: 49.99 | K73: 76.38 | L73: #N/A | M73: 39.45 | N73: 73.95 | O73: 71.2 | P73: 77.544 | Q73: 75.883 | R73: 66.879 | S73: 76.613 | T73: 98.081 | U73: 60.826 | V73: 64.141 | W73: 71.307 | X73: 10173.078 | Y73: 8665.84 | Z73: 12724.76 | AA73: #N/A | AB73: #N/A | AC73: #N/A | AD73: #N/A | AE73: 30.630474 | AF73: #N/A | AG73: 57.3769 | AH73: #N/A | AI73: 60.1432 | AJ73: 63.867 | AK73: 53.138 | AL73: 51.7369 | AM73: 53.1392 | AN73: 54.8491 | AO73: 60.8192 | AP73: 50.272 | AQ73: 56.3158 | AR73: 50.5208 | AS73: 50.1771 | AT73: 1.2704 | AU73: #N/A | AV73: #N/A | AW73: #N/A | AX73: #N/A | AY73: #N/A | AZ73: #N/A | BA73: 7726.03 | BB73: =IF(ISNUMBER(VLOOKUP($B73,CEIC_DATA!$I$26:$N$353,Haver_M!BB$2,FALSE)),VLOOKUP($B73,CEIC_DATA!$I$26:$N$353,Haver_M!BB$2,FALSE),NA()) -> 93.466589 | BC73: =IF(ISNUMBER(VLOOKUP($B73,CEIC_DATA!$I$26:$N$353,Haver_M!BC$2,FALSE)),VLOOKUP($B73,CEIC_DATA!$I$26:$N$353,Haver_M!BC$2,FALSE),NA()) -> #N/A | BD73: =IF(ISNUMBER(VLOOKUP($B73,CEIC_DATA!$I$26:$N$353,Haver_M!BD$2,FALSE)),VLOOKUP($B73,CEIC_DATA!$I$26:$N$353,Haver_M!BD$2,FALSE),NA()) -> #N/A | BE73: =IF(ISNUMBER(VLOOKUP($B73,CEIC_DATA!$I$26:$N$353,Haver_M!BE$2,FALSE)),VLOOKUP($B73,CEIC_DATA!$I$26:$N$353,Haver_M!BE$2,FALSE),NA()) -> #N/A | BF73: 604694 | BG73: 31137 | BH73: 786105 | BI73: 111367 | BJ73: #N/A | BK73: #N/A | BL73: #N/A | BM73: #N/A | BN73: 8571 | BO73: 12760 | BP73: 43.6245 | BQ73: =IF(ISNUMBER(BJ73),BJ73/$BP73,"") | BR73: =IF(ISNUMBER(BK73),BK73/$BP73,"") | BS73: =IF(ISNUMBER(BL73),BL73/$BP73,"") | BT73: =IF(ISNUMBER(BM73),BM73/$BP73,"") | BU73: 18405
A74: 0509 | B74: 38625 | C74: 6 | D74: 7.2081 | E74: 96.02433 | F74: 57.6 | G74: #N/A | H74: 64.37 | I74: 69.4 | J74: 50.89 | K74: 77.01 | L74: #N/A | M74: 38.75 | N74: 73.41 | O74: 71 | P74: 78.791 | Q74: 83.173 | R74: 68.031 | S74: 77.015 | T74: 94.36 | U74: 60.777 | V74: 61.427 | W74: 67.89 | X74: 9307.4792 | Y74: 8371.82 | Z74: 12085.74 | AA74: #N/A | AB74: #N/A | AC74: #N/A | AD74: #N/A | AE74: 38.418966 | AF74: #N/A | AG74: 56.9622 | AH74: #N/A | AI74: 59.5984 | AJ74: 63.3215 | AK74: 52.7493 | AL74: 50.3733 | AM74: 50.7228 | AN74: 57.5438 | AO74: 60.6921 | AP74: 47.9516 | AQ74: 55.0616 | AR74: 51.9027 | AS74: 51.4076 | AT74: 1.3205 | AU74: #N/A | AV74: #N/A | AW74: #N/A | AX74: #N/A | AY74: #N/A | AZ74: #N/A | BA74: 8272.32 | BB74: =IF(ISNUMBER(VLOOKUP($B74,CEIC_DATA!$I$26:$N$353,Haver_M!BB$2,FALSE)),VLOOKUP($B74,CEIC_DATA!$I$26:$N$353,Haver_M!BB$2,FALSE),NA()) -> 94.662024 | BC74: =IF(ISNUMBER(VLOOKUP($B74,CEIC_DATA!$I$26:$N$353,Haver_M!BC$2,FALSE)),VLOOKUP($B74,CEIC_DATA!$I$26:$N$353,Haver_M!BC$2,FALSE),NA()) -> 114.9 | BD74: =IF(ISNUMBER(VLOOKUP($B74,CEIC_DATA!$I$26:$N$353,Haver_M!BD$2,FALSE)),VLOOKUP($B74,CEIC_DATA!$I$26:$N$353,Haver_M!BD$2,FALSE),NA()) -> 119.6 | BE74: =IF(ISNUMBER(VLOOKUP($B74,CEIC_DATA!$I$26:$N$353,Haver_M!BE$2,FALSE)),VLOOKUP($B74,CEIC_DATA!$I$26:$N$353,Haver_M!BE$2,FALSE),NA()) -> 45.5 | BF74: 700611 | BG74: 35467 | BH74: 890769 | BI74: 115639 | BJ74: #N/A | BK74: #N/A | BL74: #N/A | BM74: #N/A | BN74: 8457 | BO74: 12896 | BP74: 43.915 | BQ74: =IF(ISNUMBER(BJ74),BJ74/$BP74,"") | BR74: =IF(ISNUMBER(BK74),BK74/$BP74,"") | BS74: =IF(ISNUMBER(BL74),BL74/$BP74,"") | BT74: =IF(ISNUMBER(BM74),BM74/$BP74,"") | BU74: 15547
A75: 0510 | B75: 38656 | C75: 6.25 | D75: 7.0784 | E75: 94.79893 | F75: 58.1 | G75: #N/A | H75: 67 | I75: 70.76 | J75: 53.59 | K75: 78.39 | L75: #N/A | M75: 39.14 | N75: 76.65 | O75: 71.2 | P75: 76.708 | Q75: 82.588 | R75: 68.143 | S75: 73.662 | T75: 90.853 | U75: 61.681 | V75: 63.639 | W75: 70.024 | X75: 9416.4094 | Y75: 8885.49 | Z75: 11472.77 | AA75: #N/A | AB75: #N/A | AC75: #N/A | AD75: #N/A | AE75: 41.996758 | AF75: #N/A | AG75: 57.8021 | AH75: #N/A | AI75: 60.9777 | AJ75: 64.3878 | AK75: 52.3517 | AL75: 50.1022 | AM75: 52.863 | AN75: 58.4867 | AO75: 60.3272 | AP75: 48.4513 | AQ75: 55.6396 | AR75: 52.3469 | AS75: 52.2449 | AT75: 1.3289 | AU75: #N/A | AV75: #N/A | AW75: #N/A | AX75: #N/A | AY75: #N/A | AZ75: #N/A | BA75: 8220.45 | BB75: =IF(ISNUMBER(VLOOKUP($B75,CEIC_DATA!$I$26:$N$353,Haver_M!BB$2,FALSE)),VLOOKUP($B75,CEIC_DATA!$I$26:$N$353,Haver_M!BB$2,FALSE),NA()) -> 96.397805 | BC75: =IF(ISNUMBER(VLOOKUP($B75,CEIC_DATA!$I$26:$N$353,Haver_M!BC$2,FALSE)),VLOOKUP($B75,CEIC_DATA!$I$26:$N$353,Haver_M!BC$2,FALSE),NA()) -> #N/A | BD75: =IF(ISNUMBER(VLOOKUP($B75,CEIC_DATA!$I$26:$N$353,Haver_M!BD$2,FALSE)),VLOOKUP($B75,CEIC_DATA!$I$26:$N$353,Haver_M!BD$2,FALSE),NA()) -> #N/A | BE75: =IF(ISNUMBER(VLOOKUP($B75,CEIC_DATA!$I$26:$N$353,Haver_M!BE$2,FALSE)),VLOOKUP($B75,CEIC_DATA!$I$26:$N$353,Haver_M!BE$2,FALSE),NA()) -> #N/A | BF75: 788811 | BG75: 35054 | BH75: 980595 | BI75: 117378 | BJ75: #N/A | BK75: #N/A | BL75: #N/A | BM75: #N/A | BN75: 8622 | BO75: 11883 | BP75: 44.818 | BQ75: =IF(ISNUMBER(BJ75),BJ75/$BP75,"") | BR75: =IF(ISNUMBER(BK75),BK75/$BP75,"") | BS75: =IF(ISNUMBER(BL75),BL75/$BP75,"") | BT75: =IF(ISNUMBER(BM75),BM75/$BP75,"") | BU75: 19798
A76: 0511 | B76: 38686 | C76: 6.25 | D76: 7.1108 | E76: 94.57299 | F76: 58.7 | G76: #N/A | H76: 64.16 | I76: 71 | J76: 46.95 | K76: 74.39 | L76: #N/A | M76: 34.98 | N76: 72.96 | O76: 72.5 | P76: 76.435 | Q76: 82.421 | R76: 67.574 | S76: 77.313 | T76: 95.049 | U76: 64.554 | V76: 63.324 | W76: 70.214 | X76: 9115.8616 | Y76: 7949.62 | Z76: 11649.67 | AA76: #N/A | AB76: #N/A | AC76: #N/A | AD76: #N/A | AE76: 38.248638 | AF76: #N/A | AG76: 55.9629 | AH76: #N/A | AI76: 58.5319 | AJ76: 61.4211 | AK76: 52.5453 | AL76: 50.7923 | AM76: 50.1333 | AN76: 54.7125 | AO76: 58.9476 | AP76: 48.4435 | AQ76: 54.22 | AR76: 52.0008 | AS76: 52.074 | AT76: 1.2679 | AU76: #N/A | AV76: #N/A | AW76: #N/A | AX76: #N/A | AY76: #N/A | AZ76: #N/A | BA76: 8534.36 | BB76: =IF(ISNUMBER(VLOOKUP($B76,CEIC_DATA!$I$26:$N$353,Haver_M!BB$2,FALSE)),VLOOKUP($B76,CEIC_DATA!$I$26:$N$353,Haver_M!BB$2,FALSE),NA()) -> 98.657892 | BC76: =IF(ISNUMBER(VLOOKUP($B76,CEIC_DATA!$I$26:$N$353,Haver_M!BC$2,FALSE)),VLOOKUP($B76,CEIC_DATA!$I$26:$N$353,Haver_M!BC$2,FALSE),NA()) -> #N/A | BD76: =IF(ISNUMBER(VLOOKUP($B76,CEIC_DATA!$I$26:$N$353,Haver_M!BD$2,FALSE)),VLOOKUP($B76,CEIC_DATA!$I$26:$N$353,Haver_M!BD$2,FALSE),NA()) -> #N/A | BE76: =IF(ISNUMBER(VLOOKUP($B76,CEIC_DATA!$I$26:$N$353,Haver_M!BE$2,FALSE)),VLOOKUP($B76,CEIC_DATA!$I$26:$N$353,Haver_M!BE$2,FALSE),NA()) -> #N/A | BF76: 630306 | BG76: 30963 | BH76: 795362 | BI76: 100825 | BJ76: #N/A | BK76: #N/A | BL76: #N/A | BM76: #N/A | BN76: 7293 | BO76: 11326 | BP76: 45.7265 | BQ76: =IF(ISNUMBER(BJ76),BJ76/$BP76,"") | BR76: =IF(ISNUMBER(BK76),BK76/$BP76,"") | BS76: =IF(ISNUMBER(BL76),BL76/$BP76,"") | BT76: =IF(ISNUMBER(BM76),BM76/$BP76,"") | BU76: 19006
A77: 0512 | B77: 38717 | C77: 6.25 | D77: 7.1191 | E77: 93.70812 | F77: 58.5 | G77: #N/A | H77: 67.46 | I77: 72 | J77: 53.21 | K77: 80.57 | L77: #N/A | M77: 36.64 | N77: 78.31 | O77: 73.6 | P77: 77.233 | Q77: 82.286 | R77: 67.856 | S77: 81.519 | T77: 94.304 | U77: 64.332 | V77: 65.917 | W77: 70.89 | X77: 9654.4542 | Y77: 9356.97 | Z77: 12768.53 | AA77: #N/A | AB77: #N/A | AC77: #N/A | AD77: #N/A | AE77: 44.533332 | AF77: 61.9521 | AG77: 55.7705 | AH77: 63.6074 | AI77: 58.231 | AJ77: 60.8108 | AK77: 52.5598 | AL77: 51.8428 | AM77: 52.3399 | AN77: 56.1576 | AO77: 57.7396 | AP77: 49.8756 | AQ77: 55.9028 | AR77: 52.5799 | AS77: 51.8473 | AT77: 1.2192 | AU77: 56.4577 | AV77: 53.7353 | AW77: 61.2502 | AX77: 59.3552 | AY77: #N/A | AZ77: 52.7295 | BA77: 9162.07 | BB77: =IF(ISNUMBER(VLOOKUP($B77,CEIC_DATA!$I$26:$N$353,Haver_M!BB$2,FALSE)),VLOOKUP($B77,CEIC_DATA!$I$26:$N$353,Haver_M!BB$2,FALSE),NA()) -> 101.16479 | BC77: =IF(ISNUMBER(VLOOKUP($B77,CEIC_DATA!$I$26:$N$353,Haver_M!BC$2,FALSE)),VLOOKUP($B77,CEIC_DATA!$I$26:$N$353,Haver_M!BC$2,FALSE),NA()) -> 124.3 | BD77: =IF(ISNUMBER(VLOOKUP($B77,CEIC_DATA!$I$26:$N$353,Haver_M!BD$2,FALSE)),VLOOKUP($B77,CEIC_DATA!$I$26:$N$353,Haver_M!BD$2,FALSE),NA()) -> 122.7 | BE77: =IF(ISNUMBER(VLOOKUP($B77,CEIC_DATA!$I$26:$N$353,Haver_M!BE$2,FALSE)),VLOOKUP($B77,CEIC_DATA!$I$26:$N$353,Haver_M!BE$2,FALSE),NA()) -> 51.3 | BF77: 601498 | BG77: 31936 | BH77: 768425 | BI77: 100597 | BJ77: #N/A | BK77: #N/A | BL77: #N/A | BM77: #N/A | BN77: 9235 | BO77: 12390 | BP77: 45.6411 | BQ77: =IF(ISNUMBER(BJ77),BJ77/$BP77,"") | BR77: =IF(ISNUMBER(BK77),BK77/$BP77,"") | BS77: =IF(ISNUMBER(BL77),BL77/$BP77,"") | BT77: =IF(ISNUMBER(BM77),BM77/$BP77,"") | BU77: 19260
A78: 0601 | B78: 38748 | C78: 6.5 | D78: 7.309 | E78: 94.94215 | F78: 58.6 | G78: #N/A | H78: 68.58 | I78: 72.68 | J78: 56.07 | K78: 81.99 | L78: #N/A | M78: 39.54 | N78: 76.94 | O78: 73.9 | P78: 75.554 | Q78: 85.166 | R78: 69.178 | S78: 80.262 | T78: 96.618 | U78: 64.495 | V78: 66.768 | W78: 72.067 | X78: 9448.812 | Y78: 9120.35 | Z78: 13055.15 | AA78: #N/A | AB78: #N/A | AC78: #N/A | AD78: #N/A | AE78: 42.228356 | AF78: 60.6139 | AG78: 55.0581 | AH78: 62.0291 | AI78: 57.4324 | AJ78: 58.9928 | AK78: 52.2573 | AL78: 51.9144 | AM78: 53.3784 | AN78: 56.0948 | AO78: 56.6441 | AP78: 49.3036 | AQ78: 55.0335 | AR78: 51.1287 | AS78: 51.0204 | AT78: 1.1965 | AU78: 56.3516 | AV78: 53.5133 | AW78: 60.7276 | AX78: 59.5498 | AY78: #N/A | AZ78: 52.0035 | BA78: 9539.67 | BB78: =IF(ISNUMBER(VLOOKUP($B78,CEIC_DATA!$I$26:$N$353,Haver_M!BB$2,FALSE)),VLOOKUP($B78,CEIC_DATA!$I$26:$N$353,Haver_M!BB$2,FALSE),NA()) -> 103.52128 | BC78: =IF(ISNUMBER(VLOOKUP($B78,CEIC_DATA!$I$26:$N$353,Haver_M!BC$2,FALSE)),VLOOKUP($B78,CEIC_DATA!$I$26:$N$353,Haver_M!BC$2,FALSE),NA()) -> #N/A | BD78: =IF(ISNUMBER(VLOOKUP($B78,CEIC_DATA!$I$26:$N$353,Haver_M!BD$2,FALSE)),VLOOKUP($B78,CEIC_DATA!$I$26:$N$353,Haver_M!BD$2,FALSE),NA()) -> #N/A | BE78: =IF(ISNUMBER(VLOOKUP($B78,CEIC_DATA!$I$26:$N$353,Haver_M!BE$2,FALSE)),VLOOKUP($B78,CEIC_DATA!$I$26:$N$353,Haver_M!BE$2,FALSE),NA()) -> #N/A | BF78: 647842 | BG78: 37492 | BH78: 847751 | BI78: 123374 | BJ78: #N/A | BK78: #N/A | BL78: #N/A | BM78: #N/A | BN78: 9168 | BO78: 12894 | BP78: 44.397 | BQ78: =IF(ISNUMBER(BJ78),BJ78/$BP78,"") | BR78: =IF(ISNUMBER(BK78),BK78/$BP78,"") | BS78: =IF(ISNUMBER(BL78),BL78/$BP78,"") | BT78: =IF(ISNUMBER(BM78),BM78/$BP78,"") | BU78: 19496
A79: 0602 | B79: 38776 | C79: 6.5 | D79: 7.3441 | E79: 95.51086 | F79: 58.6 | G79: #N/A | H79: 69.04 | I79: 73.46 | J79: 57.58 | K79: 81.12 | L79: #N/A | M79: 40.75 | N79: 76.52 | O79: 74.7 | P79: 76.619 | Q79: 85.979 | R79: 69.312 | S79: 80.381 | T79: 97.252 | U79: 63.51 | V79: 67.082 | W79: 74.389 | X79: 9605.5289 | Y79: 9336.51 | Z79: 13223.63 | AA79: #N/A | AB79: #N/A | AC79: #N/A | AD79: #N/A | AE79: 29.8453 | AF79: 62.0941 | AG79: 56.2545 | AH79: 62.9993 | AI79: 60.0593 | AJ79: 60.4539 | AK79: 51.954 | AL79: 50.5747 | AM79: 52.9885 | AN79: 54.9241 | AO79: 56.8838 | AP79: 50.8249 | AQ79: 57.6752 | AR79: 52.1837 | AS79: 50.8742 | AT79: 1.1895 | AU79: 56.3452 | AV79: 52.2218 | AW79: 61.2966 | AX79: 59.431 | AY79: #N/A | AZ79: 53.2271 | BA79: 10090.08 | BB79: =IF(ISNUMBER(VLOOKUP($B79,CEIC_DATA!$I$26:$N$353,Haver_M!BB$2,FALSE)),VLOOKUP($B79,CEIC_DATA!$I$26:$N$353,Haver_M!BB$2,FALSE),NA()) -> 105.28187 | BC79: =IF(ISNUMBER(VLOOKUP($B79,CEIC_DATA!$I$26:$N$353,Haver_M!BC$2,FALSE)),VLOOKUP($B79,CEIC_DATA!$I$26:$N$353,Haver_M!BC$2,FALSE),NA()) -> #N/A | BD79: =IF(ISNUMBER(VLOOKUP($B79,CEIC_DATA!$I$26:$N$353,Haver_M!BD$2,FALSE)),VLOOKUP($B79,CEIC_DATA!$I$26:$N$353,Haver_M!BD$2,FALSE),NA()) -> #N/A | BE79: =IF(ISNUMBER(VLOOKUP($B79,CEIC_DATA!$I$26:$N$353,Haver_M!BE$2,FALSE)),VLOOKUP($B79,CEIC_DATA!$I$26:$N$353,Haver_M!BE$2,FALSE),NA()) -> #N/A | BF79: 639717 | BG79: 38517 | BH79: 819181 | BI79: 98635 | BJ79: #N/A | BK79: #N/A | BL79: #N/A | BM79: #N/A | BN79: 9055 | BO79: 11535 | BP79: 44.3289 | BQ79: =IF(ISNUMBER(BJ79),BJ79/$BP79,"") | BR79: =IF(ISNUMBER(BK79),BK79/$BP79,"") | BS79: =IF(ISNUMBER(BL79),BL79/$BP79,"") | BT79: =IF(ISNUMBER(BM79),BM79/$BP79,"") | BU79: 18294
A80: 0603 | B80: 38807 | C80: 6.5 | D80: 7.5291 | E80: 94.69097 | F80: 58.6 | G80: #N/A | H80: 69.95 | I80: 73.89 | J80: 60.34 | K80: 83.05 | L80: #N/A | M80: 42.84 | N80: 79.3 | O80: 74.1 | P80: 75.327 | Q80: 86.446 | R80: 69.325 | S80: 81.563 | T80: 96.05 | U80: 64.056 | V80: 67.84 | W80: 71.893 | X80: 9562.3718 | Y80: 9655.54 | Z80: 14117.06 | AA80: #N/A | AB80: #N/A | AC80: #N/A | AD80: #N/A | AE80: 34.57622 | AF80: 61.9379 | AG80: 55.0909 | AH80: 63.3227 | AI80: 58.825 | AJ80: 58.0542 | AK80: 52.1012 | AL80: 51.093 | AM80: 52.1212 | AN80: 53.0359 | AO80: 56.0219 | AP80: 49.974 | AQ80: 54.5163 | AR80: 51.5972 | AS80: 49.7642 | AT80: 1.1617 | AU80: 53.7674 | AV80: 52.0502 | AW80: 61.7518 | AX80: 59.2996 | AY80: #N/A | AZ80: 51.5536 | BA80: 10857.03 | BB80: =IF(ISNUMBER(VLOOKUP($B80,CEIC_DATA!$I$26:$N$353,Haver_M!BB$2,FALSE)),VLOOKUP($B80,CEIC_DATA!$I$26:$N$353,Haver_M!BB$2,FALSE),NA()) -> 106.30198 | BC80: =IF(ISNUMBER(VLOOKUP($B80,CEIC_DATA!$I$26:$N$353,Haver_M!BC$2,FALSE)),VLOOKUP($B80,CEIC_DATA!$I$26:$N$353,Haver_M!BC$2,FALSE),NA()) -> 120.7 | BD80: =IF(ISNUMBER(VLOOKUP($B80,CEIC_DATA!$I$26:$N$353,Haver_M!BD$2,FALSE)),VLOOKUP($B80,CEIC_DATA!$I$26:$N$353,Haver_M!BD$2,FALSE),NA()) -> 125.7 | BE80: =IF(ISNUMBER(VLOOKUP($B80,CEIC_DATA!$I$26:$N$353,Haver_M!BE$2,FALSE)),VLOOKUP($B80,CEIC_DATA!$I$26:$N$353,Haver_M!BE$2,FALSE),NA()) -> 49.8 | BF80: 693952 | BG80: 48850 | BH80: 944096 | BI80: 156757 | BJ80: #N/A | BK80: #N/A | BL80: #N/A | BM80: #N/A | BN80: 11561 | BO80: 14314 | BP80: 44.481 | BQ80: =IF(ISNUMBER(BJ80),BJ80/$BP80,"") | BR80: =IF(ISNUMBER(BK80),BK80/$BP80,"") | BS80: =IF(ISNUMBER(BL80),BL80/$BP80,"") | BT80: =IF(ISNUMBER(BM80),BM80/$BP80,"") | BU80: 16620
A81: 0604 | B81: 38837 | C81: 6.5 | D81: 7.3941 | E81: 93.55525 | F81: 59.2 | G81: #N/A | H81: 69.08 | I81: 73.64 | J81: 57.35 | K81: 81.59 | L81: #N/A | M81: 44.41 | N81: 69.91 | O81: 75.1 | P81: 78.726 | Q81: 87.006 | R81: 69.633 | S81: 80.972 | T81: 98.93 | U81: 66.3 | V81: 67.471 | W81: 72.911 | X81: 9723.7208 | Y81: 8948.24 | Z81: 13213.4 | AA81: #N/A | AB81: #N/A | AC81: #N/A | AD81: #N/A | AE81: 30.910233 | AF81: 62.9058 | AG81: 56.7617 | AH81: 63.4648 | AI81: 61.6492 | AJ81: 61.7801 | AK81: 52.3622 | AL81: 52.356 | AM81: 51.9634 | AN81: 57.1998 | AO81: 57.3298 | AP81: 48.9342 | AQ81: 55.1651 | AR81: 53.6649 | AS81: 50 | AT81: 1.2625 | AU81: 55.2264 | AV81: 52.8841 | AW81: 61.7804 | AX81: 57.4054 | AY81: #N/A | AZ81: 51.8578 | BA81: 11724.05 | BB81: =IF(ISNUMBER(VLOOKUP($B81,CEIC_DATA!$I$26:$N$353,Haver_M!BB$2,FALSE)),VLOOKUP($B81,CEIC_DATA!$I$26:$N$353,Haver_M!BB$2,FALSE),NA()) -> 106.65595 | BC81: =IF(ISNUMBER(VLOOKUP($B81,CEIC_DATA!$I$26:$N$353,Haver_M!BC$2,FALSE)),VLOOKUP($B81,CEIC_DATA!$I$26:$N$353,Haver_M!BC$2,FALSE),NA()) -> #N/A | BD81: =IF(ISNUMBER(VLOOKUP($B81,CEIC_DATA!$I$26:$N$353,Haver_M!BD$2,FALSE)),VLOOKUP($B81,CEIC_DATA!$I$26:$N$353,Haver_M!BD$2,FALSE),NA()) -> #N/A | BE81: =IF(ISNUMBER(VLOOKUP($B81,CEIC_DATA!$I$26:$N$353,Haver_M!BE$2,FALSE)),VLOOKUP($B81,CEIC_DATA!$I$26:$N$353,Haver_M!BE$2,FALSE),NA()) -> #N/A | BF81: 654445 | BG81: 31814 | BH81: 832745 | BI81: 110615 | BJ81: #N/A | BK81: #N/A | BL81: #N/A | BM81: #N/A | BN81: 8625 | BO81: 12924.5 | BP81: 44.9491 | BQ81: =IF(ISNUMBER(BJ81),BJ81/$BP81,"") | BR81: =IF(ISNUMBER(BK81),BK81/$BP81,"") | BS81: =IF(ISNUMBER(BL81),BL81/$BP81,"") | BT81: =IF(ISNUMBER(BM81),BM81/$BP81,"") | BU81: 22819
A82: 0605 | B82: 38868 | C82: 6.5 | D82: 7.6809 | E82: 91.36872 | F82: 59.9 | G82: #N/A | H82: 69.94 | I82: 73.99 | J82: 56.83 | K82: 83.59 | L82: #N/A | M82: 43.44 | N82: 77.63 | O82: 75.6 | P82: 80.049 | Q82: 88.954 | R82: 68.877 | S82: 82.628 | T82: 96.372 | U82: 65.379 | V82: 66.749 | W82: 72.865 | X82: 10363.178 | Y82: 10003.85 | Z82: 13955.35 | AA82: #N/A | AB82: #N/A | AC82: #N/A | AD82: #N/A | AE82: 42.972172 | AF82: 63.8177 | AG82: 57.7181 | AH82: 64.7094 | AI82: 61.8132 | AJ82: 63.5501 | AK82: 52.0604 | AL82: 49.4521 | AM82: 52.0548 | AN82: 60.0431 | AO82: 59.1781 | AP82: 50 | AQ82: 56.3471 | AR82: 57.2802 | AS82: 51.6272 | AT82: 1.271 | AU82: 54.1045 | AV82: 52.5588 | AW82: 62.4264 | AX82: 57.2055 | AY82: #N/A | AZ82: 51.0965 | BA82: 11599.16 | BB82: =IF(ISNUMBER(VLOOKUP($B82,CEIC_DATA!$I$26:$N$353,Haver_M!BB$2,FALSE)),VLOOKUP($B82,CEIC_DATA!$I$26:$N$353,Haver_M!BB$2,FALSE),NA()) -> 106.47691 | BC82: =IF(ISNUMBER(VLOOKUP($B82,CEIC_DATA!$I$26:$N$353,Haver_M!BC$2,FALSE)),VLOOKUP($B82,CEIC_DATA!$I$26:$N$353,Haver_M!BC$2,FALSE),NA()) -> #N/A | BD82: =IF(ISNUMBER(VLOOKUP($B82,CEIC_DATA!$I$26:$N$353,Haver_M!BD$2,FALSE)),VLOOKUP($B82,CEIC_DATA!$I$26:$N$353,Haver_M!BD$2,FALSE),NA()) -> #N/A | BE82: =IF(ISNUMBER(VLOOKUP($B82,CEIC_DATA!$I$26:$N$353,Haver_M!BE$2,FALSE)),VLOOKUP($B82,CEIC_DATA!$I$26:$N$353,Haver_M!BE$2,FALSE),NA()) -> #N/A | BF82: 725780 | BG82: 36285 | BH82: 928946 | BI82: 126768 | BJ82: #N/A | BK82: #N/A | BL82: #N/A | BM82: #N/A | BN82: 10109.7 | BO82: 15106 | BP82: 45.4073 | BQ82: =IF(ISNUMBER(BJ82),BJ82/$BP82,"") | BR82: =IF(ISNUMBER(BK82),BK82/$BP82,"") | BS82: =IF(ISNUMBER(BL82),BL82/$BP82,"") | BT82: =IF(ISNUMBER(BM82),BM82/$BP82,"") | BU82: 22298
A83: 0606 | B83: 38898 | C83: 6.75 | D83: 8.1318 | E83: 91.61521 | F83: 60.8 | G83: #N/A | H83: 70.11 | I83: 74.18 | J83: 57.01 | K83: 84.14 | L83: #N/A | M83: 42.73 | N83: 81.22 | O83: 76.7 | P83: 81.087 | Q83: 90.413 | R83: 70.48 | S83: 83.688 | T83: 91.602 | U83: 67.281 | V83: 68.817 | W83: 73.803 | X83: 9759.609 | Y83: 10375.59 | Z83: 14380.4 | AA83: #N/A | AB83: #N/A | AC83: #N/A | AD83: #N/A | AE83: 55.735614 | AF83: 61.862 | AG83: 56.8163 | AH83: 62.294 | AI83: 60.8911 | AJ83: 62.1287 | AK83: 51.8564 | AL83: 51.2438 | AM83: 52.7017 | AN83: 59.1285 | AO83: 56.6832 | AP83: 49.125 | AQ83: 56.209 | AR83: 55.0712 | AS83: 51.005 | AT83: 1.2647 | AU83: 53.1337 | AV83: 52.2999 | AW83: 60.2859 | AX83: 55.9851 | AY83: #N/A | AZ83: 49.9679 | BA83: 9913.01 | BB83: =IF(ISNUMBER(VLOOKUP($B83,CEIC_DATA!$I$26:$N$353,Haver_M!BB$2,FALSE)),VLOOKUP($B83,CEIC_DATA!$I$26:$N$353,Haver_M!BB$2,FALSE),NA()) -> 106.16288 | BC83: =IF(ISNUMBER(VLOOKUP($B83,CEIC_DATA!$I$26:$N$353,Haver_M!BC$2,FALSE)),VLOOKUP($B83,CEIC_DATA!$I$26:$N$353,Haver_M!BC$2,FALSE),NA()) -> 121.8 | BD83: =IF(ISNUMBER(VLOOKUP($B83,CEIC_DATA!$I$26:$N$353,Haver_M!BD$2,FALSE)),VLOOKUP($B83,CEIC_DATA!$I$26:$N$353,Haver_M!BD$2,FALSE),NA()) -> 120.5 | BE83: =IF(ISNUMBER(VLOOKUP($B83,CEIC_DATA!$I$26:$N$353,Haver_M!BE$2,FALSE)),VLOOKUP($B83,CEIC_DATA!$I$26:$N$353,Haver_M!BE$2,FALSE),NA()) -> 46.3 | BF83: 690723 | BG83: 38045 | BH83: 893468 | BI83: 121782 | BJ83: #N/A | BK83: #N/A | BL83: #N/A | BM83: #N/A | BN83: 10420 | BO83: 14400.1 | BP83: 46.0561 | BQ83: =IF(ISNUMBER(BJ83),BJ83/$BP83,"") | BR83: =IF(ISNUMBER(BK83),BK83/$BP83,"") | BS83: =IF(ISNUMBER(BL83),BL83/$BP83,"") | BT83: =IF(ISNUMBER(BM83),BM83/$BP83,"") | BU83: 20513
A84: 0607 | B84: 38929 | C84: 7 | D84: 8.2809 | E84: 90.67149 | F84: 61.1 | G84: #N/A | H84: 72.63 | I84: 74.97 | J84: 60 | K84: 84.46 | L84: #N/A | M84: 49.12 | N84: 81.03 | O84: 77 | P84: 81.529 | Q84: 89.292 | R84: 69.717 | S84: 86.69 | T84: 95.868 | U84: 67.527 | V84: 67.994 | W84: 74.541 | X84: 9635.9663 | Y84: 10647.29 | Z84: 14678.36 | AA84: #N/A | AB84: #N/A | AC84: #N/A | AD84: #N/A | AE84: 63.438783 | AF84: 59.9209 | AG84: 55.808 | AH84: 60.1808 | AI84: 59.3366 | AJ84: 60.1716 | AK84: 52.2113 | AL84: 51.3614 | AM84: 51.8428 | AN84: 55.2552 | AO84: 56.2605 | AP84: 49.8765 | AQ84: 54.7532 | AR84: 53.9828 | AS84: 51.3587 | AT84: 1.2064 | AU84: 53.8608 | AV84: 51.9309 | AW84: 59.6358 | AX84: 55.8015 | AY84: #N/A | AZ84: 49.8247 | BA84: 10557.15 | BB84: =IF(ISNUMBER(VLOOKUP($B84,CEIC_DATA!$I$26:$N$353,Haver_M!BB$2,FALSE)),VLOOKUP($B84,CEIC_DATA!$I$26:$N$353,Haver_M!BB$2,FALSE),NA()) -> 105.99648 | BC84: =IF(ISNUMBER(VLOOKUP($B84,CEIC_DATA!$I$26:$N$353,Haver_M!BC$2,FALSE)),VLOOKUP($B84,CEIC_DATA!$I$26:$N$353,Haver_M!BC$2,FALSE),NA()) -> #N/A | BD84: =IF(ISNUMBER(VLOOKUP($B84,CEIC_DATA!$I$26:$N$353,Haver_M!BD$2,FALSE)),VLOOKUP($B84,CEIC_DATA!$I$26:$N$353,Haver_M!BD$2,FALSE),NA()) -> #N/A | BE84: =IF(ISNUMBER(VLOOKUP($B84,CEIC_DATA!$I$26:$N$353,Haver_M!BE$2,FALSE)),VLOOKUP($B84,CEIC_DATA!$I$26:$N$353,Haver_M!BE$2,FALSE),NA()) -> #N/A | BF84: 622659 | BG84: 36814 | BH84: 824544 | BI84: 119111 | BJ84: #N/A | BK84: #N/A | BL84: #N/A | BM84: #N/A | BN84: 10600.1 | BO84: 14985.4 | BP84: 46.4562 | BQ84: =IF(ISNUMBER(BJ84),BJ84/$BP84,"") | BR84: =IF(ISNUMBER(BK84),BK84/$BP84,"") | BS84: =IF(ISNUMBER(BL84),BL84/$BP84,"") | BT84: =IF(ISNUMBER(BM84),BM84/$BP84,"") | BU84: 17109
A85: 0608 | B85: 38960 | C85: 7 | D85: 7.9304 | E85: 90.4178 | F85: 61.5 | G85: #N/A | H85: 71.41 | I85: 73.6 | J85: 60.4 | K85: 84.11 | L85: #N/A | M85: 45.72 | N85: 81.29 | O85: 75.1 | P85: 78.088 | Q85: 85.057 | R85: 50.502 | S85: 85.89 | T85: 92.909 | U85: 67.13 | V85: 65.86 | W85: 74.093 | X85: 9894.0619 | Y85: 10785.83 | Z85: 15090.39 | AA85: #N/A | AB85: #N/A | AC85: #N/A | AD85: #N/A | AE85: 62.206026 | AF85: 61.4543 | AG85: 57.8743 | AH85: 61.2709 | AI85: 61.8667 | AJ85: 63.0667 | AK85: 51.8667 | AL85: 49.1935 | AM85: 54.9333 | AN85: 60.381 | AO85: 59.6515 | AP85: 49.8458 | AQ85: 57.8189 | AR85: 55.8824 | AS85: 52.057 | AT85: 1.2652 | AU85: 53.9892 | AV85: 51.0885 | AW85: 59.7535 | AX85: 53.8491 | AY85: #N/A | AZ85: 49.6561 | BA85: 11305.04 | BB85: =IF(ISNUMBER(VLOOKUP($B85,CEIC_DATA!$I$26:$N$353,Haver_M!BB$2,FALSE)),VLOOKUP($B85,CEIC_DATA!$I$26:$N$353,Haver_M!BB$2,FALSE),NA()) -> 106.19775 | BC85: =IF(ISNUMBER(VLOOKUP($B85,CEIC_DATA!$I$26:$N$353,Haver_M!BC$2,FALSE)),VLOOKUP($B85,CEIC_DATA!$I$26:$N$353,Haver_M!BC$2,FALSE),NA()) -> #N/A | BD85: =IF(ISNUMBER(VLOOKUP($B85,CEIC_DATA!$I$26:$N$353,Haver_M!BD$2,FALSE)),VLOOKUP($B85,CEIC_DATA!$I$26:$N$353,Haver_M!BD$2,FALSE),NA()) -> #N/A | BE85: =IF(ISNUMBER(VLOOKUP($B85,CEIC_DATA!$I$26:$N$353,Haver_M!BE$2,FALSE)),VLOOKUP($B85,CEIC_DATA!$I$26:$N$353,Haver_M!BE$2,FALSE),NA()) -> #N/A | BF85: 627645 | BG85: 39511 | BH85: 838914 | BI85: 126370 | BJ85: #N/A | BK85: #N/A | BL85: #N/A | BM85: #N/A | BN85: 10769.5 | BO85: 15326.7 | BP85: 46.5391 | BQ85: =IF(ISNUMBER(BJ85),BJ85/$BP85,"") | BR85: =IF(ISNUMBER(BK85),BK85/$BP85,"") | BS85: =IF(ISNUMBER(BL85),BL85/$BP85,"") | BT85: =IF(ISNUMBER(BM85),BM85/$BP85,"") | BU85: 15481
A86: 0609 | B86: 38990 | C86: 7 | D86: 7.6776 | E86: 92.51013 | F86: 61.9 | G86: #N/A | H86: 72.65 | I86: 76.23 | J86: 60.51 | K86: 87.33 | L86: #N/A | M86: 46.61 | N86: 83.43 | O86: 77.8 | P86: 77.684 | Q86: 90.193 | R86: 66.333 | S86: 87.069 | T86: 100.395 | U86: 67.465 | V86: 71.653 | W86: 76.053 | X86: 10124.54 | Y86: 10773.06 | Z86: 16143.56 | AA86: #N/A | AB86: #N/A | AC86: #N/A | AD86: #N/A | AE86: 49.955157 | AF86: 63.6112 | AG86: 59.0018 | AH86: 63.5165 | AI86: 63.8243 | AJ86: 65.1651 | AK86: 51.7995 | AL86: 49.1003 | AM86: 55.0129 | AN86: 61.1825 | AO86: 61.9201 | AP86: 51.2853 | AQ86: 57.6577 | AR86: 54.4987 | AS86: 52.0485 | AT86: 1.2706 | AU86: 54.4985 | AV86: 51.2665 | AW86: 61.067 | AX86: 54.2089 | AY86: #N/A | AZ86: 51.8488 | BA86: 12035.69 | BB86: =IF(ISNUMBER(VLOOKUP($B86,CEIC_DATA!$I$26:$N$353,Haver_M!BB$2,FALSE)),VLOOKUP($B86,CEIC_DATA!$I$26:$N$353,Haver_M!BB$2,FALSE),NA()) -> 106.70634 | BC86: =IF(ISNUMBER(VLOOKUP($B86,CEIC_DATA!$I$26:$N$353,Haver_M!BC$2,FALSE)),VLOOKUP($B86,CEIC_DATA!$I$26:$N$353,Haver_M!BC$2,FALSE),NA()) -> 120.7 | BD86: =IF(ISNUMBER(VLOOKUP($B86,CEIC_DATA!$I$26:$N$353,Haver_M!BD$2,FALSE)),VLOOKUP($B86,CEIC_DATA!$I$26:$N$353,Haver_M!BD$2,FALSE),NA()) -> 126.5 | BE86: =IF(ISNUMBER(VLOOKUP($B86,CEIC_DATA!$I$26:$N$353,Haver_M!BE$2,FALSE)),VLOOKUP($B86,CEIC_DATA!$I$26:$N$353,Haver_M!BE$2,FALSE),NA()) -> 53.1 | BF86: 839455 | BG86: 46840 | BH86: 1073751 | BI86: 138509 | BJ86: #N/A | BK86: #N/A | BL86: #N/A | BM86: #N/A | BN86: 10756.9 | BO86: 17351.1 | BP86: 46.121 | BQ86: =IF(ISNUMBER(BJ86),BJ86/$BP86,"") | BR86: =IF(ISNUMBER(BK86),BK86/$BP86,"") | BS86: =IF(ISNUMBER(BL86),BL86/$BP86,"") | BT86: =IF(ISNUMBER(BM86),BM86/$BP86,"") | BU86: 12607
A87: 0610 | B87: 39021 | C87: 7.25 | D87: 7.6417 | E87: 95.03769 | F87: 62.7 | G87: #N/A | H87: 73.31 | I87: 76.64 | J87: 58.26 | K87: 87.25 | L87: #N/A | M87: 48.99 | N87: 80.71 | O87: 78.6 | P87: 79.645 | Q87: 90.167 | R87: 68.352 | S87: 87.547 | T87: 96.939 | U87: 69.368 | V87: 70.379 | W87: 76.85 | X87: 9828.4122 | Y87: 10383.27 | Z87: 16953.72 | AA87: #N/A | AB87: #N/A | AC87: #N/A | AD87: #N/A | AE87: 30.607638 | AF87: 63.1233 | AG87: 59.3046 | AH87: 62.4608 | AI87: 64.6127 | AJ87: 66.2852 | AK87: 51.5845 | AL87: 50.8803 | AM87: 55.8099 | AN87: 56.7138 | AO87: 62.6761 | AP87: 51.2237 | AQ87: 59.1953 | AR87: 54.2254 | AS87: 52.6795 | AT87: 1.294 | AU87: 54.4365 | AV87: 53.671 | AW87: 60.6154 | AX87: 56.2681 | AY87: #N/A | AZ87: 51.677 | BA87: 12632.01 | BB87: =IF(ISNUMBER(VLOOKUP($B87,CEIC_DATA!$I$26:$N$353,Haver_M!BB$2,FALSE)),VLOOKUP($B87,CEIC_DATA!$I$26:$N$353,Haver_M!BB$2,FALSE),NA()) -> 107.32961 | BC87: =IF(ISNUMBER(VLOOKUP($B87,CEIC_DATA!$I$26:$N$353,Haver_M!BC$2,FALSE)),VLOOKUP($B87,CEIC_DATA!$I$26:$N$353,Haver_M!BC$2,FALSE),NA()) -> #N/A | BD87: =IF(ISNUMBER(VLOOKUP($B87,CEIC_DATA!$I$26:$N$353,Haver_M!BD$2,FALSE)),VLOOKUP($B87,CEIC_DATA!$I$26:$N$353,Haver_M!BD$2,FALSE),NA()) -> #N/A | BE87: =IF(ISNUMBER(VLOOKUP($B87,CEIC_DATA!$I$26:$N$353,Haver_M!BE$2,FALSE)),VLOOKUP($B87,CEIC_DATA!$I$26:$N$353,Haver_M!BE$2,FALSE),NA()) -> #N/A | BF87: 875648 | BG87: 43070 | BH87: 1101474 | BI87: 133778 | BJ87: #N/A | BK87: #N/A | BL87: #N/A | BM87: #N/A | BN87: 9928.6 | BO87: 17512.4 | BP87: 45.4684 | BQ87: =IF(ISNUMBER(BJ87),BJ87/$BP87,"") | BR87: =IF(ISNUMBER(BK87),BK87/$BP87,"") | BS87: =IF(ISNUMBER(BL87),BL87/$BP87,"") | BT87: =IF(ISNUMBER(BM87),BM87/$BP87,"") | BU87: 18649
A88: 0611 | B88: 39051 | C88: 7.25 | D88: 7.4061 | E88: 95.20263 | F88: 62.7 | G88: #N/A | H88: 77.4 | I88: 78.03 | J88: 66.77 | K88: 89.4 | L88: #N/A | M88: 53.22 | N88: 88.52 | O88: 79.4 | P88: 79.361 | Q88: 90.49 | R88: 68.268 | S88: 89.883 | T88: 95.1 | U88: 71.667 | V88: 70.544 | W88: 76.116 | X88: 10402.859 | Y88: 10889 | Z88: 16766.01 | AA88: #N/A | AB88: #N/A | AC88: #N/A | AD88: #N/A | AE88: 98.684171 | AF88: 63.6577 | AG88: 58.9428 | AH88: 63.5617 | AI88: 63.8736 | AJ88: 65.5008 | AK88: 51.3736 | AL88: 50 | AM88: 55.4945 | AN88: 58.9286 | AO88: 61.9505 | AP88: 52.0718 | AQ88: 58.39 | AR88: 52.0604 | AS88: 51.0542 | AT88: 1.2579 | AU88: 54.3309 | AV88: 54.0817 | AW88: 61.2466 | AX88: 58.5282 | AY88: #N/A | AZ88: 53.5212 | BA88: 13415.79 | BB88: =IF(ISNUMBER(VLOOKUP($B88,CEIC_DATA!$I$26:$N$353,Haver_M!BB$2,FALSE)),VLOOKUP($B88,CEIC_DATA!$I$26:$N$353,Haver_M!BB$2,FALSE),NA()) -> 107.81844 | BC88: =IF(ISNUMBER(VLOOKUP($B88,CEIC_DATA!$I$26:$N$353,Haver_M!BC$2,FALSE)),VLOOKUP($B88,CEIC_DATA!$I$26:$N$353,Haver_M!BC$2,FALSE),NA()) -> #N/A | BD88: =IF(ISNUMBER(VLOOKUP($B88,CEIC_DATA!$I$26:$N$353,Haver_M!BD$2,FALSE)),VLOOKUP($B88,CEIC_DATA!$I$26:$N$353,Haver_M!BD$2,FALSE),NA()) -> #N/A | BE88: =IF(ISNUMBER(VLOOKUP($B88,CEIC_DATA!$I$26:$N$353,Haver_M!BE$2,FALSE)),VLOOKUP($B88,CEIC_DATA!$I$26:$N$353,Haver_M!BE$2,FALSE),NA()) -> #N/A | BF88: 726105 | BG88: 44186 | BH88: 944652 | BI88: 125699 | BJ88: #N/A | BK88: #N/A | BL88: #N/A | BM88: #N/A | BN88: 9979.4 | BO88: 16381.2 | BP88: 44.8305 | BQ88: =IF(ISNUMBER(BJ88),BJ88/$BP88,"") | BR88: =IF(ISNUMBER(BK88),BK88/$BP88,"") | BS88: =IF(ISNUMBER(BL88),BL88/$BP88,"") | BT88: =IF(ISNUMBER(BM88),BM88/$BP88,"") | BU88: 17764
... A92: 0703 | B92: 39172 | C92: 7.5 | D92: 7.936 | E92: 94.69775 | F92: 62.6 | G92: #N/A | H92: 80.03 | I92: 80.53 | J92: 71.57 | K92: 90.86 | L92: #N/A | M92: 54.33 | N92: 96.21 | O92: 81.3 | P92: 82.849 | Q92: 89.346 | R92: 68.651 | S92: 92.442 | T92: 101.329 | U92: 75.423 | V92: 71.165 | W92: 77.67 | X92: 10358.063 | Y92: 10839.41 | Z92: 17346.83 | AA92: #N/A | AB92: #N/A | AC92: #N/A | AD92: #N/A | AE92: 50.917292 | AF92: 55.3764 | AG92: 53.0036 | AH92: 55.9128 | AI92: 54.1706 | AJ92: 56.0535 | AK92: 50.574 | AL92: 50.5094 | AM92: 51.0652 | AN92: 53.9196 | AO92: 53.0036 | AP92: 49.7827 | AQ92: 51.5466 | AR92: 50.3974 | AS92: 49.9668 | AT92: 1.126 | AU92: 52.0367 | AV92: 52.8175 | AW92: 55.8201 | AX92: 55.3207 | AY92: #N/A | AZ92: 52.7618 | BA92: 12857.74 | BB92: =IF(ISNUMBER(VLOOKUP($B92,CEIC_DATA!$I$26:$N$353,Haver_M!BB$2,FALSE)),VLOOKUP($B92,CEIC_DATA!$I$26:$N$353,Haver_M!BB$2,FALSE),NA()) -> 105.75548 | BC92: =IF(ISNUMBER(VLOOKUP($B92,CEIC_DATA!$I$26:$N$353,Haver_M!BC$2,FALSE)),VLOOKUP($B92,CEIC_DATA!$I$26:$N$353,Haver_M!BC$2,FALSE),NA()) -> 127.7 | BD92: =IF(ISNUMBER(VLOOKUP($B92,CEIC_DATA!$I$26:$N$353,Haver_M!BD$2,FALSE)),VLOOKUP($B92,CEIC_DATA!$I$26:$N$353,Haver_M!BD$2,FALSE),NA()) -> 126.5 | BE92: =IF(ISNUMBER(VLOOKUP($B92,CEIC_DATA!$I$26:$N$353,Haver_M!BE$2,FALSE)),VLOOKUP($B92,CEIC_DATA!$I$26:$N$353,Haver_M!BE$2,FALSE),NA()) -> 53.7 | BF92: 685554 | BG92: 55256 | BH92: 953830 | BI92: 168247 | BJ92: #N/A | BK92: #N/A | BL92: #N/A | BM92: #N/A | BN92: 12862.4 | BO92: 17136.6 | BP92: 44.0255 | BQ92: =IF(ISNUMBER(BJ92),BJ92/$BP92,"") | BR92: =IF(ISNUMBER(BK92),BK92/$BP92,"") | BS92: =IF(ISNUMBER(BL92),BL92/$BP92,"") | BT92: =IF(ISNUMBER(BM92),BM92/$BP92,"") | BU92: 17792
A93: 0704 | B93: 39202 | C93: 7.75 | D93: 8.1316 | E93: 98.19825 | F93: 63.2 | G93: #N/A | H93: 80.91 | I93: 81.92 | J93: 66.66 | K93: 90.89 | L93: #N/A | M93: 54.5 | N93: 93.6 | O93: 80 | P93: 79.287 | Q93: 88.581 | R93: 66.105 | S93: 92.936 | T93: 92.569 | U93: 71.983 | V93: 71.573 | W93: 79.08 | X93: 10400.931 | Y93: 11552.89 | Z93: 18433.05 | AA93: #N/A | AB93: #N/A | AC93: #N/A | AD93: #N/A | AE93: 62.706767 | AF93: 55.4974 | AG93: 53.8148 | AH93: 55.5796 | AI93: 55.3127 | AJ93: 57.2198 | AK93: 50.0738 | AL93: 49.6975 | AM93: 52.6054 | AN93: 52.6973 | AO93: 55.9202 | AP93: 49.3165 | AQ93: 51.1786 | AR93: 50.9232 | AS93: 50.3895 | AT93: 1.1603 | AU93: 51.6541 | AV93: 51.0687 | AW93: 54.7743 | AX93: 52.7195 | AY93: #N/A | AZ93: 50 | BA93: 13477.79 | BB93: =IF(ISNUMBER(VLOOKUP($B93,CEIC_DATA!$I$26:$N$353,Haver_M!BB$2,FALSE)),VLOOKUP($B93,CEIC_DATA!$I$26:$N$353,Haver_M!BB$2,FALSE),NA()) -> 104.65298 | BC93: =IF(ISNUMBER(VLOOKUP($B93,CEIC_DATA!$I$26:$N$353,Haver_M!BC$2,FALSE)),VLOOKUP($B93,CEIC_DATA!$I$26:$N$353,Haver_M!BC$2,FALSE),NA()) -> #N/A | BD93: =IF(ISNUMBER(VLOOKUP($B93,CEIC_DATA!$I$26:$N$353,Haver_M!BD$2,FALSE)),VLOOKUP($B93,CEIC_DATA!$I$26:$N$353,Haver_M!BD$2,FALSE),NA()) -> #N/A | BE93: =IF(ISNUMBER(VLOOKUP($B93,CEIC_DATA!$I$26:$N$353,Haver_M!BE$2,FALSE)),VLOOKUP($B93,CEIC_DATA!$I$26:$N$353,Haver_M!BE$2,FALSE),NA()) -> #N/A | BF93: 628372 | BG93: 34872 | BH93: 824636 | BI93: 121521 | BJ93: 4675.59 | BK93: 6656.94 | BL93: 4004.91 | BM93: 17560.51 | BN93: 11326.8 | BO93: 18370.6 | BP93: 42.1511 | BQ93: =IF(ISNUMBER(BJ93),BJ93/$BP93,"") -> 110.92451 | BR93: =IF(ISNUMBER(BK93),BK93/$BP93,"") -> 157.9304 | BS93: =IF(ISNUMBER(BL93),BL93/$BP93,"") -> 95.013179 | BT93: =IF(ISNUMBER(BM93),BM93/$BP93,"") -> 416.60858 | BU93: 25109
A94: 0705 | B94: 39233 | C94: 7.75 | D94: 8.1225 | E94: 100.97962 | F94: 63.6 | G94: #N/A | H94: 83.28 | I94: 82.47 | J94: 88.8 | K94: 92.13 | L94: #N/A | M94: 58.33 | N94: 91.92 | O94: 81 | P94: 80.728 | Q94: 87.942 | R94: 65.878 | S94: 94.892 | T94: 84.927 | U94: 72.579 | V94: 73.631 | W94: 79.781 | X94: 10485.027 | Y94: 12313.82 | Z94: 19608.22 | AA94: #N/A | AB94: #N/A | AC94: #N/A | AD94: #N/A | AE94: 39.191643 | AF94: 55.2132 | AG94: 53.3721 | AH94: 55.3549 | AI94: 54.8945 | AJ94: 56.1901 | AK94: 50.4756 | AL94: 50 | AM94: 51.9631 | AN94: 52.4964 | AO94: 54.9893 | AP94: 49.8664 | AQ94: 51.6536 | AR94: 50.5324 | AS94: 50.2703 | AT94: 1.1268 | AU94: 51.0782 | AV94: 50.519 | AW94: 54.7402 | AX94: 51.3196 | AY94: #N/A | AZ94: 49.9086 | BA94: 14156.47 | BB94: =IF(ISNUMBER(VLOOKUP($B94,CEIC_DATA!$I$26:$N$353,Haver_M!BB$2,FALSE)),VLOOKUP($B94,CEIC_DATA!$I$26:$N$353,Haver_M!BB$2,FALSE),NA()) -> 103.64231 | BC94: =IF(ISNUMBER(VLOOKUP($B94,CEIC_DATA!$I$26:$N$353,Haver_M!BC$2,FALSE)),VLOOKUP($B94,CEIC_DATA!$I$26:$N$353,Haver_M!BC$2,FALSE),NA()) -> #N/A | BD94: =IF(ISNUMBER(VLOOKUP($B94,CEIC_DATA!$I$26:$N$353,Haver_M!BD$2,FALSE)),VLOOKUP($B94,CEIC_DATA!$I$26:$N$353,Haver_M!BD$2,FALSE),NA()) -> #N/A | BE94: =IF(ISNUMBER(VLOOKUP($B94,CEIC_DATA!$I$26:$N$353,Haver_M!BE$2,FALSE)),VLOOKUP($B94,CEIC_DATA!$I$26:$N$353,Haver_M!BE$2,FALSE),NA()) -> #N/A | BF94: 670088 | BG94: 37278 | BH94: 885518 | BI94: 136812 | BJ94: 4670.3 | BK94: 6632.38 | BL94: 4027.19 | BM94: 17544.79 | BN94: 12455.7 | BO94: 21149.5 | BP94: 40.7795 | BQ94: =IF(ISNUMBER(BJ94),BJ94/$BP94,"") -> 114.52568 | BR94: =IF(ISNUMBER(BK94),BK94/$BP94,"") -> 162.64005 | BS94: =IF(ISNUMBER(BL94),BL94/$BP94,"") -> 98.755257 | BT94: =IF(ISNUMBER(BM94),BM94/$BP94,"") -> 430.23554 | BU94: 25927
A95: 0706 | B95: 39263 | C95: 7.75 | D95: 8.1559 | E95: 101.15402 | F95: 64.1 | G95: #N/A | H95: 83.83 | I95: 82.53 | J95: 91.38 | K95: 91.32 | L95: #N/A | M95: 61.6 | N95: 91.82 | O95: 80.4 | P95: 81.912 | Q95: 88.745 | R95: 66.984 | S95: 92.099 | T95: 92.224 | U95: 70.943 | V95: 72.852 | W95: 78.991 | X95: 10491.318 | Y95: 11852.08 | Z95: 19838.86 | AA95: #N/A | AB95: #N/A | AC95: #N/A | AD95: #N/A | AE95: 28.370945 | AF95: 55.8102 | AG95: 53.2389 | AH95: 56.3364 | AI95: 54.6272 | AJ95: 55.8055 | AK95: 50.8 | AL95: 49.5262 | AM95: 51.0935 | AN95: 52.4125 | AO95: 54.7558 | AP95: 50.542 | AQ95: 51.5154 | AR95: 50.6702 | AS95: 50.2386 | AT95: 1.1041 | AU95: 52.2884 | AV95: 50.1786 | AW95: 56.588 | AX95: 50.4305 | AY95: #N/A | AZ95: 50 | BA95: 14334.3 | BB95: =IF(ISNUMBER(VLOOKUP($B95,CEIC_DATA!$I$26:$N$353,Haver_M!BB$2,FALSE)),VLOOKUP($B95,CEIC_DATA!$I$26:$N$353,Haver_M!BB$2,FALSE),NA()) -> 102.81939 | BC95: =IF(ISNUMBER(VLOOKUP($B95,CEIC_DATA!$I$26:$N$353,Haver_M!BC$2,FALSE)),VLOOKUP($B95,CEIC_DATA!$I$26:$N$353,Haver_M!BC$2,FALSE),NA()) -> 115.8 | BD95: =IF(ISNUMBER(VLOOKUP($B95,CEIC_DATA!$I$26:$N$353,Haver_M!BD$2,FALSE)),VLOOKUP($B95,CEIC_DATA!$I$26:$N$353,Haver_M!BD$2,FALSE),NA()) -> 127.5 | BE95: =IF(ISNUMBER(VLOOKUP($B95,CEIC_DATA!$I$26:$N$353,Haver_M!BE$2,FALSE)),VLOOKUP($B95,CEIC_DATA!$I$26:$N$353,Haver_M!BE$2,FALSE),NA()) -> 51.7 | BF95: 635716 | BG95: 40801 | BH95: 854798 | BI95: 137368 | BJ95: 4698.89 | BK95: 6697.57 | BL95: 4072.69 | BM95: 17697.84 | BN95: 12101 | BO95: 20016 | BP95: 40.7719 | BQ95: =IF(ISNUMBER(BJ95),BJ95/$BP95,"") -> 115.24825 | BR95: =IF(ISNUMBER(BK95),BK95/$BP95,"") -> 164.26926 | BS95: =IF(ISNUMBER(BL95),BL95/$BP95,"") -> 99.88963 | BT95: =IF(ISNUMBER(BM95),BM95/$BP95,"") -> 434.06954 | BU95: 23907
A96: 0707 | B96: 39294 | C96: 7.75 | D96: 7.9108 | E96: 100.90424 | F96: 65 | G96: #N/A | H96: 84.13 | I96: 81.07 | J96: 94.85 | K96: 90.78 | L96: #N/A | M96: 61.25 | N96: 93.06 | O96: 80.9 | P96: 82.871 | Q96: 90.291 | R96: 68.361 | S96: 90.794 | T96: 94.459 | U96: 72.924 | V96: 74.266 | W96: 79.735 | X96: 10334.645 | Y96: 12296.08 | Z96: 20256.43 | AA96: #N/A | AB96: #N/A | AC96: #N/A | AD96: #N/A | AE96: 30.139803 | AF96: 57.5954 | AG96: 52.9081 | AH96: 59.1275 | AI96: 54.1512 | AJ96: 55.7334 | AK96: 50.3287 | AL96: 49.8819 | AM96: 50.6684 | AN96: 51.544 | AO96: 54.264 | AP96: 49.6382 | AQ96: 51.2696 | AR96: 51.0751 | AS96: 50.2625 | AT96: 1.1228 | AU96: 53.2631 | AV96: 51.9269 | AW96: 58.7229 | AX96: 54.9459 | AY96: #N/A | AZ96: 50.8474 | BA96: 15253.42 | BB96: =IF(ISNUMBER(VLOOKUP($B96,CEIC_DATA!$I$26:$N$353,Haver_M!BB$2,FALSE)),VLOOKUP($B96,CEIC_DATA!$I$26:$N$353,Haver_M!BB$2,FALSE),NA()) -> 102.42041 | BC96: =IF(ISNUMBER(VLOOKUP($B96,CEIC_DATA!$I$26:$N$353,Haver_M!BC$2,FALSE)),VLOOKUP($B96,CEIC_DATA!$I$26:$N$353,Haver_M!BC$2,FALSE),NA()) -> #N/A | BD96: =IF(ISNUMBER(VLOOKUP($B96,CEIC_DATA!$I$26:$N$353,Haver_M!BD$2,FALSE)),VLOOKUP($B96,CEIC_DATA!$I$26:$N$353,Haver_M!BD$2,FALSE),NA()) -> #N/A | BE96: =IF(ISNUMBER(VLOOKUP($B96,CEIC_DATA!$I$26:$N$353,Haver_M!BE$2,FALSE)),VLOOKUP($B96,CEIC_DATA!$I$26:$N$353,Haver_M!BE$2,FALSE),NA()) -> #N/A | BF96: 576197 | BG96: 37752 | BH96: 790985 | BI96: 135537 | BJ96: 4724.47 | BK96: 6783.6 | BL96: 4077.94 | BM96: 17814.72 | BN96: 12513.3 | BO96: 21128.6 | BP96: 40.415 | BQ96: =IF(ISNUMBER(BJ96),BJ96/$BP96,"") -> 116.89892 | BR96: =IF(ISNUMBER(BK96),BK96/$BP96,"") -> 167.84857 | BS96: =IF(ISNUMBER(BL96),BL96/$BP96,"") -> 100.90165 | BT96: =IF(ISNUMBER(BM96),BM96/$BP96,"") -> 440.79475 | BU96: 21186
A97: 0708 | B97: 39325 | C97: 7.75 | D97: 7.9194 | E97: 100.90303 | F97: 65.2 | G97: #N/A | H97: 84.36 | I97: 83.01 | J97: 88.97 | K97: 92.87 | L97: #N/A | M97: 60.99 | N97: 90.56 | O97: 82.7 | P97: 84.583 | Q97: 90.492 | R97: 68.947 | S97: 92.883 | T97: 90.51 | U97: 75.074 | V97: 76.874 | W97: 80.796 | X97: 10422.613 | Y97: 12610.99 | Z97: 19993.08 | AA97: #N/A | AB97: #N/A | AC97: #N/A | AD97: #N/A | AE97: 51.419738 | AF97: 60.6882 | AG97: 57.9282 | AH97: 60.6965 | AI97: 60.6697 | AJ97: 64.846 | AK97: 51.6506 | AL97: 50.3071 | AM97: 55.2287 | AN97: 57.8165 | AO97: 61.7009 | AP97: 51.3589 | AQ97: 54.9022 | AR97: 52.5729 | AS97: 51.5266 | AT97: 1.2626 | AU97: 54.3031 | AV97: 54.8829 | AW97: 63.8997 | AX97: 60.8356 | AY97: #N/A | AZ97: 53.2388 | BA97: 14779.05 | BB97: =IF(ISNUMBER(VLOOKUP($B97,CEIC_DATA!$I$26:$N$353,Haver_M!BB$2,FALSE)),VLOOKUP($B97,CEIC_DATA!$I$26:$N$353,Haver_M!BB$2,FALSE),NA()) -> 102.5289 | BC97: =IF(ISNUMBER(VLOOKUP($B97,CEIC_DATA!$I$26:$N$353,Haver_M!BC$2,FALSE)),VLOOKUP($B97,CEIC_DATA!$I$26:$N$353,Haver_M!BC$2,FALSE),NA()) -> #N/A | BD97: =IF(ISNUMBER(VLOOKUP($B97,CEIC_DATA!$I$26:$N$353,Haver_M!BD$2,FALSE)),VLOOKUP($B97,CEIC_DATA!$I$26:$N$353,Haver_M!BD$2,FALSE),NA()) -> #N/A | BE97: =IF(ISNUMBER(VLOOKUP($B97,CEIC_DATA!$I$26:$N$353,Haver_M!BE$2,FALSE)),VLOOKUP($B97,CEIC_DATA!$I$26:$N$353,Haver_M!BE$2,FALSE),NA()) -> #N/A | BF97: 619579 | BG97: 41328 | BH97: 850966 | BI97: 146242 | BJ97: 4825.36 | BK97: 7004.14 | BL97: 4256.45 | BM97: 18300.29 | BN97: 12640.6 | BO97: 20365.9 | BP97: 40.8176 | BQ97: =IF(ISNUMBER(BJ97),BJ97/$BP97,"") -> 118.21763 | BR97: =IF(ISNUMBER(BK97),BK97/$BP97,"") -> 171.59608 | BS97: =IF(ISNUMBER(BL97),BL97/$BP97,"") -> 104.27977 | BT97: =IF(ISNUMBER(BM97),BM97/$BP97,"") -> 448.34312 | BU97: 17947
A98: 0709 | B98: 39355 | C98: 7.75 | D98: 7.9155 | E98: 100.39246 | F98: 65.3 | G98: #N/A | H98: 82.54 | I98: 82.8 | J98: 89.2 | K98: 91.81 | L98: #N/A | M98: 56.85 | N98: 89.15 | O98: 81.8 | P98: 82.875 | Q98: 89.094 | R98: 68.652 | S98: 93.43 | T98: 89.08 | U98: 75.266 | V98: 74.748 | W98: 79.502 | X98: 10505.698 | Y98: 12689.39 | Z98: 16957.96 | AA98: #N/A | AB98: #N/A | AC98: #N/A | AD98: #N/A | AE98: 68.066884 | AF98: 61.8765 | AG98: 59.2799 | AH98: 61.4862 | AI98: 62.7539 | AJ98: 66.6208 | AK98: 50.7124 | AL98: 48.0244 | AM98: 56.6634 | AN98: 56.7506 | AO98: 64.0668 | AP98: 51.6167 | AQ98: 56.6284 | AR98: 53.3338 | AS98: 51.7311 | AT98: 1.2907 | AU98: 54.1483 | AV98: 56.3625 | AW98: 64.1576 | AX98: 60.4845 | AY98: #N/A | AZ98: 53.5502 | BA98: 16046.02 | BB98: =IF(ISNUMBER(VLOOKUP($B98,CEIC_DATA!$I$26:$N$353,Haver_M!BB$2,FALSE)),VLOOKUP($B98,CEIC_DATA!$I$26:$N$353,Haver_M!BB$2,FALSE),NA()) -> 103.13131 | BC98: =IF(ISNUMBER(VLOOKUP($B98,CEIC_DATA!$I$26:$N$353,Haver_M!BC$2,FALSE)),VLOOKUP($B98,CEIC_DATA!$I$26:$N$353,Haver_M!BC$2,FALSE),NA()) -> 118.9 | BD98: =IF(ISNUMBER(VLOOKUP($B98,CEIC_DATA!$I$26:$N$353,Haver_M!BD$2,FALSE)),VLOOKUP($B98,CEIC_DATA!$I$26:$N$353,Haver_M!BD$2,FALSE),NA()) -> 121.1 | BE98: =IF(ISNUMBER(VLOOKUP($B98,CEIC_DATA!$I$26:$N$353,Haver_M!BE$2,FALSE)),VLOOKUP($B98,CEIC_DATA!$I$26:$N$353,Haver_M!BE$2,FALSE),NA()) -> 49.5 | BF98: 744875 | BG98: 48050 | BH98: 986927 | BI98: 149212 | BJ98: 4937.9 | BK98: 7282.98 | BL98: 4490.49 | BM98: 19010.57 | BN98: 12521.4 | BO98: 18217.5 | BP98: 40.34 | BQ98: =IF(ISNUMBER(BJ98),BJ98/$BP98,"") -> 122.40704 | BR98: =IF(ISNUMBER(BK98),BK98/$BP98,"") -> 180.53991 | BS98: =IF(ISNUMBER(BL98),BL98/$BP98,"") -> 111.31606 | BT98: =IF(ISNUMBER(BM98),BM98/$BP98,"") -> 471.25855 | BU98: 15610
A99: 0710 | B99: 39386 | C99: 7.75 | D99: 7.8699 | E99: 100.66427 | F99: 65.8 | G99: #N/A | H99: 85.51 | I99: 83.91 | J99: 91.04 | K99: 93.31 | L99: #N/A | M99: 65.82 | N99: 91.09 | O99: 82.7 | P99: 85.378 | Q99: 90.403 | R99: 71.016 | S99: 90.428 | T99: 92.009 | U99: 77.63 | V99: 74.49 | W99: 79.223 | X99: 11055.396 | Y99: 15533.33 | Z99: 21007.74 | AA99: #N/A | AB99: #N/A | AC99: #N/A | AD99: #N/A | AE99: 61.717607 | AF99: 64.3455 | AG99: 61.6573 | AH99: 63.3515 | AI99: 66.5799 | AJ99: 70.8973 | AK99: 51.5909 | AL99: 49.5851 | AM99: 58.6275 | AN99: 54.0878 | AO99: 68.8105 | AP99: 52.2091 | AQ99: 61.03 | AR99: 55.003 | AS99: 52.272 | AT99: 1.358 | AU99: 53.7756 | AV99: 59.9339 | AW99: 63.258 | AX99: 61.0978 | AY99: #N/A | AZ99: 51.9689 | BA99: 18500.31 | BB99: =IF(ISNUMBER(VLOOKUP($B99,CEIC_DATA!$I$26:$N$353,Haver_M!BB$2,FALSE)),VLOOKUP($B99,CEIC_DATA!$I$26:$N$353,Haver_M!BB$2,FALSE),NA()) -> 104.06978 | BC99: =IF(ISNUMBER(VLOOKUP($B99,CEIC_DATA!$I$26:$N$353,Haver_M!BC$2,FALSE)),VLOOKUP($B99,CEIC_DATA!$I$26:$N$353,Haver_M!BC$2,FALSE),NA()) -> #N/A | BD99: =IF(ISNUMBER(VLOOKUP($B99,CEIC_DATA!$I$26:$N$353,Haver_M!BD$2,FALSE)),VLOOKUP($B99,CEIC_DATA!$I$26:$N$353,Haver_M!BD$2,FALSE),NA()) -> #N/A | BE99: =IF(ISNUMBER(VLOOKUP($B99,CEIC_DATA!$I$26:$N$353,Haver_M!BE$2,FALSE)),VLOOKUP($B99,CEIC_DATA!$I$26:$N$353,Haver_M!BE$2,FALSE),NA()) -> #N/A | BF99: 861157 | BG99: 48808 | BH99: 1113290 | BI99: 155235 | BJ99: 4901.25 | BK99: 7260.32 | BL99: 4453.47 | BM99: 18895.3 | BN99: 14674.7 | BO99: 21832.6 | BP99: 39.5132 | BQ99: =IF(ISNUMBER(BJ99),BJ99/$BP99,"") -> 124.04083 | BR99: =IF(ISNUMBER(BK99),BK99/$BP99,"") -> 183.74417 | BS99: =IF(ISNUMBER(BL99),BL99/$BP99,"") -> 112.70841 | BT99: =IF(ISNUMBER(BM99),BM99/$BP99,"") -> 478.20222 | BU99: 19716
A100: 0711 | B100: 39416 | C100: 7.75 | D100: 7.9218 | E100: 98.59133 | F100: 65.9 | G100: #N/A | H100: 87.02 | I100: 84.43 | J100: 98.01 | K100: 93.49 | L100: #N/A | M100: 70.48 | N100: 88.45 | O100: 83.1 | P100: 87.014 | Q100: 89.816 | R100: 70.247 | S100: 94.051 | T100: 91.802 | U100: 74.982 | V100: 76.851 | W100: 81.276 | X100: 10936.467 | Y100: 14061.36 | Z100: 22578.52 | AA100: #N/A | AB100: #N/A | AC100: #N/A | AD100: #N/A | AE100: 63.698318 | AF100: 64.117 | AG100: 60.8521 | AH100: 63.7538 | AI100: 64.9334 | AJ100: 70.146 | AK100: 51.7892 | AL100: 49.8211 | AM100: 56.9022 | AN100: 54.3355 | AO100: 68.2857 | AP100: 50.184 | AQ100: 59.0827 | AR100: 54.0886 | AS100: 51.8499 | AT100: 1.3978 | AU100: 53.3135 | AV100: 57.3389 | AW100: 64.1987 | AX100: 60.7543 | AY100: #N/A | AZ100: 53.0465 | BA100: 19259.55 | BB100: =IF(ISNUMBER(VLOOKUP($B100,CEIC_DATA!$I$26:$N$353,Haver_M!BB$2,FALSE)),VLOOKUP($B100,CEIC_DATA!$I$26:$N$353,Haver_M!BB$2,FALSE),NA()) -> 105.00891 | BC100: =IF(ISNUMBER(VLOOKUP($B100,CEIC_DATA!$I$26:$N$353,Haver_M!BC$2,FALSE)),VLOOKUP($B100,CEIC_DATA!$I$26:$N$353,Haver_M!BC$2,FALSE),NA()) -> #N/A | BD100: =IF(ISNUMBER(VLOOKUP($B100,CEIC_DATA!$I$26:$N$353,Haver_M!BD$2,FALSE)),VLOOKUP($B100,CEIC_DATA!$I$26:$N$353,Haver_M!BD$2,FALSE),NA()) -> #N/A | BE100: =IF(ISNUMBER(VLOOKUP($B100,CEIC_DATA!$I$26:$N$353,Haver_M!BE$2,FALSE)),VLOOKUP($B100,CEIC_DATA!$I$26:$N$353,Haver_M!BE$2,FALSE),NA()) -> #N/A | BF100: 724222 | BG100: 44977 | BH100: 957641 | BI100: 146829 | BJ100: 4980.95 | BK100: 7374.77 | BL100: 4541.94 | BM100: 19223.37 | BN100: 12909.3 | BO100: 22104.1 | BP100: 39.4495 | BQ100: =IF(ISNUMBER(BJ100),BJ100/$BP100,"") -> 126.26142 | BR100: =IF(ISNUMBER(BK100),BK100/$BP100,"") -> 186.94204 | BS100: =IF(ISNUMBER(BL100),BL100/$BP100,"") -> 115.13302 | BT100: =IF(ISNUMBER(BM100),BM100/$BP100,"") -> 487.29059 | BU100: 18475
A101: 0712 | B101: 39447 | C101: 7.75 | D101: 7.8057 | E101: 98.37503 | F101: 65.9 | G101: #N/A | H101: 87.68 | I101: 84.61 | J101: 99.02 | K101: 93.32 | L101: #N/A | M101: 71.9 | N101: 90.98 | O101: 82.7 | P101: 86.439 | Q101: 89.025 | R101: 70.279 | S101: 91.239 | T101: 92.666 | U101: 76.402 | V101: 74.219 | W101: 81.308 | X101: 10738.181 | Y101: 14701.71 | Z101: 21232.42 | AA101: #N/A | AB101: #N/A | AC101: #N/A | AD101: #N/A | AE101: 62.244059 | AF101: 63.3199 | AG101: 61.8539 | AH101: 62.4417 | AI101: 65.294 | AJ101: 72.093 | AK101: 52.2301 | AL101: 48.5458 | AM101: 57.3833 | AN101: 54.2033 | AO101: 69.6803 | AP101: 51.3607 | AQ101: 57.5712 | AR101: 53.6557 | AS101: 50.7687 | AT101: 1.4037 | AU101: 53.0093 | AV101: 55.6796 | AW101: 62.1308 | AX101: 57.9956 | AY101: #N/A | AZ101: 52.1639 | BA101: 19827.28 | BB101: =IF(ISNUMBER(VLOOKUP($B101,CEIC_DATA!$I$26:$N$353,Haver_M!BB$2,FALSE)),VLOOKUP($B101,CEIC_DATA!$I$26:$N$353,Haver_M!BB$2,FALSE),NA()) -> 105.69411 | BC101: =IF(ISNUMBER(VLOOKUP($B101,CEIC_DATA!$I$26:$N$353,Haver_M!BC$2,FALSE)),VLOOKUP($B101,CEIC_DATA!$I$26:$N$353,Haver_M!BC$2,FALSE),NA()) -> 115.9 | BD101: =IF(ISNUMBER(VLOOKUP($B101,CEIC_DATA!$I$26:$N$353,Haver_M!BD$2,FALSE)),VLOOKUP($B101,CEIC_DATA!$I$26:$N$353,Haver_M!BD$2,FALSE),NA()) -> 124.4 | BE101: =IF(ISNUMBER(VLOOKUP($B101,CEIC_DATA!$I$26:$N$353,Haver_M!BE$2,FALSE)),VLOOKUP($B101,CEIC_DATA!$I$26:$N$353,Haver_M!BE$2,FALSE),NA()) -> 50.2 | BF101: 613848 | BG101: 48504 | BH101: 834540 | BI101: 132671 | BJ101: 5026.5 | BK101: 7666.66 | BL101: 4695.25 | BM101: 19750.35 | BN101: 14625.5 | BO101: 20116.9 | BP101: 39.44 | BQ101: =IF(ISNUMBER(BJ101),BJ101/$BP101,"") -> 127.44675 | BR101: =IF(ISNUMBER(BK101),BK101/$BP101,"") -> 194.38793 | BS101: =IF(ISNUMBER(BL101),BL101/$BP101,"") -> 119.04792 | BT101: =IF(ISNUMBER(BM101),BM101/$BP101,"") -> 500.76952 | BU101: 19187
A102: 0801 | B102: 39478 | C102: 7.75 | D102: 7.5737 | E102: 97.41297 | F102: 66 | G102: #N/A | H102: 88.56 | I102: 84.2 | J102: 103.29 | K102: 94.51 | L102: #N/A | M102: 70.5 | N102: 93.57 | O102: 82.1 | P102: 88.677 | Q102: 89.401 | R102: 67.254 | S102: 94.243 | T102: 88.907 | U102: 71.192 | V102: 75.728 | W102: 80.921 | X102: 11122.658 | Y102: 15247.99 | Z102: 23597.05 | AA102: #N/A | AB102: #N/A | AC102: #N/A | AD102: #N/A | AE102: 140.39123 | AF102: 62.6529 | AG102: 60.6629 | AH102: 62.1872 | AI102: 63.6997 | AJ102: 70.036 | AK102: 52.4907 | AL102: 49.1811 | AM102: 56.0615 | AN102: 53.2643 | AO102: 66.3984 | AP102: 51.1478 | AQ102: 56.2476 | AR102: 52.8954 | AS102: 50.3002 | AT102: 1.3693 | AU102: 53.4197 | AV102: 55.5782 | AW102: 61.0845 | AX102: 57.8257 | AY102: #N/A | AZ102: 52.8163 | BA102: 19325.65 | BB102: =IF(ISNUMBER(VLOOKUP($B102,CEIC_DATA!$I$26:$N$353,Haver_M!BB$2,FALSE)),VLOOKUP($B102,CEIC_DATA!$I$26:$N$353,Haver_M!BB$2,FALSE),NA()) -> 105.92563 | BC102: =IF(ISNUMBER(VLOOKUP($B102,CEIC_DATA!$I$26:$N$353,Haver_M!BC$2,FALSE)),VLOOKUP($B102,CEIC_DATA!$I$26:$N$353,Haver_M!BC$2,FALSE),NA()) -> #N/A | BD102: =IF(ISNUMBER(VLOOKUP($B102,CEIC_DATA!$I$26:$N$353,Haver_M!BD$2,FALSE)),VLOOKUP($B102,CEIC_DATA!$I$26:$N$353,Haver_M!BD$2,FALSE),NA()) -> #N/A | BE102: =IF(ISNUMBER(VLOOKUP($B102,CEIC_DATA!$I$26:$N$353,Haver_M!BE$2,FALSE)),VLOOKUP($B102,CEIC_DATA!$I$26:$N$353,Haver_M!BE$2,FALSE),NA()) -> #N/A | BF102: 665402 | BG102: 52229 | BH102: 927586 | BI102: 167348 | BJ102: 5083.43 | BK102: 7778.63 | BL102: 4848.37 | BM102: 20096.88 | BN102: 14889.1 | BO102: 22844.4 | BP102: 39.3783 | BQ102: =IF(ISNUMBER(BJ102),BJ102/$BP102,"") -> 129.09216 | BR102: =IF(ISNUMBER(BK102),BK102/$BP102,"") -> 197.53595 | BS102: =IF(ISNUMBER(BL102),BL102/$BP102,"") -> 123.12289 | BT102: =IF(ISNUMBER(BM102),BM102/$BP102,"") -> 510.35418 | BU102: 21369
A103: 0802 | B103: 39507 | C103: 7.75 | D103: 7.6268 | E103: 96.61962 | F103: 66.4 | G103: #N/A | H103: 88.64 | I103: 84.54 | J103: 102.8 | K103: 95.08 | L103: #N/A | M103: 73.31 | N103: 96.71 | O103: 82.6 | P103: 87.356 | Q103: 89.346 | R103: 69.923 | S103: 94.973 | T103: 88.979 | U103: 74.98 | V103: 76.376 | W103: 81.054 | X103: 11548.306 | Y103: 16000.23 | Z103: 24358.75 | AA103: #N/A | AB103: #N/A | AC103: #N/A | AD103: #N/A | AE103: 80.611313 | AF103: 62.5706 | AG103: 59.4508 | AH103: 62.7312 | AI103: 62.2097 | AJ103: 68.3537 | AK103: 51.9023 | AL103: 50.1789 | AM103: 55.3861 | AN103: 57.5224 | AO103: 64.1702 | AP103: 51.2845 | AQ103: 55.6724 | AR103: 54.1969 | AS103: 50.6345 | AT103: 1.3328 | AU103: 53.8285 | AV103: 54.0693 | AW103: 60.3512 | AX103: 56.4317 | AY103: #N/A | AZ103: 51.7979 | BA103: 17727.54 | BB103: =IF(ISNUMBER(VLOOKUP($B103,CEIC_DATA!$I$26:$N$353,Haver_M!BB$2,FALSE)),VLOOKUP($B103,CEIC_DATA!$I$26:$N$353,Haver_M!BB$2,FALSE),NA()) -> 105.62176 | BC103: =IF(ISNUMBER(VLOOKUP($B103,CEIC_DATA!$I$26:$N$353,Haver_M!BC$2,FALSE)),VLOOKUP($B103,CEIC_DATA!$I$26:$N$353,Haver_M!BC$2,FALSE),NA()) -> #N/A | BD103: =IF(ISNUMBER(VLOOKUP($B103,CEIC_DATA!$I$26:$N$353,Haver_M!BD$2,FALSE)),VLOOKUP($B103,CEIC_DATA!$I$26:$N$353,Haver_M!BD$2,FALSE),NA()) -> #N/A | BE103: =IF(ISNUMBER(VLOOKUP($B103,CEIC_DATA!$I$26:$N$353,Haver_M!BE$2,FALSE)),VLOOKUP($B103,CEIC_DATA!$I$26:$N$353,Haver_M!BE$2,FALSE),NA()) -> #N/A | BF103: 623307 | BG103: 50454 | BH103: 861368 | BI103: 146474 | BJ103: 5213.89 | BK103: 8117.11 | BL103: 5051.74 | BM103: 20840.25 | BN103: 15116.2 | BO103: 20804.4 | BP103: 39.7057 | BQ103: =IF(ISNUMBER(BJ103),BJ103/$BP103,"") -> 131.31339 | BR103: =IF(ISNUMBER(BK103),BK103/$BP103,"") -> 204.43186 | BS103: =IF(ISNUMBER(BL103),BL103/$BP103,"") -> 127.22959 | BT103: =IF(ISNUMBER(BM103),BM103/$BP103,"") -> 524.86797 | BU103: 21383
A104: 0803 | B104: 39538 | C104: 7.75 | D104: 7.6367 | E104: 93.89742 | F104: 67.4 | G104: #N/A | H104: 89.61 | I104: 84.54 | J104: 105.45 | K104: 93.84 | L104: #N/A | M104: 70.29 | N104: 99.02 | O104: 83.1 | P104: 89.802 | Q104: 89.309 | R104: 67.54 | S104: 92.429 | T104: 75.694 | U104: 76.17 | V104: 77.223 | W104: 80.407 | X104: 10941.8 | Y104: 14645.58 | Z104: 24425.07 | AA104: #N/A | AB104: #N/A | AC104: #N/A | AD104: #N/A | AE104: 171.06266 | AF104: 62.8372 | AG104: 57.493 | AH104: 63.9605 | AI104: 60.3122 | AJ104: 64.0211 | AK104: 51.5449 | AL104: 48.9342 | AM104: 52.3981 | AN104: 53.7777 | AO104: 60.443 | AP104: 50.0603 | AQ104: 53.0094 | AR104: 51.7314 | AS104: 50.1254 | AT104: 1.2789 | AU104: 52.9948 | AV104: 53.9325 | AW104: 59.0496 | AX104: 54.9624 | AY104: #N/A | AZ104: 51.1356 | BA104: 15838.38 | BB104: =IF(ISNUMBER(VLOOKUP($B104,CEIC_DATA!$I$26:$N$353,Haver_M!BB$2,FALSE)),VLOOKUP($B104,CEIC_DATA!$I$26:$N$353,Haver_M!BB$2,FALSE),NA()) -> 104.60604 | BC104: =IF(ISNUMBER(VLOOKUP($B104,CEIC_DATA!$I$26:$N$353,Haver_M!BC$2,FALSE)),VLOOKUP($B104,CEIC_DATA!$I$26:$N$353,Haver_M!BC$2,FALSE),NA()) -> 122.8 | BD104: =IF(ISNUMBER(VLOOKUP($B104,CEIC_DATA!$I$26:$N$353,Haver_M!BD$2,FALSE)),VLOOKUP($B104,CEIC_DATA!$I$26:$N$353,Haver_M!BD$2,FALSE),NA()) -> 118.6 | BE104: =IF(ISNUMBER(VLOOKUP($B104,CEIC_DATA!$I$26:$N$353,Haver_M!BE$2,FALSE)),VLOOKUP($B104,CEIC_DATA!$I$26:$N$353,Haver_M!BE$2,FALSE),NA()) -> 47.7 | BF104: 706228 | BG104: 64123 | BH104: 1002704 | BI104: 192056 | BJ104: 5217.99 | BK104: 8583.44 | BL104: 5493.15 | BM104: 22048.01 | BN104: 17254 | BO104: 23573.7 | BP104: 40.3567 | BQ104: =IF(ISNUMBER(BJ104),BJ104/$BP104,"") -> 129.29675 | BR104: =IF(ISNUMBER(BK104),BK104/$BP104,"") -> 212.68934 | BS104: =IF(ISNUMBER(BL104),BL104/$BP104,"") -> 136.11494 | BT104: =IF(ISNUMBER(BM104),BM104/$BP104,"") -> 546.32837 | BU104: 19754
... A136: 1011 | B136: 40512 | C136: 6.25 | D136: 8.0498 | E136: 100.38441 | F136: 87.5 | G136: #N/A | H136: 100.14 | I136: 94.71 | J136: 123.06 | K136: 106.34 | L136: #N/A | M136: 96.25 | N136: 88.31 | O136: 93.4 | P136: 101.022 | Q136: 103.483 | R136: 109.102 | S136: 94.241 | T136: 96.945 | U136: 88.214 | V136: 89.098 | W136: 88.944 | X136: 11603.264 | Y136: 24476.8 | Z136: 30135.96 | AA136: #N/A | AB136: #N/A | AC136: #N/A | AD136: #N/A | AE136: 113.8629 | AF136: 61.2518 | AG136: 58.3664 | AH136: 60.0963 | AI136: 63.6505 | AJ136: 62.1523 | AK136: 49.8073 | AL136: 47.1525 | AM136: 59.1954 | AN136: 62.5227 | AO136: 60.2125 | AP136: 51.0016 | AQ136: 58.9624 | AR136: 52.5031 | AS136: 55.6907 | AT136: 1.2186 | AU136: 51.8985 | AV136: 52.8311 | AW136: 57.6608 | AX136: 54.9487 | AY136: #N/A | AZ136: 49.5638 | BA136: 20126.35 | BB136: =IF(ISNUMBER(VLOOKUP($B136,CEIC_DATA!$I$26:$N$353,Haver_M!BB$2,FALSE)),VLOOKUP($B136,CEIC_DATA!$I$26:$N$353,Haver_M!BB$2,FALSE),NA()) -> 115.08023 | BC136: =IF(ISNUMBER(VLOOKUP($B136,CEIC_DATA!$I$26:$N$353,Haver_M!BC$2,FALSE)),VLOOKUP($B136,CEIC_DATA!$I$26:$N$353,Haver_M!BC$2,FALSE),NA()) -> #N/A | BD136: =IF(ISNUMBER(VLOOKUP($B136,CEIC_DATA!$I$26:$N$353,Haver_M!BD$2,FALSE)),VLOOKUP($B136,CEIC_DATA!$I$26:$N$353,Haver_M!BD$2,FALSE),NA()) -> #N/A | BE136: =IF(ISNUMBER(VLOOKUP($B136,CEIC_DATA!$I$26:$N$353,Haver_M!BE$2,FALSE)),VLOOKUP($B136,CEIC_DATA!$I$26:$N$353,Haver_M!BE$2,FALSE),NA()) -> #N/A | BF136: 1044801 | BG136: 55170 | BH136: 1394207 | BI136: 231733 | BJ136: 6514.12 | BK136: 14654.77 | BL136: 7865.98 | BM136: 33153.03 | BN136: 22575 | BO136: 28842.3 | BP136: 45.0165 | BQ136: =IF(ISNUMBER(BJ136),BJ136/$BP136,"") -> 144.70516 | BR136: =IF(ISNUMBER(BK136),BK136/$BP136,"") -> 325.54219 | BS136: =IF(ISNUMBER(BL136),BL136/$BP136,"") -> 174.73549 | BT136: =IF(ISNUMBER(BM136),BM136/$BP136,"") -> 736.46396 | BU136: 48634
A137: 1012 | B137: 40543 | C137: 6.25 | D137: 7.9534 | E137: 101.49627 | F137: 88.5 | G137: #N/A | H137: 101.9 | I137: 95.62 | J137: 129.95 | K137: 108.4 | L137: #N/A | M137: 97.11 | N137: 91.64 | O137: 96.9 | P137: 99.336 | Q137: 103.399 | R137: 108.745 | S137: 101.849 | T137: 96.698 | U137: 92.115 | V137: 89.753 | W137: 92.808 | X137: 12202.523 | Y137: 23171.75 | Z137: 32256.86 | AA137: #N/A | AB137: #N/A | AC137: 116.7 | AD137: 119 | AE137: 144.09651 | AF137: 58.9165 | AG137: 56.661 | AH137: 57.7439 | AI137: 61.3504 | AJ137: 59.3199 | AK137: 49.9705 | AL137: 47.9842 | AM137: 57.31 | AN137: 64.8544 | AO137: 57.4511 | AP137: 50.3987 | AQ137: 58.2122 | AR137: 54.6901 | AS137: 53.8908 | AT137: 1.177 | AU137: 51.7761 | AV137: 54.7607 | AW137: 56.8382 | AX137: 57.6789 | AY137: #N/A | AZ137: 50.727 | BA137: 19927.59 | BB137: =IF(ISNUMBER(VLOOKUP($B137,CEIC_DATA!$I$26:$N$353,Haver_M!BB$2,FALSE)),VLOOKUP($B137,CEIC_DATA!$I$26:$N$353,Haver_M!BB$2,FALSE),NA()) -> 115.37578 | BC137: =IF(ISNUMBER(VLOOKUP($B137,CEIC_DATA!$I$26:$N$353,Haver_M!BC$2,FALSE)),VLOOKUP($B137,CEIC_DATA!$I$26:$N$353,Haver_M!BC$2,FALSE),NA()) -> 122.8 | BD137: =IF(ISNUMBER(VLOOKUP($B137,CEIC_DATA!$I$26:$N$353,Haver_M!BD$2,FALSE)),VLOOKUP($B137,CEIC_DATA!$I$26:$N$353,Haver_M!BD$2,FALSE),NA()) -> 126.5 | BE137: =IF(ISNUMBER(VLOOKUP($B137,CEIC_DATA!$I$26:$N$353,Haver_M!BE$2,FALSE)),VLOOKUP($B137,CEIC_DATA!$I$26:$N$353,Haver_M!BE$2,FALSE),NA()) -> 47.5 | BF137: 1134846 | BG137: 70811 | BH137: 1501764 | BI137: 230391 | BJ137: 6758.39 | BK137: 15510.3 | BL137: 8415.99 | BM137: 35048.23 | BN137: 23349.4 | BO137: 31511.1 | BP137: 45.1591 | BQ137: =IF(ISNUMBER(BJ137),BJ137/$BP137,"") -> 149.65732 | BR137: =IF(ISNUMBER(BK137),BK137/$BP137,"") -> 343.45901 | BS137: =IF(ISNUMBER(BL137),BL137/$BP137,"") -> 186.3631 | BT137: =IF(ISNUMBER(BM137),BM137/$BP137,"") -> 776.10559 | BU137: 47219
A138: 1101 | B138: 40574 | C138: 6.5 | D138: 8.1505 | E138: 100.00814 | F138: 89.5 | G138: 87.3 | H138: 103.1 | I138: 97.66 | J138: 120.11 | K138: 108.27 | L138: #N/A | M138: 101.1 | N138: 94.1 | O138: 99.5 | P138: 97.471 | Q138: 100.426 | R138: 107.793 | S138: 105.594 | T138: 99.081 | U138: 96.628 | V138: 92.396 | W138: 97.43 | X138: 11728.46 | Y138: 23117.5 | Z138: 33427.54 | AA138: #N/A | AB138: #N/A | AC138: #N/A | AD138: #N/A | AE138: 133.97455 | AF138: 59.5616 | AG138: 56.8164 | AH138: 58.1213 | AI138: 62.5513 | AJ138: 60.7301 | AK138: 49.4153 | AL138: 49.1291 | AM138: 54.4585 | AN138: 66.1376 | AO138: 58.3552 | AP138: 49.738 | AQ138: 55.6866 | AR138: 56.7067 | AS138: 52.4661 | AT138: 1.221 | AU138: 52.0824 | AV138: 55.3035 | AW138: 57.4256 | AX138: 61.9854 | AY138: #N/A | AZ138: 50.6952 | BA138: 19288.54 | BB138: =IF(ISNUMBER(VLOOKUP($B138,CEIC_DATA!$I$26:$N$353,Haver_M!BB$2,FALSE)),VLOOKUP($B138,CEIC_DATA!$I$26:$N$353,Haver_M!BB$2,FALSE),NA()) -> 114.77831 | BC138: =IF(ISNUMBER(VLOOKUP($B138,CEIC_DATA!$I$26:$N$353,Haver_M!BC$2,FALSE)),VLOOKUP($B138,CEIC_DATA!$I$26:$N$353,Haver_M!BC$2,FALSE),NA()) -> #N/A | BD138: =IF(ISNUMBER(VLOOKUP($B138,CEIC_DATA!$I$26:$N$353,Haver_M!BD$2,FALSE)),VLOOKUP($B138,CEIC_DATA!$I$26:$N$353,Haver_M!BD$2,FALSE),NA()) -> #N/A | BE138: =IF(ISNUMBER(VLOOKUP($B138,CEIC_DATA!$I$26:$N$353,Haver_M!BE$2,FALSE)),VLOOKUP($B138,CEIC_DATA!$I$26:$N$353,Haver_M!BE$2,FALSE),NA()) -> #N/A | BF138: 1108803 | BG138: 68415 | BH138: 1512772 | BI138: 264532 | BJ138: 6747.8 | BK138: 15260.47 | BL138: 8365.87 | BM138: 34967.97 | BN138: 22691.8 | BO138: 33353.6 | BP138: 45.3945 | BQ138: =IF(ISNUMBER(BJ138),BJ138/$BP138,"") -> 148.64796 | BR138: =IF(ISNUMBER(BK138),BK138/$BP138,"") -> 336.17443 | BS138: =IF(ISNUMBER(BL138),BL138/$BP138,"") -> 184.29259 | BT138: =IF(ISNUMBER(BM138),BM138/$BP138,"") -> 770.31292 | BU138: 47302
A139: 1102 | B139: 40602 | C139: 6.5 | D139: 8.0983 | E139: 98.51672 | F139: 88.4 | G139: 87.8 | H139: 103.33 | I139: 97.04 | J139: 107.39 | K139: 108.22 | L139: #N/A | M139: 106.91 | N139: 99.23 | O139: 99.1 | P139: 95.399 | Q139: 102.12 | R139: 107.37 | S139: 99.465 | T139: 99.445 | U139: 95.046 | V139: 96.934 | W139: 97.19 | X139: 11764.584 | Y139: 24009.38 | Z139: 35877.54 | AA139: #N/A | AB139: #N/A | AC139: #N/A | AD139: #N/A | AE139: 131.81931 | AF139: 61.0127 | AG139: 57.9414 | AH139: 60.178 | AI139: 62.7454 | AJ139: 62.3915 | AK139: 49.4378 | AL139: 47.283 | AM139: 57.4248 | AN139: 68.3926 | AO139: 61.0491 | AP139: 49.5845 | AQ139: 58.7325 | AR139: 56.2603 | AS139: 51.7533 | AT139: 1.2583 | AU139: 52.011 | AV139: 54.4324 | AW139: 59.6336 | AX139: 59.5209 | AY139: #N/A | AZ139: 50.151 | BA139: 18036.62 | BB139: =IF(ISNUMBER(VLOOKUP($B139,CEIC_DATA!$I$26:$N$353,Haver_M!BB$2,FALSE)),VLOOKUP($B139,CEIC_DATA!$I$26:$N$353,Haver_M!BB$2,FALSE),NA()) -> 113.16684 | BC139: =IF(ISNUMBER(VLOOKUP($B139,CEIC_DATA!$I$26:$N$353,Haver_M!BC$2,FALSE)),VLOOKUP($B139,CEIC_DATA!$I$26:$N$353,Haver_M!BC$2,FALSE),NA()) -> #N/A | BD139: =IF(ISNUMBER(VLOOKUP($B139,CEIC_DATA!$I$26:$N$353,Haver_M!BD$2,FALSE)),VLOOKUP($B139,CEIC_DATA!$I$26:$N$353,Haver_M!BD$2,FALSE),NA()) -> #N/A | BE139: =IF(ISNUMBER(VLOOKUP($B139,CEIC_DATA!$I$26:$N$353,Haver_M!BE$2,FALSE)),VLOOKUP($B139,CEIC_DATA!$I$26:$N$353,Haver_M!BE$2,FALSE),NA()) -> #N/A | BF139: 1157687 | BG139: 71077 | BH139: 1579044 | BI139: 276287 | BJ139: 6833.02 | BK139: 15692.2 | BL139: 8511.42 | BM139: 35635.67 | BN139: 23243.5 | BO139: 32973.4 | BP139: 45.4368 | BQ139: =IF(ISNUMBER(BJ139),BJ139/$BP139,"") -> 150.38515 | BR139: =IF(ISNUMBER(BK139),BK139/$BP139,"") -> 345.36323 | BS139: =IF(ISNUMBER(BL139),BL139/$BP139,"") -> 187.32437 | BT139: =IF(ISNUMBER(BM139),BM139/$BP139,"") -> 784.29093 | BU139: 46012
A140: 1103 | B140: 40633 | C140: 6.75 | D140: 8.0223 | E140: 98.34882 | F140: 88.4 | G140: 88.4 | H140: 106.12 | I140: 98.04 | J140: 134.36 | K140: 106.07 | L140: #N/A | M140: 101.9 | N140: 98.7 | O140: 99.5 | P140: 98.794 | Q140: 102.129 | R140: 107.075 | S140: 102.188 | T140: 98.376 | U140: 94.317 | V140: 96.334 | W140: 98.497 | X140: 11995.937 | Y140: 25707.83 | Z140: 34629.65 | AA140: #N/A | AB140: #N/A | AC140: 112.2 | AD140: 120.8 | AE140: 93.870627 | AF140: 60.0105 | AG140: 57.9272 | AH140: 58.774 | AI140: 62.5769 | AJ140: 64.2122 | AK140: 49.0809 | AL140: 50.0794 | AM140: 57.1503 | AN140: 68.6766 | AO140: 63.3918 | AP140: 50.6067 | AQ140: 57.9988 | AR140: 59.7463 | AS140: 54.9945 | AT140: 1.2688 | AU140: 53.8021 | AV140: 55.0984 | AW140: 58.4094 | AX140: 59.701 | AY140: #N/A | AZ140: 51.1577 | BA140: 18456.85 | BB140: =IF(ISNUMBER(VLOOKUP($B140,CEIC_DATA!$I$26:$N$353,Haver_M!BB$2,FALSE)),VLOOKUP($B140,CEIC_DATA!$I$26:$N$353,Haver_M!BB$2,FALSE),NA()) -> 110.81617 | BC140: =IF(ISNUMBER(VLOOKUP($B140,CEIC_DATA!$I$26:$N$353,Haver_M!BC$2,FALSE)),VLOOKUP($B140,CEIC_DATA!$I$26:$N$353,Haver_M!BC$2,FALSE),NA()) -> 122 | BD140: =IF(ISNUMBER(VLOOKUP($B140,CEIC_DATA!$I$26:$N$353,Haver_M!BD$2,FALSE)),VLOOKUP($B140,CEIC_DATA!$I$26:$N$353,Haver_M!BD$2,FALSE),NA()) -> 125.9 | BE140: =IF(ISNUMBER(VLOOKUP($B140,CEIC_DATA!$I$26:$N$353,Haver_M!BE$2,FALSE)),VLOOKUP($B140,CEIC_DATA!$I$26:$N$353,Haver_M!BE$2,FALSE),NA()) -> 50.1 | BF140: 1204301 | BG140: 86871 | BH140: 1651339 | BI140: 293302 | BJ140: 6879.44 | BK140: 16045.76 | BL140: 8942.01 | BM140: 36673.54 | BN140: 30418.5 | BO140: 34267 | BP140: 44.9895 | BQ140: =IF(ISNUMBER(BJ140),BJ140/$BP140,"") -> 152.91212 | BR140: =IF(ISNUMBER(BK140),BK140/$BP140,"") -> 356.65566 | BS140: =IF(ISNUMBER(BL140),BL140/$BP140,"") -> 198.75771 | BT140: =IF(ISNUMBER(BM140),BM140/$BP140,"") -> 815.15776 | BU140: 44313
A141: 1104 | B141: 40663 | C141: 6.75 | D141: 8.1267 | E141: 98.76965 | F141: 89.1 | G141: 89.4 | H141: 103.62 | I141: 98.36 | J141: 129.97 | K141: 107.49 | L141: #N/A | M141: 96.27 | N141: 97.39 | O141: 100.1 | P141: 99.283 | Q141: 101.776 | R141: 106.263 | S141: 103.668 | T141: 101.341 | U141: 95.939 | V141: 93.432 | W141: 97.356 | X141: 12296.585 | Y141: 23917.79 | Z141: 36068.45 | AA141: 11469 | AB141: 6889 | AC141: #N/A | AD141: #N/A | AE141: 80.495799 | AF141: 60.7373 | AG141: 57.9642 | AH141: 59.2019 | AI141: 63.9245 | AJ141: 63.0666 | AK141: 49.9624 | AL141: 49.8221 | AM141: 55.4399 | AN141: 66.3343 | AO141: 64.629 | AP141: 51.2541 | AQ141: 57.277 | AR141: 56.1961 | AS141: 52.4814 | AT141: 1.2305 | AU141: 52.6308 | AV141: 55.4224 | AW141: 57.773 | AX141: 55.6887 | AY141: #N/A | AZ141: 49.6532 | BA141: 19450.14 | BB141: =IF(ISNUMBER(VLOOKUP($B141,CEIC_DATA!$I$26:$N$353,Haver_M!BB$2,FALSE)),VLOOKUP($B141,CEIC_DATA!$I$26:$N$353,Haver_M!BB$2,FALSE),NA()) -> 107.88828 | BC141: =IF(ISNUMBER(VLOOKUP($B141,CEIC_DATA!$I$26:$N$353,Haver_M!BC$2,FALSE)),VLOOKUP($B141,CEIC_DATA!$I$26:$N$353,Haver_M!BC$2,FALSE),NA()) -> #N/A | BD141: =IF(ISNUMBER(VLOOKUP($B141,CEIC_DATA!$I$26:$N$353,Haver_M!BD$2,FALSE)),VLOOKUP($B141,CEIC_DATA!$I$26:$N$353,Haver_M!BD$2,FALSE),NA()) -> #N/A | BE141: =IF(ISNUMBER(VLOOKUP($B141,CEIC_DATA!$I$26:$N$353,Haver_M!BE$2,FALSE)),VLOOKUP($B141,CEIC_DATA!$I$26:$N$353,Haver_M!BE$2,FALSE),NA()) -> #N/A | BF141: 1219837 | BG141: 59211 | BH141: 1600602 | BI141: 250367 | BJ141: 7045.86 | BK141: 16161.3 | BL141: 8853.85 | BM141: 36829.18 | BN141: 23469.52 | BO141: 36595.86 | BP141: 44.3681 | BQ141: =IF(ISNUMBER(BJ141),BJ141/$BP141,"") -> 158.80464 | BR141: =IF(ISNUMBER(BK141),BK141/$BP141,"") -> 364.25495 | BS141: =IF(ISNUMBER(BL141),BL141/$BP141,"") -> 199.55441 | BT141: =IF(ISNUMBER(BM141),BM141/$BP141,"") -> 830.08242 | BU141: 59266
A142: 1105 | B142: 40694 | C142: 7.25 | D142: 8.4123 | E142: 97.76321 | F142: 89.8 | G142: 90.3 | H142: 101.07 | I142: 97.69 | J142: 116.77 | K142: 104.96 | L142: #N/A | M142: 94.73 | N142: 97.87 | O142: 98.5 | P142: 98.292 | Q142: 101.227 | R142: 102.337 | S142: 100.557 | T142: 102.54 | U142: 95.011 | V142: 92.851 | W142: 98.236 | X142: 12038.309 | Y142: 26480.29 | Z142: 42078.7 | AA142: 11835 | AB142: 7088 | AC142: #N/A | AD142: #N/A | AE142: 104.45028 | AF142: 57.6841 | AG142: 57.5002 | AH142: 55.0045 | AI142: 63.2461 | AJ142: 62.367 | AK142: 48.8314 | AL142: 48.7622 | AM142: 55.2663 | AN142: 63.4391 | AO142: 63.6276 | AP142: 51.1755 | AQ142: 55.9969 | AR142: 56.4363 | AS142: 52.0822 | AT142: 1.2187 | AU142: 52.9642 | AV142: 54.7881 | AW142: 54.6458 | AX142: 56.3344 | AY142: #N/A | AZ142: 48.9474 | BA142: 18325.45 | BB142: =IF(ISNUMBER(VLOOKUP($B142,CEIC_DATA!$I$26:$N$353,Haver_M!BB$2,FALSE)),VLOOKUP($B142,CEIC_DATA!$I$26:$N$353,Haver_M!BB$2,FALSE),NA()) -> 104.67303 | BC142: =IF(ISNUMBER(VLOOKUP($B142,CEIC_DATA!$I$26:$N$353,Haver_M!BC$2,FALSE)),VLOOKUP($B142,CEIC_DATA!$I$26:$N$353,Haver_M!BC$2,FALSE),NA()) -> #N/A | BD142: =IF(ISNUMBER(VLOOKUP($B142,CEIC_DATA!$I$26:$N$353,Haver_M!BD$2,FALSE)),VLOOKUP($B142,CEIC_DATA!$I$26:$N$353,Haver_M!BD$2,FALSE),NA()) -> #N/A | BE142: =IF(ISNUMBER(VLOOKUP($B142,CEIC_DATA!$I$26:$N$353,Haver_M!BE$2,FALSE)),VLOOKUP($B142,CEIC_DATA!$I$26:$N$353,Haver_M!BE$2,FALSE),NA()) -> #N/A | BF142: 1231949 | BG142: 65453 | BH142: 1604499 | BI142: 239875 | BJ142: 7059.25 | BK142: 16374.69 | BL142: 8705.93 | BM142: 36889.92 | BN142: 26521.93 | BO142: 45254.24 | BP142: 44.9048 | BQ142: =IF(ISNUMBER(BJ142),BJ142/$BP142,"") -> 157.2048 | BR142: =IF(ISNUMBER(BK142),BK142/$BP142,"") -> 364.65344 | BS142: =IF(ISNUMBER(BL142),BL142/$BP142,"") -> 193.87527 | BT142: =IF(ISNUMBER(BM142),BM142/$BP142,"") -> 821.51396 | BU142: 65595
A143: 1106 | B143: 40724 | C143: 7.5 | D143: 8.3518 | E143: 98.48898 | F143: 90.6 | G143: 90.9 | H143: 104.63 | I143: 98.31 | J143: 139.27 | K143: 105.8 | L143: #N/A | M143: 95.2 | N143: 97.22 | O143: 98.8 | P143: 97.02 | Q143: 101.221 | R143: 102.561 | S143: 100.223 | T143: 100.498 | U143: 98.004 | V143: 94.494 | W143: 96.801 | X143: 11968.545 | Y143: 25979.15 | Z143: 41495.42 | AA143: 11040 | AB143: 7205 | AC143: 116.3 | AD143: 120.2 | AE143: 113.63406 | AF143: 56.8491 | AG143: 55.2883 | AH143: 56.1245 | AI143: 58.353 | AJ143: 60.0654 | AK143: 48.7489 | AL143: 48.5052 | AM143: 52.0645 | AN143: 64.0172 | AO143: 60.5678 | AP143: 50.3405 | AQ143: 53.1929 | AR143: 54.59 | AS143: 51.4835 | AT143: 1.1932 | AU143: 52.7664 | AV143: 53.5827 | AW143: 57.0896 | AX143: 55.4189 | AY143: #N/A | AZ143: 49.0671 | BA143: 18228.94 | BB143: =IF(ISNUMBER(VLOOKUP($B143,CEIC_DATA!$I$26:$N$353,Haver_M!BB$2,FALSE)),VLOOKUP($B143,CEIC_DATA!$I$26:$N$353,Haver_M!BB$2,FALSE),NA()) -> 101.61481 | BC143: =IF(ISNUMBER(VLOOKUP($B143,CEIC_DATA!$I$26:$N$353,Haver_M!BC$2,FALSE)),VLOOKUP($B143,CEIC_DATA!$I$26:$N$353,Haver_M!BC$2,FALSE),NA()) -> 116.3 | BD143: =IF(ISNUMBER(VLOOKUP($B143,CEIC_DATA!$I$26:$N$353,Haver_M!BD$2,FALSE)),VLOOKUP($B143,CEIC_DATA!$I$26:$N$353,Haver_M!BD$2,FALSE),NA()) -> 121.9 | BE143: =IF(ISNUMBER(VLOOKUP($B143,CEIC_DATA!$I$26:$N$353,Haver_M!BE$2,FALSE)),VLOOKUP($B143,CEIC_DATA!$I$26:$N$353,Haver_M!BE$2,FALSE),NA()) -> 41.4 | BF143: 1242677 | BG143: 67574 | BH143: 1617020 | BI143: 233655 | BJ143: 7095.61 | BK143: 16574.89 | BL143: 8800.14 | BM143: 37238.94 | BN143: 26536.13 | BO143: 40849.47 | BP143: 44.8518 | BQ143: =IF(ISNUMBER(BJ143),BJ143/$BP143,"") -> 158.20123 | BR143: =IF(ISNUMBER(BK143),BK143/$BP143,"") -> 369.54793 | BS143: =IF(ISNUMBER(BL143),BL143/$BP143,"") -> 196.20483 | BT143: =IF(ISNUMBER(BM143),BM143/$BP143,"") -> 830.26634 | BU143: 64128
A144: 1107 | B144: 40755 | C144: 8 | D144: 8.4792 | E144: 99.64323 | F144: 91.8 | G144: 91.8 | H144: 102.75 | I144: 100.83 | J144: 116.86 | K144: 104.94 | L144: #N/A | M144: 101.03 | N144: 94.53 | O144: 100.2 | P144: 103.152 | Q144: 101.555 | R144: 102.092 | S144: 98.346 | T144: 98.517 | U144: 98.99 | V144: 99.625 | W144: 100.683 | X144: 12046.872 | Y144: 26359.9 | Z144: 39622.32 | AA144: 10400 | AB144: 5894 | AC144: #N/A | AD144: #N/A | AE144: 153.86446 | AF144: 57.8544 | AG144: 53.5951 | AH144: 58.1641 | AI144: 57.2118 | AJ144: 54.5483 | AK144: 51.8597 | AL144: 51.4565 | AM144: 52.7415 | AN144: 64.2824 | AO144: 56.6555 | AP144: 51.3464 | AQ144: 49.2274 | AR144: 56.0329 | AS144: 50.8751 | AT144: 1.0624 | AU144: 49.3716 | AV144: 57.0745 | AW144: 59.2782 | AX144: 58.8576 | AY144: #N/A | AZ144: 52.4868 | BA144: 18616.41 | BB144: =IF(ISNUMBER(VLOOKUP($B144,CEIC_DATA!$I$26:$N$353,Haver_M!BB$2,FALSE)),VLOOKUP($B144,CEIC_DATA!$I$26:$N$353,Haver_M!BB$2,FALSE),NA()) -> 99.068913 | BC144: =IF(ISNUMBER(VLOOKUP($B144,CEIC_DATA!$I$26:$N$353,Haver_M!BC$2,FALSE)),VLOOKUP($B144,CEIC_DATA!$I$26:$N$353,Haver_M!BC$2,FALSE),NA()) -> #N/A | BD144: =IF(ISNUMBER(VLOOKUP($B144,CEIC_DATA!$I$26:$N$353,Haver_M!BD$2,FALSE)),VLOOKUP($B144,CEIC_DATA!$I$26:$N$353,Haver_M!BD$2,FALSE),NA()) -> #N/A | BE144: =IF(ISNUMBER(VLOOKUP($B144,CEIC_DATA!$I$26:$N$353,Haver_M!BE$2,FALSE)),VLOOKUP($B144,CEIC_DATA!$I$26:$N$353,Haver_M!BE$2,FALSE),NA()) -> #N/A | BF144: 1232858 | BG144: 71722 | BH144: 1613335 | BI144: 232631 | BJ144: 7082.72 | BK144: 16589.51 | BL144: 8971.16 | BM144: 37281.58 | BN144: 26426.54 | BO144: 41105.88 | BP144: 44.4159 | BQ144: =IF(ISNUMBER(BJ144),BJ144/$BP144,"") -> 159.46362 | BR144: =IF(ISNUMBER(BK144),BK144/$BP144,"") -> 373.50386 | BS144: =IF(ISNUMBER(BL144),BL144/$BP144,"") -> 201.98082 | BT144: =IF(ISNUMBER(BM144),BM144/$BP144,"") -> 839.37464 | BU144: 61277
A145: 1108 | B145: 40786 | C145: 8 | D145: 8.3543 | E145: 98.07562 | F145: 92.7 | G145: 92.5 | H145: 101.19 | I145: 98.4 | J145: 116.37 | K145: 103.92 | L145: #N/A | M145: 95.56 | N145: 91.39 | O145: 98.7 | P145: 87.752 | Q145: 100.614 | R145: 103.305 | S145: 99.688 | T145: 98.556 | U145: 99.101 | V145: 100.212 | W145: 99.06 | X145: 11991.337 | Y145: 25717.44 | Z145: 40985.47 | AA145: 11897 | AB145: 6860 | AC145: #N/A | AD145: #N/A | AE145: 257.98672 | AF145: 54.5298 | AG145: 52.5932 | AH145: 53.8086 | AI145: 56.0267 | AJ145: 53.0578 | AK145: 49.5134 | AL145: 50.0826 | AM145: 52.7891 | AN145: 65.5907 | AO145: 55.6485 | AP145: 49.063 | AQ145: 45.0382 | AR145: 55.642 | AS145: 49.2725 | AT145: 1.0814 | AU145: 49.2405 | AV145: 57.9466 | AW145: 54.8698 | AX145: 58.8276 | AY145: #N/A | AZ145: 52.7379 | BA145: 16887.53 | BB145: =IF(ISNUMBER(VLOOKUP($B145,CEIC_DATA!$I$26:$N$353,Haver_M!BB$2,FALSE)),VLOOKUP($B145,CEIC_DATA!$I$26:$N$353,Haver_M!BB$2,FALSE),NA()) -> 97.131851 | BC145: =IF(ISNUMBER(VLOOKUP($B145,CEIC_DATA!$I$26:$N$353,Haver_M!BC$2,FALSE)),VLOOKUP($B145,CEIC_DATA!$I$26:$N$353,Haver_M!BC$2,FALSE),NA()) -> #N/A | BD145: =IF(ISNUMBER(VLOOKUP($B145,CEIC_DATA!$I$26:$N$353,Haver_M!BD$2,FALSE)),VLOOKUP($B145,CEIC_DATA!$I$26:$N$353,Haver_M!BD$2,FALSE),NA()) -> #N/A | BE145: =IF(ISNUMBER(VLOOKUP($B145,CEIC_DATA!$I$26:$N$353,Haver_M!BE$2,FALSE)),VLOOKUP($B145,CEIC_DATA!$I$26:$N$353,Haver_M!BE$2,FALSE),NA()) -> #N/A | BF145: 1280681 | BG145: 70951 | BH145: 1670989 | BI145: 241560 | BJ145: 7185.89 | BK145: 16933.33 | BL145: 8909.81 | BM145: 37610.9 | BN145: 24768.35 | BO145: 39984.69 | BP145: 45.2785 | BQ145: =IF(ISNUMBER(BJ145),BJ145/$BP145,"") -> 158.70424 | BR145: =IF(ISNUMBER(BK145),BK145/$BP145,"") -> 373.98169 | BS145: =IF(ISNUMBER(BL145),BL145/$BP145,"") -> 196.77794 | BT145: =IF(ISNUMBER(BM145),BM145/$BP145,"") -> 830.65693 | BU145: 56428
A146: 1109 | B146: 40816 | C146: 8.25 | D146: 8.3975 | E146: 95.67645 | F146: 93.8 | G146: 93.5 | H146: 101.59 | I146: 98.51 | J146: 112.86 | K146: 103.26 | L146: #N/A | M146: 100.14 | N146: 94.6 | O146: 97 | P146: 83.27 | Q146: 99.924 | R146: 101.286 | S146: 96.706 | T146: 96.416 | U146: 102.101 | V146: 95.429 | W146: 99.002 | X146: 12359.679 | Y146: 26284.65 | Z146: 39603.92 | AA146: 11228 | AB146: 6799 | AC146: 115 | AD146: 118.7 | AE146: 185.06182 | AF146: 50.2072 | AG146: 50.4146 | AH146: 49.7684 | AI146: 51.118 | AJ146: 51.253 | AK146: 47.939 | AL146: 49.7818 | AM146: 51.3867 | AN146: 62.1053 | AO146: 50.8113 | AP146: 50.0667 | AQ146: 46.3756 | AR146: 55.466 | AS146: 48.9614 | AT146: 1.0237 | AU146: 49.321 | AV146: 57.5428 | AW146: 51.5953 | AX146: 56.3402 | AY146: #N/A | AZ146: 50.8718 | BA146: 16694.77 | BB146: =IF(ISNUMBER(VLOOKUP($B146,CEIC_DATA!$I$26:$N$353,Haver_M!BB$2,FALSE)),VLOOKUP($B146,CEIC_DATA!$I$26:$N$353,Haver_M!BB$2,FALSE),NA()) -> 96.033817 | BC146: =IF(ISNUMBER(VLOOKUP($B146,CEIC_DATA!$I$26:$N$353,Haver_M!BC$2,FALSE)),VLOOKUP($B146,CEIC_DATA!$I$26:$N$353,Haver_M!BC$2,FALSE),NA()) -> 109.4 | BD146: =IF(ISNUMBER(VLOOKUP($B146,CEIC_DATA!$I$26:$N$353,Haver_M!BD$2,FALSE)),VLOOKUP($B146,CEIC_DATA!$I$26:$N$353,Haver_M!BD$2,FALSE),NA()) -> 121.5 | BE146: =IF(ISNUMBER(VLOOKUP($B146,CEIC_DATA!$I$26:$N$353,Haver_M!BE$2,FALSE)),VLOOKUP($B146,CEIC_DATA!$I$26:$N$353,Haver_M!BE$2,FALSE),NA()) -> 39.8 | BF146: 1408424 | BG146: 80177 | BH146: 1827265 | BI146: 257812 | BJ146: 7243.39 | BK146: 17236.64 | BL146: 8982.63 | BM146: 37968.93 | BN146: 26561.2 | BO146: 39756.07 | BP146: 47.638 | BQ146: =IF(ISNUMBER(BJ146),BJ146/$BP146,"") -> 152.05067 | BR146: =IF(ISNUMBER(BK146),BK146/$BP146,"") -> 361.82543 | BS146: =IF(ISNUMBER(BL146),BL146/$BP146,"") -> 188.56018 | BT146: =IF(ISNUMBER(BM146),BM146/$BP146,"") -> 797.03031 | BU146: 51874
A147: 1110 | B147: 40847 | C147: 8.5 | D147: 8.8849 | E147: 94.0585 | F147: 94.8 | G147: 94.3 | H147: 97.55 | I147: 98.67 | J147: 100.49 | K147: 100.44 | L147: #N/A | M147: 95.87 | N147: 91.63 | O147: 98.7 | P147: 94.149 | Q147: 99.086 | R147: 99.035 | S147: 93.346 | T147: 98.936 | U147: 105.924 | V147: 102.554 | W147: 99.933 | X147: 12180.747 | Y147: 24758.46 | Z147: 39340.84 | AA147: 11455 | AB147: 6820 | AC147: #N/A | AD147: #N/A | AE147: 217.2407 | AF147: 50.2977 | AG147: 51.9819 | AH147: 49.1256 | AI147: 52.7307 | AJ147: 53.7316 | AK147: 48.1786 | AL147: 47.8174 | AM147: 52.1662 | AN147: 62.0084 | AO147: 53.5504 | AP147: 49.6597 | AQ147: 49.2405 | AR147: 55.2669 | AS147: 50.6944 | AT147: 1.082 | AU147: 49.2575 | AV147: 55.9031 | AW147: 51.0115 | AX147: 54.5183 | AY147: #N/A | AZ147: 49.8987 | BA147: 16822.84 | BB147: =IF(ISNUMBER(VLOOKUP($B147,CEIC_DATA!$I$26:$N$353,Haver_M!BB$2,FALSE)),VLOOKUP($B147,CEIC_DATA!$I$26:$N$353,Haver_M!BB$2,FALSE),NA()) -> 95.875529 | BC147: =IF(ISNUMBER(VLOOKUP($B147,CEIC_DATA!$I$26:$N$353,Haver_M!BC$2,FALSE)),VLOOKUP($B147,CEIC_DATA!$I$26:$N$353,Haver_M!BC$2,FALSE),NA()) -> #N/A | BD147: =IF(ISNUMBER(VLOOKUP($B147,CEIC_DATA!$I$26:$N$353,Haver_M!BD$2,FALSE)),VLOOKUP($B147,CEIC_DATA!$I$26:$N$353,Haver_M!BD$2,FALSE),NA()) -> #N/A | BE147: =IF(ISNUMBER(VLOOKUP($B147,CEIC_DATA!$I$26:$N$353,Haver_M!BE$2,FALSE)),VLOOKUP($B147,CEIC_DATA!$I$26:$N$353,Haver_M!BE$2,FALSE),NA()) -> #N/A | BF147: 1305922 | BG147: 67805 | BH147: 1670562 | BI147: 218133 | BJ147: 7289.19 | BK147: 17355.31 | BL147: 9194.44 | BM147: 38381.89 | BN147: 23632.02 | BO147: 41175.06 | BP147: 49.2569 | BQ147: =IF(ISNUMBER(BJ147),BJ147/$BP147,"") -> 147.98313 | BR147: =IF(ISNUMBER(BK147),BK147/$BP147,"") -> 352.34272 | BS147: =IF(ISNUMBER(BL147),BL147/$BP147,"") -> 186.66299 | BT147: =IF(ISNUMBER(BM147),BM147/$BP147,"") -> 779.21855 | BU147: 55851
A148: 1111 | B148: 40877 | C148: 8.5 | D148: 8.7594 | E148: 92.10428 | F148: 95.2 | G148: 95.3 | H148: 105.02 | I148: 100.41 | J148: 116.14 | K148: 105.89 | L148: #N/A | M148: 102.37 | N148: 99.54 | O148: 101.4 | P148: 103.814 | Q148: 98.086 | R148: 97.928 | S148: 105.054 | T148: 97.826 | U148: 99.023 | V148: 103.897 | W148: 101.252 | X148: 13082.001 | Y148: 25184.2 | Z148: 41054.77 | AA148: 11279 | AB148: 7403 | AC148: #N/A | AD148: #N/A | AE148: 234.61385 | AF148: 52.3239 | AG148: 51.0425 | AH148: 53.2227 | AI148: 50.4583 | AJ148: 52.773 | AK148: 48.5854 | AL148: 47.8357 | AM148: 50.5427 | AN148: 63.1305 | AO148: 52.4852 | AP148: 50.3871 | AQ148: 50.4397 | AR148: 55.406 | AS148: 53.7865 | AT148: 1.0474 | AU148: 49.8214 | AV148: 56.0012 | AW148: 52.316 | AX148: 57.6358 | AY148: #N/A | AZ148: 50.0334 | BA148: 16664.48 | BB148: =IF(ISNUMBER(VLOOKUP($B148,CEIC_DATA!$I$26:$N$353,Haver_M!BB$2,FALSE)),VLOOKUP($B148,CEIC_DATA!$I$26:$N$353,Haver_M!BB$2,FALSE),NA()) -> 96.565157 | BC148: =IF(ISNUMBER(VLOOKUP($B148,CEIC_DATA!$I$26:$N$353,Haver_M!BC$2,FALSE)),VLOOKUP($B148,CEIC_DATA!$I$26:$N$353,Haver_M!BC$2,FALSE),NA()) -> #N/A | BD148: =IF(ISNUMBER(VLOOKUP($B148,CEIC_DATA!$I$26:$N$353,Haver_M!BD$2,FALSE)),VLOOKUP($B148,CEIC_DATA!$I$26:$N$353,Haver_M!BD$2,FALSE),NA()) -> #N/A | BE148: =IF(ISNUMBER(VLOOKUP($B148,CEIC_DATA!$I$26:$N$353,Haver_M!BE$2,FALSE)),VLOOKUP($B148,CEIC_DATA!$I$26:$N$353,Haver_M!BE$2,FALSE),NA()) -> #N/A | BF148: 1326721 | BG148: 73567 | BH148: 1733093 | BI148: 260229 | BJ148: 7271.02 | BK148: 17481.36 | BL148: 9353.2 | BM148: 38723.86 | BN148: 23269.71 | BO148: 39102.48 | BP148: 50.8433 | BQ148: =IF(ISNUMBER(BJ148),BJ148/$BP148,"") -> 143.00842 | BR148: =IF(ISNUMBER(BK148),BK148/$BP148,"") -> 343.82819 | BS148: =IF(ISNUMBER(BL148),BL148/$BP148,"") -> 183.96131 | BT148: =IF(ISNUMBER(BM148),BM148/$BP148,"") -> 761.63152 | BU148: 54815
A149: 1112 | B149: 40908 | C149: 8.5 | D149: 8.5459 | E149: 89.92178 | F149: 94.7 | G149: 95.6 | H149: 105.01 | I149: 100.43 | J149: 110.62 | K149: 106.88 | L149: #N/A | M149: 101.18 | N149: 105.46 | O149: 101.6 | P149: 104.098 | Q149: 97.53 | R149: 95.833 | S149: 101.628 | T149: 99.563 | U149: 101.803 | V149: 102.679 | W149: 101.3 | X149: 12624.354 | Y149: 25027.7 | Z149: 40401.04 | AA149: 11181 | AB149: 7656 | AC149: 116.2 | AD149: 120.2 | AE149: 220.21654 | AF149: 54.7448 | AG149: 54.1611 | AH149: 54.2368 | AI149: 55.7993 | AJ149: 57.8606 | AK149: 50.3766 | AL149: 50.4722 | AM149: 53.4857 | AN149: 62.7126 | AO149: 55.687 | AP149: 50.7243 | AQ149: 54.0798 | AR149: 56.2399 | AS149: 52.6397 | AT149: 1.1407 | AU149: 50.5551 | AV149: 57.2864 | AW149: 55.7425 | AX149: 59.0992 | AY149: #N/A | AZ149: 50.3856 | BA149: 15959.97 | BB149: =IF(ISNUMBER(VLOOKUP($B149,CEIC_DATA!$I$26:$N$353,Haver_M!BB$2,FALSE)),VLOOKUP($B149,CEIC_DATA!$I$26:$N$353,Haver_M!BB$2,FALSE),NA()) -> 97.525769 | BC149: =IF(ISNUMBER(VLOOKUP($B149,CEIC_DATA!$I$26:$N$353,Haver_M!BC$2,FALSE)),VLOOKUP($B149,CEIC_DATA!$I$26:$N$353,Haver_M!BC$2,FALSE),NA()) -> 110.1 | BD149: =IF(ISNUMBER(VLOOKUP($B149,CEIC_DATA!$I$26:$N$353,Haver_M!BD$2,FALSE)),VLOOKUP($B149,CEIC_DATA!$I$26:$N$353,Haver_M!BD$2,FALSE),NA()) -> 118.8 | BE149: =IF(ISNUMBER(VLOOKUP($B149,CEIC_DATA!$I$26:$N$353,Haver_M!BE$2,FALSE)),VLOOKUP($B149,CEIC_DATA!$I$26:$N$353,Haver_M!BE$2,FALSE),NA()) -> 35.2 | BF149: 1246980 | BG149: 81223 | BH149: 1647806 | BI149: 248825 | BJ149: 7584.25 | BK149: 18357.73 | BL149: 9700.95 | BM149: 40457.76 | BN149: 25365.69 | BO149: 40044.06 | BP149: 52.6678 | BQ149: =IF(ISNUMBER(BJ149),BJ149/$BP149,"") -> 144.00165 | BR149: =IF(ISNUMBER(BK149),BK149/$BP149,"") -> 348.55699 | BS149: =IF(ISNUMBER(BL149),BL149/$BP149,"") -> 184.19129 | BT149: =IF(ISNUMBER(BM149),BM149/$BP149,"") -> 768.16879 | BU149: 55489
A150: 1201 | B150: 40939 | C150: 8.5 | D150: 8.2878 | E150: 92.66818 | F150: 95.1 | G150: 96.3 | H150: 103.88 | I150: 99.31 | J150: 116.52 | K150: 105.54 | L150: #N/A | M150: 93.19 | N150: 105.38 | O150: 100.4 | P150: 103.856 | Q150: 98.61 | R150: 96.206 | S150: 98.88 | T150: 102.442 | U150: 100.831 | V150: 103.172 | W150: 100.592 | X150: 12049.723 | Y150: 25559.4 | Z150: 42667.83 | AA150: 11027 | AB150: 7332 | AC150: #N/A | AD150: #N/A | AE150: 188.0702 | AF150: 59.5696 | AG150: 57.4882 | AH150: 57.9824 | AI150: 62.8642 | AJ150: 62.2341 | AK150: 50.184 | AL150: 50.2728 | AM150: 56.06 | AN150: 63.3641 | AO150: 60.5 | AP150: 52.1497 | AQ150: 56.6603 | AR150: 56.0867 | AS150: 51.6457 | AT150: 1.1934 | AU150: 50.422 | AV150: 57.6597 | AW150: 58.1961 | AX150: 56.9052 | AY150: #N/A | AZ150: 49.5327 | BA150: 16381.79 | BB150: =IF(ISNUMBER(VLOOKUP($B150,CEIC_DATA!$I$26:$N$353,Haver_M!BB$2,FALSE)),VLOOKUP($B150,CEIC_DATA!$I$26:$N$353,Haver_M!BB$2,FALSE),NA()) -> 98.554194 | BC150: =IF(ISNUMBER(VLOOKUP($B150,CEIC_DATA!$I$26:$N$353,Haver_M!BC$2,FALSE)),VLOOKUP($B150,CEIC_DATA!$I$26:$N$353,Haver_M!BC$2,FALSE),NA()) -> #N/A | BD150: =IF(ISNUMBER(VLOOKUP($B150,CEIC_DATA!$I$26:$N$353,Haver_M!BD$2,FALSE)),VLOOKUP($B150,CEIC_DATA!$I$26:$N$353,Haver_M!BD$2,FALSE),NA()) -> #N/A | BE150: =IF(ISNUMBER(VLOOKUP($B150,CEIC_DATA!$I$26:$N$353,Haver_M!BE$2,FALSE)),VLOOKUP($B150,CEIC_DATA!$I$26:$N$353,Haver_M!BE$2,FALSE),NA()) -> #N/A | BF150: 1264557 | BG150: 80190 | BH150: 1719768 | BI150: 302118 | BJ150: 7635.68 | BK150: 18245.91 | BL150: 9631.27 | BM150: 40397.71 | BN150: 25379.05 | BO150: 42952.47 | BP150: 51.3461 | BQ150: =IF(ISNUMBER(BJ150),BJ150/$BP150,"") -> 148.71003 | BR150: =IF(ISNUMBER(BK150),BK150/$BP150,"") -> 355.35143 | BS150: =IF(ISNUMBER(BL150),BL150/$BP150,"") -> 187.57549 | BT150: =IF(ISNUMBER(BM150),BM150/$BP150,"") -> 786.77271 | BU150: 55346
A151: 1202 | B151: 40968 | C151: 8.5 | D151: 8.2 | E151: 94.97131 | F151: 95.5 | G151: 96.6 | H151: 104.04 | I151: 101.08 | J151: 111.37 | K151: 105.59 | L151: #N/A | M151: 100.43 | N151: 104.4 | O151: 100.7 | P151: 107.968 | Q151: 99.044 | R151: 95.181 | S151: 99.503 | T151: 98.847 | U151: 103.353 | V151: 104.189 | W151: 102.468 | X151: 12768.596 | Y151: 25837.31 | Z151: 42891.69 | AA151: 11226 | AB151: 6750 | AC151: #N/A | AD151: #N/A | AE151: 168.1912 | AF151: 57.7648 | AG151: 56.6032 | AH151: 56.4637 | AI151: 60.4654 | AJ151: 62.7862 | AK151: 48.6907 | AL151: 49.3448 | AM151: 53.1462 | AN151: 60.6121 | AO151: 61.4858 | AP151: 51.8131 | AQ151: 53.9136 | AR151: 56.6264 | AS151: 52.0007 | AT151: 1.2118 | AU151: 49.9431 | AV151: 54.6112 | AW151: 58.2057 | AX151: 56.276 | AY151: #N/A | AZ151: 50.2918 | BA151: 17836.33 | BB151: =IF(ISNUMBER(VLOOKUP($B151,CEIC_DATA!$I$26:$N$353,Haver_M!BB$2,FALSE)),VLOOKUP($B151,CEIC_DATA!$I$26:$N$353,Haver_M!BB$2,FALSE),NA()) -> 99.481952 | BC151: =IF(ISNUMBER(VLOOKUP($B151,CEIC_DATA!$I$26:$N$353,Haver_M!BC$2,FALSE)),VLOOKUP($B151,CEIC_DATA!$I$26:$N$353,Haver_M!BC$2,FALSE),NA()) -> #N/A | BD151: =IF(ISNUMBER(VLOOKUP($B151,CEIC_DATA!$I$26:$N$353,Haver_M!BD$2,FALSE)),VLOOKUP($B151,CEIC_DATA!$I$26:$N$353,Haver_M!BD$2,FALSE),NA()) -> #N/A | BE151: =IF(ISNUMBER(VLOOKUP($B151,CEIC_DATA!$I$26:$N$353,Haver_M!BE$2,FALSE)),VLOOKUP($B151,CEIC_DATA!$I$26:$N$353,Haver_M!BE$2,FALSE),NA()) -> #N/A | BF151: 1295051 | BG151: 85308 | BH151: 1758408 | BI151: 307338 | BJ151: 7609.49 | BK151: 18544.92 | BL151: 9827.29 | BM151: 40949.89 | BN151: 25194.42 | BO151: 40118.54 | BP151: 49.1577 | BQ151: =IF(ISNUMBER(BJ151),BJ151/$BP151,"") -> 154.79752 | BR151: =IF(ISNUMBER(BK151),BK151/$BP151,"") -> 377.25361 | BS151: =IF(ISNUMBER(BL151),BL151/$BP151,"") -> 199.91354 | BT151: =IF(ISNUMBER(BM151),BM151/$BP151,"") -> 833.03104 | BU151: 54526
A152: 1203 | B152: 40999 | C152: 8.5 | D152: 8.5607 | E152: 93.48885 | F152: 96.4 | G152: 97.3 | H152: 103.43 | I152: 99.48 | J152: 106.92 | K152: 105.91 | L152: #N/A | M152: 102.22 | N152: 99 | O152: 101.4 | P152: 104.438 | Q152: 99.084 | R152: 95.622 | S152: 102.283 | T152: 102.429 | U152: 100.339 | V152: 104.33 | W152: 102.481 | X152: 12712.547 | Y152: 24536.4 | Z152: 41976.5 | AA152: 12891 | AB152: 9080 | AC152: 114.6 | AD152: 115.5 | AE152: 247.13578 | AF152: 53.5921 | AG152: 54.743 | AH152: 52.3077 | AI152: 56.2581 | AJ152: 58.0963 | AK152: 51.0951 | AL152: 48.8242 | AM152: 53.5417 | AN152: 61.1706 | AO152: 58.0238 | AP152: 51.4077 | AQ152: 55.616 | AR152: 54.1442 | AS152: 56.3913 | AT152: 1.1301 | AU152: 50.6346 | AV152: 54.7692 | AW152: 54.7771 | AX152: 56.9231 | AY152: #N/A | AZ152: 50 | BA152: 17405.35 | BB152: =IF(ISNUMBER(VLOOKUP($B152,CEIC_DATA!$I$26:$N$353,Haver_M!BB$2,FALSE)),VLOOKUP($B152,CEIC_DATA!$I$26:$N$353,Haver_M!BB$2,FALSE),NA()) -> 100.07385 | BC152: =IF(ISNUMBER(VLOOKUP($B152,CEIC_DATA!$I$26:$N$353,Haver_M!BC$2,FALSE)),VLOOKUP($B152,CEIC_DATA!$I$26:$N$353,Haver_M!BC$2,FALSE),NA()) -> 114.9 | BD152: =IF(ISNUMBER(VLOOKUP($B152,CEIC_DATA!$I$26:$N$353,Haver_M!BD$2,FALSE)),VLOOKUP($B152,CEIC_DATA!$I$26:$N$353,Haver_M!BD$2,FALSE),NA()) -> 117.2 | BE152: =IF(ISNUMBER(VLOOKUP($B152,CEIC_DATA!$I$26:$N$353,Haver_M!BE$2,FALSE)),VLOOKUP($B152,CEIC_DATA!$I$26:$N$353,Haver_M!BE$2,FALSE),NA()) -> 33.6 | BF152: 1328604 | BG152: 98576 | BH152: 1835913 | BI152: 345665 | BJ152: 7828.35 | BK152: 19373.25 | BL152: 10229.6 | BM152: 42897.45 | BN152: 28839.37 | BO152: 42380.69 | BP152: 50.323 | BQ152: =IF(ISNUMBER(BJ152),BJ152/$BP152,"") -> 155.56207 | BR152: =IF(ISNUMBER(BK152),BK152/$BP152,"") -> 384.97804 | BS152: =IF(ISNUMBER(BL152),BL152/$BP152,"") -> 203.27882 | BT152: =IF(ISNUMBER(BM152),BM152/$BP152,"") -> 852.44222 | BU152: 53395
A153: 1204 | B153: 41029 | C153: 8 | D153: 8.6523 | E153: 92.26926 | F153: 97.8 | G153: 98.1 | H153: 102.43 | I153: 100.49 | J153: 101.2 | K153: 105.46 | L153: 103.73 | M153: 102.57 | N153: 100.29 | O153: 102.2 | P153: 102.53 | Q153: 100.425 | R153: 93.817 | S153: 102.206 | T153: 86.875 | U153: 106.875 | V153: 102.207 | W153: 102.686 | X153: 12604.663 | Y153: 24568.97 | Z153: 38205.43 | AA153: 10484 | AB153: 6510 | AC153: #N/A | AD153: #N/A | AE153: 202.43938 | AF153: 53.8349 | AG153: 54.9138 | AH153: 52.7635 | AI153: 56.0588 | AJ153: 61.09 | AK153: 50.9916 | AL153: 50.2205 | AM153: 49.0682 | AN153: 64.7623 | AO153: 57.1179 | AP153: 51.0258 | AQ153: 56.1872 | AR153: 58.6782 | AS153: 56.2926 | AT153: 1.1972 | AU153: 50.7549 | AV153: 54.7536 | AW153: 55.1051 | AX153: 56.3654 | AY153: #N/A | AZ153: 49.6041 | BA153: 17288 | BB153: =IF(ISNUMBER(VLOOKUP($B153,CEIC_DATA!$I$26:$N$353,Haver_M!BB$2,FALSE)),VLOOKUP($B153,CEIC_DATA!$I$26:$N$353,Haver_M!BB$2,FALSE),NA()) -> 100.24606 | BC153: =IF(ISNUMBER(VLOOKUP($B153,CEIC_DATA!$I$26:$N$353,Haver_M!BC$2,FALSE)),VLOOKUP($B153,CEIC_DATA!$I$26:$N$353,Haver_M!BC$2,FALSE),NA()) -> #N/A | BD153: =IF(ISNUMBER(VLOOKUP($B153,CEIC_DATA!$I$26:$N$353,Haver_M!BD$2,FALSE)),VLOOKUP($B153,CEIC_DATA!$I$26:$N$353,Haver_M!BD$2,FALSE),NA()) -> #N/A | BE153: =IF(ISNUMBER(VLOOKUP($B153,CEIC_DATA!$I$26:$N$353,Haver_M!BE$2,FALSE)),VLOOKUP($B153,CEIC_DATA!$I$26:$N$353,Haver_M!BE$2,FALSE),NA()) -> #N/A | BF153: 1349820 | BG153: 60847 | BH153: 1737652 | BI153: 265213 | BJ153: 7851.6 | BK153: 19362.99 | BL153: 10250.05 | BM153: 42899.11 | BN153: 23791.86 | BO153: 38171.04 | BP153: 51.8029 | BQ153: =IF(ISNUMBER(BJ153),BJ153/$BP153,"") -> 151.5668 | BR153: =IF(ISNUMBER(BK153),BK153/$BP153,"") -> 373.78197 | BS153: =IF(ISNUMBER(BL153),BL153/$BP153,"") -> 197.86634 | BT153: =IF(ISNUMBER(BM153),BM153/$BP153,"") -> 828.12178 | BU153: 71211
A154: 1205 | B154: 41060 | C154: 8 | D154: 8.4599 | E154: 90.04146 | F154: 98.6 | G154: 98.8 | H154: 104.88 | I154: 102.21 | J154: 104.46 | K154: 105.73 | L154: 111.03 | M154: 106.72 | N154: 102.04 | O154: 104.2 | P154: 106.505 | Q154: 101.495 | R154: 91.628 | S154: 103.481 | T154: 88.527 | U154: 113.644 | V154: 103.981 | W154: 103.292 | X154: 12886.158 | Y154: 24776.64 | Z154: 39427.14 | AA154: 12052 | AB154: 7711 | AC154: #N/A | AD154: #N/A | AE154: 250.03696 | AF154: 55.2539 | AG154: 54.8081 | AH154: 54.6938 | AI154: 56.4165 | AJ154: 59.5748 | AK154: 51.207 | AL154: 49.6898 | AM154: 50.4357 | AN154: 64.2415 | AO154: 57.9576 | AP154: 51.5221 | AQ154: 56.1892 | AR154: 57.7881 | AS154: 56.163 | AT154: 1.1563 | AU154: 50.5076 | AV154: 56.3688 | AW154: 55.3058 | AX154: 57.396 | AY154: #N/A | AZ154: 50.9445 | BA154: 16396.23 | BB154: =IF(ISNUMBER(VLOOKUP($B154,CEIC_DATA!$I$26:$N$353,Haver_M!BB$2,FALSE)),VLOOKUP($B154,CEIC_DATA!$I$26:$N$353,Haver_M!BB$2,FALSE),NA()) -> 99.891579 | BC154: =IF(ISNUMBER(VLOOKUP($B154,CEIC_DATA!$I$26:$N$353,Haver_M!BC$2,FALSE)),VLOOKUP($B154,CEIC_DATA!$I$26:$N$353,Haver_M!BC$2,FALSE),NA()) -> #N/A | BD154: =IF(ISNUMBER(VLOOKUP($B154,CEIC_DATA!$I$26:$N$353,Haver_M!BD$2,FALSE)),VLOOKUP($B154,CEIC_DATA!$I$26:$N$353,Haver_M!BD$2,FALSE),NA()) -> #N/A | BE154: =IF(ISNUMBER(VLOOKUP($B154,CEIC_DATA!$I$26:$N$353,Haver_M!BE$2,FALSE)),VLOOKUP($B154,CEIC_DATA!$I$26:$N$353,Haver_M!BE$2,FALSE),NA()) -> #N/A | BF154: 1367062 | BG154: 69894 | BH154: 1759510 | BI154: 267370 | BJ154: 7882.82 | BK154: 19493.69 | BL154: 10123.43 | BM154: 42902.72 | BN154: 24821.44 | BO154: 42187.32 | BP154: 54.4735 | BQ154: =IF(ISNUMBER(BJ154),BJ154/$BP154,"") -> 144.70926 | BR154: =IF(ISNUMBER(BK154),BK154/$BP154,"") -> 357.85639 | BS154: =IF(ISNUMBER(BL154),BL154/$BP154,"") -> 185.84137 | BT154: =IF(ISNUMBER(BM154),BM154/$BP154,"") -> 787.58883 | BU154: 82411
A155: 1206 | B155: 41090 | C155: 8 | D155: 8.2269 | E155: 89.34724 | F155: 99.8 | G155: 99.6 | H155: 103.72 | I155: 101.32 | J155: 102.49 | K155: 104.42 | L155: 101.77 | M155: 107.25 | N155: 107.32 | O155: 103.1 | P155: 104.604 | Q155: 100.27 | R155: 91.032 | S155: 104.748 | T155: 94.496 | U155: 105.955 | V155: 104.444 | W155: 105.303 | X155: 13077.198 | Y155: 24699.34 | Z155: 37075.12 | AA155: 10843 | AB155: 6317 | AC155: 106.7 | AD155: 115.2 | AE155: 310.10712 | AF155: 55.6668 | AG155: 55.0207 | AH155: 54.2935 | AI155: 58.5172 | AJ155: 58.5034 | AK155: 52.3774 | AL155: 51.7512 | AM155: 51.2754 | AN155: 65.0828 | AO155: 56.2441 | AP155: 52.8928 | AQ155: 52.3286 | AR155: 59.5259 | AS155: 51.4892 | AT155: 1.1061 | AU155: 51.1061 | AV155: 56.1847 | AW155: 55.6855 | AX155: 57.3817 | AY155: #N/A | AZ155: 48.6923 | BA155: 16737.14 | BB155: =IF(ISNUMBER(VLOOKUP($B155,CEIC_DATA!$I$26:$N$353,Haver_M!BB$2,FALSE)),VLOOKUP($B155,CEIC_DATA!$I$26:$N$353,Haver_M!BB$2,FALSE),NA()) -> 99.124098 | BC155: =IF(ISNUMBER(VLOOKUP($B155,CEIC_DATA!$I$26:$N$353,Haver_M!BC$2,FALSE)),VLOOKUP($B155,CEIC_DATA!$I$26:$N$353,Haver_M!BC$2,FALSE),NA()) -> 107.4 | BD155: =IF(ISNUMBER(VLOOKUP($B155,CEIC_DATA!$I$26:$N$353,Haver_M!BD$2,FALSE)),VLOOKUP($B155,CEIC_DATA!$I$26:$N$353,Haver_M!BD$2,FALSE),NA()) -> 116.8 | BE155: =IF(ISNUMBER(VLOOKUP($B155,CEIC_DATA!$I$26:$N$353,Haver_M!BE$2,FALSE)),VLOOKUP($B155,CEIC_DATA!$I$26:$N$353,Haver_M!BE$2,FALSE),NA()) -> 34.9 | BF155: 1325433 | BG155: 73524 | BH155: 1714555 | BI155: 261324 | BJ155: 8009.27 | BK155: 19991.26 | BL155: 10485.13 | BM155: 43989.26 | BN155: 24924.26 | BO155: 36157.37 | BP155: 56.0302 | BQ155: =IF(ISNUMBER(BJ155),BJ155/$BP155,"") -> 142.94559 | BR155: =IF(ISNUMBER(BK155),BK155/$BP155,"") -> 356.79437 | BS155: =IF(ISNUMBER(BL155),BL155/$BP155,"") -> 187.13355 | BT155: =IF(ISNUMBER(BM155),BM155/$BP155,"") -> 785.09911 | BU155: 80569
A156: 1207 | B156: 41121 | C156: 8 | D156: 8.2631 | E156: 91.19601 | F156: 101.1 | G156: 100.1 | H156: 102.39 | I156: 100.57 | J156: 103.5 | K156: 101.31 | L156: 104.87 | M156: 101.6 | N156: 106.34 | O156: 104 | P156: 103.509 | Q156: 100.414 | R156: 88.353 | S156: 105.353 | T156: 97.863 | U156: 109.895 | V156: 103.462 | W156: 102.406 | X156: 13282.872 | Y156: 23440.61 | Z156: 39390.58 | AA156: 11065 | AB156: 6500 | AC156: #N/A | AD156: #N/A | AE156: 148.88491 | AF156: 54.3628 | AG156: 52.8885 | AH156: 54.2041 | AI156: 54.6923 | AJ156: 54.9254 | AK156: 51.1819 | AL156: 50.0805 | AM156: 50.135 | AN156: 61.9246 | AO156: 52.0043 | AP156: 50.4972 | AQ156: 49.6568 | AR156: 57.48 | AS156: 47.5406 | AT156: 1.0877 | AU156: 51.0851 | AV156: 55.6032 | AW156: 55.7011 | AX156: 54.5028 | AY156: #N/A | AZ156: 50.6164 | BA156: 17210.19 | BB156: =IF(ISNUMBER(VLOOKUP($B156,CEIC_DATA!$I$26:$N$353,Haver_M!BB$2,FALSE)),VLOOKUP($B156,CEIC_DATA!$I$26:$N$353,Haver_M!BB$2,FALSE),NA()) -> 98.141655 | BC156: =IF(ISNUMBER(VLOOKUP($B156,CEIC_DATA!$I$26:$N$353,Haver_M!BC$2,FALSE)),VLOOKUP($B156,CEIC_DATA!$I$26:$N$353,Haver_M!BC$2,FALSE),NA()) -> #N/A | BD156: =IF(ISNUMBER(VLOOKUP($B156,CEIC_DATA!$I$26:$N$353,Haver_M!BD$2,FALSE)),VLOOKUP($B156,CEIC_DATA!$I$26:$N$353,Haver_M!BD$2,FALSE),NA()) -> #N/A | BE156: =IF(ISNUMBER(VLOOKUP($B156,CEIC_DATA!$I$26:$N$353,Haver_M!BE$2,FALSE)),VLOOKUP($B156,CEIC_DATA!$I$26:$N$353,Haver_M!BE$2,FALSE),NA()) -> #N/A | BF156: 1291125 | BG156: 73499 | BH156: 1681051 | BI156: 251075 | BJ156: 7999.61 | BK156: 19649.54 | BL156: 10356.07 | BM156: 43458.1 | BN156: 23099.88 | BO156: 40619.44 | BP156: 55.4948 | BQ156: =IF(ISNUMBER(BJ156),BJ156/$BP156,"") -> 144.15062 | BR156: =IF(ISNUMBER(BK156),BK156/$BP156,"") -> 354.07894 | BS156: =IF(ISNUMBER(BL156),BL156/$BP156,"") -> 186.61334 | BT156: =IF(ISNUMBER(BM156),BM156/$BP156,"") -> 783.1022 | BU156: 76105
...

Sheet Haver_Q
C1: GDP | D1: GDPPRIV | E1: GDPGOVT | F1: GDPGFCF | G1: GDPX | H1: GDPM | I1: GPMGDP | J1: BUSINESS | K1: BUSINESSEXP | L1: GDPYOY
A2: 1001 !Q | B2: .excel_last | C2: ="difa%("&O2&")" -> difa%(H534NGPC@EMERGEPR) | D2: ="difa%("&P2&")" -> difa%(H534NCPC@EMERGEPR) | E2: ="difa%("&Q2&")" -> difa%(H534NCGC@EMERGEPR) | F2: ="difa%("&R2&")" -> difa%(H534NFC@EMERGEPR) | G2: ="difa%("&T2&")" -> difa%(H534NXC@EMERGEPR) | H2: ="difa%("&U2&")" -> difa%(H534NMC@EMERGEPR) | L2: yryr%(N534NGPC@EMERGEPR) | O2: H534NGPC@EMERGEPR | P2: H534NCPC@EMERGEPR | Q2: H534NCGC@EMERGEPR | R2: H534NFC@EMERGEPR | S2: H534NBC@EMERGEPR | T2: H534NXC@EMERGEPR | U2: H534NMC@EMERGEPR | V2: H534NSDC@EMERGEPR | W2: H534NBDC@EMERGEPR
A3: .DESC | C3: India: GDP at Market Prices (SA, Apr.11-Mar.12.Rupees) % Change - Annual Rate | D3: India: GDP: Private Final Consumption Expenditure (SA, Apr.11-Mar.12.Rupees) % Change - Annual Rate | E3: India: GDP: Government Final Consumption Expenditure (SA, Apr.11-Mar.12.INR) % Change - Annual Rate | F3: India: GDP: Gross Fixed Capital Formation (SA, Apr.11-Mar.12.Rupees) % Change - Annual Rate | G3: India: GDP: Exports of Goods and Services (SA, Apr.11-Mar.12.Rupees) % Change - Annual Rate | H3: India: GDP: Imports of Goods and Services (SA, Apr.11-Mar.12.Rupees) % Change - Annual Rate | L3: India: GDP at Market Prices (NSA, Apr.11-Mar.12.Rupees) % Change - Year to Year | O3: India: GDP at Market Prices (SA, Bil.Apr.11-Mar.12.Rupees) | P3: India: GDP: Private Final Consumption Expenditure (SA, Bil.Apr.11-Mar.12.Rupees) | Q3: India: GDP: Government Final Consumption Expenditure (SA, Bil.Apr.11-Mar.12.INR) | R3: India: GDP: Gross Fixed Capital Formation (SA, Bil.Apr.11-Mar.12.Rupees) | S3: India: GDP: Change in Stocks (SA, Bil.Apr.11-Mar.12.Rupees) | T3: India: GDP: Exports of Goods and Services (SA, Bil.Apr.11-Mar.12.Rupees) | U3: India: GDP: Imports of Goods and Services (SA, Bil.Apr.11-Mar.12.Rupees) | V3: India: GDP: Statistical Discrepancy (SA, Bil.Apr.11-Mar.12.Rupees) | W3: India: GDP: Valuables (SA, Bil.Apr.11-Mar.12.Rupees)
A4: .T1 | C4: Q2-1996 | D4: Q2-1996 | E4: Q2-1996 | F4: Q2-1996 | G4: Q2-1996 | H4: Q2-1996 | L4: Q2-1996 | O4: Q2-1996 | P4: Q2-1996 | Q4: Q2-1996 | R4: Q2-1996 | S4: Q2-1996 | T4: Q2-1996 | U4: Q2-1996 | V4: Q2-1999 | W4: Q2-1999
A5: .TN | C5: Q3-2019 | D5: Q3-2019 | E5: Q3-2019 | F5: Q3-2019 | G5: Q3-2019 | H5: Q3-2019 | L5: Q3-2019 | O5: Q3-2019 | P5: Q3-2019 | Q5: Q3-2019 | R5: Q3-2019 | S5: Q3-2019 | T5: Q3-2019 | U5: Q3-2019 | V5: Q3-2019 | W5: Q3-2019
A6: 001 | B6: 36616 | C6: 0.10298596 | D6: -0.080891714 | E6: -0.27771343 | F6: 0.16943464 | G6: 0.41846563 | H6: 0.40045025 | I6: 5.3384295 | L6: 0.072432586 | O6: 9749.07 | P6: 5731.11 | Q6: 1243.68 | R6: 2357.3 | S6: 431.41 | T6: 1014.89 | U6: 1647.53 | V6: 534.19 | W6: 84.02
A7: 002 | B7: 36707 | C7: 0.0083467931 | D7: -0.069146974 | E7: -0.036477147 | F7: -0.056131956 | G7: 0.012632194 | H7: -0.45554436 | I7: 5.031488 | L7: 0.052297761 | O7: 9769.35 | P7: 5629.36 | Q7: 1232.18 | R7: 2323.5 | S7: 345.84 | T7: 1018.08 | U7: 1415.22 | V7: 555.48 | W7: 80.13
A8: 003 | B8: 36799 | C8: 0.037168714 | D8: 0.098204012 | E8: 0.22795888 | F8: -0.026654259 | G8: 0.038376154 | H8: 0.33707978 | I8: 3.1388242 | L8: 0.066273572 | O8: 9858.89 | P8: 5762.75 | Q8: 1297.09 | R8: 2307.86 | S8: 351.37 | T8: 1027.71 | U8: 1521.82 | V8: 553.09 | W8: 80.84
A9: 004 | B9: 36891 | C9: 0.01372271 | D9: 0.1347202 | E9: -0.078961034 | F9: -0.063345716 | G9: 0.49900807 | H9: 0.17153646 | I9: 2.831619 | L9: 0.038146346 | O9: 9892.54 | P9: 5947.74 | Q9: 1270.69 | R9: 2270.41 | S9: 212.98 | T9: 1137.16 | U9: 1583.26 | V9: 556.22 | W9: 80.6
A10: 011 | B10: 36981 | C10: 0.0076315179 | D10: 0.018739009 | E10: 0.4281147 | F10: -0.038028668 | G10: 0.059094445 | H10: -0.085866707 | I10: 1.8286258 | L10: 0.010917664 | O10: 9911.36 | P10: 5975.41 | Q10: 1389.09 | R10: 2248.51 | S10: 297.14 | T10: 1153.6 | U10: 1548.12 | V10: 308.55 | W10: 87.18
A11: 012 | B11: 37072 | C11: 0.094898379 | D11: 0.10341268 | E11: -0.14356514 | F11: 0.34125045 | G11: 0.14381384 | H11: 0.13768823 | I11: 1.9835864 | L11: 0.03841364 | O11: 10138.57 | P11: 6124.24 | Q11: 1336.3 | R11: 2419.76 | S11: 253.83 | T11: 1193.01 | U11: 1598.86 | V11: 333.6 | W11: 76.69
A12: 013 | B12: 37164 | C12: 0.031243569 | D12: 0.017037228 | E12: -0.10329025 | F12: -0.046892377 | G12: -0.30579566 | H12: 0.013098135 | I12: 0.88840616 | L12: 0.043623591 | O12: 10216.85 | P12: 6150.16 | Q12: 1300.37 | R12: 2390.88 | S12: 226.51 | T12: 1088.97 | U12: 1604.07 | V12: 587.09 | W12: 76.94
A13: 014 | B13: 37256 | C13: 0.1292502 | D13: 0.059153327 | E13: 0.35318165 | F13: 0.15527607 | G13: 0.06843106 | H13: -0.18175975 | I13: 1.8425459 | L13: 0.062866803 | O13: 10532.09 | P13: 6239.16 | Q13: 1402.51 | R13: 2478.73 | S13: 202.35 | T13: 1107.14 | U13: 1525.61 | V13: 549.08 | W13: 78.73
A14: 021 | B14: 37346 | C14: 0.0090161959 | D14: 0.012663961 | E14: -0.1757537 | F14: 0.070197837 | G14: 0.26209661 | H14: 0.062915773 | I14: 3.3692314 | L14: 0.061150813 | O14: 10555.75 | P14: 6258.82 | Q14: 1336.35 | R14: 2521.13 | S14: 217.74 | T14: 1173.48 | U14: 1549.06 | V14: 519.15 | W14: 78.14
A15: 022 | B15: 37437 | C15: 0.043371935 | D15: -0.016841461 | E15: -0.15082821 | F15: 0.010656611 | G15: 1.0994839 | H15: 0.11644551 | I15: 4.3446296 | L15: 0.050723819 | O15: 10668.39 | P15: 6232.3 | Q15: 1282.83 | R15: 2527.82 | S15: 325.16 | T15: 1412.55 | U15: 1592.31 | V15: 412.46 | W15: 67.58
A16: 023 | B16: 37529 | C16: 0.0013429589 | D16: 0.030140818 | E16: 0.04118786 | F16: 0.10639596 | G16: -0.11997675 | H16: 0.24853706 | I16: 3.4716421 | L16: 0.053333461 | O16: 10671.97 | P16: 6278.74 | Q16: 1295.84 | R16: 2592.53 | S16: 316.77 | T16: 1368.13 | U16: 1683.17 | V16: 429.4 | W16: 73.73
A17: 024 | B17: 37621 | C17: 0.042458985 | D17: 0.084560084 | E17: 0.23368133 | F17: 0.12651077 | G17: 0.037891688 | H17: 0.14446715 | I17: 2.4451578 | L17: 0.019690116 | O17: 10783.49 | P17: 6407.46 | Q17: 1365.69 | R17: 2670.9 | S17: 319.46 | T17: 1380.91 | U17: 1740.92 | V17: 301.44 | W17: 78.55
... A49: 104 | B49: 40543 | C49: 0.13915256 | D49: -0.036736549 | E49: 0.049709634 | F49: 0.30224953 | G49: 0.60136005 | H49: 0.10357525 | I49: 4.8324771 | L49: 0.10690423 | O49: 20753.64 | P49: 11063.72 | Q49: 2287.82 | R49: 7024.47 | S49: 744.66 | T49: 4859.2 | U49: 5559.27 | V49: -266.72 | W49: 599.76
A50: 111 | B50: 40633 | C50: 0.088866212 | D50: 0.22855971 | E50: 0.13429488 | F50: 0.02932423 | G50: 0.25568462 | H50: 0.25668005 | I50: 4.1425236 | L50: 0.10326062 | N50: 2011Q1 | O50: 21200.1 | P50: 11647.97 | Q50: 2361.04 | R50: 7075.41 | S50: 772.97 | T50: 5143.81 | U50: 5886.05 | V50: -512.95 | W50: 597.9
A51: 112 | B51: 40724 | C51: 0.051238887 | D51: 0.14693717 | E51: -0.13424047 | F51: 0.14996361 | G51: -0.017819678 | H51: 0.49059468 | I51: 3.2539486 | L51: 0.08319065 | N51: 2011Q2 | O51: 21466.6 | P51: 12054.11 | Q51: 2277.47 | R51: 7326.94 | S51: 529.28 | T51: 5120.74 | U51: 6503.75 | V51: 87.86 | W51: 573.95
A52: 113 | B52: 40816 | C52: -0.015899395 | D52: 0.0018064158 | E52: 0.15746396 | F52: 0.025511619 | G52: -0.0085570999 | H52: -0.097432441 | I52: 3.2996467 | L52: 0.066770618 | N52: 2011Q3 | O52: 21380.76 | P52: 12059.55 | Q52: 2362.27 | R52: 7373.23 | S52: 517.55 | T52: 5109.75 | U52: 6339.19 | V52: -343.96 | W52: 641.56
A53: 114 | B53: 40908 | C53: 0.12744341 | D53: 0.092218435 | E53: 0.22414717 | F53: 0.077773809 | G53: 0.3651791 | H53: 0.53924456 | I53: 3.4300128 | L53: 0.061760153 | N53: 2011Q4 | O53: 22031.64 | P53: 12328.45 | Q53: 2484.78 | R53: 7512.59 | S53: 513.94 | T53: 5523.28 | U53: 7060.91 | V53: 87.98 | W53: 641.53
A54: 121 | B54: 40999 | C54: 0.079823306 | D54: 0.07118318 | E54: 0.24207367 | F54: 0.16032687 | G54: 0.085620791 | H54: 0.096812261 | I54: 4.2483499 | L54: 0.056325329 | N54: 2012Q1 | O54: 22458.72 | P54: 12542.22 | Q54: 2623.16 | R54: 7797.13 | S54: 508.87 | T54: 5637.89 | U54: 7225.93 | V54: -89.26 | W54: 664.64
A55: 122 | B55: 41090 | C55: 0.0121824 | D55: -0.12077882 | E55: -0.24622674 | F55: 0.050453337 | G55: -0.11923332 | H55: -0.1721104 | I55: 2.3173451 | L55: 0.048676495 | N55: 2012Q2 | O55: 22526.81 | P55: 12145.04 | Q55: 2444.19 | R55: 7893.67 | S55: 508.63 | T55: 5461.75 | U55: 6892.66 | V55: 286.8 | W55: 679.39
A56: 123 | B56: 41182 | C56: 0.057861908 | D56: 0.31761065 | E56: 0.25413319 | F56: -0.04749274 | G56: 0.99634198 | H56: 0.28563733 | I56: 2.9352427 | L56: 0.074931836 | N56: 2012Q3 | O56: 22845.83 | P56: 13012.05 | Q56: 2586.55 | R56: 7798.23 | S56: 521.7 | T56: 6492.18 | U56: 7339.5 | V56: -863.98 | W56: 638.6
A57: 124 | B57: 41274 | C57: 0.070289931 | D57: 0.11282447 | E57: -0.51813908 | F57: -0.017528618 | G57: -0.5532042 | H57: -0.0088755442 | I57: 2.800003 | L57: 0.053763929 | N57: 2012Q4 | O57: 23237.12 | P57: 13364.49 | Q57: 2155.02 | R57: 7763.83 | S57: 508.56 | T57: 5307.84 | U57: 7323.16 | V57: 819.33 | W57: 641.21
A58: 131 | B58: 41364 | C58: 0.059737849 | D58: -0.056803616 | E58: 1.145779 | F58: 0.15440793 | G58: 0.24803453 | H58: -0.062063629 | I58: 3.714431 | L58: 0.042960336 | N58: 2013Q1 | O58: 23576.64 | P58: 13170.52 | Q58: 2608.24 | R58: 8047.59 | S58: 470.75 | T58: 5610.15 | U58: 7206.79 | V58: 245.09 | W58: 631.09
A59: 132 | B59: 41455 | C59: 0.061592498 | D59: 0.037330072 | E59: 0.25998667 | F59: -0.014179176 | G59: 0.061503537 | H59: -0.24271538 | I59: 3.6774311 | L59: 0.064471031 | N59: 2013Q2 | O59: 23931.58 | P59: 13291.75 | Q59: 2763.37 | R59: 8018.91 | S59: 354.45 | T59: 5694.49 | U59: 6722.9 | V59: 171.09 | W59: 360.42
A60: 133 | B60: 41547 | C60: 0.066919483 | D60: 0.12286641 | E60: -0.33053803 | F60: -0.043159629 | G60: 0.54800868 | H60: -0.010318457 | I60: 4.2666244 | L60: 0.073377487 | N60: 2013Q3 | O60: 24322.28 | P60: 13682.46 | Q60: 2499.6 | R60: 7930.95 | S60: 325.67 | T60: 6351.82 | U60: 6705.49 | V60: -138.93 | W60: 376.2
A61: 134 | B61: 41639 | C61: 0.089467639 | D61: 0.19281531 | E61: -0.38812775 | F61: 0.032237499 | G61: -0.090874274 | H61: -0.21369728 | I61: 3.6445539 | L61: 0.065349777 | N61: 2013Q4 | O61: 24848.94 | P61: 14299.06 | Q61: 2210.73 | R61: 7994.11 | S61: 342.35 | T61: 6202.32 | U61: 6314.34 | V61: -250.08 | W61: 364.79
... A84: 193 | B84: 43738 | C84: 0.044720431 | D84: 0.16294483 | E84: 0.39683153 | F84: -0.020244037 | G84: -0.10278138 | H84: -0.20225825 | I84: 2.9608417 | L84: 0.045485586 | N84: 2019Q3 | O84: 36535.18 | P84: 20933.09 | Q84: 4263.54 | R84: 11564.5 | S84: 391.14 | T84: 7218.52 | U84: 8529.43 | V84: 294.08 | W84: 399.74
N85: 2019Q4
N86: 2020Q1
N87: 2020Q2
N88: 2020Q3
N89: 2020Q4

Sheet CEIC_DATA
A1: Select this link and click Refresh/Edit Download to update data and add or remove series | B1: RBI: Industrial Outlook Survey: Business Expectation Index: Assessment for Current Quarter | C1: RBI Forecast: Industrial Outlook Survey: Business Expectation Index: Expectation for Next Quarter | D1: RBI Forecast: Industrial Outlook Survey: Overall Business Situation | E1: CEIC Leading Indicator: India | F1: CEIC Leading Indicator: Smoothed: India
A2: Region | B2: India | C2: India | D2: India | E2: India | F2: India
A3: Subnational
A4: Frequency | B4: Quarterly, Ending "mar, June, Sep, Dec" | C4: Quarterly, Ending "mar, June, Sep, Dec" | D4: Quarterly, Ending "mar, June, Sep, Dec" | E4: Monthly | F4: Monthly
A5: Unit | B5: NA | C5: NA | D5: % | E5: NA | F5: NA
A6: Source | B6: Reserve Bank of India | C6: Reserve Bank of India | D6: Reserve Bank of India | E6: CEIC Data | F6: CEIC Data
A7: Status | B7: Active | C7: Active | D7: Active | E7: Active | F7: Active
A8: Series ID | B8: 224244002 | C8: 234029202 | D8: 224244202 (ISAAAAAB) | E8: 412736927 (ISAAAALNAAAAYE) | F8: 412736937 (ISAAAALNAAAAYF)
A9: SR Code | B9: SR7033552 | C9: SR7033596 | D9: SR4271955 | E9: SR125637687 | F9: SR125637697
A10: Mnemonic
A11: Function Information
A12: First Obs. Date | B12: 36586 | C12: 36678 | D12: 36678 | E12: 35004 | F12: 35004
A13: Last Obs. Date | B13: 43800 | C13: 43891 | D13: 43891 | E13: 43831 | F13: 43831
A14: Last Update time | B14: 43867 | C14: 43867 | D14: 43867 | E14: 43875 | F14: 43875
A15: Series Remarks
A16: Suggestions
A17: Mean | B17: 110.91125 | C17: 117.38375 | D17: 38.74125 | E17: 100.14201 | F17: 100.1431
A18: Variance | B18: 71.630631 | C18: 34.402391 | D18: 77.965998 | E18: 68.969216 | F18: 49.347962
A19: Standard Deviation | B19: 8.4634881 | C19: 5.8653551 | D19: 8.8298357 | E19: 8.3047707 | F19: 7.0248104
A20: Skewness | B20: -0.45507728 | C20: -0.7066849 | D20: -0.33475063 | E20: -0.29608189 | F20: 0.021971553
A21: Kurtosis | B21: 0.41321752 | C21: 1.2380357 | D21: -0.017799975 | E21: 1.0999979 | F21: 0.91922284
A22: Coefficient Variation | B22: 0.076308653 | C22: 0.049967352 | D22: 0.22791819 | E22: 0.082929942 | F22: 0.070147721
A23: Min | B23: 82.6 | C23: 96.4 | D23: 11.2 | E23: 65.627514 | F23: 77.584025
A24: Max | B24: 127.7 | C24: 127.5 | D24: 53.8 | E24: 124.19616 | F24: 118.91702
A25: Median | B25: 110.05 | C25: 117.45 | D25: 36.95 | E25: 100.48893 | F25: 99.484244 | I25: 1 | J25: 2 | K25: 3 | L25: 4 | M25: 5 | N25: 6
A26: No. of Obs | B26: 80 | C26: 80 | D26: 80 | E26: 291 | F26: 291 | J26: =B1 -> RBI: Industrial Outlook Survey: Business Expectation Index: Assessment for Current Quarter | K26: =C1 -> RBI Forecast: Industrial Outlook Survey: Business Expectation Index: Expectation for Next Quarter | L26: =D1 -> RBI Forecast: Industrial Outlook Survey: Overall Business Situation | M26: =E1 -> CEIC Leading Indicator: India | N26: =F1 -> CEIC Leading Indicator: Smoothed: India
A27: 35004 | E27: 95.480275 | F27: 94.561876 | H27: =A27 -> 35004 | I27: 35033 | J27: =IF(ISNUMBER(VLOOKUP($H27,$A$27:$F$369,J$25,FALSE)),VLOOKUP($H27,$A$27:$F$369,J$25,FALSE),NA()) -> #N/A | K27: =IF(ISNUMBER(VLOOKUP($H27,$A$27:$F$369,K$25,FALSE)),VLOOKUP($H27,$A$27:$F$369,K$25,FALSE),NA()) -> #N/A | L27: =IF(ISNUMBER(VLOOKUP($H27,$A$27:$F$369,L$25,FALSE)),VLOOKUP($H27,$A$27:$F$369,L$25,FALSE),NA()) -> #N/A | M27: =IF(ISNUMBER(VLOOKUP($H27,$A$27:$F$369,M$25,FALSE)),VLOOKUP($H27,$A$27:$F$369,M$25,FALSE),NA()) -> 95.480275 | N27: =IF(ISNUMBER(VLOOKUP($H27,$A$27:$F$369,N$25,FALSE)),VLOOKUP($H27,$A$27:$F$369,N$25,FALSE),NA()) -> 94.561876
A28: 35034 | E28: 95.756128 | F28: 95.025222 | H28: =A28 -> 35034 | I28: 35064 | J28: =IF(ISNUMBER(VLOOKUP($H28,$A$27:$F$369,J$25,FALSE)),VLOOKUP($H28,$A$27:$F$369,J$25,FALSE),NA()) -> #N/A | K28: =IF(ISNUMBER(VLOOKUP($H28,$A$27:$F$369,K$25,FALSE)),VLOOKUP($H28,$A$27:$F$369,K$25,FALSE),NA()) -> #N/A | L28: =IF(ISNUMBER(VLOOKUP($H28,$A$27:$F$369,L$25,FALSE)),VLOOKUP($H28,$A$27:$F$369,L$25,FALSE),NA()) -> #N/A | M28: =IF(ISNUMBER(VLOOKUP($H28,$A$27:$F$369,M$25,FALSE)),VLOOKUP($H28,$A$27:$F$369,M$25,FALSE),NA()) -> 95.756128 | N28: =IF(ISNUMBER(VLOOKUP($H28,$A$27:$F$369,N$25,FALSE)),VLOOKUP($H28,$A$27:$F$369,N$25,FALSE),NA()) -> 95.025222
A29: 35065 | E29: 91.514894 | F29: 95.554167 | H29: =A29 -> 35065 | I29: 35095 | J29: =IF(ISNUMBER(VLOOKUP($H29,$A$27:$F$369,J$25,FALSE)),VLOOKUP($H29,$A$27:$F$369,J$25,FALSE),NA()) -> #N/A | K29: =IF(ISNUMBER(VLOOKUP($H29,$A$27:$F$369,K$25,FALSE)),VLOOKUP($H29,$A$27:$F$369,K$25,FALSE),NA()) -> #N/A | L29: =IF(ISNUMBER(VLOOKUP($H29,$A$27:$F$369,L$25,FALSE)),VLOOKUP($H29,$A$27:$F$369,L$25,FALSE),NA()) -> #N/A | M29: =IF(ISNUMBER(VLOOKUP($H29,$A$27:$F$369,M$25,FALSE)),VLOOKUP($H29,$A$27:$F$369,M$25,FALSE),NA()) -> 91.514894 | N29: =IF(ISNUMBER(VLOOKUP($H29,$A$27:$F$369,N$25,FALSE)),VLOOKUP($H29,$A$27:$F$369,N$25,FALSE),NA()) -> 95.554167
A30: 35096 | E30: 96.663707 | F30: 96.266519 | H30: =A30 -> 35096 | I30: 35124 | J30: =IF(ISNUMBER(VLOOKUP($H30,$A$27:$F$369,J$25,FALSE)),VLOOKUP($H30,$A$27:$F$369,J$25,FALSE),NA()) -> #N/A | K30: =IF(ISNUMBER(VLOOKUP($H30,$A$27:$F$369,K$25,FALSE)),VLOOKUP($H30,$A$27:$F$369,K$25,FALSE),NA()) -> #N/A | L30: =IF(ISNUMBER(VLOOKUP($H30,$A$27:$F$369,L$25,FALSE)),VLOOKUP($H30,$A$27:$F$369,L$25,FALSE),NA()) -> #N/A | M30: =IF(ISNUMBER(VLOOKUP($H30,$A$27:$F$369,M$25,FALSE)),VLOOKUP($H30,$A$27:$F$369,M$25,FALSE),NA()) -> 96.663707 | N30: =IF(ISNUMBER(VLOOKUP($H30,$A$27:$F$369,N$25,FALSE)),VLOOKUP($H30,$A$27:$F$369,N$25,FALSE),NA()) -> 96.266519
A31: 35125 | E31: 95.983354 | F31: 96.991567 | H31: =A31 -> 35125 | I31: 35155 | J31: =IF(ISNUMBER(VLOOKUP($H31,$A$27:$F$369,J$25,FALSE)),VLOOKUP($H31,$A$27:$F$369,J$25,FALSE),NA()) -> #N/A | K31: =IF(ISNUMBER(VLOOKUP($H31,$A$27:$F$369,K$25,FALSE)),VLOOKUP($H31,$A$27:$F$369,K$25,FALSE),NA()) -> #N/A | L31: =IF(ISNUMBER(VLOOKUP($H31,$A$27:$F$369,L$25,FALSE)),VLOOKUP($H31,$A$27:$F$369,L$25,FALSE),NA()) -> #N/A | M31: =IF(ISNUMBER(VLOOKUP($H31,$A$27:$F$369,M$25,FALSE)),VLOOKUP($H31,$A$27:$F$369,M$25,FALSE),NA()) -> 95.983354 | N31: =IF(ISNUMBER(VLOOKUP($H31,$A$27:$F$369,N$25,FALSE)),VLOOKUP($H31,$A$27:$F$369,N$25,FALSE),NA()) -> 96.991567
A32: 35156 | E32: 99.871832 | F32: 97.586969 | H32: =A32 -> 35156 | I32: 35185 | J32: =IF(ISNUMBER(VLOOKUP($H32,$A$27:$F$369,J$25,FALSE)),VLOOKUP($H32,$A$27:$F$369,J$25,FALSE),NA()) -> #N/A | K32: =IF(ISNUMBER(VLOOKUP($H32,$A$27:$F$369,K$25,FALSE)),VLOOKUP($H32,$A$27:$F$369,K$25,FALSE),NA()) -> #N/A | L32: =IF(ISNUMBER(VLOOKUP($H32,$A$27:$F$369,L$25,FALSE)),VLOOKUP($H32,$A$27:$F$369,L$25,FALSE),NA()) -> #N/A | M32: =IF(ISNUMBER(VLOOKUP($H32,$A$27:$F$369,M$25,FALSE)),VLOOKUP($H32,$A$27:$F$369,M$25,FALSE),NA()) -> 99.871832 | N32: =IF(ISNUMBER(VLOOKUP($H32,$A$27:$F$369,N$25,FALSE)),VLOOKUP($H32,$A$27:$F$369,N$25,FALSE),NA()) -> 97.586969
A33: 35186 | E33: 100.11664 | F33: 97.838369 | H33: =A33 -> 35186 | I33: 35216 | J33: =IF(ISNUMBER(VLOOKUP($H33,$A$27:$F$369,J$25,FALSE)),VLOOKUP($H33,$A$27:$F$369,J$25,FALSE),NA()) -> #N/A | K33: =IF(ISNUMBER(VLOOKUP($H33,$A$27:$F$369,K$25,FALSE)),VLOOKUP($H33,$A$27:$F$369,K$25,FALSE),NA()) -> #N/A | L33: =IF(ISNUMBER(VLOOKUP($H33,$A$27:$F$369,L$25,FALSE)),VLOOKUP($H33,$A$27:$F$369,L$25,FALSE),NA()) -> #N/A | M33: =IF(ISNUMBER(VLOOKUP($H33,$A$27:$F$369,M$25,FALSE)),VLOOKUP($H33,$A$27:$F$369,M$25,FALSE),NA()) -> 100.11664 | N33: =IF(ISNUMBER(VLOOKUP($H33,$A$27:$F$369,N$25,FALSE)),VLOOKUP($H33,$A$27:$F$369,N$25,FALSE),NA()) -> 97.838369
A34: 35217 | E34: 98.274346 | F34: 97.694614 | H34: =A34 -> 35217 | I34: 35246 | J34: =IF(ISNUMBER(VLOOKUP($H34,$A$27:$F$369,J$25,FALSE)),VLOOKUP($H34,$A$27:$F$369,J$25,FALSE),NA()) -> #N/A | K34: =IF(ISNUMBER(VLOOKUP($H34,$A$27:$F$369,K$25,FALSE)),VLOOKUP($H34,$A$27:$F$369,K$25,FALSE),NA()) -> #N/A | L34: =IF(ISNUMBER(VLOOKUP($H34,$A$27:$F$369,L$25,FALSE)),VLOOKUP($H34,$A$27:$F$369,L$25,FALSE),NA()) -> #N/A | M34: =IF(ISNUMBER(VLOOKUP($H34,$A$27:$F$369,M$25,FALSE)),VLOOKUP($H34,$A$27:$F$369,M$25,FALSE),NA()) -> 98.274346 | N34: =IF(ISNUMBER(VLOOKUP($H34,$A$27:$F$369,N$25,FALSE)),VLOOKUP($H34,$A$27:$F$369,N$25,FALSE),NA()) -> 97.694614
A35: 35247 | E35: 97.508869 | F35: 97.267287 | H35: =A35 -> 35247 | I35: 35277 | J35: =IF(ISNUMBER(VLOOKUP($H35,$A$27:$F$369,J$25,FALSE)),VLOOKUP($H35,$A$27:$F$369,J$25,FALSE),NA()) -> #N/A | K35: =IF(ISNUMBER(VLOOKUP($H35,$A$27:$F$369,K$25,FALSE)),VLOOKUP($H35,$A$27:$F$369,K$25,FALSE),NA()) -> #N/A | L35: =IF(ISNUMBER(VLOOKUP($H35,$A$27:$F$369,L$25,FALSE)),VLOOKUP($H35,$A$27:$F$369,L$25,FALSE),NA()) -> #N/A | M35: =IF(ISNUMBER(VLOOKUP($H35,$A$27:$F$369,M$25,FALSE)),VLOOKUP($H35,$A$27:$F$369,M$25,FALSE),NA()) -> 97.508869 | N35: =IF(ISNUMBER(VLOOKUP($H35,$A$27:$F$369,N$25,FALSE)),VLOOKUP($H35,$A$27:$F$369,N$25,FALSE),NA()) -> 97.267287
A36: 35278 | E36: 97.24894 | F36: 96.709377 | H36: =A36 -> 35278 | I36: 35308 | J36: =IF(ISNUMBER(VLOOKUP($H36,$A$27:$F$369,J$25,FALSE)),VLOOKUP($H36,$A$27:$F$369,J$25,FALSE),NA()) -> #N/A | K36: =IF(ISNUMBER(VLOOKUP($H36,$A$27:$F$369,K$25,FALSE)),VLOOKUP($H36,$A$27:$F$369,K$25,FALSE),NA()) -> #N/A | L36: =IF(ISNUMBER(VLOOKUP($H36,$A$27:$F$369,L$25,FALSE)),VLOOKUP($H36,$A$27:$F$369,L$25,FALSE),NA()) -> #N/A | M36: =IF(ISNUMBER(VLOOKUP($H36,$A$27:$F$369,M$25,FALSE)),VLOOKUP($H36,$A$27:$F$369,M$25,FALSE),NA()) -> 97.24894 | N36: =IF(ISNUMBER(VLOOKUP($H36,$A$27:$F$369,N$25,FALSE)),VLOOKUP($H36,$A$27:$F$369,N$25,FALSE),NA()) -> 96.709377
A37: 35309 | E37: 94.325761 | F37: 96.191132 | H37: =A37 -> 35309 | I37: 35338 | J37: =IF(ISNUMBER(VLOOKUP($H37,$A$27:$F$369,J$25,FALSE)),VLOOKUP($H37,$A$27:$F$369,J$25,FALSE),NA()) -> #N/A | K37: =IF(ISNUMBER(VLOOKUP($H37,$A$27:$F$369,K$25,FALSE)),VLOOKUP($H37,$A$27:$F$369,K$25,FALSE),NA()) -> #N/A | L37: =IF(ISNUMBER(VLOOKUP($H37,$A$27:$F$369,L$25,FALSE)),VLOOKUP($H37,$A$27:$F$369,L$25,FALSE),NA()) -> #N/A | M37: =IF(ISNUMBER(VLOOKUP($H37,$A$27:$F$369,M$25,FALSE)),VLOOKUP($H37,$A$27:$F$369,M$25,FALSE),NA()) -> 94.325761 | N37: =IF(ISNUMBER(VLOOKUP($H37,$A$27:$F$369,N$25,FALSE)),VLOOKUP($H37,$A$27:$F$369,N$25,FALSE),NA()) -> 96.191132
A38: 35339 | E38: 95.309393 | F38: 95.921339 | H38: =A38 -> 35339 | I38: 35369 | J38: =IF(ISNUMBER(VLOOKUP($H38,$A$27:$F$369,J$25,FALSE)),VLOOKUP($H38,$A$27:$F$369,J$25,FALSE),NA()) -> #N/A | K38: =IF(ISNUMBER(VLOOKUP($H38,$A$27:$F$369,K$25,FALSE)),VLOOKUP($H38,$A$27:$F$369,K$25,FALSE),NA()) -> #N/A | L38: =IF(ISNUMBER(VLOOKUP($H38,$A$27:$F$369,L$25,FALSE)),VLOOKUP($H38,$A$27:$F$369,L$25,FALSE),NA()) -> #N/A | M38: =IF(ISNUMBER(VLOOKUP($H38,$A$27:$F$369,M$25,FALSE)),VLOOKUP($H38,$A$27:$F$369,M$25,FALSE),NA()) -> 95.309393 | N38: =IF(ISNUMBER(VLOOKUP($H38,$A$27:$F$369,N$25,FALSE)),VLOOKUP($H38,$A$27:$F$369,N$25,FALSE),NA()) -> 95.921339
... A78: 36557 | E78: 124.19616 | F78: 118.91702 | H78: =A78 -> 36557 | I78: 36585 | J78: =IF(ISNUMBER(VLOOKUP($H78,$A$27:$F$369,J$25,FALSE)),VLOOKUP($H78,$A$27:$F$369,J$25,FALSE),NA()) -> #N/A | K78: =IF(ISNUMBER(VLOOKUP($H78,$A$27:$F$369,K$25,FALSE)),VLOOKUP($H78,$A$27:$F$369,K$25,FALSE),NA()) -> #N/A | L78: =IF(ISNUMBER(VLOOKUP($H78,$A$27:$F$369,L$25,FALSE)),VLOOKUP($H78,$A$27:$F$369,L$25,FALSE),NA()) -> #N/A | M78: =IF(ISNUMBER(VLOOKUP($H78,$A$27:$F$369,M$25,FALSE)),VLOOKUP($H78,$A$27:$F$369,M$25,FALSE),NA()) -> 124.19616 | N78: =IF(ISNUMBER(VLOOKUP($H78,$A$27:$F$369,N$25,FALSE)),VLOOKUP($H78,$A$27:$F$369,N$25,FALSE),NA()) -> 118.91702
A79: 36586 | B79: 122.8 | E79: 119.23876 | F79: 118.53685 | H79: =A79 -> 36586 | I79: 36616 | J79: =IF(ISNUMBER(VLOOKUP($H79,$A$27:$F$369,J$25,FALSE)),VLOOKUP($H79,$A$27:$F$369,J$25,FALSE),NA()) -> 122.8 | K79: =IF(ISNUMBER(VLOOKUP($H79,$A$27:$F$369,K$25,FALSE)),VLOOKUP($H79,$A$27:$F$369,K$25,FALSE),NA()) -> #N/A | L79: =IF(ISNUMBER(VLOOKUP($H79,$A$27:$F$369,L$25,FALSE)),VLOOKUP($H79,$A$27:$F$369,L$25,FALSE),NA()) -> #N/A | M79: =IF(ISNUMBER(VLOOKUP($H79,$A$27:$F$369,M$25,FALSE)),VLOOKUP($H79,$A$27:$F$369,M$25,FALSE),NA()) -> 119.23876 | N79: =IF(ISNUMBER(VLOOKUP($H79,$A$27:$F$369,N$25,FALSE)),VLOOKUP($H79,$A$27:$F$369,N$25,FALSE),NA()) -> 118.53685
A80: 36617 | E80: 116.7804 | F80: 117.60795 | H80: =A80 -> 36617 | I80: 36646 | J80: =IF(ISNUMBER(VLOOKUP($H80,$A$27:$F$369,J$25,FALSE)),VLOOKUP($H80,$A$27:$F$369,J$25,FALSE),NA()) -> #N/A | K80: =IF(ISNUMBER(VLOOKUP($H80,$A$27:$F$369,K$25,FALSE)),VLOOKUP($H80,$A$27:$F$369,K$25,FALSE),NA()) -> #N/A | L80: =IF(ISNUMBER(VLOOKUP($H80,$A$27:$F$369,L$25,FALSE)),VLOOKUP($H80,$A$27:$F$369,L$25,FALSE),NA()) -> #N/A | M80: =IF(ISNUMBER(VLOOKUP($H80,$A$27:$F$369,M$25,FALSE)),VLOOKUP($H80,$A$27:$F$369,M$25,FALSE),NA()) -> 116.7804 | N80: =IF(ISNUMBER(VLOOKUP($H80,$A$27:$F$369,N$25,FALSE)),VLOOKUP($H80,$A$27:$F$369,N$25,FALSE),NA()) -> 117.60795
A81: 36647 | E81: 115.5413 | F81: 116.38076 | H81: =A81 -> 36647 | I81: 36677 | J81: =IF(ISNUMBER(VLOOKUP($H81,$A$27:$F$369,J$25,FALSE)),VLOOKUP($H81,$A$27:$F$369,J$25,FALSE),NA()) -> #N/A | K81: =IF(ISNUMBER(VLOOKUP($H81,$A$27:$F$369,K$25,FALSE)),VLOOKUP($H81,$A$27:$F$369,K$25,FALSE),NA()) -> #N/A | L81: =IF(ISNUMBER(VLOOKUP($H81,$A$27:$F$369,L$25,FALSE)),VLOOKUP($H81,$A$27:$F$369,L$25,FALSE),NA()) -> #N/A | M81: =IF(ISNUMBER(VLOOKUP($H81,$A$27:$F$369,M$25,FALSE)),VLOOKUP($H81,$A$27:$F$369,M$25,FALSE),NA()) -> 115.5413 | N81: =IF(ISNUMBER(VLOOKUP($H81,$A$27:$F$369,N$25,FALSE)),VLOOKUP($H81,$A$27:$F$369,N$25,FALSE),NA()) -> 116.38076
A82: 36678 | B82: 115.2 | C82: 125.5 | D82: 53.8 | E82: 116.28013 | F82: 115.04659 | H82: =A82 -> 36678 | I82: 36707 | J82: =IF(ISNUMBER(VLOOKUP($H82,$A$27:$F$369,J$25,FALSE)),VLOOKUP($H82,$A$27:$F$369,J$25,FALSE),NA()) -> 115.2 | K82: =IF(ISNUMBER(VLOOKUP($H82,$A$27:$F$369,K$25,FALSE)),VLOOKUP($H82,$A$27:$F$369,K$25,FALSE),NA()) -> 125.5 | L82: =IF(ISNUMBER(VLOOKUP($H82,$A$27:$F$369,L$25,FALSE)),VLOOKUP($H82,$A$27:$F$369,L$25,FALSE),NA()) -> 53.8 | M82: =IF(ISNUMBER(VLOOKUP($H82,$A$27:$F$369,M$25,FALSE)),VLOOKUP($H82,$A$27:$F$369,M$25,FALSE),NA()) -> 116.28013 | N82: =IF(ISNUMBER(VLOOKUP($H82,$A$27:$F$369,N$25,FALSE)),VLOOKUP($H82,$A$27:$F$369,N$25,FALSE),NA()) -> 115.04659
A83: 36708 | E83: 110.28892 | F83: 113.73682 | H83: =A83 -> 36708 | I83: 36738 | J83: =IF(ISNUMBER(VLOOKUP($H83,$A$27:$F$369,J$25,FALSE)),VLOOKUP($H83,$A$27:$F$369,J$25,FALSE),NA()) -> #N/A | K83: =IF(ISNUMBER(VLOOKUP($H83,$A$27:$F$369,K$25,FALSE)),VLOOKUP($H83,$A$27:$F$369,K$25,FALSE),NA()) -> #N/A | L83: =IF(ISNUMBER(VLOOKUP($H83,$A$27:$F$369,L$25,FALSE)),VLOOKUP($H83,$A$27:$F$369,L$25,FALSE),NA()) -> #N/A | M83: =IF(ISNUMBER(VLOOKUP($H83,$A$27:$F$369,M$25,FALSE)),VLOOKUP($H83,$A$27:$F$369,M$25,FALSE),NA()) -> 110.28892 | N83: =IF(ISNUMBER(VLOOKUP($H83,$A$27:$F$369,N$25,FALSE)),VLOOKUP($H83,$A$27:$F$369,N$25,FALSE),NA()) -> 113.73682
A84: 36739 | E84: 112.35137 | F84: 112.67092 | H84: =A84 -> 36739 | I84: 36769 | J84: =IF(ISNUMBER(VLOOKUP($H84,$A$27:$F$369,J$25,FALSE)),VLOOKUP($H84,$A$27:$F$369,J$25,FALSE),NA()) -> #N/A | K84: =IF(ISNUMBER(VLOOKUP($H84,$A$27:$F$369,K$25,FALSE)),VLOOKUP($H84,$A$27:$F$369,K$25,FALSE),NA()) -> #N/A | L84: =IF(ISNUMBER(VLOOKUP($H84,$A$27:$F$369,L$25,FALSE)),VLOOKUP($H84,$A$27:$F$369,L$25,FALSE),NA()) -> #N/A | M84: =IF(ISNUMBER(VLOOKUP($H84,$A$27:$F$369,M$25,FALSE)),VLOOKUP($H84,$A$27:$F$369,M$25,FALSE),NA()) -> 112.35137 | N84: =IF(ISNUMBER(VLOOKUP($H84,$A$27:$F$369,N$25,FALSE)),VLOOKUP($H84,$A$27:$F$369,N$25,FALSE),NA()) -> 112.67092
A85: 36770 | B85: 116.1 | C85: 126.1 | D85: 49 | E85: 111.16392 | F85: 111.82207 | H85: =A85 -> 36770 | I85: 36799 | J85: =IF(ISNUMBER(VLOOKUP($H85,$A$27:$F$369,J$25,FALSE)),VLOOKUP($H85,$A$27:$F$369,J$25,FALSE),NA()) -> 116.1 | K85: =IF(ISNUMBER(VLOOKUP($H85,$A$27:$F$369,K$25,FALSE)),VLOOKUP($H85,$A$27:$F$369,K$25,FALSE),NA()) -> 126.1 | L85: =IF(ISNUMBER(VLOOKUP($H85,$A$27:$F$369,L$25,FALSE)),VLOOKUP($H85,$A$27:$F$369,L$25,FALSE),NA()) -> 49 | M85: =IF(ISNUMBER(VLOOKUP($H85,$A$27:$F$369,M$25,FALSE)),VLOOKUP($H85,$A$27:$F$369,M$25,FALSE),NA()) -> 111.16392 | N85: =IF(ISNUMBER(VLOOKUP($H85,$A$27:$F$369,N$25,FALSE)),VLOOKUP($H85,$A$27:$F$369,N$25,FALSE),NA()) -> 111.82207
A86: 36800 | E86: 110.79451 | F86: 111.14065 | H86: =A86 -> 36800 | I86: 36830 | J86: =IF(ISNUMBER(VLOOKUP($H86,$A$27:$F$369,J$25,FALSE)),VLOOKUP($H86,$A$27:$F$369,J$25,FALSE),NA()) -> #N/A | K86: =IF(ISNUMBER(VLOOKUP($H86,$A$27:$F$369,K$25,FALSE)),VLOOKUP($H86,$A$27:$F$369,K$25,FALSE),NA()) -> #N/A | L86: =IF(ISNUMBER(VLOOKUP($H86,$A$27:$F$369,L$25,FALSE)),VLOOKUP($H86,$A$27:$F$369,L$25,FALSE),NA()) -> #N/A | M86: =IF(ISNUMBER(VLOOKUP($H86,$A$27:$F$369,M$25,FALSE)),VLOOKUP($H86,$A$27:$F$369,M$25,FALSE),NA()) -> 110.79451 | N86: =IF(ISNUMBER(VLOOKUP($H86,$A$27:$F$369,N$25,FALSE)),VLOOKUP($H86,$A$27:$F$369,N$25,FALSE),NA()) -> 111.14065
A87: 36831 | E87: 111.10499 | F87: 110.53002 | H87: =A87 -> 36831 | I87: 36860 | J87: =IF(ISNUMBER(VLOOKUP($H87,$A$27:$F$369,J$25,FALSE)),VLOOKUP($H87,$A$27:$F$369,J$25,FALSE),NA()) -> #N/A | K87: =IF(ISNUMBER(VLOOKUP($H87,$A$27:$F$369,K$25,FALSE)),VLOOKUP($H87,$A$27:$F$369,K$25,FALSE),NA()) -> #N/A | L87: =IF(ISNUMBER(VLOOKUP($H87,$A$27:$F$369,L$25,FALSE)),VLOOKUP($H87,$A$27:$F$369,L$25,FALSE),NA()) -> #N/A | M87: =IF(ISNUMBER(VLOOKUP($H87,$A$27:$F$369,M$25,FALSE)),VLOOKUP($H87,$A$27:$F$369,M$25,FALSE),NA()) -> 111.10499 | N87: =IF(ISNUMBER(VLOOKUP($H87,$A$27:$F$369,N$25,FALSE)),VLOOKUP($H87,$A$27:$F$369,N$25,FALSE),NA()) -> 110.53002
A88: 36861 | B88: 113.9 | C88: 124.4 | D88: 51.7 | E88: 110.33327 | F88: 109.86881 | H88: =A88 -> 36861 | I88: 36891 | J88: =IF(ISNUMBER(VLOOKUP($H88,$A$27:$F$369,J$25,FALSE)),VLOOKUP($H88,$A$27:$F$369,J$25,FALSE),NA()) -> 113.9 | K88: =IF(ISNUMBER(VLOOKUP($H88,$A$27:$F$369,K$25,FALSE)),VLOOKUP($H88,$A$27:$F$369,K$25,FALSE),NA()) -> 124.4 | L88: =IF(ISNUMBER(VLOOKUP($H88,$A$27:$F$369,L$25,FALSE)),VLOOKUP($H88,$A$27:$F$369,L$25,FALSE),NA()) -> 51.7 | M88: =IF(ISNUMBER(VLOOKUP($H88,$A$27:$F$369,M$25,FALSE)),VLOOKUP($H88,$A$27:$F$369,M$25,FALSE),NA()) -> 110.33327 | N88: =IF(ISNUMBER(VLOOKUP($H88,$A$27:$F$369,N$25,FALSE)),VLOOKUP($H88,$A$27:$F$369,N$25,FALSE),NA()) -> 109.86881
