Workbook
Name _DLX1.USE: Haver_M!$A$2:$HG$5
Name _DLX2.USE: Haver_Q!$A$2:$CL$5
Name EdssBatchRange: #REF!

Sheet Haver_M
C1: RS | D1: LTY | E1: REER | F1: CPI | G1: CORE | H1: IPALL | I1: IPMINE | J1: IPUTIL | K1: IPCONST | L1: IPMANU | M1: UNR | N1: WAGE | O1: LEAD | P1: SALES_R | Q1: WHOLESALE | R1: EXPORTS | S1: IMPORTS | T1: COINCI | U1: CCI | V1: PCI | W1: PMI | X1: PMIManu | Y1: PMINO | Z1: PMIEMP | AA1: PMIDELI | AB1: PMIStocks | AC1: PMIIP | AD1: PMIPURCH | AE1: PMISTOCKS | AF1: PMINEO | AG1: PMIMPRI | AH1: PMIBACK | AI1: STOCKS | AJ1: PCONS | AK1: PCONS_D | AP1: EAI | AQ1: GFCF | AR1: TOURISM | AS1: OILPROD | AT1: OIL_X | AU1: IMEFBC | AV1: NEWS
A2: 10001 !M | B2: .excel_last | C2: N273RD@EMERGELA | D2: R273MA@EMERGELA | E2: N273XJCB@EMERGELA | F2: H273PJ@EMERGELA | G2: H273PJXQ@EMERGELA | H2: S273DW@EMERGELA | I2: S273DN@EMERGELA | J2: S273DV@EMERGELA | K2: S273DR@EMERGELA | L2: S273DM@EMERGELA | M2: H273EPAU@EMERGELA | N2: S273E9M@EMERGELA | O2: N273VLD@EMERGELA | P2: S273TRS@EMERGELA | Q2: S273TWS@EMERGELA | R2: S273TXD@EMERGELA | S2: S273TMD@EMERGELA | T2: N273VLC@EMERGELA | U2: S273VPCC@EMERGELA | V2: N273VCP@EMERGELA | W2: S273M@MKTPMI | X2: S273MG@MKTPMI | Y2: S273MO@MKTPMI | Z2: S273ME@MKTPMI | AA2: S273MD@MKTPMI | AB2: S273MSP@MKTPMI | AC2: S273MPI@MKTPMI | AD2: S273MQP@MKTPMI | AE2: S273MSF@MKTPMI | AF2: S273MX@MKTPMI | AG2: S273MPO@MKTPMI | AH2: S273MB@MKTPMI | AI2: C273KNV@EMERGELA | AJ2: S273NCPI@EMERGELA | AK2: S273NCVI@EMERGELA | AL2: S273NCUI@EMERGELA | AM2: S273NCSI@EMERGELA | AN2: S273NCMI@EMERGELA | AO2: N273TM@EMERGELA | AP2: S273GVI@EMERGELA | AQ2: S273NFI@EMERGELA | AR2: sa(N273TA55@EMERGELA) | AS2: H273IUQ@EMERGELA | AT2: C273TXUQ@EMERGELA | AU2: S273VMA@EMERGELA | AV2: sa(N273VIUC@EMERGELA) | AW2: S273VMNA@EMERGELA
A3: .DESC | C3: Mexico: Overnight Interbank Funding Rate: [Target Rate - Tasa objetivo] (EOP, %) | D3: Mexico: 10 Year Treasury Bond Mid Yield (% p.a.) | E3: Mexico: JPMorgan Real Broad Effective Exchange Rate Index, CPI Based (2010=100) | F3: Mexico: Consumer Price Index (SA, Jul 16-31, 2018=100) | G3: Mexico: Consumer Price Index: Core (SA, Jul 16-31, 2018=100) | H3: Mexico: Industrial Production (SA, 2013=100) | I3: Mexico: Industrial Production: Mining (SA, 2013=100) | J3: Mexico: Industrial Production: Utilities (SA, 2013=100) | K3: Mexico: Industrial Production: Construction (SA, 2013=100) | L3: Mexico: Industrial Production: Manufacturing (SA, 2013=100) | M3: Mexico: NES: Unemployed Population: Percent of Econ Active Pop (SA, %) | N3: Mexico: Avg Real Earnings Per Employee: Manufacturing (SA, 2013=100) | O3: Mexico: Leading Index (NSA, LT Avg=100) | P3: Mexico: Retail Sales Volume [Goods & Services] (SA, 2013=100) | Q3: Mexico: Wholesale Sales [Goods & Services] (SA, 2013=100) | R3: Mexico: Exports, fob (SA, Mil.US$) | S3: Mexico: Imports, fob (SA, Mil.US$) | T3: Mexico: Coincident Index (NSA, LT Avg=100) | U3: Mexico: Consumer Confidence (SA, 50+=Optimistic) | V3: Mexico: Producer Confidence Index (NSA, Points) | W3: Mexico PMI: Manufacturing (SA, 50+= Expansion) | X3: Mexico PMI: Manufacturing (SA, 50+= Expansion) | Y3: Mexico PMI: Manufacturing New Orders (SA, 50+= Expansion) | Z3: Mexico PMI: Manufacturing Employment (SA, 50+= Expansion) | AA3: Mexico PMI: Manufacturing Suppliers' Delivery Times (SA, 50+= Expansion) | AB3: Mexico PMI: Manufacturing Stocks of Purchases (SA, 50+= Expansion) | AC3: Mexico PMI: Manufacturing Input Prices (SA, 50+= Expansion) | AD3: Mexico PMI: Manufacturing Quantity of Purchases (SA, 50+= Expansion) | AE3: Mexico PMI: Manufacturing Stocks of Finished Goods (SA, 50+= Expansion) | AF3: Mexico PMI: Manufacturing New Export Orders (SA, 50+= Expansion) | AG3: Mexico PMI: Manufacturing Output Prices (SA, 50+= Expansion) | AH3: Mexico PMI: Manufacturing Backlogs of Work (SA, 50+= Expansion) | AI3: Mexico: Stock Price Index: IPC (Avg, 11/78=0.78) | AJ3: Mexico: Private Consumption in Domestic Market (SA, 2013=100) | AK3: Mexico: Private Consumption in Domestic Market, Total Domestic (SA, 2013=100) | AL3: Mexico: Private Consumption in Domestic Market, Domestic Goods (SA, 2013=100) | AM3: Mexico: Private Consumption in Domestic Market, Domestic Services (SA, 2013=100) | AN3: Mexico: Private Consumption in Domestic Market, Imported Goods (SA, 2013=100) | AO3: Mexico: Mfg Goods Sales: Manufacturing (NSA, Thous.Pesos) | AP3: Mexico: Economic Activity Indicator (SWDA, 2013=100) | AQ3: Mexico: Gross Fixed Capital Formation (SA, 2013=100) | AR3: Mexico: Inbound International Tourism Expenditure (NSA, Thous.US$) - Seasonal Adjustment, All | AS3: Mexico: Production of Crude Petroleum (SA, Thous.Bbls/Day) | AT3: Mexico: Petroleum Exports: Crude (Thous.Barrels/Day) | AU3: Mexico: IMEF Business Climate Index: Mfg Adj by Co Size (SA, 50+=Econ Expand) | AV3: Mexico: News Based Economic Policy Uncertainty Index (Jan 1996-Dec 2016=100) - Seasonal Adjustment, All | AW3: Mexico: IMEF Business Climate Index: Nonmfg Adj by Co Size (SA, 50+=Econ Expand)
A4: .T1 | C4: Jan-2008 | D4: Jan-2008 | E4: Jan-1970 | F4: Jan-1969 | G4: Jan-1982 | H4: Jan-1980 | I4: Jan-1980 | J4: Jan-1980 | K4: Jan-1980 | L4: Jan-1980 | M4: Apr-2000 | N4: Jan-2007 | O4: Jan-1980 | P4: Jan-1994 | Q4: Jan-2008 | R4: Jan-1980 | S4: Jan-1980 | T4: Jan-1980 | U4: Apr-2001 | V4: Jan-2004 | W4: Apr-2011 | X4: Apr-2011 | Y4: Apr-2011 | Z4: Apr-2011 | AA4: Apr-2011 | AB4: Apr-2011 | AC4: Apr-2011 | AD4: Apr-2011 | AE4: Apr-2011 | AF4: Apr-2011 | AG4: Apr-2011 | AH4: Apr-2011 | AI4: Jan-1980 | AJ4: Jan-1993 | AK4: Jan-1993 | AL4: Jan-1993 | AM4: Jan-1993 | AN4: Jan-1993 | AO4: Jan-2007 | AP4: Jan-1993 | AQ4: Jan-1993 | AR4: Jan-1980 | AS4: Jan-1984 | AT4: Jan-1980 | AU4: Jan-2005 | AV4: Jan-1996 | AW4: Jan-2005
A5: .TN | C5: Jun-2020 | D5: Jun-2020 | E5: Jun-2020 | F5: Jun-2020 | G5: Jun-2020 | H5: May-2020 | I5: May-2020 | J5: May-2020 | K5: May-2020 | L5: May-2020 | M5: May-2020 | N5: May-2020 | O5: May-2020 | P5: May-2020 | Q5: May-2020 | R5: Jun-2020 | S5: Jun-2020 | T5: Apr-2020 | U5: Mar-2020 | V5: Jun-2020 | W5: Jun-2020 | X5: Jun-2020 | Y5: Jun-2020 | Z5: Jun-2020 | AA5: Jun-2020 | AB5: Jun-2020 | AC5: Jun-2020 | AD5: Jun-2020 | AE5: Jun-2020 | AF5: Jun-2020 | AG5: Jun-2020 | AH5: Jun-2020 | AI5: Jun-2020 | AJ5: Apr-2020 | AK5: Apr-2020 | AL5: Apr-2020 | AM5: Apr-2020 | AN5: Apr-2020 | AO5: May-2020 | AP5: May-2020 | AQ5: Apr-2020 | AR5: May-2020 | AS5: May-2020 | AT5: May-2020 | AU5: Jun-2020 | AV5: May-2020 | AW5: Jun-2020
A6: 0001 | B6: 36556 | C6: #N/A | D6: #N/A | E6: 113.55455 | F6: 44.6533 | G6: 48.932 | H6: 89.3466 | I6: 101.1315 | J6: 53.8108 | K6: 85.3286 | L6: 89.9685 | M6: #N/A | N6: #N/A | O6: 101.39 | P6: 73.5288 | Q6: #N/A | R6: 13046 | S6: 13621.5 | T6: 101.2 | U6: #N/A | V6: #N/A | W6: #N/A | X6: #N/A | Y6: #N/A | Z6: #N/A | AA6: #N/A | AB6: #N/A | AC6: #N/A | AD6: #N/A | AE6: #N/A | AF6: #N/A | AG6: #N/A | AH6: #N/A | AI6: 7010.52 | AJ6: 75.869 | AK6: 79.911 | AL6: 89.059 | AM6: 70.937 | AN6: 36.914 | AO6: #N/A | AP6: 79.339849 | AQ6: 77.5 | AR6: 643302.84 | AS6: 2964 | AT6: 1517 | AU6: #N/A | AV6: 129.33691 | AW6: #N/A
A7: 0002 | B7: 36585 | C7: #N/A | D7: #N/A | E7: 115.46699 | F7: 44.999 | G7: 49.3 | H7: 89.9714 | I7: 99.6387 | J7: 54.6009 | K7: 86.2041 | L7: 90.6876 | M7: #N/A | N7: #N/A | O7: 101.49 | P7: 73.7749 | Q7: #N/A | R7: 13421.6 | S7: 13734.9 | T7: 101.34 | U7: #N/A | V7: #N/A | W7: #N/A | X7: #N/A | Y7: #N/A | Z7: #N/A | AA7: #N/A | AB7: #N/A | AC7: #N/A | AD7: #N/A | AE7: #N/A | AF7: #N/A | AG7: #N/A | AH7: #N/A | AI7: 7372.96 | AJ7: 75.635 | AK7: 79.688 | AL7: 88.186 | AM7: 71.219 | AN7: 39.045 | AO7: #N/A | AP7: 78.869914 | AQ7: 77.2 | AR7: 689953.4 | AS7: 2890 | AT7: 1531 | AU7: #N/A | AV7: 182.08916 | AW7: #N/A
A8: 0003 | B8: 36616 | C8: #N/A | D8: #N/A | E8: 117.33534 | F8: 45.3135 | G8: 49.5671 | H8: 89.9666 | I8: 101.1593 | J8: 55.207 | K8: 84.0667 | L8: 90.8005 | M8: #N/A | N8: #N/A | O8: 101.54 | P8: 71.9695 | Q8: #N/A | R8: 12899.9 | S8: 13380.6 | T8: 101.47 | U8: #N/A | V8: #N/A | W8: #N/A | X8: #N/A | Y8: #N/A | Z8: #N/A | AA8: #N/A | AB8: #N/A | AC8: #N/A | AD8: #N/A | AE8: #N/A | AF8: #N/A | AG8: #N/A | AH8: #N/A | AI8: 7958.76 | AJ8: 75.914 | AK8: 80.026 | AL8: 88.542 | AM8: 71.516 | AN8: 39.096 | AO8: #N/A | AP8: 78.657455 | AQ8: 74.6 | AR8: 692837.23 | AS8: 2956 | AT8: 1534 | AU8: #N/A | AV8: 119.76352 | AW8: #N/A
A9: 0004 | B9: 36646 | C9: #N/A | D9: #N/A | E9: 116.90303 | F9: 45.5985 | G9: 49.8246 | H9: 90.3034 | I9: 103.7515 | J9: 54.9528 | K9: 84.5754 | L9: 90.845 | M9: 2.77 | N9: #N/A | O9: 101.52 | P9: 75.7444 | Q9: #N/A | R9: 13176.4 | S9: 13844.5 | T9: 101.61 | U9: #N/A | V9: #N/A | W9: #N/A | X9: #N/A | Y9: #N/A | Z9: #N/A | AA9: #N/A | AB9: #N/A | AC9: #N/A | AD9: #N/A | AE9: #N/A | AF9: #N/A | AG9: #N/A | AH9: #N/A | AI9: 6918.29 | AJ9: 76.807 | AK9: 80.329 | AL9: 88.741 | AM9: 71.717 | AN9: 44.034 | AO9: #N/A | AP9: 79.397635 | AQ9: 77.4 | AR9: 654738.82 | AS9: 3053 | AT9: 1679 | AU9: #N/A | AV9: 108.51464 | AW9: #N/A
A10: 0005 | B10: 36677 | C10: #N/A | D10: #N/A | E10: 116.64526 | F10: 45.9655 | G10: 50.144 | H10: 91.1724 | I10: 103.1344 | J10: 55.1982 | K10: 85.5695 | L10: 91.6277 | M10: 2.72 | N10: #N/A | O10: 101.44 | P10: 76.8112 | Q10: #N/A | R10: 13561.4 | S10: 14366.8 | T10: 101.74 | U10: #N/A | V10: #N/A | W10: #N/A | X10: #N/A | Y10: #N/A | Z10: #N/A | AA10: #N/A | AB10: #N/A | AC10: #N/A | AD10: #N/A | AE10: #N/A | AF10: #N/A | AG10: #N/A | AH10: #N/A | AI10: 6067.96 | AJ10: 77.43 | AK10: 80.952 | AL10: 89.804 | AM10: 71.951 | AN10: 46.002 | AO10: #N/A | AP10: 79.856351 | AQ10: 77.5 | AR10: 676591.82 | AS10: 3044 | AT10: 1684 | AU10: #N/A | AV10: 149.59285 | AW10: #N/A
A11: 0006 | B11: 36707 | C11: #N/A | D11: #N/A | E11: 112.26979 | F11: 46.3367 | G11: 50.4345 | H11: 91.7436 | I11: 104.3887 | J11: 55.2032 | K11: 84.6837 | L11: 92.7064 | M11: 2.72 | N11: #N/A | O11: 101.34 | P11: 78.3705 | Q11: #N/A | R11: 13796 | S11: 14427.7 | T11: 101.87 | U11: #N/A | V11: #N/A | W11: #N/A | X11: #N/A | Y11: #N/A | Z11: #N/A | AA11: #N/A | AB11: #N/A | AC11: #N/A | AD11: #N/A | AE11: #N/A | AF11: #N/A | AG11: #N/A | AH11: #N/A | AI11: 6536.47 | AJ11: 77.992 | AK11: 81.209 | AL11: 90.169 | AM11: 72.097 | AN11: 49.692 | AO11: #N/A | AP11: 80.310105 | AQ11: 78.1 | AR11: 722413.11 | AS11: 3071 | AT11: 1685 | AU11: #N/A | AV11: 261.59393 | AW11: #N/A
A12: 0007 | B12: 36738 | C12: #N/A | D12: #N/A | E12: 117.72534 | F12: 46.6904 | G12: 50.7695 | H12: 91.4115 | I12: 96.7789 | J12: 54.6904 | K12: 83.3649 | L12: 96.4267 | M12: 2.39 | N12: #N/A | O12: 101.2 | P12: 78.6167 | Q12: #N/A | R12: 13930.7 | S12: 14899.4 | T12: 101.95 | U12: #N/A | V12: #N/A | W12: #N/A | X12: #N/A | Y12: #N/A | Z12: #N/A | AA12: #N/A | AB12: #N/A | AC12: #N/A | AD12: #N/A | AE12: #N/A | AF12: #N/A | AG12: #N/A | AH12: #N/A | AI12: 7063.39 | AJ12: 78.803 | AK12: 81.84 | AL12: 90.961 | AM12: 72.527 | AN12: 51.144 | AO12: #N/A | AP12: 80.417845 | AQ12: 77.9 | AR12: 695570.2 | AS12: 2844 | AT12: 1723 | AU12: #N/A | AV12: 144.08678 | AW12: #N/A
A13: 0008 | B13: 36769 | C13: #N/A | D13: #N/A | E13: 120.57772 | F13: 47.0132 | G13: 51.0742 | H13: 91.6441 | I13: 105.6175 | J13: 55.3312 | K13: 83.2526 | L13: 92.7329 | M13: 2.75 | N13: #N/A | O13: 101.01 | P13: 79.1911 | Q13: #N/A | R13: 14357.5 | S13: 15111.6 | T13: 101.99 | U13: #N/A | V13: #N/A | W13: #N/A | X13: #N/A | Y13: #N/A | Z13: #N/A | AA13: #N/A | AB13: #N/A | AC13: #N/A | AD13: #N/A | AE13: #N/A | AF13: #N/A | AG13: #N/A | AH13: #N/A | AI13: 6464.2 | AJ13: 78.075 | AK13: 81.526 | AL13: 90.201 | AM13: 72.563 | AN13: 47.797 | AO13: #N/A | AP13: 80.51353 | AQ13: 78.5 | AR13: 675626.05 | AS13: 3132 | AT13: 1756 | AU13: #N/A | AV13: 94.650131 | AW13: #N/A
A14: 0009 | B14: 36799 | C14: #N/A | D14: #N/A | E14: 120.15479 | F14: 47.2826 | G14: 51.3214 | H14: 91.508 | I14: 107.4547 | J14: 55.9557 | K14: 81.8831 | L14: 92.7816 | M14: 2.67 | N14: #N/A | O14: 100.78 | P14: 80.0938 | Q14: #N/A | R14: 14143.7 | S14: 15071.5 | T14: 101.98 | U14: #N/A | V14: #N/A | W14: #N/A | X14: #N/A | Y14: #N/A | Z14: #N/A | AA14: #N/A | AB14: #N/A | AC14: #N/A | AD14: #N/A | AE14: #N/A | AF14: #N/A | AG14: #N/A | AH14: #N/A | AI14: 6680.32 | AJ14: 78.997 | AK14: 81.93 | AL14: 90.581 | AM14: 73.171 | AN14: 51.529 | AO14: #N/A | AP14: 80.639012 | AQ14: 77.1 | AR14: 729377.6 | AS14: 3167 | AT14: 1720 | AU14: #N/A | AV14: 62.056772 | AW14: #N/A
A15: 0010 | B15: 36830 | C15: #N/A | D15: #N/A | E15: 119.1305 | F15: 47.6152 | G15: 51.6425 | H15: 90.6057 | I15: 99.7742 | J15: 56.1961 | K15: 82.128 | L15: 92.9708 | M15: 2.54 | N15: #N/A | O15: 100.49 | P15: 80.0118 | Q15: #N/A | R15: 14662.9 | S15: 15239 | T15: 101.92 | U15: #N/A | V15: #N/A | W15: #N/A | X15: #N/A | Y15: #N/A | Z15: #N/A | AA15: #N/A | AB15: #N/A | AC15: #N/A | AD15: #N/A | AE15: #N/A | AF15: #N/A | AG15: #N/A | AH15: #N/A | AI15: 6061.31 | AJ15: 79.864 | AK15: 83.003 | AL15: 92.47 | AM15: 73.157 | AN15: 52.543 | AO15: #N/A | AP15: 80.503439 | AQ15: 77.3 | AR15: 725220.49 | AS15: 2983 | AT15: 1549 | AU15: #N/A | AV15: 103.55553 | AW15: #N/A
A16: 0011 | B16: 36860 | C16: #N/A | D16: #N/A | E16: 120.55956 | F16: 47.8724 | G16: 52.0251 | H16: 89.7542 | I16: 102.3906 | J16: 56.7744 | K16: 80.4441 | L16: 91.4017 | M16: 2.32 | N16: #N/A | O16: 100.18 | P16: 78.8628 | Q16: #N/A | R16: 14474.3 | S16: 15215.5 | T16: 101.8 | U16: #N/A | V16: #N/A | W16: #N/A | X16: #N/A | Y16: #N/A | Z16: #N/A | AA16: #N/A | AB16: #N/A | AC16: #N/A | AD16: #N/A | AE16: #N/A | AF16: #N/A | AG16: #N/A | AH16: #N/A | AI16: 6125.42 | AJ16: 79.59 | AK16: 81.75 | AL16: 89.922 | AM16: 73.387 | AN16: 60.134 | AO16: #N/A | AP16: 80.239524 | AQ16: 76.1 | AR16: 732509.82 | AS16: 3006 | AT16: 1697 | AU16: #N/A | AV16: 174.553 | AW16: #N/A
A17: 0012 | B17: 36891 | C17: #N/A | D17: #N/A | E17: 121.8344 | F17: 48.2735 | G17: 52.3128 | H17: 88.622 | I17: 102.9357 | J17: 56.5097 | K17: 79.6392 | L17: 89.54 | M17: 2.6 | N17: #N/A | O17: 99.9 | P17: 78.6167 | Q17: #N/A | R17: 14552.2 | S17: 15425.6 | T17: 101.64 | U17: #N/A | V17: #N/A | W17: #N/A | X17: #N/A | Y17: #N/A | Z17: #N/A | AA17: #N/A | AB17: #N/A | AC17: #N/A | AD17: #N/A | AE17: #N/A | AF17: #N/A | AG17: #N/A | AH17: #N/A | AI17: 5601.73 | AJ17: 79.504 | AK17: 81.911 | AL17: 90.466 | AM17: 73.082 | AN17: 56.216 | AO17: #N/A | AP17: 79.790284 | AQ17: 74.5 | AR17: 684800.22 | AS17: 3023 | AT17: 1749 | AU17: #N/A | AV17: 88.497361 | AW17: #N/A
A18: 0101 | B18: 36922 | C18: #N/A | D18: #N/A | E18: 117.98875 | F18: 48.2937 | G18: 52.493 | H18: 89.9924 | I18: 103.8013 | J18: 56.3833 | K18: 78.4819 | L18: 92.7053 | M18: 2.56 | N18: #N/A | O18: 99.66 | P18: 80.5862 | Q18: #N/A | R18: 13864.3 | S18: 14668.1 | T18: 101.45 | U18: #N/A | V18: #N/A | W18: #N/A | X18: #N/A | Y18: #N/A | Z18: #N/A | AA18: #N/A | AB18: #N/A | AC18: #N/A | AD18: #N/A | AE18: #N/A | AF18: #N/A | AG18: #N/A | AH18: #N/A | AI18: 6118.06 | AJ18: 78.996 | AK18: 81.899 | AL18: 89.823 | AM18: 74.055 | AN18: 54.143 | AO18: #N/A | AP18: 79.773189 | AQ18: 73.4 | AR18: 725886.24 | AS18: 3017 | AT18: 1750 | AU18: #N/A | AV18: 123.11118 | AW18: #N/A
A19: 0102 | B19: 36950 | C19: #N/A | D19: #N/A | E19: 118.65244 | F19: 48.2383 | G19: 52.726 | H19: 89.5158 | I19: 107.1877 | J19: 56.8557 | K19: 77.0956 | L19: 91.2698 | M19: 3.15 | N19: #N/A | O19: 99.49 | P19: 80.2579 | Q19: #N/A | R19: 13631 | S19: 14363.3 | T19: 101.25 | U19: #N/A | V19: #N/A | W19: #N/A | X19: #N/A | Y19: #N/A | Z19: #N/A | AA19: #N/A | AB19: #N/A | AC19: #N/A | AD19: #N/A | AE19: #N/A | AF19: #N/A | AG19: #N/A | AH19: #N/A | AI19: 6276.83 | AJ19: 79.123 | AK19: 81.784 | AL19: 89.31 | AM19: 74.245 | AN19: 54.224 | AO19: #N/A | AP19: 79.570087 | AQ19: 72.5 | AR19: 723385.62 | AS19: 3137 | AT19: 1759 | AU19: #N/A | AV19: 103.7103 | AW19: #N/A
A20: 0103 | B20: 36981 | C20: #N/A | D20: #N/A | E20: 121.48672 | F20: 48.5948 | G20: 52.9991 | H20: 89.1202 | I20: 105.9494 | J20: 57.0714 | K20: 76.6878 | L20: 90.157 | M20: 2.66 | N20: #N/A | O20: 99.41 | P20: 80.9965 | Q20: #N/A | R20: 13987.5 | S20: 14776.7 | T20: 101.06 | U20: #N/A | V20: #N/A | W20: #N/A | X20: #N/A | Y20: #N/A | Z20: #N/A | AA20: #N/A | AB20: #N/A | AC20: #N/A | AD20: #N/A | AE20: #N/A | AF20: #N/A | AG20: #N/A | AH20: #N/A | AI20: 5926.31 | AJ20: 79.448 | AK20: 82.053 | AL20: 89.535 | AM20: 74.531 | AN20: 55.48 | AO20: #N/A | AP20: 79.525193 | AQ20: 71.2 | AR20: 728591.12 | AS20: 3122 | AT20: 1757 | AU20: #N/A | AV20: 120.51498 | AW20: #N/A
A21: 0104 | B21: 37011 | C21: #N/A | D21: #N/A | E21: 125.89816 | F21: 48.886 | G21: 53.2653 | H21: 87.0186 | I21: 102.5126 | J21: 57.7249 | K21: 73.4465 | L21: 89.5538 | M21: 2.7 | N21: #N/A | O21: 99.41 | P21: 79.3552 | Q21: #N/A | R21: 13782.2 | S21: 14722.7 | T21: 100.88 | U21: 46.9 | V21: #N/A | W21: #N/A | X21: #N/A | Y21: #N/A | Z21: #N/A | AA21: #N/A | AB21: #N/A | AC21: #N/A | AD21: #N/A | AE21: #N/A | AF21: #N/A | AG21: #N/A | AH21: #N/A | AI21: 5884.99 | AJ21: 79.203 | AK21: 82.21 | AL21: 89.77 | AM21: 74.362 | AN21: 51.584 | AO21: #N/A | AP21: 79.364557 | AQ21: 69.8 | AR21: 745852.66 | AS21: 3018 | AT21: 1716 | AU21: #N/A | AV21: 132.17547 | AW21: #N/A
A22: 0105 | B22: 37042 | C22: #N/A | D22: #N/A | E22: 128.21088 | F22: 49.2175 | G22: 53.5588 | H22: 88.1817 | I22: 102.2353 | J22: 57.4636 | K22: 75.1537 | L22: 90.2907 | M22: 2.79 | N22: #N/A | O22: 99.49 | P22: 79.6014 | Q22: #N/A | R22: 13153.3 | S22: 14034.9 | T22: 100.71 | U22: 44.4 | V22: #N/A | W22: #N/A | X22: #N/A | Y22: #N/A | Z22: #N/A | AA22: #N/A | AB22: #N/A | AC22: #N/A | AD22: #N/A | AE22: #N/A | AF22: #N/A | AG22: #N/A | AH22: #N/A | AI22: 6351.16 | AJ22: 79.227 | AK22: 82.155 | AL22: 89.733 | AM22: 74.376 | AN22: 53.341 | AO22: #N/A | AP22: 79.182549 | AQ22: 69.6 | AR22: 744680.72 | AS22: 3043 | AT22: 1719 | AU22: #N/A | AV22: 165.55541 | AW22: #N/A
A23: 0106 | B23: 37072 | C23: #N/A | D23: #N/A | E23: 129.65588 | F23: 49.4256 | G23: 53.8522 | H23: 88.5819 | I23: 105.7305 | J23: 58.0391 | K23: 76.1192 | L23: 89.4682 | M23: 2.75 | N23: #N/A | O23: 99.57 | P23: 79.8476 | Q23: #N/A | R23: 13360.1 | S23: 13983.2 | T23: 100.57 | U23: 44 | V23: #N/A | W23: #N/A | X23: #N/A | Y23: #N/A | Z23: #N/A | AA23: #N/A | AB23: #N/A | AC23: #N/A | AD23: #N/A | AE23: #N/A | AF23: #N/A | AG23: #N/A | AH23: #N/A | AI23: 6642.04 | AJ23: 80.569 | AK23: 83.3 | AL23: 91.774 | AM23: 74.659 | AN23: 55.313 | AO23: #N/A | AP23: 79.518017 | AQ23: 70.7 | AR23: 734358.78 | AS23: 3142 | AT23: 1716 | AU23: #N/A | AV23: 115.99765 | AW23: #N/A
A24: 0107 | B24: 37103 | C24: #N/A | D24: #N/A | E24: 128.51874 | F24: 49.4591 | G24: 54.0828 | H24: 89.2125 | I24: 106.2793 | J24: 57.5581 | K24: 78.8768 | L24: 89.0838 | M24: 2.77 | N24: #N/A | O24: 99.61 | P24: 79.1911 | Q24: #N/A | R24: 12794.8 | S24: 13532.5 | T24: 100.43 | U24: 46.1 | V24: #N/A | W24: #N/A | X24: #N/A | Y24: #N/A | Z24: #N/A | AA24: #N/A | AB24: #N/A | AC24: #N/A | AD24: #N/A | AE24: #N/A | AF24: #N/A | AG24: #N/A | AH24: #N/A | AI24: 6552.96 | AJ24: 79.39 | AK24: 82.258 | AL24: 89.494 | AM24: 74.749 | AN24: 53.263 | AO24: #N/A | AP24: 79.625331 | AQ24: 72.5 | AR24: 715506.87 | AS24: 3157 | AT24: 1711 | AU24: #N/A | AV24: 97.896514 | AW24: #N/A
A25: 0108 | B25: 37134 | C25: #N/A | D25: #N/A | E25: 128.89868 | F25: 49.7791 | G25: 54.3248 | H25: 88.8813 | I25: 105.8388 | J25: 59.0452 | K25: 79.0235 | L25: 88.5506 | M25: 2.27 | N25: #N/A | O25: 99.63 | P25: 79.7656 | Q25: #N/A | R25: 13049.5 | S25: 13691.3 | T25: 100.29 | U25: 47.4 | V25: #N/A | W25: #N/A | X25: #N/A | Y25: #N/A | Z25: #N/A | AA25: #N/A | AB25: #N/A | AC25: #N/A | AD25: #N/A | AE25: #N/A | AF25: #N/A | AG25: #N/A | AH25: #N/A | AI25: 6466.42 | AJ25: 79.983 | AK25: 82.755 | AL25: 90.667 | AM25: 74.743 | AN25: 55.675 | AO25: #N/A | AP25: 79.936959 | AQ25: 72 | AR25: 709838.95 | AS25: 3140 | AT25: 1648 | AU25: #N/A | AV25: 113.21612 | AW25: #N/A
A26: 0109 | B26: 37164 | C26: #N/A | D26: #N/A | E26: 125.62601 | F26: 50.1473 | G26: 54.5723 | H26: 88.8659 | I26: 106.7873 | J26: 58.8933 | K26: 78.2627 | L26: 88.8807 | M26: 2.53 | N26: #N/A | O26: 99.65 | P26: 80.5041 | Q26: #N/A | R26: 12984.4 | S26: 13768.8 | T26: 100.13 | U26: 44.7 | V26: #N/A | W26: #N/A | X26: #N/A | Y26: #N/A | Z26: #N/A | AA26: #N/A | AB26: #N/A | AC26: #N/A | AD26: #N/A | AE26: #N/A | AF26: #N/A | AG26: #N/A | AH26: #N/A | AI26: 5546.51 | AJ26: 80.283 | AK26: 82.963 | AL26: 91.326 | AM26: 74.514 | AN26: 55.267 | AO26: #N/A | AP26: 79.732419 | AQ26: 72.4 | AR26: 572489.08 | AS26: 3166 | AT26: 1648 | AU26: #N/A | AV26: 246.23597 | AW26: #N/A
A27: 0110 | B27: 37195 | C27: #N/A | D27: #N/A | E27: 127.92358 | F27: 50.3546 | G27: 54.7521 | H27: 86.7493 | I27: 103.8515 | J27: 59.4714 | K27: 76.0367 | L27: 87.0561 | M27: 2.92 | N27: #N/A | O27: 99.75 | P27: 79.6835 | Q27: #N/A | R27: 12825.1 | S27: 13721.4 | T27: 99.95 | U27: 42.3 | V27: #N/A | W27: #N/A | X27: #N/A | Y27: #N/A | Z27: #N/A | AA27: #N/A | AB27: #N/A | AC27: #N/A | AD27: #N/A | AE27: #N/A | AF27: #N/A | AG27: #N/A | AH27: #N/A | AI27: 5567.04 | AJ27: 80.043 | AK27: 82.841 | AL27: 91.205 | AM27: 74.257 | AN27: 55.412 | AO27: #N/A | AP27: 78.823013 | AQ27: 69.3 | AR27: 608237.91 | AS27: 3113 | AT27: 1734 | AU27: #N/A | AV27: 284.99277 | AW27: #N/A
A28: 0111 | B28: 37225 | C28: #N/A | D28: #N/A | E28: 130.33858 | F28: 50.3609 | G28: 54.9241 | H28: 88.3928 | I28: 108.2167 | J28: 60.1631 | K28: 76.7226 | L28: 87.457 | M28: 2.93 | N28: #N/A | O28: 99.91 | P28: 79.9297 | Q28: #N/A | R28: 12544.6 | S28: 13468 | T28: 99.79 | U28: 42.8 | V28: #N/A | W28: #N/A | X28: #N/A | Y28: #N/A | Z28: #N/A | AA28: #N/A | AB28: #N/A | AC28: #N/A | AD28: #N/A | AE28: #N/A | AF28: #N/A | AG28: #N/A | AH28: #N/A | AI28: 5707.32 | AJ28: 80.088 | AK28: 82.736 | AL28: 91.068 | AM28: 74.263 | AN28: 56.808 | AO28: #N/A | AP28: 79.396361 | AQ28: 71.3 | AR28: 665944.53 | AS28: 3213 | AT28: 1682 | AU28: #N/A | AV28: 190.50982 | AW28: #N/A
A29: 0112 | B29: 37256 | C29: #N/A | D29: #N/A | E29: 131.60927 | F29: 50.3568 | G29: 55.0658 | H29: 88.454 | I29: 109.0177 | J29: 60.4354 | K29: 78.331 | L29: 86.7558 | M29: 3.07 | N29: #N/A | O29: 100.1 | P29: 79.5194 | Q29: #N/A | R29: 12930.8 | S29: 13602.3 | T29: 99.64 | U29: 42.7 | V29: #N/A | W29: #N/A | X29: #N/A | Y29: #N/A | Z29: #N/A | AA29: #N/A | AB29: #N/A | AC29: #N/A | AD29: #N/A | AE29: #N/A | AF29: #N/A | AG29: #N/A | AH29: #N/A | AI29: 6214.49 | AJ29: 80.615 | AK29: 82.918 | AL29: 91.293 | AM29: 74.259 | AN29: 58.127 | AO29: #N/A | AP29: 79.326697 | AQ29: 72.3 | AR29: 669154.73 | AS29: 3243 | AT29: 1685 | AU29: #N/A | AV29: 221.31069 | AW29: #N/A
A30: 0201 | B30: 37287 | C30: #N/A | D30: #N/A | E30: 133.14067 | F30: 50.64 | G30: 55.1898 | H30: 86.7948 | I30: 106.2968 | J30: 56.7137 | K30: 74.2768 | L30: 86.8879 | M30: 3.42 | N30: #N/A | O30: 100.26 | P30: 79.3552 | Q30: #N/A | R30: 12757.2 | S30: 13146.5 | T30: 99.52 | U30: 36.8 | V30: #N/A | W30: #N/A | X30: #N/A | Y30: #N/A | Z30: #N/A | AA30: #N/A | AB30: #N/A | AC30: #N/A | AD30: #N/A | AE30: #N/A | AF30: #N/A | AG30: #N/A | AH30: #N/A | AI30: 6633.51 | AJ30: 79.621 | AK30: 82.66 | AL30: 91.073 | AM30: 74.161 | AN30: 54.924 | AO30: #N/A | AP30: 77.93077 | AQ30: 68.5 | AR30: 694656.74 | AS30: 3189 | AT30: 1793 | AU30: #N/A | AV30: 165.2789 | AW30: #N/A
A31: 0202 | B31: 37315 | C31: #N/A | D31: #N/A | E31: 134.08656 | F31: 50.6002 | G31: 55.4317 | H31: 86.156 | I31: 106.0989 | J31: 57.167 | K31: 74.2369 | L31: 86.3616 | M31: 2.97 | N31: #N/A | O31: 100.35 | P31: 79.6014 | Q31: #N/A | R31: 12968 | S31: 13765.6 | T31: 99.45 | U31: 38.3 | V31: #N/A | W31: #N/A | X31: #N/A | Y31: #N/A | Z31: #N/A | AA31: #N/A | AB31: #N/A | AC31: #N/A | AD31: #N/A | AE31: #N/A | AF31: #N/A | AG31: #N/A | AH31: #N/A | AI31: 6685.32 | AJ31: 79.697 | AK31: 82.434 | AL31: 91.082 | AM31: 73.828 | AN31: 54.226 | AO31: #N/A | AP31: 78.493449 | AQ31: 69.8 | AR31: 685134.11 | AS31: 3143 | AT31: 1714 | AU31: #N/A | AV31: 132.92212 | AW31: #N/A
A32: 0203 | B32: 37346 | C32: #N/A | D32: #N/A | E32: 134.75093 | F32: 50.8282 | G32: 55.5789 | H32: 86.2015 | I32: 104.2174 | J32: 57.0083 | K32: 70.4627 | L32: 87.5605 | M32: 3.02 | N32: #N/A | O32: 100.35 | P32: 79.5194 | Q32: #N/A | R32: 13240.3 | S32: 14250.7 | T32: 99.42 | U32: 39.5 | V32: #N/A | W32: #N/A | X32: #N/A | Y32: #N/A | Z32: #N/A | AA32: #N/A | AB32: #N/A | AC32: #N/A | AD32: #N/A | AE32: #N/A | AF32: #N/A | AG32: #N/A | AH32: #N/A | AI32: 7233.28 | AJ32: 80.857 | AK32: 83.426 | AL32: 92.811 | AM32: 74.204 | AN32: 57.206 | AO32: #N/A | AP32: 78.826568 | AQ32: 67.4 | AR32: 739576.84 | AS32: 3113 | AT32: 1699 | AU32: #N/A | AV32: 137.79895 | AW32: #N/A
... A53: 0312 | B53: 37986 | C53: #N/A | D53: #N/A | E53: 107.20342 | F53: 55.2661 | G53: 59.4819 | H53: 90.5486 | I53: 113.2776 | J53: 61.4197 | K53: 79.09 | L53: 87.7296 | M53: 3.36 | N53: #N/A | O53: 100.12 | P53: 85.0177 | Q53: #N/A | R53: 14662.7 | S53: 15009.2 | T53: 98.68 | U53: 39 | V53: #N/A | W53: #N/A | X53: #N/A | Y53: #N/A | Z53: #N/A | AA53: #N/A | AB53: #N/A | AC53: #N/A | AD53: #N/A | AE53: #N/A | AF53: #N/A | AG53: #N/A | AH53: #N/A | AI53: 8546.41 | AJ53: 85.32 | AK53: 87.353 | AL53: 95.167 | AM53: 79.154 | AN53: 63.534 | AO53: #N/A | AP53: 81.713458 | AQ53: 71 | AR53: 824793.48 | AS53: 3417 | AT53: 2141 | AU53: #N/A | AV53: 221.73944 | AW53: #N/A
A54: 0401 | B54: 38017 | C54: #N/A | D54: #N/A | E54: 110.05424 | F54: 55.523 | G54: 59.6376 | H54: 91.0236 | I54: 112.8947 | J54: 65.2599 | K54: 85.6989 | L54: 87.1305 | M54: 3.81 | N54: #N/A | O54: 100.2 | P54: 85.1817 | Q54: #N/A | R54: 14676.1 | S54: 14719 | T54: 98.8 | U54: 39.5 | V54: 99.02 | W54: #N/A | X54: #N/A | Y54: #N/A | Z54: #N/A | AA54: #N/A | AB54: #N/A | AC54: #N/A | AD54: #N/A | AE54: #N/A | AF54: #N/A | AG54: #N/A | AH54: #N/A | AI54: 9267.79 | AJ54: 83.436 | AK54: 86.602 | AL54: 93.871 | AM54: 79.123 | AN54: 57.276 | AO54: #N/A | AP54: 82.175198 | AQ54: 75.2 | AR54: 843411.59 | AS54: 3387 | AT54: 1897 | AU54: #N/A | AV54: 99.450043 | AW54: #N/A
A55: 0402 | B55: 38046 | C55: #N/A | D55: #N/A | E55: 109.61216 | F55: 55.859 | G55: 59.8034 | H55: 90.8923 | I55: 112.5663 | J55: 65.5862 | K55: 82.4612 | L55: 87.4015 | M55: 3.98 | N55: #N/A | O55: 100.25 | P55: 85.1817 | Q55: #N/A | R55: 14822.2 | S55: 15436.3 | T55: 98.91 | U55: 40 | V55: 99.11 | W55: #N/A | X55: #N/A | Y55: #N/A | Z55: #N/A | AA55: #N/A | AB55: #N/A | AC55: #N/A | AD55: #N/A | AE55: #N/A | AF55: #N/A | AG55: #N/A | AH55: #N/A | AI55: 9897.86 | AJ55: 84.782 | AK55: 87.262 | AL55: 95.277 | AM55: 79.196 | AN55: 63.156 | AO55: #N/A | AP55: 82.483083 | AQ55: 73.3 | AR55: 877687.7 | AS55: 3367 | AT55: 1752 | AU55: #N/A | AV55: 103.41336 | AW55: #N/A
A56: 0403 | B56: 38077 | C56: #N/A | D56: #N/A | E56: 110.33435 | F56: 56.0447 | G56: 59.9896 | H56: 92.234 | I56: 112.233 | J56: 67.3091 | K56: 83.6237 | L56: 89.5256 | M56: 3.95 | N56: #N/A | O56: 100.24 | P56: 87.1513 | Q56: #N/A | R56: 15204.5 | S56: 15662.9 | T56: 99.02 | U56: 39.1 | V56: 99.21 | W56: #N/A | X56: #N/A | Y56: #N/A | Z56: #N/A | AA56: #N/A | AB56: #N/A | AC56: #N/A | AD56: #N/A | AE56: #N/A | AF56: #N/A | AG56: #N/A | AH56: #N/A | AI56: 10104.65 | AJ56: 86.26 | AK56: 88.325 | AL56: 96.96 | AM56: 79.588 | AN56: 66.785 | AO56: #N/A | AP56: 83.43584 | AQ56: 74.6 | AR56: 847649.37 | AS56: 3385 | AT56: 1789 | AU56: #N/A | AV56: 102.82116 | AW56: #N/A
A57: 0404 | B57: 38107 | C57: #N/A | D57: #N/A | E57: 107.86164 | F57: 56.1758 | G57: 60.2041 | H57: 92.2939 | I57: 114.2347 | J57: 66.6832 | K57: 83.991 | L57: 89.0112 | M57: 3.96 | N57: #N/A | O57: 100.21 | P57: 87.7257 | Q57: #N/A | R57: 15043.2 | S57: 15752.4 | T57: 99.1 | U57: 39.9 | V57: 99.35 | W57: #N/A | X57: #N/A | Y57: #N/A | Z57: #N/A | AA57: #N/A | AB57: #N/A | AC57: #N/A | AD57: #N/A | AE57: #N/A | AF57: #N/A | AG57: #N/A | AH57: #N/A | AI57: 10580.25 | AJ57: 85.597 | AK57: 87.822 | AL57: 95.547 | AM57: 79.929 | AN57: 66.266 | AO57: #N/A | AP57: 83.253844 | AQ57: 75.9 | AR57: 877004.86 | AS57: 3419 | AT57: 1766 | AU57: #N/A | AV57: 89.289902 | AW57: #N/A
A58: 0405 | B58: 38138 | C58: #N/A | D58: #N/A | E58: 105.60213 | F58: 56.3759 | G58: 60.4125 | H58: 92.0734 | I58: 112.9062 | J58: 66.1061 | K58: 83.1413 | L58: 89.0902 | M58: 3.85 | N58: #N/A | O58: 100.14 | P58: 88.7105 | Q58: #N/A | R58: 16039 | S58: 16545.2 | T58: 99.17 | U58: 40.5 | V58: 99.48 | W58: #N/A | X58: #N/A | Y58: #N/A | Z58: #N/A | AA58: #N/A | AB58: #N/A | AC58: #N/A | AD58: #N/A | AE58: #N/A | AF58: #N/A | AG58: #N/A | AH58: #N/A | AI58: 9882.5 | AJ58: 86.214 | AK58: 88.067 | AL58: 96.168 | AM58: 79.928 | AN58: 69.377 | AO58: #N/A | AP58: 83.805945 | AQ58: 75.6 | AR58: 879905.3 | AS58: 3399 | AT58: 1967 | AU58: #N/A | AV58: 127.32442 | AW58: #N/A
A59: 0406 | B59: 38168 | C59: #N/A | D59: #N/A | E59: 106.28859 | F59: 56.5879 | G59: 60.6345 | H59: 92.2275 | I59: 113.7036 | J59: 66.4504 | K59: 83.3064 | L59: 89.0239 | M59: 3.93 | N59: #N/A | O59: 100.06 | P59: 87.9719 | Q59: #N/A | R59: 15502.3 | S59: 16288.8 | T59: 99.2 | U59: 40.8 | V59: 99.6 | W59: #N/A | X59: #N/A | Y59: #N/A | Z59: #N/A | AA59: #N/A | AB59: #N/A | AC59: #N/A | AD59: #N/A | AE59: #N/A | AF59: #N/A | AG59: #N/A | AH59: #N/A | AI59: 10161.72 | AJ59: 86.721 | AK59: 88.674 | AL59: 96.698 | AM59: 80.364 | AN59: 67.433 | AO59: #N/A | AP59: 83.627714 | AQ59: 75.6 | AR59: 867285.34 | AS59: 3395 | AT59: 1846 | AU59: #N/A | AV59: 80.301644 | AW59: #N/A
A60: 0407 | B60: 38199 | C60: #N/A | D60: #N/A | E60: 105.45391 | F60: 56.8084 | G60: 60.8206 | H60: 91.831 | I60: 111.2628 | J60: 66.7924 | K60: 82.8433 | L60: 89.6807 | M60: 3.82 | N60: #N/A | O60: 99.99 | P60: 89.367 | Q60: #N/A | R60: 15657.8 | S60: 16533 | T60: 99.24 | U60: 39.6 | V60: 99.69 | W60: #N/A | X60: #N/A | Y60: #N/A | Z60: #N/A | AA60: #N/A | AB60: #N/A | AC60: #N/A | AD60: #N/A | AE60: #N/A | AF60: #N/A | AG60: #N/A | AH60: #N/A | AI60: 10036.76 | AJ60: 87.153 | AK60: 89.254 | AL60: 97.401 | AM60: 81.009 | AN60: 68.295 | AO60: #N/A | AP60: 83.213987 | AQ60: 75.6 | AR60: 884296.7 | AS60: 3373 | AT60: 1805 | AU60: #N/A | AV60: 93.797958 | AW60: #N/A
A61: 0408 | B61: 38230 | C61: #N/A | D61: #N/A | E61: 106.74599 | F61: 57.1401 | G61: 61.0354 | H61: 91.8392 | I61: 110.8219 | J61: 67.5699 | K61: 80.7516 | L61: 90.2139 | M61: 4.12 | N61: #N/A | O61: 99.93 | P61: 88.8746 | Q61: #N/A | R61: 15991.6 | S61: 16574.5 | T61: 99.27 | U61: 39.2 | V61: 99.77 | W61: #N/A | X61: #N/A | Y61: #N/A | Z61: #N/A | AA61: #N/A | AB61: #N/A | AC61: #N/A | AD61: #N/A | AE61: #N/A | AF61: #N/A | AG61: #N/A | AH61: #N/A | AI61: 10059.26 | AJ61: 87.406 | AK61: 89.216 | AL61: 97.221 | AM61: 81.1 | AN61: 71.193 | AO61: #N/A | AP61: 83.4438 | AQ61: 73.8 | AR61: 909504.99 | AS61: 3343 | AT61: 1815 | AU61: #N/A | AV61: 63.087223 | AW61: #N/A
A62: 0409 | B62: 38260 | C62: #N/A | D62: #N/A | E62: 106.19713 | F62: 57.4545 | G62: 61.2202 | H62: 92.4192 | I62: 114.4294 | J62: 67.884 | K62: 82.5398 | L62: 89.8776 | M62: 3.89 | N62: #N/A | O62: 99.9 | P62: 89.9414 | Q62: #N/A | R62: 15829.4 | S62: 16325.4 | T62: 99.33 | U62: 40.1 | V62: 99.82 | W62: #N/A | X62: #N/A | Y62: #N/A | Z62: #N/A | AA62: #N/A | AB62: #N/A | AC62: #N/A | AD62: #N/A | AE62: #N/A | AF62: #N/A | AG62: #N/A | AH62: #N/A | AI62: 10668.76 | AJ62: 87.321 | AK62: 89.234 | AL62: 96.988 | AM62: 81.337 | AN62: 71.11 | AO62: #N/A | AP62: 83.653032 | AQ62: 74.6 | AR62: 938517.03 | AS62: 3405 | AT62: 1894 | AU62: #N/A | AV62: 46.525938 | AW62: #N/A
A63: 0410 | B63: 38291 | C63: #N/A | D63: #N/A | E63: 106.68661 | F63: 57.8005 | G63: 61.4277 | H63: 92.7884 | I63: 116.4717 | J63: 68.2858 | K63: 83.0801 | L63: 90.0302 | M63: 3.93 | N63: #N/A | O63: 99.89 | P63: 90.8441 | Q63: #N/A | R63: 16355 | S63: 16840.6 | T63: 99.4 | U63: 39.8 | V63: 99.85 | W63: #N/A | X63: #N/A | Y63: #N/A | Z63: #N/A | AA63: #N/A | AB63: #N/A | AC63: #N/A | AD63: #N/A | AE63: #N/A | AF63: #N/A | AG63: #N/A | AH63: #N/A | AI63: 11137.56 | AJ63: 86.982 | AK63: 88.938 | AL63: 96.585 | AM63: 81.5 | AN63: 70.294 | AO63: #N/A | AP63: 83.912294 | AQ63: 75.9 | AR63: 977220.15 | AS63: 3526 | AT63: 1980 | AU63: #N/A | AV63: 95.051785 | AW63: #N/A
A64: 0411 | B64: 38321 | C64: #N/A | D64: #N/A | E64: 106.41829 | F64: 58.0436 | G64: 61.6135 | H64: 92.9108 | I64: 114.3778 | J64: 68.491 | K64: 83.656 | L64: 89.9798 | M64: 3.81 | N64: #N/A | O64: 99.91 | P64: 92.7316 | Q64: #N/A | R64: 16429.4 | S64: 17701.3 | T64: 99.47 | U64: 40.2 | V64: 99.88 | W64: #N/A | X64: #N/A | Y64: #N/A | Z64: #N/A | AA64: #N/A | AB64: #N/A | AC64: #N/A | AD64: #N/A | AE64: #N/A | AF64: #N/A | AG64: #N/A | AH64: #N/A | AI64: 11898.57 | AJ64: 89.242 | AK64: 90.754 | AL64: 99.401 | AM64: 81.739 | AN64: 74.391 | AO64: #N/A | AP64: 84.721945 | AQ64: 77.1 | AR64: 948628.04 | AS64: 3403 | AT64: 1950 | AU64: #N/A | AV64: 105.85602 | AW64: #N/A
A65: 0412 | B65: 38352 | C65: #N/A | D65: #N/A | E65: 107.58665 | F65: 58.1007 | G65: 61.7973 | H65: 92.799 | I65: 108.5986 | J65: 68.9469 | K65: 83.4966 | L65: 90.953 | M65: 3.93 | N65: #N/A | O65: 99.92 | P65: 91.3364 | Q65: #N/A | R65: 15755.7 | S65: 17328.9 | T65: 99.51 | U65: 41.1 | V65: 99.91 | W65: #N/A | X65: #N/A | Y65: #N/A | Z65: #N/A | AA65: #N/A | AB65: #N/A | AC65: #N/A | AD65: #N/A | AE65: #N/A | AF65: #N/A | AG65: #N/A | AH65: #N/A | AI65: 12503.79 | AJ65: 89.207 | AK65: 90.401 | AL65: 98.607 | AM65: 81.866 | AN65: 74.036 | AO65: #N/A | AP65: 84.418444 | AQ65: 77 | AR65: 982947.35 | AS65: 3194 | AT65: 1974 | AU65: #N/A | AV65: 106.45698 | AW65: #N/A
A66: 0501 | B66: 38383 | C66: #N/A | D66: #N/A | E66: 107.14464 | F66: 58.0399 | G66: 61.9702 | H66: 93.3549 | I66: 113.242 | J66: 70.9917 | K66: 88.3705 | L66: 90.1392 | M66: 3.99 | N66: #N/A | O66: 99.91 | P66: 91.8288 | Q66: #N/A | R66: 16364.9 | S66: 17697.5 | T66: 99.54 | U66: 42 | V66: 99.93 | W66: #N/A | X66: #N/A | Y66: #N/A | Z66: #N/A | AA66: #N/A | AB66: #N/A | AC66: #N/A | AD66: #N/A | AE66: #N/A | AF66: #N/A | AG66: #N/A | AH66: #N/A | AI66: 12752.58 | AJ66: 88.736 | AK66: 90.756 | AL66: 99.523 | AM66: 81.787 | AN66: 73.374 | AO66: #N/A | AP66: 84.537968 | AQ66: 79.9 | AR66: 966427.69 | AS66: 3333 | AT66: 1818 | AU66: 52.4 | AV66: 87.126524 | AW66: 56.6
A67: 0502 | B67: 38411 | C67: #N/A | D67: #N/A | E67: 108.28602 | F67: 58.2338 | G67: 62.1264 | H67: 93.4514 | I67: 113.4427 | J67: 71.5905 | K67: 84.8223 | L67: 90.8754 | M67: 3.63 | N67: #N/A | O67: 99.87 | P67: 91.6648 | Q67: #N/A | R67: 16722.9 | S67: 17667.8 | T67: 99.56 | U67: 43.8 | V67: 99.94 | W67: #N/A | X67: #N/A | Y67: #N/A | Z67: #N/A | AA67: #N/A | AB67: #N/A | AC67: #N/A | AD67: #N/A | AE67: #N/A | AF67: #N/A | AG67: #N/A | AH67: #N/A | AI67: 13586 | AJ67: 88.62 | AK67: 90.242 | AL67: 98.379 | AM67: 81.897 | AN67: 74.432 | AO67: #N/A | AP67: 84.779174 | AQ67: 78.7 | AR67: 1001139.4 | AS67: 3360 | AT67: 1898 | AU67: 53.6 | AV67: 76.060993 | AW67: 55
A68: 0503 | B68: 38442 | C68: #N/A | D68: #N/A | E68: 108.08723 | F68: 58.4299 | G68: 62.2362 | H68: 93.0627 | I68: 111.4179 | J68: 71.5153 | K68: 85.1853 | L68: 90.6886 | M68: 3.65 | N68: #N/A | O68: 99.81 | P68: 92.2392 | Q68: #N/A | R68: 16578.1 | S68: 17491 | T68: 99.56 | U68: 42.2 | V68: 99.93 | W68: #N/A | X68: #N/A | Y68: #N/A | Z68: #N/A | AA68: #N/A | AB68: #N/A | AC68: #N/A | AD68: #N/A | AE68: #N/A | AF68: #N/A | AG68: #N/A | AH68: #N/A | AI68: 13294.26 | AJ68: 88.241 | AK68: 89.879 | AL68: 97.89 | AM68: 81.812 | AN68: 74.007 | AO68: #N/A | AP68: 84.487928 | AQ68: 79.5 | AR68: 1044991.4 | AS68: 3272 | AT68: 1856 | AU68: 51.5 | AV68: 55.697063 | AW68: 54.4
A69: 0504 | B69: 38472 | C69: #N/A | D69: #N/A | E69: 108.98516 | F69: 58.8298 | G69: 62.4473 | H69: 93.6297 | I69: 114.2302 | J69: 71.8169 | K69: 84.9593 | L69: 90.7694 | M69: 3.8 | N69: #N/A | O69: 99.75 | P69: 91.6648 | Q69: #N/A | R69: 17628.9 | S69: 18030.9 | T69: 99.57 | U69: 41.2 | V69: 99.92 | W69: #N/A | X69: #N/A | Y69: #N/A | Z69: #N/A | AA69: #N/A | AB69: #N/A | AC69: #N/A | AD69: #N/A | AE69: #N/A | AF69: #N/A | AG69: #N/A | AH69: #N/A | AI69: 12284.35 | AJ69: 88.755 | AK69: 90.24 | AL69: 98.634 | AM69: 81.804 | AN69: 75.144 | AO69: #N/A | AP69: 84.943248 | AQ69: 78.5 | AR69: 988538.08 | AS69: 3376 | AT69: 1781 | AU69: 49.9 | AV69: 182.10377 | AW69: 51.5
A70: 0505 | B70: 38503 | C70: #N/A | D70: #N/A | E70: 110.22448 | F70: 59.0078 | G70: 62.5956 | H70: 95.0878 | I70: 116.0768 | J70: 72.2879 | K70: 85.8305 | L70: 91.4752 | M70: 3.74 | N70: #N/A | O70: 99.74 | P70: 92.3212 | Q70: #N/A | R70: 17202.5 | S70: 17720.6 | T70: 99.58 | U70: 40.1 | V70: 99.9 | W70: #N/A | X70: #N/A | Y70: #N/A | Z70: #N/A | AA70: #N/A | AB70: #N/A | AC70: #N/A | AD70: #N/A | AE70: #N/A | AF70: #N/A | AG70: #N/A | AH70: #N/A | AI70: 12717.73 | AJ70: 89.056 | AK70: 90.682 | AL70: 99.656 | AM70: 81.608 | AN70: 74.475 | AO70: #N/A | AP70: 85.905433 | AQ70: 79.3 | AR70: 1007360.7 | AS70: 3441 | AT70: 1841 | AU70: 50.3 | AV70: 84.259365 | AW70: 54
A71: 0506 | B71: 38533 | C71: #N/A | D71: #N/A | E71: 112.41038 | F71: 59.0826 | G71: 62.7883 | H71: 93.4634 | I71: 115.7101 | J71: 73.3547 | K71: 85.685 | L71: 88.9737 | M71: 3.93 | N71: #N/A | O71: 99.78 | P71: 90.3518 | Q71: #N/A | R71: 17895.1 | S71: 18204 | T71: 99.6 | U71: 40.9 | V71: 99.9 | W71: #N/A | X71: #N/A | Y71: #N/A | Z71: #N/A | AA71: #N/A | AB71: #N/A | AC71: #N/A | AD71: #N/A | AE71: #N/A | AF71: #N/A | AG71: #N/A | AH71: #N/A | AI71: 13375.52 | AJ71: 88.263 | AK71: 89.423 | AL71: 97.031 | AM71: 81.666 | AN71: 77.483 | AO71: #N/A | AP71: 84.543423 | AQ71: 79.5 | AR71: 1026026.9 | AS71: 3380 | AT71: 1796 | AU71: 50.5 | AV71: 68.761204 | AW71: 54.7
A72: 0507 | B72: 38564 | C72: #N/A | D72: #N/A | E72: 114.25119 | F72: 59.3512 | G72: 62.9792 | H72: 91.6306 | I72: 105.7775 | J72: 73.5675 | K72: 84.7388 | L72: 90.1625 | M72: 3.81 | N72: #N/A | O72: 99.86 | P72: 90.762 | Q72: #N/A | R72: 17155.2 | S72: 18276.1 | T72: 99.67 | U72: 41 | V72: 99.91 | W72: #N/A | X72: #N/A | Y72: #N/A | Z72: #N/A | AA72: #N/A | AB72: #N/A | AC72: #N/A | AD72: #N/A | AE72: #N/A | AF72: #N/A | AG72: #N/A | AH72: #N/A | AI72: 14003.4 | AJ72: 89.014 | AK72: 90.273 | AL72: 99.006 | AM72: 81.52 | AN72: 78.134 | AO72: #N/A | AP72: 84.821743 | AQ72: 78.4 | AR72: 994691.76 | AS72: 3099 | AT72: 1714 | AU72: 51 | AV72: 81.944411 | AW72: 57.2
A73: 0508 | B73: 38595 | C73: #N/A | D73: #N/A | E73: 113.01056 | F73: 59.4011 | G73: 63.1184 | H73: 94.3266 | I73: 115.5784 | J73: 72.7875 | K73: 84.4963 | L73: 91.0977 | M73: 3.36 | N73: #N/A | O73: 99.98 | P73: 92.2392 | Q73: #N/A | R73: 17865.8 | S73: 18403.1 | T73: 99.8 | U73: 40.1 | V73: 99.96 | W73: #N/A | X73: #N/A | Y73: #N/A | Z73: #N/A | AA73: #N/A | AB73: #N/A | AC73: #N/A | AD73: #N/A | AE73: #N/A | AF73: #N/A | AG73: #N/A | AH73: #N/A | AI73: 14580.26 | AJ73: 89.564 | AK73: 91.218 | AL73: 100.465 | AM73: 81.804 | AN73: 74.616 | AO73: #N/A | AP73: 85.998676 | AQ73: 79.6 | AR73: 979484.48 | AS73: 3414 | AT73: 1766 | AU73: 51.2 | AV73: 70.376107 | AW73: 54.7
A74: 0509 | B74: 38625 | C74: #N/A | D74: #N/A | E74: 111.34645 | F74: 59.4669 | G74: 63.2745 | H74: 94.3877 | I74: 113.5651 | J74: 73.1989 | K74: 85.676 | L74: 92.1055 | M74: 3.41 | N74: #N/A | O74: 100.13 | P74: 94.4549 | Q74: #N/A | R74: 18314.4 | S74: 18421.4 | T74: 99.96 | U74: 41.6 | V74: 100.03 | W74: #N/A | X74: #N/A | Y74: #N/A | Z74: #N/A | AA74: #N/A | AB74: #N/A | AC74: #N/A | AD74: #N/A | AE74: #N/A | AF74: #N/A | AG74: #N/A | AH74: #N/A | AI74: 15393.03 | AJ74: 90.149 | AK74: 91.74 | AL74: 101.165 | AM74: 82.097 | AN74: 76.955 | AO74: #N/A | AP74: 86.128849 | AQ74: 80.3 | AR74: 1095126.5 | AS74: 3338 | AT74: 1677 | AU74: 52.2 | AV74: 74.33734 | AW74: 55
A75: 0510 | B75: 38656 | C75: #N/A | D75: #N/A | E75: 111.44351 | F75: 59.5537 | G75: 63.4559 | H75: 94.3024 | I75: 111.7772 | J75: 73.7226 | K75: 86.1 | L75: 93.2236 | M75: 3.4 | N75: #N/A | O75: 100.29 | P75: 93.4702 | Q75: #N/A | R75: 18807.3 | S75: 19303 | T75: 100.13 | U75: 42.8 | V75: 100.14 | W75: #N/A | X75: #N/A | Y75: #N/A | Z75: #N/A | AA75: #N/A | AB75: #N/A | AC75: #N/A | AD75: #N/A | AE75: #N/A | AF75: #N/A | AG75: #N/A | AH75: #N/A | AI75: 15362.09 | AJ75: 89.572 | AK75: 90.967 | AL75: 99.965 | AM75: 82.01 | AN75: 77.651 | AO75: #N/A | AP75: 86.277167 | AQ75: 80.3 | AR75: 960746.36 | AS75: 3275 | AT75: 1908 | AU75: 51.9 | AV75: 88.145928 | AW75: 54.1
A76: 0511 | B76: 38686 | C76: #N/A | D76: #N/A | E76: 114.82468 | F76: 59.7247 | G76: 63.6301 | H76: 96.2253 | I76: 115.0995 | J76: 74.4508 | K76: 87.5136 | L76: 94.0069 | M76: 3.22 | N76: #N/A | O76: 100.47 | P76: 93.0598 | Q76: #N/A | R76: 19499.7 | S76: 20004.2 | T76: 100.3 | U76: 43.3 | V76: 100.25 | W76: #N/A | X76: #N/A | Y76: #N/A | Z76: #N/A | AA76: #N/A | AB76: #N/A | AC76: #N/A | AD76: #N/A | AE76: #N/A | AF76: #N/A | AG76: #N/A | AH76: #N/A | AI76: 16354.64 | AJ76: 89.999 | AK76: 91.292 | AL76: 100.268 | AM76: 81.878 | AN76: 77.742 | AO76: #N/A | AP76: 87.13293 | AQ76: 82.7 | AR76: 845917.83 | AS76: 3350 | AT76: 1909 | AU76: 52.6 | AV76: 45.535162 | AW76: 55.1
A77: 0512 | B77: 38717 | C77: #N/A | D77: #N/A | E77: 115.66074 | F77: 60.0028 | G77: 63.8044 | H77: 97.8572 | I77: 115.4182 | J77: 73.346 | K77: 89.5564 | L77: 94.6292 | M77: 3.21 | N77: #N/A | O77: 100.63 | P77: 93.306 | Q77: #N/A | R77: 20238.4 | S77: 20721.9 | T77: 100.45 | U77: 43.6 | V77: 100.36 | W77: #N/A | X77: #N/A | Y77: #N/A | Z77: #N/A | AA77: #N/A | AB77: #N/A | AC77: #N/A | AD77: #N/A | AE77: #N/A | AF77: #N/A | AG77: #N/A | AH77: #N/A | AI77: 17626.65 | AJ77: 90.264 | AK77: 90.539 | AL77: 98.085 | AM77: 82.604 | AN77: 82.113 | AO77: #N/A | AP77: 87.617952 | AQ77: 85.1 | AR77: 916957.54 | AS77: 3369 | AT77: 1848 | AU77: 52.7 | AV77: 59.744308 | AW77: 56
... A89: 0612 | B89: 39082 | C89: #N/A | D89: #N/A | E89: 112.04289 | F89: 62.422 | G89: 66.1218 | H89: 98.204 | I89: 105.1401 | J89: 84.6121 | K89: 94.9168 | L89: 96.0814 | M89: 3.85 | N89: #N/A | O89: 101.74 | P89: 95.85 | Q89: #N/A | R89: 21136.8 | S89: 22020.3 | T89: 100.77 | U89: 44.1 | V89: 101.55 | W89: #N/A | X89: #N/A | Y89: #N/A | Z89: #N/A | AA89: #N/A | AB89: #N/A | AC89: #N/A | AD89: #N/A | AE89: #N/A | AF89: #N/A | AG89: #N/A | AH89: #N/A | AI89: 25747.31 | AJ89: 93.932 | AK89: 94.027 | AL89: 101.787 | AM89: 85.895 | AN89: 86.317 | AO89: #N/A | AP89: 90.109916 | AQ89: 90.3 | AR89: 1141664.3 | AS89: 2967 | AT89: 1525 | AU89: 52.5 | AV89: 31.829011 | AW89: 50.1
A90: 0701 | B90: 39113 | C90: #N/A | D90: #N/A | E90: 111.90525 | F90: 62.6967 | G90: 66.3783 | H90: 97.775 | I90: 110.3624 | J90: 84.4686 | K90: 94.7646 | L90: 95.7051 | M90: 3.72 | N90: 99.5 | O90: 101.84 | P90: 95.7679 | Q90: #N/A | R90: 20533.1 | S90: 21922.8 | T90: 100.8 | U90: 42.6 | V90: 101.69 | W90: #N/A | X90: #N/A | Y90: #N/A | Z90: #N/A | AA90: #N/A | AB90: #N/A | AC90: #N/A | AD90: #N/A | AE90: #N/A | AF90: #N/A | AG90: #N/A | AH90: #N/A | AI90: 26564.1 | AJ90: 93.649 | AK90: 94.706 | AL90: 101.923 | AM90: 87.327 | AN90: 84.252 | AO90: 278158036 | AP90: 90.049368 | AQ90: 87.2 | AR90: 1085422.6 | AS90: 3140 | AT90: 1582 | AU90: 50.3 | AV90: 29.182122 | AW90: 52.6
A91: 0702 | B91: 39141 | C91: #N/A | D91: #N/A | E91: 111.16606 | F91: 62.8671 | G91: 66.5686 | H91: 98.639 | I91: 111.1932 | J91: 83.329 | K91: 95.9676 | L91: 95.8918 | M91: 3.8 | N91: 99.75 | O91: 101.94 | P91: 96.4244 | Q91: #N/A | R91: 21367.5 | S91: 22267.9 | T91: 100.86 | U91: 42.8 | V91: 101.78 | W91: #N/A | X91: #N/A | Y91: #N/A | Z91: #N/A | AA91: #N/A | AB91: #N/A | AC91: #N/A | AD91: #N/A | AE91: #N/A | AF91: #N/A | AG91: #N/A | AH91: #N/A | AI91: 28106.18 | AJ91: 94.185 | AK91: 95.279 | AL91: 103.273 | AM91: 87.019 | AN91: 85.445 | AO91: 276192380 | AP91: 90.297156 | AQ91: 90.4 | AR91: 1050974.4 | AS91: 3151 | AT91: 1773 | AU91: 51.3 | AV91: 51.594071 | AW91: 51.8
A92: 0703 | B92: 39172 | C92: #N/A | D92: #N/A | E92: 109.39735 | F92: 63.0197 | G92: 66.7243 | H92: 99.2679 | I92: 111.4369 | J92: 85.2469 | K92: 96.3351 | L92: 97.0287 | M92: 4.22 | N92: 99.79 | O92: 102.02 | P92: 95.1935 | Q92: #N/A | R92: 21559.6 | S92: 22403.8 | T92: 100.93 | U92: 43 | V92: 101.82 | W92: #N/A | X92: #N/A | Y92: #N/A | Z92: #N/A | AA92: #N/A | AB92: #N/A | AC92: #N/A | AD92: #N/A | AE92: #N/A | AF92: #N/A | AG92: #N/A | AH92: #N/A | AI92: 27310.64 | AJ92: 94.842 | AK92: 95.725 | AL92: 104.082 | AM92: 87.278 | AN92: 88.245 | AO92: 314457797 | AP92: 90.457499 | AQ92: 90.7 | AR92: 1052557.1 | AS92: 3188 | AT92: 1782 | AU92: 52.1 | AV92: 39.799185 | AW92: 52
A93: 0704 | B93: 39202 | C93: #N/A | D93: #N/A | E93: 109.71768 | F93: 63.0646 | G93: 66.8873 | H93: 99.0185 | I93: 111.1933 | J93: 84.6001 | K93: 96.0901 | L93: 96.5773 | M93: 3.69 | N93: 100.57 | O93: 102.09 | P93: 95.6858 | Q93: #N/A | R93: 21536.4 | S93: 22809.5 | T93: 101.03 | U93: 43.3 | V93: 101.81 | W93: #N/A | X93: #N/A | Y93: #N/A | Z93: #N/A | AA93: #N/A | AB93: #N/A | AC93: #N/A | AD93: #N/A | AE93: #N/A | AF93: #N/A | AG93: #N/A | AH93: #N/A | AI93: 29489.71 | AJ93: 95.285 | AK93: 96.075 | AL93: 103.853 | AM93: 88.312 | AN93: 88.648 | AO93: 294752007 | AP93: 91.037756 | AQ93: 91.7 | AR93: 1061326.4 | AS93: 3147 | AT93: 1679 | AU93: 52.7 | AV93: 9.4294138 | AW93: 51.6
A94: 0705 | B94: 39233 | C94: #N/A | D94: #N/A | E94: 110.06048 | F94: 63.2155 | G94: 67.0759 | H94: 99.0383 | I94: 109.2119 | J94: 85.6188 | K94: 94.8141 | L94: 97.4567 | M94: 3.67 | N94: 100.68 | O94: 102.13 | P94: 96.0141 | Q94: #N/A | R94: 22182.8 | S94: 23509.4 | T94: 101.13 | U94: 43.6 | V94: 101.77 | W94: #N/A | X94: #N/A | Y94: #N/A | Z94: #N/A | AA94: #N/A | AB94: #N/A | AC94: #N/A | AD94: #N/A | AE94: #N/A | AF94: #N/A | AG94: #N/A | AH94: #N/A | AI94: 30307.04 | AJ94: 95.073 | AK94: 96.178 | AL94: 104.59 | AM94: 87.795 | AN94: 86.804 | AO94: 319301195 | AP94: 91.524736 | AQ94: 90.4 | AR94: 1023351.6 | AS94: 3111 | AT94: 1758 | AU94: 52.2 | AV94: 87.953954 | AW94: 53.5
A95: 0706 | B95: 39263 | C95: #N/A | D95: #N/A | E95: 109.76367 | F95: 63.4277 | G95: 67.291 | H95: 99.599 | I95: 112.1844 | J95: 85.3867 | K95: 93.5933 | L95: 97.507 | M95: 3.52 | N95: 100.72 | O95: 102.16 | P95: 96.9989 | Q95: #N/A | R95: 22481.3 | S95: 23999.5 | T95: 101.22 | U95: 43.1 | V95: 101.72 | W95: #N/A | X95: #N/A | Y95: #N/A | Z95: #N/A | AA95: #N/A | AB95: #N/A | AC95: #N/A | AD95: #N/A | AE95: #N/A | AF95: #N/A | AG95: #N/A | AH95: #N/A | AI95: 31647.54 | AJ95: 95.64 | AK95: 96.273 | AL95: 104.957 | AM95: 87.839 | AN95: 89.809 | AO95: 319611552 | AP95: 91.765106 | AQ95: 89.8 | AR95: 1088976.8 | AS95: 3169 | AT95: 1737 | AU95: 52.2 | AV95: 95.643579 | AW95: 51.7
A96: 0707 | B96: 39294 | C96: #N/A | D96: #N/A | E96: 109.45584 | F96: 63.7059 | G96: 67.5334 | H96: 99.4528 | I96: 111.9615 | J96: 85.992 | K96: 96.2125 | L96: 97.0479 | M96: 3.6 | N96: 100 | O96: 102.19 | P96: 97.4092 | Q96: #N/A | R96: 22444.4 | S96: 23197.7 | T96: 101.29 | U96: 42.9 | V96: 101.68 | W96: #N/A | X96: #N/A | Y96: #N/A | Z96: #N/A | AA96: #N/A | AB96: #N/A | AC96: #N/A | AD96: #N/A | AE96: #N/A | AF96: #N/A | AG96: #N/A | AH96: #N/A | AI96: 31702.56 | AJ96: 94.833 | AK96: 96.137 | AL96: 104.061 | AM96: 87.823 | AN96: 82.888 | AO96: 302137432 | AP96: 91.824121 | AQ96: 91.7 | AR96: 1079582.1 | AS96: 3186 | AT96: 1758 | AU96: 51.7 | AV96: 45.79773 | AW96: 51.9
A97: 0708 | B97: 39325 | C97: #N/A | D97: #N/A | E97: 107.53554 | F97: 63.948 | G97: 67.7895 | H97: 98.0548 | I97: 101.2003 | J97: 86.4918 | K97: 98.3708 | L97: 97.2711 | M97: 3.6 | N97: 100.15 | O97: 102.2 | P97: 97.9015 | Q97: #N/A | R97: 23315.4 | S97: 23907 | T97: 101.33 | U97: 43.5 | V97: 101.63 | W97: #N/A | X97: #N/A | Y97: #N/A | Z97: #N/A | AA97: #N/A | AB97: #N/A | AC97: #N/A | AD97: #N/A | AE97: #N/A | AF97: #N/A | AG97: #N/A | AH97: #N/A | AI97: 29486.45 | AJ97: 95.745 | AK97: 96.603 | AL97: 105.008 | AM97: 88.059 | AN97: 89.184 | AO97: 322995885 | AP97: 91.797707 | AQ97: 93.6 | AR97: 1043004.5 | AS97: 2856 | AT97: 1631 | AU97: 53.2 | AV97: 89.547002 | AW97: 51.6
A98: 0709 | B98: 39355 | C98: #N/A | D98: #N/A | E98: 107.33157 | F98: 64.2708 | G98: 68.0065 | H98: 99.7044 | I98: 109.8282 | J98: 87.262 | K98: 100.0256 | L98: 96.2906 | M98: 3.59 | N98: 99.86 | O98: 102.19 | P98: 98.9683 | Q98: #N/A | R98: 23961.6 | S98: 24409.6 | T98: 101.37 | U98: 42.6 | V98: 101.58 | W98: #N/A | X98: #N/A | Y98: #N/A | Z98: #N/A | AA98: #N/A | AB98: #N/A | AC98: #N/A | AD98: #N/A | AE98: #N/A | AF98: #N/A | AG98: #N/A | AH98: #N/A | AI98: 30405.67 | AJ98: 95.502 | AK98: 96.376 | AL98: 104.474 | AM98: 88.114 | AN98: 89.72 | AO98: 305623497 | AP98: 92.279804 | AQ98: 95.6 | AR98: 1116050.8 | AS98: 3113 | AT98: 1679 | AU98: 52.1 | AV98: 72.959912 | AW98: 52.4
A99: 0710 | B99: 39386 | C99: #N/A | D99: #N/A | E99: 108.54158 | F99: 64.4567 | G99: 68.2606 | H99: 99.3539 | I99: 107.853 | J99: 87.8149 | K99: 100.8927 | L99: 95.7452 | M99: 3.7 | N99: 100.77 | O99: 102.15 | P99: 98.3119 | Q99: #N/A | R99: 23235.6 | S99: 24210.3 | T99: 101.4 | U99: 42.2 | V99: 101.53 | W99: #N/A | X99: #N/A | Y99: #N/A | Z99: #N/A | AA99: #N/A | AB99: #N/A | AC99: #N/A | AD99: #N/A | AE99: #N/A | AF99: #N/A | AG99: #N/A | AH99: #N/A | AI99: 31908.49 | AJ99: 96.42 | AK99: 97.356 | AL99: 105.637 | AM99: 88.733 | AN99: 86.634 | AO99: 324885964 | AP99: 92.582393 | AQ99: 96.3 | AR99: 1100103.9 | AS99: 3006 | AT99: 1503 | AU99: 52.5 | AV99: 52.449882 | AW99: 53.5
A100: 0711 | B100: 39416 | C100: #N/A | D100: #N/A | E100: 107.21441 | F100: 64.624 | G100: 68.4729 | H100: 98.5845 | I100: 105.7568 | J100: 88.0074 | K100: 102.5301 | L100: 94.816 | M100: 3.67 | N100: 99.67 | O100: 102.05 | P100: 97.9015 | Q100: #N/A | R100: 24566.6 | S100: 24307.1 | T100: 101.44 | U100: 41.9 | V100: 101.44 | W100: #N/A | X100: #N/A | Y100: #N/A | Z100: #N/A | AA100: #N/A | AB100: #N/A | AC100: #N/A | AD100: #N/A | AE100: #N/A | AF100: #N/A | AG100: #N/A | AH100: #N/A | AI100: 29311.57 | AJ100: 95.024 | AK100: 95.627 | AL100: 102.063 | AM100: 89.048 | AN100: 90.065 | AO100: 313851800 | AP100: 91.896552 | AQ100: 97.4 | AR100: 1089621.8 | AS100: 2926 | AT100: 1872 | AU100: 51.2 | AV100: 63.13707 | AW100: 53.1
A101: 0712 | B101: 39447 | C101: #N/A | D101: #N/A | E101: 107.86854 | F101: 64.7632 | G101: 68.6799 | H101: 99.5871 | I101: 106.3593 | J101: 88.8705 | K101: 103.8314 | L101: 93.9634 | M101: 3.78 | N101: 100.97 | O101: 101.92 | P101: 97.7375 | Q101: #N/A | R101: 24365.4 | S101: 24597.9 | T101: 101.48 | U101: 42.2 | V101: 101.3 | W101: #N/A | X101: #N/A | Y101: #N/A | Z101: #N/A | AA101: #N/A | AB101: #N/A | AC101: #N/A | AD101: #N/A | AE101: #N/A | AF101: #N/A | AG101: #N/A | AH101: #N/A | AI101: 29982.48 | AJ101: 94.325 | AK101: 93.933 | AL101: 98.619 | AM101: 88.93 | AN101: 90.765 | AO101: 290805512 | AP101: 91.908109 | AQ101: 97.2 | AR101: 1138123 | AS101: 2923 | AT101: 1496 | AU101: 51 | AV101: 86.974308 | AW101: 51.9
A102: 0801 | B102: 39478 | C102: 7.5 | D102: 7.9214 | E102: 106.74151 | F102: 65.0039 | G102: 68.9177 | H102: 98.6916 | I102: 105.8065 | J102: 87.2956 | K102: 101.5725 | L102: 96.3126 | M102: 3.8 | N102: 100.34 | O102: 101.75 | P102: 99.332 | Q102: 92.2541 | R102: 24501.6 | S102: 25591.6 | T102: 101.54 | U102: 42 | V102: 101.1 | W102: #N/A | X102: #N/A | Y102: #N/A | Z102: #N/A | AA102: #N/A | AB102: #N/A | AC102: #N/A | AD102: #N/A | AE102: #N/A | AF102: #N/A | AG102: #N/A | AH102: #N/A | AI102: 27909.77 | AJ102: 96.065 | AK102: 96.477 | AL102: 103.797 | AM102: 88.965 | AN102: 92.358 | AO102: 314698562 | AP102: 92.394096 | AQ102: 97.7 | AR102: 1132013.6 | AS102: 2926 | AT102: 1434 | AU102: 50.5 | AV102: 85.440238 | AW102: 52.1
A103: 0802 | B103: 39507 | C103: 7.5 | D103: 7.5391 | E103: 107.32355 | F103: 65.1832 | G103: 69.1472 | H103: 100.1177 | I103: 105.6221 | J103: 89.7138 | K103: 103.9149 | L103: 96.7185 | M103: 3.71 | N103: 100.81 | O103: 101.57 | P103: 98.9498 | Q103: 93.3784 | R103: 24254.2 | S103: 25859.6 | T103: 101.6 | U103: 41.6 | V103: 100.84 | W103: #N/A | X103: #N/A | Y103: #N/A | Z103: #N/A | AA103: #N/A | AB103: #N/A | AC103: #N/A | AD103: #N/A | AE103: #N/A | AF103: #N/A | AG103: #N/A | AH103: #N/A | AI103: 29135.77 | AJ103: 96.577 | AK103: 97.386 | AL103: 105.4 | AM103: 89.345 | AN103: 90.893 | AO103: 311831882 | AP103: 92.402503 | AQ103: 100.3 | AR103: 1145405.8 | AS103: 2906 | AT103: 1429 | AU103: 51.2 | AV103: 61.81138 | AW103: 52.9
A104: 0803 | B104: 39538 | C104: 7.5 | D104: 7.4992 | E104: 106.79498 | F104: 65.6064 | G104: 69.4143 | H104: 98.6208 | I104: 104.2489 | J104: 87.2033 | K104: 101.7976 | L104: 96.407 | M104: 4.11 | N104: 100.47 | O104: 101.37 | P104: 98.1627 | Q104: 93.3662 | R104: 25374.1 | S104: 25845.2 | T104: 101.66 | U104: 41.5 | V104: 100.54 | W104: #N/A | X104: #N/A | Y104: #N/A | Z104: #N/A | AA104: #N/A | AB104: #N/A | AC104: #N/A | AD104: #N/A | AE104: #N/A | AF104: #N/A | AG104: #N/A | AH104: #N/A | AI104: 29464.04 | AJ104: 96.143 | AK104: 97.016 | AL104: 104.279 | AM104: 89.569 | AN104: 90.689 | AO104: 320524933 | AP104: 91.500826 | AQ104: 97.8 | AR104: 1113365.9 | AS104: 2836 | AT104: 1628 | AU104: 48.6 | AV104: 60.688564 | AW104: 53.6
A105: 0804 | B105: 39568 | C105: 7.5 | D105: 7.6479 | E105: 108.67382 | F105: 65.9851 | G105: 69.7916 | H105: 98.3466 | I105: 100.7984 | J105: 86.967 | K105: 102.0873 | L105: 96.6263 | M105: 3.71 | N105: 102.4 | O105: 101.15 | P105: 99.2946 | Q105: 98.9435 | R105: 25913.7 | S105: 26700.1 | T105: 101.7 | U105: 40 | V105: 100.22 | W105: #N/A | X105: #N/A | Y105: #N/A | Z105: #N/A | AA105: #N/A | AB105: #N/A | AC105: #N/A | AD105: #N/A | AE105: #N/A | AF105: #N/A | AG105: #N/A | AH105: #N/A | AI105: 31467.09 | AJ105: 96.384 | AK105: 97.486 | AL105: 105.24 | AM105: 89.665 | AN105: 85.17 | AO105: 340142345 | AP105: 93.032238 | AQ105: 98.4 | AR105: 1087853.9 | AS105: 2732 | AT105: 1439 | AU105: 52.6 | AV105: 70.231439 | AW105: 53.6
A106: 0805 | B106: 39599 | C106: 7.5 | D106: 8.0316 | E106: 109.21095 | F106: 66.3543 | G106: 70.1439 | H106: 98.4092 | I106: 102.2604 | J106: 87.7166 | K106: 103.3307 | L106: 95.3968 | M106: 3.62 | N106: 100.79 | O106: 100.86 | P106: 97.6271 | Q106: 97.934 | R106: 25596 | S106: 26393.7 | T106: 101.71 | U106: 39 | V106: 99.88 | W106: #N/A | X106: #N/A | Y106: #N/A | Z106: #N/A | AA106: #N/A | AB106: #N/A | AC106: #N/A | AD106: #N/A | AE106: #N/A | AF106: #N/A | AG106: #N/A | AH106: #N/A | AI106: 31226.91 | AJ106: 97.021 | AK106: 98.219 | AL106: 105.951 | AM106: 90.858 | AN106: 88.79 | AO106: 342534067 | AP106: 92.746047 | AQ106: 101 | AR106: 1182606.4 | AS106: 2794 | AT106: 1376 | AU106: 51 | AV106: 57.93611 | AW106: 51.8
A107: 0806 | B107: 39629 | C107: 7.75 | D107: 8.7317 | E107: 109.98255 | F107: 66.7683 | G107: 70.5053 | H107: 99.7428 | I107: 103.5366 | J107: 86.6667 | K107: 105.2302 | L107: 96.1055 | M107: 3.79 | N107: 101.46 | O107: 100.46 | P107: 98.7201 | Q107: 98.9601 | R107: 25677.1 | S107: 26327.3 | T107: 101.65 | U107: 37.7 | V107: 99.49 | W107: #N/A | X107: #N/A | Y107: #N/A | Z107: #N/A | AA107: #N/A | AB107: #N/A | AC107: #N/A | AD107: #N/A | AE107: #N/A | AF107: #N/A | AG107: #N/A | AH107: #N/A | AI107: 30291.16 | AJ107: 97.515 | AK107: 98.401 | AL107: 106.298 | AM107: 90.968 | AN107: 89.77 | AO107: 343992207 | AP107: 93.344882 | AQ107: 102.8 | AR107: 1188846.6 | AS107: 2811 | AT107: 1415 | AU107: 51.1 | AV107: 73.69704 | AW107: 50.9
A108: 0807 | B108: 39660 | C108: 8 | D108: 9.0546 | E108: 110.87179 | F108: 67.1369 | G108: 70.8203 | H108: 98.0179 | I108: 103.3718 | J108: 86.0338 | K108: 102.7827 | L108: 95.0109 | M108: 3.8 | N108: 100.55 | O108: 99.91 | P108: 98.2481 | Q108: 98.3333 | R108: 26800.4 | S108: 27913 | T108: 101.5 | U108: 36.5 | V108: 99.02 | W108: #N/A | X108: #N/A | Y108: #N/A | Z108: #N/A | AA108: #N/A | AB108: #N/A | AC108: #N/A | AD108: #N/A | AE108: #N/A | AF108: #N/A | AG108: #N/A | AH108: #N/A | AI108: 27858.71 | AJ108: 97.235 | AK108: 97.866 | AL108: 106.245 | AM108: 88.922 | AN108: 92.029 | AO108: 341675896 | AP108: 93.405468 | AQ108: 102.4 | AR108: 1111512.3 | AS108: 2794 | AT108: 1377 | AU108: 50.4 | AV108: 69.367501 | AW108: 50.7
A109: 0808 | B109: 39691 | C109: 8.25 | D109: 8.6462 | E109: 114.19555 | F109: 67.5253 | G109: 71.1988 | H109: 97.5853 | I109: 102.4661 | J109: 87.2893 | K109: 99.9798 | L109: 95.0245 | M109: 3.82 | N109: 99.96 | O109: 99.21 | P109: 96.9896 | Q109: 95.7493 | R109: 25679.7 | S109: 27542.7 | T109: 101.26 | U109: 36.7 | V109: 98.44 | W109: #N/A | X109: #N/A | Y109: #N/A | Z109: #N/A | AA109: #N/A | AB109: #N/A | AC109: #N/A | AD109: #N/A | AE109: #N/A | AF109: #N/A | AG109: #N/A | AH109: #N/A | AI109: 26765.93 | AJ109: 95.831 | AK109: 96.989 | AL109: 104.94 | AM109: 88.866 | AN109: 87.144 | AO109: 335668793 | AP109: 92.362932 | AQ109: 99.1 | AR109: 1166485.3 | AS109: 2775 | AT109: 1416 | AU109: 49.2 | AV109: 62.811148 | AW109: 50.4
A110: 0809 | B110: 39721 | C110: 8.25 | D110: 8.4886 | E110: 110.31382 | F110: 67.8169 | G110: 71.5287 | H110: 96.7669 | I110: 100.5442 | J110: 85.5842 | K110: 99.1463 | L110: 94.9295 | M110: 3.94 | N110: 101.28 | O110: 98.36 | P110: 96.5842 | Q110: 95.9739 | R110: 24119.2 | S110: 26065.2 | T110: 100.91 | U110: 36.2 | V110: 97.73 | W110: #N/A | X110: #N/A | Y110: #N/A | Z110: #N/A | AA110: #N/A | AB110: #N/A | AC110: #N/A | AD110: #N/A | AE110: #N/A | AF110: #N/A | AG110: #N/A | AH110: #N/A | AI110: 25408.59 | AJ110: 95.387 | AK110: 96.359 | AL110: 103.882 | AM110: 88.627 | AN110: 86.68 | AO110: 328748883 | AP110: 92.083955 | AQ110: 96.7 | AR110: 1084081.1 | AS110: 2706 | AT110: 1060 | AU110: 49.7 | AV110: 84.42698 | AW110: 48
A111: 0810 | B111: 39752 | C111: 8.25 | D111: 9.1861 | E111: 96.35738 | F111: 68.2105 | G111: 71.7638 | H111: 97.5995 | I111: 103.8503 | J111: 85.7551 | K111: 100.8262 | L111: 93.7997 | M111: 3.88 | N111: 101.32 | O111: 97.47 | P111: 96.2931 | Q111: 97.2073 | R111: 22735 | S111: 25331.2 | T111: 100.46 | U111: 35.1 | V111: 96.95 | W111: #N/A | X111: #N/A | Y111: #N/A | Z111: #N/A | AA111: #N/A | AB111: #N/A | AC111: #N/A | AD111: #N/A | AE111: #N/A | AF111: #N/A | AG111: #N/A | AH111: #N/A | AI111: 20511.94 | AJ111: 94.124 | AK111: 95.276 | AL111: 102.513 | AM111: 87.773 | AN111: 83.862 | AO111: 359369419 | AP111: 92.704779 | AQ111: 98.3 | AR111: 1079035.7 | AS111: 2763 | AT111: 1434 | AU111: 49.1 | AV111: 113.72736 | AW111: 47.9
A112: 0811 | B112: 39782 | C112: 8.25 | D112: 9.2778 | E112: 96.20312 | F112: 68.6684 | G112: 72.1543 | H112: 95.5504 | I112: 103.1626 | J112: 85.985 | K112: 98.0319 | L112: 92.2664 | M112: 4.66 | N112: 101.38 | O112: 96.67 | P112: 95.365 | Q112: 93.0445 | R112: 21129.9 | S112: 24039 | T112: 99.91 | U112: 35.8 | V112: 96.23 | W112: #N/A | X112: #N/A | Y112: #N/A | Z112: #N/A | AA112: #N/A | AB112: #N/A | AC112: #N/A | AD112: #N/A | AE112: #N/A | AF112: #N/A | AG112: #N/A | AH112: #N/A | AI112: 19665.77 | AJ112: 93.151 | AK112: 95.04 | AL112: 101.772 | AM112: 87.963 | AN112: 77.926 | AO112: 324728021 | AP112: 91.063536 | AQ112: 95.4 | AR112: 1074692.2 | AS112: 2749 | AT112: 1501 | AU112: 44 | AV112: 106.07161 | AW112: 47.7
A113: 0812 | B113: 39813 | C113: 8.25 | D113: 8.2627 | E113: 94.35059 | F113: 68.9935 | G113: 72.4834 | H113: 94.4796 | I113: 101.5688 | J113: 84.7205 | K113: 98.2101 | L113: 88.916 | M113: 4.72 | N113: 100.44 | O113: 96.05 | P113: 95.2428 | Q113: 90.7677 | R113: 17990.4 | S113: 19722.1 | T113: 99.32 | U113: 34.6 | V113: 95.65 | W113: #N/A | X113: #N/A | Y113: #N/A | Z113: #N/A | AA113: #N/A | AB113: #N/A | AC113: #N/A | AD113: #N/A | AE113: #N/A | AF113: #N/A | AG113: #N/A | AH113: #N/A | AI113: 21509.22 | AJ113: 92.206 | AK113: 93.087 | AL113: 97.6 | AM113: 88.309 | AN113: 76.658 | AO113: 304233615 | AP113: 89.804322 | AQ113: 92.9 | AR113: 1012759.5 | AS113: 2709 | AT113: 1327 | AU113: 46.1 | AV113: 107.19721 | AW113: 48
... A140: 1103 | B140: 40633 | C140: 4.5 | D140: 7.5552 | E140: 103.11157 | F140: 75.2324 | G140: 78.9202 | H140: 95.6785 | I140: 99.531 | J140: 97.4166 | K140: 91.96 | L140: 94.8527 | M140: 5.12 | N140: 99.61 | O140: 101.23 | P140: 94.5023 | Q140: 93.5237 | R140: 28884.1 | S140: 28430.7 | T140: 99.63 | U140: 38.5 | V140: 101.63 | W140: #N/A | X140: #N/A | Y140: #N/A | Z140: #N/A | AA140: #N/A | AB140: #N/A | AC140: #N/A | AD140: #N/A | AE140: #N/A | AF140: #N/A | AG140: #N/A | AH140: #N/A | AI140: 36483.92 | AJ140: 95.094 | AK140: 96.515 | AL140: 101.394 | AM140: 91.39 | AN140: 82.506 | AO140: 408611478 | AP140: 94.052533 | AQ140: 92.9 | AR140: 969555.15 | AS140: 2571 | AT140: 1424 | AU140: 53.7 | AV140: 85.532765 | AW140: 55.4
A141: 1104 | B141: 40663 | C141: 4.5 | D141: 7.3556 | E141: 104.40704 | F141: 75.3758 | G141: 78.9704 | H141: 96.1489 | I141: 99.7467 | J141: 97.9592 | K141: 97.093 | L141: 94.3751 | M141: 5.18 | N141: 98.98 | O141: 101.19 | P141: 95.33 | Q141: 91.4723 | R141: 28491.8 | S141: 28304.9 | T141: 99.71 | U141: 37.6 | V141: 101.49 | W141: 56.2511 | X141: 56.521 | Y141: 59.2527 | Z141: 56.7138 | AA141: 46.8009 | AB141: 50.2244 | AC141: 67.5327 | AD141: 55.9908 | AE141: 55.5952 | AF141: 57.0683 | AG141: 57.2985 | AH141: 54.1749 | AI141: 37183.63 | AJ141: 95.366 | AK141: 96.712 | AL141: 101.124 | AM141: 92.342 | AN141: 83.014 | AO141: 373236475 | AP141: 93.595827 | AQ141: 94.9 | AR141: 1033911 | AS141: 2568 | AT141: 1223 | AU141: 53.3 | AV141: 62.08677 | AW141: 55.6
A142: 1105 | B142: 40694 | C142: 4.5 | D142: 7.1106 | E142: 103.78578 | F142: 75.4707 | G142: 79.1932 | H142: 96.9623 | I142: 99.3676 | J142: 97.2094 | K142: 97.2581 | L142: 95.422 | M142: 5.35 | N142: 99.41 | O142: 101.1 | P142: 95.5079 | Q142: 92.838 | R142: 29418.3 | S142: 29354.7 | T142: 99.79 | U142: 37.7 | V142: 101.35 | W142: 54.5525 | X142: 57.4553 | Y142: 56.3941 | Z142: 53.74 | AA142: 49.47 | AB142: 49.4292 | AC142: 58.4662 | AD142: 55.1659 | AE142: 51.9556 | AF142: 56.1171 | AG142: 56.7201 | AH142: 49.7076 | AI142: 35467.57 | AJ142: 95.631 | AK142: 96.922 | AL142: 101.706 | AM142: 92.532 | AN142: 86.132 | AO142: 393306502 | AP142: 94.506471 | AQ142: 96.9 | AR142: 979045.52 | AS142: 2557 | AT142: 1368 | AU142: 54.6 | AV142: 44.460991 | AW142: 55.7
A143: 1106 | B143: 40724 | C143: 4.5 | D143: 6.9493 | E143: 102.19238 | F143: 75.6117 | G143: 79.4079 | H143: 97.8785 | I143: 99.7394 | J143: 97.9295 | K143: 103.1896 | L143: 94.9779 | M143: 5.51 | N143: 99.39 | O143: 100.95 | P143: 95.5554 | Q143: 93.9129 | R143: 29507.6 | S143: 30199.4 | T143: 99.86 | U143: 38.5 | V143: 101.2 | W143: 55.3151 | X143: 58.0524 | Y143: 57.9617 | Z143: 54.8787 | AA143: 50.5274 | AB143: 50.1684 | AC143: 57.3957 | AD143: 54.8396 | AE143: 52.3586 | AF143: 54.4842 | AG143: 53.8531 | AH143: 50.5189 | AI143: 35363.35 | AJ143: 95.813 | AK143: 97.002 | AL143: 101.599 | AM143: 92.816 | AN143: 85.59 | AO143: 398938821 | AP143: 95.085529 | AQ143: 101.2 | AR143: 986772.59 | AS143: 2555 | AT143: 1425 | AU143: 54 | AV143: 66.077499 | AW143: 56.3
A144: 1107 | B144: 40755 | C144: 4.5 | D144: 6.8364 | E144: 103.35239 | F144: 75.9646 | G144: 79.6229 | H144: 97.8356 | I144: 99.5682 | J144: 97.3939 | K144: 99.0709 | L144: 96.0197 | M144: 5.32 | N144: 99.28 | O144: 100.76 | P144: 94.8621 | Q144: 92.2942 | R144: 29310.4 | S144: 30009.8 | T144: 99.92 | U144: 38.9 | V144: 101.05 | W144: 54.7331 | X144: 55.9985 | Y144: 56.8708 | Z144: 53.5955 | AA144: 48.7389 | AB144: 52.6402 | AC144: 57.2352 | AD144: 55.7492 | AE144: 53.374 | AF144: 52.134 | AG144: 56.0004 | AH144: 50.0096 | AI144: 36070.25 | AJ144: 96.461 | AK144: 97.84 | AL144: 102.231 | AM144: 93.312 | AN144: 84.824 | AO144: 389875176 | AP144: 95.494906 | AQ144: 98.8 | AR144: 986251.06 | AS144: 2556 | AT144: 1223 | AU144: 53.5 | AV144: 85.261068 | AW144: 55.7
A145: 1108 | B145: 40786 | C145: 4.5 | D145: 6.1391 | E145: 98.34826 | F145: 76.1209 | G145: 79.809 | H145: 97.7511 | I145: 99.6969 | J145: 97.5213 | K145: 100.3201 | L145: 95.6442 | M145: 5.4 | N145: 100.66 | O145: 100.55 | P145: 95.4614 | Q145: 96.8321 | R145: 29048 | S145: 29257.5 | T145: 99.99 | U145: 38.4 | V145: 100.89 | W145: 51.742 | X145: 52.4341 | Y145: 53.3272 | Z145: 50.2671 | AA145: 49.7151 | AB145: 50.392 | AC145: 58.1054 | AD145: 52.5751 | AE145: 51.8843 | AF145: 49.2409 | AG145: 53.6398 | AH145: 49.6766 | AI145: 33928.19 | AJ145: 97.064 | AK145: 98.17 | AL145: 102.537 | AM145: 93.709 | AN145: 86.225 | AO145: 411387349 | AP145: 96.086048 | AQ145: 100.3 | AR145: 979365.79 | AS145: 2563 | AT145: 1439 | AU145: 53.4 | AV145: 103.44681 | AW145: 55
A146: 1109 | B146: 40816 | C146: 4.5 | D146: 6.2333 | E146: 93.18449 | F146: 76.1896 | G146: 79.9883 | H146: 97.1863 | I146: 97.9297 | J146: 97.8375 | K146: 99.368 | L146: 96.2037 | M146: 5.31 | N146: 100.5 | O146: 100.36 | P146: 96.5049 | Q146: 99.9065 | R146: 29106.7 | S146: 30157.6 | T146: 100.06 | U146: 38.1 | V146: 100.76 | W146: 53.0332 | X146: 54.5459 | Y146: 55.04 | Z146: 50.4514 | AA146: 48.1954 | AB146: 50.2372 | AC146: 62.6761 | AD146: 54.5002 | AE146: 52.6187 | AF146: 52.4891 | AG146: 55.7294 | AH146: 49.3794 | AI146: 34122.88 | AJ146: 97.644 | AK146: 98.854 | AL146: 103.136 | AM146: 94.479 | AN146: 86.975 | AO146: 414577624 | AP146: 96.186543 | AQ146: 99.2 | AR146: 994897.17 | AS146: 2488 | AT146: 1242 | AU146: 53.1 | AV146: 78.714123 | AW146: 51.9
A147: 1110 | B147: 40847 | C147: 4.5 | D147: 6.3553 | E147: 91.37142 | F147: 76.5699 | G147: 80.2143 | H147: 99.0944 | I147: 101.1269 | J147: 97.5187 | K147: 101.2516 | L147: 97.1105 | M147: 4.83 | N147: 100.6 | O147: 100.25 | P147: 96.94 | Q147: 98.3252 | R147: 29228.5 | S147: 29451.5 | T147: 100.14 | U147: 38.4 | V147: 100.66 | W147: 54.6616 | X147: 56.7041 | Y147: 56.8207 | Z147: 52.6302 | AA147: 48.3729 | AB147: 51.6925 | AC147: 72.3583 | AD147: 55.301 | AE147: 51.2245 | AF147: 51.9371 | AG147: 59.3627 | AH147: 52.0374 | AI147: 34550.71 | AJ147: 97.481 | AK147: 98.914 | AL147: 102.575 | AM147: 94.884 | AN147: 85.767 | AO147: 431312863 | AP147: 96.224999 | AQ147: 100.5 | AR147: 961602.22 | AS147: 2545 | AT147: 1375 | AU147: 53.1 | AV147: 44.420548 | AW147: 54.3
A148: 1111 | B148: 40877 | C148: 4.5 | D148: 6.34 | E148: 90.83241 | F148: 76.9952 | G148: 80.5487 | H148: 99.7901 | I148: 100.7888 | J148: 97.4296 | K148: 103.1158 | L148: 98.0724 | M148: 5.08 | N148: 100.25 | O148: 100.21 | P148: 96.6225 | Q148: 99.4751 | R148: 29702.1 | S148: 29867.5 | T148: 100.22 | U148: 38.3 | V148: 100.59 | W148: 53.7375 | X148: 55.7727 | Y148: 55.5859 | Z148: 52.1169 | AA148: 48.4181 | AB148: 49.5786 | AC148: 67.1673 | AD148: 54.8479 | AE148: 52.2384 | AF148: 49.3531 | AG148: 58.1983 | AH148: 51.1777 | AI148: 36345.82 | AJ148: 97.044 | AK148: 98.364 | AL148: 102.244 | AM148: 93.736 | AN148: 84.114 | AO148: 429796616 | AP148: 97.128789 | AQ148: 102.7 | AR148: 1001616.4 | AS148: 2545 | AT148: 1362 | AU148: 53.8 | AV148: 89.352945 | AW148: 55.7
A149: 1112 | B149: 40908 | C149: 4.5 | D149: 6.4465 | E149: 91.3071 | F149: 77.4689 | G149: 80.8208 | H149: 100.2423 | I149: 100.523 | J149: 99.9534 | K149: 102.606 | L149: 98.3515 | M149: 5.03 | N149: 100.3 | O149: 100.23 | P149: 98.3097 | Q149: 101.6268 | R149: 30161.4 | S149: 30243.4 | T149: 100.28 | U149: 37.6 | V149: 100.54 | W149: 53.1405 | X149: 54.9318 | Y149: 55.3258 | Z149: 51.431 | AA149: 49.5329 | AB149: 49.5358 | AC149: 62.2875 | AD149: 52.9968 | AE149: 52.4176 | AF149: 52.2409 | AG149: 55.5471 | AH149: 50.1665 | AI149: 36702.27 | AJ149: 98.481 | AK149: 99.301 | AL149: 102.827 | AM149: 95.975 | AN149: 89.519 | AO149: 413618941 | AP149: 96.816799 | AQ149: 104.3 | AR149: 1063759.1 | AS149: 2544 | AT149: 1281 | AU149: 54.2 | AV149: 49.92673 | AW149: 54.2
A150: 1201 | B150: 40939 | C150: 4.5 | D150: 6.2023 | E150: 94.19899 | F150: 77.8907 | G150: 81.097 | H150: 99.2742 | I150: 98.198 | J150: 97.6825 | K150: 101.8951 | L150: 98.9806 | M150: 4.7 | N150: 100.31 | O150: 100.29 | P150: 98.5558 | Q150: 102.9373 | R150: 30977.3 | S150: 30412.9 | T150: 100.33 | U150: 39.1 | V150: 100.5 | W150: 52.1825 | X150: 53.1411 | Y150: 54.2889 | Z150: 50.073 | AA150: 48.3976 | AB150: 48.5562 | AC150: 61.8632 | AD150: 53.5332 | AE150: 49.2025 | AF150: 51.0539 | AG150: 53.3249 | AH150: 49.6726 | AI150: 37160.11 | AJ150: 98.479 | AK150: 99.263 | AL150: 102.382 | AM150: 95.845 | AN150: 90.208 | AO150: 426787598 | AP150: 97.305284 | AQ150: 103 | AR150: 982165.35 | AS150: 2518 | AT150: 1191 | AU150: 54.8 | AV150: 54.289176 | AW150: 53.5
A151: 1202 | B151: 40968 | C151: 4.5 | D151: 6.2276 | E151: 97.982 | F151: 77.9444 | G151: 81.2931 | H151: 99.4162 | I151: 99.665 | J151: 98.8303 | K151: 100.1298 | L151: 99.1048 | M151: 5.36 | N151: 100.41 | O151: 100.34 | P151: 99.142 | Q151: 101.2218 | R151: 31198.4 | S151: 31313.2 | T151: 100.36 | U151: 39.5 | V151: 100.46 | W151: 53.6653 | X151: 55.2338 | Y151: 55.7139 | Z151: 51.5883 | AA151: 47.934 | AB151: 50.1512 | AC151: 65.0581 | AD151: 55.8486 | AE151: 47.9407 | AF151: 50.8765 | AG151: 55.1412 | AH151: 49.0545 | AI151: 37990.07 | AJ151: 97.859 | AK151: 99.054 | AL151: 102.335 | AM151: 95.923 | AN151: 87.286 | AO151: 422894852 | AP151: 97.607303 | AQ151: 102.5 | AR151: 1054309 | AS151: 2538 | AT151: 1229 | AU151: 57.1 | AV151: 74.493384 | AW151: 51.8
A152: 1203 | B152: 40999 | C152: 4.5 | D152: 6.2765 | E152: 98.28278 | F152: 78.004 | G152: 81.4921 | H152: 99.5932 | I152: 100.1657 | J152: 98.6401 | K152: 99.5256 | L152: 99.0684 | M152: 5.14 | N152: 100.39 | O152: 100.34 | P152: 99.6331 | Q152: 100.4708 | R152: 31275.4 | S152: 30456.8 | T152: 100.39 | U152: 39.1 | V152: 100.4 | W152: 53.8527 | X152: 56.2965 | Y152: 55.354 | Z152: 51.9928 | AA152: 48.2915 | AB152: 50.1753 | AC152: 60.4999 | AD152: 54.8617 | AE152: 50.9584 | AF152: 52.0309 | AG152: 53.1809 | AH152: 48.1993 | AI152: 38264.67 | AJ152: 97.774 | AK152: 98.92 | AL152: 101.847 | AM152: 95.887 | AN152: 87.841 | AO152: 452166450 | AP152: 97.916488 | AQ152: 102.6 | AR152: 1049659.1 | AS152: 2553 | AT152: 1284 | AU152: 52.7 | AV152: 57.327574 | AW152: 53.9
... A248: 2003 | B248: 43921 | C248: 6.5 | D248: 7.3024 | E248: 74.55918 | F248: 106.2245 | G248: 106.1174 | H248: 97.7905 | I248: 74.6597 | J248: 116.9476 | K248: 96.1844 | L248: 107.0733 | M248: 3.26 | N248: 108.41 | O248: 99.34 | P248: 113.7764 | Q248: 105.1238 | R248: 36535.6 | S248: 34598.6 | T248: 98.59 | U248: 42.6 | V248: 98.75 | W248: 47.917 | X248: 46.9487 | Y248: 45.4608 | Z248: 49.1627 | AA248: 47.5635 | AB248: 48.4359 | AC248: 52.0221 | AD248: 49.6388 | AE248: 49.6633 | AF248: 48.9646 | AG248: 49.8513 | AH248: 50.0188 | AI248: 37457.62 | AJ248: 113.304 | AK248: 113.399 | AL248: 112.635 | AM248: 113.291 | AN248: 109.698 | AO248: 687506319 | AP248: 109.73618 | AQ248: 94 | AR248: 1141929.4 | AS248: 1747 | AT248: 1144 | AU248: 46 | AV248: 245.43391 | AW248: 41.5
A249: 2004 | B249: 43951 | C249: 6 | D249: 6.9939 | E249: 69.18179 | F249: 105.5198 | G249: 106.4422 | H249: 73.1399 | I249: 70.2818 | J249: 115.8271 | K249: 64.6808 | L249: 74.3157 | M249: 4.72 | N249: 106.09 | O249: 98.82 | P249: 88.1269 | Q249: 86.0319 | R249: 23051.8 | S249: 27227.3 | T249: 90.83 | V249: 98.15 | W249: 35.0331 | X249: 29.6712 | Y249: 27.699 | Z249: 34.1904 | AA249: 37.1367 | AB249: 30.3797 | AC249: 45.8059 | AD249: 29.1825 | AE249: 47.0406 | AF249: 30.799 | AG249: 43.7129 | AH249: 36.8467 | AI249: 34555.57 | AJ249: 91.004 | AK249: 91.713 | AL249: 90.007 | AM249: 93.092 | AN249: 86.281 | AO249: 389872464 | AP249: 90.793462 | AQ249: 66.8 | AR249: 133420.18 | AS249: 1716 | AT249: 1178 | AU249: 41.5 | AV249: 182.68365 | AW249: 39.4
A250: 2005 | B250: 43982 | C250: 5.5 | D250: 6.1372 | E250: 71.56816 | F250: 106.5867 | G250: 106.8774 | H250: 71.7892 | I250: 68.1802 | J250: 104.0667 | K250: 63.8118 | L250: 74.0764 | M250: 4.22 | N250: 103.77 | O250: 98.39 | P250: 88.8085 | Q250: 81.6198 | R250: 18042.1 | S250: 22136.1 | V250: 97.67 | W250: 38.314 | X250: 34.2477 | Y250: 32.8243 | Z250: 35.6909 | AA250: 37.5462 | AB250: 33.9853 | AC250: 47.6392 | AD250: 34.9894 | AE250: 42.9787 | AF250: 34.2016 | AG250: 44.2622 | AH250: 37.2234 | AI250: 36478.54 | AO250: 393582130 | AP250: 88.414125 | AR250: 183837.1 | AS250: 1628 | AT250: 1062 | AU250: 39.1 | AV250: 139.41801 | AW250: 39.4
A251: 2006 | B251: 44012 | C251: 5 | D251: 6.003 | E251: 75.03301 | F251: 107.3229 | G251: 107.3086 | R251: 31677.1 | S251: 27058.3 | V251: 97.31 | W251: 38.5646 | X251: 34.1116 | Y251: 33.8742 | Z251: 36.792 | AA251: 40.1668 | AB251: 35.4108 | AC251: 47.5741 | AD251: 33.9719 | AE251: 40.0909 | AF251: 36.1227 | AG251: 44.1267 | AH251: 39.3047 | AI251: 37982.4 | AU251: 46.2 | AW251: 44.2

Sheet Haver_Q
C1: GDP | E1: GDPGOVT | F1: GDPPRIV | H1: GDPGFCF | I1: GDPX | J1: GDPM | K1: GPMGDP
A2: 1001 !Q | B2: .excel_last | C2: difa%(S273NGPC@EMERGELA) | D2: difa%(S273NCC@EMERGELA) | E2: difa%(S273NCGC@EMERGELA) | F2: difa%(S273NCPC@EMERGELA) | G2: difa%(S273NBC@EMERGELA) | H2: difa%(S273NFC@EMERGELA) | I2: difa%(S273NXC@EMERGELA) | J2: difa%(S273NMC@EMERGELA)
A3: .DESC | C3: Mexico: Gross Domestic Product, Market Prices (SAAR, 2013.NewPesos) % Change - Annual Rate | D3: Mexico: GDP: Total Consumption (SAAR, 2013.NewPesos) % Change - Annual Rate | E3: Mexico: GDP: Government Consumption (SAAR, 2013.NewPesos) % Change - Annual Rate | F3: Mexico: GDP: Private Consumption (SAAR, 2013.NewPesos) % Change - Annual Rate | G3: Mexico: GDP: Change in Inventories (SAAR, 2013.NewPesos) % Change - Annual Rate | H3: Mexico: GDP: Gross Fixed Capital Formation (SAAR, 2013.NewPesos) % Change - Annual Rate | I3: Mexico: GDP: Exports of Goods and Services (SAAR, 2013.NewPesos) % Change - Annual Rate | J3: Mexico: GDP: Imports of Goods and Services (SAAR, 2013.NewPesos) % Change - Annual Rate
A4: .T1 | C4: Q1-1980 | D4: Q1-1993 | E4: Q1-1993 | F4: Q1-1993 | G4: Q1-1993 | H4: Q1-1993 | I4: Q1-1993 | J4: Q1-1993
A5: .TN | C5: Q1-2020 | D5: Q1-2020 | E5: Q1-2020 | F5: Q1-2020 | G5: Q1-2020 | H5: Q1-2020 | I5: Q1-2020 | J5: Q1-2020
A6: 001 | B6: 36616 | C6: 0.078908208 | D6: 0.096133268 | E6: 0.12149992 | F6: 0.096004588 | G6: 0.044602791 | H6: 0.14079916 | I6: 0.17042392 | J6: 0.2754633 | K6: 5.3384295
A7: 002 | B7: 36707 | C7: 0.062703483 | D7: 0.073046384 | E7: -0.020346867 | F7: 0.088398814 | G7: 0.036853635 | H7: 0.057696005 | I7: 0.12937207 | J7: 0.12211141 | K7: 5.031488
A8: 003 | B8: 36799 | C8: 0.031479804 | D8: 0.060657067 | E8: 0.0026588307 | F8: 0.072302863 | G8: -0.61591445 | H8: -0.016482029 | I8: 0.12589966 | J8: 0.30634637 | K8: 3.1388242
A9: 004 | B9: 36891 | C9: -0.026232726 | D9: 0.033403463 | E9: -0.02427157 | F9: 0.044443038 | G9: -0.69108115 | H9: -0.091565594 | I9: 0.054053264 | J9: 0.037157616 | K9: 2.831619
A10: 011 | B10: 36981 | C10: 0.002761665 | D10: -0.016846107 | E10: -0.09129194 | F10: 0.0020262783 | G10: 1.5981973 | H10: -0.15457791 | I10: -0.062618244 | J10: -0.0897092 | K10: 1.8286258
A11: 012 | B11: 37072 | C11: -0.021975885 | D11: 0.0064594971 | E11: -0.0071002921 | F11: 0.0059673562 | G11: -0.67361092 | H11: -0.1251323 | I11: -0.018460077 | J11: -0.08156603 | K11: 1.9835864
A12: 013 | B12: 37164 | C12: 0.0010251254 | D12: 0.014354559 | E12: 0.026648864 | F12: 0.010978292 | G12: -0.17817914 | H12: 0.09574572 | I12: -0.11416183 | J12: -0.08425753 | K12: 0.88840616
A13: 014 | B13: 37256 | C13: -0.018571058 | D13: 0.02415084 | E13: -0.0012273665 | F13: 0.029383994 | G13: -0.74355978 | H13: -0.049084195 | I13: -0.033634967 | J13: 0.01754401 | K13: 1.8425459
A14: 021 | B14: 37346 | C14: -0.02622608 | D14: 0.0060969934 | E14: -0.0027802238 | F14: 0.010964823 | G14: -0.76102295 | H14: -0.10533267 | I14: 0.04046553 | J14: 0.084662852 | K14: 3.3692314
A15: 022 | B15: 37437 | C15: 0.036368636 | D15: 0.033474102 | E15: -0.01860815 | F15: 0.040853518 | G15: 136.15934 | H15: 0.034664389 | I15: 0.056535939 | J15: 0.10651387 | K15: 4.3446296
A16: 023 | B16: 37529 | C16: 0.027976816 | D16: 0.011859253 | E16: 0.049431331 | F16: 0.0036862307 | G16: 1.3022546 | H16: 0.049917225 | I16: 0.049356051 | J16: 0.010177188 | K16: 3.4716421
A17: 024 | B17: 37621 | C17: 0.01253326 | D17: -0.018626536 | E17: -0.015509685 | F17: -0.017693341 | G17: -0.75578781 | H17: -0.0050157728 | I17: 0.0069513695 | J17: -0.22869353 | K17: 2.4451578
... A85: 194 | B85: 43830 | C85: -0.022543674 | D85: -0.0074105785 | E85: 0.028018082 | F85: -0.015155554 | G85: -0.44635392 | H85: -0.065926735 | I85: -0.14793567 | J85: -0.10175143 | K85: 2.6073257
A86: 201 | B86: 43921 | C86: -0.048722731 | D86: -0.029057321 | E86: 0.13430904 | F86: -0.056732311 | G86: -0.98890473 | H86: -0.083393377 | I86: 0.13026239 | J86: -0.073409822
A87: 202 | B87: 44012

Sheet Bloomberg_m
C1: BALTIC | D1: WCIFREIGHT | E1: SHANGHAI | F1: RUSSELL | L1: WTI
C2: BDI Baltic Exchange Dry Index | D2: WCI Composite Container Freight Benchmark Rate per 40 Foot Box | E2: Shanghai Shipping Exchange Shanghai (Export) Containerized Freight Index | F2: Russell 3000 Shipping Index | G2: Shanghai Shipping Exchange China (Export) Containerized Freight Index | H2: Dow Jones Global Shipping USD Index | I2: Philadelphia Stock Exchange Marine Shipping Index | J2: RGUSPSSH Index | K2: Oslo Shipping Index | L2: WTI Price
A3: 0 | B3: Security | C3: BDIY Index | D3: WCIDCOMP Index | E3: SHSPSCFI Index | F3: RGUSPSH Index | G3: SHSPCCFI Index | H3: DJGSH Index | I3: PHLXSHX Index | J3: RGUSPSSH Index | K3: OSLSHX Index | L3: USCRWTIC Index
A4: 2 | B4: Fields | C4: px_last | D4: =C4 -> px_last | E4: =D4 -> px_last | F4: =E4 -> px_last | G4: =F4 -> px_last | H4: =G4 -> px_last | I4: =H4 -> px_last | J4: =I4 -> px_last | K4: =J4 -> px_last | L4: =K4 -> px_last
A5: 3 | B5: Start Date | C5: 36523 | D5: =$C$5 -> 36523 | E5: =$C$5 -> 36523 | F5: =$C$5 -> 36523 | G5: =$C$5 -> 36523 | H5: =$C$5 -> 36523 | I5: =$C$5 -> 36523 | J5: =$C$5 -> 36523 | K5: =$C$5 -> 36523 | L5: =$C$5 -> 36523
A6: 4 | B6: End Date
A7: D,W,M,Q,S,Y | B7: Per= | C7: m | D7: =$C$7 -> m | E7: =$C$7 -> m | F7: =$C$7 -> m | G7: =$C$7 -> m | H7: =$C$7 -> m | I7: =$C$7 -> m | J7: =$C$7 -> m | K7: =$C$7 -> m | L7: =$C$7 -> m
A8: N,C,T,W,A | B8: Days= | C8: N | D8: =$C$8 -> N | E8: =$C$8 -> N | F8: =$C$8 -> N | G8: =$C$8 -> N | H8: =$C$8 -> N | I8: =$C$8 -> N | J8: =$C$8 -> N | K8: =$C$8 -> N | L8: =$C$8 -> N
A9: C,P,E,B | B9: Fill= | C9: B | D9: =$C$9 -> B | E9: =$C$9 -> B | F9: =$C$9 -> B | G9: =$C$9 -> B | H9: =$C$9 -> B | I9: =$C$9 -> B | J9: =$C$9 -> B | K9: =$C$9 -> B | L9: =$C$9 -> B
A10: TRUE,FALSE | B10: Dts= | C10: TRUE | D10: FALSE | E10: FALSE | F10: FALSE | G10: FALSE | H10: FALSE | I10: FALSE | J10: FALSE | K10: FALSE | L10: FALSE
A11: P,Y | B11: QtTyp=
A12: C,A,R,D | B12: Sort=
A13: USD | B13: Curr=
A14: G=Avg C=Last | B14: Quote= | C14: G | D14: =$C$14 -> G | E14: =$C$14 -> G | F14: =$C$14 -> G | G14: =$C$14 -> G | H14: =$C$14 -> G | I14: =$C$14 -> G | J14: =$C$14 -> G | K14: =$C$14 -> G | L14: =$C$14 -> G
A15: Units | C15: =_xll.BDP(C3,"indx_units") -> #N/A Connection | D15: =_xll.BDP(D3,"indx_units") -> #N/A Connection | E15: =_xll.BDP(E3,"indx_units") -> #N/A Connection | F15: =_xll.BDP(F3,"indx_units") -> #N/A Connection | G15: =_xll.BDP(G3,"indx_units") -> #N/A Connection | H15: =_xll.BDP(H3,"indx_units") -> #N/A Connection | I15: =_xll.BDP(I3,"indx_units") -> #N/A Connection | J15: =_xll.BDP(J3,"indx_units") -> #N/A Connection | ... L15: =_xll.BDP(L3,"indx_units") -> #N/A Connection
A16: Bloomberg Description | C16: =_xll.BDP(C3,"long_comp_name") -> #N/A Connection | D16: =_xll.BDP(D3,"long_comp_name") -> #N/A Connection | E16: =_xll.BDP(E3,"long_comp_name") -> #N/A Connection | F16: =_xll.BDP(F3,"long_comp_name") -> #N/A Connection | G16: =_xll.BDP(G3,"long_comp_name") -> #N/A Connection | H16: =_xll.BDP(H3,"long_comp_name") -> #N/A Connection | I16: =_xll.BDP(I3,"long_comp_name") -> #N/A Connection | J16: =_xll.BDP(J3,"long_comp_name") -> #N/A Connection | ... L16: =_xll.BDP(L3,"long_comp_name") -> #N/A Connection
B17: =_xll.BDH(C3,C4,C5,C6,$B$7&C7,$B$8&C8,$B$9&C9,$B$10&C10,$B$11&C11,$B$12&C12,$B$13&C13,$B$14&C14,"cols=2;rows=247") -> 36525 | C17: 1343 | D17: =_xll.BDH(D3,D4,D5,D6,$B$7&D7,$B$8&D8,$B$9&D9,$B$10&D10,$B$11&D11,$B$12&D12,$B$13&D13,$B$14&D14,"cols=1;rows=247") | E17: =_xll.BDH(E3,E4,E5,E6,$B$7&E7,$B$8&E8,$B$9&E9,$B$10&E10,$B$11&E11,$B$12&E12,$B$13&E13,$B$14&E14,"cols=1;rows=247") | F17: =_xll.BDH(F3,F4,F5,F6,$B$7&F7,$B$8&F8,$B$9&F9,$B$10&F10,$B$11&F11,$B$12&F12,$B$13&F13,$B$14&F14,"cols=1;rows=247") | G17: =_xll.BDH(G3,G4,G5,G6,$B$7&G7,$B$8&G8,$B$9&G9,$B$10&G10,$B$11&G11,$B$12&G12,$B$13&G13,$B$14&G14,"cols=1;rows=247") | H17: =_xll.BDH(H3,H4,H5,H6,$B$7&H7,$B$8&H8,$B$9&H9,$B$10&H10,$B$11&H11,$B$12&H12,$B$13&H13,$B$14&H14,"cols=1;rows=247") | I17: =_xll.BDH(I3,I4,I5,I6,$B$7&I7,$B$8&I8,$B$9&I9,$B$10&I10,$B$11&I11,$B$12&I12,$B$13&I13,$B$14&I14,"cols=1;rows=247") | J17: =_xll.BDH(J3,J4,J5,J6,$B$7&J7,$B$8&J8,$B$9&J9,$B$10&J10,$B$11&J11,$B$12&J12,$B$13&J13,$B$14&J14,"cols=1;rows=247") | K17: =_xll.BDH(K3,K4,K5,K6,$B$7&K7,$B$8&K8,$B$9&K9,$B$10&K10,$B$11&K11,$B$12&K12,$B$13&K13,$B$14&K14,"cols=1;rows=247") | L17: =_xll.BDH(L3,L4,L5,L6,$B$7&L7,$B$8&L8,$B$9&L9,$B$10&L10,$B$11&L11,$B$12&L12,$B$13&L13,$B$14&L14,"cols=1;rows=247") -> 26.08
B18: 36556 | C18: 1371 | L18: 27.27
B19: 36585 | C19: 1393 | L19: 29.35
B20: 36616 | C20: 1621 | L20: 29.89
B21: 36644 | C21: 1667 | L21: 25.78
B22: 36677 | C22: 1602 | L22: 28.78
B23: 36707 | C23: 1589 | L23: 31.86
B24: 36738 | C24: 1618 | L24: 29.7
B25: 36769 | C25: 1639 | L25: 31.31
B26: 36798 | C26: 1712 | L26: 33.89
B27: 36830 | C27: 1734 | L27: 33.05
B28: 36860 | C28: 1722 | L28: 34.37
B29: 36889 | C29: 1609 | L29: 28.4
... B88: 38686 | C88: 2916 | L88: 58.28
B89: 38716 | C89: 2600 | H89: 1000 | L89: 59.41
B90: 38748 | C90: 2262 | H90: 1020.48 | L90: 65.48
B91: 38776 | C91: 2444 | H91: 1025.57 | L91: 61.62
B92: 38807 | C92: 2599 | H92: 1003.46 | L92: 62.89
B93: 38835 | C93: 2465 | H93: 1007.59 | L93: 69.54
B94: 38868 | C94: 2442 | H94: 984.88 | L94: 70.93
B95: 38898 | C95: 2718 | H95: 940.01 | L95: 70.93
B96: 38929 | C96: 3050 | H96: 1019.9 | L96: 74.4
B97: 38960 | C97: 3687 | H97: 1088.73 | L97: 73.04
B98: 38989 | C98: 4039 | H98: 1066.98 | L98: 63.82
B99: 39021 | C99: 4028 | H99: 1076.18 | L99: 58.85
B100: 39051 | C100: 4190 | H100: 1120.74 | L100: 59.13
... B103: 39141 | C103: 4398 | H103: 1314.07 | L103: 59.25
B104: 39171 | C104: 5123 | H104: 1338.32 | I104: 256.58 | L104: 60.6
B105: 39202 | C105: 5754 | H105: 1449.97 | I105: 276.55 | L105: 63.94
B106: 39233 | C106: 6402 | H106: 1589.63 | I106: 300.34 | L106: 63.45
B107: 39262 | C107: 5772 | H107: 1675.17 | I107: 304.43 | L107: 67.49
B108: 39294 | C108: 6572 | H108: 1882.93 | I108: 338.79 | L108: 74.14
B109: 39325 | C109: 7195 | H109: 1810.69 | I109: 323.14 | L109: 72.38
B110: 39353 | C110: 8574 | H110: 1993.3 | I110: 356.49 | L110: 79.91
B111: 39386 | C111: 10426 | H111: 2208.19 | I111: 410.51 | L111: 85.9
B112: 39416 | C112: 10543 | H112: 1995.53 | I112: 377.85 | L112: 94.76
B113: 39447 | C113: 9854 | H113: 1872.86 | I113: 386.17 | L113: 91.36
B114: 39478 | C114: 7170 | H114: 1612.47 | I114: 341.27 | L114: 92.98
B115: 39507 | C115: 6874 | H115: 1691.39 | I115: 370.89 | L115: 95.38
... B130: 39962 | C130: 2540 | H130: 836.2 | I130: 167.14 | L130: 59.12
B131: 39994 | C131: 3823 | F131: 485.11 | H131: 877.27 | I131: 166.9 | J131: 457.45 | L131: 69.62
B132: 40025 | C132: 3362 | F132: 466.9 | H132: 824.43 | I132: 154.12 | J132: 437.94 | L132: 64.12
B133: 40056 | C133: 2685 | F133: 491.41 | H133: 866.55 | I133: 162.2 | J133: 454.16 | L133: 71.06
B134: 40086 | C134: 2351 | F134: 505.77 | H134: 876.4 | I134: 171.48 | J134: 451.96 | L134: 69.44
B135: 40116 | C135: 2746 | F135: 513.73 | H135: 907.71 | I135: 174.69 | J135: 461.63 | L135: 75.77
B136: 40147 | C136: 3941 | F136: 504.19 | H136: 900.7 | I136: 170.89 | J136: 453.1 | L136: 78
B137: 40178 | C137: 3572 | F137: 523.78 | H137: 906.33 | I137: 174.9 | J137: 454.16 | L137: 74.49
B138: 40207 | C138: 3168 | F138: 547.76 | H138: 1001.01 | I138: 184.58 | J138: 471.03 | L138: 78.36
B139: 40235 | C139: 2678 | F139: 504.92 | H139: 946.3 | I139: 173.46 | J139: 432.88 | L139: 76.41
B140: 40268 | C140: 3207 | F140: 546.26 | H140: 1018.57 | I140: 186.83 | J140: 476.32 | L140: 81.25
B141: 40298 | C141: 3043 | F141: 585.88 | H141: 1074.69 | I141: 197.87 | J141: 504.03 | L141: 84.48
B142: 40329 | C142: 3838 | F142: 551.27 | H142: 988.99 | I142: 182.9 | J142: 470.82 | L142: 73.73
B143: 40359 | C143: 3088 | F143: 525.31 | H143: 978.12 | I143: 177.37 | J143: 440.5 | K143: 84.63 | L143: 75.35
B144: 40389 | C144: 1910 | F144: 517.18 | H144: 975.65 | I144: 175.11 | J144: 432.13 | K144: 86.74 | L144: 76.35
B145: 40421 | C145: 2432 | F145: 512.34 | H145: 994.75 | I145: 176.06 | J145: 429.07 | K145: 86.78 | L145: 76.6
B146: 40451 | C146: 2719 | F146: 521.58 | H146: 995.7 | I146: 176.7 | J146: 427.56 | K146: 88.19 | L146: 75.29
B147: 40480 | C147: 2693 | F147: 543.81 | H147: 1021.71 | I147: 183.62 | J147: 437.65 | K147: 93.32 | L147: 81.9
B148: 40512 | C148: 2321 | E148: 1202.68 | F148: 572.93 | G148: 1103.22 | H148: 1063.74 | I148: 190.62 | J148: 450.75 | K148: 106.04 | L148: 84.24
B149: 40543 | C149: 2031 | E149: 1103.66 | F149: 575.19 | G149: 1064.43 | H149: 1068.66 | I149: 188.06 | J149: 440.07 | K149: 113.85 | L149: 89.15
B150: 40574 | C150: 1401 | E150: 1112.82 | F150: 591.17 | G150: 1060.61 | H150: 1093.04 | I150: 186 | J150: 438.67 | K150: 121.71 | L150: 89.41
B151: 40602 | C151: 1181 | E151: 1062.77 | F151: 604.8 | G151: 1053.24 | H151: 1090.66 | I151: 185.21 | J151: 429.6 | K151: 122.21 | L151: 89.53
B152: 40633 | C152: 1493 | E152: 999.1 | F152: 603.69 | G152: 1029.75 | H152: 1060.12 | I152: 182.74 | J152: 420.82 | K152: 117.82 | L152: 102.92
B153: 40662 | C153: 1343 | E153: 1023.63 | F153: 606.07 | G153: 1008.08 | H153: 1050.14 | I153: 182.63 | J153: 397.61 | K153: 117.68 | L153: 109.96
B154: 40694 | C154: 1352 | E154: 1072.48 | F154: 578.65 | G154: 1011.93 | H154: 1015.74 | I154: 169.35 | J154: 373.84 | K154: 116.09 | L154: 101.28
B155: 40724 | C155: 1433 | D155: 1599.44 | E155: 1039.41 | F155: 542.88 | G155: 996.88 | H155: 954.34 | I155: 155.2 | J155: 350.78 | K155: 108.78 | L155: 96.25
B156: 40753 | C156: 1366 | D156: 1611.89 | E156: 1020.14 | F156: 539.58 | G156: 982.44 | H156: 951.17 | I156: 149.53 | J156: 340.57 | K156: 115.22 | L156: 97.31
B157: 40786 | C157: 1387 | D157: 1703.82 | E157: 1045.19 | F157: 450.62 | G157: 987.06 | H157: 772.53 | I157: 113.91 | J157: 263.78 | K157: 93.35 | L157: 86.32
B158: 40816 | C158: 1840 | D158: 1653.65 | E158: 1016.76 | F158: 440.16 | G158: 991.24 | H158: 715.75 | I158: 107.78 | J158: 246.98 | K158: 91.64 | L158: 85.58
B159: 40847 | C159: 2072 | D159: 1487.56 | E159: 939.77 | F159: 429.75 | G159: 956.77 | H159: 685.44 | I159: 103.22 | J159: 234.68 | K159: 94.27 | L159: 86.41
B160: 40877 | C160: 1835 | D160: 1365.08 | E160: 895.51 | F160: 443.84 | G160: 936.33 | H160: 650.46 | I160: 98.93 | J160: 225.99 | K160: 100.34 | L160: 97.12
B161: 40907 | C161: 1869 | D161: 1215.69 | E161: 876.34 | F161: 435.62 | G161: 902.64 | H161: 646.94 | I161: 89.09 | J161: 199.25 | K161: 105.24 | L161: 98.56
B162: 40939 | C162: 1039 | D162: 1495.43 | E162: 979.64 | F162: 464.71 | G162: 913.62 | H162: 694.4 | I162: 97.04 | J162: 216.48 | K162: 110.49 | L162: 100.29
B163: 40968 | C163: 703 | D163: 1460.67 | E163: 965.59 | F163: 493.56 | G163: 943.53 | H163: 780.86 | I163: 108.88 | J163: 234.34 | K163: 114.43 | L163: 102.21
B164: 40998 | C164: 859 | D164: 2051.34 | E164: 1227.09 | F164: 500.39 | G164: 1040.06 | H164: 802.94 | I164: 114.46 | J164: 237.38 | K164: 111.14 | L164: 106.15
B165: 41029 | C165: 1021 | D165: 2411.67 | E165: 1426.54 | F165: 500.74 | G165: 1213.09 | H165: 794.45 | I165: 113.28 | J165: 233.21 | K165: 106.08 | L165: 103.28
B166: 41060 | C166: 1101 | D166: 2609.48 | E166: 1450.27 | F166: 462.12 | G166: 1313.3 | H166: 719.76 | I166: 98.96 | J166: 203.1 | K166: 103.18 | L166: 94.68
... B197: 42004 | C197: 910 | D197: 1841.72 | E197: 1060.08 | F197: 495.23 | G197: 1038.49 | H197: 782.18 | I197: 76.34 | J197: 138.26 | K197: 185.21 | L197: 59.26
B198: 42034 | C198: 725 | D198: 2032.7 | E198: 1051.76 | F198: 492.94 | G198: 1060.57 | H198: 785.7 | J198: 142.03 | K198: 197.81 | L198: 47.27
B199: 42062 | C199: 539 | D199: 2101.27 | E199: 1066.21 | F199: 507.89 | G199: 1073.53 | H199: 802.48 | J199: 141.77 | K199: 191.37 | L199: 50.61
B200: 42094 | C200: 576 | D200: 1752.16 | E200: 868.47 | F200: 527.47 | G200: 1044.21 | H200: 811.25 | J200: 144.04 | K200: 203.02 | L200: 47.78
B201: 42124 | C201: 591 | D201: 1404.28 | E201: 748.39 | F201: 562.83 | G201: 948.25 | H201: 843 | J201: 147.38 | K201: 209.46 | L201: 54.44
B202: 42153 | C202: 597 | D202: 1438.01 | E202: 731.35 | F202: 549.07 | G202: 886.39 | H202: 838.56 | J202: 147.01 | K202: 209.64 | L202: 59.27
B203: 42185 | C203: 699 | D203: 1109.27 | E203: 600.52 | F203: 535.26 | G203: 837.64 | H203: 807.35 | J203: 149.48 | K203: 217.24 | L203: 59.8
B204: 42216 | C204: 975 | D204: 1313.86 | E204: 675.17 | F204: 523.44 | G204: 819.18 | H204: 763.59 | J204: 148.99 | K204: 226.96 | L204: 50.9
...

Sheet data
B1: GDP | C1: GDPGOVT | D1: GDPPRIV | E1: GDPGFCF | F1: GDPX | G1: GDPM | H1: GPMGDP | I1: BALTIC | J1: WCIFREIGHT | K1: SHANGHAI | L1: WTI | M1: RS | N1: LTY | O1: REER | P1: CPI | Q1: CORE | R1: IPALL | S1: IPMINE | T1: IPUTIL | U1: IPCONST | V1: IPMANU | W1: UNR | X1: WAGE | Y1: LEAD | Z1: SALES_R | AA1: WHOLESALE | AB1: EXPORTS | AC1: IMPORTS | AD1: COINCI | AE1: CCI | AF1: PCI | AG1: PMI | AH1: PMIManu | AI1: PMINO | AJ1: PMIEMP | AK1: PMIDELI | AL1: PMIStocks | AM1: PMIIP | AN1: PMIPURCH | AO1: PMISTOCKS | AP1: PMINEO | AQ1: PMIMPRI | AR1: PMIBACK | AS1: STOCKS | AT1: PCONS | AU1: EAI | AV1: GFCF | AW1: TOURISM | AX1: OILPROD | AY1: OIL_X | AZ1: IMEFBC | BA1: NEWS
A2: 36556 | B2: =IF(ISNUMBER(INDEX(Haver_Q!$B$1:$BD$1000,MATCH(data!$A2,Haver_Q!$B$1:$B$1000,0),MATCH(data!B$1,Haver_Q!$B$1:$BD$1,0))),100*INDEX(Haver_Q!$B$1:$BD$1000,MATCH(data!$A2,Haver_Q!$B$1:$B$1000,0),MATCH(data!B$1,Haver_Q!$B$1:$BD$1,0)),"na") -> na | C2: =IF(ISNUMBER(INDEX(Haver_Q!$B$1:$BD$1000,MATCH(data!$A2,Haver_Q!$B$1:$B$1000,0),MATCH(data!C$1,Haver_Q!$B$1:$BD$1,0))),100*INDEX(Haver_Q!$B$1:$BD$1000,MATCH(data!$A2,Haver_Q!$B$1:$B$1000,0),MATCH(data!C$1,Haver_Q!$B$1:$BD$1,0)),"na") -> na | D2: =IF(ISNUMBER(INDEX(Haver_Q!$B$1:$BD$1000,MATCH(data!$A2,Haver_Q!$B$1:$B$1000,0),MATCH(data!D$1,Haver_Q!$B$1:$BD$1,0))),100*INDEX(Haver_Q!$B$1:$BD$1000,MATCH(data!$A2,Haver_Q!$B$1:$B$1000,0),MATCH(data!D$1,Haver_Q!$B$1:$BD$1,0)),"na") -> na | E2: =IF(ISNUMBER(INDEX(Haver_Q!$B$1:$BD$1000,MATCH(data!$A2,Haver_Q!$B$1:$B$1000,0),MATCH(data!E$1,Haver_Q!$B$1:$BD$1,0))),100*INDEX(Haver_Q!$B$1:$BD$1000,MATCH(data!$A2,Haver_Q!$B$1:$B$1000,0),MATCH(data!E$1,Haver_Q!$B$1:$BD$1,0)),"na") -> na | F2: =IF(ISNUMBER(INDEX(Haver_Q!$B$1:$BD$1000,MATCH(data!$A2,Haver_Q!$B$1:$B$1000,0),MATCH(data!F$1,Haver_Q!$B$1:$BD$1,0))),100*INDEX(Haver_Q!$B$1:$BD$1000,MATCH(data!$A2,Haver_Q!$B$1:$B$1000,0),MATCH(data!F$1,Haver_Q!$B$1:$BD$1,0)),"na") -> na | G2: =IF(ISNUMBER(INDEX(Haver_Q!$B$1:$BD$1000,MATCH(data!$A2,Haver_Q!$B$1:$B$1000,0),MATCH(data!G$1,Haver_Q!$B$1:$BD$1,0))),100*INDEX(Haver_Q!$B$1:$BD$1000,MATCH(data!$A2,Haver_Q!$B$1:$B$1000,0),MATCH(data!G$1,Haver_Q!$B$1:$BD$1,0)),"na") -> na | H2: =IF(ISNUMBER(INDEX(Haver_Q!$B$1:$BD$1000,MATCH(data!$A2,Haver_Q!$B$1:$B$1000,0),MATCH(data!H$1,Haver_Q!$B$1:$BD$1,0))),100*INDEX(Haver_Q!$B$1:$BD$1000,MATCH(data!$A2,Haver_Q!$B$1:$B$1000,0),MATCH(data!H$1,Haver_Q!$B$1:$BD$1,0)),"na") -> na | I2: =IF(ISNUMBER(Bloomberg_m!C18),Bloomberg_m!C18,"na") -> 1371 | J2: =IF(ISNUMBER(Bloomberg_m!D18),Bloomberg_m!D18,"na") -> na | K2: =IF(ISNUMBER(Bloomberg_m!E18),Bloomberg_m!E18,"na") -> na | L2: =IF(ISNUMBER(Bloomberg_m!L18),Bloomberg_m!L18,"na") -> 27.27 | M2: =IF(ISNUMBER(INDEX(Haver_M!$B$1:$ZN$1000,MATCH(data!$A2,Haver_M!$B$1:$B$1000,0),MATCH(data!M$1,Haver_M!$B$1:$ZN$1,0))),INDEX(Haver_M!$B$1:$ZN$1000,MATCH(data!$A2,Haver_M!$B$1:$B$1000,0),MATCH(data!M$1,Haver_M!$B$1:$ZN$1,0)),"na") -> na | N2: =IF(ISNUMBER(INDEX(Haver_M!$B$1:$ZN$1000,MATCH(data!$A2,Haver_M!$B$1:$B$1000,0),MATCH(data!N$1,Haver_M!$B$1:$ZN$1,0))),INDEX(Haver_M!$B$1:$ZN$1000,MATCH(data!$A2,Haver_M!$B$1:$B$1000,0),MATCH(data!N$1,Haver_M!$B$1:$ZN$1,0)),"na") -> na | O2: =IF(ISNUMBER(INDEX(Haver_M!$B$1:$ZN$1000,MATCH(data!$A2,Haver_M!$B$1:$B$1000,0),MATCH(data!O$1,Haver_M!$B$1:$ZN$1,0))),INDEX(Haver_M!$B$1:$ZN$1000,MATCH(data!$A2,Haver_M!$B$1:$B$1000,0),MATCH(data!O$1,Haver_M!$B$1:$ZN$1,0)),"na") -> 113.55455 | P2: =IF(ISNUMBER(INDEX(Haver_M!$B$1:$ZN$1000,MATCH(data!$A2,Haver_M!$B$1:$B$1000,0),MATCH(data!P$1,Haver_M!$B$1:$ZN$1,0))),INDEX(Haver_M!$B$1:$ZN$1000,MATCH(data!$A2,Haver_M!$B$1:$B$1000,0),MATCH(data!P$1,Haver_M!$B$1:$ZN$1,0)),"na") -> 44.6533 | Q2: =IF(ISNUMBER(INDEX(Haver_M!$B$1:$ZN$1000,MATCH(data!$A2,Haver_M!$B$1:$B$1000,0),MATCH(data!Q$1,Haver_M!$B$1:$ZN$1,0))),INDEX(Haver_M!$B$1:$ZN$1000,MATCH(data!$A2,Haver_M!$B$1:$B$1000,0),MATCH(data!Q$1,Haver_M!$B$1:$ZN$1,0)),"na") -> 48.932 | R2: =IF(ISNUMBER(INDEX(Haver_M!$B$1:$ZN$1000,MATCH(data!$A2,Haver_M!$B$1:$B$1000,0),MATCH(data!R$1,Haver_M!$B$1:$ZN$1,0))),INDEX(Haver_M!$B$1:$ZN$1000,MATCH(data!$A2,Haver_M!$B$1:$B$1000,0),MATCH(data!R$1,Haver_M!$B$1:$ZN$1,0)),"na") -> 89.3466 | S2: =IF(ISNUMBER(INDEX(Haver_M!$B$1:$ZN$1000,MATCH(data!$A2,Haver_M!$B$1:$B$1000,0),MATCH(data!S$1,Haver_M!$B$1:$ZN$1,0))),INDEX(Haver_M!$B$1:$ZN$1000,MATCH(data!$A2,Haver_M!$B$1:$B$1000,0),MATCH(data!S$1,Haver_M!$B$1:$ZN$1,0)),"na") -> 101.1315 | T2: =IF(ISNUMBER(INDEX(Haver_M!$B$1:$ZN$1000,MATCH(data!$A2,Haver_M!$B$1:$B$1000,0),MATCH(data!T$1,Haver_M!$B$1:$ZN$1,0))),INDEX(Haver_M!$B$1:$ZN$1000,MATCH(data!$A2,Haver_M!$B$1:$B$1000,0),MATCH(data!T$1,Haver_M!$B$1:$ZN$1,0)),"na") -> 53.8108 | ... BA2: =IF(ISNUMBER(INDEX(Haver_M!$B$1:$ZN$1000,MATCH(data!$A2,Haver_M!$B$1:$B$1000,0),MATCH(data!BA$1,Haver_M!$B$1:$ZN$1,0))),INDEX(Haver_M!$B$1:$ZN$1000,MATCH(data!$A2,Haver_M!$B$1:$B$1000,0),MATCH(data!BA$1,Haver_M!$B$1:$ZN$1,0)),"na") -> 129.33691 | BB2: =IF(ISNUMBER(INDEX(Haver_M!$B$1:$ZN$1000,MATCH(data!$A2,Haver_M!$B$1:$B$1000,0),MATCH(data!BB$1,Haver_M!$B$1:$ZN$1,0))),INDEX(Haver_M!$B$1:$ZN$1000,MATCH(data!$A2,Haver_M!$B$1:$B$1000,0),MATCH(data!BB$1,Haver_M!$B$1:$ZN$1,0)),"")
A3: 36585 | B3: =IF(ISNUMBER(INDEX(Haver_Q!$B$1:$BD$1000,MATCH(data!$A3,Haver_Q!$B$1:$B$1000,0),MATCH(data!B$1,Haver_Q!$B$1:$BD$1,0))),100*INDEX(Haver_Q!$B$1:$BD$1000,MATCH(data!$A3,Haver_Q!$B$1:$B$1000,0),MATCH(data!B$1,Haver_Q!$B$1:$BD$1,0)),"na") -> na | C3: =IF(ISNUMBER(INDEX(Haver_Q!$B$1:$BD$1000,MATCH(data!$A3,Haver_Q!$B$1:$B$1000,0),MATCH(data!C$1,Haver_Q!$B$1:$BD$1,0))),100*INDEX(Haver_Q!$B$1:$BD$1000,MATCH(data!$A3,Haver_Q!$B$1:$B$1000,0),MATCH(data!C$1,Haver_Q!$B$1:$BD$1,0)),"na") -> na | D3: =IF(ISNUMBER(INDEX(Haver_Q!$B$1:$BD$1000,MATCH(data!$A3,Haver_Q!$B$1:$B$1000,0),MATCH(data!D$1,Haver_Q!$B$1:$BD$1,0))),100*INDEX(Haver_Q!$B$1:$BD$1000,MATCH(data!$A3,Haver_Q!$B$1:$B$1000,0),MATCH(data!D$1,Haver_Q!$B$1:$BD$1,0)),"na") -> na | E3: =IF(ISNUMBER(INDEX(Haver_Q!$B$1:$BD$1000,MATCH(data!$A3,Haver_Q!$B$1:$B$1000,0),MATCH(data!E$1,Haver_Q!$B$1:$BD$1,0))),100*INDEX(Haver_Q!$B$1:$BD$1000,MATCH(data!$A3,Haver_Q!$B$1:$B$1000,0),MATCH(data!E$1,Haver_Q!$B$1:$BD$1,0)),"na") -> na | F3: =IF(ISNUMBER(INDEX(Haver_Q!$B$1:$BD$1000,MATCH(data!$A3,Haver_Q!$B$1:$B$1000,0),MATCH(data!F$1,Haver_Q!$B$1:$BD$1,0))),100*INDEX(Haver_Q!$B$1:$BD$1000,MATCH(data!$A3,Haver_Q!$B$1:$B$1000,0),MATCH(data!F$1,Haver_Q!$B$1:$BD$1,0)),"na") -> na | G3: =IF(ISNUMBER(INDEX(Haver_Q!$B$1:$BD$1000,MATCH(data!$A3,Haver_Q!$B$1:$B$1000,0),MATCH(data!G$1,Haver_Q!$B$1:$BD$1,0))),100*INDEX(Haver_Q!$B$1:$BD$1000,MATCH(data!$A3,Haver_Q!$B$1:$B$1000,0),MATCH(data!G$1,Haver_Q!$B$1:$BD$1,0)),"na") -> na | H3: =IF(ISNUMBER(INDEX(Haver_Q!$B$1:$BD$1000,MATCH(data!$A3,Haver_Q!$B$1:$B$1000,0),MATCH(data!H$1,Haver_Q!$B$1:$BD$1,0))),100*INDEX(Haver_Q!$B$1:$BD$1000,MATCH(data!$A3,Haver_Q!$B$1:$B$1000,0),MATCH(data!H$1,Haver_Q!$B$1:$BD$1,0)),"na") -> na | I3: =IF(ISNUMBER(Bloomberg_m!C19),Bloomberg_m!C19,"na") -> 1393 | J3: =IF(ISNUMBER(Bloomberg_m!D19),Bloomberg_m!D19,"na") -> na | K3: =IF(ISNUMBER(Bloomberg_m!E19),Bloomberg_m!E19,"na") -> na | L3: =IF(ISNUMBER(Bloomberg_m!L19),Bloomberg_m!L19,"na") -> 29.35 | M3: =IF(ISNUMBER(INDEX(Haver_M!$B$1:$ZN$1000,MATCH(data!$A3,Haver_M!$B$1:$B$1000,0),MATCH(data!M$1,Haver_M!$B$1:$ZN$1,0))),INDEX(Haver_M!$B$1:$ZN$1000,MATCH(data!$A3,Haver_M!$B$1:$B$1000,0),MATCH(data!M$1,Haver_M!$B$1:$ZN$1,0)),"na") -> na | N3: =IF(ISNUMBER(INDEX(Haver_M!$B$1:$ZN$1000,MATCH(data!$A3,Haver_M!$B$1:$B$1000,0),MATCH(data!N$1,Haver_M!$B$1:$ZN$1,0))),INDEX(Haver_M!$B$1:$ZN$1000,MATCH(data!$A3,Haver_M!$B$1:$B$1000,0),MATCH(data!N$1,Haver_M!$B$1:$ZN$1,0)),"na") -> na | O3: =IF(ISNUMBER(INDEX(Haver_M!$B$1:$ZN$1000,MATCH(data!$A3,Haver_M!$B$1:$B$1000,0),MATCH(data!O$1,Haver_M!$B$1:$ZN$1,0))),INDEX(Haver_M!$B$1:$ZN$1000,MATCH(data!$A3,Haver_M!$B$1:$B$1000,0),MATCH(data!O$1,Haver_M!$B$1:$ZN$1,0)),"na") -> 115.46699 | P3: =IF(ISNUMBER(INDEX(Haver_M!$B$1:$ZN$1000,MATCH(data!$A3,Haver_M!$B$1:$B$1000,0),MATCH(data!P$1,Haver_M!$B$1:$ZN$1,0))),INDEX(Haver_M!$B$1:$ZN$1000,MATCH(data!$A3,Haver_M!$B$1:$B$1000,0),MATCH(data!P$1,Haver_M!$B$1:$ZN$1,0)),"na") -> 44.999 | Q3: =IF(ISNUMBER(INDEX(Haver_M!$B$1:$ZN$1000,MATCH(data!$A3,Haver_M!$B$1:$B$1000,0),MATCH(data!Q$1,Haver_M!$B$1:$ZN$1,0))),INDEX(Haver_M!$B$1:$ZN$1000,MATCH(data!$A3,Haver_M!$B$1:$B$1000,0),MATCH(data!Q$1,Haver_M!$B$1:$ZN$1,0)),"na") -> 49.3 | R3: =IF(ISNUMBER(INDEX(Haver_M!$B$1:$ZN$1000,MATCH(data!$A3,Haver_M!$B$1:$B$1000,0),MATCH(data!R$1,Haver_M!$B$1:$ZN$1,0))),INDEX(Haver_M!$B$1:$ZN$1000,MATCH(data!$A3,Haver_M!$B$1:$B$1000,0),MATCH(data!R$1,Haver_M!$B$1:$ZN$1,0)),"na") -> 89.9714 | S3: =IF(ISNUMBER(INDEX(Haver_M!$B$1:$ZN$1000,MATCH(data!$A3,Haver_M!$B$1:$B$1000,0),MATCH(data!S$1,Haver_M!$B$1:$ZN$1,0))),INDEX(Haver_M!$B$1:$ZN$1000,MATCH(data!$A3,Haver_M!$B$1:$B$1000,0),MATCH(data!S$1,Haver_M!$B$1:$ZN$1,0)),"na") -> 99.6387 | T3: =IF(ISNUMBER(INDEX(Haver_M!$B$1:$ZN$1000,MATCH(data!$A3,Haver_M!$B$1:$B$1000,0),MATCH(data!T$1,Haver_M!$B$1:$ZN$1,0))),INDEX(Haver_M!$B$1:$ZN$1000,MATCH(data!$A3,Haver_M!$B$1:$B$1000,0),MATCH(data!T$1,Haver_M!$B$1:$ZN$1,0)),"na") -> 54.6009 | ... BA3: =IF(ISNUMBER(INDEX(Haver_M!$B$1:$ZN$1000,MATCH(data!$A3,Haver_M!$B$1:$B$1000,0),MATCH(data!BA$1,Haver_M!$B$1:$ZN$1,0))),INDEX(Haver_M!$B$1:$ZN$1000,MATCH(data!$A3,Haver_M!$B$1:$B$1000,0),MATCH(data!BA$1,Haver_M!$B$1:$ZN$1,0)),"na") -> 182.08916 | BB3: =IF(ISNUMBER(INDEX(Haver_M!$B$1:$ZN$1000,MATCH(data!$A3,Haver_M!$B$1:$B$1000,0),MATCH(data!BB$1,Haver_M!$B$1:$ZN$1,0))),INDEX(Haver_M!$B$1:$ZN$1000,MATCH(data!$A3,Haver_M!$B$1:$B$1000,0),MATCH(data!BB$1,Haver_M!$B$1:$ZN$1,0)),"")
A4: 36616 | B4: =IF(ISNUMBER(INDEX(Haver_Q!$B$1:$BD$1000,MATCH(data!$A4,Haver_Q!$B$1:$B$1000,0),MATCH(data!B$1,Haver_Q!$B$1:$BD$1,0))),100*INDEX(Haver_Q!$B$1:$BD$1000,MATCH(data!$A4,Haver_Q!$B$1:$B$1000,0),MATCH(data!B$1,Haver_Q!$B$1:$BD$1,0)),"na") -> 7.8908208 | C4: =IF(ISNUMBER(INDEX(Haver_Q!$B$1:$BD$1000,MATCH(data!$A4,Haver_Q!$B$1:$B$1000,0),MATCH(data!C$1,Haver_Q!$B$1:$BD$1,0))),100*INDEX(Haver_Q!$B$1:$BD$1000,MATCH(data!$A4,Haver_Q!$B$1:$B$1000,0),MATCH(data!C$1,Haver_Q!$B$1:$BD$1,0)),"na") -> 12.149992 | D4: =IF(ISNUMBER(INDEX(Haver_Q!$B$1:$BD$1000,MATCH(data!$A4,Haver_Q!$B$1:$B$1000,0),MATCH(data!D$1,Haver_Q!$B$1:$BD$1,0))),100*INDEX(Haver_Q!$B$1:$BD$1000,MATCH(data!$A4,Haver_Q!$B$1:$B$1000,0),MATCH(data!D$1,Haver_Q!$B$1:$BD$1,0)),"na") -> 9.6004588 | E4: =IF(ISNUMBER(INDEX(Haver_Q!$B$1:$BD$1000,MATCH(data!$A4,Haver_Q!$B$1:$B$1000,0),MATCH(data!E$1,Haver_Q!$B$1:$BD$1,0))),100*INDEX(Haver_Q!$B$1:$BD$1000,MATCH(data!$A4,Haver_Q!$B$1:$B$1000,0),MATCH(data!E$1,Haver_Q!$B$1:$BD$1,0)),"na") -> 14.079916 | F4: =IF(ISNUMBER(INDEX(Haver_Q!$B$1:$BD$1000,MATCH(data!$A4,Haver_Q!$B$1:$B$1000,0),MATCH(data!F$1,Haver_Q!$B$1:$BD$1,0))),100*INDEX(Haver_Q!$B$1:$BD$1000,MATCH(data!$A4,Haver_Q!$B$1:$B$1000,0),MATCH(data!F$1,Haver_Q!$B$1:$BD$1,0)),"na") -> 17.042392 | G4: =IF(ISNUMBER(INDEX(Haver_Q!$B$1:$BD$1000,MATCH(data!$A4,Haver_Q!$B$1:$B$1000,0),MATCH(data!G$1,Haver_Q!$B$1:$BD$1,0))),100*INDEX(Haver_Q!$B$1:$BD$1000,MATCH(data!$A4,Haver_Q!$B$1:$B$1000,0),MATCH(data!G$1,Haver_Q!$B$1:$BD$1,0)),"na") -> 27.54633 | H4: =IF(ISNUMBER(INDEX(Haver_Q!$B$1:$BD$1000,MATCH(data!$A4,Haver_Q!$B$1:$B$1000,0),MATCH(data!H$1,Haver_Q!$B$1:$BD$1,0))),100*INDEX(Haver_Q!$B$1:$BD$1000,MATCH(data!$A4,Haver_Q!$B$1:$B$1000,0),MATCH(data!H$1,Haver_Q!$B$1:$BD$1,0)),"na") -> 533.84295 | I4: =IF(ISNUMBER(Bloomberg_m!C20),Bloomberg_m!C20,"na") -> 1621 | J4: =IF(ISNUMBER(Bloomberg_m!D20),Bloomberg_m!D20,"na") -> na | K4: =IF(ISNUMBER(Bloomberg_m!E20),Bloomberg_m!E20,"na") -> na | L4: =IF(ISNUMBER(Bloomberg_m!L20),Bloomberg_m!L20,"na") -> 29.89 | M4: =IF(ISNUMBER(INDEX(Haver_M!$B$1:$ZN$1000,MATCH(data!$A4,Haver_M!$B$1:$B$1000,0),MATCH(data!M$1,Haver_M!$B$1:$ZN$1,0))),INDEX(Haver_M!$B$1:$ZN$1000,MATCH(data!$A4,Haver_M!$B$1:$B$1000,0),MATCH(data!M$1,Haver_M!$B$1:$ZN$1,0)),"na") -> na | N4: =IF(ISNUMBER(INDEX(Haver_M!$B$1:$ZN$1000,MATCH(data!$A4,Haver_M!$B$1:$B$1000,0),MATCH(data!N$1,Haver_M!$B$1:$ZN$1,0))),INDEX(Haver_M!$B$1:$ZN$1000,MATCH(data!$A4,Haver_M!$B$1:$B$1000,0),MATCH(data!N$1,Haver_M!$B$1:$ZN$1,0)),"na") -> na | O4: =IF(ISNUMBER(INDEX(Haver_M!$B$1:$ZN$1000,MATCH(data!$A4,Haver_M!$B$1:$B$1000,0),MATCH(data!O$1,Haver_M!$B$1:$ZN$1,0))),INDEX(Haver_M!$B$1:$ZN$1000,MATCH(data!$A4,Haver_M!$B$1:$B$1000,0),MATCH(data!O$1,Haver_M!$B$1:$ZN$1,0)),"na") -> 117.33534 | P4: =IF(ISNUMBER(INDEX(Haver_M!$B$1:$ZN$1000,MATCH(data!$A4,Haver_M!$B$1:$B$1000,0),MATCH(data!P$1,Haver_M!$B$1:$ZN$1,0))),INDEX(Haver_M!$B$1:$ZN$1000,MATCH(data!$A4,Haver_M!$B$1:$B$1000,0),MATCH(data!P$1,Haver_M!$B$1:$ZN$1,0)),"na") -> 45.3135 | Q4: =IF(ISNUMBER(INDEX(Haver_M!$B$1:$ZN$1000,MATCH(data!$A4,Haver_M!$B$1:$B$1000,0),MATCH(data!Q$1,Haver_M!$B$1:$ZN$1,0))),INDEX(Haver_M!$B$1:$ZN$1000,MATCH(data!$A4,Haver_M!$B$1:$B$1000,0),MATCH(data!Q$1,Haver_M!$B$1:$ZN$1,0)),"na") -> 49.5671 | R4: =IF(ISNUMBER(INDEX(Haver_M!$B$1:$ZN$1000,MATCH(data!$A4,Haver_M!$B$1:$B$1000,0),MATCH(data!R$1,Haver_M!$B$1:$ZN$1,0))),INDEX(Haver_M!$B$1:$ZN$1000,MATCH(data!$A4,Haver_M!$B$1:$B$1000,0),MATCH(data!R$1,Haver_M!$B$1:$ZN$1,0)),"na") -> 89.9666 | S4: =IF(ISNUMBER(INDEX(Haver_M!$B$1:$ZN$1000,MATCH(data!$A4,Haver_M!$B$1:$B$1000,0),MATCH(data!S$1,Haver_M!$B$1:$ZN$1,0))),INDEX(Haver_M!$B$1:$ZN$1000,MATCH(data!$A4,Haver_M!$B$1:$B$1000,0),MATCH(data!S$1,Haver_M!$B$1:$ZN$1,0)),"na") -> 101.1593 | T4: =IF(ISNUMBER(INDEX(Haver_M!$B$1:$ZN$1000,MATCH(data!$A4,Haver_M!$B$1:$B$1000,0),MATCH(data!T$1,Haver_M!$B$1:$ZN$1,0))),INDEX(Haver_M!$B$1:$ZN$1000,MATCH(data!$A4,Haver_M!$B$1:$B$1000,0),MATCH(data!T$1,Haver_M!$B$1:$ZN$1,0)),"na") -> 55.207 | ... BA4: =IF(ISNUMBER(INDEX(Haver_M!$B$1:$ZN$1000,MATCH(data!$A4,Haver_M!$B$1:$B$1000,0),MATCH(data!BA$1,Haver_M!$B$1:$ZN$1,0))),INDEX(Haver_M!$B$1:$ZN$1000,MATCH(data!$A4,Haver_M!$B$1:$B$1000,0),MATCH(data!BA$1,Haver_M!$B$1:$ZN$1,0)),"na") -> 119.76352 | BB4: =IF(ISNUMBER(INDEX(Haver_M!$B$1:$ZN$1000,MATCH(data!$A4,Haver_M!$B$1:$B$1000,0),MATCH(data!BB$1,Haver_M!$B$1:$ZN$1,0))),INDEX(Haver_M!$B$1:$ZN$1000,MATCH(data!$A4,Haver_M!$B$1:$B$1000,0),MATCH(data!BB$1,Haver_M!$B$1:$ZN$1,0)),"")
A5: 36646 | B5: =IF(ISNUMBER(INDEX(Haver_Q!$B$1:$BD$1000,MATCH(data!$A5,Haver_Q!$B$1:$B$1000,0),MATCH(data!B$1,Haver_Q!$B$1:$BD$1,0))),100*INDEX(Haver_Q!$B$1:$BD$1000,MATCH(data!$A5,Haver_Q!$B$1:$B$1000,0),MATCH(data!B$1,Haver_Q!$B$1:$BD$1,0)),"na") -> na | C5: =IF(ISNUMBER(INDEX(Haver_Q!$B$1:$BD$1000,MATCH(data!$A5,Haver_Q!$B$1:$B$1000,0),MATCH(data!C$1,Haver_Q!$B$1:$BD$1,0))),100*INDEX(Haver_Q!$B$1:$BD$1000,MATCH(data!$A5,Haver_Q!$B$1:$B$1000,0),MATCH(data!C$1,Haver_Q!$B$1:$BD$1,0)),"na") -> na | D5: =IF(ISNUMBER(INDEX(Haver_Q!$B$1:$BD$1000,MATCH(data!$A5,Haver_Q!$B$1:$B$1000,0),MATCH(data!D$1,Haver_Q!$B$1:$BD$1,0))),100*INDEX(Haver_Q!$B$1:$BD$1000,MATCH(data!$A5,Haver_Q!$B$1:$B$1000,0),MATCH(data!D$1,Haver_Q!$B$1:$BD$1,0)),"na") -> na | E5: =IF(ISNUMBER(INDEX(Haver_Q!$B$1:$BD$1000,MATCH(data!$A5,Haver_Q!$B$1:$B$1000,0),MATCH(data!E$1,Haver_Q!$B$1:$BD$1,0))),100*INDEX(Haver_Q!$B$1:$BD$1000,MATCH(data!$A5,Haver_Q!$B$1:$B$1000,0),MATCH(data!E$1,Haver_Q!$B$1:$BD$1,0)),"na") -> na | F5: =IF(ISNUMBER(INDEX(Haver_Q!$B$1:$BD$1000,MATCH(data!$A5,Haver_Q!$B$1:$B$1000,0),MATCH(data!F$1,Haver_Q!$B$1:$BD$1,0))),100*INDEX(Haver_Q!$B$1:$BD$1000,MATCH(data!$A5,Haver_Q!$B$1:$B$1000,0),MATCH(data!F$1,Haver_Q!$B$1:$BD$1,0)),"na") -> na | G5: =IF(ISNUMBER(INDEX(Haver_Q!$B$1:$BD$1000,MATCH(data!$A5,Haver_Q!$B$1:$B$1000,0),MATCH(data!G$1,Haver_Q!$B$1:$BD$1,0))),100*INDEX(Haver_Q!$B$1:$BD$1000,MATCH(data!$A5,Haver_Q!$B$1:$B$1000,0),MATCH(data!G$1,Haver_Q!$B$1:$BD$1,0)),"na") -> na | H5: =IF(ISNUMBER(INDEX(Haver_Q!$B$1:$BD$1000,MATCH(data!$A5,Haver_Q!$B$1:$B$1000,0),MATCH(data!H$1,Haver_Q!$B$1:$BD$1,0))),100*INDEX(Haver_Q!$B$1:$BD$1000,MATCH(data!$A5,Haver_Q!$B$1:$B$1000,0),MATCH(data!H$1,Haver_Q!$B$1:$BD$1,0)),"na") -> na | I5: =IF(ISNUMBER(Bloomberg_m!C21),Bloomberg_m!C21,"na") -> 1667 | J5: =IF(ISNUMBER(Bloomberg_m!D21),Bloomberg_m!D21,"na") -> na | K5: =IF(ISNUMBER(Bloomberg_m!E21),Bloomberg_m!E21,"na") -> na | L5: =IF(ISNUMBER(Bloomberg_m!L21),Bloomberg_m!L21,"na") -> 25.78 | M5: =IF(ISNUMBER(INDEX(Haver_M!$B$1:$ZN$1000,MATCH(data!$A5,Haver_M!$B$1:$B$1000,0),MATCH(data!M$1,Haver_M!$B$1:$ZN$1,0))),INDEX(Haver_M!$B$1:$ZN$1000,MATCH(data!$A5,Haver_M!$B$1:$B$1000,0),MATCH(data!M$1,Haver_M!$B$1:$ZN$1,0)),"na") -> na | N5: =IF(ISNUMBER(INDEX(Haver_M!$B$1:$ZN$1000,MATCH(data!$A5,Haver_M!$B$1:$B$1000,0),MATCH(data!N$1,Haver_M!$B$1:$ZN$1,0))),INDEX(Haver_M!$B$1:$ZN$1000,MATCH(data!$A5,Haver_M!$B$1:$B$1000,0),MATCH(data!N$1,Haver_M!$B$1:$ZN$1,0)),"na") -> na | O5: =IF(ISNUMBER(INDEX(Haver_M!$B$1:$ZN$1000,MATCH(data!$A5,Haver_M!$B$1:$B$1000,0),MATCH(data!O$1,Haver_M!$B$1:$ZN$1,0))),INDEX(Haver_M!$B$1:$ZN$1000,MATCH(data!$A5,Haver_M!$B$1:$B$1000,0),MATCH(data!O$1,Haver_M!$B$1:$ZN$1,0)),"na") -> 116.90303 | P5: =IF(ISNUMBER(INDEX(Haver_M!$B$1:$ZN$1000,MATCH(data!$A5,Haver_M!$B$1:$B$1000,0),MATCH(data!P$1,Haver_M!$B$1:$ZN$1,0))),INDEX(Haver_M!$B$1:$ZN$1000,MATCH(data!$A5,Haver_M!$B$1:$B$1000,0),MATCH(data!P$1,Haver_M!$B$1:$ZN$1,0)),"na") -> 45.5985 | Q5: =IF(ISNUMBER(INDEX(Haver_M!$B$1:$ZN$1000,MATCH(data!$A5,Haver_M!$B$1:$B$1000,0),MATCH(data!Q$1,Haver_M!$B$1:$ZN$1,0))),INDEX(Haver_M!$B$1:$ZN$1000,MATCH(data!$A5,Haver_M!$B$1:$B$1000,0),MATCH(data!Q$1,Haver_M!$B$1:$ZN$1,0)),"na") -> 49.8246 | R5: =IF(ISNUMBER(INDEX(Haver_M!$B$1:$ZN$1000,MATCH(data!$A5,Haver_M!$B$1:$B$1000,0),MATCH(data!R$1,Haver_M!$B$1:$ZN$1,0))),INDEX(Haver_M!$B$1:$ZN$1000,MATCH(data!$A5,Haver_M!$B$1:$B$1000,0),MATCH(data!R$1,Haver_M!$B$1:$ZN$1,0)),"na") -> 90.3034 | S5: =IF(ISNUMBER(INDEX(Haver_M!$B$1:$ZN$1000,MATCH(data!$A5,Haver_M!$B$1:$B$1000,0),MATCH(data!S$1,Haver_M!$B$1:$ZN$1,0))),INDEX(Haver_M!$B$1:$ZN$1000,MATCH(data!$A5,Haver_M!$B$1:$B$1000,0),MATCH(data!S$1,Haver_M!$B$1:$ZN$1,0)),"na") -> 103.7515 | T5: =IF(ISNUMBER(INDEX(Haver_M!$B$1:$ZN$1000,MATCH(data!$A5,Haver_M!$B$1:$B$1000,0),MATCH(data!T$1,Haver_M!$B$1:$ZN$1,0))),INDEX(Haver_M!$B$1:$ZN$1000,MATCH(data!$A5,Haver_M!$B$1:$B$1000,0),MATCH(data!T$1,Haver_M!$B$1:$ZN$1,0)),"na") -> 54.9528 | ... BA5: =IF(ISNUMBER(INDEX(Haver_M!$B$1:$ZN$1000,MATCH(data!$A5,Haver_M!$B$1:$B$1000,0),MATCH(data!BA$1,Haver_M!$B$1:$ZN$1,0))),INDEX(Haver_M!$B$1:$ZN$1000,MATCH(data!$A5,Haver_M!$B$1:$B$1000,0),MATCH(data!BA$1,Haver_M!$B$1:$ZN$1,0)),"na") -> 108.51464 | BB5: =IF(ISNUMBER(INDEX(Haver_M!$B$1:$ZN$1000,MATCH(data!$A5,Haver_M!$B$1:$B$1000,0),MATCH(data!BB$1,Haver_M!$B$1:$ZN$1,0))),INDEX(Haver_M!$B$1:$ZN$1000,MATCH(data!$A5,Haver_M!$B$1:$B$1000,0),MATCH(data!BB$1,Haver_M!$B$1:$ZN$1,0)),"")
A6: 36677 | B6: =IF(ISNUMBER(INDEX(Haver_Q!$B$1:$BD$1000,MATCH(data!$A6,Haver_Q!$B$1:$B$1000,0),MATCH(data!B$1,Haver_Q!$B$1:$BD$1,0))),100*INDEX(Haver_Q!$B$1:$BD$1000,MATCH(data!$A6,Haver_Q!$B$1:$B$1000,0),MATCH(data!B$1,Haver_Q!$B$1:$BD$1,0)),"na") -> na | C6: =IF(ISNUMBER(INDEX(Haver_Q!$B$1:$BD$1000,MATCH(data!$A6,Haver_Q!$B$1:$B$1000,0),MATCH(data!C$1,Haver_Q!$B$1:$BD$1,0))),100*INDEX(Haver_Q!$B$1:$BD$1000,MATCH(data!$A6,Haver_Q!$B$1:$B$1000,0),MATCH(data!C$1,Haver_Q!$B$1:$BD$1,0)),"na") -> na | D6: =IF(ISNUMBER(INDEX(Haver_Q!$B$1:$BD$1000,MATCH(data!$A6,Haver_Q!$B$1:$B$1000,0),MATCH(data!D$1,Haver_Q!$B$1:$BD$1,0))),100*INDEX(Haver_Q!$B$1:$BD$1000,MATCH(data!$A6,Haver_Q!$B$1:$B$1000,0),MATCH(data!D$1,Haver_Q!$B$1:$BD$1,0)),"na") -> na | E6: =IF(ISNUMBER(INDEX(Haver_Q!$B$1:$BD$1000,MATCH(data!$A6,Haver_Q!$B$1:$B$1000,0),MATCH(data!E$1,Haver_Q!$B$1:$BD$1,0))),100*INDEX(Haver_Q!$B$1:$BD$1000,MATCH(data!$A6,Haver_Q!$B$1:$B$1000,0),MATCH(data!E$1,Haver_Q!$B$1:$BD$1,0)),"na") -> na | F6: =IF(ISNUMBER(INDEX(Haver_Q!$B$1:$BD$1000,MATCH(data!$A6,Haver_Q!$B$1:$B$1000,0),MATCH(data!F$1,Haver_Q!$B$1:$BD$1,0))),100*INDEX(Haver_Q!$B$1:$BD$1000,MATCH(data!$A6,Haver_Q!$B$1:$B$1000,0),MATCH(data!F$1,Haver_Q!$B$1:$BD$1,0)),"na") -> na | G6: =IF(ISNUMBER(INDEX(Haver_Q!$B$1:$BD$1000,MATCH(data!$A6,Haver_Q!$B$1:$B$1000,0),MATCH(data!G$1,Haver_Q!$B$1:$BD$1,0))),100*INDEX(Haver_Q!$B$1:$BD$1000,MATCH(data!$A6,Haver_Q!$B$1:$B$1000,0),MATCH(data!G$1,Haver_Q!$B$1:$BD$1,0)),"na") -> na | H6: =IF(ISNUMBER(INDEX(Haver_Q!$B$1:$BD$1000,MATCH(data!$A6,Haver_Q!$B$1:$B$1000,0),MATCH(data!H$1,Haver_Q!$B$1:$BD$1,0))),100*INDEX(Haver_Q!$B$1:$BD$1000,MATCH(data!$A6,Haver_Q!$B$1:$B$1000,0),MATCH(data!H$1,Haver_Q!$B$1:$BD$1,0)),"na") -> na | I6: =IF(ISNUMBER(Bloomberg_m!C22),Bloomberg_m!C22,"na") -> 1602 | J6: =IF(ISNUMBER(Bloomberg_m!D22),Bloomberg_m!D22,"na") -> na | K6: =IF(ISNUMBER(Bloomberg_m!E22),Bloomberg_m!E22,"na") -> na | L6: =IF(ISNUMBER(Bloomberg_m!L22),Bloomberg_m!L22,"na") -> 28.78 | M6: =IF(ISNUMBER(INDEX(Haver_M!$B$1:$ZN$1000,MATCH(data!$A6,Haver_M!$B$1:$B$1000,0),MATCH(data!M$1,Haver_M!$B$1:$ZN$1,0))),INDEX(Haver_M!$B$1:$ZN$1000,MATCH(data!$A6,Haver_M!$B$1:$B$1000,0),MATCH(data!M$1,Haver_M!$B$1:$ZN$1,0)),"na") -> na | N6: =IF(ISNUMBER(INDEX(Haver_M!$B$1:$ZN$1000,MATCH(data!$A6,Haver_M!$B$1:$B$1000,0),MATCH(data!N$1,Haver_M!$B$1:$ZN$1,0))),INDEX(Haver_M!$B$1:$ZN$1000,MATCH(data!$A6,Haver_M!$B$1:$B$1000,0),MATCH(data!N$1,Haver_M!$B$1:$ZN$1,0)),"na") -> na | O6: =IF(ISNUMBER(INDEX(Haver_M!$B$1:$ZN$1000,MATCH(data!$A6,Haver_M!$B$1:$B$1000,0),MATCH(data!O$1,Haver_M!$B$1:$ZN$1,0))),INDEX(Haver_M!$B$1:$ZN$1000,MATCH(data!$A6,Haver_M!$B$1:$B$1000,0),MATCH(data!O$1,Haver_M!$B$1:$ZN$1,0)),"na") -> 116.64526 | P6: =IF(ISNUMBER(INDEX(Haver_M!$B$1:$ZN$1000,MATCH(data!$A6,Haver_M!$B$1:$B$1000,0),MATCH(data!P$1,Haver_M!$B$1:$ZN$1,0))),INDEX(Haver_M!$B$1:$ZN$1000,MATCH(data!$A6,Haver_M!$B$1:$B$1000,0),MATCH(data!P$1,Haver_M!$B$1:$ZN$1,0)),"na") -> 45.9655 | Q6: =IF(ISNUMBER(INDEX(Haver_M!$B$1:$ZN$1000,MATCH(data!$A6,Haver_M!$B$1:$B$1000,0),MATCH(data!Q$1,Haver_M!$B$1:$ZN$1,0))),INDEX(Haver_M!$B$1:$ZN$1000,MATCH(data!$A6,Haver_M!$B$1:$B$1000,0),MATCH(data!Q$1,Haver_M!$B$1:$ZN$1,0)),"na") -> 50.144 | R6: =IF(ISNUMBER(INDEX(Haver_M!$B$1:$ZN$1000,MATCH(data!$A6,Haver_M!$B$1:$B$1000,0),MATCH(data!R$1,Haver_M!$B$1:$ZN$1,0))),INDEX(Haver_M!$B$1:$ZN$1000,MATCH(data!$A6,Haver_M!$B$1:$B$1000,0),MATCH(data!R$1,Haver_M!$B$1:$ZN$1,0)),"na") -> 91.1724 | S6: =IF(ISNUMBER(INDEX(Haver_M!$B$1:$ZN$1000,MATCH(data!$A6,Haver_M!$B$1:$B$1000,0),MATCH(data!S$1,Haver_M!$B$1:$ZN$1,0))),INDEX(Haver_M!$B$1:$ZN$1000,MATCH(data!$A6,Haver_M!$B$1:$B$1000,0),MATCH(data!S$1,Haver_M!$B$1:$ZN$1,0)),"na") -> 103.1344 | T6: =IF(ISNUMBER(INDEX(Haver_M!$B$1:$ZN$1000,MATCH(data!$A6,Haver_M!$B$1:$B$1000,0),MATCH(data!T$1,Haver_M!$B$1:$ZN$1,0))),INDEX(Haver_M!$B$1:$ZN$1000,MATCH(data!$A6,Haver_M!$B$1:$B$1000,0),MATCH(data!T$1,Haver_M!$B$1:$ZN$1,0)),"na") -> 55.1982 | ... BA6: =IF(ISNUMBER(INDEX(Haver_M!$B$1:$ZN$1000,MATCH(data!$A6,Haver_M!$B$1:$B$1000,0),MATCH(data!BA$1,Haver_M!$B$1:$ZN$1,0))),INDEX(Haver_M!$B$1:$ZN$1000,MATCH(data!$A6,Haver_M!$B$1:$B$1000,0),MATCH(data!BA$1,Haver_M!$B$1:$ZN$1,0)),"na") -> 149.59285 | BB6: =IF(ISNUMBER(INDEX(Haver_M!$B$1:$ZN$1000,MATCH(data!$A6,Haver_M!$B$1:$B$1000,0),MATCH(data!BB$1,Haver_M!$B$1:$ZN$1,0))),INDEX(Haver_M!$B$1:$ZN$1000,MATCH(data!$A6,Haver_M!$B$1:$B$1000,0),MATCH(data!BB$1,Haver_M!$B$1:$ZN$1,0)),"")
A7: 36707 | B7: =IF(ISNUMBER(INDEX(Haver_Q!$B$1:$BD$1000,MATCH(data!$A7,Haver_Q!$B$1:$B$1000,0),MATCH(data!B$1,Haver_Q!$B$1:$BD$1,0))),100*INDEX(Haver_Q!$B$1:$BD$1000,MATCH(data!$A7,Haver_Q!$B$1:$B$1000,0),MATCH(data!B$1,Haver_Q!$B$1:$BD$1,0)),"na") -> 6.2703483 | C7: =IF(ISNUMBER(INDEX(Haver_Q!$B$1:$BD$1000,MATCH(data!$A7,Haver_Q!$B$1:$B$1000,0),MATCH(data!C$1,Haver_Q!$B$1:$BD$1,0))),100*INDEX(Haver_Q!$B$1:$BD$1000,MATCH(data!$A7,Haver_Q!$B$1:$B$1000,0),MATCH(data!C$1,Haver_Q!$B$1:$BD$1,0)),"na") -> -2.0346867 | D7: =IF(ISNUMBER(INDEX(Haver_Q!$B$1:$BD$1000,MATCH(data!$A7,Haver_Q!$B$1:$B$1000,0),MATCH(data!D$1,Haver_Q!$B$1:$BD$1,0))),100*INDEX(Haver_Q!$B$1:$BD$1000,MATCH(data!$A7,Haver_Q!$B$1:$B$1000,0),MATCH(data!D$1,Haver_Q!$B$1:$BD$1,0)),"na") -> 8.8398814 | E7: =IF(ISNUMBER(INDEX(Haver_Q!$B$1:$BD$1000,MATCH(data!$A7,Haver_Q!$B$1:$B$1000,0),MATCH(data!E$1,Haver_Q!$B$1:$BD$1,0))),100*INDEX(Haver_Q!$B$1:$BD$1000,MATCH(data!$A7,Haver_Q!$B$1:$B$1000,0),MATCH(data!E$1,Haver_Q!$B$1:$BD$1,0)),"na") -> 5.7696005 | F7: =IF(ISNUMBER(INDEX(Haver_Q!$B$1:$BD$1000,MATCH(data!$A7,Haver_Q!$B$1:$B$1000,0),MATCH(data!F$1,Haver_Q!$B$1:$BD$1,0))),100*INDEX(Haver_Q!$B$1:$BD$1000,MATCH(data!$A7,Haver_Q!$B$1:$B$1000,0),MATCH(data!F$1,Haver_Q!$B$1:$BD$1,0)),"na") -> 12.937207 | G7: =IF(ISNUMBER(INDEX(Haver_Q!$B$1:$BD$1000,MATCH(data!$A7,Haver_Q!$B$1:$B$1000,0),MATCH(data!G$1,Haver_Q!$B$1:$BD$1,0))),100*INDEX(Haver_Q!$B$1:$BD$1000,MATCH(data!$A7,Haver_Q!$B$1:$B$1000,0),MATCH(data!G$1,Haver_Q!$B$1:$BD$1,0)),"na") -> 12.211141 | H7: =IF(ISNUMBER(INDEX(Haver_Q!$B$1:$BD$1000,MATCH(data!$A7,Haver_Q!$B$1:$B$1000,0),MATCH(data!H$1,Haver_Q!$B$1:$BD$1,0))),100*INDEX(Haver_Q!$B$1:$BD$1000,MATCH(data!$A7,Haver_Q!$B$1:$B$1000,0),MATCH(data!H$1,Haver_Q!$B$1:$BD$1,0)),"na") -> 503.1488 | I7: =IF(ISNUMBER(Bloomberg_m!C23),Bloomberg_m!C23,"na") -> 1589 | J7: =IF(ISNUMBER(Bloomberg_m!D23),Bloomberg_m!D23,"na") -> na | K7: =IF(ISNUMBER(Bloomberg_m!E23),Bloomberg_m!E23,"na") -> na | L7: =IF(ISNUMBER(Bloomberg_m!L23),Bloomberg_m!L23,"na") -> 31.86 | M7: =IF(ISNUMBER(INDEX(Haver_M!$B$1:$ZN$1000,MATCH(data!$A7,Haver_M!$B$1:$B$1000,0),MATCH(data!M$1,Haver_M!$B$1:$ZN$1,0))),INDEX(Haver_M!$B$1:$ZN$1000,MATCH(data!$A7,Haver_M!$B$1:$B$1000,0),MATCH(data!M$1,Haver_M!$B$1:$ZN$1,0)),"na") -> na | N7: =IF(ISNUMBER(INDEX(Haver_M!$B$1:$ZN$1000,MATCH(data!$A7,Haver_M!$B$1:$B$1000,0),MATCH(data!N$1,Haver_M!$B$1:$ZN$1,0))),INDEX(Haver_M!$B$1:$ZN$1000,MATCH(data!$A7,Haver_M!$B$1:$B$1000,0),MATCH(data!N$1,Haver_M!$B$1:$ZN$1,0)),"na") -> na | O7: =IF(ISNUMBER(INDEX(Haver_M!$B$1:$ZN$1000,MATCH(data!$A7,Haver_M!$B$1:$B$1000,0),MATCH(data!O$1,Haver_M!$B$1:$ZN$1,0))),INDEX(Haver_M!$B$1:$ZN$1000,MATCH(data!$A7,Haver_M!$B$1:$B$1000,0),MATCH(data!O$1,Haver_M!$B$1:$ZN$1,0)),"na") -> 112.26979 | P7: =IF(ISNUMBER(INDEX(Haver_M!$B$1:$ZN$1000,MATCH(data!$A7,Haver_M!$B$1:$B$1000,0),MATCH(data!P$1,Haver_M!$B$1:$ZN$1,0))),INDEX(Haver_M!$B$1:$ZN$1000,MATCH(data!$A7,Haver_M!$B$1:$B$1000,0),MATCH(data!P$1,Haver_M!$B$1:$ZN$1,0)),"na") -> 46.3367 | Q7: =IF(ISNUMBER(INDEX(Haver_M!$B$1:$ZN$1000,MATCH(data!$A7,Haver_M!$B$1:$B$1000,0),MATCH(data!Q$1,Haver_M!$B$1:$ZN$1,0))),INDEX(Haver_M!$B$1:$ZN$1000,MATCH(data!$A7,Haver_M!$B$1:$B$1000,0),MATCH(data!Q$1,Haver_M!$B$1:$ZN$1,0)),"na") -> 50.4345 | R7: =IF(ISNUMBER(INDEX(Haver_M!$B$1:$ZN$1000,MATCH(data!$A7,Haver_M!$B$1:$B$1000,0),MATCH(data!R$1,Haver_M!$B$1:$ZN$1,0))),INDEX(Haver_M!$B$1:$ZN$1000,MATCH(data!$A7,Haver_M!$B$1:$B$1000,0),MATCH(data!R$1,Haver_M!$B$1:$ZN$1,0)),"na") -> 91.7436 | S7: =IF(ISNUMBER(INDEX(Haver_M!$B$1:$ZN$1000,MATCH(data!$A7,Haver_M!$B$1:$B$1000,0),MATCH(data!S$1,Haver_M!$B$1:$ZN$1,0))),INDEX(Haver_M!$B$1:$ZN$1000,MATCH(data!$A7,Haver_M!$B$1:$B$1000,0),MATCH(data!S$1,Haver_M!$B$1:$ZN$1,0)),"na") -> 104.3887 | T7: =IF(ISNUMBER(INDEX(Haver_M!$B$1:$ZN$1000,MATCH(data!$A7,Haver_M!$B$1:$B$1000,0),MATCH(data!T$1,Haver_M!$B$1:$ZN$1,0))),INDEX(Haver_M!$B$1:$ZN$1000,MATCH(data!$A7,Haver_M!$B$1:$B$1000,0),MATCH(data!T$1,Haver_M!$B$1:$ZN$1,0)),"na") -> 55.2032 | ... BA7: =IF(ISNUMBER(INDEX(Haver_M!$B$1:$ZN$1000,MATCH(data!$A7,Haver_M!$B$1:$B$1000,0),MATCH(data!BA$1,Haver_M!$B$1:$ZN$1,0))),INDEX(Haver_M!$B$1:$ZN$1000,MATCH(data!$A7,Haver_M!$B$1:$B$1000,0),MATCH(data!BA$1,Haver_M!$B$1:$ZN$1,0)),"na") -> 261.59393 | BB7: =IF(ISNUMBER(INDEX(Haver_M!$B$1:$ZN$1000,MATCH(data!$A7,Haver_M!$B$1:$B$1000,0),MATCH(data!BB$1,Haver_M!$B$1:$ZN$1,0))),INDEX(Haver_M!$B$1:$ZN$1000,MATCH(data!$A7,Haver_M!$B$1:$B$1000,0),MATCH(data!BB$1,Haver_M!$B$1:$ZN$1,0)),"")
A8: 36738 | B8: =IF(ISNUMBER(INDEX(Haver_Q!$B$1:$BD$1000,MATCH(data!$A8,Haver_Q!$B$1:$B$1000,0),MATCH(data!B$1,Haver_Q!$B$1:$BD$1,0))),100*INDEX(Haver_Q!$B$1:$BD$1000,MATCH(data!$A8,Haver_Q!$B$1:$B$1000,0),MATCH(data!B$1,Haver_Q!$B$1:$BD$1,0)),"na") -> na | C8: =IF(ISNUMBER(INDEX(Haver_Q!$B$1:$BD$1000,MATCH(data!$A8,Haver_Q!$B$1:$B$1000,0),MATCH(data!C$1,Haver_Q!$B$1:$BD$1,0))),100*INDEX(Haver_Q!$B$1:$BD$1000,MATCH(data!$A8,Haver_Q!$B$1:$B$1000,0),MATCH(data!C$1,Haver_Q!$B$1:$BD$1,0)),"na") -> na | D8: =IF(ISNUMBER(INDEX(Haver_Q!$B$1:$BD$1000,MATCH(data!$A8,Haver_Q!$B$1:$B$1000,0),MATCH(data!D$1,Haver_Q!$B$1:$BD$1,0))),100*INDEX(Haver_Q!$B$1:$BD$1000,MATCH(data!$A8,Haver_Q!$B$1:$B$1000,0),MATCH(data!D$1,Haver_Q!$B$1:$BD$1,0)),"na") -> na | E8: =IF(ISNUMBER(INDEX(Haver_Q!$B$1:$BD$1000,MATCH(data!$A8,Haver_Q!$B$1:$B$1000,0),MATCH(data!E$1,Haver_Q!$B$1:$BD$1,0))),100*INDEX(Haver_Q!$B$1:$BD$1000,MATCH(data!$A8,Haver_Q!$B$1:$B$1000,0),MATCH(data!E$1,Haver_Q!$B$1:$BD$1,0)),"na") -> na | F8: =IF(ISNUMBER(INDEX(Haver_Q!$B$1:$BD$1000,MATCH(data!$A8,Haver_Q!$B$1:$B$1000,0),MATCH(data!F$1,Haver_Q!$B$1:$BD$1,0))),100*INDEX(Haver_Q!$B$1:$BD$1000,MATCH(data!$A8,Haver_Q!$B$1:$B$1000,0),MATCH(data!F$1,Haver_Q!$B$1:$BD$1,0)),"na") -> na | G8: =IF(ISNUMBER(INDEX(Haver_Q!$B$1:$BD$1000,MATCH(data!$A8,Haver_Q!$B$1:$B$1000,0),MATCH(data!G$1,Haver_Q!$B$1:$BD$1,0))),100*INDEX(Haver_Q!$B$1:$BD$1000,MATCH(data!$A8,Haver_Q!$B$1:$B$1000,0),MATCH(data!G$1,Haver_Q!$B$1:$BD$1,0)),"na") -> na | H8: =IF(ISNUMBER(INDEX(Haver_Q!$B$1:$BD$1000,MATCH(data!$A8,Haver_Q!$B$1:$B$1000,0),MATCH(data!H$1,Haver_Q!$B$1:$BD$1,0))),100*INDEX(Haver_Q!$B$1:$BD$1000,MATCH(data!$A8,Haver_Q!$B$1:$B$1000,0),MATCH(data!H$1,Haver_Q!$B$1:$BD$1,0)),"na") -> na | I8: =IF(ISNUMBER(Bloomberg_m!C24),Bloomberg_m!C24,"na") -> 1618 | J8: =IF(ISNUMBER(Bloomberg_m!D24),Bloomberg_m!D24,"na") -> na | K8: =IF(ISNUMBER(Bloomberg_m!E24),Bloomberg_m!E24,"na") -> na | L8: =IF(ISNUMBER(Bloomberg_m!L24),Bloomberg_m!L24,"na") -> 29.7 | M8: =IF(ISNUMBER(INDEX(Haver_M!$B$1:$ZN$1000,MATCH(data!$A8,Haver_M!$B$1:$B$1000,0),MATCH(data!M$1,Haver_M!$B$1:$ZN$1,0))),INDEX(Haver_M!$B$1:$ZN$1000,MATCH(data!$A8,Haver_M!$B$1:$B$1000,0),MATCH(data!M$1,Haver_M!$B$1:$ZN$1,0)),"na") -> na | N8: =IF(ISNUMBER(INDEX(Haver_M!$B$1:$ZN$1000,MATCH(data!$A8,Haver_M!$B$1:$B$1000,0),MATCH(data!N$1,Haver_M!$B$1:$ZN$1,0))),INDEX(Haver_M!$B$1:$ZN$1000,MATCH(data!$A8,Haver_M!$B$1:$B$1000,0),MATCH(data!N$1,Haver_M!$B$1:$ZN$1,0)),"na") -> na | O8: =IF(ISNUMBER(INDEX(Haver_M!$B$1:$ZN$1000,MATCH(data!$A8,Haver_M!$B$1:$B$1000,0),MATCH(data!O$1,Haver_M!$B$1:$ZN$1,0))),INDEX(Haver_M!$B$1:$ZN$1000,MATCH(data!$A8,Haver_M!$B$1:$B$1000,0),MATCH(data!O$1,Haver_M!$B$1:$ZN$1,0)),"na") -> 117.72534 | P8: =IF(ISNUMBER(INDEX(Haver_M!$B$1:$ZN$1000,MATCH(data!$A8,Haver_M!$B$1:$B$1000,0),MATCH(data!P$1,Haver_M!$B$1:$ZN$1,0))),INDEX(Haver_M!$B$1:$ZN$1000,MATCH(data!$A8,Haver_M!$B$1:$B$1000,0),MATCH(data!P$1,Haver_M!$B$1:$ZN$1,0)),"na") -> 46.6904 | Q8: =IF(ISNUMBER(INDEX(Haver_M!$B$1:$ZN$1000,MATCH(data!$A8,Haver_M!$B$1:$B$1000,0),MATCH(data!Q$1,Haver_M!$B$1:$ZN$1,0))),INDEX(Haver_M!$B$1:$ZN$1000,MATCH(data!$A8,Haver_M!$B$1:$B$1000,0),MATCH(data!Q$1,Haver_M!$B$1:$ZN$1,0)),"na") -> 50.7695 | R8: =IF(ISNUMBER(INDEX(Haver_M!$B$1:$ZN$1000,MATCH(data!$A8,Haver_M!$B$1:$B$1000,0),MATCH(data!R$1,Haver_M!$B$1:$ZN$1,0))),INDEX(Haver_M!$B$1:$ZN$1000,MATCH(data!$A8,Haver_M!$B$1:$B$1000,0),MATCH(data!R$1,Haver_M!$B$1:$ZN$1,0)),"na") -> 91.4115 | S8: =IF(ISNUMBER(INDEX(Haver_M!$B$1:$ZN$1000,MATCH(data!$A8,Haver_M!$B$1:$B$1000,0),MATCH(data!S$1,Haver_M!$B$1:$ZN$1,0))),INDEX(Haver_M!$B$1:$ZN$1000,MATCH(data!$A8,Haver_M!$B$1:$B$1000,0),MATCH(data!S$1,Haver_M!$B$1:$ZN$1,0)),"na") -> 96.7789 | T8: =IF(ISNUMBER(INDEX(Haver_M!$B$1:$ZN$1000,MATCH(data!$A8,Haver_M!$B$1:$B$1000,0),MATCH(data!T$1,Haver_M!$B$1:$ZN$1,0))),INDEX(Haver_M!$B$1:$ZN$1000,MATCH(data!$A8,Haver_M!$B$1:$B$1000,0),MATCH(data!T$1,Haver_M!$B$1:$ZN$1,0)),"na") -> 54.6904 | ... BA8: =IF(ISNUMBER(INDEX(Haver_M!$B$1:$ZN$1000,MATCH(data!$A8,Haver_M!$B$1:$B$1000,0),MATCH(data!BA$1,Haver_M!$B$1:$ZN$1,0))),INDEX(Haver_M!$B$1:$ZN$1000,MATCH(data!$A8,Haver_M!$B$1:$B$1000,0),MATCH(data!BA$1,Haver_M!$B$1:$ZN$1,0)),"na") -> 144.08678 | BB8: =IF(ISNUMBER(INDEX(Haver_M!$B$1:$ZN$1000,MATCH(data!$A8,Haver_M!$B$1:$B$1000,0),MATCH(data!BB$1,Haver_M!$B$1:$ZN$1,0))),INDEX(Haver_M!$B$1:$ZN$1000,MATCH(data!$A8,Haver_M!$B$1:$B$1000,0),MATCH(data!BB$1,Haver_M!$B$1:$ZN$1,0)),"")
A9: 36769 | B9: =IF(ISNUMBER(INDEX(Haver_Q!$B$1:$BD$1000,MATCH(data!$A9,Haver_Q!$B$1:$B$1000,0),MATCH(data!B$1,Haver_Q!$B$1:$BD$1,0))),100*INDEX(Haver_Q!$B$1:$BD$1000,MATCH(data!$A9,Haver_Q!$B$1:$B$1000,0),MATCH(data!B$1,Haver_Q!$B$1:$BD$1,0)),"na") -> na | C9: =IF(ISNUMBER(INDEX(Haver_Q!$B$1:$BD$1000,MATCH(data!$A9,Haver_Q!$B$1:$B$1000,0),MATCH(data!C$1,Haver_Q!$B$1:$BD$1,0))),100*INDEX(Haver_Q!$B$1:$BD$1000,MATCH(data!$A9,Haver_Q!$B$1:$B$1000,0),MATCH(data!C$1,Haver_Q!$B$1:$BD$1,0)),"na") -> na | D9: =IF(ISNUMBER(INDEX(Haver_Q!$B$1:$BD$1000,MATCH(data!$A9,Haver_Q!$B$1:$B$1000,0),MATCH(data!D$1,Haver_Q!$B$1:$BD$1,0))),100*INDEX(Haver_Q!$B$1:$BD$1000,MATCH(data!$A9,Haver_Q!$B$1:$B$1000,0),MATCH(data!D$1,Haver_Q!$B$1:$BD$1,0)),"na") -> na | E9: =IF(ISNUMBER(INDEX(Haver_Q!$B$1:$BD$1000,MATCH(data!$A9,Haver_Q!$B$1:$B$1000,0),MATCH(data!E$1,Haver_Q!$B$1:$BD$1,0))),100*INDEX(Haver_Q!$B$1:$BD$1000,MATCH(data!$A9,Haver_Q!$B$1:$B$1000,0),MATCH(data!E$1,Haver_Q!$B$1:$BD$1,0)),"na") -> na | F9: =IF(ISNUMBER(INDEX(Haver_Q!$B$1:$BD$1000,MATCH(data!$A9,Haver_Q!$B$1:$B$1000,0),MATCH(data!F$1,Haver_Q!$B$1:$BD$1,0))),100*INDEX(Haver_Q!$B$1:$BD$1000,MATCH(data!$A9,Haver_Q!$B$1:$B$1000,0),MATCH(data!F$1,Haver_Q!$B$1:$BD$1,0)),"na") -> na | G9: =IF(ISNUMBER(INDEX(Haver_Q!$B$1:$BD$1000,MATCH(data!$A9,Haver_Q!$B$1:$B$1000,0),MATCH(data!G$1,Haver_Q!$B$1:$BD$1,0))),100*INDEX(Haver_Q!$B$1:$BD$1000,MATCH(data!$A9,Haver_Q!$B$1:$B$1000,0),MATCH(data!G$1,Haver_Q!$B$1:$BD$1,0)),"na") -> na | H9: =IF(ISNUMBER(INDEX(Haver_Q!$B$1:$BD$1000,MATCH(data!$A9,Haver_Q!$B$1:$B$1000,0),MATCH(data!H$1,Haver_Q!$B$1:$BD$1,0))),100*INDEX(Haver_Q!$B$1:$BD$1000,MATCH(data!$A9,Haver_Q!$B$1:$B$1000,0),MATCH(data!H$1,Haver_Q!$B$1:$BD$1,0)),"na") -> na | I9: =IF(ISNUMBER(Bloomberg_m!C25),Bloomberg_m!C25,"na") -> 1639 | J9: =IF(ISNUMBER(Bloomberg_m!D25),Bloomberg_m!D25,"na") -> na | K9: =IF(ISNUMBER(Bloomberg_m!E25),Bloomberg_m!E25,"na") -> na | L9: =IF(ISNUMBER(Bloomberg_m!L25),Bloomberg_m!L25,"na") -> 31.31 | M9: =IF(ISNUMBER(INDEX(Haver_M!$B$1:$ZN$1000,MATCH(data!$A9,Haver_M!$B$1:$B$1000,0),MATCH(data!M$1,Haver_M!$B$1:$ZN$1,0))),INDEX(Haver_M!$B$1:$ZN$1000,MATCH(data!$A9,Haver_M!$B$1:$B$1000,0),MATCH(data!M$1,Haver_M!$B$1:$ZN$1,0)),"na") -> na | N9: =IF(ISNUMBER(INDEX(Haver_M!$B$1:$ZN$1000,MATCH(data!$A9,Haver_M!$B$1:$B$1000,0),MATCH(data!N$1,Haver_M!$B$1:$ZN$1,0))),INDEX(Haver_M!$B$1:$ZN$1000,MATCH(data!$A9,Haver_M!$B$1:$B$1000,0),MATCH(data!N$1,Haver_M!$B$1:$ZN$1,0)),"na") -> na | O9: =IF(ISNUMBER(INDEX(Haver_M!$B$1:$ZN$1000,MATCH(data!$A9,Haver_M!$B$1:$B$1000,0),MATCH(data!O$1,Haver_M!$B$1:$ZN$1,0))),INDEX(Haver_M!$B$1:$ZN$1000,MATCH(data!$A9,Haver_M!$B$1:$B$1000,0),MATCH(data!O$1,Haver_M!$B$1:$ZN$1,0)),"na") -> 120.57772 | P9: =IF(ISNUMBER(INDEX(Haver_M!$B$1:$ZN$1000,MATCH(data!$A9,Haver_M!$B$1:$B$1000,0),MATCH(data!P$1,Haver_M!$B$1:$ZN$1,0))),INDEX(Haver_M!$B$1:$ZN$1000,MATCH(data!$A9,Haver_M!$B$1:$B$1000,0),MATCH(data!P$1,Haver_M!$B$1:$ZN$1,0)),"na") -> 47.0132 | Q9: =IF(ISNUMBER(INDEX(Haver_M!$B$1:$ZN$1000,MATCH(data!$A9,Haver_M!$B$1:$B$1000,0),MATCH(data!Q$1,Haver_M!$B$1:$ZN$1,0))),INDEX(Haver_M!$B$1:$ZN$1000,MATCH(data!$A9,Haver_M!$B$1:$B$1000,0),MATCH(data!Q$1,Haver_M!$B$1:$ZN$1,0)),"na") -> 51.0742 | R9: =IF(ISNUMBER(INDEX(Haver_M!$B$1:$ZN$1000,MATCH(data!$A9,Haver_M!$B$1:$B$1000,0),MATCH(data!R$1,Haver_M!$B$1:$ZN$1,0))),INDEX(Haver_M!$B$1:$ZN$1000,MATCH(data!$A9,Haver_M!$B$1:$B$1000,0),MATCH(data!R$1,Haver_M!$B$1:$ZN$1,0)),"na") -> 91.6441 | S9: =IF(ISNUMBER(INDEX(Haver_M!$B$1:$ZN$1000,MATCH(data!$A9,Haver_M!$B$1:$B$1000,0),MATCH(data!S$1,Haver_M!$B$1:$ZN$1,0))),INDEX(Haver_M!$B$1:$ZN$1000,MATCH(data!$A9,Haver_M!$B$1:$B$1000,0),MATCH(data!S$1,Haver_M!$B$1:$ZN$1,0)),"na") -> 105.6175 | T9: =IF(ISNUMBER(INDEX(Haver_M!$B$1:$ZN$1000,MATCH(data!$A9,Haver_M!$B$1:$B$1000,0),MATCH(data!T$1,Haver_M!$B$1:$ZN$1,0))),INDEX(Haver_M!$B$1:$ZN$1000,MATCH(data!$A9,Haver_M!$B$1:$B$1000,0),MATCH(data!T$1,Haver_M!$B$1:$ZN$1,0)),"na") -> 55.3312 | ... BA9: =IF(ISNUMBER(INDEX(Haver_M!$B$1:$ZN$1000,MATCH(data!$A9,Haver_M!$B$1:$B$1000,0),MATCH(data!BA$1,Haver_M!$B$1:$ZN$1,0))),INDEX(Haver_M!$B$1:$ZN$1000,MATCH(data!$A9,Haver_M!$B$1:$B$1000,0),MATCH(data!BA$1,Haver_M!$B$1:$ZN$1,0)),"na") -> 94.650131 | BB9: =IF(ISNUMBER(INDEX(Haver_M!$B$1:$ZN$1000,MATCH(data!$A9,Haver_M!$B$1:$B$1000,0),MATCH(data!BB$1,Haver_M!$B$1:$ZN$1,0))),INDEX(Haver_M!$B$1:$ZN$1000,MATCH(data!$A9,Haver_M!$B$1:$B$1000,0),MATCH(data!BB$1,Haver_M!$B$1:$ZN$1,0)),"")
A10: 36799 | B10: =IF(ISNUMBER(INDEX(Haver_Q!$B$1:$BD$1000,MATCH(data!$A10,Haver_Q!$B$1:$B$1000,0),MATCH(data!B$1,Haver_Q!$B$1:$BD$1,0))),100*INDEX(Haver_Q!$B$1:$BD$1000,MATCH(data!$A10,Haver_Q!$B$1:$B$1000,0),MATCH(data!B$1,Haver_Q!$B$1:$BD$1,0)),"na") -> 3.1479804 | C10: =IF(ISNUMBER(INDEX(Haver_Q!$B$1:$BD$1000,MATCH(data!$A10,Haver_Q!$B$1:$B$1000,0),MATCH(data!C$1,Haver_Q!$B$1:$BD$1,0))),100*INDEX(Haver_Q!$B$1:$BD$1000,MATCH(data!$A10,Haver_Q!$B$1:$B$1000,0),MATCH(data!C$1,Haver_Q!$B$1:$BD$1,0)),"na") -> 0.26588307 | D10: =IF(ISNUMBER(INDEX(Haver_Q!$B$1:$BD$1000,MATCH(data!$A10,Haver_Q!$B$1:$B$1000,0),MATCH(data!D$1,Haver_Q!$B$1:$BD$1,0))),100*INDEX(Haver_Q!$B$1:$BD$1000,MATCH(data!$A10,Haver_Q!$B$1:$B$1000,0),MATCH(data!D$1,Haver_Q!$B$1:$BD$1,0)),"na") -> 7.2302863 | E10: =IF(ISNUMBER(INDEX(Haver_Q!$B$1:$BD$1000,MATCH(data!$A10,Haver_Q!$B$1:$B$1000,0),MATCH(data!E$1,Haver_Q!$B$1:$BD$1,0))),100*INDEX(Haver_Q!$B$1:$BD$1000,MATCH(data!$A10,Haver_Q!$B$1:$B$1000,0),MATCH(data!E$1,Haver_Q!$B$1:$BD$1,0)),"na") -> -1.6482029 | F10: =IF(ISNUMBER(INDEX(Haver_Q!$B$1:$BD$1000,MATCH(data!$A10,Haver_Q!$B$1:$B$1000,0),MATCH(data!F$1,Haver_Q!$B$1:$BD$1,0))),100*INDEX(Haver_Q!$B$1:$BD$1000,MATCH(data!$A10,Haver_Q!$B$1:$B$1000,0),MATCH(data!F$1,Haver_Q!$B$1:$BD$1,0)),"na") -> 12.589966 | G10: =IF(ISNUMBER(INDEX(Haver_Q!$B$1:$BD$1000,MATCH(data!$A10,Haver_Q!$B$1:$B$1000,0),MATCH(data!G$1,Haver_Q!$B$1:$BD$1,0))),100*INDEX(Haver_Q!$B$1:$BD$1000,MATCH(data!$A10,Haver_Q!$B$1:$B$1000,0),MATCH(data!G$1,Haver_Q!$B$1:$BD$1,0)),"na") -> 30.634637 | H10: =IF(ISNUMBER(INDEX(Haver_Q!$B$1:$BD$1000,MATCH(data!$A10,Haver_Q!$B$1:$B$1000,0),MATCH(data!H$1,Haver_Q!$B$1:$BD$1,0))),100*INDEX(Haver_Q!$B$1:$BD$1000,MATCH(data!$A10,Haver_Q!$B$1:$B$1000,0),MATCH(data!H$1,Haver_Q!$B$1:$BD$1,0)),"na") -> 313.88242 | I10: =IF(ISNUMBER(Bloomberg_m!C26),Bloomberg_m!C26,"na") -> 1712 | J10: =IF(ISNUMBER(Bloomberg_m!D26),Bloomberg_m!D26,"na") -> na | K10: =IF(ISNUMBER(Bloomberg_m!E26),Bloomberg_m!E26,"na") -> na | L10: =IF(ISNUMBER(Bloomberg_m!L26),Bloomberg_m!L26,"na") -> 33.89 | M10: =IF(ISNUMBER(INDEX(Haver_M!$B$1:$ZN$1000,MATCH(data!$A10,Haver_M!$B$1:$B$1000,0),MATCH(data!M$1,Haver_M!$B$1:$ZN$1,0))),INDEX(Haver_M!$B$1:$ZN$1000,MATCH(data!$A10,Haver_M!$B$1:$B$1000,0),MATCH(data!M$1,Haver_M!$B$1:$ZN$1,0)),"na") -> na | N10: =IF(ISNUMBER(INDEX(Haver_M!$B$1:$ZN$1000,MATCH(data!$A10,Haver_M!$B$1:$B$1000,0),MATCH(data!N$1,Haver_M!$B$1:$ZN$1,0))),INDEX(Haver_M!$B$1:$ZN$1000,MATCH(data!$A10,Haver_M!$B$1:$B$1000,0),MATCH(data!N$1,Haver_M!$B$1:$ZN$1,0)),"na") -> na | O10: =IF(ISNUMBER(INDEX(Haver_M!$B$1:$ZN$1000,MATCH(data!$A10,Haver_M!$B$1:$B$1000,0),MATCH(data!O$1,Haver_M!$B$1:$ZN$1,0))),INDEX(Haver_M!$B$1:$ZN$1000,MATCH(data!$A10,Haver_M!$B$1:$B$1000,0),MATCH(data!O$1,Haver_M!$B$1:$ZN$1,0)),"na") -> 120.15479 | P10: =IF(ISNUMBER(INDEX(Haver_M!$B$1:$ZN$1000,MATCH(data!$A10,Haver_M!$B$1:$B$1000,0),MATCH(data!P$1,Haver_M!$B$1:$ZN$1,0))),INDEX(Haver_M!$B$1:$ZN$1000,MATCH(data!$A10,Haver_M!$B$1:$B$1000,0),MATCH(data!P$1,Haver_M!$B$1:$ZN$1,0)),"na") -> 47.2826 | Q10: =IF(ISNUMBER(INDEX(Haver_M!$B$1:$ZN$1000,MATCH(data!$A10,Haver_M!$B$1:$B$1000,0),MATCH(data!Q$1,Haver_M!$B$1:$ZN$1,0))),INDEX(Haver_M!$B$1:$ZN$1000,MATCH(data!$A10,Haver_M!$B$1:$B$1000,0),MATCH(data!Q$1,Haver_M!$B$1:$ZN$1,0)),"na") -> 51.3214 | R10: =IF(ISNUMBER(INDEX(Haver_M!$B$1:$ZN$1000,MATCH(data!$A10,Haver_M!$B$1:$B$1000,0),MATCH(data!R$1,Haver_M!$B$1:$ZN$1,0))),INDEX(Haver_M!$B$1:$ZN$1000,MATCH(data!$A10,Haver_M!$B$1:$B$1000,0),MATCH(data!R$1,Haver_M!$B$1:$ZN$1,0)),"na") -> 91.508 | S10: =IF(ISNUMBER(INDEX(Haver_M!$B$1:$ZN$1000,MATCH(data!$A10,Haver_M!$B$1:$B$1000,0),MATCH(data!S$1,Haver_M!$B$1:$ZN$1,0))),INDEX(Haver_M!$B$1:$ZN$1000,MATCH(data!$A10,Haver_M!$B$1:$B$1000,0),MATCH(data!S$1,Haver_M!$B$1:$ZN$1,0)),"na") -> 107.4547 | T10: =IF(ISNUMBER(INDEX(Haver_M!$B$1:$ZN$1000,MATCH(data!$A10,Haver_M!$B$1:$B$1000,0),MATCH(data!T$1,Haver_M!$B$1:$ZN$1,0))),INDEX(Haver_M!$B$1:$ZN$1000,MATCH(data!$A10,Haver_M!$B$1:$B$1000,0),MATCH(data!T$1,Haver_M!$B$1:$ZN$1,0)),"na") -> 55.9557 | ... BA10: =IF(ISNUMBER(INDEX(Haver_M!$B$1:$ZN$1000,MATCH(data!$A10,Haver_M!$B$1:$B$1000,0),MATCH(data!BA$1,Haver_M!$B$1:$ZN$1,0))),INDEX(Haver_M!$B$1:$ZN$1000,MATCH(data!$A10,Haver_M!$B$1:$B$1000,0),MATCH(data!BA$1,Haver_M!$B$1:$ZN$1,0)),"na") -> 62.056772 | BB10: =IF(ISNUMBER(INDEX(Haver_M!$B$1:$ZN$1000,MATCH(data!$A10,Haver_M!$B$1:$B$1000,0),MATCH(data!BB$1,Haver_M!$B$1:$ZN$1,0))),INDEX(Haver_M!$B$1:$ZN$1000,MATCH(data!$A10,Haver_M!$B$1:$B$1000,0),MATCH(data!BB$1,Haver_M!$B$1:$ZN$1,0)),"")
A11: 36830 | B11: =IF(ISNUMBER(INDEX(Haver_Q!$B$1:$BD$1000,MATCH(data!$A11,Haver_Q!$B$1:$B$1000,0),MATCH(data!B$1,Haver_Q!$B$1:$BD$1,0))),100*INDEX(Haver_Q!$B$1:$BD$1000,MATCH(data!$A11,Haver_Q!$B$1:$B$1000,0),MATCH(data!B$1,Haver_Q!$B$1:$BD$1,0)),"na") -> na | C11: =IF(ISNUMBER(INDEX(Haver_Q!$B$1:$BD$1000,MATCH(data!$A11,Haver_Q!$B$1:$B$1000,0),MATCH(data!C$1,Haver_Q!$B$1:$BD$1,0))),100*INDEX(Haver_Q!$B$1:$BD$1000,MATCH(data!$A11,Haver_Q!$B$1:$B$1000,0),MATCH(data!C$1,Haver_Q!$B$1:$BD$1,0)),"na") -> na | D11: =IF(ISNUMBER(INDEX(Haver_Q!$B$1:$BD$1000,MATCH(data!$A11,Haver_Q!$B$1:$B$1000,0),MATCH(data!D$1,Haver_Q!$B$1:$BD$1,0))),100*INDEX(Haver_Q!$B$1:$BD$1000,MATCH(data!$A11,Haver_Q!$B$1:$B$1000,0),MATCH(data!D$1,Haver_Q!$B$1:$BD$1,0)),"na") -> na | E11: =IF(ISNUMBER(INDEX(Haver_Q!$B$1:$BD$1000,MATCH(data!$A11,Haver_Q!$B$1:$B$1000,0),MATCH(data!E$1,Haver_Q!$B$1:$BD$1,0))),100*INDEX(Haver_Q!$B$1:$BD$1000,MATCH(data!$A11,Haver_Q!$B$1:$B$1000,0),MATCH(data!E$1,Haver_Q!$B$1:$BD$1,0)),"na") -> na | F11: =IF(ISNUMBER(INDEX(Haver_Q!$B$1:$BD$1000,MATCH(data!$A11,Haver_Q!$B$1:$B$1000,0),MATCH(data!F$1,Haver_Q!$B$1:$BD$1,0))),100*INDEX(Haver_Q!$B$1:$BD$1000,MATCH(data!$A11,Haver_Q!$B$1:$B$1000,0),MATCH(data!F$1,Haver_Q!$B$1:$BD$1,0)),"na") -> na | G11: =IF(ISNUMBER(INDEX(Haver_Q!$B$1:$BD$1000,MATCH(data!$A11,Haver_Q!$B$1:$B$1000,0),MATCH(data!G$1,Haver_Q!$B$1:$BD$1,0))),100*INDEX(Haver_Q!$B$1:$BD$1000,MATCH(data!$A11,Haver_Q!$B$1:$B$1000,0),MATCH(data!G$1,Haver_Q!$B$1:$BD$1,0)),"na") -> na | H11: =IF(ISNUMBER(INDEX(Haver_Q!$B$1:$BD$1000,MATCH(data!$A11,Haver_Q!$B$1:$B$1000,0),MATCH(data!H$1,Haver_Q!$B$1:$BD$1,0))),100*INDEX(Haver_Q!$B$1:$BD$1000,MATCH(data!$A11,Haver_Q!$B$1:$B$1000,0),MATCH(data!H$1,Haver_Q!$B$1:$BD$1,0)),"na") -> na | I11: =IF(ISNUMBER(Bloomberg_m!C27),Bloomberg_m!C27,"na") -> 1734 | J11: =IF(ISNUMBER(Bloomberg_m!D27),Bloomberg_m!D27,"na") -> na | K11: =IF(ISNUMBER(Bloomberg_m!E27),Bloomberg_m!E27,"na") -> na | L11: =IF(ISNUMBER(Bloomberg_m!L27),Bloomberg_m!L27,"na") -> 33.05 | M11: =IF(ISNUMBER(INDEX(Haver_M!$B$1:$ZN$1000,MATCH(data!$A11,Haver_M!$B$1:$B$1000,0),MATCH(data!M$1,Haver_M!$B$1:$ZN$1,0))),INDEX(Haver_M!$B$1:$ZN$1000,MATCH(data!$A11,Haver_M!$B$1:$B$1000,0),MATCH(data!M$1,Haver_M!$B$1:$ZN$1,0)),"na") -> na | N11: =IF(ISNUMBER(INDEX(Haver_M!$B$1:$ZN$1000,MATCH(data!$A11,Haver_M!$B$1:$B$1000,0),MATCH(data!N$1,Haver_M!$B$1:$ZN$1,0))),INDEX(Haver_M!$B$1:$ZN$1000,MATCH(data!$A11,Haver_M!$B$1:$B$1000,0),MATCH(data!N$1,Haver_M!$B$1:$ZN$1,0)),"na") -> na | O11: =IF(ISNUMBER(INDEX(Haver_M!$B$1:$ZN$1000,MATCH(data!$A11,Haver_M!$B$1:$B$1000,0),MATCH(data!O$1,Haver_M!$B$1:$ZN$1,0))),INDEX(Haver_M!$B$1:$ZN$1000,MATCH(data!$A11,Haver_M!$B$1:$B$1000,0),MATCH(data!O$1,Haver_M!$B$1:$ZN$1,0)),"na") -> 119.1305 | P11: =IF(ISNUMBER(INDEX(Haver_M!$B$1:$ZN$1000,MATCH(data!$A11,Haver_M!$B$1:$B$1000,0),MATCH(data!P$1,Haver_M!$B$1:$ZN$1,0))),INDEX(Haver_M!$B$1:$ZN$1000,MATCH(data!$A11,Haver_M!$B$1:$B$1000,0),MATCH(data!P$1,Haver_M!$B$1:$ZN$1,0)),"na") -> 47.6152 | Q11: =IF(ISNUMBER(INDEX(Haver_M!$B$1:$ZN$1000,MATCH(data!$A11,Haver_M!$B$1:$B$1000,0),MATCH(data!Q$1,Haver_M!$B$1:$ZN$1,0))),INDEX(Haver_M!$B$1:$ZN$1000,MATCH(data!$A11,Haver_M!$B$1:$B$1000,0),MATCH(data!Q$1,Haver_M!$B$1:$ZN$1,0)),"na") -> 51.6425 | R11: =IF(ISNUMBER(INDEX(Haver_M!$B$1:$ZN$1000,MATCH(data!$A11,Haver_M!$B$1:$B$1000,0),MATCH(data!R$1,Haver_M!$B$1:$ZN$1,0))),INDEX(Haver_M!$B$1:$ZN$1000,MATCH(data!$A11,Haver_M!$B$1:$B$1000,0),MATCH(data!R$1,Haver_M!$B$1:$ZN$1,0)),"na") -> 90.6057 | S11: =IF(ISNUMBER(INDEX(Haver_M!$B$1:$ZN$1000,MATCH(data!$A11,Haver_M!$B$1:$B$1000,0),MATCH(data!S$1,Haver_M!$B$1:$ZN$1,0))),INDEX(Haver_M!$B$1:$ZN$1000,MATCH(data!$A11,Haver_M!$B$1:$B$1000,0),MATCH(data!S$1,Haver_M!$B$1:$ZN$1,0)),"na") -> 99.7742 | T11: =IF(ISNUMBER(INDEX(Haver_M!$B$1:$ZN$1000,MATCH(data!$A11,Haver_M!$B$1:$B$1000,0),MATCH(data!T$1,Haver_M!$B$1:$ZN$1,0))),INDEX(Haver_M!$B$1:$ZN$1000,MATCH(data!$A11,Haver_M!$B$1:$B$1000,0),MATCH(data!T$1,Haver_M!$B$1:$ZN$1,0)),"na") -> 56.1961 | ... BA11: =IF(ISNUMBER(INDEX(Haver_M!$B$1:$ZN$1000,MATCH(data!$A11,Haver_M!$B$1:$B$1000,0),MATCH(data!BA$1,Haver_M!$B$1:$ZN$1,0))),INDEX(Haver_M!$B$1:$ZN$1000,MATCH(data!$A11,Haver_M!$B$1:$B$1000,0),MATCH(data!BA$1,Haver_M!$B$1:$ZN$1,0)),"na") -> 103.55553 | BB11: =IF(ISNUMBER(INDEX(Haver_M!$B$1:$ZN$1000,MATCH(data!$A11,Haver_M!$B$1:$B$1000,0),MATCH(data!BB$1,Haver_M!$B$1:$ZN$1,0))),INDEX(Haver_M!$B$1:$ZN$1000,MATCH(data!$A11,Haver_M!$B$1:$B$1000,0),MATCH(data!BB$1,Haver_M!$B$1:$ZN$1,0)),"")
A12: 36860 | B12: =IF(ISNUMBER(INDEX(Haver_Q!$B$1:$BD$1000,MATCH(data!$A12,Haver_Q!$B$1:$B$1000,0),MATCH(data!B$1,Haver_Q!$B$1:$BD$1,0))),100*INDEX(Haver_Q!$B$1:$BD$1000,MATCH(data!$A12,Haver_Q!$B$1:$B$1000,0),MATCH(data!B$1,Haver_Q!$B$1:$BD$1,0)),"na") -> na | C12: =IF(ISNUMBER(INDEX(Haver_Q!$B$1:$BD$1000,MATCH(data!$A12,Haver_Q!$B$1:$B$1000,0),MATCH(data!C$1,Haver_Q!$B$1:$BD$1,0))),100*INDEX(Haver_Q!$B$1:$BD$1000,MATCH(data!$A12,Haver_Q!$B$1:$B$1000,0),MATCH(data!C$1,Haver_Q!$B$1:$BD$1,0)),"na") -> na | D12: =IF(ISNUMBER(INDEX(Haver_Q!$B$1:$BD$1000,MATCH(data!$A12,Haver_Q!$B$1:$B$1000,0),MATCH(data!D$1,Haver_Q!$B$1:$BD$1,0))),100*INDEX(Haver_Q!$B$1:$BD$1000,MATCH(data!$A12,Haver_Q!$B$1:$B$1000,0),MATCH(data!D$1,Haver_Q!$B$1:$BD$1,0)),"na") -> na | E12: =IF(ISNUMBER(INDEX(Haver_Q!$B$1:$BD$1000,MATCH(data!$A12,Haver_Q!$B$1:$B$1000,0),MATCH(data!E$1,Haver_Q!$B$1:$BD$1,0))),100*INDEX(Haver_Q!$B$1:$BD$1000,MATCH(data!$A12,Haver_Q!$B$1:$B$1000,0),MATCH(data!E$1,Haver_Q!$B$1:$BD$1,0)),"na") -> na | F12: =IF(ISNUMBER(INDEX(Haver_Q!$B$1:$BD$1000,MATCH(data!$A12,Haver_Q!$B$1:$B$1000,0),MATCH(data!F$1,Haver_Q!$B$1:$BD$1,0))),100*INDEX(Haver_Q!$B$1:$BD$1000,MATCH(data!$A12,Haver_Q!$B$1:$B$1000,0),MATCH(data!F$1,Haver_Q!$B$1:$BD$1,0)),"na") -> na | G12: =IF(ISNUMBER(INDEX(Haver_Q!$B$1:$BD$1000,MATCH(data!$A12,Haver_Q!$B$1:$B$1000,0),MATCH(data!G$1,Haver_Q!$B$1:$BD$1,0))),100*INDEX(Haver_Q!$B$1:$BD$1000,MATCH(data!$A12,Haver_Q!$B$1:$B$1000,0),MATCH(data!G$1,Haver_Q!$B$1:$BD$1,0)),"na") -> na | H12: =IF(ISNUMBER(INDEX(Haver_Q!$B$1:$BD$1000,MATCH(data!$A12,Haver_Q!$B$1:$B$1000,0),MATCH(data!H$1,Haver_Q!$B$1:$BD$1,0))),100*INDEX(Haver_Q!$B$1:$BD$1000,MATCH(data!$A12,Haver_Q!$B$1:$B$1000,0),MATCH(data!H$1,Haver_Q!$B$1:$BD$1,0)),"na") -> na | I12: =IF(ISNUMBER(Bloomberg_m!C28),Bloomberg_m!C28,"na") -> 1722 | J12: =IF(ISNUMBER(Bloomberg_m!D28),Bloomberg_m!D28,"na") -> na | K12: =IF(ISNUMBER(Bloomberg_m!E28),Bloomberg_m!E28,"na") -> na | L12: =IF(ISNUMBER(Bloomberg_m!L28),Bloomberg_m!L28,"na") -> 34.37 | M12: =IF(ISNUMBER(INDEX(Haver_M!$B$1:$ZN$1000,MATCH(data!$A12,Haver_M!$B$1:$B$1000,0),MATCH(data!M$1,Haver_M!$B$1:$ZN$1,0))),INDEX(Haver_M!$B$1:$ZN$1000,MATCH(data!$A12,Haver_M!$B$1:$B$1000,0),MATCH(data!M$1,Haver_M!$B$1:$ZN$1,0)),"na") -> na | N12: =IF(ISNUMBER(INDEX(Haver_M!$B$1:$ZN$1000,MATCH(data!$A12,Haver_M!$B$1:$B$1000,0),MATCH(data!N$1,Haver_M!$B$1:$ZN$1,0))),INDEX(Haver_M!$B$1:$ZN$1000,MATCH(data!$A12,Haver_M!$B$1:$B$1000,0),MATCH(data!N$1,Haver_M!$B$1:$ZN$1,0)),"na") -> na | O12: =IF(ISNUMBER(INDEX(Haver_M!$B$1:$ZN$1000,MATCH(data!$A12,Haver_M!$B$1:$B$1000,0),MATCH(data!O$1,Haver_M!$B$1:$ZN$1,0))),INDEX(Haver_M!$B$1:$ZN$1000,MATCH(data!$A12,Haver_M!$B$1:$B$1000,0),MATCH(data!O$1,Haver_M!$B$1:$ZN$1,0)),"na") -> 120.55956 | P12: =IF(ISNUMBER(INDEX(Haver_M!$B$1:$ZN$1000,MATCH(data!$A12,Haver_M!$B$1:$B$1000,0),MATCH(data!P$1,Haver_M!$B$1:$ZN$1,0))),INDEX(Haver_M!$B$1:$ZN$1000,MATCH(data!$A12,Haver_M!$B$1:$B$1000,0),MATCH(data!P$1,Haver_M!$B$1:$ZN$1,0)),"na") -> 47.8724 | Q12: =IF(ISNUMBER(INDEX(Haver_M!$B$1:$ZN$1000,MATCH(data!$A12,Haver_M!$B$1:$B$1000,0),MATCH(data!Q$1,Haver_M!$B$1:$ZN$1,0))),INDEX(Haver_M!$B$1:$ZN$1000,MATCH(data!$A12,Haver_M!$B$1:$B$1000,0),MATCH(data!Q$1,Haver_M!$B$1:$ZN$1,0)),"na") -> 52.0251 | R12: =IF(ISNUMBER(INDEX(Haver_M!$B$1:$ZN$1000,MATCH(data!$A12,Haver_M!$B$1:$B$1000,0),MATCH(data!R$1,Haver_M!$B$1:$ZN$1,0))),INDEX(Haver_M!$B$1:$ZN$1000,MATCH(data!$A12,Haver_M!$B$1:$B$1000,0),MATCH(data!R$1,Haver_M!$B$1:$ZN$1,0)),"na") -> 89.7542 | S12: =IF(ISNUMBER(INDEX(Haver_M!$B$1:$ZN$1000,MATCH(data!$A12,Haver_M!$B$1:$B$1000,0),MATCH(data!S$1,Haver_M!$B$1:$ZN$1,0))),INDEX(Haver_M!$B$1:$ZN$1000,MATCH(data!$A12,Haver_M!$B$1:$B$1000,0),MATCH(data!S$1,Haver_M!$B$1:$ZN$1,0)),"na") -> 102.3906 | T12: =IF(ISNUMBER(INDEX(Haver_M!$B$1:$ZN$1000,MATCH(data!$A12,Haver_M!$B$1:$B$1000,0),MATCH(data!T$1,Haver_M!$B$1:$ZN$1,0))),INDEX(Haver_M!$B$1:$ZN$1000,MATCH(data!$A12,Haver_M!$B$1:$B$1000,0),MATCH(data!T$1,Haver_M!$B$1:$ZN$1,0)),"na") -> 56.7744 | ... BA12: =IF(ISNUMBER(INDEX(Haver_M!$B$1:$ZN$1000,MATCH(data!$A12,Haver_M!$B$1:$B$1000,0),MATCH(data!BA$1,Haver_M!$B$1:$ZN$1,0))),INDEX(Haver_M!$B$1:$ZN$1000,MATCH(data!$A12,Haver_M!$B$1:$B$1000,0),MATCH(data!BA$1,Haver_M!$B$1:$ZN$1,0)),"na") -> 174.553 | BB12: =IF(ISNUMBER(INDEX(Haver_M!$B$1:$ZN$1000,MATCH(data!$A12,Haver_M!$B$1:$B$1000,0),MATCH(data!BB$1,Haver_M!$B$1:$ZN$1,0))),INDEX(Haver_M!$B$1:$ZN$1000,MATCH(data!$A12,Haver_M!$B$1:$B$1000,0),MATCH(data!BB$1,Haver_M!$B$1:$ZN$1,0)),"")
A13: 36891 | B13: =IF(ISNUMBER(INDEX(Haver_Q!$B$1:$BD$1000,MATCH(data!$A13,Haver_Q!$B$1:$B$1000,0),MATCH(data!B$1,Haver_Q!$B$1:$BD$1,0))),100*INDEX(Haver_Q!$B$1:$BD$1000,MATCH(data!$A13,Haver_Q!$B$1:$B$1000,0),MATCH(data!B$1,Haver_Q!$B$1:$BD$1,0)),"na") -> -2.6232726 | C13: =IF(ISNUMBER(INDEX(Haver_Q!$B$1:$BD$1000,MATCH(data!$A13,Haver_Q!$B$1:$B$1000,0),MATCH(data!C$1,Haver_Q!$B$1:$BD$1,0))),100*INDEX(Haver_Q!$B$1:$BD$1000,MATCH(data!$A13,Haver_Q!$B$1:$B$1000,0),MATCH(data!C$1,Haver_Q!$B$1:$BD$1,0)),"na") -> -2.427157 | D13: =IF(ISNUMBER(INDEX(Haver_Q!$B$1:$BD$1000,MATCH(data!$A13,Haver_Q!$B$1:$B$1000,0),MATCH(data!D$1,Haver_Q!$B$1:$BD$1,0))),100*INDEX(Haver_Q!$B$1:$BD$1000,MATCH(data!$A13,Haver_Q!$B$1:$B$1000,0),MATCH(data!D$1,Haver_Q!$B$1:$BD$1,0)),"na") -> 4.4443038 | E13: =IF(ISNUMBER(INDEX(Haver_Q!$B$1:$BD$1000,MATCH(data!$A13,Haver_Q!$B$1:$B$1000,0),MATCH(data!E$1,Haver_Q!$B$1:$BD$1,0))),100*INDEX(Haver_Q!$B$1:$BD$1000,MATCH(data!$A13,Haver_Q!$B$1:$B$1000,0),MATCH(data!E$1,Haver_Q!$B$1:$BD$1,0)),"na") -> -9.1565594 | F13: =IF(ISNUMBER(INDEX(Haver_Q!$B$1:$BD$1000,MATCH(data!$A13,Haver_Q!$B$1:$B$1000,0),MATCH(data!F$1,Haver_Q!$B$1:$BD$1,0))),100*INDEX(Haver_Q!$B$1:$BD$1000,MATCH(data!$A13,Haver_Q!$B$1:$B$1000,0),MATCH(data!F$1,Haver_Q!$B$1:$BD$1,0)),"na") -> 5.4053264 | G13: =IF(ISNUMBER(INDEX(Haver_Q!$B$1:$BD$1000,MATCH(data!$A13,Haver_Q!$B$1:$B$1000,0),MATCH(data!G$1,Haver_Q!$B$1:$BD$1,0))),100*INDEX(Haver_Q!$B$1:$BD$1000,MATCH(data!$A13,Haver_Q!$B$1:$B$1000,0),MATCH(data!G$1,Haver_Q!$B$1:$BD$1,0)),"na") -> 3.7157616 | H13: =IF(ISNUMBER(INDEX(Haver_Q!$B$1:$BD$1000,MATCH(data!$A13,Haver_Q!$B$1:$B$1000,0),MATCH(data!H$1,Haver_Q!$B$1:$BD$1,0))),100*INDEX(Haver_Q!$B$1:$BD$1000,MATCH(data!$A13,Haver_Q!$B$1:$B$1000,0),MATCH(data!H$1,Haver_Q!$B$1:$BD$1,0)),"na") -> 283.1619 | I13: =IF(ISNUMBER(Bloomberg_m!C29),Bloomberg_m!C29,"na") -> 1609 | J13: =IF(ISNUMBER(Bloomberg_m!D29),Bloomberg_m!D29,"na") -> na | K13: =IF(ISNUMBER(Bloomberg_m!E29),Bloomberg_m!E29,"na") -> na | L13: =IF(ISNUMBER(Bloomberg_m!L29),Bloomberg_m!L29,"na") -> 28.4 | M13: =IF(ISNUMBER(INDEX(Haver_M!$B$1:$ZN$1000,MATCH(data!$A13,Haver_M!$B$1:$B$1000,0),MATCH(data!M$1,Haver_M!$B$1:$ZN$1,0))),INDEX(Haver_M!$B$1:$ZN$1000,MATCH(data!$A13,Haver_M!$B$1:$B$1000,0),MATCH(data!M$1,Haver_M!$B$1:$ZN$1,0)),"na") -> na | N13: =IF(ISNUMBER(INDEX(Haver_M!$B$1:$ZN$1000,MATCH(data!$A13,Haver_M!$B$1:$B$1000,0),MATCH(data!N$1,Haver_M!$B$1:$ZN$1,0))),INDEX(Haver_M!$B$1:$ZN$1000,MATCH(data!$A13,Haver_M!$B$1:$B$1000,0),MATCH(data!N$1,Haver_M!$B$1:$ZN$1,0)),"na") -> na | O13: =IF(ISNUMBER(INDEX(Haver_M!$B$1:$ZN$1000,MATCH(data!$A13,Haver_M!$B$1:$B$1000,0),MATCH(data!O$1,Haver_M!$B$1:$ZN$1,0))),INDEX(Haver_M!$B$1:$ZN$1000,MATCH(data!$A13,Haver_M!$B$1:$B$1000,0),MATCH(data!O$1,Haver_M!$B$1:$ZN$1,0)),"na") -> 121.8344 | P13: =IF(ISNUMBER(INDEX(Haver_M!$B$1:$ZN$1000,MATCH(data!$A13,Haver_M!$B$1:$B$1000,0),MATCH(data!P$1,Haver_M!$B$1:$ZN$1,0))),INDEX(Haver_M!$B$1:$ZN$1000,MATCH(data!$A13,Haver_M!$B$1:$B$1000,0),MATCH(data!P$1,Haver_M!$B$1:$ZN$1,0)),"na") -> 48.2735 | Q13: =IF(ISNUMBER(INDEX(Haver_M!$B$1:$ZN$1000,MATCH(data!$A13,Haver_M!$B$1:$B$1000,0),MATCH(data!Q$1,Haver_M!$B$1:$ZN$1,0))),INDEX(Haver_M!$B$1:$ZN$1000,MATCH(data!$A13,Haver_M!$B$1:$B$1000,0),MATCH(data!Q$1,Haver_M!$B$1:$ZN$1,0)),"na") -> 52.3128 | R13: =IF(ISNUMBER(INDEX(Haver_M!$B$1:$ZN$1000,MATCH(data!$A13,Haver_M!$B$1:$B$1000,0),MATCH(data!R$1,Haver_M!$B$1:$ZN$1,0))),INDEX(Haver_M!$B$1:$ZN$1000,MATCH(data!$A13,Haver_M!$B$1:$B$1000,0),MATCH(data!R$1,Haver_M!$B$1:$ZN$1,0)),"na") -> 88.622 | S13: =IF(ISNUMBER(INDEX(Haver_M!$B$1:$ZN$1000,MATCH(data!$A13,Haver_M!$B$1:$B$1000,0),MATCH(data!S$1,Haver_M!$B$1:$ZN$1,0))),INDEX(Haver_M!$B$1:$ZN$1000,MATCH(data!$A13,Haver_M!$B$1:$B$1000,0),MATCH(data!S$1,Haver_M!$B$1:$ZN$1,0)),"na") -> 102.9357 | T13: =IF(ISNUMBER(INDEX(Haver_M!$B$1:$ZN$1000,MATCH(data!$A13,Haver_M!$B$1:$B$1000,0),MATCH(data!T$1,Haver_M!$B$1:$ZN$1,0))),INDEX(Haver_M!$B$1:$ZN$1000,MATCH(data!$A13,Haver_M!$B$1:$B$1000,0),MATCH(data!T$1,Haver_M!$B$1:$ZN$1,0)),"na") -> 56.5097 | ... BA13: =IF(ISNUMBER(INDEX(Haver_M!$B$1:$ZN$1000,MATCH(data!$A13,Haver_M!$B$1:$B$1000,0),MATCH(data!BA$1,Haver_M!$B$1:$ZN$1,0))),INDEX(Haver_M!$B$1:$ZN$1000,MATCH(data!$A13,Haver_M!$B$1:$B$1000,0),MATCH(data!BA$1,Haver_M!$B$1:$ZN$1,0)),"na") -> 88.497361 | BB13: =IF(ISNUMBER(INDEX(Haver_M!$B$1:$ZN$1000,MATCH(data!$A13,Haver_M!$B$1:$B$1000,0),MATCH(data!BB$1,Haver_M!$B$1:$ZN$1,0))),INDEX(Haver_M!$B$1:$ZN$1000,MATCH(data!$A13,Haver_M!$B$1:$B$1000,0),MATCH(data!BB$1,Haver_M!$B$1:$ZN$1,0)),"")
... A250: 44104 | B250: =IF(ISNUMBER(INDEX(Haver_Q!$B$1:$BD$1000,MATCH(data!$A250,Haver_Q!$B$1:$B$1000,0),MATCH(data!B$1,Haver_Q!$B$1:$BD$1,0))),100*INDEX(Haver_Q!$B$1:$BD$1000,MATCH(data!$A250,Haver_Q!$B$1:$B$1000,0),MATCH(data!B$1,Haver_Q!$B$1:$BD$1,0)),"na") -> na | C250: =IF(ISNUMBER(INDEX(Haver_Q!$B$1:$BD$1000,MATCH(data!$A250,Haver_Q!$B$1:$B$1000,0),MATCH(data!C$1,Haver_Q!$B$1:$BD$1,0))),100*INDEX(Haver_Q!$B$1:$BD$1000,MATCH(data!$A250,Haver_Q!$B$1:$B$1000,0),MATCH(data!C$1,Haver_Q!$B$1:$BD$1,0)),"na") -> na | D250: =IF(ISNUMBER(INDEX(Haver_Q!$B$1:$BD$1000,MATCH(data!$A250,Haver_Q!$B$1:$B$1000,0),MATCH(data!D$1,Haver_Q!$B$1:$BD$1,0))),100*INDEX(Haver_Q!$B$1:$BD$1000,MATCH(data!$A250,Haver_Q!$B$1:$B$1000,0),MATCH(data!D$1,Haver_Q!$B$1:$BD$1,0)),"na") -> na | E250: =IF(ISNUMBER(INDEX(Haver_Q!$B$1:$BD$1000,MATCH(data!$A250,Haver_Q!$B$1:$B$1000,0),MATCH(data!E$1,Haver_Q!$B$1:$BD$1,0))),100*INDEX(Haver_Q!$B$1:$BD$1000,MATCH(data!$A250,Haver_Q!$B$1:$B$1000,0),MATCH(data!E$1,Haver_Q!$B$1:$BD$1,0)),"na") -> na | F250: =IF(ISNUMBER(INDEX(Haver_Q!$B$1:$BD$1000,MATCH(data!$A250,Haver_Q!$B$1:$B$1000,0),MATCH(data!F$1,Haver_Q!$B$1:$BD$1,0))),100*INDEX(Haver_Q!$B$1:$BD$1000,MATCH(data!$A250,Haver_Q!$B$1:$B$1000,0),MATCH(data!F$1,Haver_Q!$B$1:$BD$1,0)),"na") -> na | G250: =IF(ISNUMBER(INDEX(Haver_Q!$B$1:$BD$1000,MATCH(data!$A250,Haver_Q!$B$1:$B$1000,0),MATCH(data!G$1,Haver_Q!$B$1:$BD$1,0))),100*INDEX(Haver_Q!$B$1:$BD$1000,MATCH(data!$A250,Haver_Q!$B$1:$B$1000,0),MATCH(data!G$1,Haver_Q!$B$1:$BD$1,0)),"na") -> na | H250: =IF(ISNUMBER(INDEX(Haver_Q!$B$1:$BD$1000,MATCH(data!$A250,Haver_Q!$B$1:$B$1000,0),MATCH(data!H$1,Haver_Q!$B$1:$BD$1,0))),100*INDEX(Haver_Q!$B$1:$BD$1000,MATCH(data!$A250,Haver_Q!$B$1:$B$1000,0),MATCH(data!H$1,Haver_Q!$B$1:$BD$1,0)),"na") -> na | I250: =IF(ISNUMBER(Bloomberg_m!C266),Bloomberg_m!C266,"na") -> na | J250: =IF(ISNUMBER(Bloomberg_m!D266),Bloomberg_m!D266,"na") -> na | K250: =IF(ISNUMBER(Bloomberg_m!E266),Bloomberg_m!E266,"na") -> na | L250: =IF(ISNUMBER(Bloomberg_m!L266),Bloomberg_m!L266,"na") -> na | M250: =IF(ISNUMBER(INDEX(Haver_M!$B$1:$ZN$1000,MATCH(data!$A250,Haver_M!$B$1:$B$1000,0),MATCH(data!M$1,Haver_M!$B$1:$ZN$1,0))),INDEX(Haver_M!$B$1:$ZN$1000,MATCH(data!$A250,Haver_M!$B$1:$B$1000,0),MATCH(data!M$1,Haver_M!$B$1:$ZN$1,0)),"na") -> na | N250: =IF(ISNUMBER(INDEX(Haver_M!$B$1:$ZN$1000,MATCH(data!$A250,Haver_M!$B$1:$B$1000,0),MATCH(data!N$1,Haver_M!$B$1:$ZN$1,0))),INDEX(Haver_M!$B$1:$ZN$1000,MATCH(data!$A250,Haver_M!$B$1:$B$1000,0),MATCH(data!N$1,Haver_M!$B$1:$ZN$1,0)),"na") -> na | O250: =IF(ISNUMBER(INDEX(Haver_M!$B$1:$ZN$1000,MATCH(data!$A250,Haver_M!$B$1:$B$1000,0),MATCH(data!O$1,Haver_M!$B$1:$ZN$1,0))),INDEX(Haver_M!$B$1:$ZN$1000,MATCH(data!$A250,Haver_M!$B$1:$B$1000,0),MATCH(data!O$1,Haver_M!$B$1:$ZN$1,0)),"na") -> na | P250: =IF(ISNUMBER(INDEX(Haver_M!$B$1:$ZN$1000,MATCH(data!$A250,Haver_M!$B$1:$B$1000,0),MATCH(data!P$1,Haver_M!$B$1:$ZN$1,0))),INDEX(Haver_M!$B$1:$ZN$1000,MATCH(data!$A250,Haver_M!$B$1:$B$1000,0),MATCH(data!P$1,Haver_M!$B$1:$ZN$1,0)),"na") -> na | Q250: =IF(ISNUMBER(INDEX(Haver_M!$B$1:$ZN$1000,MATCH(data!$A250,Haver_M!$B$1:$B$1000,0),MATCH(data!Q$1,Haver_M!$B$1:$ZN$1,0))),INDEX(Haver_M!$B$1:$ZN$1000,MATCH(data!$A250,Haver_M!$B$1:$B$1000,0),MATCH(data!Q$1,Haver_M!$B$1:$ZN$1,0)),"na") -> na | R250: =IF(ISNUMBER(INDEX(Haver_M!$B$1:$ZN$1000,MATCH(data!$A250,Haver_M!$B$1:$B$1000,0),MATCH(data!R$1,Haver_M!$B$1:$ZN$1,0))),INDEX(Haver_M!$B$1:$ZN$1000,MATCH(data!$A250,Haver_M!$B$1:$B$1000,0),MATCH(data!R$1,Haver_M!$B$1:$ZN$1,0)),"na") -> na | S250: =IF(ISNUMBER(INDEX(Haver_M!$B$1:$ZN$1000,MATCH(data!$A250,Haver_M!$B$1:$B$1000,0),MATCH(data!S$1,Haver_M!$B$1:$ZN$1,0))),INDEX(Haver_M!$B$1:$ZN$1000,MATCH(data!$A250,Haver_M!$B$1:$B$1000,0),MATCH(data!S$1,Haver_M!$B$1:$ZN$1,0)),"na") -> na | T250: =IF(ISNUMBER(INDEX(Haver_M!$B$1:$ZN$1000,MATCH(data!$A250,Haver_M!$B$1:$B$1000,0),MATCH(data!T$1,Haver_M!$B$1:$ZN$1,0))),INDEX(Haver_M!$B$1:$ZN$1000,MATCH(data!$A250,Haver_M!$B$1:$B$1000,0),MATCH(data!T$1,Haver_M!$B$1:$ZN$1,0)),"na") -> na | ... BA250: =IF(ISNUMBER(INDEX(Haver_M!$B$1:$ZN$1000,MATCH(data!$A250,Haver_M!$B$1:$B$1000,0),MATCH(data!BA$1,Haver_M!$B$1:$ZN$1,0))),INDEX(Haver_M!$B$1:$ZN$1000,MATCH(data!$A250,Haver_M!$B$1:$B$1000,0),MATCH(data!BA$1,Haver_M!$B$1:$ZN$1,0)),"na") -> na | BB250: =IF(ISNUMBER(INDEX(Haver_M!$B$1:$ZN$1000,MATCH(data!$A250,Haver_M!$B$1:$B$1000,0),MATCH(data!BB$1,Haver_M!$B$1:$ZN$1,0))),INDEX(Haver_M!$B$1:$ZN$1000,MATCH(data!$A250,Haver_M!$B$1:$B$1000,0),MATCH(data!BB$1,Haver_M!$B$1:$ZN$1,0)),"")
